Workbook

Sheet Dashboard
A1: Sales tracking
A2: Key Metrics | B2: YTD | C2: January | D2: February | E2: March | F2: April | G2: May | H2: June | I2: July | J2: August | K2: September | L2: October | M2: November | N2: December | O2: SPARKLINES
A3: Conversion Rate: | B3: =iferror(B12/B10,"") | C3: =Jan!I2 -> #REF! | D3: =IFERROR(Feb!I2,"") | E3: =Mar!I2 -> #REF! | F3: =IFERROR(Apr!I2,"") -> 0.13333333 | G3: =IFERROR(May!I2,"") -> 0.57142857 | H3: =IFERROR(Jun!I2,"") -> 0.64285714 | I3: =IFERROR(Jul!I2,"") -> 0.61111111 | J3: =IFERROR(Aug!I2,"") -> 0.54545455 | K3: =IFERROR(Sep!L2,"") -> 0.36170213 | L3: =IFERROR(Oct!L2,"") -> 0.65957447 | M3: =IFERROR(Nov!I2,"") | N3: =IFERROR(Dec!I2,"") | O3: =IFERROR(__xludf.DUMMYFUNCTION("IFERROR(SPARKLINE(C3:N3, {""chartype"", ""line""; ""color"", ""blue""})) "),"")
A4: Offer To Close Rate: | B4: =iferror(B12/B11,"") | C4: =Jan!I3 -> #REF! | D4: =IFERROR(Feb!I3,"") | E4: =IFERROR(Mar!I3,"") | F4: =IFERROR(Apr!I3,"") -> 0.13333333 | G4: =IFERROR(May!I3,"") -> 0.57142857 | H4: =IFERROR(Jun!I3,"") -> 0.64285714 | I4: =IFERROR(Jul!I3,"") -> 0.61111111 | J4: =IFERROR(Aug!I3,"") -> 0.54545455 | K4: =IFERROR(Sep!L3,"") -> 0.36170213 | L4: =IFERROR(Oct!L3,"") -> 0.65957447 | M4: =IFERROR(Nov!I3,"") | N4: =IFERROR(Dec!I3,"") | O4: =IFERROR(__xludf.DUMMYFUNCTION("IFERROR(SPARKLINE(C4:N4, {""chartype"", ""line""; ""color"", ""blue""})) "),"")
A5: Call To Offer Rate: | B5: =IFERROR(B11/B10,"") | C5: =Jan!I4 -> #REF! | D5: =IFERROR(Feb!I4,"") | E5: =IFERROR(Mar!I4,"") | F5: =IFERROR(Apr!I4,"") -> 1 | G5: =IFERROR(May!I4,"") -> 1 | H5: =IFERROR(Jun!I4,"") -> 1 | I5: =IFERROR(Jul!I4,"") -> 1 | J5: =IFERROR(Aug!I4,"") -> 1 | K5: =IFERROR(Sep!L4,"") -> 1 | L5: =IFERROR(Oct!L4,"") -> 1 | M5: =IFERROR(Nov!I4,"") | N5: =IFERROR(Dec!I4,"") | O5: =IFERROR(__xludf.DUMMYFUNCTION("IFERROR(SPARKLINE(C5:N5, {""chartype"", ""line""; ""color"", ""blue""})) "),"")
A6: Revenue: | B6: =IFERROR(SUM(C6:N6),"") | C6: =Jan!C3 -> #REF! | D6: =IFERROR(Feb!C3,"") | E6: =IFERROR(Mar!$C3,"") | F6: =IFERROR(Apr!$C3,"") -> 9000 | G6: =IFERROR(May!$C3,"") -> 38994 | H6: =IFERROR(Jun!$C3,"") -> 60000 | I6: =IFERROR(Jul!$C3,"") -> 79500 | J6: =IFERROR(Aug!$C3,"") -> 103500 | K6: =IFERROR(Sep!$C3,"") -> 151500 | L6: =IFERROR(Oct!$C3,"") -> 276000 | M6: =IFERROR(Nov!$C3,"") -> 160500 | N6: =IFERROR(Dec!$C3,"") -> 60000 | O6: =IFERROR(__xludf.DUMMYFUNCTION("IFERROR(SPARKLINE(C6:N6, {""chartype"", ""line""; ""color"", ""blue""})) "),"")
A7: Cash: | B7: =IFERROR(SUM(C7:N7),"") | C7: =Jan!C4 -> #REF! | D7: =IFERROR(Feb!C4,"") | E7: =IFERROR(Mar!$C4,"") | F7: =IFERROR(Apr!$C4,"") -> 3000 | G7: =IFERROR(May!$C4,"") -> 31498 | H7: =IFERROR(Jun!$C4,"") -> 34500 | I7: =IFERROR(Jul!$C4,"") -> 47000 | J7: =IFERROR(Aug!$C4,"") -> 49500 | K7: =IFERROR(Sep!$C4,"") -> 52500 | L7: =IFERROR(Oct!$C4,"") -> 88500 | M7: =IFERROR(Nov!$C4,"") -> 67500 | N7: =IFERROR(Dec!$C4,"") -> 25500 | O7: =IFERROR(__xludf.DUMMYFUNCTION("IFERROR(SPARKLINE(C7:N7, {""chartype"", ""line""; ""color"", ""blue""})) "),"")
A8: Bookings: | B8: =IFERROR(SUM(C8:N8),"") | C8: =Jan!I6 -> #REF! | D8: =IFERROR(Feb!I6,"") | E8: =IFERROR(Mar!$I6,"") | F8: =IFERROR(Apr!$I6,"") -> 15 | G8: =IFERROR(May!$I6,"") -> 14 | H8: =IFERROR(Jun!$I6,"") -> 14 | I8: =IFERROR(Jul!$I6,"") -> 18 | J8: =IFERROR(Aug!$I6,"") -> 23 | K8: =IFERROR(Sep!$L6,"") -> 80 | L8: =IFERROR(Oct!$L6,"") -> 71 | M8: =IFERROR(Nov!$I6,"") -> 41 | N8: =IFERROR(Dec!$I6,"") -> 17 | O8: =IFERROR(__xludf.DUMMYFUNCTION("IFERROR(SPARKLINE(C8:N8, {""chartype"", ""line""; ""color"", ""blue""})) "),"")
A9: Shows: | B9: =sum(C9:N9) -> #REF! | C9: =Jan!I7 -> #REF! | D9: =IFERROR(Feb!$I$7,"") | E9: =IFERROR(Mar!$I$7,"") | F9: =IFERROR(Apr!$I$7,"") -> 15 | G9: =IFERROR(May!$I$7,"") -> 14 | H9: =IFERROR(Jun!$I$7,"") -> 14 | I9: =IFERROR(Jul!$I$7,"") -> 18 | J9: =IFERROR(Aug!$I$7,"") -> 22 | K9: =IFERROR(Sep!$L$7,"") -> 47 | L9: =IFERROR(Oct!$L$7,"") -> 47 | M9: =IFERROR(Nov!$I$7,"") -> 33 | N9: =IFERROR(Dec!$I$7,"") -> 11 | O9: =IFERROR(__xludf.DUMMYFUNCTION("IFERROR(SPARKLINE(C9:N9, {""chartype"", ""line""; ""color"", ""blue""})) "),"")
A10: Calls: | B10: =IFERROR(SUM(C10:N10),"") | C10: =Jan!I7 -> #REF! | D10: =IFERROR(Feb!I8,"") | E10: =IFERROR(Mar!$I8,"") | F10: =IFERROR(Apr!$I8,"") -> 15 | G10: =IFERROR(May!$I8,"") -> 14 | H10: =IFERROR(Jun!$I8,"") -> 14 | I10: =IFERROR(Jul!$I8,"") -> 18 | J10: =IFERROR(Aug!$I8,"") -> 22 | K10: =IFERROR(Sep!$L8,"") -> 47 | L10: =IFERROR(Oct!$L8,"") -> 47 | M10: =IFERROR(Nov!$I8,"") -> 33 | N10: =IFERROR(Dec!$I8,"") -> 11 | O10: =IFERROR(__xludf.DUMMYFUNCTION("IFERROR(SPARKLINE(C10:N10, {""chartype"", ""line""; ""color"", ""blue""})) "),"")
A11: Offers: | B11: =IFERROR(SUM(C11:N11),"") | C11: =Jan!I9 -> #REF! | D11: =IFERROR(Feb!I9,"") | E11: =IFERROR(Mar!$I9,"") | F11: =IFERROR(Apr!$I9,"") -> 15 | G11: =IFERROR(May!$I9,"") -> 14 | H11: =IFERROR(Jun!$I9,"") -> 14 | I11: =IFERROR(Jul!$I9,"") -> 18 | J11: =IFERROR(Aug!$I9,"") -> 22 | K11: =IFERROR(Sep!$L9,"") -> 47 | L11: =IFERROR(Oct!$L9,"") -> 47 | M11: =IFERROR(Nov!$I9,"") -> 33 | N11: =IFERROR(Dec!$I9,"") -> 11 | O11: =IFERROR(__xludf.DUMMYFUNCTION("IFERROR(SPARKLINE(C11:N11, {""chartype"", ""line""; ""color"", ""blue""})) "),"")
A12: Deals: | B12: =IFERROR(SUM(C12:N12),"") | C12: =Jan!I10 -> #REF! | D12: =IFERROR(Feb!I10,"") | E12: =IFERROR(Mar!$I10,"") | F12: =IFERROR(Apr!$I10,"") -> 2 | G12: =IFERROR(May!$I10,"") -> 8 | H12: =IFERROR(Jun!$I10,"") -> 9 | I12: =IFERROR(Jul!$I10,"") -> 11 | J12: =IFERROR(Aug!$I10,"") -> 12 | K12: =IFERROR(Sep!$L10,"") -> 17 | L12: =IFERROR(Oct!$L10,"") -> 31 | M12: =IFERROR(Nov!$I10,"") -> 17 | N12: =IFERROR(Dec!$I10,"") -> 6 | O12: =IFERROR(__xludf.DUMMYFUNCTION("IFERROR(SPARKLINE(C12:N12, {""chartype"", ""line""; ""color"", ""blue""})) "),"")
A13: Full-Pay: | B13: =IFERROR(SUM(C13:N13),"") | C13: =Jan!F2 -> #REF! | D13: =IFERROR(Feb!F2,"") | E13: =IFERROR(Mar!$F2,"") | F13: =IFERROR(Apr!$F2,"") -> 2 | G13: =IFERROR(May!$F2,"") -> 7 | H13: =IFERROR(Jun!$F2,"") -> 3 | I13: =IFERROR(Jul!$F2,"") -> 4 | J13: =IFERROR(Aug!$F2,"") -> 3 | K13: =IFERROR(Sep!$I2,"") -> 2 | L13: =IFERROR(Oct!$I2,"") -> 1 | M13: =IFERROR(Nov!$F2,"") -> 4 | N13: =IFERROR(Dec!$F2,"") -> 2 | O13: =IFERROR(__xludf.DUMMYFUNCTION("IFERROR(SPARKLINE(C13:N13, {""chartype"", ""line""; ""color"", ""blue""})) "),"")
A14: Split-Pay: | B14: =IFERROR(SUM(C14:N14),"") | C14: =Jan!F3 -> #REF! | D14: =IFERROR(Feb!F3,"") | E14: =IFERROR(Mar!$F3,"") | F14: =IFERROR(Apr!$F3,"") -> 0 | G14: =IFERROR(May!$F3,"") -> 1 | H14: =IFERROR(Jun!$F3,"") -> 6 | I14: =IFERROR(Jul!$F3,"") -> 7 | J14: =IFERROR(Aug!$F3,"") -> 9 | K14: =IFERROR(Sep!$I3,"") -> 15 | L14: =IFERROR(Oct!$I3,"") -> 30 | M14: =IFERROR(Nov!$F3,"") -> 13 | N14: =IFERROR(Dec!$F3,"") -> 4 | O14: =IFERROR(__xludf.DUMMYFUNCTION("IFERROR(SPARKLINE(C14:N14, {""chartype"", ""line""; ""color"", ""blue""})) "),"")
A15: Deposits: | B15: =IFERROR(SUM(C15:N15),"") | C15: =Jan!F4 -> #REF! | D15: =IFERROR(Feb!F4,"") | E15: =IFERROR(Mar!$F4,"") | F15: =IFERROR(Apr!$F4,"") -> 0 | G15: =IFERROR(May!$F4,"") -> 0 | H15: =IFERROR(Jun!$F4,"") -> 0 | I15: =IFERROR(Jul!$F4,"") -> 0 | J15: =IFERROR(Aug!$F4,"") -> 0 | K15: =IFERROR(Sep!$I4,"") -> 4 | L15: =IFERROR(Oct!$I4,"") -> 0 | M15: =IFERROR(Nov!$F4,"") -> 3 | N15: =IFERROR(Dec!$F4,"") -> 0 | O15: =IFERROR(__xludf.DUMMYFUNCTION("IFERROR(SPARKLINE(C15:N15, {""chartype"", ""line""; ""color"", ""blue""})) "),"")
A16: Show-Up Rate: | B16: =B9/B8 -> #REF! | C16: =C9/C8 -> #REF! | D16: =D9/D8 -> #DIV/0! | E16: =E9/E8 -> #DIV/0! | F16: =F9/F8 -> 1 | G16: =G9/G8 -> 1 | H16: =H9/H8 -> 1 | I16: =I9/I8 -> 1 | ... N16: =N9/N8 -> 0.64705882 | O16: =IFERROR(__xludf.DUMMYFUNCTION("IFERROR(SPARKLINE(C16:N16, {""chartype"", ""line""; ""color"", ""blue""})) "),"")
A17: Conducted Rate: | B17: =B10/B8 -> #DIV/0! | C17: =C10/C8 -> #REF! | D17: =D10/D8 -> #DIV/0! | E17: =E10/E8 -> #DIV/0! | F17: =F10/F8 -> 1 | G17: =G10/G8 -> 1 | H17: =H10/H8 -> 1 | I17: =I10/I8 -> 1 | ... N17: =N10/N8 -> 0.64705882 | O17: =IFERROR(__xludf.DUMMYFUNCTION("IFERROR(SPARKLINE(C17:N17, {""chartype"", ""line""; ""color"", ""blue""})) "),"")

Sheet Apr
B1: Rep: | C1: Anna | E1: Outcome | H1: KPIs% | K1: Show Rate | N1: Objections | Q1: Source | U1: Tracking
E2: Full-Pay: | F2: =IFERROR(COUNTIFS(I13:I287, "Full-Pay"),"") -> 2 | H2: Conversion Rate: | I2: =iferror(I10/I8,"") -> 0.13333333 | K2: Rescheduling Rate: | L2: =iferror(F8/I6,"") -> 0 | N2: Think About It | O2: =IFERROR(COUNTIFS(N13:N286, "think about it"),"") -> 7 | Q2: Reschedule | R2: =IFERROR(COUNTIF(H13:H286,Q2),"") -> 0 | S2: Cold Call | T2: =IFERROR(COUNTIF(H13:H286,S2),"") -> 0
B3: Revenue | C3: =IFERROR(SUM(K13:K284),"") -> 9000 | E3: Split-Pay: | F3: =IFERROR(COUNTIFS(I13:I287, "Split-Pay"),"") -> 0 | H3: Offer To Close Rate: | I3: =IFERROR(I10/I9,"") -> 0.13333333 | K3: Cancellation Rate: | L3: =iferror(F9/I6,"") -> 0 | N3: Money | O3: =IFERROR(COUNTIFS(N13:N286, "money"),"") -> 4 | Q3: YouTube | R3: =IFERROR(COUNTIF(H13:H286,Q3),"") -> 0 | S3: Twitter | T3: =IFERROR(COUNTIF(H13:H286,S3),"") -> 0
B4: Cash | C4: =IFERROR(SUM(L13:L284),"") -> 3000 | E4: Deposits: | F4: =IFERROR(COUNTIFS(I13:I287, "Deposit"),"") -> 0 | H4: Call To Offer Rate: | I4: =IFERROR(I9/I8,"") -> 1 | K4: No-Shows Rate: | L4: =iferror(F10/I6,"") -> 0 | N4: Time | O4: =IFERROR(COUNTIFS(N13:N286, "time"),"") -> 2 | Q4: YouTube Ads | R4: =IFERROR(COUNTIF(H13:H286,Q4),"") -> 0 | S4: Skool | T4: =IFERROR(COUNTIF(H13:H286,S4),"") -> 0
E5: Offer & Didn't Buy: | F5: =IFERROR(COUNTIFS(I13:I287, "Offer & Didn't Buy"),"") -> 13 | H5: Drag Over Rate: | I5: =IFERROR(F7/(C6+F7+F8),"") -> 0 | K5: Drag Over Rate: | L5: =iferror(F7/I6,"") -> 0 | N5: Partner | O5: =IFERROR(COUNTIFS(N13:N286, "partner"),"") -> 1 | Q5: Email | R5: =IFERROR(COUNTIF(H13:H286,Q5),"") -> 0 | S5: Instagram | T5: =IFERROR(COUNTIF(H13:H286,S5),"") -> 0
B6: Total Calls : | C6: =IFERROR(SUM(F2:F6),"") -> 15 | E6: Bad Fit & No Offer: | F6: =IFERROR(COUNTIFS(I13:I287, "Bad Fit & No Offer"),"") -> 0 | H6: Bookings: | I6: =IFERROR(SUM(F2:F10),"") -> 15 | K6: Show-Up Rate: | L6: =iferror(I7/I6,"") -> 1 | N6: Fear | O6: =IFERROR(COUNTIFS(N13:N286, "fear"),"") -> 0 | Q6: Facebook | R6: =IFERROR(COUNTIF(H13:H286,Q6),"") -> 0 | S6: TikTok | T6: =IFERROR(COUNTIF(H13:H286,S6),"") -> 0
B7: Total Won : | C7: =IFERROR(F2+F3,"") -> 2 | E7: Drag Over & Show: | F7: =IFERROR(COUNTIFS(I13:I287, "Drag Over & Show"),"") -> 0 | H7: Shows: | I7: =IFERROR(SUM(F2:F7),"") -> 15 | K7: Conducted Rate: | L7: =IFERROR(I8/I6,"") -> 1 | N7: Value | O7: =IFERROR(COUNTIFS(N14:N287, "value"),"") -> 0 | Q7: Facebook Ads | R7: =IFERROR(COUNTIF(H13:H286,Q7),"") -> 0 | S7: Google | T7: =IFERROR(COUNTIF(H13:H286,S7),"") -> 0
B8: Total Lost : | C8: =COUNTIF(I13:I286,"offer & didn't buy")+countif(I13:I286,"deposit")+countif(I13:I286,"bad fit & no offer") -> 13 | E8: Rescheduled: | F8: =IFERROR(COUNTIFS(I13:I287, "Rescheduled"),"") -> 0 | H8: Calls: | I8: =IFERROR(SUM(F2:F6),"") -> 15 | Q8: LinkedIn | R8: =IFERROR(COUNTIF(H13:H286,Q8),"") -> 0 | S8: Referral | T8: =IFERROR(COUNTIF(H13:H286,S8),"") -> 0
B9: Closing % : | C9: =iferror(SUM(C7/C6),"") -> 0.13333333 | E9: Cancelled: | F9: =IFERROR(COUNTIFS(I13:I287, "Cancelled"),"") -> 0 | H9: Offers: | I9: =IFERROR(sum(F2:F5),"") -> 15
E10: No-Show: | F10: =IFERROR(COUNTIFS(I13:I287, "No-Show"),"") -> 0 | H10: Deals | I10: =F2+F3 -> 2
B12: Date | C12: Name | E12: Phone No. | F12: Email | H12: Source | I12: Outcome | K12: Revenue | L12: Cash | N12: Objection | O12: Objection Notes | Q12: Length | R12: Recording Link | S12: Follow Up/Next Steps | T12: Call Summary
B13: 03.04.25 | C13: Mia Friis Knudsen | E13: 29852397 | F13: mia-friis-knudsen@hotmail.com | H13: Setter | I13: Offer & Didn't Buy | N13: Think About It | O13: Usikker på om forløbet er noget for hende | R13: https://slack-files.com/T089JBRTVMM-F08LKAN042Z-53ae7da4ea | S13: X | T13: Ender med at synes det er for mange penge, ville høre nærmere. Virkede usikker på om det var noget for hende.
B14: 04.04.25 | C14: Mira Ælmholdt Ottesen | E14: 31329041 | F14: miraottesen@gmail.com | H14: Setter | I14: Offer & Didn't Buy | N14: Think About It | O14: Overvejer at prøve selv først | R14: https://slack-files.com/T089JBRTVMM-F08M2DVVB6D-c84eeabb5d | S14: X | T14: Følte et forløb kunne være et godt suplement til den livsstil hun allerede er ved at bygge op. Er usikker på om hun skal prøve selv, eller få hjælpen til at blive skubbet godt igang. Hjælp til kostvaner, træning og rutiner i hverdagen.
B15: 04.04.25 | C15: Clara S. Been | E15: 0 459 023 332 | F15: beenclara@gmail.com | H15: Setter | I15: Offer & Didn't Buy | N15: Think About It | O15: Ville tænke over om det passede til hende, og om hun kunne finde det i budgettet. | R15: Forhindret | S15: X | T15: Har fitness coash. Med i løbeklub. Vegetar, mangler protein. Ønsker hjælp til kost.
B16: 04.04.25 | C16: (ringet og skrevet)Canan Benli | E16: 42317156 | F16: canan.benli@hotmail.com | H16: Setter | I16: Full-Pay | K16: 9000 | L16: 3000 | Q16: 5 måneder | R16: https://slack-files.com/T089JBRTVMM-F08MFE0CJD6-e1d174471b | S16: Closed | T16: Mangler struktur og den rette løsning. Prøvet meget i mange år uden held. Mega klar til at skabe foranding nu!
B17: 06.04.25 | C17: Ida Mogensen | E17: 40 74 87 87 | F17: ida.mogensen@live.dk | H17: Setter | I17: Offer & Didn't Buy | N17: Think About It | O17: På SU synes det er mange penge | R17: https://slack-files.com/T089JBRTVMM-F08LJSDM32B-e1f6fd421a | S17: X | T17: Synes forløbet lød perfekt i forhold til hendes egen tilgang. (Ikke restriktiv) Små ændringer.
B18: 06.04.25 | C18: Mathilde Nordberg | E18: 25 38 44 97 | F18: mathilde2002@icloud.com | H18: Setter | I18: Offer & Didn't Buy | N18: Money | O18: Studerende, synes det er mange penge | R18: https://slack-files.com/T089JBRTVMM-F08M9TK74BT-71681a9462 | S18: X | T18: Følte forløbet var for hende. Nervøs for at købe da hun har brugt mange penge på coaches før. Har brug for hjælp til vaner, overspisning, struktur, træning, tabe fedt. Har været utilfreds med krop siden 2018.
B19: 07.04.25 | C19: (ringet og skrevet)Ida Nyvang Lundgren Larsen | E19: 20 31 10 45 | F19: ida.nyvang@icloud.com | H19: Setter | I19: Full-Pay | K19: 9,000.00 kr | L19: 1,500.00 kr | N19: Time | O19: Stod midt i nye rammer - snart nyt studie + flytning + rejse | Q19: 5 måneder | R19: https://slack-files.com/T089JBRTVMM-F08M1FVN70D-80cf01cc98 | S19: Closed | T19: Ønsker sig en mere tonet krop, hjælp til at blive tryg i træningscenter, implementering af sunde vaner i en travl, omskiftelig hverdag.
B20: 08.04.25 | C20: Nellie Waaben | E20: 50 19 29 20 | F20: nelliewaaben@gmail.com | H20: Setter | I20: Offer & Didn't Buy | N20: Money | O20: Synes det var meget dyrt, men forløbet er perfekt for hende. | R20: https://slack-files.com/T089JBRTVMM-F08ME5NBDT4-6ab2e9895a | S20: X | T20: Havde brug for støtte til at holde fast i sunde rutiner. Ønskede vægttab, omlægning af kostvaner, hjælp til at ændre mindset og føle sig godt tilpas i sin egen krop. Utilfreds. Ønsker sig mere energi.
B21: 09.04.25 | C21: Louise Christina Gade | E21: 26 23 17 72 | F21: louisecrgade@gmail.com | H21: Setter | I21: Offer & Didn't Buy | N21: Think About It | O21: I tvivl om hun skal vælge et holistisk tarmforløb hun har været på igen, eller Olivia. | R21: https://slack-files.com/T089JBRTVMM-F08M81C5P5L-5eb99c335e | S21: X | T21: Mangler motivation til at skabe de ændringer hun ønsker sig. Når aldrig helt i mål. Har barn, kæreste og har svært ved at passe hendes valg ind med familielivet. Har irriteret tarm og har masser af indsigt i hvad der fungerer for hende, men mangler støtte til at håndtere når motivationen daler.
B22: 10.04.25 | C22: Amira A. Mouna | E22: 30 44 18 74 | F22: Amiramaliamouna1@gmail.com | H22: Setter | I22: Offer & Didn't Buy | N22: Money | O22: Intet på selve kaldet, men fortrød efterfølgende | R22: https://slack-files.com/T089JBRTVMM-F08MQ8K02EP-12dd9edf08 | S22: Follow Up | T22: Var meget motiveret for at skabe de forandringer hun ønsker. Kost og krop holder hende tilbage - ikke glad for hvad hun ser i spejlet.
B23: 11.04.25 | C23: Emma Reinholdt Nissen | E23: 23 11 55 04 | F23: emmareinholdtnissen@gmail.com | H23: Setter | I23: Offer & Didn't Buy | N23: Think About It | O23: Ville sove på det og mange penge | R23: https://slack-files.com/T089JBRTVMM-F08MWHHUFPU-0abf9ab21c | S23: Follow Up | T23: Kunne spejle sig meget i Olivias content, og fortæller at hun ønsker Olivia specifikt, da hun føler de deler samme fortid/historie - ønsker hjælp til træning, kost, søvnmønster og det mentale.
B24: 11.04.25 | C24: Kimmie Liv Sennova | E24: 53 60 69 50 | F24: kimmielivsennova@gmail.com | H24: Setter | I24: Offer & Didn't Buy | N24: Partner | O24: Sove på det og snakke med kæreste | R24: https://slack-files.com/T089JBRTVMM-F08MCD15TPH-c3e664aa76 | S24: Follow Up | T24: Havde brug for hjælp til teknik i træning (glutes) for at se resultater, kost og føle sig godt tilpas i sin krop. Fedttab og toning af kroppen og ønsker all over at skabe en sund livsstil for sig selv som også vil gavne hendes arbejdsliv som performer.
B25: 11.04.25 | C25: Eva Youseff El-Gazzi | E25: 31 31 86 99 | F25: eelghazzi@gmail.com | H25: Setter | I25: Offer & Didn't Buy | N25: Time | O25: Skulle på ferie i 14 dage og havde ikke penge til start up fee før d. 1. maj | R25: https://slack-files.com/T089JBRTVMM-F08MWLVLPFW-3165787c27 | S25: Follow Up | T25: Var meget klar til at komme igang, men blev overrasket over hun skulle betale på dagen. Hun informerer at hun ønsker opstart d. 1. maj
B26: 13.04.25 | C26: Gulpari Khan | E26: 24 43 42 36 | F26: gulparikhan@hotmail.com | H26: Setter | I26: Offer & Didn't Buy | N26: Think About It | O26: Skulle overveje motivation og penge | R26: https://slack-files.com/T089JBRTVMM-F08NA605KQR-a23a9edf51 | S26: X | T26: Var interesseret i at høre mere om hvordan coachesforløb fungerede og deres pris. Ønsker hjælp til kost, vaner, træning og mindset - fokuseret på vægt og havde et klart billede om hvordan hun gerne ville se ud, men synes der var langt. Afhængig af sukker - føler det har taget overhånd.
B27: 14.04.25 | C27: Simone Haarbo | E27: 29 80 31 86 | F27: simone2808@hotmail.dk | H27: Setter | I27: Offer & Didn't Buy | N27: Money | O27: SU | R27: https://slack-files.com/T089JBRTVMM-F08N5UW4D18-ab53728404 | S27: Follow Up | T27: Brug for hjælp til at se fremskridt - sidder fast og ser ingen resultater af sin træning og kostomlægning.
S29: Follow Up | T29: Brug for hjælp til kost og vaner. Har styr på træningsdelen. Ønsker det maksimale udbytte af sin træning - virker meget varm på et 1:1 forløb - vender tilbage inden 24 timer.
S30: Closed | T30: Brug for hjælp til at skabe varige ændringer og arbejde med selvbillede og mindset.
S31: Follow Up | T31: Brug for hjælp til vægttab og kostplan - snacker meget og ønsker mere struktur på kost og træning.
S32: Follow Up | T32: Brug for hjælp til mere tonet krop, bryde med usunde vaner, støtte til at holde de gode rutiner og få styr på kosten - har besværligheder med maven. Har kørt andet forløb før som var restriktivt.
S33: Closed | T33: Brug for hjælp til at bryde med overspisning og finde en god balance i sin kost så det matcher hendes aktivitetsniveau (svømning + løb). Føler sig utilpas i sin krop. Ønsker vægttab og mere tonet.
T34: Ønsker hjælp til vægttab, kost/overspisning, mindset - ønsker at finde den helt rette balance og få alle værktøjer til hvordan hun gør fremadrettet for at holde vægten og balancen i forhold til madvaner. Har prøvet meget selv, og været i restiktivt forløb mens hun havde det svært psykisk (kan derfor ikke huske denne periode)
S35: Closed | T35: Vægttab, opstramning/tonet, kost.
C37: Ringet til
C38: I forløb, reference efterspurgt
C39: Fulgt op 1 gang, potentielt interesseret

Sheet May
B1: Rep: | C1: Name | E1: Outcome | H1: KPIs% | K1: Show Rate | N1: Objections | Q1: Source | U1: Tracking
E2: Full-Pay: | F2: =IFERROR(COUNTIFS(I13:I287, "Full-Pay"),"") -> 7 | H2: Conversion Rate: | I2: =iferror(I10/I8,"") -> 0.57142857 | K2: Rescheduling Rate: | L2: =iferror(F8/I6,"") -> 0 | N2: Think About It | O2: =IFERROR(COUNTIFS(N13:N286, "think about it"),"") -> 2 | Q2: Reschedule | R2: =IFERROR(COUNTIF(H13:H286,Q2),"") -> 0 | S2: Cold Call | T2: =IFERROR(COUNTIF(H13:H286,S2),"") -> 0
B3: Revenue | C3: =IFERROR(SUM(K13:K283),"") -> 38994 | E3: Split-Pay: | F3: =IFERROR(COUNTIFS(I13:I287, "Split-Pay"),"") -> 1 | H3: Offer To Close Rate: | I3: =IFERROR(I10/I9,"") -> 0.57142857 | K3: Cancellation Rate: | L3: =iferror(F9/I6,"") -> 0 | N3: Money | O3: =IFERROR(COUNTIFS(N13:N286, "money"),"") -> 7 | Q3: YouTube | R3: =IFERROR(COUNTIF(H13:H286,Q3),"") -> 0 | S3: Twitter | T3: =IFERROR(COUNTIF(H13:H286,S3),"") -> 0
B4: Cash | C4: =IFERROR(SUM(L13:L284),"") -> 31498 | E4: Deposits: | F4: =IFERROR(COUNTIFS(I13:I287, "Deposit"),"") -> 0 | H4: Call To Offer Rate: | I4: =IFERROR(I9/I8,"") -> 1 | K4: No-Shows Rate: | L4: =iferror(F10/I6,"") -> 0 | N4: Time | O4: =IFERROR(COUNTIFS(N13:N286, "time"),"") -> 2 | Q4: YouTube Ads | R4: =IFERROR(COUNTIF(H13:H286,Q4),"") -> 0 | S4: Skool | T4: =IFERROR(COUNTIF(H13:H286,S4),"") -> 0
E5: Offer & Didn't Buy: | F5: =IFERROR(COUNTIFS(I13:I287, "Offer & Didn't Buy"),"") -> 6 | H5: Drag Over Rate: | I5: =IFERROR(F7/(C6+F7+F8),"") -> 0 | K5: Drag Over Rate: | L5: =iferror(F7/I6,"") -> 0 | N5: Partner | O5: =IFERROR(COUNTIFS(N13:N286, "partner"),"") -> 0 | Q5: Email | R5: =IFERROR(COUNTIF(H13:H286,Q5),"") -> 0 | S5: Instagram | T5: =IFERROR(COUNTIF(H13:H286,S5),"") -> 0
B6: Total Calls : | C6: =IFERROR(SUM(F2:F6),"") -> 14 | E6: Bad Fit & No Offer: | F6: =IFERROR(COUNTIFS(I13:I287, "Bad Fit & No Offer"),"") -> 0 | H6: Bookings: | I6: =IFERROR(SUM(F2:F10),"") -> 14 | K6: Show-Up Rate: | L6: =iferror(I7/I6,"") -> 1 | N6: Fear | O6: =IFERROR(COUNTIFS(N13:N286, "fear"),"") -> 1 | Q6: Facebook | R6: =IFERROR(COUNTIF(H13:H286,Q6),"") -> 0 | S6: TikTok | T6: =IFERROR(COUNTIF(H13:H286,S6),"") -> 0
B7: Total Won : | C7: =IFERROR(F2+F3,"") -> 8 | E7: Drag Over & Show: | F7: =IFERROR(COUNTIFS(I13:I287, "Drag Over & Show"),"") -> 0 | H7: Shows: | I7: =IFERROR(SUM(F2:F7),"") -> 14 | K7: Conducted Rate: | L7: =IFERROR(I8/I6,"") -> 1 | N7: Value | O7: =IFERROR(COUNTIFS(N14:N287, "value"),"") -> 0 | Q7: Facebook Ads | R7: =IFERROR(COUNTIF(H13:H286,Q7),"") -> 0 | S7: Google | T7: =IFERROR(COUNTIF(H13:H286,S7),"") -> 0
B8: Total Lost : | C8: =COUNTIF(I13:I286,"offer & didn't buy")+countif(I13:I286,"deposit")+countif(I13:I286,"bad fit & no offer") -> 6 | E8: Rescheduled: | F8: =IFERROR(COUNTIFS(I13:I287, "Rescheduled"),"") -> 0 | H8: Calls: | I8: =IFERROR(SUM(F2:F6),"") -> 14 | Q8: LinkedIn | R8: =IFERROR(COUNTIF(H13:H286,Q8),"") -> 0 | S8: Referral | T8: =IFERROR(COUNTIF(H13:H286,S8),"") -> 0
B9: Closing % : | C9: =iferror(SUM(C7/C6),"") -> 0.57142857 | E9: Cancelled: | F9: =IFERROR(COUNTIFS(I13:I287, "Cancelled"),"") -> 0 | H9: Offers: | I9: =IFERROR(sum(F2:F5),"") -> 14
E10: No-Show: | F10: =IFERROR(COUNTIFS(I13:I287, "No-Show"),"") -> 0 | H10: Deals | I10: =F2+F3 -> 8
B12: Date | C12: Name | E12: Phone No. | F12: Email | H12: Source | I12: Outcome | K12: Revenue | L12: Cash | N12: Objection | O12: Objection Notes | Q12: Length | R12: Recording Link | S12: Follow Up/Next Steps | T12: Call Summary
B13: 02.05.25 | C13: Alma Styrbech | E13: 42 76 48 52 | F13: astyrbech@gmail.com | H13: Setter | I13: Full-Pay | K13: 2247 | L13: 749 | N13: Think About It | O13: Overvejer opstart i start juni | Q13: Selvstændig | R13: https://slack-files.com/T089JBRTVMM-F08QR5YR1EX-62568a2bb0 | S13: Closed | T13: Brug for hjælp til kost og vaner. Har styr på træningsdelen. Ønsker det maksimale udbytte af sin træning - virker meget varm på et 1:1 forløb - vender tilbage inden 24 timer.
B14: 06.05.25 | C14: Tina Andersen | E14: 29 79 95 26 | F14: tina_and98@hotmail.com | H14: Setter | I14: Full-Pay | K14: 3000 | L14: 3000 | N14: Money | Q14: 3 måneder | R14: https://slack-files.com/T089JBRTVMM-F08QPB5BW87-2190d0f762 | S14: Closed | T14: Brug for hjælp til at skabe varige ændringer og arbejde med selvbillede og mindset.
B15: 10.05.25 | C15: Pavitha Kasirajah (skrevet besked) | E15: 42 47 43 62 | F15: ktpavitha@gmail.com | H15: Setter | I15: Offer & Didn't Buy | N15: Money | O15: På SU - overvejer budget | R15: https://slack-files.com/T089JBRTVMM-F08RUGEQXUJ-81378ae256 | S15: X | T15: Brug for hjælp til vægttab og kostplan - snacker meget og ønsker mere struktur på kost og træning.
B16: 07.05.25 | C16: Maria Hjort Tønnesen (ringer og skrevet) | E16: 22 78 05 79 | F16: mhjortt@gmail.com | H16: Setter | I16: Offer & Didn't Buy | N16: Time | O16: Står midt i jobskifte | R16: https://slack-files.com/T089JBRTVMM-F08RYPSEGN4-938d06b03b | S16: Follow Up | T16: Brug for hjælp til mere tonet krop, bryde med usunde vaner, støtte til at holde de gode rutiner og få styr på kosten - har besværligheder med maven. Har kørt andet forløb før som var restriktivt.
B17: 12.05.25 | C17: Leonora Amalie Minet Ricks | E17: 26 11 17 72 | F17: leonoraricks@gmail.com | H17: Setter | I17: Full-Pay | K17: 6000 | L17: 6000 | Q17: 3 måneder | R17: https://slack-files.com/T089JBRTVMM-F08SL8SQ796-48d7110029 | S17: Closed | T17: Brug for hjælp til at bryde med overspisning og finde en god balance i sin kost så det matcher hendes aktivitetsniveau (svømning + løb). Føler sig utilpas i sin krop. Ønsker vægttab og mere tonet.
B18: 14.05.25 | C18: Julie Kristensen | E18: 61 16 66 08 | F18: julierlk@hotmail.com | H18: Setter | I18: Offer & Didn't Buy | N18: Fear | R18: https://slack-files.com/T089JBRTVMM-F08T0P7C9FA-9c57ca676d | S18: Follow Up | T18: Ønsker hjælp til vægttab, kost/overspisning, mindset - ønsker at finde den helt rette balance og få alle værktøjer til hvordan hun gør fremadrettet for at holde vægten og balancen i forhold til madvaner. Har prøvet meget selv, og været i restiktivt forløb mens hun havde det svært psykisk (kan derfor ikke huske denne periode)
B19: 15.05.25 | C19: Melani Juul Nysom Pedersen | E19: 21 30 08 29 | F19: melanifrugthaven@gmail.com | H19: Setter | I19: Full-Pay | K19: 2247 | L19: 749 | N19: Think About It | Q19: Selvstændig | R19: https://slack-files.com/T089JBRTVMM-F08SLJP0M6G-d551736604 | S19: Closed | T19: Vægttab, opstramning/tonet, kost.
B20: 19.05.25 | C20: Laura Hvilshøj Liin | E20: 29 17 73 61 | F20: lauraliin350a@gmail.com | H20: Setter | I20: Full-Pay | K20: 6000 | L20: 6000 | O20: Penge - mellem jobs. I tvivl om det var lige nu. | Q20: 3 måneder | R20: https://slack-files.com/T089JBRTVMM-F08T1GR9AHY-cec6910858 | S20: Closed | T20: Mindset, muskelmasse, styrketræning, struktur til nye rutiner, motivation til at komme afsted (har veninde som også går i forløb), ro i sindet, kostoverblik.
B21: 20.05.25 | C21: Mia Adamsen | E21: 25 72 14 41 | F21: m@henrikadamsen.com | H21: Setter | I21: Offer & Didn't Buy | N21: Money | O21: Penge og samtale med andre coaches | R21: https://slack-files.com/T089JBRTVMM-F08TVQZ397T-e9af25da65 | S21: X | T21: Synes alt ved forløbet var perfekt. Havde brug for hjælp til balance i kost, sunde vner.
B22: 21.05.25 | C22: Freja Ladehoff | E22: 50 44 96 71 | F22: freja.ladehoff04@gmail.com | H22: Setter | I22: Full-Pay | K22: 6000 | L22: 6000 | N22: Money | R22: https://slack-files.com/T089JBRTVMM-F08SYJ51ZTR-0f551d8bd7 | S22: Closed | T22: Hjælp til kost, oppustethed, mindset og toning af krop.
B23: 21.05.25 | C23: Kirstine Braüner | E23: 27 59 73 99 | F23: kirstine_brauner@hotmail.com | H23: Setter | I23: Offer & Didn't Buy | N23: Time | Q23: Selvstændig | S23: Follow Up | T23: Ønsker hjælp til indre ro, pauser, nervesystem og meditation - mindset
B24: 28.05.25 | C24: Melissa Mortensen (skrevet) | E24: 23 62 57 15 | F24: melissaengelsted@gmail.com | H24: Setter | I24: Offer & Didn't Buy | N24: Money | R24: https://slack-files.com/T089JBRTVMM-F08V02U273J-9c1dff272e | S24: Follow Up | T24: Oppustethed, vægttab, selvbillede og selvtillid, mindset, utilpas i sin krop - mangler at finde balancen hele vejen rundt.
B25: 30.05.25 | C25: Anna Friis | E25: 30 48 50 18 | F25: annahugfriis@icloud.com | H25: Setter | I25: Split-pay | K25: 6000 | L25: 1500 | N25: Money | O25: På SU | R25: https://slack-files.com/T089JBRTVMM-F08UPR50350-e5949fc516 | S25: Closed | T25: Hjælp til mindset - opbygge selvværd. Kost. Usikker i træningscentret. Taler dårligt til sig selv - påvirker hendes parforhold.
B26: 29.05.25 | C26: Amalie Johansen | E26: 29 79 49 55 | F26: ama.johansen@live.dk | H26: Setter | I26: Full-Pay | K26: 7500 | L26: 7500 | N26: Money | R26: https://slack-files.com/T089JBRTVMM-F08UAV6UBV4-5bc0a5d8f9 | S26: Closed | T26: Motivation til styrketræning (trænet før) gør mange ting, men ser ikke fremgang, overspiser, ønsker at tabe sig 10 kg. strammet op og forbedre løb + få intro til maskiner i fitness.

Sheet Jun
B1: Rep: | C1: Name | E1: Outcome | H1: KPIs% | K1: Show Rate | N1: Objections | Q1: Source | U1: Tracking
E2: Full-Pay: | F2: =IFERROR(COUNTIFS(I13:I287, "Full-Pay"),"") -> 3 | H2: Conversion Rate: | I2: =iferror(I10/I8,"") -> 0.64285714 | K2: Rescheduling Rate: | L2: =iferror(F8/I6,"") -> 0 | N2: Think About It | O2: =IFERROR(COUNTIFS(N13:N286, "think about it"),"") -> 2 | Q2: Reschedule | R2: =IFERROR(COUNTIF(H13:H286,Q2),"") -> 0 | S2: Cold Call | T2: =IFERROR(COUNTIF(H13:H286,S2),"") -> 0
B3: Revenue | C3: =IFERROR(SUM(K13:K283),"") -> 60000 | E3: Split-Pay: | F3: =IFERROR(COUNTIFS(I13:I287, "Split-Pay"),"") -> 6 | H3: Offer To Close Rate: | I3: =IFERROR(I10/I9,"") -> 0.64285714 | K3: Cancellation Rate: | L3: =iferror(F9/I6,"") -> 0 | N3: Money | O3: =IFERROR(COUNTIFS(N13:N286, "money"),"") -> 8 | Q3: YouTube | R3: =IFERROR(COUNTIF(H13:H286,Q3),"") -> 0 | S3: Twitter | T3: =IFERROR(COUNTIF(H13:H286,S3),"") -> 0
B4: Cash | C4: =IFERROR(SUM(L13:L284),"") -> 34500 | E4: Deposits: | F4: =IFERROR(COUNTIFS(I13:I287, "Deposit"),"") -> 0 | H4: Call To Offer Rate: | I4: =IFERROR(I9/I8,"") -> 1 | K4: No-Shows Rate: | L4: =iferror(F10/I6,"") -> 0 | N4: Time | O4: =IFERROR(COUNTIFS(N13:N286, "time"),"") -> 0 | Q4: YouTube Ads | R4: =IFERROR(COUNTIF(H13:H286,Q4),"") -> 0 | S4: Skool | T4: =IFERROR(COUNTIF(H13:H286,S4),"") -> 0
E5: Offer & Didn't Buy: | F5: =IFERROR(COUNTIFS(I13:I287, "Offer & Didn't Buy"),"") -> 5 | H5: Drag Over Rate: | I5: =IFERROR(F7/(C6+F7+F8),"") -> 0 | K5: Drag Over Rate: | L5: =iferror(F7/I6,"") -> 0 | N5: Partner | O5: =IFERROR(COUNTIFS(N13:N286, "partner"),"") -> 0 | Q5: Email | R5: =IFERROR(COUNTIF(H13:H286,Q5),"") -> 0 | S5: Instagram | T5: =IFERROR(COUNTIF(H13:H286,S5),"") -> 0
B6: Total Calls : | C6: =IFERROR(SUM(F2:F6),"") -> 14 | E6: Bad Fit & No Offer: | F6: =IFERROR(COUNTIFS(I13:I287, "Bad Fit & No Offer"),"") -> 0 | H6: Bookings: | I6: =IFERROR(SUM(F2:F10),"") -> 14 | K6: Show-Up Rate: | L6: =iferror(I7/I6,"") -> 1 | N6: Fear | O6: =IFERROR(COUNTIFS(N13:N286, "fear"),"") -> 0 | Q6: Facebook | R6: =IFERROR(COUNTIF(H13:H286,Q6),"") -> 0 | S6: TikTok | T6: =IFERROR(COUNTIF(H13:H286,S6),"") -> 0
B7: Total Won : | C7: =IFERROR(F2+F3,"") -> 9 | E7: Drag Over & Show: | F7: =IFERROR(COUNTIFS(I13:I287, "Drag Over & Show"),"") -> 0 | H7: Shows: | I7: =IFERROR(SUM(F2:F7),"") -> 14 | K7: Conducted Rate: | L7: =IFERROR(I8/I6,"") -> 1 | N7: Value | O7: =IFERROR(COUNTIFS(N14:N287, "value"),"") -> 0 | Q7: Facebook Ads | R7: =IFERROR(COUNTIF(H13:H286,Q7),"") -> 0 | S7: Google | T7: =IFERROR(COUNTIF(H13:H286,S7),"") -> 0
B8: Total Lost : | C8: =COUNTIF(I13:I286,"offer & didn't buy")+countif(I13:I286,"deposit")+countif(I13:I286,"bad fit & no offer") -> 5 | E8: Rescheduled: | F8: =IFERROR(COUNTIFS(I13:I287, "Rescheduled"),"") -> 0 | H8: Calls: | I8: =IFERROR(SUM(F2:F6),"") -> 14 | Q8: LinkedIn | R8: =IFERROR(COUNTIF(H13:H286,Q8),"") -> 0 | S8: Referral | T8: =IFERROR(COUNTIF(H13:H286,S8),"") -> 0
B9: Closing % : | C9: =iferror(SUM(C7/C6),"") -> 0.64285714 | E9: Cancelled: | F9: =IFERROR(COUNTIFS(I13:I287, "Cancelled"),"") -> 0 | H9: Offers: | I9: =IFERROR(sum(F2:F5),"") -> 14
E10: No-Show: | F10: =IFERROR(COUNTIFS(I13:I287, "No-Show"),"") -> 0 | H10: Deals | I10: =F2+F3 -> 9
B12: Date | C12: Name | E12: Phone No. | F12: Email | H12: Source | I12: Outcome | K12: Revenue | L12: Cash | N12: Objection | O12: Objection Notes | Q12: Length | R12: Recording Link | S12: Follow Up/Next Steps | T12: Call Summary
B13: 02.06.25 | C13: Laura Snerle Kranker | E13: 51 20 22 33 | F13: lauracsk@gmail.com | H13: Setter | I13: Split-pay | K13: 6000 | L13: 3000 | N13: Money | Q13: 3 måneder | R13: https://slack-files.com/T089JBRTVMM-F08TVR24X5X-171325519b | S13: Closed | T13: Nyt kald aftalt d. 2. juni - Binge-eating spiral, mave, struktur, motivation, kost - mood svings, dårligt selvværd - går 8 år tilbage.
B14: 02.06.25 | C14: Sofie Pihl Rasmussen | E14: 42 75 09 15 | F14: rasmussensofiepihl@gmail.com | H14: Setter | I14: Split-pay | K14: 6000 | L14: 1500 | N14: Money | O14: Skal flytte, på SU inden længe og ud at rejse | Q14: 3 måneder | R14: https://slack-files.com/T089JBRTVMM-F08UM3C1527-ffa11987c0 | S14: Closed | T14: Haft spiseforstyrrelse - hjælp til mindset og tænke gode tanker om sig selv, nået langt men mangler det sidste. Ønsker hjælp til træningsprogram, selvtillid - fred og ro omkring mad.
B15: 04.06.25 | C15: Lykke Christine Elvstrøm | E15: 93 92 27 18 | F15: lykkeelvstroem15@gmail.com | H15: Setter | I15: Full-Pay | K15: 6000 | L15: 6000 | Q15: 3 måneder | R15: https://slack-files.com/T089JBRTVMM-F08VDB9TU2G-ad3ba23f37 | S15: Closed | T15: Hjælp til tonet krop - balancen mellem kost og træning. Alt eller intet-mentalitet. Ønsker tydelige resultater af sin indsats. Har altid trænet regulært, men ser ingen tydelige forandringer.
B16: 06.06.25 | C16: Karen-Cecilie Kortenbach | E16: 22 89 01 12 | F16: tessduus@hotmail.com | H16: Setter | I16: Full-Pay | K16: 7500 | L16: 7500 | Q16: 4 måneder | R16: https://slack-files.com/T089JBRTVMM-F08V9HLUSGP-e854fe9c76 | S16: Closed | T16: Hjemmetræningsprogram. Rigtig godt igang med gode vaner selv. Hjælp til balance mellem kost og træning - føler sig meget sulten fordi hun ikke spiser i løbet af dagen og overspiser om aftenen. Ønsker mere viden omkring kost og træning for at nå helt i mål - har tabt 20 kg. på egen hånd.
B17: 08.06.25 | C17: Rebekka Lindholm | E17: 29 44 21 39 | F17: rebekka@riislindholm.dk | H17: Setter | I17: Offer & Didn't Buy | N17: Think About It | Q17: 4 måneder | R17: https://slack-files.com/T089JBRTVMM-F090J524ASG-50f341609d | S17: X | T17: Ønsker mere viden omkring træning og kost. Har de sidste 5 år været utilfreds med sin krop hvilket går ud over hendes selvværd og selvstillid. Er gymnast. Går i gym. Har i øjeblikket stress. Føler forløbet kan hjælpe hende i mål med det hun ønsker.
B18: 09.06.25 | C18: Amalie Mikkelsen | E18: 21 75 63 03 | F18: nikitalist@hotmail.com | H18: Setter | I18: Split-pay | K18: 9000 | L18: 4500 | N18: Think About It | Q18: 5 måneder | R18: https://slack-files.com/T089JBRTVMM-F090M7X1GKW-6cdd3a3ab1 | S18: Closed | T18: Har et biologisk ur der tikker i forhold til tidlig overgangsalder hvorfor hun har brug for at skabe en livsstilsændring (28 år).
B19: 10.06.25 | C19: Emma Junker | E19: 29 28 26 72 | F19: emmathobo@gmail.com | H19: Setter | I19: Offer & Didn't Buy | N19: Money | Q19: 3 måneder | R19: https://slack-files.com/T089JBRTVMM-F090T3647U3-5467e18aaa | S19: X | T19: Vægttab - mere selvtillid og selvsikker. Hjælp til træning, kost. Mere tonet krop. Overvejet at skabe forandringer i 3 år.
B20: 11.06.25 | C20: Pernille Frederikke Juhl Rosenkilde | E20: 52 30 45 28 | F20: pf.rosenkilde@gmail.com | H20: Setter | I20: Split-pay | K20: 6000 | L20: 1500 | N20: Money | Q20: 3 måneder | R20: https://slack-files.com/T089JBRTVMM-F090STS7V0E-6489aefab7 | S20: Closed | T20: Hjælp til kost og træning. Har været i forløb før. Ser ikke resultater af sin indsats selv om hun træner jævnligt. Har været i forløb flere gange før. SU
B21: 17.06.25 | C21: Josephine Kristensen | E21: 29 85 82 72 | F21: josephinekristensen2@gmail.com | H21: Setter | I21: Offer & Didn't Buy | Q21: 3 måneder | R21: https://slack-files.com/T089JBRTVMM-F092HLN02D6-222160e8d2 | S21: Follow Up | T21: Har gang i træning men manlger hjælp til at nå det sidste - få styr på kost så hun begynder at se tydelige resultater. Vægttab, tonet, mere tilpas i krop. Klar til at der skal ske noget nu. Forsøgt de sidste 3 måneder, men mangler redskaber og viden.
B22: 17.06.25 | C22: Louise Krejberg Jensen | E22: 50 70 32 90 | F22: louisekjensen27@gmail.com | H22: Setter | I22: Offer & Didn't Buy | N22: Money | O22: Midt i flytning | Q22: 4 måneder | R22: https://slack-files.com/T089JBRTVMM-F091V4RS560-8e2e62fcee | S22: Follow Up | T22: Ønsker hjælp til vægttab, muskelmasse og kostvejledning - klar over hun er nødt til at ændre adfærd hvis hun skal nå i mål. Står stille selv om hun træner meget. Stået stille i 6 måneder. Balance og madro.
B23: 18.06.25 | C23: Janne Winther | E23: 27 39 51 76 | F23: janne@myron.dk | H23: Setter | I23: Full-Pay | K23: 7500 | L23: 7500 | N23: Money | Q23: 4 måneder | R23: https://slack-files.com/T089JBRTVMM-F091YRAUUGM-d8d2583099 | S23: Closed | T23: 57 år. Mangler hjælp til livsstilsændring. Ønsker at tabe 10 kg, spise mindre sukker og etablere sunde kostvaner og hjemmetræningsprogram. Mindset og motivation til sunde rutiner. Klar til forandring - har sagt job op og vil bruge sommeren på at bygge sig selv op.
B24: 20.06.25 | C24: Lilian Ostersen Rørby | E24: 27 58 40 96 | F24: lilianrorby@gmail.com | H24: Setter | I24: Split-pay | K24: 6000 | L24: 1500 | N24: Money | O24: Økonomi | Q24: 3 måneder | R24: https://slack-files.com/T089JBRTVMM-F092CPC6C84-d73376f8d3 | S24: Closed | T24: Hjælp til kost - træner meget og vil gerne have mere energi og overskud i en travl hverdag. Nyligt fraskilt og har taget en beslutning om en livsstilsændring. Maveproblemer - oppustethed og irritabel tyktarm. Ønsker at føle sig mæt hele dagen.
B25: 24.06.25 | C25: Freja Høgsted | E25: 24 24 67 80 | F25: frejahoegsted8@gmail.com | H25: Setter | I25: Split-pay | K25: 6000 | L25: 1500 | N25: Money | O25: Økonomi | Q25: 3 måneder | R25: https://slack-files.com/T089JBRTVMM-F092R7XC5B7-1e4b864eb2 | S25: Closed
B26: 25.06.25 | C26: Mariam Mehmood | E26: 42 25 16 31 | F26: mariam-mehmood@hotmail.com | H26: Setter | I26: Offer & Didn't Buy | O26: Måske brækket fod. Venter på svar fra læge | Q26: 3 måneder | R26: https://slack-files.com/T089JBRTVMM-F0931K0S2UC-0c286e8757 | S26: X | T26: Ønsker hjælp til sundere kostvaner - ked af fedt på maven. Mere tonet krop.

Sheet Jul
A1: e | B1: Rep: | C1: Name | E1: Outcome | H1: KPIs% | K1: Show Rate | N1: Objections | Q1: Source | U1: Tracking
E2: Full-Pay: | F2: =IFERROR(COUNTIFS(I13:I287, "Full-Pay"),"") -> 4 | H2: Conversion Rate: | I2: =iferror(I10/I8,"") -> 0.61111111 | K2: Rescheduling Rate: | L2: =iferror(F8/I6,"") -> 0 | N2: Think About It | O2: =IFERROR(COUNTIFS(N13:N286, "think about it"),"") -> 2 | Q2: Reschedule | R2: =IFERROR(COUNTIF(H13:H286,Q2),"") -> 0 | S2: Cold Call | T2: =IFERROR(COUNTIF(H13:H286,S2),"") -> 0
B3: Revenue | C3: =IFERROR(SUM(K13:K283),"") -> 79500 | E3: Split-Pay: | F3: =IFERROR(COUNTIFS(I13:I287, "Split-Pay"),"") -> 7 | H3: Offer To Close Rate: | I3: =IFERROR(I10/I9,"") -> 0.61111111 | K3: Cancellation Rate: | L3: =iferror(F9/I6,"") -> 0 | N3: Money | O3: =IFERROR(COUNTIFS(N13:N286, "money"),"") -> 9 | Q3: YouTube | R3: =IFERROR(COUNTIF(H13:H286,Q3),"") -> 0 | S3: Twitter | T3: =IFERROR(COUNTIF(H13:H286,S3),"") -> 0
B4: Cash | C4: =IFERROR(SUM(L13:L284),"") -> 47000 | E4: Deposits: | F4: =IFERROR(COUNTIFS(I13:I287, "Deposit"),"") -> 0 | H4: Call To Offer Rate: | I4: =IFERROR(I9/I8,"") -> 1 | K4: No-Shows Rate: | L4: =iferror(F10/I6,"") -> 0 | N4: Time | O4: =IFERROR(COUNTIFS(N13:N286, "time"),"") -> 0 | Q4: YouTube Ads | R4: =IFERROR(COUNTIF(H13:H286,Q4),"") -> 0 | S4: Skool | T4: =IFERROR(COUNTIF(H13:H286,S4),"") -> 0
E5: Offer & Didn't Buy: | F5: =IFERROR(COUNTIFS(I13:I287, "Offer & Didn't Buy"),"") -> 7 | H5: Drag Over Rate: | I5: =IFERROR(F7/(C6+F7+F8),"") -> 0 | K5: Drag Over Rate: | L5: =iferror(F7/I6,"") -> 0 | N5: Partner | O5: =IFERROR(COUNTIFS(N13:N286, "partner"),"") -> 0 | Q5: Email | R5: =IFERROR(COUNTIF(H13:H286,Q5),"") -> 0 | S5: Instagram | T5: =IFERROR(COUNTIF(H13:H286,S5),"") -> 0
B6: Total Calls : | C6: =IFERROR(SUM(F2:F6),"") -> 18 | E6: Bad Fit & No Offer: | F6: =IFERROR(COUNTIFS(I13:I287, "Bad Fit & No Offer"),"") -> 0 | H6: Bookings: | I6: =IFERROR(SUM(F2:F10),"") -> 18 | K6: Show-Up Rate: | L6: =iferror(I7/I6,"") -> 1 | N6: Fear | O6: =IFERROR(COUNTIFS(N13:N286, "fear"),"") -> 2 | Q6: Facebook | R6: =IFERROR(COUNTIF(H13:H286,Q6),"") -> 0 | S6: TikTok | T6: =IFERROR(COUNTIF(H13:H286,S6),"") -> 0
B7: Total Won : | C7: =IFERROR(F2+F3,"") -> 11 | E7: Drag Over & Show: | F7: =IFERROR(COUNTIFS(I13:I287, "Drag Over & Show"),"") -> 0 | H7: Shows: | I7: =IFERROR(SUM(F2:F7),"") -> 18 | K7: Conducted Rate: | L7: =IFERROR(I8/I6,"") -> 1 | N7: Value | O7: =IFERROR(COUNTIFS(N14:N287, "value"),"") -> 1 | Q7: Facebook Ads | R7: =IFERROR(COUNTIF(H13:H286,Q7),"") -> 0 | S7: Google | T7: =IFERROR(COUNTIF(H13:H286,S7),"") -> 0
B8: Total Lost : | C8: =COUNTIF(I13:I286,"offer & didn't buy")+countif(I13:I286,"deposit")+countif(I13:I286,"bad fit & no offer") -> 7 | E8: Rescheduled: | F8: =IFERROR(COUNTIFS(I13:I287, "Rescheduled"),"") -> 0 | H8: Calls: | I8: =IFERROR(SUM(F2:F6),"") -> 18 | Q8: LinkedIn | R8: =IFERROR(COUNTIF(H13:H286,Q8),"") -> 0 | S8: Referral | T8: =IFERROR(COUNTIF(H13:H286,S8),"") -> 0
B9: Closing % : | C9: =iferror(SUM(C7/C6),"") -> 0.61111111 | E9: Cancelled: | F9: =IFERROR(COUNTIFS(I13:I287, "Cancelled"),"") -> 0 | H9: Offers: | I9: =IFERROR(sum(F2:F5),"") -> 18
B10: Rev per lead | C10: =C3/C6 -> 4416.6667 | E10: No-Show: | F10: =IFERROR(COUNTIFS(I13:I287, "No-Show"),"") -> 0 | H10: Deals | I10: =F2+F3 -> 11
B12: Date | C12: Name | E12: Phone No. | F12: Email | H12: Source | I12: Outcome | K12: Revenue | L12: Cash | N12: Objection | O12: Objection Notes | Q12: Length | R12: Recording Link | S12: Follow Up/Next Steps | T12: Call Summary
B13: 01.07.25 | C13: Katia Kirstine Agri | E13: 28 78 59 01 | F13: katiac2992@gmail.com | H13: Setter | I13: Split-pay | K13: 6000 | L13: 3000 | Q13: 3 måneder | R13: https://slack-files.com/T089JBRTVMM-F093GLB4NKH-8d9f85d0df | S13: Closed | T13: Vægttab, spiseforstyrrelse siden hun var 6 år (er 33) glæden tilbage ved mad, struktur og gode vaner. Selvbillede. Har diabetes 1, IBS, glutenallergi.
B14: 01.07.25 | C14: Eva Boye Rasmussen | E14: 31 33 35 64 | F14: evabr99@gmail.com | H14: Setter | I14: Offer & Didn't Buy | N14: Money | O14: På SU. Usikker på resultater | Q14: 3 måneder | S14: X | T14: Spiseforstyrrelse. Går 13 år tilbage. Aldrig haft balance i kosten. Prøvet flere ting uden at lykkedes. Genoptrænings hos fys. Meget tvivl omkring hun kan lykkes med det.
B15: 05.07.25 | C15: Jessica Rasmussen | E15: 40 61 97 89 | F15: rasmussenjessica9@gmail.com | H15: Setter | I15: Split-pay | K15: 9000 | L15: 1500 | N15: Money | O15: På kontakthjælp | Q15: 5 måneder | R15: https://slack-files.com/T089JBRTVMM-F0943BG3G31-a11871ad1f | S15: Closed | T15: Har i 6 år kæmpet med overvægt. Været på vægttabsmedicin og tog alt på igen. Har vejet over 100 kg og ønsker forandring nu. Opstart 1. aug. Afsluttet i okt. grundet økonomi
B16: 08.07.25 | C16: Rikke Petersen | E16: 50 56 13 21 | F16: rik98@outlook.dk | H16: Setter | I16: Offer & Didn't Buy | N16: Fear | O16: Snak med partner | Q16: 4 måender | R16: https://slack-files.com/T089JBRTVMM-F094ZRKDD50-21466958f8 | S16: X | T16: Skabe opbyggende rutiner som styrker selvværd. Har svært ved at stå stærkt i sig selv og sige nej. Går 8 år tilbage - har ikke knækket koden til den livsstil hun ønsker sig. Mindset
B17: 08.07.25 | C17: Karen Magrethe René Sørensen | E17: 28 15 82 15 | F17: karsoe25@icloud.com | H17: Setter | I17: Full-Pay | K17: 7500 | L17: 7500 | Q17: 4 måneder | R17: https://slack-files.com/T089JBRTVMM-F095F4WCB08-4eec636472 | S17: Closed | T17: Manger træningsplan, motivation og lyst til at holde fast i vaner. Tabe fedt på maven og få en stærkere krop. Går 6 år tilbage.
B18: 09.07.25 | C18: Emma Kjærsgaard Gyldenvang | E18: 91 56 68 91 | F18: emmagyldenvang@gmail.com | H18: Setter | I18: Split-pay | K18: 7500 | L18: 5000 | N18: Money | O18: På SU | Q18: 4 måneder | R18: https://slack-files.com/T089JBRTVMM-F094U35EKQT-559a3c6aca | S18: Closed | T18: Døjer med konstant oppustethed (sidste 2-3 år) Mere viden omkring kost
B19: 10.07.25 | C19: Sara Pedersen | E19: 42 18 67 87 | F19: saraepedersen@hotmail.dk | H19: Setter | I19: Full-Pay | K19: 7500 | L19: 7500 | N19: Money | O19: Stor investering men ser værdien | Q19: 4 måneder | R19: https://slack-files.com/T089JBRTVMM-F09565V8VJN-716aa456e1 | S19: Closed | T19: Hjælp til at få helt styr på kosten. Er på vægttabsmedicin og vil meget gerne af den! Har tabt 17 kg. på 3 måneder via medicin og ønsker nu at skabe en sund livsstil så hun kan bevare vægttabet. Har vejet over 100 kg og altid haft svært ved sund kost og overvægt.
B20: 14.07.25 | C20: Frederikke Leonthin (ringet + skrevet) | E20: 41 15 11 41 | F20: fleonthin@hotmail.com | H20: Setter | I20: Full-Pay | K20: 9000 | L20: 9000 | Q20: 5 måneder | R20: https://slack-files.com/T089JBRTVMM-F095Q3DKSRJ-ba4b55697b | S20: Closed | T20: Ønsker viden omkring sammensætning af kost, styrketræning i fitness (teknik). Meget fokus på mindset. Har haft svært ved kost og døjet med undervægt i 20 år (hun er 30). Fik talt sig varm på at starte nu. Tilladelse til at kontakte om en måneds tid for at høre hvordan det går. Har veninde der er i forløb hun kan følges med.
B21: 14.07.25 | C21: Annette Bangshøj | E21: 28 15 05 11 | F21: annette-clausen@hotmail.com | H21: Setter | I21: Offer & Didn't Buy | N21: Value | O21: Ikke nok pain | Q21: 3 måneder | R21: https://slack-files.com/T089JBRTVMM-F096HC7U8UQ-5c0844adb4 | S21: X | T21: Ønsker at få styr på sine spisevaner - træner meget i forvejen og føler hun har godt styr på det. Kosten er også okay, men hun mangler lige det sidste. Mere energi og viden om mad
B22: 18.07.25 | C22: Ida Sjømann (skrevet og ringet) | E22: 30 48 25 14 | F22: idasjoemann@gmail.com | H22: Setter | I22: Full-Pay | K22: 7500 | L22: 7500 | Q22: 4 måneder | R22: https://slack-files.com/T089JBRTVMM-F096ELC6EGJ-67e1074c2c | S22: Closed | T22: Styr på kosten. Er ved politiet med omskiftelige arbejdstider. mangler en overskuelig madplan og ønsker hjælp til hjemmetræning. tabe 5 kg og tonet krop.
B23: 20.07.25 | C23: Sara Ingwersen (ringet og skrevet) | E23: 42 16 63 16 | F23: sara1508@hotmail.dk | H23: Setter | I23: Split-pay | K23: 9000 | L23: 3000 | N23: Money | Q23: 5 måneder | R23: https://slack-files.com/T089JBRTVMM-F09710309FT-d2831088d6 | S23: Closed | T23: Har været i coach-forløb før, men er klar på at finde den rette hjælp og investere i sig selv. Vil gerne tabe 5-10 kg. Viden om kost og særligt mindset!
B24: 22.07.25 | C24: Cecilie Dybdal Holm | E24: 24 26 16 46 | F24: cecilie.holm@hotmail.com | H24: Setter | I24: Offer & Didn't Buy | N24: Money | O24: Penge og frygt | Q24: 5 måneder | R24: https://slack-files.com/T089JBRTVMM-F096WT5M04A-aa1c520e04 | S24: X | T24: Har været i forløb før - uheldig oplevelse. Ønsker hjælp til at tabe 10+kg, mindset. Går 8 år tilbage on og off. Løber meget. Snacker. Ønsker mere balance i kosten og hjælp til styrketræning.
B25: 25.07.25 | C25: Camilla Ø. Christensen | E25: 30 28 20 39 | F25: camilla_oestergaard@hotmail.com | H25: Setter | I25: Offer & Didn't Buy | N25: Think About It | O25: Snakket med andre coaches | Q25: 5 måneder | R25: https://slack-files.com/T089JBRTVMM-F097HRZ36SG-3d8b6769d4 | S25: X | T25: Har brug for hjælp til at finde tilbage til rytmen. Tabe 8 kg. Støtte og en til at holde hende på rette vej
B26: 28.07.25 | C26: Joanna Sadiq | E26: 28 11 42 77 | F26: joannasadiq@gmail.com | H26: Setter | I26: Offer & Didn't Buy | N26: Fear | Q26: 4 måneder | R26: https://slack-files.com/T089JBRTVMM-F097R8V42R4-0b2c1429c3 | S26: X | T26: Hjælp til kostvaner - snacker meget. Har fundet et træningsprogram hun godt kan lide men er usikker på teknik (delte mavemuskler)
B27: 28.07.25 | C27: Tina Biltzing (ringet + skrevet) | E27: 24 61 58 98 | F27: tinabiltzing@hotmail.com | H27: Setter | I27: Split-pay | N27: Money | Q27: 5 måneder | R27: https://slack-files.com/T089JBRTVMM-F097R0NAJ6R-6c03255696 | S27: Closed | T27: Svært ved søvnrytme og prioritere tid til sig selv. Ønsker redskaber til at fastholde rutiner der passer ind i hendes hverdag som familiemor. Ønsker at tabe 20 kg og føle sig tilpas i sin krop.
B28: 28.07.25 | C28: Emilie Bojesen Harboe | E28: 42 77 13 32 | F28: emiliebojesenharboe@gmail.com | H28: Setter | I28: Offer & Didn't Buy | N28: Think About It | Q28: 4 måneder | R28: https://slack-files.com/T089JBRTVMM-F097R8T6WNA-3f8f89a3ed | S28: X | T28: Har fint styr på træningen, men ønsker hjælp til kosten og mere protein. Mæthed. Mere energi - finde en god struktur tabe 5 kg. Går 4 år tilbage. Overspiser op til sin cyklus.
B29: 30.07.25 | C29: Maiken Xia Engemand (forlænget) | E29: 60 48 80 41 | F29: maiken.engemand@gmail.com | H29: Setter | I29: Split-pay | K29: 7500 | L29: 1500 | N29: Money | Q29: 4 måneder | R29: https://slack-files.com/T089JBRTVMM-F0980EV9X0B-a088f9f3c9 | S29: Closed | T29: Brug for at tage 3 kg på. Har forhøjet stofskifte og har ikke kunne tage på de sidste 5 år. Har brug for balance i rutiner omkring kost og træning. Stress, søvn, angst, oppustet. Læge siger hun har en spiseforstyrrelse men det mener hun ikke selv hun har.
B30: 30.07.25 | C30: Nina Feddersen | E30: 28 18 90 56 | F30: ninafeddersen@yahoo.dk | H30: Setter | I30: Split-pay | K30: 9000 | L30: 1500 | N30: Money | Q30: 5 måneder | R30: https://slack-files.com/T089JBRTVMM-F0986P0EMKL-f55388be31 | S30: Closed | T30: Brug for ro omkring mad. Måske et vægttab på 5 kg hvis muligt men ikke målet. Struktur på sin træning. Holdbare vaner. Mindset omkring mad.

Sheet Aug
B1: Rep: | C1: Name | E1: Outcome | H1: KPIs% | K1: Show Rate | N1: Objections | Q1: Source | U1: Tracking
E2: Full-Pay: | F2: =IFERROR(COUNTIFS(I13:I287, "Full-Pay"),"") -> 3 | H2: Conversion Rate: | I2: =iferror(I10/I8,"") -> 0.54545455 | K2: Rescheduling Rate: | L2: =iferror(F8/I6,"") -> 0.043478261 | N2: Think About It | O2: =IFERROR(COUNTIFS(N13:N286, "think about it"),"") -> 2 | Q2: Reschedule | R2: =IFERROR(COUNTIF(H13:H286,Q2),"") -> 0 | S2: Cold Call | T2: =IFERROR(COUNTIF(H13:H286,S2),"") -> 0
B3: Revenue | C3: =IFERROR(SUM(K13:K283),"") -> 103500 | E3: Split-Pay: | F3: =IFERROR(COUNTIFS(I13:I287, "Split-Pay"),"") -> 9 | H3: Offer To Close Rate: | I3: =IFERROR(I10/I9,"") -> 0.54545455 | K3: Cancellation Rate: | L3: =iferror(F9/I6,"") -> 0 | N3: Money | O3: =IFERROR(COUNTIFS(N13:N286, "money"),"") -> 13 | Q3: YouTube | R3: =IFERROR(COUNTIF(H13:H286,Q3),"") -> 0 | S3: Twitter | T3: =IFERROR(COUNTIF(H13:H286,S3),"") -> 0
B4: Cash | C4: =IFERROR(SUM(L13:L284),"") -> 49500 | E4: Deposits: | F4: =IFERROR(COUNTIFS(I13:I287, "Deposit"),"") -> 0 | H4: Call To Offer Rate: | I4: =IFERROR(I9/I8,"") -> 1 | K4: No-Shows Rate: | L4: =iferror(F10/I6,"") -> 0 | N4: Time | O4: =IFERROR(COUNTIFS(N13:N286, "time"),"") -> 1 | Q4: YouTube Ads | R4: =IFERROR(COUNTIF(H13:H286,Q4),"") -> 0 | S4: Skool | T4: =IFERROR(COUNTIF(H13:H286,S4),"") -> 0
E5: Offer & Didn't Buy: | F5: =IFERROR(COUNTIFS(I13:I287, "Offer & Didn't Buy"),"") -> 10 | H5: Drag Over Rate: | I5: =IFERROR(F7/(C6+F7+F8),"") -> 0 | K5: Drag Over Rate: | L5: =iferror(F7/I6,"") -> 0 | N5: Partner | O5: =IFERROR(COUNTIFS(N13:N286, "partner"),"") -> 5 | Q5: Email | R5: =IFERROR(COUNTIF(H13:H286,Q5),"") -> 0 | S5: Instagram | T5: =IFERROR(COUNTIF(H13:H286,S5),"") -> 0
B6: Total Calls : | C6: =IFERROR(SUM(F2:F6),"") -> 22 | E6: Bad Fit & No Offer: | F6: =IFERROR(COUNTIFS(I13:I287, "Bad Fit & No Offer"),"") -> 0 | H6: Bookings: | I6: =IFERROR(SUM(F2:F10),"") -> 23 | K6: Show-Up Rate: | L6: =iferror(I7/I6,"") -> 0.95652174 | N6: Fear | O6: =IFERROR(COUNTIFS(N13:N286, "fear"),"") -> 2 | Q6: Facebook | R6: =IFERROR(COUNTIF(H13:H286,Q6),"") -> 0 | S6: TikTok | T6: =IFERROR(COUNTIF(H13:H286,S6),"") -> 0
B7: Total Won : | C7: =IFERROR(F2+F3,"") -> 12 | E7: Drag Over & Show: | F7: =IFERROR(COUNTIFS(I13:I287, "Drag Over & Show"),"") -> 0 | H7: Shows: | I7: =IFERROR(SUM(F2:F7),"") -> 22 | K7: Conducted Rate: | L7: =IFERROR(I8/I6,"") -> 0.95652174 | N7: Value | O7: =IFERROR(COUNTIFS(N14:N287, "value"),"") -> 0 | Q7: Facebook Ads | R7: =IFERROR(COUNTIF(H13:H286,Q7),"") -> 0 | S7: Google | T7: =IFERROR(COUNTIF(H13:H286,S7),"") -> 0
B8: Total Lost : | C8: =COUNTIF(I13:I286,"offer & didn't buy")+countif(I13:I286,"deposit")+countif(I13:I286,"bad fit & no offer") -> 10 | E8: Rescheduled: | F8: =IFERROR(COUNTIFS(I13:I287, "Rescheduled"),"") -> 1 | H8: Calls: | I8: =IFERROR(SUM(F2:F6),"") -> 22 | Q8: LinkedIn | R8: =IFERROR(COUNTIF(H13:H286,Q8),"") -> 0 | S8: Referral | T8: =IFERROR(COUNTIF(H13:H286,S8),"") -> 0
B9: Closing % : | C9: =iferror(SUM(C7/C6),"") -> 0.54545455 | E9: Cancelled: | F9: =IFERROR(COUNTIFS(I13:I287, "Cancelled"),"") -> 0 | H9: Offers: | I9: =IFERROR(sum(F2:F5),"") -> 22
B10: Rev per lead | C10: =C3/C6 -> 4704.5455 | E10: No-Show: | F10: =IFERROR(COUNTIFS(I13:I287, "No-Show"),"") -> 0 | H10: Deals | I10: =F2+F3 -> 12
B12: Date | C12: Name | E12: Phone No. | F12: Email | H12: Source | I12: Outcome | K12: Revenue | L12: Cash | N12: Objection | O12: Objection Notes | Q12: Length | R12: Recording Link | S12: Follow Up/Next Steps | T12: Call Summary
B13: 04.08.25 | C13: Tine Hauerslev (skrevet + ringet) | E13: 60 84 20 84 | F13: tine.hauerslev@hotmail.com | H13: Setter | I13: Full-Pay | K13: 9000 | L13: 9000 | Q13: 5 måneder | R13: https://slack-files.com/T089JBRTVMM-F098DN2HSGP-b0165539e8 | S13: Closed | T13: Har de sidste 4 år haft svært ved at finde tilbage efter en stresset periode. Har skiftet arbejde til et roligt miljø og ønsker nu at få både træningsrutine og kostvaner på plads. Har haft en spiseforstyrrelse hvor hun kontrollerer alt hun spiser. Har taget 10 kg. på - det er ikke målet i sig selv at tabe dem. Mere madro og forbinde til kroppens signaler igen.
B14: 05.08.25 | C14: Amalie Raunsbæk Hagedron | E14: 22 21 74 80 | F14: amalieraunsbk.hagedorn@hotmail.com | H14: Setter | I14: Split-pay | K14: 9000 | L14: 3000 | N14: Partner | Q14: 5 måneder | R14: https://slack-files.com/T089JBRTVMM-F0993JCB8G4-0b9f65fdc7 | S14: Closed | T14: Er konstant oppustet. Har været i forløb før hvor hun talte meget kalorier hvilket har givet hende et ubalanceret forhold til kost. Alt eller intet mentaltiet. Dårlig søvn. Hjemmetræningsprogram og balance i kosten. Mere energi og overskud.
B15: 05.08.25 | C15: Astrid Kudahl Lyngsø | E15: 81 10 03 95 | F15: askuly04@gmail.com | H15: Setter | I15: Offer & Didn't Buy | N15: Think About It | Q15: 3 måneder | R15: https://slack-files.com/T089JBRTVMM-F098Y8NCXDZ-6f8ae40844 | S15: X | T15: Snacker meget og har svært ved at finde en god balance i kosten. Har eksem og vil gerne spise efter det. Have mere energi og sund livsstil så hun kan præstere bedre. Spiller badminton 3 gange i ugen men ønsker muligvis hjemmetræningsprogram.
B16: 06.08.25 | C16: Line Sofie Pico | E16: 61 46 14 98 | F16: line_pico@hotmail.com | H16: Setter | I16: Split-pay | K16: 9000 | L16: 3000 | N16: Money | Q16: 5 måneder | R16: https://slack-files.com/T089JBRTVMM-F0991JF7DTQ-bd5e205964 | S16: Closed | T16: Line har kræft i livmoderen og er jævnligt sengelæggende 3-4 måneder af gangen pga. operationer. Har sin sidste operation 12.sep. Har tidligere været meget trænet og spise stadig sundt, men har nu meget væske og fedt i kroppen grundet sygdom. Vil gerne tilbage på sporet så hun kan føle sig som sig selv igen. Hjemmetræning og vægttab på 15 kg. Støtte til at holde gejsten oppe.
B17: 08.08.25 | C17: Sofie Madsen | E17: 53 35 44 04 | F17: svbmadsen@gmail.com | H17: Setter | I17: Full-Pay | K17: 9000 | L17: 9000 | N17: Money | Q17: 5 måneder | R17: https://slack-files.com/T089JBRTVMM-F099Q2HRZ36-b50ae346ed | S17: Closed | T17: Ønsker at føle sig tilpas i sin egen krop. Har svært ved at hendes kæreste rør hende nogle steder på kroppen fordi hun er usikker. Har prøvet at finde balance i kosten og træningen siden 8. klasse (er 21) Indre stemme fylder meget. Mindset. Har ikke knækket koden til hvad der fungerer for hende.
B18: 09.08.25 | C18: Mai Laub Nielsen | E18: 29 89 85 07 | F18: mainielsen4@gmail.com | H18: Setter | I18: Offer & Didn't Buy | N18: Partner | Q18: 5 måneder | R18: https://slack-files.com/T089JBRTVMM-F099ADUKLCX-cf9e0ade9f | S18: X | T18: Alt eller intet mentalitet. Balance i kosten. Svinger 5-10 kg. i vægt. Sundere forhold til mad så hun kan vende tilbage til sig selv. Motivation.
B19: 11.08.25 | C19: Merete Jacobsen | E19: 22 10 29 36 | F19: merete81@hotmail.com | H19: Setter | I19: Offer & Didn't Buy | N19: Money | O19: Har brug for tænketid og kigge på økonomi. Har sat et loft på 1000 kr. men vil kigge på om hun kan få det til at køre rundt. Snakket med hende om at følge op i januar | Q19: 4 måneder | R19: https://slack-files.com/T089JBRTVMM-F09ALFYT6PJ-88386d2205 | S19: Follow Up | T19: Merete er i andet forløb, men føler sig presset med den tilgang der bliver brugt og ønsker derfor at skifte forløb til noget mere balanceret. Hun har de sidste 8 måneder været ude af takt med de gode rutiner og ønsker at finde tilbage. VIl gerne have en mere tonet krop, vægttab på 5 kg, bedre søvn, balance i kosten. Har spillet fodbold på eliteplan og har en tendens til at overtærne og har derfor brug for stuktur, også på sine hvil så hun kan finde mere ro i hverdagen. Hendes tilstand stopper hende i flere ting som rejser, finde en kæreste og at søge nyt job. Løber
B20: 12.08.25 | C20: Alma Murguz | E20: 30 82 62 20 | F20: almamurguz@hotmail.com | H20: Setter | I20: Offer & Didn't Buy | N20: Money | O20: Forældre betaling | Q20: 5 måneder | R20: https://slack-files.com/T089JBRTVMM-F099UAX0E11-f28f8c81f5 | S20: X | T20: Ønsker at finde balance i kosten og finde en god træningsrutine. Tabe ca 5 kg fedt og få tonet krop. Mangler indblik og viden i forhold til kostsammensætning. Har for 1,5 år siden haft en forstyrret spisning med opkastninger. Varede 3-4 måneder og fik selv stoppet det. Ønsker hjemmetræning til en start. Det går 4-5 år tilbage.
B21: 13.08.25 | C21: Christina Kraul Møllegaard | E21: 28 71 83 89 | F21: christinamoe93@hotmail.com | H21: Setter | I21: Split-pay | K21: 7500 | L21: 1500 | N21: Money | O21: Ønsker 5 måneder men starter med 4 grundet økonomi | Q21: 4-5 måneder | R21: https://slack-files.com/T089JBRTVMM-F09A5REG4P7-98cf85d13a | S21: Closed | T21: Rejseleder og ønsker derfor et fleksibelt træningsprogram - hjemmetræning uden for mange redskaber og fitnesscenter (elsker at løfte tungt). Vægttab på 5 kg + mere muskelmasse. Føler sig ikke tilfreds med sin krop. Har fokus på at skifte mindset - kan ikke overholde aftaler med sig selv og laver altid undskyldninger for ikke at komme afsted. Oppustet, balance i kosten, overspisninger da hun kommer fra et hjem hvor man spiser op.
B22: 14.08.25 | C22: Siggi Løvstrøm | E22: 61 28 67 11 | F22: sikki-l@hotmail.com | H22: Setter | I22: Rescheduled | N22: Money | O22: Follow up dec. | Q22: 4 måneder | R22: https://slack-files.com/T089JBRTVMM-F09AFLY1WA2-7e028e4514 | S22: Follow Up | T22: ADD, misbrug af hash (går i behandling) ønsker først og fremmest at arbejde på sit mindset - taler hårdt til sig selv, dårlig selvværd - går 10 år tilbage. Træner og vil gerne leve sundt og stå skarpt. Tabe 5 kg. fedt.
B23: 15.08.25 | C23: Camilla B Andersen | E23: 26 29 24 62 | F23: milla0509@hotmail.com | H23: Setter | I23: Split-pay | K23: 9000 | L23: 3000 | N23: Money | O23: Dagpenge | Q23: 5 måneder | R23: https://slack-files.com/T08TMAAKCCU-F09AY42GCJD-c17940c484 | S23: Closed | T23: Camilla er i en meget presset situation - hendes x stalker hende, hun føler sig utryg og stresset. Ønsker at skabe de bedste forudsætninger for at stå imod de udfordringer hun har i livet. Hun siger selv hun er mester i at udsætte! Nu skal det være slut. Ønsker hjælp til træning - både hjemme og i centret. Mere rytme og balance i kosten. Er nysgerrig på mere viden. Går til psykolog. Har været stresset og deprimeret over flere omgange. Ønsker børn i fremtiden (er 33 år - evt første barn bliver doner da hun ikke har kæreste - tid) så vil derfor også gerne have en sund krop.
B24: 15.08.25 | C24: Emilie Spørring | E24: 42 16 16 63 | F24: emiliespoerring@icloud.com | H24: Setter | I24: Full-Pay | K24: 9000 | L24: 9000 | Q24: 5 måneder | R24: https://slack-files.com/T08TMAAKCCU-F09AP90NUCU-eae9d9d3a4 | S24: Closed | T24: Emilie har svært ved at finde ind i de sunde rutiner. For et år siden døde hendes veninde hvilket kastede hende ud af balance - hun tabte sig på en usund måde. Har de sidste 4-5 år været utilfreds med sin krop. Mangler kropsbevidsthed så hun kan mærke mæthed og sult. Ønsker at blive strammet op og få en tonet krop. Ked af sit mavefedt - ønsker at tabe 5-10 kg. Vil gerne etablere et godt balanceret for hold til mad.
B25: 15.08.25 | C25: Newros Secilmis (afsluttet før tid) | E25: 60 60 64 89 | F25: nevruzsecilmis@live.dk | H25: Setter | I25: Split-pay | K25: 9000 | L25: 1500 | N25: Money | O25: Prøvet mange forløb | Q25: 5 måneder | R25: https://slack-files.com/T08TMAAKCCU-F09AM6ERP4N-9cac8d5b5d | S25: Closed | T25: Newros har prøvet mange forskellige forløb. Meget berørt af hendes situation: Manglende overskud til træning, hopper over måltider og overspiser om aftenen. Har to børn og mangler energi. Ønsker at blive den bedste version af sig selv for sine børn og sig selv. Vægttab på 10 kg. men går mest op i at føle sig godt tilpas og finde rytmen og balancen. Ønsker hjemmetræning der passer til hendes manglende tid i hverdagen.
B26: 18.08.25 | C26: Astrid Lausten, skrevet | E26: 53 40 44 60 | F26: astrid.lausten@hotmail.com | H26: Setter | I26: Offer & Didn't Buy | N26: Time | O26: Flytning | Q26: 4 måneder | R26: https://slack-files.com/T08TMAAKCCU-F09AXS125QV-04c596a81f | S26: X | T26: Næsten i mål selv. Har tabt næsten 20 kg. selv. Mangler 5 kg. Hjælp til balance i kosten. Struktur. Har en skade efter en ulykke der gør det svært at træne. Har været elite badmintonspiller. Ønsker at bygge muskelmasse - hjemmetræning.
B27: 19.08.25 | C27: Luna Friis Hansen | E27: 21 30 65 97 | F27: lunafriishansen@gmail.com | H27: Setter | I27: Offer & Didn't Buy | N27: Money | O27: Stor gæld | Q27: 5 måneder | R27: https://slack-files.com/T08TMAAKCCU-F09B2HQ42KG-c8e863f986 | S27: X | T27: Ønsker at tabe 10 kg. Overspisning. Oppustet hele tiden. Kan ikke finde balancen i kosten og rytmen i træningen. Ikke motiveret. Vægten stiger hver gang. Har taget 20 kg. på de sidste 4 år. Gammel elitegymnast - savner at føle sig tilpas i sin krop.
B28: 20.08.25 | C28: Nancy Natalie | E28: 21 73 40 15 | F28: raufort95@gmail.com | H28: Setter | I28: Split-pay | K28: 9000 | L28: 3000 | N28: Money | Q28: 5 måneder | R28: https://slack-files.com/T08TMAAKCCU-F09B71EGSKU-7f825c1317 | S28: Closed | T28: Vejer 103 kg og er bange for at vægten fortsat stiger. Hun har kæmpet med dårlige vaner i 11 år og kan ikke komme ud af den onde cirkel. Ønsker en livsstilsændring så hun kan få det godt med sig selv og blive mere mobil. Har smerter og skader grundet overvægt. Mangler energi og overskud. Har svært ved at mærke mæthed.
B29: 21.08.26 | C29: Laura Kirstine Hunæus Kaas | E29: 24 43 20 30 | F29: laurakhkaas@gmail.com | H29: Setter | I29: Offer & Didn't Buy | N29: Fear | Q29: 5 måneder | R29: https://slack-files.com/T08TMAAKCCU-F09B14V23TR-5a9e4a6525 | S29: X | T29: Laura bliver ved med at tabe sig grundet sin ADHD medicin. Hun har kvalme hver dag, og kaster ufrivilligt op når hun spiser. Hun er bange for at blive taget af sin medicin da den har kæmpe betydning for hendes funktionsniveau. Hjælp til søvn, kost, hjemmetræning. Har stress som kan lede til depression (har lægen sagt). Mangler overskud og overblik.
B30: 22.08.25 | C30: Sarah Damkær | E30: 22 75 65 30 | F30: sarahdamkaerm@gmail.com | H30: Setter | I30: Split-pay | K30: 9000 | L30: 1500 | N30: Money | O30: Flytning | Q30: 5 måneder | R30: https://slack-files.com/T08TMAAKCCU-F09CDAQ0DEU-c959aaeb2d | S30: Closed | T30: Sarah ønsker at tabe 10 kg og få styr på træningen - både hjemmetræning og center. Hun ønsker at føle sig mere tilpas i sin krop og blive mere tonet. Hun vil gerne have styr på kosten og mangler vejledning omkring hvordan hun kan sammensætte den så hun får det hendes krop har brug for. IBS
B31: 26.08.25 | C31: Jessika Kristensen | E31: 28 10 11 51 | F31: jessika_844@hotmail.com | H31: Setter | I31: Offer & Didn't Buy | N31: Money | Q31: 4 måneder | R31: https://slack-files.com/T089JBRTVMM-F09D31BCR08-6a569007e3 | S31: X | T31: Skilsmisse og flytning. Ønsker at skabe sunde vaner for sig selv og sine tre børn. Hjemmetræning, strammet op, kostsammensætning. Vægttab 4 kg. Pædagog + børn - integreret.
B32: 27.08.25 | C32: Natasha Kjær | E32: 60 70 01 91 | F32: kjaernatasha@gmail.com | H32: Setter | I32: Offer & Didn't Buy | N32: Think About It | O32: Ikke Olivia som første kontakt | Q32: 5 måneder | R32: https://slack-files.com/T08TMAAKCCU-F09D3RQ2WMN-751c37dacd | S32: X | T32: Balance i kost og træning. Bankrådgiver, stillesiddende arbejde. Ønsker mere glæde og har haft svingende vægt i 4 år. Har en kæreste der støtter hende i at få det bedre med sig selv. Lændesmerter. Ønsker hjemmetræningsprogram. Vægttab på 4 kg. Ønsker mere overskud. Hjælp til kostsammensætning. Har haft kost-coach grundet overspising for 2,5 år siden + træningscoach. Ikke pleg for at investere i sig selv. Synes 9000 kr. lød super fair.
B33: 28.08.25 | C33: Pernille Mikkelsen | E33: 28 58 80 27 | F33: pernillebmikkelsen@hotmail.com | H33: Setter | I33: Split-pay | K33: 6000 | L33: 3000 | N33: Money | O33: Gravid - ønsker at forlænge løbende | Q33: 3 måneder | R33: https://slack-files.com/T08TMAAKCCU-F09C23ELAQ7-595e4071a1 | S33: Closed | T33: Pernille har brug for hjælp til at ændre sit mindset. Hun er meget negativ og brokker sig meget. Har intet overskud til sine børn og mand - kan hverken give eller modtage. (Sygeplejerske - sygemeldt som gravid i 4,5 måned) Har et lavt selvværd og mangler troen på sig selv og sin egen værdi. Vil gerne være den bedste mor hun kan være.
B34: 28.08.25 | C34: Rebecca Secher | E34: 53 35 62 61 | F34: rsecher@gmail.com | H34: Setter | I34: Split-pay | K34: 9000 | L34: 3000 | N34: Fear | O34: Bange for ikke at lykkes med resultater | Q34: 5 måneder (3 måneders binding) | R34: https://slack-files.com/T08TMAAKCCU-F09CHHXF19U-22f450545a | S34: Closed | T34: Dagligt oppustet. Vil gerne have hjælp til træning. Strammes op. Vægttab på 3 kg. Utilfreds med krop og mave. Tøj.Arbejder ved SAS og har en travl hverdag. Kæreste fylder meget grundet psyiske udfordringer. Hun har svært ved at prioritere sig selv, men ønsker nu at ændre på det. Svært at tage næste skridt -frygt
B35: 28.08.25 | C35: Melanie Martinussen | E35: 61 91 51 43 | F35: melaniemartinussen93@gmail.com | H35: Setter | I35: Offer & Didn't Buy | N35: Partner | O35: Ønsker graviditet + økonomi | Q35: 5 måneder | R35: https://slack-files.com/T08TMAAKCCU-F09C2SC0ZM5-283af0c01b | S35: X | T35: Glutenallergi - spisemønster og madro. Utilpas i krop. Mangler energi og overskud. Advokat med mange arbejdstimer. Vægttab - hofter+mave. Mere balance. Let træning - lidt betænkelig ved træning i forhold til tid og overskud. Har stået på i mange år!
B37: Vincens:
B38: 29.08.25 | C38: Emma Junker | E38: 22 32 84 20 | F38: emmajc2004@icloud.com | H38: Setter | N38: Partner | O38: Forældre
B39: 29.08.25 | C39: Sille Byrgesen | E39: 28 89 64 17 | F39: sillebyrgesen7@gmail.com | H39: Setter | N39: Partner | O39: Forældre - er i forløb i forvejen | Q39: 5 måneder | R39: https://slack-files.com/T08TMAAKCCU-F09CNS6CGDC-cfc8cef8a8 | S39: Follow Up

Sheet Sep
B1: Rep: | C1: Name | E1: Anton KPI's | H1: Outcome | K1: KPIs% | N1: Show Rate | Q1: Objections | T1: Source
E2: Rev per call | F2: =C3/C6 -> 3223.4043 | H2: Full-Pay: | I2: =IFERROR(COUNTIFS(I13:I287, "Full-Pay"),"") -> 2 | K2: Conversion Rate: | L2: =iferror(L10/L8,"") -> 0.36170213 | N2: Rescheduling Rate: | O2: =iferror(I8/L6,"") -> 0.025 | Q2: Think About It | R2: =IFERROR(COUNTIFS(N13:N286, "think about it"),"") -> 1 | T2: Reschedule | U2: =IFERROR(COUNTIF(H13:H286,T2),"") -> 0
B3: Revenue | C3: =IFERROR(SUM(K13:K283),"") -> 151500 | E3: Cash per call | F3: =C4/C6 -> 1117.0213 | H3: Split-Pay: | I3: =IFERROR(COUNTIFS(I13:I287, "Split-Pay"),"") -> 15 | K3: Offer To Close Rate: | L3: =IFERROR(L10/L9,"") -> 0.36170213 | N3: Cancellation Rate: | O3: =iferror(I9/L6,"") -> 0.3625 | Q3: Money | R3: =IFERROR(COUNTIFS(N13:N286, "money"),"") -> 27 | T3: YouTube | U3: =IFERROR(COUNTIF(H13:H286,T3),"") -> 0
B4: Cash | C4: =IFERROR(SUM(L13:L284),"") -> 52500 | E4: Cash upfront % | F4: =C4/C3*100 -> 34.653465 | H4: Deposits: | I4: =IFERROR(COUNTIFS(I13:I287, "Deposit"),"") -> 4 | K4: Call To Offer Rate: | L4: =IFERROR(L9/L8,"") -> 1 | N4: No-Shows Rate: | O4: =iferror(I10/L6,"") -> 0.025 | Q4: Time | R4: =IFERROR(COUNTIFS(N13:N286, "time"),"") -> 0 | T4: YouTube Ads | U4: =IFERROR(COUNTIF(H13:H286,T4),"") -> 0
E5: PIF % | F5: =I2/C7*100 -> 11.764706 | H5: Offer & Didn't Buy: | I5: =IFERROR(COUNTIFS(I13:I287, "Offer & Didn't Buy"),"") -> 26 | K5: Drag Over Rate: | L5: =IFERROR(I7/(C6+I7+I8),"") -> 0 | N5: Drag Over Rate: | O5: =iferror(I7/L6,"") -> 0 | Q5: Partner | R5: =IFERROR(COUNTIFS(N13:N286, "partner"),"") -> 1 | T5: Email | U5: =IFERROR(COUNTIF(H13:H286,T5),"") -> 0
B6: Total Calls : | C6: =IFERROR(SUM(I2:I6),"") -> 47 | E6: Average Binding | F6: =AVERAGE(Q13:Q104) -> 4.9375 | H6: Bad Fit & No Offer: | I6: =IFERROR(COUNTIFS(I13:I287, "Bad Fit & No Offer"),"") -> 0 | K6: Bookings: | L6: =IFERROR(SUM(I2:I10),"") -> 80 | N6: Show-Up Rate: | O6: =iferror(L7/L6,"") -> 0.5875 | Q6: Fear | R6: =IFERROR(COUNTIFS(N13:N286, "fear"),"") -> 6 | T6: Facebook | U6: =IFERROR(COUNTIF(H13:H286,T6),"") -> 0
B7: Total Won : | C7: =IFERROR(I2+I3,"") -> 17 | E7: Average deal | F7: =C3/C7 -> 8911.7647 | H7: Drag Over & Show: | I7: =IFERROR(COUNTIFS(I13:I287, "Drag Over & Show"),"") -> 0 | K7: Shows: | L7: =IFERROR(SUM(I2:I7),"") -> 47 | N7: Conducted Rate: | O7: =IFERROR(L8/L6,"") -> 0.5875 | Q7: Value | R7: =IFERROR(COUNTIFS(N14:N287, "value"),"") -> 1 | T7: Facebook Ads | U7: =IFERROR(COUNTIF(H13:H286,T7),"") -> 0
B8: Total Lost : | C8: =COUNTIF(I13:I286,"offer & didn't buy")+countif(I13:I286,"deposit")+countif(I13:I286,"bad fit & no offer") -> 30 | E8: Average cash | F8: =C4/C7 -> 3088.2353 | H8: Rescheduled: | I8: =IFERROR(COUNTIFS(I13:I287, "Rescheduled"),"") -> 2 | K8: Calls: | L8: =IFERROR(SUM(I2:I6),"") -> 47 | T8: LinkedIn | U8: =IFERROR(COUNTIF(H13:H286,T8),"") -> 0
B9: Closing % : | C9: =iferror(SUM(C7/C6),"") -> 0.36170213 | H9: Cancelled: | I9: =IFERROR(COUNTIFS(I13:I287, "Cancelled"),"") -> 29 | K9: Offers: | L9: =IFERROR(sum(I2:I5),"") -> 47
H10: No-Show: | I10: =IFERROR(COUNTIFS(I13:I287, "No-Show"),"") -> 2 | K10: Deals | L10: =I2+I3 -> 17
B12: Date | C12: Name | E12: Phone No. | F12: Ig name | H12: Source | I12: Outcome | K12: Revenue | L12: Cash | N12: Objection | O12: Objection Notes | Q12: Length | R12: Recording Link | S12: Follow Up/Next Steps | T12: Call Summary
B13: 02.09.25 R | C13: Emma Neuhausen | E13: 20 98 36 97 | H13: Setter | I13: Split-pay | K13: 9000 | L13: 3000 | N13: Money | Q13: 5 | R13: https://slack-files.com/T08TMAAKCCU-F09D72BA7GC-6c1b103813 | S13: Closed | T13: Emma har vejet 131 kg i 2022. Gik i forløb hos Türker. Har sat et mål om at stå på scenen i bikinifitness. Ønsker et vægttab på ca. 13. kg. Mere madro. Mere tonet. Mere røv. Smidig og styrke. Tilladelse til kald senere i forløb.
B14: 02.09.25 | C14: Rebekka Mikkelsen | E14: 30 14 01 21 | H14: Setter | I14: Full-Pay | K14: 7500 | L14: 7500 | Q14: 4 | R14: https://slack-files.com/T08TMAAKCCU-F09CYM6DLSX-5c296e81ff | S14: Closed | T14: Tabe 4 kg. Strammet op. Af og til oppustet. Ønsker rytme i kostvaner og træningsrutine der giver hende det sidste. Har været været ved coach før for 1,5 år siden men var ikke tilfreds med forløb. Mangler håndgribelige redskaber og struktur.
B15: 02.09.25 R | C15: Emilie Liccardi | E15: 61 60 50 62 | H15: Setter | I15: Split-pay | K15: 9000 | L15: 3000 | N15: Money | Q15: 5 | R15: https://slack-files.com/T08TMAAKCCU-F09D8MCR6FN-1700994994 | S15: Closed | T15: Har aldrig haft styr på kosten - har et anstrengt forhold til mad. Kan bedst lide flydende mad og straffer sig selv mentalt når hun spiser på forkerte tidspunkter. Snakkede ind i madro og at genfinde glæden ved mad igen. Har social-angst - går kun ture alene om aftenen når der ikke er mennesker. Mener det hænger sammen med hendes selvværd og udseende. NU skal det være slut. Hun vil have en sund krop og gode vaner for sig selv og hendes søn. Tilladelse til kald senere i forløb.
B16: 03.09.25 | C16: Isabella Fyrst | E16: 28 76 18 76 | H16: Setter | I16: Offer & Didn't Buy | N16: Money | O16: Flexjob | R16: https://slack-files.com/T08TMAAKCCU-F09DBFWRNMC-984f069ab0 | S16: X | T16: Vægttab på 6 kg. Strammet op lår og mave. Elsker at løbe. Måske hjælp til træningcentret. Har forsøgt at melde sig ind masser af gange men mister motivationen fordi hun ikke ser resultater. Har særligt brug for hjælp til kost hendes mand også kan lide. Mangler redskaber, vejledning og mere energi. God til at udsætte, men ønsker at handle på det.
B17: 03.09.25 | C17: Kübra Øzkaya | E17: 60 18 83 12 | F17: kubraozkaya@hotmail.com | H17: Setter | I17: Offer & Didn't Buy | N17: Money | O17: Måske til januar | R17: https://slack-files.com/T08TMAAKCCU-F09D6KSH4CB-1d60e09bc3 | S17: Follow Up | T17: Træning: Teknik, vejledning og inspiration. Kostbalance: protein og næring. Har aldrig rigtig fundet rytmen og balancen i kosten. Ønsker et vægttab på 5 kg. fedt og mere muskelmasse. Bange for at tage på. Lider af overspisning - mængder! Mangler energi, slår sig selv i hovedet, mangler redskaber. Utilfreds med krop - tilbage på rette spor. Mere madro og mindset. Mæthed.
B18: 05.09.25 R | C18: Camilla Rosendal | E18: 23 35 82 84 | F18: camillasurma@gmail.com | H18: Setter | I18: Full-Pay | K18: 9000 | L18: 9000 | Q18: 5 | R18: https://slack-files.com/T08TMAAKCCU-F09DPUFUYRY-5ce1c17bac | S18: Closed | T18: Mindset og mental sundhed er vigtigst for hende. Hun vejer over 100 kg. og har altid fået af vide fra sin mor at hun var for stor (første gang da hun var 14). Føler sig ikke tilpas i sin krop. Blodpropper i familien. Oppustet. Vægttab på 20 kg. +. Angst, tankemylder, uro i kroppen (strikker for at holde sig rolig). Sammenhængen mellem mindset og kost. Ønsker en holdbar livsstilsændring.
B19: 05.09.25 | C19: Winnie Albers | E19: 28 72 32 70 | F19: winniealbers@hotmail.com | H19: Setter | I19: Offer & Didn't Buy | N19: Money | O19: Penge, følg op i okt | Q19: 4 | R19: https://slack-files.com/T08TMAAKCCU-F09DUJ11ZRS-9df8b3080a | S19: X | T19: Har prøvet længe at nå helt i mål med den krop hun ønsker sig. Kæmper stadig med kost og personlig træner i fitnesscentret, men ser ikke de resultater hun ønsker sig. Hun vil gerne være et forbillede for sine 3 børn og føle sig godt tilpas med det hun ser i spejlet. Delte mavemuskler, tonet.
B20: 06.09.25 | C20: Laura Jensen | E20: 21 69 69 28 | F20: laurajen02@icloud.com | H20: Setter | I20: Split-pay | K20: 9000 | L20: 1500 | N20: Money | O20: SU | Q20: 5 | R20: https://slack-files.com/T08TMAAKCCU-F09ENKFAFG8-9e090499a5 | S20: Closed | T20: Har prøvet flere gange, men kan ikke nå i mål med de resultater hun ønsker sig. Har svært ved at sammensætte kosten så hun både bygger muskel og taber fedt. Mangler energi og overskud i hverdagen. Svært ved at finde rytmen i sine vaner så de holder. Realistiske vaner og struktur hun kan holde.
B21: 09.09.25 | C21: Louise Segerlund | E21: 21 71 95 72 | F21: louisesegerlund@newmail.dk | H21: Setter | I21: Offer & Didn't Buy | N21: Value | O21: Følte hun havde styr på det | R21: https://slack-files.com/T08TMAAKCCU-F09EPV1JQ0H-be24db5f72 | S21: X | T21: Havde ikke rigtig brug for hjælp men synes det lød spændende.
B22: 09.09.25 | C22: Wiktoria Malmvig | E22: 60 83 30 35 | F22: wikmdm@hotmail.com | H22: Setter | I22: Split-pay | K22: 9000 | L22: 1500 | N22: Partner | O22: Bange for hvad partner ville sige | Q22: 5 (Satte forløb på pause d. 21. okt. grundet graviditet) | R22: https://slack-files.com/T08TMAAKCCU-F09EAQYHP9C-343185256b | S22: Closed | T22: Vægttab 10 kg. Føler sig ikke tilpas og glad for sin krop. Mangler energi og dunker ofte sig selv i hovedet over hvorfor hun ikke bare kan få styr på det. Tænker konstant over hvordan andre ser hende og spejler sig i andre. PCOS. Nu er det nok! Skiftende arbejdstider som sygeplejerske. Datter på 2,5 år.
B23: 09.09.25 | C23: Jasmin Sahanli | E23: 27 51 30 93 | F23: jasminsahanli@hotmail.com | H23: Setter | I23: Rescheduled | N23: Money | O23: Ønsker at starte senere. Kald slut okt. | R23: https://slack-files.com/T08TMAAKCCU-F09EPVCUCJV-0d294b5581 | S23: Follow Up | T23: Vægttab 21 kg. Ønsker en rund bagdel. Har forsøgt i 6 år. VIl gerne løbe og have hjælp til hjemmetræning. Oplever ofte cravings og vil gerne have inspiration til kosten. Har været i en periode hvor hun mistede sig selv helt, og vil nu gerne genfinde sig selv og langt om længe se sig i spejlet og føle sig tilpas og glad for det hun ser. Søvn er dårlig grundet datter. Viden om sunde vaner. Selvværd og bedste version af sig selv.Har haft svær periode i parforhold grundet dette.
B24: 09.09.25 | C24: Nicoline | E24: 21 26 42 53 | F24: nicolinegrp@gmail.com | H24: Setter | I24: Offer & Didn't Buy | N24: Think About It | O24: Fint styr på det, men mere brug for hjælp end forventet | R24: https://slack-files.com/T08TMAAKCCU-F09EAP690R0-ef6b438e51 | S24: X | T24: Nicoline fandt ud af hun havde mere brug for hjælp end forventet gennem samtalen. Hun er ked af sine arme og vil gerne have strammet op. Frygt for at tage på igen. Har dårlig søvn fordi hun spiser snacks lige før sengetid. Mangler energi, vil gerne være gladere. Hendes forhold til træning og mad handler meget om hvordan hun ser ud! Hun vil gerne have vendt sit mindset til ikke at fokusere så meget på udseende, men mere på hvordan det føles.
B25: 09.09.25 | C25: Emilie Lasborg | E25: 24 21 53 07 | F25: emilielasborg1@live.dk | H25: Setter | I25: Split-pay | K25: 9000 | L25: 3000 | N25: Money | Q25: 5 | R25: https://slack-files.com/T08TMAAKCCU-F09EEP9HWMA-0429f422df | S25: Closed | T25: Var i forløb i 2021 men måtte afbryde grundet corona-lunger. Selvbillede, føler sig ikke tiltrækkende over for sin kæreste. Ønsker hjemmetræning til en start. Måske en træning i center på sigt. Er meget træt til hverdag. Har et meget nedladende syn på sig selv. Dårlige tanker fylder enormt meget. Tager ansvaret på sig - sin egen forandring Ikke lægge over på familiemedlemmer og har brug for coach for at have sin egen proces. Kæreste træner ofte. Ændre adfærd
B26: 10.09.25 | C26: Line Klint | E26: 42 83 85 32 | F26: linethklint@gmail.com | H26: Setter | I26: Offer & Didn't Buy | N26: Fear | O26: Lagde på ved betaling | R26: https://slack-files.com/T08TMAAKCCU-F09E1V5LDGF-c3e7b43242 | T26: Vejer 100 kg. Vægttab på 20 kg. Vil gerne i fertilitetbehandling, men vejer for meget så det er sat på pause. Sidder fast - har gjort siden januar. Sygemeldt med ryg fra hjemmeplejen. Hjælp til at finde ud af hvad der er galt og hvorfor hun ikke taber sig. Siger selv hun lever af skyr og faster hver dag....
B27: 10.09.25 | C27: Amalie Mikkelsen | E27: 24 40 21 72 | F27: a.mikkelsen2000@gmail.com | H27: Setter | I27: Offer & Didn't Buy | O27: Afklaring med behandler. Opfølgning 1. okt + følger op igen i marts | R27: https://slack-files.com/T08TMAAKCCU-F09EE833ME1-6c68176dfc | S27: Follow Up | T27: Har vaccineinduceret myalgisk encephalomyelitis som gør hende kronisk træt og har inflamation i kroppen og hjernen. Har brug for meget fleksibilitet i forhold til sin sygdom. 5%bliver raske. Vil gerne være mere selvstændig/selvhjulpen (bro hus forældre) i forhold til kost - nemt og overskuelig mad. Ønsker ikke træningsprogram, men mere kigge ind i hvad der er muligt af let bevægelse de dage hun kan.
B28: 10.09.25 | C28: Freja Lohmann | E28: 93931125 | F28: freja.my@lohmannstrobel.dk | H28: Setter | I28: Split-pay | K28: 9000 | L28: 3000 | N28: Money | O28: Nervøs for om det er scam | Q28: 5 | R28: https://slack-files.com/T08TMAAKCCU-F09EJGRHM1C-46f6386ee3 | S28: Closed | T28: Vægttab på 10 kg. Gammel håndboldspiller. Snacker mega meget, overspiser, store portioner, søde sager. Svært ved at mærke efter. Stået på i 5 år. Tøj, usikker, stille. Mangler redskaber og har motivationen. Er lost når det kommer til træning og hvad der virker/hvordan man gør. Har medlemsskbet.
B29: 11.09.25 | C29: Sofie Sabina Kock | E29: 50 41 08 09 | F29: sofiesabina@gmail.com | H29: Setter | I29: Split-pay | K29: 9000 | L29: 3000 | Q29: 5 | R29: https://slack-files.com/T08TMAAKCCU-F09EPRDR8TU-7d9657e17f | S29: Closed | T29: Sofie kan ikke tage på (vejer 43 kg. og vil gerne tage 8 kg. på) Hun føler hun spise meget, og har været på et hav af fedekure. Hun kan godt lide mad, men føler mad bliver en uoverskuelig opgave fordi hun mangler inspiration og ikke ved hvordan hun skal sammensætte den. Ønsker hjælp til hjemmetræningsprogram. Bor med sin kæreste som gerne vil tabe sig og "være med" i de nye madvaner. Hun har altid fået mange kommentarer på sit udseende og med alderen er hun blevet mere ligeglad men det påvirker hendes selvsikkerhed. Ønsker at komme igang med løb. INGEN proteinpulver.
B30: 11.09.25 | C30: Larua Berthelsen | E30: 42 60 00 98 | H30: Setter | I30: Offer & Didn't Buy | N30: Fear | O30: Frygt, penge, tvivl - starter til psykolog næste uge. Opfølgning slut oktober | R30: https://slack-files.com/T08TMAAKCCU-F09ENE2N8TV-90ae986409 | S30: Follow Up | T30: Træning og kost fylder alt for meget. Kan ikke sidde stille for dårlig samvittighed. Ønsker mere mental ro omkring sine vaner. Svært ved at bede om hjælp. Er bange for det ender med en spiseforstyrrelse hvis det fortsætter meget længere. Påvirker hendes venskaber - blevet introvært. Føler sig oppustet konstant - har været ved lægen, men ingen hjælp at hente.
B31: 13.09.25 | C31: Freja Abrahamsen | E31: 26 17 94 00 | F31: mille-3000@hotmail.com | H31: Setter | I31: Offer & Didn't Buy | N31: Money | O31: Ikke vendt tilbage på aftale | Q31: 5 | R31: https://slack-files.com/T08TMAAKCCU-F09G30UQVHN-e3cdcb48a3 | S31: X | T31: Forsvandt og meldte ikke tilbage. Ellers meget varm på kaldet og ville bare igang! Har tabt 11 kg selv men vægten har stået stille 2 måneder. Stress og søvn. Tidligere elitefodboldspiller. Knæoperation for 2,5 måneder siden. Ønsker at tabe 10 kg. mere. Balance i kosten + træningen - vil gerne resette det hele og finde ud af hvad der fungerer godt for hendes krop det sted hun er nu. Mere balance i rutiner. Muskelmasse. Har haft yoyo-vægt hele sit liv - har ikke knækket koden. Mere ro på, mere selvtillid, sundhedsperspektiv, mindset. Siger hun er stædig.
B32: 13.09.25 | C32: Stine Vondran | E32: 61 72 18 19 | F32: stine.v.kristensen@live.dk | H32: Setter | I32: Offer & Didn't Buy | N32: Money | O32: SU | R32: https://slack-files.com/T08TMAAKCCU-F09FEQ0TWJY-f3c7cf90b3 | S32: X | T32: Stine vil gerne være mere tonet - vægttab på 5 kg. styrketræner 3 gange i ugen + løb. Er i tvivl om kosten og kunne godt tænke sig at sætte nogle klare mål for sig selv. Døjer meget med oppustethed. Glæder, tilpas i krop, energi, sundhedsaspekt - mangler vejledning og redskaber. har haft en spiseforstyrrelse for 5 år siden og ønsker nu at finde balancen. holdbare vaner der kan blive til livsstil
B33: 15.09.25 | C33: Maria Bejerholm | E33: 60 21 56 48 | F33: maria.bejerholm2602@gmail.com | H33: Setter | I33: Split-pay | K33: 9000 | L33: 3000 | Q33: 5 | R33: https://slack-files.com/T08TMAAKCCU-F09FQ797W9X-f99cfb8803 | S33: Closed | T33: Kører i spiral og har prøvet at få styr på både kostvaner og motivation for træning længe. Hun ønsker at få støtte til at lægge en plan så hun kan finde rytmen i hendes holdtræning, og få helt styr på kosten - særligt mængder er svære for hende. Struktur, ugeplaner, motivation, 20 kg. vægttab. Går 4 år tilbage. Vil gerne være mere glad og tilpas i sin krop - livsglæder, udstråling!
B34: 15.09.25 | C34: Josephine Holst | E34: 50 40 11 64 | F34: josseholst95@gmail.com | H34: Setter | I34: Offer & Didn't Buy | N34: Money | O34: SU + partner + tænke over det | R34: https://slack-files.com/T08TMAAKCCU-F09F6F9U259-7b0bc3d1b0 | S34: X | T34: Vendte aldrig tilbage på follow up. Josephine er meget aktiv: badminthon, styrketræner, reformer har altid trænet meget og været elite badminthonspiller. 24 år. Ønsker sig inspiration og balance i kosten - hvordan kan hun sammensætte maden så de fungerer for hende (har været i mange forløb før, hvor hun synes det var dårligt sammensat mad som virkede urealistsike og upersonlige). Krop har ændret sig - vil gerne føle sig godt tilpas med det hun ser i spejlet. Mere sund og stærk. Har aldrig rigtig fået knækket koden. Vil gerne finde balancen så hun kan performe bedre.
B35: 16.09.25 | C35: Isabella Pallisgaard | E35: 53 21 26 62 | F35: isabellapallisgaard@hotmail.com | H35: Setter | I35: Offer & Didn't Buy | N35: Money | O35: SU | R35: https://slack-files.com/T08TMAAKCCU-F09FM9KF39S-e37e4565e5 | S35: X | T35: Døjer med overspisninger og underspisninger. Kan ikke finde balacen i kosten så hun føler sig mæt. Vil gerne tabe sig 10 kg. Hjemmetræning, løb. Kost: næring, mængder, rytme - mere madro. Kost fylder enormt meget i hendes bevidsthed hver dag. Alt eller intet mentalitet.
B36: 16.09.25 | C36: Caroline Kristiansen | E36: 30 14 58 34 | F36: caroline.kristiansen15@gmail.com | H36: Setter | I36: Offer & Didn't Buy | N36: Fear | O36: Opfølgning d. 16. okt. Bange for at bryde med gammelt mønster. | Q36: 5 | R36: https://slack-files.com/T08TMAAKCCU-F09FKU35L68-d9196e3997 | S36: X | T36: Træning - form,muskelmasse. Fedttab: 5-10 kg. Hjemmetræning, løb. Ønsker hjælp til at motivere til at holde fast i træningen. Landmand. Spiser meget lidt nogle dage for at "straffe" sig selv fordi hun føler sig utilpas og for stor. Havde en spiseforstyrrelse i 7 klasse hvor hun stoppede med at spise. Sidder stadig i hende. Føler sig konstant træt hvilket har inflydelse på hendes overskud og sociale liv.
B37: 17.09.25 | C37: Calina Jensen | E37: 50 57 07 02 | F37: calina.jensen@outlook.com | H37: Setter | I37: Offer & Didn't Buy | N37: Money | O37: Har lavet follow up. SU + Value - har opsparing. FU om en måned | Q37: 5 | R37: https://slack-files.com/T08TMAAKCCU-F09FT4G9P5J-40da8faef2 | S37: X | T37: Hælspore/betændelse i svangsenen: træning med forbehold. Har været i forløb hos Türker for 1,5 år siden. Nåede i mål, men ikke holdbare resultater. Nævnte mindset mindst 30 gange på kaldet! Vigtigt for hende da hun føler det er den holdbare løsning for hende. Vaner og gode valg. Vægttab på 10-12 kg. Meget aktiv person. Har meget sukkertrang og ønsker inspiration til whole foods, bedre mad og mere inspiration - forhold til kost skal forbedres. Kropsbevidsthed - firbindelse til mæthed. Ser ikke resultater selv om hun er aktiv. Føler sig ikke tilpas i sin krop. Føler op om en måned og ser hvor hun er.
B38: 17.09.25 | C38: Cecilia Åstrand | E38: 30 86 10 05 | F38: ceciliaaastrand@gmail.com | H38: Setter | I38: Split-pay | K38: 9000 | L38: 1500 | N38: Money | O38: SU | Q38: 5 | R38: https://slack-files.com/T08TMAAKCCU-F09FL1XKYMT-14eac54cb8 | S38: Closed | T38: Prøvet forløb før for et år siden. Vægttab 8 kg. Kost: inspiration, ikke tælle og veje, glæde ved maden - det skal være nemt, og ikke tage for lang tid. Sidder på udvekling i Rom og har en veninde der træner meget - træner med hende men vil gerne have et skræddersyet program til fitnesscentret. Måske hjælp til løb. Sidder fast i en spiral og har ikke fundet ud af hvad der fungerer godt for hende endnu. Banker sig selv i hovedet over det ikke fungerer for hende og at hun ikke kan selv. Mere ro og glæde og færre bekymringer. Ubalance i kosten går 3 år tilbage. Har prøvet Keto, apps og meget andet. Ønsker at finde sin egen vej.
B39: 17.09.25 | C39: Sofie Rohde | E39: 52 58 13 09 | F39: sofierohdedanielsen@gmail.com | H39: Setter | I39: Offer & Didn't Buy | N39: Fear | O39: Penge, logistik, tankemylder, fear | Q39: 5 | R39: https://slack-files.com/T08TMAAKCCU-F09G2T36917-787353a527 | S39: X | T39: Follow op på mandag. Mangler mest af alt struktur over sin kost og træning - passe ind i hendes travle hverdag med to jobs. Vigtigt for hende at have en sund krop og få styr på de gode vaner før hun flytter hjemmefra. Har stået på i 4 år. Koble mindset og kost - har tendens til oppustethed og svært ved at styre sin trang med arbejde i en isbutik. Fedttab på 7 kg. Har meget tankemylder omkring hvordan hun kan løse det og finde gode vaner så hun kan føle sig godt tilpas i krop. Vejledning og hvordan hun får sig selv afsted, selv på de svære dage hvor motivationen er lav. Langt kald! Ville gerne
B40: 17.09.25 | C40: Emilie Bjerre | E40: 40 98 06 69 | F40: ebnulstrup00@gmail.com | H40: Setter | I40: Split-pay | K40: 9000 | L40: 1500 | O40: (Pause fra forløb start nov grundet økonomi - ønsker at vende tilbage) | Q40: 5 | R40: https://slack-files.com/T08TMAAKCCU-F09FKN03NTD-817f667f76 | S40: Closed | T40: Emilie har for 4 år siden mistet sin bedste veninde (venindes far myrede hele familien) og hendes bedstefar døde. Hun er lige nu sygemeldt fra sit arbejde som pædagog pga. psykisk pres fra en kollega, uden hendes leders opbakning. Emilie har ikke passet godt på sig selv de sidste 4 år. Har overspist og snacker sig igennem hele dagen (har tabt 14 kg. selv) ønsker et vægttab på 15 kg. Gider ikke i fitnesscenter men måske på sigt når hun bliver tryg da hendes svigermor gerne vil have hende med. Vil gerne have en mindre numse og flad mave. Elsker at lave mad. Har en kjole i skabet hun købte for 5 år siden som hun gerne vil ned i. Vi har aftalt jeg ringer til hende om nogle måneder for at høre hvor tæt vi er på målet.
B41: 18.09.25 | C41: Frederikke Aagaard | E41: 20 26 26 10 | F41: freder1002@hotmail.com | H41: Setter | I41: Offer & Didn't Buy | N41: Fear | O41: Og value (har været i flere forløb) | R41: https://slack-files.com/T08TMAAKCCU-F09FGJHP0DD-f9873ff3e8 | S41: X | T41: Har været i vægttabsforløb (3 år siden) + coachingforløb omkring mindset og kost (6 måneder siden). Har et anstrengt forhold til mad. Over- og underspiser. Hyperfokuseret på mad. Bange for fedt. Ønsker at finde madro da det fylder meget mentalt. Har en mor der har lidt af spiseforstyrrelse. Ønsker et godt forhold til sin krop. Er bange for at "falde tilbage" til gamle krop hvor hun tager på grundet overspisning. Sidder fast men tror på hun selv kan komme i mål. Var i tvivl om forløbet da hun har investeret mange penge i det førhen uden det har hjulpet, og har fået mange redskaber som hun tror hun kan bruge fremadrettet.
B42: 18.09.25 | C42: Katrine Larsen | E42: 21 30 03 89 | F42: katrinelarsen22@gmail.com | H42: Setter | I42: Offer & Didn't Buy | R42: https://slack-files.com/T08TMAAKCCU-F09FV01QF9B-2237f9ae57 | S42: X | T42: Vejer over 100 kg. Vil gerne ned på 77 kg. igen. Har prøvet fitness, svømning og ændring af kostvaner, men kan ikke nå i mål og bryde dårlige vaner. Spiser mange burgere og store mængder mad. Hun føler sig træt på daglig basis og vægten går ud over hendes selvværd. Vil gerne både have hjemmetræningsprogram + træningscenter. Har været på sygehuset og få taget prøver som viser dårlige resultater! Livsnødvendig forandring. Vægtøgning har stået på i 7 år. Vil gerne i bikini og kjole igen. Har en drøm om engang at blive fotomodel.
B43: 18.09.25 | C43: Victoria Dommer | E43: 42 22 58 56 | F43: viktoriadommer1@gmail.com | H43: Setter | I43: Offer & Didn't Buy | N43: Money | O43: Vi snakkede økonomi og madbudget | R43: https://slack-files.com/T08TMAAKCCU-F09GQHBFTH6-aa116b4e7a | S43: X | T43: Gammel eliteatlet. Ønsker struktur og hjemmetrænignsprogram hun kan følge for at bygge muskelmasse og blive stærkere. Går på CBS og sidder meget ned. Savner sin gamle stærke krop. Overvejede hjælp til kost da hendes mor er kostvejleder, men endte med at synes det gav mening at kigge på det hele billede - finde balance i kosten og træningen så hun kan bygge styrke. Mad hopper hun ofte over. Det skal være nemt, billigt og ikke tage lang tid! Mere næring og protein. Vigtigt for hende at være sund og stærk. Har smerter i ryggen - tænker træning kan hjælpe, men hver gang hun selv har trænet har det givet smerter.
B44: 22.09.25 | C44: Petra Sigvør | E44: 22 86 76 36 | F44: petrahoydal@outlook.dk | H44: Setter | I44: Split-pay | K44: 9000 | L44: 3000 | Q44: 5 | R44: https://slack-files.com/T08TMAAKCCU-F09GWNHDRFB-99167e4506 | S44: Closed | T44: Elite-fodboldspiller, bor i Italien. Lige færdiggjort gym og er nu klar til at give den fuld gas. Har brug for hjælp til at finde struktur og rytme i sin spisning. Hopper ofte over måltider fordi hun ikke ved hvad hun skal lave. Det skal være simpelt så hun holder fast i det. Hun føler ikke hun kan bygge muskelmasse i forhold til hendes andre holdkammerter. Hun føler det står stille og har gjort det noget tid nu. Hun føler hun er inde i en dårlig spiral og får ofte dårlig samvittighed over ikke at spise det hendes krop har behov for. Struktur, energi, performe maksimalt, muskelopbygning.
B45: 22.09.25 | C45: Janni Lykke | E45: 60 57 82 82 | F45: jannilykkestenderup@gmail.com | H45: Setter | I45: Offer & Didn't Buy | N45: Money | O45: Forældre, | Q45: 5 | R45: https://slack-files.com/T08TMAAKCCU-F09GHT3JP54-8e6dd8addd | S45: Follow Up | T45: Spiseforstyrrelse: Overspisning. Har været ved lægen, men kunne ikke få hjælp. Overvejer også psykolog men kan se fordelen ved at få Olivias hjælp på daglig basis. Har tabt sig og taget på mange gange. Det fylder hele Jannis liv og bevidsthed at have fokus på mad og føler sig meget hæmmet af det. Har meget andet hun ønsker at bruge energi på (spiller musik, ønsker at være model og influencer). Hun sidder fast og kan ikke se sig ud af det på egen hånd. Føler hun spilder sit liv.
B47: 02.09.25 | C47: Isabella | E47: 28 76 18 76 | F47: fyrstenborg79@icloud.com | H47: Setter | I47: Cancelled
B48: 02.09.25 | C48: Chikondi | E48: 29 92 55 30 | H48: Setter | I48: Cancelled
B49: 03.09.25 | C49: Caroline | E49: 20 70 96 13 | H49: Setter | I49: Cancelled
B50: 03.09.25 | C50: Kathrine | E50: 22 66 46 84 | H50: Setter | I50: Cancelled
B51: 05.09.25 | C51: Maria | E51: 31 56 81 03 | H51: Setter | I51: Cancelled
B52: 08.09.25 | C52: Eliana Seferides | E52: 71 54 05 58 | H52: Setter | I52: Cancelled
B53: 08.09.25 | C53: Therese | E53: 93 93 26 44 | H53: Setter | I53: Cancelled
B54: 10.09.25 | C54: Amalie Mikkelsen | E54: 24 40 21 72 | F54: a.mikkelsen2000@gmail.com | H54: Setter | I54: Cancelled
B55: 10.09.25 | C55: Therese | E55: 30 20 49 35 | F55: nikki-emira@hotmail.com | H55: Setter | I55: Cancelled
B56: 11.09.25 | C56: Camilla Kold | E56: 28 86 98 93 | F56: camilla.kold@hotmail.com | H56: Setter | I56: Cancelled
B57: 11.09.25 | C57: Sara Petersen | E57: 52 99 35 45 | F57: sarapetersen917@gmail.com | H57: Setter | I57: Cancelled
B58: 11.09.25 | C58: Annika | E58: 22 19 11 25 | F58: annikahs4131@gmail.com | H58: Setter | I58: Cancelled
B59: 12.09.25 | C59: Maria Lindebro | E59: 26 70 10 77 | F59: frk.lindebro@gmail.com | H59: Setter | I59: Cancelled
B60: 12.09.25 | C60: Stine Vorndran Kristensen | E60: 61 72 18 19 | H60: Setter | I60: Cancelled
B61: 13.09.25 | C61: Caroline Steenfeldt | E61: 42 20 52 46 | F61: steenfeldtcaroline@gmail.com | H61: Setter | I61: Cancelled
B62: 13.09.25 | C62: Josefine Holst | E62: 50 40 11 64 | F62: josseholst95@gmail.com | H62: Setter | I62: Cancelled
B63: 15.09.25 | C63: Stine Vorndran Kristensen | H63: Setter | I63: Cancelled
B64: 16.09.25 | C64: Huda | E64: 28 44 74 20 | H64: Setter | I64: Cancelled
B65: 16.09.25 | C65: Maria Andersen | E65: 31 58 51 05 | F65: maria.andersen96@hotmail.com | H65: Setter | I65: Cancelled
B66: 19.09.25 | C66: Isabella | E66: 52 30 25 02 | F66: pilegaardisabella@gmail.com | H66: Setter | I66: Cancelled
B67: 19.09.25 | C67: Petra Sigvør | E67: 22 86 76 36 | F67: petrahoydal@outlook.dk | H67: Setter | I67: Cancelled
B68: 19.09.25 | C68: Clara | E68: 53 62 06 36 | F68: claraporsdal@hotmail.com | H68: Setter | I68: Cancelled
B69: 20.09.25 | C69: Michala Koesgaard | E69: 31 39 24 60 | F69: michalakoesgaard@yahoo.dk | H69: Setter | I69: Cancelled
B70: 21.09.25 | C70: Liva Foresberg | E70: 60 52 08 66 | F70: livaforsberg2012@gmail.com | H70: Setter | I70: Cancelled
B71: 21.09.25 | C71: Katrine Cecilie | E71: 81 61 76 86 | F71: sindahl0512@live.dk | H71: Setter | I71: Cancelled
B72: 22.09.25 | C72: Shima Riesvand | E72: 51 92 03 52 | F72: shimariesvand@outlook.dk | H72: Setter | I72: Cancelled
B73: 23.09.25 | C73: Julie Dyhrenberg | F73: juliedyhrberg123@gmail.com | H73: Setter | I73: Cancelled
B74: 24.09.25 | C74: Camilla Rosenbjerg | E74: 21 60 58 59 | F74: camillakobberholm@icloud.com | H74: Setter | I74: Cancelled
B76: 24.09.25 | C76: Amalie Elnegaard | E76: 42 32 92 67 | F76: malle-1998@live.dk | H76: Setter | I76: Offer & Didn't Buy | N76: Money | O76: Og fear | Q76: 5 | R76: https://slack-files.com/T08TMAAKCCU-F09GVFSR3UM-30cd82a97b | S76: X | T76: Træning - mere viden, tryghed, teknik. 27 år, økonomistyring. Kost: peotein, balance, viden, nemt! Har dårlig samvittighed over hun ikke når i mål med de sunde vaner. Tonet krop, selvtillid, sundhedsperspektiv fremadrettet, prioritet nu. Muskelmasse - øge sin vægt. Kan ikke finde ud af hvordan hun kan skabe vaner der holder. Har prøvet af flere omgange. Ingen resultater.
B77: 25.09.25 | C77: Helene Andersen | E77: 27 52 72 72 | F77: heleneandersen89@hotmail.com | H77: Setter | I77: Split-pay | K77: 9000 | L77: 3000 | O77: Lidt fear for at bryde gammelt mønster | Q77: 5 | R77: https://slack-files.com/T08TMAAKCCU-F09HFPE1FTK-35238c4631 | S77: Closed | T77: Brug for hjælp til at finde balacen i kosten. Har haft udfordringer med mad i mange år! Døjer med oppustethed som tager meget af hendes energi. Har sat sig for at lave en halv ironman til næste år, og vil gerne passe bedre på sin krop så hun gennemfører på en god måde. Mangler inspiration til mad hun kan lave med sine børn. Oplever svimmelhed og har lavt blodtryk. Mega klar på at der skal ske noget nu, langt om længe!
B78: 25.09.25 | C78: Simone Hansen | E78: 52 25 41 14 | F78: simonejj2304@gmail.com | H78: Setter | I78: Rescheduled | Q78: 5
B79: 25.08.25 | C79: Olivia Riis | F79: oliviariisbh@gmail.com | H79: Setter | I79: Split-pay | K79: 9000 | L79: 3000 | Q79: 5 | R79: https://slack-files.com/T08TMAAKCCU-F09HY01U472-142ba01ea0 | S79: Closed | T79: Har svært ved at nå i mål. Mangler redskaber og ser ingen resultater selv om hun går i fitness 5-6 gange i ugen. Hun ved ikke altid hvad hun skal lave og om hun gør det rigtigt. Brug for hjælp til kost - kommer til at overspise om aftenen og føler sig ofte træt. Hun har brugt 4 år på at være enomt usikker og ønsker noget skal ændre sig nu - både for sig selv men også for at være et forbillede for andre og en bedre ven. Har brug for rammer og støtte til at finde rytmen i de gode vaner så hun kan blive den bedste version af sig selv. Er meget interesseret i at arbejde med det mentale da hun har meget tankemylder, usikkerhed på sin krop og sig selv, svært ved at sætte grænser. Lille vægttab på 5 kg. (vejer sig ikke da de har spiseforstyrrelse i familien) + muskelmasse. Stærk krop.
B80: 26.09.25 | C80: Kristina Schneider | E80: 28 11 76 27 | F80: schneider1603@hotmail.com | H80: Setter | I80: Offer & Didn't Buy | N80: Money | O80: Kæbe og tandlægeregning | Q80: 5 | R80: https://slack-files.com/T08TMAAKCCU-F09HPLXPBNV-c260fbef83 | S80: X | T80: Kost: Har ændret kostvaner de sidste 4 måneder, men er meget i tvivl om det hun gør er godt/sundt. Ønsker mere madro, overblik over sund, nem kost. Skidt kostrytme i weekenderne. Får ikke spist hele dagen og overspiser om aftenen. Rytme. Mor til 3 + kæreste. Har flere sygdomme - lever og tarmsygdom. Lige blevet opereret i kæben og har derfor været sengelæggende længe og tabt muskelmasse. Hun ønsker at se mere tonet ud og alt hendes fedt sætter sig på maven - ønsker sig en talje og de rette værktøjer til at se resultater. Vil gerne have et hjemmetræningsprogram og hjælp til centret. Vil gerne være den bedste udgave af sig selv for sine børn, kæreste, venner. Styrke. Badetøj. vægttab: 3 kg. fedt. Mere mental ro.
B81: 26.09.25 | C81: Terese Christensen | E81: 30 20 49 35 | F81: nikki-emira@hotmail.com | H81: Setter | I81: Deposit | N81: Money | O81: Opstart + betaling d. 1. okt (3000 kr) | Q81: 5 | R81: https://slack-files.com/T08TMAAKCCU-F09HA4XQUKY-5d9a05607f | S81: Closed | T81: Har været psykisk presset forhold gennem længere tid. Lige kommet ud af det for en uge siden og ønsker en ny begyndelse for hende og hendes to børn. Hun har ikke har overskud til at prioritere sig selv før nu, men nu er der momentum! Hun ønsker at få helt styr på kosten: har fået fjernet sin milt/andet organ tæt på maven - som giver hende smerter efter særlige madvarer - fx mælk tror hun. Ønsker at finde ud af hvad hun kan tåle og ikke kan tåle. Meget optaget af Olivias tag på mindset og mental velvære. Hun vil gerne være mere positiv og føle sig god nok og mere ro i sig selv. Nu er det tid. Har stået på i 5 år. Gode vaner for fremtiden - også for børn.
B82: 26.09.25 | C82: Nikkie | E82: 50 14 50 58 | F82: nikkiemelina@gmail.com | H82: Setter | I82: No-Show
B83: 26.09.25 | C83: Simone Hansen | E83: 52 25 41 14 | F83: simonejj2304@gmail.com | H83: Setter | I83: Deposit | O83: Kort spærret - venter på nyt (max 8 dage) | Q83: 5 | R83: https://slack-files.com/T08TMAAKCCU-F09HRE4RVR7-988b42bb4f | S83: Closed | T83: Brug for hjælp til struktur på både kost og træning! Har følt sig usikker på sin krop i mange år (har en mor der har gået i et forløb som har fåe tflotte resultater) Har flere jobs så har brug for at finde en balaceneret kost der giver hende mere energi og mealpreppe så det bliver lettere for hende at få noget ordentligt mad. Spiser mange pomfritter på arbejdet. Får ikke det hun skal have. Ved ikke om det hun laver i fitnesscentret er rigtigt - ser ingen resultater. Overspiser om aftenen og føler sig ofte oppustet. Det kan af og til påvirke hendes lyst til at være social. Vil gerne strammes op - særligt på maven.
B84: 27.09.25 | C84: Camilla Brøchner | E84: 22 88 23 02 | F84: camillavedel23@gmail.com | H84: Setter | I84: Split-pay | K84: 9000 | L84: 1500 | R84: https://slack-files.com/T08TMAAKCCU-F09HD7Y4HQV-5f0fa4635a | S84: Closed | T84: Vægttab på 8-10 kg. Tabt 10 kg. selv men kan ikke komme videre. Har en kæreste (datter på 2) der træner meget og prøver at motivere hende til at komme igang. Har stået stille i et år. Mangler redskaber og vejledning til hvordan hun kommer helt i mål. Mangler rytme og balance i kosten. LIder af IBS og oppustethed. Føler sig usikker. Selvtillid. Tilpas i krop. Pas på sig selv nu. Har tendens til overspringshandlinger - slut nu. Glæden ved træning og mad uden bekymring og tvivl. Ønsker at have stramt tøj på - flad mave og booty. Mere muskelmasse. Har rygsmerter som forsvinder ved træning.
B85: 27.09.25 | C85: Sarah Svenson | E85: 27 13 80 42 | F85: sarah.svenson@hotmail.com | H85: Setter | I85: Offer & Didn't Buy | N85: Money | Q85: 5 | R85: https://slack-files.com/T08TMAAKCCU-F09JAFBDX5W-2be8f0c389 | S85: X | T85: Arbejder på kontor - stillesiddende arbejde. Døjer meget med oppustethed på daglig basis - sidste lange stykke tid. Har forsøgt at undgå gluten hvilket virker men hun føler sig ikke mæt og er usikker på om hun får næring nok. Vil gerne finde glæden tilbage ved mad uden bekymringer og stress. Inspiration til nemt, sundt mad! Struktur og finde glæden ved styrketræning. Sparring og vejledning til hvad der virker. Ønsker at skabe realistsike mål så hun kan få succesoplevelser. ønsker bedre holdning og stærk ryg. Energi, styrke, hud, træt, overskud, tilpas i krop, rutiner, madro. Prioriterer sin sundhed højt!
B86: 2709.25 | C86: Tilde Johnson (skrevet) | E86: 93 95 79 80 | F86: tilde@johnsenholck.dk | H86: Setter | I86: Offer & Didn't Buy | N86: Money | O86: Fylder 18 i okt. følg op i nov ang. økonomi | Q86: 5 | R86: https://slack-files.com/T08TMAAKCCU-F09HMCT149J-73c3e9a881 | S86: Follow Up | T86: Spiller håndbold og styrketræner i samme forbindelse. Kan ikke yde sit bedste fordi hun ikke får den mad og næring hendes krop har behov for. Hopper af og til over måltider fordi hun er bange for at tage på og kan ikke finde en stabil rytme i maden. Træt, energi, tilpas i krop, overskud, glæde - mangler støtte, vejleding inspiration og struktur. Sover ikke nok. Fedttab på 5 kg. Haft været utilpas og ude af balance i 2 år.
B87: 27.09.25 | C87: Anne-Katrine Christiansen | E87: 52 50 72 51 | F87: annekatrinechristiansen7@gmail.com | H87: Setter | I87: Deposit | N87: Money | O87: Betaler d. 1. okt | Q87: 5 | R87: https://slack-files.com/T08TMAAKCCU-F09HMCUMNCC-e76f800da1 | S87: Closed | T87: Har mange bekymringer omkring mad! blev ked af det på kaldet fordi det fylder så meget for hende i dag dagligdagen. Overtænker og stresser og hvad og hvor meget hun skal spise hvornår. Ender med at overspise og føle sig oppustet. Mangler struktur, viden og vejledning. Er ked af sin mave. Madro og stærk krop. Har prøvet selv mange gange men ender i spiral. Alt eller intet. Vægttab på 5 kg. Ønsker talje og færre bekymringer.
B88: 27.09.25 | C88: Sigriður hlin | E88: 42 67 10 51 | F88: sigridhlinj@gmail.com | H88: Setter | I88: Deposit | N88: Money | O88: Betaler d. 1. okt | Q88: 5 | R88: https://slack-files.com/T08TMAAKCCU-F09HGLGA5EE-00468e4d7b | S88: Closed | T88: Alene med en søn på 8 og går i skole - tilpasses. Har været igennem et presset forløb (mor døde for 2 år siden). har ikke passet ordentligt på sig selv. Drukket mange energidrikke. Vaper. Cirkel K hver morgen. Ønsker sunde rutiner og en god struktur som passer ind i hendes travle hverdag. Program til centret, gå, løb - mave. Spejl. Kronisk stress. SMerter i ryggen. Træt + muskelmasse. Ønsker en bedre livsstil så hun kan være mere aktiv med sin søn. vægttab på 7 kg. ikke flere undskyldninger.
B89: 29.09.25 | C89: Cecilie Fiil | E89: 42 16 77 15 | F89: cecillie13@live.dk | H89: Setter | I89: Offer & Didn't Buy | N89: Money | O89: Havde 500 kr. max | Q89: 5 (kortere binding) | R89: https://slack-files.com/T08TMAAKCCU-F09HN4HJN2Z-9eb11a897f | S89: X | T89: Vægttab på 10 kg. Ønsker hjælp til hjemmetræning (måske center på sigt). Selvstændig beauty - negle, vipper: kunne gå bedre og mangler penge. Synes fitnesscentret er dyrt. Kost: Springer over måltider og snacker sig gennem dagen. Usunde tiltag og færdigretter. Partner vil ikke deltage i kostomlægning og spiser ofte snacks foran Cecilie. Hun savner sit gamle jeg og har prøvet meget forskelligt selv. Har tøjkrise hver dag og føler sig utilpas med krop. Føler forløbet er det helt rigtige for hende, men hun har ikke mere i budgettet end 500 kr. når hun skraber sammen. Ingen opsparring og vil ikke låne penge.
B90: 29.09.25 | C90: Julie Kirban | E90: 24 40 24 39 | F90: juliekirban@gmail.com | H90: Setter | I90: Offer & Didn't Buy | N90: Fear | O90: Det går for stærkt. Vil gerne selv tage kontakt til follow up | Q90: 5 | R90: https://slack-files.com/T08TMAAKCCU-F09HN4QMRSR-a402e11b18 | S90: X | T90: Har altid været meget aktiv. Træning: motivation til at komme afsted, viden, plan, intro til maskiner - har svært ved at forbinde til særlige muskelgrupper og ønsker at øge kropsbevidsthed. Strammes op. Styrke, muskelmasse, booty. Kost: Overspiser, sulter sig selv, rytme - kan godt lide at lave mad men mangler inspiration. Stået på i 2,5 år og hende og kæresten har gerne ville gøre noget i 1 år. Kæresten er igang men Julie vil gerne have et program der passer til hendes krop og mål. Mere enerig. Føler sig tung, tøj, usikkerhed, overskud. Færdig med at udsætte. Blev bange for at tage næste skridt allerede før price drop. "Det går meget hurtigt".
B91: 29.09.25 | C91: Nikoline Emilie Nielsen | E91: 31 50 05 67 | F91: nikolineemiliet@gmail.com | H91: Setter | I91: Split-pay | K91: 9000 | L91: 1500 | N91: Money | Q91: 5 | R91: https://slack-files.com/T08TMAAKCCU-F09HPUVC1HU-e692a85d32 | S91: Closed | T91: Vægttab: 7 kg. Meget lav arousal under kald. Prøvet coach før hvor hun ikke fortalte sandheden og dækkede over sig selv. Føler hun spilder tiden på at have det skidt med sig selv. Kost: overtænker og snacker rigtig meget. Mangler viden og mere madro. Selvsikker, lettere sind, klogere på mad, udseende (går nogle gange hjem fra byen fordi der er mange smukke kvinder på Nørrebro og hun føler sig ikke god eller pæn nok) Synes det er fedt Olivia arbejder med mindset. Mave arme, sundhedsaspekt. Sunde rutiner, oppustet, hud, stærkt krop.
B92: 29.09.25 | C92: Laura Jakobsen | E92: 61 16 27 91 | F92: laurajakobsen007@gmail.com | H92: Setter | I92: Offer & Didn't Buy | N92: Money | O92: Tænke over det + kigge økonomi | Q92: 5 | R92: https://slack-files.com/T08TMAAKCCU-F09HW344F6Y-f9830f293b | S92: X | T92: Vægttab på 7 kg. Har okay styr på træningen som hun kører med en veninde, men vil meget gerne have helt styr på kosten. Mere struktur, balance, inspiration til sund nem mad - næring og protein. Meal prepping. Har siddet fast i 2 år. Føler sig ikke tilpas i krop. Dårligt humør og træt. Mangler vejledning og hjælp. Nu er det nu!
B93: 29.09.25 | C93: Julie Åsleff | E93: 29 93 17 15 | F93: juliesleff@outlook.dk | H93: Setter | I93: No-Show
B94: 30.09.25 | C94: Caroline Brandhelft | E94: 40 91 96 45 | F94: carolineskanvigb@gmail.com | H94: Setter | I94: Cancelled

Sheet Oct
B1: Rep: | C1: Name | E1: Anton KPI's | H1: Outcome | K1: KPIs% | N1: Show Rate | Q1: Objections | T1: Source
E2: Rev per call | F2: =C3/C6 -> 5872.3404 | H2: Full-Pay: | I2: =IFERROR(COUNTIFS(I13:I287, "Full-Pay"),"") -> 1 | K2: Conversion Rate: | L2: =iferror(L10/L8,"") -> 0.65957447 | N2: Rescheduling Rate: | O2: =iferror(I8/L6,"") -> 0.098591549 | Q2: Think About It | R2: =IFERROR(COUNTIFS(N13:N286, "think about it"),"") -> 4 | T2: Reschedule | U2: =IFERROR(COUNTIF(H13:H286,T2),"") -> 0
B3: Revenue | C3: =IFERROR(SUM(K13:K283),"") -> 276000 | E3: Cash per call | F3: =C4/C6 -> 1882.9787 | H3: Split-Pay: | I3: =IFERROR(COUNTIFS(I13:I287, "Split-Pay"),"") -> 30 | K3: Offer To Close Rate: | L3: =IFERROR(L10/L9,"") -> 0.65957447 | N3: Cancellation Rate: | O3: =iferror(I9/L6,"") -> 0.15492958 | Q3: Money | R3: =IFERROR(COUNTIFS(N13:N286, "money"),"") -> 15 | T3: YouTube | U3: =IFERROR(COUNTIF(H13:H286,T3),"") -> 0
B4: Cash | C4: =IFERROR(SUM(L13:L284),"") -> 88500 | E4: Cash upfront % | F4: =C4/C3*100 -> 32.065217 | H4: Deposits: | I4: =IFERROR(COUNTIFS(I13:I287, "Deposit"),"") -> 0 | K4: Call To Offer Rate: | L4: =IFERROR(L9/L8,"") -> 1 | N4: No-Shows Rate: | O4: =iferror(I10/L6,"") -> 0.084507042 | Q4: Time | R4: =IFERROR(COUNTIFS(N13:N286, "time"),"") -> 0 | T4: YouTube Ads | U4: =IFERROR(COUNTIF(H13:H286,T4),"") -> 0
E5: PIF % | F5: =I2/C7*100 -> 3.2258065 | H5: Offer & Didn't Buy: | I5: =IFERROR(COUNTIFS(I13:I287, "Offer & Didn't Buy"),"") -> 16 | K5: Drag Over Rate: | L5: =IFERROR(I7/(C6+I7+I8),"") -> 0 | N5: Drag Over Rate: | O5: =iferror(I7/L6,"") -> 0 | Q5: Partner | R5: =IFERROR(COUNTIFS(N13:N286, "partner"),"") -> 1 | T5: Email | U5: =IFERROR(COUNTIF(H13:H286,T5),"") -> 0
B6: Total Calls : | C6: =IFERROR(SUM(I2:I6),"") -> 47 | E6: Average Binding | F6: =AVERAGE(Q13:Q104) -> 5.125 | H6: Bad Fit & No Offer: | I6: =IFERROR(COUNTIFS(I13:I287, "Bad Fit & No Offer"),"") -> 0 | K6: Bookings: | L6: =IFERROR(SUM(I2:I10),"") -> 71 | N6: Show-Up Rate: | O6: =iferror(L7/L6,"") -> 0.66197183 | Q6: Fear | R6: =IFERROR(COUNTIFS(N13:N286, "fear"),"") -> 2 | T6: Facebook | U6: =IFERROR(COUNTIF(H13:H286,T6),"") -> 0
B7: Total Won : | C7: =IFERROR(I2+I3,"") -> 31 | E7: Average deal | F7: =C3/C7 -> 8903.2258 | H7: Drag Over & Show: | I7: =IFERROR(COUNTIFS(I13:I287, "Drag Over & Show"),"") -> 0 | K7: Shows: | L7: =IFERROR(SUM(I2:I7),"") -> 47 | N7: Conducted Rate: | O7: =IFERROR(L8/L6,"") -> 0.66197183 | Q7: Value | R7: =IFERROR(COUNTIFS(N14:N287, "value"),"") -> 0 | T7: Facebook Ads | U7: =IFERROR(COUNTIF(H13:H286,T7),"") -> 0
B8: Total Lost : | C8: =COUNTIF(I13:I286,"offer & didn't buy")+countif(I13:I286,"deposit")+countif(I13:I286,"bad fit & no offer") -> 16 | E8: Average cash | F8: =C4/C7 -> 2854.8387 | H8: Rescheduled: | I8: =IFERROR(COUNTIFS(I13:I287, "Rescheduled"),"") -> 7 | K8: Calls: | L8: =IFERROR(SUM(I2:I6),"") -> 47 | T8: LinkedIn | U8: =IFERROR(COUNTIF(H13:H286,T8),"") -> 0
B9: Closing % : | C9: =iferror(SUM(C7/C6),"") -> 0.65957447 | H9: Cancelled: | I9: =IFERROR(COUNTIFS(I13:I287, "Cancelled"),"") -> 11 | K9: Offers: | L9: =IFERROR(sum(I2:I5),"") -> 47
H10: No-Show: | I10: =IFERROR(COUNTIFS(I13:I287, "No-Show"),"") -> 6 | K10: Deals | L10: =I2+I3 -> 31
B12: Date | C12: Name | E12: Phone No. | F12: Email | H12: Source | I12: Outcome | K12: Revenue | L12: Cash | N12: Objection | O12: Objection Notes | Q12: Length | R12: Recording Link | S12: Follow Up/Next Steps | T12: Call Summary
B13: 01.10.25 | C13: Terese Kristensen | E13: 30 20 49 35 | F13: nikki-emira@hotmail.com | H13: Setter | I13: Split-pay | K13: 9000 | L13: 3000 | O13: (Har stoppet forløb d. 21. okt) | Q13: 5 | S13: Closed | T13: Fra sep.
B14: 01.10.25 | C14: Anne-Katrine Christiansen | E14: 52 50 72 51 | F14: annekatrinechristiansen7@gmail.com | H14: Setter | I14: Split-pay | K14: 9000 | L14: 3000 | Q14: 5 | S14: Closed | T14: Fra sep.
B17: 01.10.25 | C17: Charlotte Skov | E17: 50 18 07 01 | F17: tusindfryd20@hotmail.com | H17: Setter | I17: Rescheduled
B18: 01.10.25 | C18: Katrine | E18: 26 11 29 97 | H18: Setter | I18: Cancelled
B19: 01.10.25 | C19: Amalie Klinkby | E19: 20 62 93 62 | F19: amalielarsen69@gmail.com | H19: Setter | I19: Cancelled
B20: 01.10.25 | C20: Didde Nicolaisen | E20: 26 11 29 97 | F20: nicolaisendidde3@gmail.com | H20: Setter | I20: Rescheduled
B21: 01.10.25 | C21: Josefine Nymann (afsluttet før tid) | E21: 60 80 29 14 | F21: josefine@nymann-nederland.dk | H21: Setter | I21: Split-pay | K21: 1500 | L21: 1500 | Q21: 5 | R21: https://slack-files.com/T08TMAAKCCU-F09J1DZNDSR-1f91470871 | S21: Closed | T21: Havde været i forløb før med kost og træning for 3 år siden. Det gik godt, men hun kan ikke holde vægten stabil. Hun ønsker vaner der føles naturlige uden at måle og veje. Har fokus på ikke-restiktiv spisning og hvad hun har lyst til i moderate mængder. Gider ikke tælle, måle og veje. Vil gerne have mere viden omkring kostsammensætning. Når hun er på højeste vægt har det stor indflydelse på hendes humør og føler sig utilpas i krop. Ikke super interesseret i træning - måske gåture.
B22: 03.10.25 | C22: Agata | E22: 71 63 60 51 | F22: agata215@icloud.com | H22: Setter | I22: Offer & Didn't Buy | N22: Money | Q22: 5 | R22: https://slack-files.com/T08TMAAKCCU-F09KD4QJNRE-e31f553292 | S22: X | T22: Streng alt eller intet mentalitet. Hvis hun spiser et stykke chokolade begynder hun at overspise resten af dagen. Har dårlig samvittighed hver gang hun spiser usundt og det påvirker hende meget mentalt. Ønsker et vægttab på 5 kg. Har gang i trænin - løb + styrketræning. Har talt kalorier og er meget opsat på ikke at gøre det igen. Balance mellem kost og det mentale. Har stået på i 4-5 år.
B23: 03.10.25 | C23: Mathilde Flensted - ringet og skrevet | E23: 51 89 39 86 | F23: mathilde.f.n1449@gmail.com | H23: Setter | I23: Offer & Didn't Buy | N23: Money | O23: Penge (hjemmeboende SU) + forældre | Q23: 5 | R23: https://slack-files.com/T08TMAAKCCU-F09JH539V0E-eddcea2fbe | S23: X | T23: Oppustethed og snacking. Fylder rigtig meget mentalt og er gået ud over selvtillid. Ønsker vægttab på 5-10 kg. Har svært ved at bryde med usunde vaner - særligt når det står foran hende. Ønsker mere balance og rytme i kost så hun undgår snacking. Føler sig meget træt. Føler hun bruger sin tid forkert. Vidste ikke oppustethed var en ting før hun så Olivia på IG og blev meget glad da hun fandt ud af det kunne løses. Hvile i sig selv - ved ikke hvordan hun kommer igang.
B24: 03.10.25 | C24: Nikkie Melina | E24: 50 14 40 58 | F24: nikkiemelina@gmail.com | H24: Setter | I24: Rescheduled | T24: Var i Bilka da jeg ringede
B25: 03.10.25 | C25: Amalie Hansen | E25: 24 25 16 17 | F25: hertzumamalie@gmail.com | H25: Setter | I25: No-Show
B26: 05.10.25 | C26: Julie Amalie Malchow | E26: 24 60 64 85 | F26: juliemalchow@outlook.dk | H26: Setter | I26: Split-pay | K26: 9000 | L26: 3000 | Q26: 5 | R26: https://slack-files.com/T08TMAAKCCU-F09KMQC46KS-416946a575 | S26: Closed | T26: Kamp med egen krop i 10 år. Arbejder i vuggestue 28 år. Prøvet wegovy og kostvejleder men ikke fundet en holdbar løsning endnu. Hun bruger enormt meget tid og energi på at tænke på mad og føler det er en kamp at finde ud af - mere viden om kost. Synes det er særligt atraktivt at arbejde med mindset og mad samlet. Vægttab på 15 kg. Går op i at have en sund krop og gode vaner så hun kan føle sig godt tilpas. Adfærd og vaneændringer. Mangler en træningsplan og føler sig ofte usikker på hvordan hun griber øvelser an - teknik og formål. Træt, energi, tøj, tilreds, selvsikker - bæredygtig livsstil.
B27: 05.10.25 | C27: Mikkeline Vjernø | E27: 26 24 07 02 | F27: mikkelinebjerno@gmail.com | H27: Setter | I27: Split-pay | K27: 9000 | L27: 3000 | Q27: 5 | R27: https://slack-files.com/T08TMAAKCCU-F09K6GSSZMF-631afc54bb | S27: Closed | T27: Vægttab 30 kg. Har i 10 år ønsket at tabe sig, men er usikker på hvordan. Hun har forsøgt med keto, kalorietælling, men kan ikke ændre vaner/livsstil så det holder. Hun mangler hjælp, råd, rammer og motivation. Har et brændende ænske og føler sig motiveret, men kan ikke gøre det der skal til på egen hånd. Føler hun har ramt en mur lige nu og har aldrig overvejet hjælp før nu. Er bekymret for hvad der sker med hende hvis hun ikke får hjælp nu.
B28: 05.10.25 | C28: Sandra Adrian | E28: 41 10 01 56 | F28: sandramusen24@gmail.com | H28: Setter | I28: No-Show
B29: 05.10.25 | C29: Ida Lyhne | E29: 40 86 91 38 | F29: ida.lyhne@gmail.com | H29: Setter | I29: Cancelled
B30: 07.10.25 | C30: Nellie Skovhus | E30: 53 70 39 00 | F30: nellie.skovhus@gmail.com | H30: Setter | I30: Split-pay | K30: 9000 | L30: 1500 | N30: Money | Q30: 5 | R30: https://slack-files.com/T08TMAAKCCU-F09JR0DUXBR-7d39fa5d71 | S30: Closed | T30: Vægttab på ca. 10 kg. Arbejder på Café - ikke mange penge. Er i en periode i sit liv hvor hun tager hurtigere beslutninger, hvilket hun synes føles fedt da hun plejer at overtænke. Vil gerne have hjælp til træning: styrketræning, hjemmetræning, løb. Mad: Spiser slik på daglig basis. Smed alt ud der var usundt men endte med at gå ned efter slik alligvel. Tøj, spejl, tilpas i krop, dårlig samvittighed. Sunde vaner - sundhedsperspektiv, motivation. Sagde sit job op spontant fordi hun fik nok. Har lige været igennem en svær periode hvor hendes kæreste var hende utro med veninde som nu er kærester. Påvirket mentalt, men lige trådt ind i en ny periode. Momentum. Snakkede om ørepoeration, men endte med at prioritere forløbet som det første.
B31: 08.10.25 | C31: Helene Adlefedt | E31: 60 63 71 16 | F31: heleneadlefeldt@gmail.com | H31: Setter | I31: Offer & Didn't Buy | N31: Money | O31: Kontanthjælp (7000 kr før skat), ingen opsparing - meldt ind som vikar og venter på svar - vil gerne starte hvis hun får mere. Klar til at gøre det til højeste prioritet | Q31: 5 | R31: https://slack-files.com/T08TMAAKCCU-F09KDC0PMKL-b57a28166f | S31: X | T31: Har fulgt op d. 28/10 for at høre om hun har fået vikarjob. Det har hun ikke. Prøve at følge op igen i dec. Hun er meget interesseret. Har prøvet pesonlig træner. Arbejdsløs på kontanthjælp. 2 x depression. Mental kamp. Ønsker at bryde med et mønster hun har forsøgt at komme ud af i 10 år (er 33 år). Vil gerne finde løsninger. Mangler støtte til at nå i mål. Har ramt en mur og vil gerne handle på det nu. Kost: Overskueligt, rytme, meal preppe, billigt, balance, fedttab. Træning: hjemmetræning og sat gåture i system. Vil gerne af sin medicin (anti-depressiv) Humørspiser - enten spiser hun meget eller lidt. God snak og endte med meget gerne at ville handle på sin situation.
B32: 08.10.25 | C32: Amalie Rasmussen | E32: 20 98 62 08 | F32: amalierasmussen14@gmail.com | H32: Setter | I32: No-Show
B33: 08.10.25 | C33: Nikkie Melina | E33: 50 14 40 58 | F33: nikkiemelina@gmail.com | H33: Setter | I33: Cancelled | O33: Grundet operation i maven/tarmen
B34: 07.10.25 | C34: Amalie Klinkby | E34: 20 62 93 62 | F34: amalielarsen69@gmail.com | H34: Setter | I34: Offer & Didn't Buy | N34: Think About It | Q34: 5 | R34: https://slack-files.com/T08TMAAKCCU-F09K26XURS9-6f6ca047ff | S34: X | T34: Skriver besked om hun vil starte. Meget tynd. Vil gerne være stærkere. Vil gerne være den bedste udgave af sig selv for sin datter og kæreste. Er meget træt og lav på energi generelt. Kort lunte. Flad mave, stærk ryg, booty, viden. Kost: balance, sammensætning, familie, viden og inspiration. Kan ikke overskue at finde på nyt sundt hver dag. Rutiner, tøj, usikker - spilder tid. Ser ikke resultter af sin træning - demotiveret. Hjemmetræning og løb.
B35: 07.10.25 | C35: Clara Posedal | E35: 53 62 06 36 | F35: claraporsdal@hotmail.com | H35: Setter | I35: Offer & Didn't Buy | N35: Money | O35: Hører mor om hun vil hjælpe økonomisk - follow up d. 9/10 | Q35: 5 | R35: https://slack-files.com/T08TMAAKCCU-F09K3J1HFM4-ec68e9ca99 | S35: X | T35: Spiseforstyrrelse: Overspiser + opkastning. Har været i forløb i psykiatri - lige afsluttet. Ønsker støtte til overgangen. Mangler at få etableret et normalt forhold til mad. Tænker konstant på mad. Glemt hvad der er normalt. Hundehvalp fordi hun isolerer sig. 1,5 år siden fik mor kræft som startede spiseforsyrrelsen. Mangler konkrete værktøjer til hvordan hun kan finde balancen i kosten. Lægger meget mærke til kroppens signaler - fryser meget og bliver nervøs for om det er fordi hun ikke spiser nok. Mistet sig selv. Restiktiv! Madro. Livslyst - er bange for hvad der sker hvis hun ikke får hjem ("så er jeg her nok ikke mere")
B36: 08.10.25 | C36: Natacha Gade | E36: 20 83 12 36 | F36: ngandersen@hotmail.dk | H36: Setter | I36: Split-pay | K36: 9000 | L36: 1500 | N36: Money | O36: Var i forløb i forvejen (afsluttes slut nov) | Q36: 5 | R36: https://slack-files.com/T08TMAAKCCU-F09K05JK98X-daaa83f20b | S36: Closed | T36: I forløb i forvejen på 3-4 måned. Afsluttes først kontraktmæssigt slut nov. Men var klar på at tage næste skridt alligevel. Ønsker et vægttab på 25 kg. Har haft jojo-vægt i 10 år. Oppustet, overspiser, snacker meget, sulten - efterlader hende fysisk og psykisk dårlig. Sidder fast. Vil gerne have en sund krop til at få børn på sigt. Super vigtigt: Vi kigger på adfæren bag overspisningen og det mentale/mindset. Derfor hun vil starte i forløb da det lød anderledes end andet hun har prøvet.
B37: 08.10.25 | C37: Amalie Hansen | E37: 24 25 16 76 | F37: hertzumamalie@gmail.com | H37: Setter | I37: No-Show | K37: For 2. gang
B38: 08.10.25 | C38: Emilie Kjær | E38: 31 10 12 53 | F38: emilie.k.theodorsen@gmail.com | H38: Setter | I38: Split-pay | K38: 9000 | L38: 3000 | Q38: 5 | R38: https://slack-files.com/T08TMAAKCCU-F09KCLGDKM3-14ccfff864 | S38: Closed | T38: Har kæmpet i 10 år med jojo-vægt og er blevet mobbet en del pga. sin krop - vil gerne blive bedre venner med den. Kost: Tæller konstant kalorier og er hyperfokuseret på det. Har haft en forstyrret spisning. Får ikke den næring hun har brug for. Arbejder i bager og spiser meget brød. Er ofte oppustet og træt. Vil gerne have madro! Ønsker sig en ny livsstil og Emilie 2.0 i 2026. Træning: mere muskelmasse og styrke. Men først og fremmest ro i hovedet og struktur på sunde rutiner.
B39: 08.10.25 | C39: Camilla Glistrup | E39: 28 72 33 92 | F39: camillagn@live.dk | H39: Setter | I39: Cancelled
B40: 09.10.25 | C40: Mathilde Gudsø | E40: 29 88 21 31 | F40: mathilde.g.nielsen@hotmail.com | H40: Setter | I40: Split-pay | K40: 9000 | L40: 3000 | Q40: 5 | R40: https://slack-files.com/T08TMAAKCCU-F09KKR8GNHY-cbd2d3f19c | S40: Closed | T40: Har hele sit liv døjet med maven/tarmene. Smerter og oppustethed. Har været ved lægen og prøvet meget med mad på egen hånd, men ved ikke hvad det er og hvad der virker. Altid oppustet ligemeget hvad hun spiser. Enten ser hun super tynd eller gravid ud. Træning: Elsker at træne men har svært ved at finde rytmen så snart hun er ude af vante rammer. Har brug for at få konkrete redskaber til hvordan hun holder rytmen konstant når det bliver svært. Meget sulten på mere viden omkring træning og kost. Mangler viden omkring træning. Bange for at lave skade på sig selv ved at gøre øvelser forkert. Føler sig usikker i et træningscenter fordi hun ikke ved 100 % hvordan hun går til øvelserne. Føler sig ofte træt og energiforladt. Elsker rutiner, men har svært ved at fastholde dem. Struktur, samtale og sparring.
B41: 09.10.25 | C41: Clara Riley | E41: 61 27 29 94 | F41: clara.b.riley@gmail.com | H41: Setter | I41: Cancelled
B42: 09.10.25 | C42: Hana Jakupovic | E42: 60 48 16 17 | F42: hana.jakupovic@outlook.dk | H42: Setter | I42: Split-pay | K42: 9000 | L42: 3000 | O42: Prøve selv | Q42: 5 | R42: https://slack-files.com/T08TMAAKCCU-F09KZNMTNQZ-31c7019b99 | S42: Closed | T42: Studerer til audiolopæd. Har siden august gerne ville gøre noget ved sin livsstil. Kan ikke finde en god rutine i træningen, og er i tvivl om hvad der fungerer når det kommer til øvelser og kost. Hun har været meget opmærksom på at tælle kalorier i en grad så det blev usundt. Er meget opsat på at gøre det på en sund måde. Mere tonet, energi, tilpas i krop, mere ro omkring hvad der virker. Mangler støtte og vejledning. Sundhed i fremtiden - børn. Vægttab: 10 kg. men ikke hovedfokus. Det skaber ængestelighed at hun ikke ved hvad der virker og hvordan man gør.
B43: 09.10.25 | C43: Mathilde Schøler | E43: 24 52 24 66 | F43: mlindvald@gmail.com | H43: Setter | I43: Split-pay | K43: 9000 | L43: 3000 | Q43: 5 | R43: https://slack-files.com/T08TMAAKCCU-F09L0AMMSE5-ca732c83b2 | S43: Closed | T43: STX + arbejde. Travl hverdag og vil gerne have sunde rutiner der passer ind. Overspiser og snacker sig igennem dagen. Køber ofte take out fordi hun ikke kan overskue at lave mad. Mangler inspiration og vil gerne kigge ind i meal prepping. Føle sig mæt henover dagen. Hun har prøvet selv i et år, men kan ikke finde ind i rutinen. Træning: ønsker at få helt styr på et træningsprogram i centret. Mangler motivation. Er ofte ked af det når hun tænker på de usunde vaner - det er vigtigt for hende at have en sund livsstil også fremover i hendes liv. Vægttab: 5-10 kg. Gennem søster som kom i mål fik hun også troen på sig selv og ville ikke længere acceptere situationen som den er. Nok! Selvsikkerhed, struktur, overskud, gladere.
B44: 09.10.25 | C44: Sofie Le Fevre | E44: 21 20 00 44 | F44: lefevre190704@gmail.com | H44: Setter | I44: Offer & Didn't Buy | N44: Think About It | O44: Overvejer alternativer - sport | Q44: 5 | R44: https://slack-files.com/T08TMAAKCCU-F09KREHS4H2-ea35b59c07 | S44: X | T44: Opfølgning lørdag. Gammel elitesvømmer. Rejse til januar hvor hun gerne vil stå skarpt i bikini. Føler sig utilpas i sin krop. Ser ikke de resultater hun ønsker sig af træning og kost. Har brug for vejledning. Sunde, lækre snacks. Mere protein og næring. Vil gerne prøve hjemmetræning. Løber. Tøj, spejl, mave, ansigt - ønsker sig tonet krop, booty muskelmasse. Krop har ændret sig og det fylder meget mentalt for hende.
B45: 09.10.25 | C45: Mette Riishøj | E45: 42 95 73 73 | F45: metteriishoj95@gmail.com | H45: Setter | I45: Split-pay | K45: 9000 | L45: 1500 | N45: Money | Q45: 5 | R45: https://slack-files.com/T08TMAAKCCU-F09L1A0E2KT-d9d92536a6 | S45: Closed | T45: Har haft spiseforstyrrelse og vejet omkring de 35 kg. Har svinget med 30 kg. i vægt. PTSD + OCD. Ønsker at skabe de bedste forudsætninger for familie og børn i fremtiden. Stærk krop der kan bære en graviditet. Har haft svært ved mad og træning så langt tilbage hun kan huske. Svær opvækst med vold og utryghed. Bor hos veninde lige nu, men ser muligheder i at hun starter i forløb (veninde vil også gerne spise sundt og tabe sig). Hjælp til træning i center + hjemmetræning. Ønsker sig booty og blive strammet op. Har dårlig kondi og følser sig slap. Mangler styrke i kroppen. Meget træt. Meal prepping efter lange dage på arbjedet (lagerarbejde med lange vagter) 30 år. Ingen forbindelse til sult og mæthed - signaler og kropsbevidsthed.
B46: 10.10.25 | C46: Charlotte Skov | E46: 50 18 07 01 | F46: tusindfryd20@hotmail.com | H46: Setter | I46: Offer & Didn't Buy | N46: Money | O46: Sygemeldt på 4. år - understøttelse + to børn | Q46: 5 | R46: https://slack-files.com/T08TMAAKCCU-F09KQN07CAZ-011c750fc8 | S46: X | T46: Sygemeldt med kronisk hovedpine (IIH - vand i hovedet). 34 år. Vægttab på 10 kg. Kost: spiser på følelser. Slik om aftenen. Ingen rytme i maden. Hjemmetræning + struktur på gåture og bevægelse i hverdagen. Tøj, tilpas i krop, føler sig ikke sexet, mave, lår. Har haft jojo-vægt hele sit liv. Mangler en plan og støtte til at nå i mål.
B47: 10.10.25 | C47: Didde Nicolaisen | E47: 26 11 29 97 | F47: nicolaisendidde3@gmail.com | H47: Setter | I47: Rescheduled
B48: 10.10.25 | C48: Cecilie Victoria Rask Nielsen | E48: 42 91 11 61 | F48: cillemusen0697@gmail.com | H48: Setter | I48: Split-pay | K48: 9000 | L48: 3000 | O48: (Stoppet grundet økonomi i nov) | Q48: 5 | R48: https://slack-files.com/T08TMAAKCCU-F09KCN8RL15-3b4f52f91c | S48: Closed | T48: Døjer med oppustethed på 5. år. Har store omkostniner både fysisk, mentalt og socialt. Hun isolerer sig og har mistet flere venner fordi hun bliver i sengen de dage det er slemt. Sulter sig selv og drikker sig mæt i vand for at undgå oppustethed. Ingen energi, overskud. Selvværd. Er der mere for andre end sig selv, hvilket hun nu er klar på at lave om på. Hun synes det har været svært at bede om hjælp (grænseoverskridende) men er nu klar på at træde ud af sin komfortzone for at komme godt videre. Rytme og balance i kost. Stress. Træning: Usikker i et træningscenter, men vil gerne på sigt. Starte med hjemmetræning, løb og gåture. Tro på sig selv, har ofte en facade som hun ikke orker mere.
B49: 10.10.25 | C49: Frida Andersen | E49: 20 88 98 90 | F49: fridolina@ymail.com | H49: Setter | I49: Split-pay | K49: 9000 | L49: 3000 | Q49: 5 | R49: https://slack-files.com/T08TMAAKCCU-F09LPS5V8KS-51aece27af | S49: Closed | T49: Bor i Mexico og pendler til DK. Tager altid på når hun kommer til DK og vil gerne finde ud af hvad der virker for hendes krop det sted hun er i livet lige nu. For 8 år siden tabte hun 10 kg. på egen hånd, men kan mærke det ikke er det samme der virker for hende nu. Vægttabet er sekundært og hun ønsker først og fremmest at have sunde vaner og passe godt på sin krop. Har haft jojo-vægt altid - ønsker stabil vægt. Har diætist der kommer med to måltider i ugen. Lige nu lever hun meget af junk og hvad der er nemt hvilket hun mærker på sin energi og sit overskud. Tid til at prioritere sig selv. Balance, sund, energi, tonet krop. Ønsker en realistisk rutine i fitnesscentret. Har skader der skal tages højde for. Ønsker at blive bedre til at overholde aftaler med sig selv - det har hun meget svært ved i alle henseender. Travl hverdag. Stabile vaner der holder i det lange løb.
B50: 11.10.25 | C50: Celine Hornemann | E50: 60 13 69 98 | F50: cp151204@yahoo.com | H50: Setter | I50: Split-pay | K50: 9000 | L50: 1500 | N50: Partner | O50: Og penge | Q50: 5 | R50: https://slack-files.com/T08TMAAKCCU-F09KZRSHTQS-0b2baa7dd6 | S50: Closed | T50: Arbejder i institution, bor med kæreste, 20 år, gammel gymnast. Ønsker hjælp til træningen. Er usikker i et fitnesscenter - teknik, struktur, øvelser, klar plan. Meget glad for kontrol og overblik! Kost: overspiser - mængder, vane. Ender med dårlig samvittighed og ubehag i kroppen. Meget sulten på mere viden omkring kost og træning. Har taget en beslutning om at ændre sin livssituation - skabe sunde vaner og øge sin livskvalitet. Ofte negativ. Skriver derfor taknemmelighedsdagbog hver morgen så hun kan vende sit mindset. Mere glæde, muskelmasse, styrke, energi. Hendes egen proces.
B51: 11.10.25 | C51: Victoria Kreiler | E51: 51 16 65 88 | F51: kreilervictoria@gmail.com | H51: Setter | I51: Split-pay | K51: 9000 | L51: 3000 | Q51: 5 | R51: https://slack-files.com/T08TMAAKCCU-F09KWRH0BS9-2d72c80aca | S51: Closed | T51: Forstyrret og restiktiv spisning. Straffer sig selv ved at kompensere med træning eller sulte sig selv hvis hun har spist noget hun ikke "burde". Overspiser og har haft tendens til at kaste op efter og have fysisk og mentalt ubehag. Dårlig samvittighed. Selvværd, overskud, energi, tanker om udseende, forskruet syn på kost og træning (siger hun selv) mentalt drænet af at tænke på mad. Kan ikke mærke lysten til mad. Ønsker madro og at finde glæden ved mad. Ændre perspektiv til at mad ikke er farligt, men næring for hendes krop. Besluttet at gøre noget godt for sig selv - blive gode venner med kroppen. Livsstil. Skammer sig over sine vaner. Har altid stået alene med det og ikke fortalt nogen om det.
B52: 13.10.25 | C52: Sofie Brix | E52: 51 78 22 35 | F52: sofiebrixtofte@gmail.com | H52: Setter | I52: Cancelled
B53: 13.10.25 | C53: Camilla Alstrup | E53: 60 22 14 85 | F53: mille_333@hotmail.com | H53: Setter | I53: Rescheduled
B54: 13.10.25 | C54: Lone Mørch (Stoppet før tid) | E54: 42 20 97 15 | F54: lone.m.fosdal@gmail.com | H54: Setter | I54: Split-pay | K54: 9000 | L54: 3000 | Q54: 5 | R54: https://slack-files.com/T08TMAAKCCU-F09LM27HPND-efb040b2cf | S54: Closed | T54: Lone har haft en discus i nakken siden sidste år. Er lige blevet smertefri efter både fys, læge og akkupunktur. Har været vant til at kroppen har set ud som den altid har gjort, men efter forløbet hvor hun har været sat ud af spil, mærker hun en stor forskel og føler sig utilpas i sin krop (31 år) og mærker alderen har noget at sige - ønsker at gøre noget nu og ser fordelen ved at handle nu og ikke senere når det bliver sværere. Bioanalytikker og meget travl kvinde - også på kald om natten. Har haft en presset periode i lang tid nu så synes det at Olivia arbejder med stress var en god gevinst. Har investeret i personlig træner 2 gange før men har ikke følt de metoder og redskaber fungerer for hende det sted hun står nu. Hjælp til centret - mere effektiv træning som ikke kun handler om redskaber (står ofte og venter længe til det er hendes tur) + hjemmetræning + løb. Motivation på de svære dage. Ønsker ikke at tage billeder af sin krop til forløbet. Søvn, energi, overskud, stærk krop, livsstil, appelsinhud, tøj.
B55: 13.10.25 | C55: Anna Dicte | E55: 21 56 32 62 | F55: annadicteamby@hotmail.com | H55: Setter | I55: Offer & Didn't Buy | N55: Money | O55: Studenterhue, hestevogn og skiferie lige betalt | Q55: 5 | R55: https://slack-files.com/T08TMAAKCCU-F09KX7Y2LBH-022a67775f | S55: X | T55: Vil gerne igang og motiveret for at skabe forandring. Har en travl dag med skole og arbejde - har brug for nye stabile vaner passer ind i hverdag. 18 år. Lavt stofskifte. Jojo-vægt gennem flere år. Hjælp til centret, løb, hjemmetræning. Kost: Har været meget restriktiv i forhold til at tælle kalorier (meget usundt siger hun selv) føler sig ofte oppustet hvilket påvirker hende meget. Sundhed, struktur, tonet, strammet op, rutine, tøj, træthed, overskud, viden - alt eller intet. Spiral i 3 år. Godt mindset med gode prioriteter. Klar på at investere i sig selv.
B56: 14.10.25 | C56: Cecilie Burholm | E56: 60 71 10 92 | F56: cburholm@gmail.com | H56: Setter | I56: Split-pay | K56: 9000 | L56: 1500 | N56: Money | Q56: 5 | R56: https://slack-files.com/T08TMAAKCCU-F09KZ1UJJHM-77c81c4aec | S56: Closed | T56: Primært hjælp til kosten: overtænker og har hyperfokus på hvad hun spiser hvilket er drændende. Har brug for at få struktur og viden omkring kost. Mæthed! Hjælp til hvordan hun håndterer det at være ude af vante rammer hvor hun ikke har kontrol over det der bliver serveret. Snacker. Madro. Sidder fast i spiral og har prøvet en del selv.
B57: 14.10.25 | C57: Louise Gråbæk | E57: 50 77 07 91 | F57: louisebrinch@hotmail.com | H57: Setter | I57: Rescheduled
B58: 14.10.25 | C58: Birgitte Provstgaard | E58: 30 15 34 46 | F58: birgitte@provstgaard.net | H58: Setter | I58: Split-pay | K58: 9000 | L58: 3000 | Q58: 5 | R58: https://slack-files.com/T08TMAAKCCU-F09LCCSLC3G-8c66df9df9 | S58: Closed | T58: Mangler struktur på kosten. Bruger meget tid på at bekymre sig og tænke over hvor meget, hvor lidt og hvad hun skal spise. Har i mange år ikke prioriteret sig selv, men står nu er et sted hvor hun både gør det for sig selv og sin datter (forbillede). Hun har haft tendens til at hoppe over måltider og overspise - frygt for at tage på. Bedre fordøjelse - ofte forstoppet. Madro og generelt mere ro i hovedet. Selvtillid. Usikker. Snakker meget om det at være tynd har fyldt for hende. Træning: er glad for at løbe. Kunne godt tænke sig at få styr på hjemmetræning - vigtigt det er korte effektive træninger som ikke kræver meget tid. Skal giftes til næste sommer. Vil gerne være den bedste version af sig selv. Jojo-vægt. Klar til at comitte sig. Hjælp til sociale arrangementer og tage gode valg. (Datter på 2)
B59: 14.10.25 | C59: Mathilde Pottier | E59: 20 48 36 21 | F59: mp2200@icloud.com | H59: Setter | I59: Offer & Didn't Buy | N59: Money | O59: Følger op på torsdag. Overvejer investering | Q59: 5 | R59: https://slack-files.com/T08TMAAKCCU-F09KZ1CBJNB-7d15c405fd | S59: X | T59: Sygemeldt med stress. Stille og roligt vendt tilbage til arbejdet på 3 timer om dagen. Nervøs for hvordan det ser ud når hun har 37 timer igen. Ser hendes sygemelding som en mulighed for at forbedre og samle sig selv op - tid. Kost: rytme, viden, nemt, overskueligt - kommer til at overspise søde sager efterladt med dårlig samvittighed. Bor alene og vil gerne have inspiration til nemme, sunde retter. Sundhedsaspekt. Træning: Stabil rytme. Hjemmetræning. Måske center på sigt. Bedre med sig selv, selvtillid. vægttab 3 kg. fedt. Stærkere krop.
B60: 15.10.25 | C60: Louise Gråbæk | E60: 50 77 07 91 | F60: louisebrinch@hotmail.com | H60: Setter | I60: Offer & Didn't Buy | N60: Money | O60: Og frygt - har været i flere forløb. Bange for at tage en chance igen uden at tænke grundligt over det. Selv om hun kan høre dette forløb er anderledes - fokus på mindset og bæredygtige vaner. | Q60: 5 | R60: https://slack-files.com/T08TMAAKCCU-F09M0349UM7-c08203ae8f | S60: X | T60: De sidste 6 år har Louise været på kure og to andre forløb. De gav resultater mens hun var i dem, men ikke holdbare. Ønsker at finde en bæredygtig løsning som bevarer de resultater hun opnår. Sunde vaner som passer ind i livet med to børn og mand. Er meget bevidst omkring cyklus - falder ned i "sort hul" og skal samle sig selv op og starte forfra. Mangler hjælp til at knække koden. Glad for sin træning - løb og hold. Måske på sigt hjælp til at blive bedre løber og styrketræningsdelen. Primært nysgerrig på kost og mindset. Vægttab: 5 kg. Lære at tage gode valg og hvad der lægger bag de valg og tanker hun har nu. Oppustet, tøj, føle sig tilfreds i sin krop, struktur, energi, rytme. Meal prepping så hun har noget sundt og let tilgængeligt i en travl hverdag.
B61: 15.10.25 | C61: Ingeborg Speyermann | E61: 41 12 13 05 | F61: ingeborg2308@gmail.com | H61: Setter | I61: Split-pay | K61: 9000 | L61: 3000 | Q61: 5 | R61: https://slack-files.com/T08TMAAKCCU-F09L5N135JB-7bb14e624a | S61: Closed | T61: Har i 10 år haft et anstrengt, restriktivt forhold til mad - overtænker, alt eller intet. Overspiser på følelser. Mangler rytme, inspiration, balance. Tænker meget over hvordan hun ser ud. Meget interesseret i mindset og at ændre tankemønstre, arbejde med selvværd - isolerer sig fra sine veninder fordi hun spejler sig i dem og føler sig mindre værd. Vil gerne have hjælp til løb, styrketræning, hjemmetræning. Overtænker alt. Klar til at tage handling nu. Højskole til næste efterår - ønsker at være den bedste version af sig selv. Har sabatår nu. 20 år. Arbejder på en skole og plejecenter. Mangler energi, overskud. Muskelmasse og stærk krop.
B62: 15.10.25 | C62: Nana Gleerup | E62: 22 38 44 09 | F62: nanagleerupandersennana@gmail.com | H62: Setter | I62: Rescheduled
B63: 16.10.25 | C63: Olivia Plauborg | E63: 53 37 06 56 | F63: oliviapphilipp7@gmail.com | H63: Setter | I63: Split-pay | K63: 9000 | L63: 3000 | O63: 17 år | Q63: 5 | R63: https://slack-files.com/T08TMAAKCCU-F09MNPDPUGG-1b5b681c7b | S63: Closed | T63: Kost: Overspiser/stress-spiser. Mere struktur, balance og rytme i målrider. Træning: Hjemmetræningsprogram + center - styrke, struktur, plan og mere viden. Mindset: Madro, selvbillede, livsglæde og ønsker at være mere fri i sin krop og sit sind. Har siddet fast i 5 år. Gået hos psykoterapeut. Ønsker at føle sig tilpas i sin krop - mere styrke og selvværd.
B64: 16.10.25 | C64: Josefine Jessen Høyer-Reutin | E64: 31 33 31 24 | F64: josefinereutin@hotmail.com | H64: Setter | I64: Offer & Didn't Buy | N64: Money | O64: 15 år - høre forældre ang. økonomisk tilskud (har selv lidt hun kan betale) | Q64: 5 | R64: https://slack-files.com/T08TMAAKCCU-F09M818KDUZ-c2db00c587 | S64: X | T64: Utilpas i krop. Vil gerne have styr på træningsrutinen - mere sikker og tryg i øvelser og træningscenter. Mere selvsikker. Teknik. Tonet, muskelmasse. Har et svært forhold til mad - "burde ikke/må ikke". Har fyldt meget de sidste 3-4 år.
B65: 16.10.25 | C65: Sofie Brix | E65: 51 78 22 35 | F65: sofiebrixtofte@gmail.com | H65: Setter | I65: Split-pay | K65: 9000 | L65: 3000 | Q65: 5 | R65: https://slack-files.com/T08TMAAKCCU-F09M97VDYLR-bebe58d770 | S65: Closed | T65: Havde en depression for et år siden og er begyndt at mærke tegn på det igen. Vil gerne undgå det gentager sig. Handicaphjælper og fleksibel. Skade i knæ og hypermobile håndled. Har siddet fast i dårlige vaner de sidste 10 år. Har udsat at handle på det mange gange. Træning: Muskelmasse, fedttab 5 kg. tonet. Stabil rutine, mave, styrke, teknik. Hjemmetræning. Kost: Snacker ofte. Mere balance inspiration - mealpreppe og sunde snacks. Har mange øvdage og føler hun er på vej ned i et sort hul igen. Bryder sig ikke om at være omringet af mange mennesker. Forbedre syn på selv. Mindset. Vil ud at opleve mere i stedet for at isoliere sig. Mindset: selvkritik. selvtillid/selvværd - ser fejl. Negativ
B66: 16.10.25 | C66: Christina Nyborg | E66: 51 60 16 53 | F66: christina@frabolivia.dk | H66: Setter | I66: Offer & Didn't Buy | N66: Fear | O66: Startede op og fortrød dagen efter - eventuelt følge op om et par måneder | Q66: 5 | R66: https://slack-files.com/T08TMAAKCCU-F09LV4UEZE2-07ab114b80 | S66: X | T66: Ønsker at have en selvstændig proces og forbedre sit mindset. Ønsker et mere positivt selvbillede - positiv indre stemme. RO omkring krop og udseende. Ønsker at skabe bæredygtige vaner der holder - livsstil. Ser muligheder under kaldet. Sund krop i balance. Tilpas. Tage sin træning mere seriøst så hun begynder at se resultater. Har forsøgt med kroppen i 4 år. Har forsøgt med mindset/selvbillede i 13 år. er 23 år og pædagog. Sagde til sidst efter pitch at hun var endnu mere sikker på Olivias forløb var det rigtige for hende. NU
B67: 17.10.25 | C67: Helena Bay | E67: 21 76 32 76 | F67: helenabaypedersen@gmail.com | H67: Setter | I67: Offer & Didn't Buy | O67: Følger op på mandag/tirsdag | Q67: 5 | R67: https://slack-files.com/T08TMAAKCCU-F09M5MB8NKX-9404b8ab16 | S67: X | T67: Svært ved at finde pain i begyndelsen på kaldet. Kost: Snacker, stabil rytme, balance, tage flere gode valg. Beskriver at hun claimer kage på arbejdet og føler hendes navn står på det og derfor må spise det. Vil gerne spille af med sukkertrangen og føle sig mere mæt i løbet af dagen. Har et motto: Don't think, just do it". Dårlig søvn. Alt eller intet. 25 år. Har haft en drøm om at nå i mål med krop i 8 år. Nu er hende og hendes mand gået all in på resultater. Framer sig selv som selvstændig og er derfor usikker på hvordan hun vil have det med at komme i forløb og få hjælp. Snakker ind i hvad det ville gøre for hendes udvikling at få hjælp, og hvordan det er en styrke at vide præcis hvornår hjælp er nødvendigt for at komme godt videre og nå sine mål.
B68: 19.10.25 | C68: Sara Wejrup | E68: 61 71 63 43 | F68: sarawejrup@hotmail.com | H68: Setter | I68: Split-pay | K68: 9000 | L68: 3000 | O68: Stoppet i nov grundet økonomi og manglende overskud | Q68: 5 | R68: https://slack-files.com/T08TMAAKCCU-F09M5GGT2PM-11efcec537 | S68: Closed | T68: 20 år, bor hjemme. Går til gymnastik 3 gange i ugen. Glutenalleri. Kost: Tvivl, nemme løsninger, inspiration, næring, mere alsidig kost! Træning: Struktur, mave og ben, tonet krop, klar plan, resultater, styrke. Mindset: Sammenligner sig med andre, selvsikker. Sulten på at vide mere om sunde vaner. har siddet fast i 2 år.
B69: 19.10.25 | C69: Amalie Dahl Søgaard Pedersen | E69: 25 79 51 88 | F69: amalie-dahl@outlook.dk | H69: Setter | I69: Split-pay | K69: 9000 | L69: 3000 | Q69: 5 | R69: https://slack-files.com/T08TMAAKCCU-F09MQU5HKAM-5080d7c3df | S69: Closed | T69: Gymnasiet. Ønsker at være tilpas i sin krop og sind til sommer når hun færdiggør gym. Kost: overspiser/stress-spiser på følelser. Oppustet. Ønsker insiration til sunde snacks. Træning: Center. Tonet. Muskelmasse. Flad mave + ked af arme. Vægttab: 10-15 kg. Alt eller intet - undskyldringer. Mindset: selvtillid. Selvbillede. Sammenligner sig med andre. gemmer sig i tøj. Utilpas og usikker. Forbinde til sin mæthed. 3 år +.
B70: 20.10.25 | C70: Camilla Alstrup | E70: 60 22 14 85 | F70: mille_333@hotmail.com | H70: Setter | I70: Offer & Didn't Buy | N70: Think About It | O70: Partner, fear, money | Q70: 5 | R70: https://slack-files.com/T08TMAAKCCU-F09MDNU2ZQD-22d171cac4 | S70: X | T70: Kort lunte, irriteret, mangler overskud og energi. Ved hvor godt hun kan have det når hun har den krop hun føler sig tilpas i og sunde vaner. For 5 år siden døde hendes far, og hun har haft svært ved at finde rytmen siden. Hendes mand støtter hende i at tage forløb og gøre hvad der skal til for at hun når sine mål. Migræneanfald. Har haft stress. Er privat børnepasser - mand + 2 børn. Sidder fast i dårlig spiral. Stået på i 6 måneder - har været utilpas i 5 år. Vægttab på 10-12 kg. Kost: har stor trang til søde sager. Hopper over måltider for at spare kalorier. Får ikke nok næring. Struktur på kost. Kosten er hendes hovedfokus. Mealpreppe sunde snacks når hun får trang til sødt. Træning: Elsker at løbe, vil gerne have sat det i strutur og have en hjemmetræning der understøtter hendes løb og forebygger skader. Mindset: Bruger meget energi på at være i tvivl. Ønsker sunde rutiner, og det fylder meget for hende mentalt ikke at etablere det. Har fokus på det skal passe ind i familien så hun ikke bruger tid alene, men kan inddrage hendes børn. Ser fordelen ved egen proces selv om hun snakker meget om folk hun kan trække på i netværk
B71: 20.10.25 | C71: Malou Friis Jensen | E71: 81 71 12 74 | F71: mmfj4800@icloud.com | H71: Setter | I71: Cancelled
B72: 20.10.25 | C72: Charlotte Uldum | E72: 21 44 03 31 | F72: charlottethisgaard@live.dk | H72: Setter | I72: Cancelled
B73: 21.10.25 | C73: Bless | E73: 27 29 61 66 | F73: henrietta.laryea@outlook.dk | H73: Setter | I73: Offer & Didn't Buy | N73: Money | O73: Kontanthjælp | Q73: 5 | R73: https://slack-files.com/T08TMAAKCCU-F09N1413F41-7a6ea2d6b2 | S73: X | T73: Primært fokus på kost. Mangler inspiration og en plan. Har slet ikke overblik over hvordan hun skal spise. Prøver at etablere sunde kostvaner, men falder i og overspiser usunde snacks. Har lypus type 5 og vil derfor gerne have en sundere livsstil. Fedttab: 10 kg. Mere muskelmasse. Har altid haft en usund kost siden hun var barn - afrikansk mad. Utilfreds med hvordan hun ser ud. Selvsikker. Mere ro i hovedet.
B74: 21.10.25 | C74: Julie Schach | E74: 27 20 49 27 | F74: jeilschou@hotmail.com | H74: Setter | I74: Split-pay | K74: 9000 | L74: 1500 | N74: Money | O74: Dagpenge (har meldt pause i forløb fra nov-1. januar og fortsætter herfra) | Q74: 5 | R74: https://slack-files.com/T08TMAAKCCU-F09MS7CKNF6-b022227a61 | S74: Closed | T74: Udfordringer med fordøjelsen, forstoppet. Inspiration til hvordan hun kan sammensætte sin mad. Har prøvet meget forskelligt de sidste 3 år, men har ikke fundet en løsning. Har en lyskeoperation og er usikker på hvordan hun kan træne med den. Ønsker mere tonet krop. Hjemmetræningsprogram. Booty, ben, arme. Mere ro i hovedet. Har haft en venstresidet lammelse grundet gammelt arbejde hun nu har sagt op, hvorfor hun går på dagpenge nu. Føler hun har tiden til at finde ind i gode rutiner - fremtidsudsiger sund krop til at kunne bære en graviditet. Muskelmasse. Bedste version af sig selv - føler hun er blevet en mere bekymret version af sig selv nu. Hvilket hun er ked af.
B75: 21.10.25 | C75: Sille Marie Erritzøe | E75: 23 61 48 86 | F75: sillemarie1@gmail.com | H75: Setter | I75: Cancelled
B76: 21.10.25 | C76: Luca Rose Andersen | E76: 30 28 42 38 | F76: lucaandresen@outlook.com | H76: Setter | I76: Split-pay | K76: 9000 | L76: 3000 | Q76: 5 | R76: https://slack-files.com/T08TMAAKCCU-F09M85BQ0SK-8107dd99eb | S76: Closed | T76: Uni møbel (Herning) + selvstændigt firma. Alt eller intet. Kost: Meal preppe, overskuelig, nemt, balance, energi. Skal spille sammen med hendes træning. Træning: Har okay styr på træningen. Hjælp til gåture. Tabe fedt, øge muskelmasse. Motivation. Mindset: ro i hovedet, glad, overskud, selvomsorg, afgrænse og sige fra. Mistet sig selv - ønsker at blive den bedste version af sig selv nu. Har isoleret sig - plejer hun ikke! Mangler sit drive og ved hvad sunde rutiner kan give hende.
B77: 21.10.25 | C77: Rebecca Østergaard | E77: 20 40 41 87 | F77: rebecca.vejen4@gmail.com | H77: Setter | I77: Split-pay | K77: 9000 | L77: 3000 | O77: Afsluttet forløbet i dec. | Q77: 5 | R77: https://slack-files.com/T08TMAAKCCU-F09NJKA14KS-55bb301885 | S77: Closed | T77: Havde stress og angst for et år siden. Har siddet fast i dårlige vaner de sidste 6 måneder. Kost: Hjælp til sunde snacks, mængder, balance, rytme, nemt. Træning: Løb, struktur, hjemmetræning der understøtter løb. Mindset: Rutiner og gode valg, motivation - hvordan håndteres svære perioder, overskud energi. Føler sig meget træt, i dårligt humør, energiforladt - ikke glad for krop. Dårlig spiral. Studerer sundhed. Tænker på fremtid. Vægttab på 3 kg.
B78: 22.10.25 | C78: Nana Gleerup | E78: 22 38 44 09 | F78: nanagleerupandersennana@gmail.com | H78: Setter | I78: No-Show | K78: 2. gang
B79: 23.10.25 | C79: Jessica Gjerdrum | E79: 25 21 33 44 | F79: gjerdrumjessica@gmail.com | H79: Setter | I79: Split-pay | K79: 10500 | L79: 3000 | O79: Forældre (er 17) | Q79: 6 | R79: https://slack-files.com/T08TMAAKCCU-F09NZGPKRUG-cc91d6f4e6 | S79: Closed | T79: Følger op lørdag.Spiseforstyrrelse. Over- og underspiser. Tæller meget kalorier. Spise sjældent i selvskab med andre. har selv haft sin egen mad med når hun skal ud så hun ved hvad der er i. Dræner hende psykisk. Vil gerne have balance og mere madro så det ikke skal fylde. Danser hver fredag og går ture. Ønsker at tabe 5-10 kg for at ramme "normal" vægt. Har været meget tynd, men har nu taget på efter hun er begyndt med overspisning. Har stået på i 3 år.
B80: 23.10.25 | C80: Stella Smukke Kath | E80: 27 57 04 61 | F80: romeokath@hotmail.com | H80: Setter | I80: Split-pay | K80: 10500 | L80: 3000 | N80: Fear | O80: Knæoperation for 5 uger siden | Q80: 6 | R80: https://slack-files.com/T08TMAAKCCU-F09NJS38RLZ-81732ab3eb | S80: Closed | T80: Knæoperation for 5 uger siden. Kost: konstiperet dagligt. Nem overskuelig kost. Har en sød tand - alternativer. Rytme, balance. Vil gerne drage sin egen viden omkring kost ind i forløbet - noget i forhold til organer hun har læst.. Snacker om aftenen på følelser, af kedsomhed. Overgangsalder. Træning: hvad der er muligt i forhold til overkrop lige nu. Arme og bryst. Muskelmasse, Hjemmetræning. På sigt løb. Vægttab på 12.kg. siddet fast i 2 år. Vil gerne vide hvorfor ting virker og ikke virker. Meditation. Yogalærer. Sige fra og mærke efter i kroppen. Alt eller intet. Dårlig søvn - sover uroligt og af og til 9 timer. Knække koden til hvad der fungerer for hende i det lange løb. Har prøvet meget selv
B81: 28.10.25 | C81: Liva Rank Andersen | E81: 93 95 17 01 | F81: livarankandersen@gmail.com | H81: Setter | I81: Cancelled
B82: 28.10.25 | C82: Charlotte Uldum | E82: 21 44 03 31 | F82: charlottethisgaard@live.dk | H82: Setter | I82: Full-Pay | K82: 9000 | L82: 9000 | Q82: 6 | R82: https://slack-files.com/T08TMAAKCCU-F09NNL491ST-bb1d486133 | S82: Closed | T82: Jobsøgende - kandidat i informationsvidenskab. Århus, rygsmerter, knæskade, stress-fraktur i fod (overbelastning). Har haft depression. Forsøgt on og off i 10 år at nå i mål med den livsstil hun ønsker sig. Kost: Tager medcin og føler sig derfor sjældent rigtig mæt. Har altid været undervægtig og har nu taget 15 kg på hvilket hun er okay glad for, men vil gerne konvertere lidt fedt til muskelmasse. Mere viden omkring kost, inspiration, sammensætning, balance. Træning: Ønsker intro til øvelser, overblik, teknik. Vil gerne igang med spinning igen. Ønsker også hjemmetræning for fleksibilitet. Mindset: Selvværd, overskud, motivation på den lange bane. Bæredygitg vaner. Gladere, sove mindre i hverdagene. Særligt her i perioden hvor hun ikke har arbejde (dog frivillig).
B83: 29.10.25 | C83: Camilla Kure (+mødebooking) | E83: 28 40 06 74 | F83: camillaskure@gmail.com | H83: Setter | I83: Split-pay | K83: 10500 | L83: 3000 | Q83: 6 | R83: https://slack-files.com/T08TMAAKCCU-F09PFQF2CTC-48855ff077 | S83: Closed | T83: Har haft anoreksi i 5-6 år. Har fundet et ok sted hvor hun spiser, men stadig er bange for at tage på. Hun træner og føler hun har fint styr på det. 21 år. Kæreste hun bor med. Hendes primære problem er balancen mellem mindset og kost. Hun overspiser slik hver fredag (800g) til hun har mavekramper. Hun kan ikke finde balancen og vil gerne have et naturligt forhold til søde sager og kost generelt. Hun har fed energi på at bryde med gamle mønstre og fornbinde til kroppens naturige stopklods ved overspisning. Overspisning af slik har stået på i 3,5 år.
B84: 21.10.25 | C84: Frieda Marie | E84: 22 97 02 96 | F84: friedamarie457@gmail.com | H84: Setter | O84: Mor er med, far skal overtales (17 år) | Q84: 6 | R84: https://slack-files.com/T08TMAAKCCU-F09PVMS2E06-28cc8ea496 | S84: Follow Up | T84: Snak med mor 8.30 lørdag. Overspisning og BED. Har været på efterskole hvor hun oplede hvordan struktur hjælper hende til at have det bedre og undgå overspisninger. Meget velreflekteret og ved hun spiser på stress eller svære følelser. 80/20% i forhold til mad. Mangler mest af at struktur og overblik. Vil gerne igang med træning i center + løb som hun har været så glad for. Vægttab på 5-8 kg. Føler der er momentumØnsker sig mere livsenergi og at kunne være mere social og tilpas i sin krop.
B85: 21.10.25 | C85: Amanda Jensen | E85: 51 54 79 36 | F85: amanda_jensen_36@hotmail.com | H85: Setter | I85: Offer & Didn't Buy | N85: Think About It | O85: Partner, money, tid | Q85: 6 | R85: https://slack-files.com/T08TMAAKCCU-F09QANDUM1P-a26d6d3eb5 | S85: Follow Up | T85: Follow up søndag. Varm på forløb. Skulle udfordre hendes perspektiv i forhold til at tage action. 2 børn, kæreste. Uddannelse i ernæring og sundhed. Kost: meget restriktiv spisning. alt eller intet. Har ingen stopknap og overspiser jævnligt - holder det hemmeligt og gemmer indpakninger fra hendes overspisning så står alene med det. Ønsker en støtte her hun kan tale med. Elsker chokolade og is. vil gerne lande et sted hvor der er balance og mental ro omkring mad. Oppustet, balance, rytme. På bar bund i forhold til overspisninger og redskaber?? Har stået på i 6 år. Går nu til psykolog og ønsker at prioritere sig selv efter to børn. Være den bedste udgave af sig selv også for dem. Vil gerne igang med at løbe igen. Vedvarende resultater. Bryde gammel spiral. Vedvarende positiv selvfølelse. Spejl, ro. Ofte træt og ked af det.
B86: 21.10.25 | C86: Cecilie Sørensen | E86: 25 36 66 52 | F86: ceciliesorensen25@gmail.com | H86: Setter | I86: No-Show

Sheet Nov
B1: Rep: | C1: Name | E1: Outcome | H1: KPIs% | K1: Show Rate | N1: Objections | Q1: Source | U1: Tracking
E2: Full-Pay: | F2: =IFERROR(COUNTIFS(I13:I287, "Full-Pay"),"") -> 4 | H2: Conversion Rate: | I2: =iferror(I10/I8,"") -> 0.51515152 | K2: Rescheduling Rate: | L2: =iferror(F8/I6,"") -> 0.024390244 | N2: Think About It | O2: =IFERROR(COUNTIFS(N13:N286, "think about it"),"") -> 2 | Q2: Reschedule | R2: =IFERROR(COUNTIF(H13:H286,Q2),"") -> 0 | S2: Cold Call | T2: =IFERROR(COUNTIF(H13:H286,S2),"") -> 0
B3: Revenue | C3: =IFERROR(SUM(K13:K283),"") -> 160500 | E3: Split-Pay: | F3: =IFERROR(COUNTIFS(I13:I287, "Split-Pay"),"") -> 13 | H3: Offer To Close Rate: | I3: =IFERROR(I10/I9,"") -> 0.51515152 | K3: Cancellation Rate: | L3: =iferror(F9/I6,"") -> 0.14634146 | N3: Money | O3: =IFERROR(COUNTIFS(N13:N286, "money"),"") -> 15 | Q3: YouTube | R3: =IFERROR(COUNTIF(H13:H286,Q3),"") -> 0 | S3: Twitter | T3: =IFERROR(COUNTIF(H13:H286,S3),"") -> 0
B4: Cash | C4: =IFERROR(SUM(L13:L284),"") -> 67500 | E4: Deposits: | F4: =IFERROR(COUNTIFS(I13:I287, "Deposit"),"") -> 3 | H4: Call To Offer Rate: | I4: =IFERROR(I9/I8,"") -> 1 | K4: No-Shows Rate: | L4: =iferror(F10/I6,"") -> 0.024390244 | N4: Time | O4: =IFERROR(COUNTIFS(N13:N286, "time"),"") -> 0 | Q4: YouTube Ads | R4: =IFERROR(COUNTIF(H13:H286,Q4),"") -> 0 | S4: Skool | T4: =IFERROR(COUNTIF(H13:H286,S4),"") -> 0
E5: Offer & Didn't Buy: | F5: =IFERROR(COUNTIFS(I13:I287, "Offer & Didn't Buy"),"") -> 13 | H5: Drag Over Rate: | I5: =IFERROR(F7/(C6+F7+F8),"") -> 0 | K5: Drag Over Rate: | L5: =iferror(F7/I6,"") -> 0 | N5: Partner | O5: =IFERROR(COUNTIFS(N13:N286, "partner"),"") -> 2 | Q5: Email | R5: =IFERROR(COUNTIF(H13:H286,Q5),"") -> 0 | S5: Instagram | T5: =IFERROR(COUNTIF(H13:H286,S5),"") -> 0
B6: Total Calls : | C6: =IFERROR(SUM(F2:F6),"") -> 33 | E6: Bad Fit & No Offer: | F6: =IFERROR(COUNTIFS(I13:I287, "Bad Fit & No Offer"),"") -> 0 | H6: Bookings: | I6: =IFERROR(SUM(F2:F10),"") -> 41 | K6: Show-Up Rate: | L6: =iferror(I7/I6,"") -> 0.80487805 | N6: Fear | O6: =IFERROR(COUNTIFS(N13:N286, "fear"),"") -> 5 | Q6: Facebook | R6: =IFERROR(COUNTIF(H13:H286,Q6),"") -> 0 | S6: TikTok | T6: =IFERROR(COUNTIF(H13:H286,S6),"") -> 0
B7: Total Won : | C7: =IFERROR(F2+F3,"") -> 17 | E7: Drag Over & Show: | F7: =IFERROR(COUNTIFS(I13:I287, "Drag Over & Show"),"") -> 0 | H7: Shows: | I7: =IFERROR(SUM(F2:F7),"") -> 33 | K7: Conducted Rate: | L7: =IFERROR(I8/I6,"") -> 0.80487805 | N7: Value | O7: =IFERROR(COUNTIFS(N14:N287, "value"),"") -> 0 | Q7: Facebook Ads | R7: =IFERROR(COUNTIF(H13:H286,Q7),"") -> 0 | S7: Google | T7: =IFERROR(COUNTIF(H13:H286,S7),"") -> 0
B8: Total Lost : | C8: =COUNTIF(I13:I286,"offer & didn't buy")+countif(I13:I286,"deposit")+countif(I13:I286,"bad fit & no offer") -> 16 | E8: Rescheduled: | F8: =IFERROR(COUNTIFS(I13:I287, "Rescheduled"),"") -> 1 | H8: Calls: | I8: =IFERROR(SUM(F2:F6),"") -> 33 | Q8: LinkedIn | R8: =IFERROR(COUNTIF(H13:H286,Q8),"") -> 0 | S8: Referral | T8: =IFERROR(COUNTIF(H13:H286,S8),"") -> 0
B9: Closing % : | C9: =iferror(SUM(C7/C6),"") -> 0.51515152 | E9: Cancelled: | F9: =IFERROR(COUNTIFS(I13:I287, "Cancelled"),"") -> 6 | H9: Offers: | I9: =IFERROR(sum(F2:F5),"") -> 33
E10: No-Show: | F10: =IFERROR(COUNTIFS(I13:I287, "No-Show"),"") -> 1 | H10: Deals | I10: =F2+F3 -> 17
B12: Date | C12: Name | E12: Phone No. | F12: Email | H12: Source | I12: Outcome | K12: Revenue | L12: Cash | N12: Objection | O12: Objection Notes | Q12: Length | R12: Recording Link | S12: Follow Up/Next Steps | T12: Call Summary
B13: 02.11.25 | C13: Oline Larsen | E13: 50 13 34 53 | H13: Setter | I13: Cancelled
B14: 03.11.25 | C14: Rie Viuf | E14: 26 36 81 32 | F14: rieviuf8@gmail.com | H14: Setter | I14: Offer & Didn't Buy | O14: PIF men mor annullerede aftalen samme dag | Q14: 6 | R14: https://slack-files.com/T08TMAAKCCU-F09QC3DQ03F-39033e0597 | S14: X | T14: 19 år til dec. Bor hjemme. Har tabt 30 kg. selv. Går i gym + arbejde. Færdig til sommer. Går til fodbold. Ønsker et vægttab på 10 kg. Alt eller intet. Sidder fast i spiral som har givet hende dårligt selvværd og selvtillid. Er blevet lidt bedre efter selv at have tabt 30 kg. på en knap så sund måde (restriktiv som ikke er holdbar). Bange for at tage det på igen hvis hun ikke får hjælp. Lægger særligt vægt på sit mindset. Ønsker at blive mere positiv. Vedvarende vaner. Føle sig tilpas i krop. Har overspisninger efterfuglt af ubehag og slå sig selv i hovedet. Tæner, men vil gerne have hjælp til træningsprogram.
B15: 03.11.25 | C15: Nadia Hvelplund | E15: 27 82 64 57 | F15: nadia92@live.dk | H15: Setter | I15: Offer & Didn't Buy | N15: Think About It | O15: Og penge | Q15: 6 | R15: https://slack-files.com/T08TMAAKCCU-F09QA2W2WAF-e051618709 | S15: X | T15: Lige skilt. Flyttet til ny by. Børn. Har investeret i flere forløb før. Kost: Mængder, forhold til mad, snacker, stabilitet, nemt, mæt, balance, inspiration. Træning: Rytme, hjemmetræning, strammet op - arme og bagdel. Muskelmasse. Vægttab: 4-5 kg. Mindset: Madro, mental ro, stress af. Vedvarende vaner.
B16: 04.11.25 | C16: Nishanthi Rasayogam | E16: 42 25 40 16 | F16: nishanthi.7@hotmail.com | H16: Setter | I16: Offer & Didn't Buy | O16: Startet andet forløb i går - følg op i januar | Q16: 6 | R16: https://slack-files.com/T08TMAAKCCU-F09QGLXF85R-be6ef25e3f | S16: Follow Up | T16: Gluten + laktose. Oppustet som plager hende hver dag - påvirker hvordan hun er socialt, indre uro og hvilket tøj hun tager på. Dårlig fordøjelse, forstoppelse relateret til hendes stress. Arbejder som pædagog på deltid efter stress-sygmelding. Humørsvingninger, glæder, træt, overskud - går op i mindset og mental ro. Mærke efter - kroppens signaler. Livskvalitet. Træning: gåture, fodbold, træningscenter. Vant til at være aktiv.
B17: 05.11.25 | C17: Ronja T. H. | E17: 40 62 62 89 | F17: ronjaht@gmail.com | H17: Setter | I17: Split-pay | K17: 9000 | L17: 4500 | N17: Fear | O17: Og penge | Q17: 6 | R17: https://slack-files.com/T08TMAAKCCU-F09QRALMPJ7-32b737542c | S17: Closed | T17: Atypisk spiseforstyrrelse. Kost: Madro uden systemer. Er bange for at skemer og planer "fodrer" hendes systemer. Mere intuiti spisning. Hyperfokus og gør det svært at tage ud at spise med veninder. Har i perioder meget travls som freelancer - travl vs meget rolige perioder. Træning: hjemmetræning + gåture. Ked af mave men vi snakkede om at mindset kommer før ønsket om at se anderledes ud. Man kan godt have et mål udadtil men det vigtigeste er hun finder fred med sin krop og føler sig tilpas i den uanset hvordan den ser ud. Stor frygt for at tage på. Kropshad. Tøj. Meget social hvilket også gør hende ængestelig. Sanseapparat - ønsker ikke at miste det og er glad for hendes fokus på krop (bortforklaring af hyperfokus og stress omring sin egen fremtræden). Acceptere kroppen. Uden regnskab. Lære at tage pauser uden at skulle kompensere for det senere. Håndtere svære perioder uden motivation.
B18: 05.11.25 | C18: Jasmin Nilsson | E18: 23 10 10 90 | F18: jasminecobbynilsson@gmail.com | H18: Setter | I18: Offer & Didn't Buy | N18: Money | O18: 18 år, gym uden arbejde. Får 1000 kr i SU pr måned. Har opsparing | Q18: 6 | R18: https://slack-files.com/T08TMAAKCCU-F09QT8W6VQB-ae2ade9f0f | S18: X | T18: Kost: spiser ikke kød. Snacker en del. Føler sig oppustet. Træning: Firtnesscenter + hjemmetræning. Har brug for et program og en plan så hun kan finde en i en god rutine. Mere muskelmasse og mere tonet. Apps. Træning 2 gange i ugen. Mindset: Selvværd, positive tanker om krop. Søvn! Dårlig samvittighed og indre uro. Mangler motivation og viden - hænger sammen for hende. Gym. 18 år. Bor hjemme.
B19: 06.11.25 | C19: Emma Odgaard | E19: 61 73 42 12 | F19: emmaodgaard2004@gmail.com | H19: Setter | I19: Full-Pay | K19: 9000 | L19: 9000 | N19: Fear | O19: Forældre | Q19: 6 | R19: https://slack-files.com/T08TMAAKCCU-F09RM1UEDQR-d45bc850d6 | S19: Closed | T19: Har haft anoreksi. Århus. Uni, Jura. Kost: Balance. Protein. Næring. Madro. Træning: tonet. Styrke. Gåture (går lange ture og elsker det) hjemmetræningsprogram. Mindset: ønsker at finde fred med sin krop og føle sig godt tilpas i den. Bedre livsstil. Glæde ved krop. Balance i vaner. Ustabilitet. Kan være meget plaget af at vælge tøj og fravælger nogle gange sociale sammenkomster fordi det bliver for overvældende for hende at finde tøj hun føler sig tilpas i. Spejl. Hjemme i krop. Selvværd. Humør. Negative tanker. Vedholden. Alt eller intet. Har kæmpet med det i 2 år kan ikke finde balancen selv. Vil meget gerne i forløb og skabe positive ændringer men har svært ved at løsrive sig fra forældre - deres mening er vigtig for hendes beslutning. Snakkede vi en del om.
B20: 06.11.25 | C20: Frederikke R. Sørensen | E20: 42 43 95 75 | F20: frederikkesorensen@icloud.com | H20: Setter | I20: Full-Pay | K20: 9000 | L20: 9000 | Q20: 6 | R20: https://slack-files.com/T08TMAAKCCU-F09RM2FJRS5-6602d5a283 | S20: Closed | T20: Frederikke har i to år forsøgt at tabe sig og holde vægten stabil, men ender i alt eller intet og følelsen af at skulle begynde forfra. Tæller kalorier og vil gerne væk fra det. Madro. Tilpas i krop. Bæredygtige vaner. Lige påbegyndt morgenrutine fordi hun gerne vil skabe positive forandringer. Træning: Tonet, muskelmasse - primært center, måske hjemmetræning. Gåture. Synes det er rart der bliver taget udganspunkt i mindset. Mere selvsikker. Manger støtte og styrke selvfølelsen. Vægttab: 10-15 kg.
B21: 06.11.25 | C21: Freida Marie de Groot | E21: 22 97 02 96 | F21: friedamarie457@gmail.com | H21: Setter | I21: Split-pay | K21: 10500 | O21: Forældre | Q21: 6 | R21: Sidste måned | S21: Closed
B22: 07.11.25 | C22: Isabella Rosendal | E22: 21 81 01 06 | F22: isabella.lynghoj@gmail.com | H22: Setter | I22: Split-pay | K22: 10500 | L22: 3000 | Q22: 6 | R22: https://slack-files.com/T08TMAAKCCU-F09RUJW94F3-f2ffeb83f8 | S22: Closed | T22: Har i 7 år følt sig utilpas i krop. Holder hende tilbage fra at handle og være udadvendt i sociale sammenhænge - Tøj. Struktur. Tage rette skridt man ved virker, uden at fumle med det selv og få tilbagefald. Mindset: spiser på følelser, har mange negative tanker om krop. Ønsker at blive mere selvsikker. Kost: struktur. Overspiser - fysisk ubehag og slå i hovedet. Tvivl i forhold til hvordan hun skal spise fylder meget for hende hver dag. Høj prioritet at være sund og stærk. Træning: Tonet, hjemmetræning, rytme. mave og arme. Sidder fast i spiral. Brug for støtte og viden. Klar NU. motivation for ændringer.
B23: 07.11.25 | C23: Sophia Nørgaard | E23: 21 37 60 94 | F23: sophiaest@outlook.dk | H23: Setter | I23: Split-pay | K23: 10500 | L23: 3000 | Q23: 6 | R23: https://slack-files.com/T08TMAAKCCU-F09RD5JENVB-1fe21a97af | S23: Closed | T23: Har de sidste 4 år forsøgt at nå i mål med den krop hun ønsker sig. sabatår, hjemmeplejen. Kost: oppustet. overspiser om aftenen. Sundt forhold til kost. Mere viden og balance. Protein. inspiration. mealprepping til skæve arbejdstider. Går til reformer. Hjemmetræningsprogram. Strammet op. Særligt arme, ansigt, mave. Teknik og øvelser. Ønsker at føle sig 100% tilpas i krop! tvivl om hvordan hun skal gøre - hvad er sundt og usundt? spiral. Mental ro og madro. Mere selvtillid. Mad fylder meget mentalt.
B24: 07.11.25 | C24: Camilla Maarup | E24: 40 31 97 07 | F24: camilla4031@gmail.com | H24: Setter | I24: Full-Pay | K24: 9000 | L24: 9000 | Q24: 6 | R24: https://slack-files.com/T08TMAAKCCU-F09RAN537U3-5fe5c87783 | S24: Closed | T24: Vægttab: 20 kg. Fodbold. Sygeplejestuderende. Har ønsket at tabe sig 7+ år. Kosten er den sværeste for hende: Nemt, overskueigt, inspiration og glæden ved at lave mad. Lige nu køber hun meget take out og tager de nemme, usunde løsninger. Sundhedsaspekt - overvægtige forældre. Selvbillede - slår sig selv i hovedet. spejl. tøj. sammenligner. Tage flere gode valg og sige nej tak.
B25: 09.11.25 | C25: Alma Hartmann-Pedersen | E25: 60 51 79 30 | F25: ahartped@gmail.com | H25: Setter | I25: Offer & Didn't Buy | N25: Fear | O25: Vi snakkede direkte om hendes midnset og lysten til at udsætte igen | Q25: 6 | R25: https://slack-files.com/T08TMAAKCCU-F09SM1SM00Y-674717e5f7 | S25: X | T25: Har spillet meget håndbold, men er nu blevet skadet. Har ikke spillet i 4 måneder. Stor omvæltning og har nu brug for at finde ind i rutiner som fungerer godt for hende. Kost: Overspiser og snacker på følelser og kedsomhed. Rytme, balance. Vil gerne have en plan hun kan forholde sig til så det ikke skal fylde mentalt for hende. Har udskudt længe og føler der er momentum nu. Har siddet fast i 1 år. Træning: Ønsker at knække koden til motivation - hvordan griber hun det an i svære perioder. Træningsplan til fitnesscentret. Løb: ønsker struktur på løb (har skinnebensbetændelse). Dårlige tanker om selv, tilpas i krop, træt, energi. Mindset: motivation, styre tanker.
B26: 09.11.25 | C26: Mathilde Bøgelund Elmose | E26: 93 89 00 17 | F26: matelmose@outlook.dk | H26: Setter | I26: Offer & Didn't Buy | N26: Money | O26: Forældre | Q26: 6 | R26: https://slack-files.com/T08TMAAKCCU-F09RSNE41PU-207aa33b64 | S26: X | T26: Kost: tracker mad og bliver helt panisk hvis hendes trackerapp ikke virker. Tryghed og kontrol. Overspiser og snacker meget. Alt eller intet. Balance. Madro. Nævner mindset flere gange - at det er her den langvarige forandring sker for hende. Træning: har ok styr på træningen (3 gange i ugen). Men vægten stiger mere og mere, og det skal stoppes nu. Har stået på i 3 år. Bruger meget energi på at tænke over tøj og føle sig utilpas på daglig basis. Ønsker mere selvkontrol og har mange negative tanker. Vægttab: 10 kg. Stabil vægt.
B27: 10.11.25 | C27: Julie Nielsen | E27: 30 64 60 55 | F27: julle32@icloud.com | H27: Setter | I27: Split-pay | K27: 10500 | L27: 1500 | N27: Money | O27: SU | Q27: 6 | R27: https://slack-files.com/T08TMAAKCCU-F09RWP9T39Q-9a845adceb | S27: Closed | T27: Ved at blive udredt for ADHD. Har svært ved at sætte struktur på sin hverdag - glæden ved at lave mad. Nemt, overskueligt, tid, balance, rytme. Meal preppe (billigere løsninger) Kræsen. Træning: Vil gerne i form, løb, struktur og en klar plan. Hjemmetræning. Vægttab 5 kg. Har haft stress for 6 måneder siden. Svært ved at komme tilbage. Forbinde til krop. Selvstændighed. Mindset: mere ro, regulere nervesystemet - dårlig samvittighed "burde gøre noget". Har svært ved at tage pause med god samvittighed.
B28: 10.11.25 | C28: Mathilde Jepsen | E28: 36 21 44 03 | F28: mathildejepsen205@gmail.com | H28: Setter | I28: Offer & Didn't Buy | N28: Money | Q28: 6 | R28: https://slack-files.com/T08TMAAKCCU-F09SCAQ455X-38a790eb13 | S28: X | T28: Besluttede sig for 1 år siden at gøre noget drastigt ved sin situation - vægttab: 20 kg. Træner 5-6 gange i fitness. Kan ikke finde ud af at balancere sin kost - sundt, nærende, mæt, plan, struktur - spiser meget forarbejdet mad der bliver serveret på hendes kollegie (burger, hotdogs) Ønsker at blive tilpas i sin krop. Mere energi.
B29: 11.11.25 | C29: Signe Johanne | E29: 25 11 84 42 | F29: signespaanhede@gmail.com | H29: Setter | I29: Split-pay | K29: 10500 | L29: 3000 | Q29: 6 | R29: https://slack-files.com/T08TMAAKCCU-F09SKHSEQQZ-93e001a13c | S29: Closed | T29: Har haft coach før. ADHD. Medicin gør at hun mister apetitten og glemmer at spise. Spiseforstyrrelse/meget kræsen! Har altid enten forstoppelse eller det modsatte. Altid oppustet. Træning: Muskelmasse. Usikkerhed i forhold til øvelser i træningscentret. Vil gerne igang med løb for god kondition. Har speciale næste år og er bange for ikke at præstere grundet manglende struktur, motivation. Kommer ikke særlig ofte til forelæsninger. Kan ikke holde fast. Påvirker hvem der gider hende på studiet - ensom. Ønsker at blive mere selvstædnig. 5 år har det stået på. Vil leve livet fuldt ud.
B30: 11.11.25 | C30: Mine Avci | E30: 42 34 57 17 | F30: mine-avci@live.dk | H30: Setter | I30: Split-pay | K30: 10500 | L30: 3000 | Q30: 6 + | R30: https://slack-files.com/T08TMAAKCCU-F09T1BH457A-18615508ab | S30: Closed | T30: 27. Sygeplejerske - har gået på politiskolen. Har været i god form. For 2 år siden gik det ned af bakke. fuld drøn på karierre glemte sig selv. Høj prioritet for hende at have en sund krop. Kost: overspiser, snacker. Rytme. Balance. Protein, næring, oppustet. Træning: hjemmetræning hun let kan gå til. Meget travl hverdag har altid gang i noget. Vil gerne tabe sig og øge muskelmasse. Har dårlig søvn - sover 5 timer. Mere ro omkring kost og vaner. Virkelig gået ned af bakke de sidet 6 måneder - slut! Har flere venner som er coaches men har brug for sin egen proces. Mangler generelt bare motivation og struktur.
B31: 12.11.25 | C31: Emilie Nielsen | E31: 42 75 26 73 | F31: emilie.8840@gmail.com | H31: Setter | I31: Offer & Didn't Buy | N31: Money | O31: Ghostet | Q31: 6 + | R31: Ingen (IG-call) | S31: X | T31: Vejer 105 kg. Vil gerne tabe omkring de 30 kg. Svær fortid med grov mobning (politi involveret) Hendes mor døde for 2 måneder siden og de talte om at hun skulle få den krop hun altid havde ønsket sig. Kost: Spiser på følelser, køber meget mad. Træning: Gåture + hjemmetræning. Mangler en der holder hende accounteble når hun falder i. Kun dårlige tanker om sig selv og sin krop. Mindset: bedre selvværd. Har stået på i 10 år.
B32: 14.11.24 | C32: Eja Littau | E32: 28 49 85 13 | F32: ejajb007@gmail.com | H32: Setter | I32: Full-Pay | K32: 9000 | L32: 9000 | N32: Partner | Q32: 6 | R32: https://slack-files.com/T08TMAAKCCU-F09T2L5ALG6-4668f89162 | S32: Closed | T32: Ring om et par måneder. Kost: Vegetar. elsker søde sager - alternativer. Tytme. Mangler kropsbevidsthed - kan ikke mærke sin mæthedsfornemmelse. Står midt i flytning fra kbh til odense med kæresten. Jobskifte og husrenovering. Ser det hele som en ny start og mulighed for at ændre sit liv. Træning: Rutine, øvelser, teknik, fitnesscenter. Måske starte til dans. Mindset: Stress. selvtillid - nogen der holder hende accounteble og lærer hende hvordan hun holder aftaler med sig selv + motivation i svære perioder. Tid til at passe på sig selv - ansvar. Fremtidige børn og livsstil. Stået på i 6 måneder. Gemmer spisning og skammer sig af og til. Tøj. Undgår spejle. påvirker hendes forhold. Vægttab.
B33: 14.11.25 | C33: Aya Safad | E33: 42 75 57 28 | F33: aya.abdullrahim@hotmail.com | H33: Setter | I33: Split-pay | K33: 10500 | L33: 1500 | N33: Partner | O33: Penge - SU | Q33: 6 | R33: https://slack-files.com/T08TMAAKCCU-F09T2LBTCKE-f44ef96286 | S33: Closed | T33: 2 børn + mand. Går på uni. Haft depression og stress. Ked af hvordan hun ser ud. Fylder meget hver dag. Har ikke lyst til at vise sig på uni grundet sit udseende. Føler hun er blevet for stor. Har stået på i 6 år. Kost: viden, mængder, mæthedsfølelse. Mindset: Selvbillede, selvtillid. Pauser og hvile. Træning: træner slet ikke. Vil gerne igang. Motivation. Fitnesscenter 1 gang i ugen + hjemmetræning for fleksibel træning - rytme. Vægttab 10-15 kg. NU. På SU. vi aftale udenom mand så hun selv styrer økonomien.
B34: 14.11.25 | C34: Milla Marie Tarp | E34: 28 30 93 29 | F34: millapoulsenn@gmail.com | H34: Setter | I34: Split-pay | K34: 10500 | L34: 3000 | Q34: 6 | R34: https://slack-files.com/T08TMAAKCCU-F09SZF1BJRG-861d26d04d | S34: Closed | T34: Vægttab: 5 kg. Træning: muskelmasse, hjemmetræning. mave og lår, tonet. Kost: springer måltider over fordi hun ønsker at tabe sig. Ønsker at lære mere om kostsammensætning og finde en god rytme så hun kan nå i mål med den krop hun ønsker sig. Mindset: selvsikker. motivation. energi. gladere. VIl ikke udsætte mere. søvn. har stået på i et år. 17 år.
B35: 17.11.25 | C35: Isabella Geertsen | E35: 53 37 87 83 | F35: igeertsen@outlook.dk | H35: Setter | I35: Split-pay | K35: 10500 | L35: 3000 | N35: Fear | O35: Og penge | Q35: 6 | R35: https://slack-files.com/T08TMAAKCCU-F09TUNQMNHF-04ff94bddb | S35: Closed | T35: Vægttab: 20 kg. Har hele livet altid været hende den store veninde og familiemedlem som hun er træt af og som er en del af hendes identitet. Er blevet mobbet en del. Vi brugte meget tid på at snakke om hendes tidligere forløb hos en coach (af to omgange) da det tydeligvis har givet hende frygt for om hun kan nå i mål. Var ret overrasket over at der kunne tages udgangspunkt i hende og de behov hun har i stedet for at få restriktive planer hun skulle overholde. Endte i gamle forløb med at have bokse med mad alle steder da hun var bange for at spise uden for planen og slog sig selv i hovedet når hun gjort. Evigt regnskab. Der var lidt money i begyndelsen, men brugte framet at hun først og fremmest skulle føle forløbet var anderledes end det hun havde prøvet før, og noget der kunne få hende i mål. Så skulle vi nok finde løsning på alt det praktiske. Spiser meget på følelser - mængder/overspiser. Hader spejle. Tænker på krop, vaner og sundhed 80% af sin tid. Fylder meget for hende og påvirker de valg hun tager.
B36: 18.11.25 | C36: Isabella Abkjær | E36: 42 73 83 25 | F36: abkjaer.isabella@gmail.com | H36: Setter | I36: Offer & Didn't Buy | N36: Money | O36: 16 år. Mor holder kort til opsparing | Q36: 6 | R36: https://slack-files.com/T08TMAAKCCU-F09UTBSV1H6-810f1ed52e | S36: X | T36: 1,5 år taget på. Vægttab 10 kg. Føler sig meget utilpas i krop og har ikke lyst til at bruge mere tid på den måde. Har prøvet meget selv, sultet sig selv meget, for at tabe sig, men tager bare mere på. Snacker sig gennem dagen med usunde ting. Mangler rytme, balance i kosten. Træning: har ikke trænet i noget tid grundet manglende motivation og struktur. Vil gerne igang igen - ben og mave. Mindset: Ro i hovedet, selvtillid, komforbabel og selvværd. Mangler overskud. Tøj. Ked af det. 16 år. Vi taler ind i fremtidsperspektiv - hvad det kunne give hende at nå sit mål og skabe et sundt, solidt fundament. Mor døjer selv med vægt og ønsker Isabella får hjælp (vil gerne støtte økonomisk). Virker meget klar til at komme igang nu og siger flere gange hun er indstillet på det bliver hårdt, men det er det der skal til nu.
B37: 18.11.25 | C37: Hezra Malik | E37: 53 31 70 09 | F37: hezra1990@hotmail.com | H37: Setter | I37: Split-pay | L37: 3000 | N37: Fear | O37: Tid. Prøvet forløb før. Mange spørgsmål. Kontrol. Vil starte på en måned. | Q37: 1+ | R37: https://slack-files.com/T08TMAAKCCU-F09TZ2BHMEW-780fff9b95 | S37: Closed | T37: Meget frygt for commitment hvilket jeg gik ind i helt i starten af kaldet og adresserer flere gange i løbet af vores snak. Forsøger at få vendt hendes perspektiv, og til sidst vil hun gerne forkorte de 6 måneder hvilket vi også tager en snak om - hvorfor har hun det behov for at have en god ude, og hvad der fordelene ved at committe sig og gå all in på alle månederne. Har været i forløb før som ikke virkede. Barn på 1 + mand. Ikke meget tid. Vi snakker om at hun helst skulle spare en masse tid og energi ved at få overblik og støtte. Har siddet fast i 8 år. meget brug for kontrol. Havde mange spørgsmål - jeg blev ved med at spørge om der var andet hun havde behov for at få afklaret for at have ro i maven. Det fungerede ret godt og tonen endte med at være meget positiv. Gik ind i partner objection både i begyndelsen og slutningen. Tvivl. Mindset i forhold til at tage en chance så hun kan ændre sin situation. Mindset: det primære fokusområde er hendes forhold til mad. Dårlig cyklus af over- og underspisning. Meget motiveret for at træne. Vi snakkede om hviledage og overtærning bunder i en frygt for at tage på. Balance i kost - stabil mæthed for mere energi.
B38: 19.11.25 | C38: Clara Lind | E38: 26 27 80 79 | F38: claralindc@gmail.com | H38: Setter | I38: Offer & Didn't Buy | N38: Money | O38: Forældre - beslutningsproces | Q38: 6 | R38: https://slack-files.com/T089JBRTVMM-F09UUNC0SQY-5eab6ba462 | S38: Follow Up | T38: Snakkes ved i februar - kærste skulle flytte til udlandet så måske penge på rejser kommer til at fylde meget + hun ville give det et skud selv. Arbejder på folkeskole. Sabatår. Bor hjemme. Kæreste som støtter hende. Har siddet fast i mønster i 2 år. Har svært ved at overholde aftaler med sig selv og tage beslutninger hvilket jeg udfordrede hende en helt del på - at det netop starter i dag og hvordan det ville føles for hende at stå stærkt i sig selv omkring beslutnignen af gøre det her for sig selv uden andres approval. Føler sig ikke tilpas i krop - ked af det. Tøj. Sammenligner. Kost: Snacker og overspiser. Mere balance, meal prepping, rytme. Træning: Smide lidt fedt og bygge muskelmasse - fitnesscenter + hjemmetræning. alt eller intet. Mindset: dårlig samvittighed, selvaccept, aftaler med sig selv. Hele familien og bedsteforældre er meget aktive! Føler ikke helt hun passer ind lige nu.
B41: 03.11.25 | C41: Freja Aunbøl Futtrup | E41: 21 96 75 85 | F41: freja.futtrup@gmail.com | H41: Setter | I41: Cancelled | O41: Vil selv række ud når behovet opstår
B42: 05.11.25 | C42: Anette Jakobsen | E42: 42 57 29 80 | F42: jakobsenanette75@gmail.com | H42: Setter | I42: Cancelled
B43: 06.11.25 | C43: Emma Jensen | E43: 25 75 14 19 | F43: 2710emma@gmail.com | H43: Setter | I43: Cancelled
B44: 11.11.25 | C44: Michelle Rosenlund | E44: 22 24 70 89 | F44: michelrosenlund@gmail.com | H44: Setter | I44: Cancelled
B45: 12.11.25 | C45: Karina Leonard Haugaard | E45: 28 11 37 57 | F45: karina.haugaard@hotmail.com | H45: Setter | I45: Cancelled
B47: 20.11.25 | C47: Victoria Blomstrand | E47: 60 74 91 88 | F47: victoriablomstrand@gmail.com | H47: Setter | I47: Offer & Didn't Buy | N47: Money | O47: Hjemmeboende SU | Q47: 6 | R47: https://slack-files.com/T08TMAAKCCU-F09UBA83SUC-d16f292d83 | S47: Follow Up | T47: 19 år. Håndbold 3 gange i ugen. Har siddet fast i et år. Kost: overspiser på følelser og har altid gjort det. Føler sig meget træt og utilpas i sin krop. Træning: vil gerne styrketræne og have mere muskelmasse - hjemmetræning. Mindset: stress, indre ro, forbinde til sult og mæthed, positive tanker om sig selv. Jeg havde svært ved at få hende helt ned i pain. Samtalen blev mere overfladisk end normalt.
B48: 20.11.25 | C48: Katrine Hjort | E48: 42 19 01 01 | F48: katrine.h.j@outlook.dk | H48: Setter | I48: Split-pay | K48: 10500 | L48: 1500 | N48: Money | O48: Sygemeldt | Q48: 6 | R48: https://slack-files.com/T08TMAAKCCU-F09U8R52E90-91de8ac657 | S48: Closed | T48: x-misbruger. Stadig i AA. Har haft spiseforstyrrelse, selvskadende adfærd. Ønsker støtte til at finde indhold og sunde rutiner i sin hverdag. Har aldrig haft balance i sit liv og ønsker nu at finde rytmen og bygge sig selv op. Mental ro. Madro. Træning: fastlagt plan, styrketræning, muskelmasse. Handling - ikke mere på mandag. Bange for tilbagefald. Ønsker at blive i stand til at overholde aftaler med sig selv. Meget motiveret. Aftalt jeg ringer til hende om 2-3 måneder og hører hvordan det går.
B49: 23.11.25 | C49: Therese Luchau | E49: 53 80 41 57 | F49: thereseluchau1995@gmail.com | H49: Setter | I49: Rescheduled | O49: I tog på vej hjem fra Jylland. Kunne ikke nå det.
B50: 24.11.25 | C50: Therese Luchau | E50: 53 80 41 57 | F50: thereseluchau1995@gmail.com | H50: Setter | I50: Deposit | N50: Money | O50: Opstart d. 1. jan grundet økonomi | Q50: 6 | R50: https://slack-files.com/T08TMAAKCCU-F09UWEAFQNS-a5b1836038 | S50: Closed | T50: Kost: Hopper over måltider og køber ofte usunde, nemme løsninger på farten. Føler sig meget træt og energiforladt og ender mest af alt på sofaen. Rytme, overskueligt, meal preppe i weekender, alternativer til søde sager, billig, balance. Træning: Starter ud med hjemmetræningsprogram men vil gerne i fitnesscenter på sigt. Muskelmasse og styrke. Mindset: Alt eller intet-mentalitet. siddet fast i 1 år. Har udsat så mange gange. Klar på at det skal være nu og ikke efter nytår. Elevatorvægt.
B51: 24.11.25 | C51: Nina H. Kirkbak | E51: 31 51 95 03 | F51: ninakirkbak@gmail.com | H51: Setter | I51: Deposit | N51: Money | O51: Opstart d. 1. dec - intet problem med betaling derfra (synes det var en mega god pris!) Skrev med Olivia på IG at hun ikke ville starte i forløb. | Q51: 6+ | R51: https://slack-files.com/T08TMAAKCCU-F0A0ATFRJ00-1bcce40b99 | S51: X | T51: Har sagt ja til opkald om en måned og ser hvordan det går. Vægttab på 20 kg. Meget motiveret! Jeg brugte meget tid på at snakke om handling nu, og hvorfor hun var klar til at skabe forandring i dag. Urgency, Tog en beslutning i mandags om at starte på kur så hun kunne tabe sig. Har vejet 57 kg. for 15 år siden. 2 børn. Skilsmisse nu ny kæreste som støtter hende i forløbet/forandringen. Kost: ikke restriktiv. Balance. Oppustet. Træning: Overskueligt program til hjemme og fitnes. Gåture. På sigt løb - meget motiveret for at nå dertil igen! Holdbare vaner der føles naturligt. Madro. Ikke tælle. Har meget tvivl i forhold til hvad der virker hvilket jeg brugte som primær salgsargument. Føler det skred for 6 måender siden og er røget helt af sporet nu. Føle sig god tilpas i krop
B52: 26.11.25 | C52: Isabella Haas | E52: 81 75 10 56 | F52: ihaasbornand@gmail.com | H52: Setter | N52: Money | O52: SU - Frygt fylder en del | Q52: 6 | R52: https://slack-files.com/T08TMAAKCCU-F0A0UJJB84Q-f4fe10f895 | S52: Follow Up | T52: Meget ængstelig. indtager meget sukker og kaffe. Kost: oppustet, balance, sundere, tid - nemt, protein. Stabil. Træning: Fitness + hjemmetræning - styrketræning. Primært fokus på kost. Dårlig søvn. VIl gerne forbedre sit fysiske og mentale helbred. Kronisk træt. Mindset: mental ro. angst, depression, motivaion. Udskudt længe. Vil gerne passe bedre på sig selv nu. Går på uni/SU.
B53: 26.11.25 | C53: Celina Pedersen | E53: 60 48 47 53 | F53: celinapedersen040@gmail.com | H53: Setter | I53: Split-pay | K53: 10500 | L53: 1500 | N53: Money | O53: Opstart d. 1. jan | Q53: 6 | R53: https://slack-files.com/T08TMAAKCCU-F0A0D7KU9JM-5df7ac9675 | S53: Closed | T53: 18 år. vil gerne nå i mål før studenterkørsel til sommer. Kost: snacker meget, rytme, balance, hopper over måltider og ender med overspisning. Mangler inspiration til sund kost. Træning: Meget usikker på hvad der virker. Mangler hjælp til teknik og en klar plan. Tonet krop. Særligt maven er hun ked af. At hun føler sig utilpas i sin krop stjæler hendes nærvær med sine venner. Sidder fast i dårlig spiral. selvsikker. Fedt på mave.
B54: 26.11.25 | C54: Vigga Meng | E54: 93 89 32 20 | F54: viggahmeng@outlook.dk | H54: Setter | I54: Offer & Didn't Buy | N54: Money | O54: 2. g med hjemmeboende SU | Q54: 6 | R54: https://slack-files.com/T08TMAAKCCU-F0A00Q8B6BU-7f6ce7a111 | S54: X | T54: 18 år. Kost: oppustet. Rytme, mængder, struktur. Mindre vægttab på 3 kg. Mere tonet krop. Både hjemmetræning og fitness. Mave og hofter for store hvilket gør hende meget usikker på sig selv. Tøj. Meget træt - mangler energi. Har højcostal vejrtræning - snakker om stress. Mindset: fejlfinder, negative tanker om selv. Motivation. Fremtidsperspektiv - sundhed.
B55: 27.11.25 | C55: Maria Catarina Søgaard | E55: 21 34 86 70 | F55: soegaard.m@gmail.com | H55: Setter | I55: Deposit | N55: Think About It | O55: Follow up: Vil gerne igang fra 1. januar | Q55: 6 | R55: https://slack-files.com/T08TMAAKCCU-F0A01M5GU9Z-ca99f8a29c | S55: Follow Up | T55: Stewardese - brug for fleksible løsninger både i forhold til kost og træning. Har et stort ønske om en brystreduktion som forudsætter hun taber 7 kg. Vil gerne tabe 10. Det har stået stille længe og hun kan ikke finde ind i rutinerne igen + manger motivation og struktur. Nævner flere gange i kaldet at hun mangler viden og vejledning i forhold til hvad der faktisk virker. Har været på rette vej med træning og kost hvor hun så en forskel for et år siden, men kan ikke komme tilbage og ved egentlig heller ikke præcis hvad der virker. Hun er ofte ude at rejse og har lange arbejdsdage hvor de spiser ude. Hjælp til at tage bedre valg. Synes forløbet virker meget attraktivt for hende fordi det er skræddersyet og fleksibelt. Har prøvet forløb før for 7 år siden som hun mistede motivationen for efter 2 måneder.
B56: 27.11.25 | C56: Sanne Veda-Nielsen | E56: 29 31 65 47 | F56: sanne.veda@gmail.com | H56: Setter | I56: No-Show
B57: 27.11.25 | C57: Lathusana | E57: 60 54 91 25 | F57: lathusanaa@gmail.com | H57: Setter | I57: Offer & Didn't Buy | N57: Money | O57: 17 år. Økonomi, men opsparing | Q57: 6 | R57: https://slack-files.com/T08TMAAKCCU-F09V6KBB1QX-7e118a8d2c | S57: X | T57: Vægttab: 10-15 kg. Mangler en plan. Ved ikke hvordan hun skal gøre. Overspiser. Oppustet. Dårlig samvittighed. Tøj, spejl. Struktur og vaner. Vil gerne i træningscentret og måske starte løb på sigt. Utilpas i krop. Jeg øvede mit double down og lagde ekstra vægt på pain i kaldet.

Sheet Dec
B1: Rep: | C1: Name | E1: Outcome | H1: KPIs% | K1: Show Rate | N1: Objections | Q1: Source | U1: Tracking
E2: Full-Pay: | F2: =IFERROR(COUNTIFS(I13:I287, "Full-Pay"),"") -> 2 | H2: Conversion Rate: | I2: =iferror(I10/I8,"") -> 0.54545455 | K2: Rescheduling Rate: | L2: =iferror(F8/I6,"") -> 0 | N2: Think About It | O2: =IFERROR(COUNTIFS(N13:N286, "think about it"),"") -> 0 | Q2: Reschedule | R2: =IFERROR(COUNTIF(H13:H286,Q2),"") -> 0 | S2: Cold Call | T2: =IFERROR(COUNTIF(H13:H286,S2),"") -> 0
B3: Revenue | C3: =IFERROR(SUM(K13:K283),"") -> 60000 | E3: Split-Pay: | F3: =IFERROR(COUNTIFS(I13:I287, "Split-Pay"),"") -> 4 | H3: Offer To Close Rate: | I3: =IFERROR(I10/I9,"") -> 0.54545455 | K3: Cancellation Rate: | L3: =iferror(F9/I6,"") -> 0.35294118 | N3: Money | O3: =IFERROR(COUNTIFS(N13:N286, "money"),"") -> 5 | Q3: YouTube | R3: =IFERROR(COUNTIF(H13:H286,Q3),"") -> 0 | S3: Twitter | T3: =IFERROR(COUNTIF(H13:H286,S3),"") -> 0
B4: Cash | C4: =IFERROR(SUM(L13:L284),"") -> 25500 | E4: Deposits: | F4: =IFERROR(COUNTIFS(I13:I287, "Deposit"),"") -> 0 | H4: Call To Offer Rate: | I4: =IFERROR(I9/I8,"") -> 1 | K4: No-Shows Rate: | L4: =iferror(F10/I6,"") -> 0 | N4: Time | O4: =IFERROR(COUNTIFS(N13:N286, "time"),"") -> 0 | Q4: YouTube Ads | R4: =IFERROR(COUNTIF(H13:H286,Q4),"") -> 0 | S4: Skool | T4: =IFERROR(COUNTIF(H13:H286,S4),"") -> 0
E5: Offer & Didn't Buy: | F5: =IFERROR(COUNTIFS(I13:I287, "Offer & Didn't Buy"),"") -> 5 | H5: Drag Over Rate: | I5: =IFERROR(F7/(C6+F7+F8),"") -> 0 | K5: Drag Over Rate: | L5: =iferror(F7/I6,"") -> 0 | N5: Partner | O5: =IFERROR(COUNTIFS(N13:N286, "partner"),"") -> 0 | Q5: Email | R5: =IFERROR(COUNTIF(H13:H286,Q5),"") -> 0 | S5: Instagram | T5: =IFERROR(COUNTIF(H13:H286,S5),"") -> 0
B6: Total Calls : | C6: =IFERROR(SUM(F2:F6),"") -> 11 | E6: Bad Fit & No Offer: | F6: =IFERROR(COUNTIFS(I13:I287, "Bad Fit & No Offer"),"") -> 0 | H6: Bookings: | I6: =IFERROR(SUM(F2:F10),"") -> 17 | K6: Show-Up Rate: | L6: =iferror(I7/I6,"") -> 0.64705882 | N6: Fear | O6: =IFERROR(COUNTIFS(N13:N286, "fear"),"") -> 3 | Q6: Facebook | R6: =IFERROR(COUNTIF(H13:H286,Q6),"") -> 0 | S6: TikTok | T6: =IFERROR(COUNTIF(H13:H286,S6),"") -> 0
B7: Total Won : | C7: =IFERROR(F2+F3,"") -> 6 | E7: Drag Over & Show: | F7: =IFERROR(COUNTIFS(I13:I287, "Drag Over & Show"),"") -> 0 | H7: Shows: | I7: =IFERROR(SUM(F2:F7),"") -> 11 | K7: Conducted Rate: | L7: =IFERROR(I8/I6,"") -> 0.64705882 | N7: Value | O7: =IFERROR(COUNTIFS(N14:N287, "value"),"") -> 0 | Q7: Facebook Ads | R7: =IFERROR(COUNTIF(H13:H286,Q7),"") -> 0 | S7: Google | T7: =IFERROR(COUNTIF(H13:H286,S7),"") -> 0
B8: Total Lost : | C8: =COUNTIF(I13:I286,"offer & didn't buy")+countif(I13:I286,"deposit")+countif(I13:I286,"bad fit & no offer") -> 5 | E8: Rescheduled: | F8: =IFERROR(COUNTIFS(I13:I287, "Rescheduled"),"") -> 0 | H8: Calls: | I8: =IFERROR(SUM(F2:F6),"") -> 11 | Q8: LinkedIn | R8: =IFERROR(COUNTIF(H13:H286,Q8),"") -> 0 | S8: Referral | T8: =IFERROR(COUNTIF(H13:H286,S8),"") -> 0
B9: Closing % : | C9: =iferror(SUM(C7/C6),"") -> 0.54545455 | E9: Cancelled: | F9: =IFERROR(COUNTIFS(I13:I287, "Cancelled"),"") -> 6 | H9: Offers: | I9: =IFERROR(sum(F2:F5),"") -> 11
E10: No-Show: | F10: =IFERROR(COUNTIFS(I13:I287, "No-Show"),"") -> 0 | H10: Deals | I10: =F2+F3 -> 6
B12: Date | C12: Name | E12: Phone No. | F12: Email | H12: Source | I12: Outcome | K12: Revenue | L12: Cash | N12: Objection | O12: Objection Notes | Q12: Length | R12: Recording Link | S12: Follow Up/Next Steps | T12: Call Summary
B13: 01.12.25 | C13: Isabella Haas | E13: 81 75 10 56 | F13: ihaasbornand@gmail.com | H13: Setter | I13: split-pay | K13: 10500 | L13: 1500 | N13: Money | O13: Uni, SU + fear | Q13: 6 | S13: Closed | T13: Follow up fra nov. Gratis december måned.
B14: 01.12.25 | C14: Selma Fink | E14: 61 39 98 13 | F14: selmafink1908@gmail.com | H14: Setter | I14: Offer & Didn't Buy | N14: Money | O14: SU (hører forældre om tilskud + har tilbudt dec. gratis) Eksaminer. Virkede interesseret i at starte på et senere tidspunkt. | Q14: 6 | R14: https://slack-files.com/T08TMAAKCCU-F0A0Y71MUJY-6be6bcc874 | S14: Follow Up | T14: Bæredygitge vaner. Hoppet af p-piller og har taget lidt på efter det. Vægttab på 5 kg. Har ikke følt sig 100% tilpas i sin krop de sidste 5 år. Vil gerne finde sunde rutiner. Føler weekenden er en udfordring - alkohol og dårlig mad. Spiral det sidste år. Dårlig søvn. Skrtuktur, tøj, motivation er en udfordring i forhold til træning. Vil gerne starte til reformer. Det var svært for mig at mærke hende på kaldet - ikke lige så god connection som normalt. Mere dybde.
B15: 01.12.25 | C15: Emilie Munk | E15: 52 16 72 62 | F15: emiliemunkkurtzmann@gmail.com | H15: Setter | I15: Cancelled
B16: 02.12.25 | C16: Maria Catarina Søgaard | E16: 21 34 86 70 | F16: soegaard.m@gmail.com | H16: Setter | I16: split-pay | K16: 10500 | L16: 1500 | N16: Money | Q16: 6 | S16: Closed | T16: Kontaktet fra sidste måned. Ville gerne starte op 1. jan. Fik tilbud om gratis december.
B17: 02.12.25 | C17: Josefine Steen-Jørgensen | E17: 61 45 79 82 | F17: josefinesteenj@gmail.com | H17: Setter | I17: Full-Pay | K17: 9000 | L17: 9000 | N17: Fear | O17: Forældre, troen på at ting kan ændre sig | Q17: 6 | R17: https://slack-files.com/T08TMAAKCCU-F0A10RRG0BF-daf50a8f91 | S17: Closed | T17: PCOS. Vægttab på 10 kg. ADD. Alt står stille selv om hun forsøger. Har stået stille i minimum 5 år. Spiser i øjeblikket anitinflammatorisk. Mangler inspiration til nem, overskuelig kost. Struktur. Dårlig søvn. Utilpas i krop. Mangler sunde rutiner. Mere energi og overskud. Vil bare gerne have det godt. Det var svært at komme tæt på hende de første 10 min. men så fik jeg spurgt ind til hvordan hun faktisk har det som gjorde hende meget berørt. Ked af det flere gange på kaldet - også til sidst efter pitch da hun virkelig føler det er det rigtige forløb for hende. Mange fordomme overfor coaches (altid med i realityprogrammer) men gik ind til samtalen med et åbent mindset. Gider ikke udsætte mere. Meget nervøs for om Olivia har tid nok til sine klienter eller om man bliver en af 1000 og forsvinder i systemet. Aftalt at snakkes ved om et par måneder.
B18: 03.12.25 | C18: Emma Louise Spangaard Bittan | E18: 60 61 02 36 | F18: emma-bittan@hotmail.com | H18: Setter | I18: Cancelled | Q18: 6
B19: 05.12.25 | C19: Nicoline Benedicte Mona Andreasen | E19: 41 15 43 02 | F19: nicolineandreasen0202@gmail.com | H19: Setter | I19: split-pay | K19: 10500 | L19: 3000 | Q19: 6 | R19: https://slack-files.com/T08TMAAKCCU-F0A1LTMSTTM-24317f94bc | S19: Closed | T19: Har været i forløb før for 1 år siden med sin bror - skulle tælle og veje alt. Arbejder i bager. 2. sabatår. Træning: har okay styr på træningen men vil gerne have hjælp. Kost: skidt forhold til kost - siger selv at det fylder meget for hende hver dag. Vil gerne have styr på mindset og kost. Etablere et sundt forhold til mad. Overspisning. Oppustethed fylder meget. Siger selv hun føler sig ulækker og bliver meget ked af det da vi taler ind i det er noget hun gør ved sig selv. Og at hun nu er klar til at behandle sig selv bedre. Mere selvtillid. Tøj. Spiser meget hele dagen nogle gange - føler sig ikke mæt og har usunde vaner. Vil gerne tabe 5-8 kg. på den rigtige måde.
B20: 07.12.25 | C20: Caroline Steenfeldt | E20: 42 20 52 46 | F20: steenfeldtcaroline@gmail.com | H20: Setter | I20: Offer & Didn't Buy | N20: Money | O20: Partner (ønsker parforløb) | Q20: 6 | R20: https://slack-files.com/T08TMAAKCCU-F0A1W8EQ2CB-9eac1c3651 | S20: X | T20: (Fandt forløb sammen med kæreste) Forløb før hvor hun talte kalorier. Køber meget Take away og slik - vil gerne finde balancen så hende og hendes kæreste ikke slipper i weekenderne. Har altid følt sig utilpas i sin krop og vil gerne nå i mål nu. Snakker om at hun ikke vil bruge mere tid det sted hun er nu da det er spild af tid. Taler meget om at tage handling nu. Vil gerne tabe 5-6 kg. Har sagt "på mandag" alt for længe. Mindset: blive god til at overholde aftaler med sig selv. Kost: hele fødevarer og inspiration til kostsammensætning. Træning: bedre kondi, sparring til styrketræning (4 gange i ugen) mere viden. Tøj fylder meget for hende. Hun tænker på sin krop hver 2. time dagligt.
B21: 10.12.25 | C21: Cille Nissen | E21: 41 10 89 70 | F21: cillen93@hotmail.com | H21: Setter | I21: Offer & Didn't Buy | N21: Fear | O21: Tid, udsætte, frygt for at fejle, penge | Q21: 6 | R21: https://slack-files.com/T08TMAAKCCU-F0A2QFJV0GJ-e02692e78e | S21: Follow Up | T21: Har skrevet besked hun vil tænke over opstart. Prøvet mange forskellige forløb - både PT og kostvejledning. Sygemeldt med stress. Skolelærer. Selv PT. Wegovy: tabt 30 kg. men er ved at tage på igen. Alt eller intet mentalitet. Ved det er kosten der halter. Prøver men kan ikke finde balancen. Vægttab: 5-6 kg. Træning: funktionel træning, muskemasse - træner meget med kæreste. Har døjet med overspisninger og dårlig samvittighed. Gør stadig på ugentlig basis. Var ikke glad for at åbne op omkring det. Får ikke optimalt ud af sin træning. Stilstand de sidste 6 måneder mens vægten stiger. Havde paraderne oppe gennem hele kaldet. Ville ikke tage beslutninger og frygten for at købe sig endnu et forløb der ikke virkede fyldte meget for hende.
B22: 10.12.25 | C22: Kathrine Kondrup | E22: 42 41 42 70 | F22: kathrinekondrup@gmail.com | H22: Setter | I22: Cancelled
B23: 11.12.25 | C23: Caroline Skou Markussen | E23: 30 25 44 39 | F23: caroline-skou@hotmail.com | H23: Setter | I23: Offer & Didn't Buy | N23: Money | O23: Fulgt op på 2 gange - vil ikke bruge 1500 pr. måned | Q23: 6 | R23: https://slack-files.com/T08TMAAKCCU-F0A36QUQPEW-6b6e35e0be | S23: X | T23: 2 børn. På wegovy - ønsker yderligere vægttab på 10 kg. Har været på kure, forløb med online coaches før, men er ikke nået i mål. Ofte har hun løget overfor sig selv og coachen hvilket jeg dykkede ned i og sagde vi nok skulle gøre hvad vi kunne for at skabe den tillid, men om hun på den anden side også var klar til at være ærlig over for sig selv og os så vi kan få hende i mål. Taler meget grimt til sig selv. Bruger ordet "ulækker krop" om sig selv. Føler ikke hun er god nok. Slevværd. Startede ud med udelukkende at ville have en træningsplan men vi fandt frem til det var et bredere behov og at det hele hang sammen. Ønsker madro - overspiser på kedsomhed. Vil gerne være den bedste version af sig selv for sine børn. Ked af sin mave efter 15 kg. vægttab på 6 måneder. strammes op.
