Workbook

Sheet Dashboard
A1: Sales tracking
A2: Key Metrics | B2: YTD | C2: January | D2: February | E2: March | F2: April | G2: May | H2: June | I2: July | J2: August | K2: September | L2: October | M2: November | N2: December | O2: SPARKLINES
A3: Conversion Rate: | B3: =iferror(B12/B10,"") -> 0.39364303 | D3: =IFERROR(Feb!I2,"") | E3: =Mar!I2 -> 0.44444444 | F3: =IFERROR(Apr!I2,"") -> 0.375 | G3: =IFERROR(May!I2,"") -> 0.47252747 | H3: =IFERROR(Jun!I2,"") -> 0.34259259 | I3: =IFERROR(Jul!I2,"") -> 0.37234043 | J3: =IFERROR(Aug!I2,"") | K3: =IFERROR(Sep!I2,"") | L3: =IFERROR(Oct!I2,"") | M3: =IFERROR(Nov!I2,"") | N3: =IFERROR(Dec!I2,"") | O3: =IFERROR(__xludf.DUMMYFUNCTION("IFERROR(SPARKLINE(C3:N3, {""chartype"", ""line""; ""color"", ""blue""})) "),"")
A4: Offer To Close Rate: | B4: =iferror(B12/B11,"") -> 0.39655172 | D4: =IFERROR(Feb!I3,"") | E4: =IFERROR(Mar!I3,"") -> 0.44444444 | F4: =IFERROR(Apr!I3,"") -> 0.37974684 | G4: =IFERROR(May!I3,"") -> 0.47252747 | H4: =IFERROR(Jun!I3,"") -> 0.34579439 | I4: =IFERROR(Jul!I3,"") -> 0.37634409 | J4: =IFERROR(Aug!I3,"") | K4: =IFERROR(Sep!I3,"") | L4: =IFERROR(Oct!I3,"") | M4: =IFERROR(Nov!I3,"") | N4: =IFERROR(Dec!I3,"") | O4: =IFERROR(__xludf.DUMMYFUNCTION("IFERROR(SPARKLINE(C4:N4, {""chartype"", ""line""; ""color"", ""blue""})) "),"")
A5: Call To Offer Rate: | B5: =IFERROR(B11/B10,"") -> 0.99266504 | D5: =IFERROR(Feb!I4,"") | E5: =IFERROR(Mar!I4,"") -> 1 | F5: =IFERROR(Apr!I4,"") -> 0.9875 | G5: =IFERROR(May!I4,"") -> 1 | H5: =IFERROR(Jun!I4,"") -> 0.99074074 | I5: =IFERROR(Jul!I4,"") -> 0.9893617 | J5: =IFERROR(Aug!I4,"") | K5: =IFERROR(Sep!I4,"") | L5: =IFERROR(Oct!I4,"") | M5: =IFERROR(Nov!I4,"") | N5: =IFERROR(Dec!I4,"") | O5: =IFERROR(__xludf.DUMMYFUNCTION("IFERROR(SPARKLINE(C5:N5, {""chartype"", ""line""; ""color"", ""blue""})) "),"")
A6: Revenue: | B6: =IFERROR(SUM(C6:N6),"") -> 1285000 | D6: =IFERROR(Feb!C3,"") | E6: =IFERROR(Mar!$C3,"") -> 119400 | F6: =IFERROR(Apr!$C3,"") -> 242800 | G6: =IFERROR(May!$C3,"") -> 315000 | H6: =IFERROR(Jun!$C3,"") -> 289200 | I6: =IFERROR(Jul!$C3,"") -> 318600 | J6: =IFERROR(Aug!$C3,"") | K6: =IFERROR(Sep!$C3,"") | L6: =IFERROR(Oct!$C3,"") | M6: =IFERROR(Nov!$C3,"") | N6: =IFERROR(Dec!$C3,"") | O6: =IFERROR(__xludf.DUMMYFUNCTION("IFERROR(SPARKLINE(C6:N6, {""chartype"", ""line""; ""color"", ""blue""})) "),"")
A7: Cash: | B7: =IFERROR(SUM(C7:N7),"") -> 580400 | D7: =IFERROR(Feb!C4,"") | E7: =IFERROR(Mar!$C4,"") -> 44800 | F7: =IFERROR(Apr!$C4,"") -> 85700 | G7: =IFERROR(May!$C4,"") -> 130600 | H7: =IFERROR(Jun!$C4,"") -> 162400 | I7: =IFERROR(Jul!$C4,"") -> 156900 | J7: =IFERROR(Aug!$C4,"") | K7: =IFERROR(Sep!$C4,"") | L7: =IFERROR(Oct!$C4,"") | M7: =IFERROR(Nov!$C4,"") | N7: =IFERROR(Dec!$C4,"") | O7: =IFERROR(__xludf.DUMMYFUNCTION("IFERROR(SPARKLINE(C7:N7, {""chartype"", ""line""; ""color"", ""blue""})) "),"")
A8: Bookings: | B8: =IFERROR(SUM(C8:N8),"") -> 536 | D8: =IFERROR(Feb!I6,"") | E8: =IFERROR(Mar!$I6,"") -> 40 | F8: =IFERROR(Apr!$I6,"") -> 100 | G8: =IFERROR(May!$I6,"") -> 110 | H8: =IFERROR(Jun!$I6,"") -> 146 | I8: =IFERROR(Jul!$I6,"") -> 140 | J8: =IFERROR(Aug!$I6,"") | K8: =IFERROR(Sep!$I6,"") | L8: =IFERROR(Oct!$I6,"") | M8: =IFERROR(Nov!$I6,"") | N8: =IFERROR(Dec!$I6,"") | O8: =IFERROR(__xludf.DUMMYFUNCTION("IFERROR(SPARKLINE(C8:N8, {""chartype"", ""line""; ""color"", ""blue""})) "),"")
A9: Shows: | B9: =sum(C9:N9) -> 409 | D9: =IFERROR(Feb!$I$7,"") | E9: =IFERROR(Mar!$I$7,"") -> 36 | F9: =IFERROR(Apr!$I$7,"") -> 80 | G9: =IFERROR(May!$I$7,"") -> 91 | H9: =IFERROR(Jun!$I$7,"") -> 108 | I9: =IFERROR(Jul!$I$7,"") -> 94 | J9: =IFERROR(Aug!$I$7,"") | K9: =IFERROR(Sep!$I$7,"") | L9: =IFERROR(Oct!$I$7,"") | M9: =IFERROR(Nov!$I$7,"") | N9: =IFERROR(Dec!$I$7,"") | O9: =IFERROR(__xludf.DUMMYFUNCTION("IFERROR(SPARKLINE(C9:N9, {""chartype"", ""line""; ""color"", ""blue""})) "),"")
A10: Calls: | B10: =IFERROR(SUM(C10:N10),"") -> 409 | D10: =IFERROR(Feb!I8,"") | E10: =IFERROR(Mar!$I8,"") -> 36 | F10: =IFERROR(Apr!$I8,"") -> 80 | G10: =IFERROR(May!$I8,"") -> 91 | H10: =IFERROR(Jun!$I8,"") -> 108 | I10: =IFERROR(Jul!$I8,"") -> 94 | J10: =IFERROR(Aug!$I8,"") | K10: =IFERROR(Sep!$I8,"") | L10: =IFERROR(Oct!$I8,"") | M10: =IFERROR(Nov!$I8,"") | N10: =IFERROR(Dec!$I8,"") | O10: =IFERROR(__xludf.DUMMYFUNCTION("IFERROR(SPARKLINE(C10:N10, {""chartype"", ""line""; ""color"", ""blue""})) "),"")
A11: Offers: | B11: =IFERROR(SUM(C11:N11),"") -> 406 | D11: =IFERROR(Feb!I9,"") | E11: =IFERROR(Mar!$I9,"") -> 36 | F11: =IFERROR(Apr!$I9,"") -> 79 | G11: =IFERROR(May!$I9,"") -> 91 | H11: =IFERROR(Jun!$I9,"") -> 107 | I11: =IFERROR(Jul!$I9,"") -> 93 | J11: =IFERROR(Aug!$I9,"") | K11: =IFERROR(Sep!$I9,"") | L11: =IFERROR(Oct!$I9,"") | M11: =IFERROR(Nov!$I9,"") | N11: =IFERROR(Dec!$I9,"") | O11: =IFERROR(__xludf.DUMMYFUNCTION("IFERROR(SPARKLINE(C11:N11, {""chartype"", ""line""; ""color"", ""blue""})) "),"")
A12: Deals: | B12: =IFERROR(SUM(C12:N12),"") -> 161 | D12: =IFERROR(Feb!I10,"") | E12: =IFERROR(Mar!$I10,"") -> 16 | F12: =IFERROR(Apr!$I10,"") -> 30 | G12: =IFERROR(May!$I10,"") -> 43 | H12: =IFERROR(Jun!$I10,"") -> 37 | I12: =IFERROR(Jul!$I10,"") -> 35 | J12: =IFERROR(Aug!$I10,"") | K12: =IFERROR(Sep!$I10,"") | L12: =IFERROR(Oct!$I10,"") | M12: =IFERROR(Nov!$I10,"") | N12: =IFERROR(Dec!$I10,"") | O12: =IFERROR(__xludf.DUMMYFUNCTION("IFERROR(SPARKLINE(C12:N12, {""chartype"", ""line""; ""color"", ""blue""})) "),"")
A13: Full-Pay: | B13: =IFERROR(SUM(C13:N13),"") -> 72 | D13: =IFERROR(Feb!F2,"") | E13: =IFERROR(Mar!$F2,"") -> 14 | F13: =IFERROR(Apr!$F2,"") -> 30 | G13: =IFERROR(May!$F2,"") -> 4 | H13: =IFERROR(Jun!$F2,"") -> 14 | I13: =IFERROR(Jul!$F2,"") -> 10 | J13: =IFERROR(Aug!$F2,"") | K13: =IFERROR(Sep!$F2,"") | L13: =IFERROR(Oct!$F2,"") | M13: =IFERROR(Nov!$F2,"") | N13: =IFERROR(Dec!$F2,"") | O13: =IFERROR(__xludf.DUMMYFUNCTION("IFERROR(SPARKLINE(C13:N13, {""chartype"", ""line""; ""color"", ""blue""})) "),"")
A14: Split-Pay: | B14: =IFERROR(SUM(C14:N14),"") -> 89 | D14: =IFERROR(Feb!F3,"") | E14: =IFERROR(Mar!$F3,"") -> 2 | F14: =IFERROR(Apr!$F3,"") -> 0 | G14: =IFERROR(May!$F3,"") -> 39 | H14: =IFERROR(Jun!$F3,"") -> 23 | I14: =IFERROR(Jul!$F3,"") -> 25 | J14: =IFERROR(Aug!$F3,"") | K14: =IFERROR(Sep!$F3,"") | L14: =IFERROR(Oct!$F3,"") | M14: =IFERROR(Nov!$F3,"") | N14: =IFERROR(Dec!$F3,"") | O14: =IFERROR(__xludf.DUMMYFUNCTION("IFERROR(SPARKLINE(C14:N14, {""chartype"", ""line""; ""color"", ""blue""})) "),"")
A15: Deposits: | B15: =IFERROR(SUM(C15:N15),"") -> 36 | D15: =IFERROR(Feb!F4,"") | E15: =IFERROR(Mar!$F4,"") -> 1 | F15: =IFERROR(Apr!$F4,"") -> 6 | G15: =IFERROR(May!$F4,"") -> 4 | H15: =IFERROR(Jun!$F4,"") -> 9 | I15: =IFERROR(Jul!$F4,"") -> 16 | J15: =IFERROR(Aug!$F4,"") | K15: =IFERROR(Sep!$F4,"") | L15: =IFERROR(Oct!$F4,"") | M15: =IFERROR(Nov!$F4,"") | N15: =IFERROR(Dec!$F4,"") | O15: =IFERROR(__xludf.DUMMYFUNCTION("IFERROR(SPARKLINE(C15:N15, {""chartype"", ""line""; ""color"", ""blue""})) "),"")
A16: Show-Up Rate: | B16: =B9/B8 -> 0.7630597 | D16: =IFERROR(Feb!$L6,"") | E16: =IFERROR(Mar!$L6,"") -> 0.9 | F16: =IFERROR(Apr!$L6,"") -> 0.8 | G16: =IFERROR(May!$L6,"") -> 0.82727273 | H16: =IFERROR(Jun!$L6,"") -> 0.73972603 | I16: =IFERROR(Jul!$L6,"") -> 0.67142857 | J16: =IFERROR(Aug!$L6,"") | K16: =IFERROR(Sep!$L6,"") | L16: =IFERROR(Oct!$L6,"") | M16: =IFERROR(Nov!$L6,"") | N16: =IFERROR(Dec!$L6,"") | O16: =IFERROR(__xludf.DUMMYFUNCTION("IFERROR(SPARKLINE(C16:N16, {""chartype"", ""line""; ""color"", ""blue""})) "),"")
A17: Conducted Rate: | B17: =B10/B8 -> 0.7630597 | D17: =IFERROR(Feb!$L7,"") | E17: =IFERROR(Mar!$L7,"") -> 0.9 | F17: =IFERROR(Apr!$L7,"") -> 0.8 | G17: =IFERROR(May!$L7,"") -> 0.82727273 | H17: =IFERROR(Jun!$L7,"") -> 0.73972603 | I17: =IFERROR(Jul!$L7,"") -> 0.67142857 | J17: =IFERROR(Aug!$L7,"") | K17: =IFERROR(Sep!$L7,"") | L17: =IFERROR(Oct!$L7,"") | M17: =IFERROR(Nov!$L7,"") | N17: =IFERROR(Dec!$L7,"") | O17: =IFERROR(__xludf.DUMMYFUNCTION("IFERROR(SPARKLINE(C17:N17, {""chartype"", ""line""; ""color"", ""blue""})) "),"")

Sheet Mar
B1: Rep: | C1: Name | E1: Outcome | H1: KPIs% | K1: Show Rate | N1: Objections | Q1: Source | U1: Tracking
E2: Full-Pay: | F2: =IFERROR(COUNTIFS(I16:I292, "Full-Pay"),"") -> 14 | H2: Conversion Rate: | I2: =iferror(I10/I8,"") -> 0.44444444 | K2: Rescheduling Rate: | L2: =iferror(F8/I6,"") -> 0 | N2: Think About It | O2: =IFERROR(COUNTIFS(N16:N291, "think about it"),"") -> 9 | Q2: Setter | R2: =IFERROR(COUNTIF(H16:H291,"setter"),"") -> 40 | S2: Cold Call | T2: =IFERROR(COUNTIF(H16:H291,S2),"") -> 0
B3: Revenue | C3: =IFERROR(SUM(K16:K288),"") -> 119400 | E3: Split-Pay: | F3: =IFERROR(COUNTIFS(I16:I292, "Split-Pay"),"") -> 2 | H3: Offer To Close Rate: | I3: =IFERROR(I10/I9,"") -> 0.44444444 | K3: Cancellation Rate: | L3: =iferror(F9/I6,"") -> 0.05 | N3: Money | O3: =IFERROR(COUNTIFS(N16:N291, "money"),"") -> 11 | Q3: IG | R3: =IFERROR(COUNTIF(H16:H291,"IG"),"") -> 0 | S3: Twitter | T3: =IFERROR(COUNTIF(H16:H291,S3),"") -> 0
B4: Cash | C4: =IFERROR(SUM(L16:L289),"") -> 44800 | E4: Deposits: | F4: =IFERROR(COUNTIFS(I16:I292, "Deposit"),"") -> 1 | H4: Call To Offer Rate: | I4: =IFERROR(I9/I8,"") -> 1 | K4: No-Shows Rate: | L4: =iferror(F10/I6,"") -> 0.05 | N4: Time | O4: =IFERROR(COUNTIFS(N16:N291, "time"),"") -> 1 | Q4: YouTube | R4: =IFERROR(COUNTIF(H16:H291,"youtube"),"") -> 0 | S4: Skool | T4: =IFERROR(COUNTIF(H16:H291,S4),"") -> 0
E5: Offer & Didn't Buy: | F5: =IFERROR(COUNTIFS(I16:I292, "Offer & Didn't Buy"),"") -> 19 | H5: Drag Over Rate: | I5: =IFERROR(F7/(C6+F7+F8),"") -> 0 | K5: Drag Over Rate: | L5: =iferror(F7/I6,"") -> 0 | N5: Partner | O5: =IFERROR(COUNTIFS(N16:N291, "partner"),"") -> 1 | Q5: Email | R5: =IFERROR(COUNTIF(H16:H291,"email"),"") -> 0 | S5: Instagram | T5: =IFERROR(COUNTIF(H16:H291,S5),"") -> 0
B6: Total Calls : | C6: =IFERROR(SUM(F2:F6),"") -> 36 | E6: Bad Fit & No Offer: | F6: =IFERROR(COUNTIFS(I16:I292, "Bad Fit & No Offer"),"") -> 0 | H6: Bookings: | I6: =IFERROR(SUM(F2:F10),"") -> 40 | K6: Show-Up Rate: | L6: =iferror(I7/I6,"") -> 0.9 | N6: Fear | O6: =IFERROR(COUNTIFS(N16:N291, "fear"),"") -> 2 | Q6: Facebook | R6: =IFERROR(COUNTIF(H16:H291,"facebook"),"") -> 0 | S6: TikTok | T6: =IFERROR(COUNTIF(H16:H291,S6),"") -> 0
B7: Total Won : | C7: =IFERROR(F2+F3,"") -> 16 | E7: Drag Over & Show: | F7: =IFERROR(COUNTIFS(I16:I292, "Drag Over & Show"),"") -> 0 | H7: Shows: | I7: =IFERROR(SUM(F2:F7),"") -> 36 | K7: Conducted Rate: | L7: =IFERROR(I8/I6,"") -> 0.9 | N7: Value | O7: =IFERROR(COUNTIFS(N17:N292, "value"),"") -> 0 | Q7: Facebook Ads | R7: =IFERROR(COUNTIF(H16:H291,"facebook ads"),"") -> 0 | S7: Google | T7: =IFERROR(COUNTIF(H16:H291,S7),"") -> 0
B8: Total Lost : | C8: =COUNTIF(I16:I291,"offer & didn't buy")+countif(I16:I291,"deposit")+countif(I16:I291,"bad fit & no offer") -> 20 | E8: Rescheduled: | F8: =IFERROR(COUNTIFS(I16:I292, "Rescheduled"),"") -> 0 | H8: Calls: | I8: =IFERROR(SUM(F2:F6),"") -> 36 | Q8: LinkedIn | R8: =IFERROR(COUNTIF(H16:H291,Q8),"") -> 0 | S8: Referral | T8: =IFERROR(COUNTIF(H16:H291,S8),"") -> 0
B9: Closing % : | C9: =iferror(SUM(C7/C6),"") -> 0.44444444 | E9: Cancelled: | F9: =IFERROR(COUNTIFS(I16:I292, "Cancelled"),"") -> 2 | H9: Offers: | I9: =IFERROR(sum(F2:F5),"") -> 36
C10: =C3/C6 -> 3316.6667 | E10: No-Show: | F10: =IFERROR(COUNTIFS(I16:I292, "No-Show"),"") -> 2 | H10: Deals | I10: =F2+F3 -> 16
B12: Date | C12: Name | E12: Phone No. | F12: IG Navn | H12: Source | I12: Outcome | K12: Revenue | L12: Cash | N12: Objection | O12: Objection Notes | Q12: Length | R12: Recording Link | S12: Follow Up/Next Steps | T12: Call Summary
B13: 45841 | C13: Lucas Lund | E13: 52640883 | F13: Lucaslund11 | H13: Setter | I13: Offer & Didn't Buy | N13: Money | O13: Han havde intet arbejde | S13: X | T13: Han var klar så snart der var penge i kassen
B14: 45841 | C14: Bilal | E14: 42323092 | F14: biloo_elmoro | H14: Setter | I14: Offer & Didn't Buy | N14: Money | O14: Han blev lukket, men kunne først betale efter kaldet | S14: X | T14: Han kunne først betale efter kaldet og hørte aldrig fra ham igen
B15: 45841 | C15: Adam Olsen | E15: 22776949 | F15: ady.olsen | H15: Setter | I15: Offer & Didn't Buy | N15: Think About It | O15: Skulle snakke med sin mor | S15: X | T15: Skulle snakke med sin mor og hørte aldrig fra ham
B16: 45933 | C16: Christian Sulkjaer | E16: 22624099 | F16: chrsitiansulkjaer | H16: Setter | I16: Full-Pay | K16: 8700 | L16: 2700 | Q16: 6 mdr | S16: Closed
B17: 45933 | C17: Gustav Mortensen | E17: 23231943 | F17: Mortensen_gustav | H17: Setter | I17: Full-Pay | K17: 8700 | L17: 2700 | Q17: 6 mdr | S17: Closed
B18: 45726 | C18: Lukas Kjelgaard | E18: 29342904 | F18: Lukas.kjelgaard | H18: Setter | I18: Cancelled | N18: Fear | O18: Ikke klar til at give den gas | S18: X | T18: Personen var ikke klar til at hoppe på et kald alligevel, da han ikke følte sig klar endnu
B19: 45726 | C19: Ramazan Karali | E19: 28255187 | F19: r | H19: Setter | I19: Offer & Didn't Buy | N19: Money | O19: Kostede for meget | S19: X | T19: Personen synes det var for dyrt
B20: 45726 | C20: Markus Olsen | E20: 30440961 | F20: markusriberolsen | H20: Setter | I20: Offer & Didn't Buy | N20: Money | O20: Kostede for meget | S20: X | T20: Personen synes det var for dyrt
B21: 45727 | C21: Lukas Pedersen | E21: 25127373 | F21: Lukas_p63 | H21: Setter | I21: Full-Pay | K21: 8700 | L21: 2700 | Q21: 6 mdr | S21: Closed
B22: 45994 | C22: Sebastian Pedersen | E22: 42250101 | F22: seb_mond_pedersen | H22: Setter | I22: Offer & Didn't Buy | N22: Think About It | O22: Han skulle tænke over det | S22: Hot Follow Up | T22: Han vender tilbage om han er ready eller ej
B23: 45994 | C23: Nicolas | E23: 53730010 | F23: Nicolas.haestrup | H23: Setter | I23: Offer & Didn't Buy | N23: Think About It | O23: Han skulle tænke over det | S23: Hot Follow Up | T23: Han vender tilbage om han er ready eller ej
B24: 13/03/2025 | C24: Arpen | F24: arpencc | H24: Setter | I24: No-Show
B25: 13/03/2025 | C25: Erik Bjerregaard | E25: 25739488 | F25: erikgbjerregaard | H25: Setter | I25: Full-Pay | K25: 13500 | L25: 2700 | Q25: 10 mdr | S25: Closed
B26: 14/03/2025 | C26: Christoffer | E26: 30425868 | F26: christofferhellmann | H26: Setter | I26: No-Show | N26: Think About It
B27: 14/03/2025 | C27: Jibril | E27: 31359020 | F27: jibreel.ch.j | H27: Setter | I27: Offer & Didn't Buy | N27: Think About It | O27: Han skulle tænke over det | S27: X | T27: Han vender tilbage
B28: 15/03/2025 | C28: Tobias Nillson | E28: 42724780 | F28: toby_261006 | H28: Setter | I28: Offer & Didn't Buy | N28: Money | O28: Han startede, men hoppede så fra | S28: Hot Follow Up
B29: 15/03/2025 | C29: William Oscar | E29: 27859070 | F29: williamoscarjensen | H29: Setter | I29: Cancelled | N29: Fear | O29: Han aflyste | S29: X
B30: 16/03/2025 | C30: Magnus Johansen | E30: 42317712 | F30: magnus___j | H30: Setter | I30: Offer & Didn't Buy | N30: Money | O30: Han startede ikke op pga penge | S30: Hot Follow Up | T30: Han kan snildt lukkes
B31: 18/03/2025 | C31: simon.dinitzen | E31: 53810095 | F31: simon.dinitzen | H31: Setter | I31: Full-Pay | K31: 4600 | L31: 2200 | Q31: 3 mdr | S31: Closed
B32: 18/03/2025 | C32: Murad Adam | E32: over instagram | F32: murad__simsek | H32: Setter | I32: Full-Pay | K32: 8700 | L32: 2700 | Q32: 6 mdr | S32: Closed
B33: 19/03/2025 | C33: Tobias Kirketerp | E33: over instagram | F33: tobias.kirketerp | H33: Setter | I33: Full-Pay | K33: 6300 | L33: 2700 | Q33: 4 Mdr | S33: Closed
B34: 25/03/2025 | C34: Mikkel Andreassen | E34: Over instagram | F34: Ingen ide | H34: Setter | I34: Full-Pay | K34: 6300 | L34: 2700 | Q34: 4 Mdr | S34: Closed
B35: 25/03/2025 | C35: Sylvester | E35: Over instagram | F35: sylvester_e_schoier | H35: Setter | I35: Offer & Didn't Buy | N35: Money | O35: Han havde ikke penge | S35: Follow Up Set | T35: Manden havde ikke et arbejde og ingen penge
B36: 25/03/2026 | C36: Marcus Thiersen | E36: Over instagram | F36: Ingen ide | H36: Setter | I36: Full-Pay | K36: 8700 | L36: 2700 | N36: Money | S36: Closed
B37: 26/03/2027 | C37: Casper Bess | E37: 91544085 | F37: bess.casper | H37: Setter | I37: Offer & Didn't Buy | N37: Think About It | O37: Han synes det var dyrt | S37: Hot Follow Up | T37: Han har allerede haft anders trust som coach, men han synes det var dyrt
B38: 26/03/2027 | C38: Volkan Deniz | E38: over instagram | F38: volle_de | H38: Setter | I38: Split-Pay | K38: 6300 | L38: 2700 | Q38: 4 Mdr | S38: Closed
B39: 26/03/2027 | C39: Marvin Bøckel | E39: 29833828 | F39: marvin_boeckel | H39: Setter | I39: Offer & Didn't Buy | N39: Think About It | O39: Han skulle snakke med sin mor | S39: Hot Follow Up | T39: Han skulle snakke med sin mor
B40: 26/03/2027 | C40: Albert Trillingsgaard | E40: 53654401 | F40: Albert.Trillingsgaard | H40: Setter | I40: Full-Pay | K40: 5600 | L40: 2000 | Q40: 4 Mdr | S40: Closed
B41: 26/03/2027 | C41: Bashar mageed | E41: Over instagram | F41: Bashar.mageed | H41: Setter | I41: Full-Pay | K41: 8700 | L41: 2700 | Q41: 6 mdr | S41: Closed
B42: 27/03/2027 | C42: Izain | E42: 27898430 | F42: izainnazir | H42: Setter | I42: Offer & Didn't Buy | N42: Think About It | O42: Han skulle tænke over det | S42: Hot Follow Up | T42: Han skulle tænke over det og ville vende tilbage efter han havde undersøgt andre muligheder
B43: 27/03/2027 | C43: Vithushan | E43: 42456593 | F43: vithuuu_s | H43: Setter | I43: Offer & Didn't Buy | N43: Money | O43: Han synes det kostede for meget | S43: X | T43: Han var på SU og var ikke klar på at give den gas. Gav ham dog et tilbud og han vender tilbage
B44: 27/03/2027 | C44: Lukas Romanius | E44: 42232679 | F44: Lukas.romanius | H44: Setter | I44: Full-Pay | K44: 8700 | L44: 2700 | Q44: 6 mdr | S44: Closed
B45: 29/03/2027 | C45: Kornelius Pedersen | E45: 21550741 | F45: kornelius.pedersen | H45: Setter | I45: Offer & Didn't Buy | N45: Money | O45: Han havde ikke penge til det | S45: X | T45: Han var 17 år gammel, var tømrelærling og dyrkede kampsport. Han havde dog ikke penge til det
B46: 29/03/2027 | C46: Mads Reimer | E46: 22550306 | F46: reimer1999 | H46: Setter | I46: Full-Pay | L46: 7200 | Q46: 6 mdr | S46: Closed
B47: 29/03/2027 | C47: Nicklas Jensen | E47: 26237075 | F47: nicklas.ingemann | H47: Setter | I47: Offer & Didn't Buy | N47: Money | O47: Han havde ikke penge til det | S47: Follow Up Set | T47: Han havde ingen penge
B48: 29/03/2027 | C48: Raafat | E48: 20692072 | F48: raafat_malla94 | H48: Setter | I48: Offer & Didn't Buy | N48: Money | O48: Manden var på SU | S48: X | T48: 31 årige mand som var på SU
B49: 29/03/2027 | C49: Valdemar | E49: 24665256 | F49: valdemar.dalhauge | H49: Setter | I49: Offer & Didn't Buy | N49: Money | O49: Manden havde ingen penge | S49: X | T49: Han har allerede haft coach på før, men havde ikke penge til det nu
B50: 29/03/2027 | C50: Bilal | E50: 52224087 | F50: bilal.rashiid | H50: Setter | I50: Offer & Didn't Buy | N50: Think About It | O50: Han skulle snakke med sin bror | S50: Hot Follow Up | T50: Han skulle snakke med sin bror som måske også var klar
B51: 29/03/2027 | C51: Gustav | E51: 60511128 | F51: gustav_tue | H51: Setter | I51: Offer & Didn't Buy | N51: Partner | O51: Skulle snakke med sin fam | S51: Hot Follow Up | T51: Skulle snakke med sin fam
B52: 29/03/2027 | C52: Malthe Trudslev | E52: 61485599 | F52: malthe_trudslev | H52: Setter | I52: Split-Pay | K52: 7200 | L52: 1000 | S52: Closed
B53: 29/03/2027 | C53: Sebastian Rex | E53: 28763060 | F53: Sebastian__rex | H53: Setter | I53: Offer & Didn't Buy | N53: Time | O53: Han venter lidt | S53: Hot Follow Up | T53: Han var super klar til at give den gas, men han venter til eksamen er done
B54: 30/03/2027 | C54: Jimmi Pedersen | E54: 29834939 | F54: jimmip1987 | H54: Setter | I54: Deposit | N54: Think About It | S54: Closed | T54: Han starter d 1 juni
B55: 30/03/2027 | C55: Ziad Nakad | E55: Ingen ide | F55: ziad_nakad | H55: Setter | I55: Full-Pay | K55: 8700 | L55: 2700 | Q55: 6 mdr | S55: Closed

Sheet Apr
B1: Rep: | C1: Name | E1: Outcome | H1: KPIs% | K1: Show Rate | N1: Objections | Q1: Source | U1: Tracking
E2: Full-Pay: | F2: =IFERROR(COUNTIFS(I13:I286, "Full-Pay"),"") -> 30 | H2: Conversion Rate: | I2: =iferror(I10/I8,"") -> 0.375 | K2: Rescheduling Rate: | L2: =iferror(F8/I6,"") -> 0 | N2: Think About It | O2: =IFERROR(COUNTIFS(N13:N285, "think about it"),"") -> 10 | Q2: Reschedule | R2: =IFERROR(COUNTIF(H13:H285,Q2),"") -> 0 | S2: Cold Call | T2: =IFERROR(COUNTIF(H13:H285,S2),"") -> 0
B3: Revenue | C3: =IFERROR(SUM(K13:K282),"") -> 242800 | E3: Split-Pay: | F3: =IFERROR(COUNTIFS(I13:I286, "Split-Pay"),"") -> 0 | H3: Offer To Close Rate: | I3: =IFERROR(I10/I9,"") -> 0.37974684 | K3: Cancellation Rate: | L3: =iferror(F9/I6,"") -> 0.08 | N3: Money | O3: =IFERROR(COUNTIFS(N13:N285, "money"),"") -> 26 | Q3: YouTube | R3: =IFERROR(COUNTIF(H13:H285,Q3),"") -> 0 | S3: Twitter | T3: =IFERROR(COUNTIF(H13:H285,S3),"") -> 0
B4: Cash | C4: =IFERROR(SUM(L13:L283),"") -> 85700 | E4: Deposits: | F4: =IFERROR(COUNTIFS(I13:I286, "Deposit"),"") -> 6 | H4: Call To Offer Rate: | I4: =IFERROR(I9/I8,"") -> 0.9875 | K4: No-Shows Rate: | L4: =iferror(F10/I6,"") -> 0.12 | N4: Time | O4: =IFERROR(COUNTIFS(N13:N285, "time"),"") -> 2 | Q4: YouTube Ads | R4: =IFERROR(COUNTIF(H13:H285,Q4),"") -> 0 | S4: Skool | T4: =IFERROR(COUNTIF(H13:H285,S4),"") -> 0
E5: Offer & Didn't Buy: | F5: =IFERROR(COUNTIFS(I13:I286, "Offer & Didn't Buy"),"") -> 43 | H5: Drag Over Rate: | I5: =IFERROR(F7/(C6+F7+F8),"") -> 0 | K5: Drag Over Rate: | L5: =iferror(F7/I6,"") -> 0 | N5: Partner | O5: =IFERROR(COUNTIFS(N13:N285, "partner"),"") -> 3 | Q5: Email | R5: =IFERROR(COUNTIF(H13:H285,Q5),"") -> 0 | S5: Instagram | T5: =IFERROR(COUNTIF(H13:H285,S5),"") -> 0
B6: Total Calls : | C6: =IFERROR(SUM(F2:F6),"") -> 80 | E6: Bad Fit & No Offer: | F6: =IFERROR(COUNTIFS(I13:I286, "Bad Fit & No Offer"),"") -> 1 | H6: Bookings: | I6: =IFERROR(SUM(F2:F10),"") -> 100 | K6: Show-Up Rate: | L6: =iferror(I7/I6,"") -> 0.8 | N6: Fear | O6: =IFERROR(COUNTIFS(N13:N285, "fear"),"") -> 2 | Q6: Facebook | R6: =IFERROR(COUNTIF(H13:H285,Q6),"") -> 0 | S6: TikTok | T6: =IFERROR(COUNTIF(H13:H285,S6),"") -> 0
B7: Total Won : | C7: =IFERROR(F2+F3,"") -> 30 | E7: Drag Over & Show: | F7: =IFERROR(COUNTIFS(I13:I286, "Drag Over & Show"),"") -> 0 | H7: Shows: | I7: =IFERROR(SUM(F2:F7),"") -> 80 | K7: Conducted Rate: | L7: =IFERROR(I8/I6,"") -> 0.8 | N7: Value | O7: =IFERROR(COUNTIFS(N14:N286, "value"),"") -> 0 | Q7: Facebook Ads | R7: =IFERROR(COUNTIF(H13:H285,Q7),"") -> 0 | S7: Google | T7: =IFERROR(COUNTIF(H13:H285,S7),"") -> 0
B8: Total Lost : | C8: =COUNTIF(I13:I285,"offer & didn't buy")+countif(I13:I285,"deposit")+countif(I13:I285,"bad fit & no offer") -> 50 | E8: Rescheduled: | F8: =IFERROR(COUNTIFS(I13:I286, "Rescheduled"),"") -> 0 | H8: Calls: | I8: =IFERROR(SUM(F2:F6),"") -> 80 | Q8: LinkedIn | R8: =IFERROR(COUNTIF(H13:H285,Q8),"") -> 0 | S8: Referral | T8: =IFERROR(COUNTIF(H13:H285,S8),"") -> 0
B9: Closing % : | C9: =iferror(SUM(C7/C6),"") -> 0.375 | E9: Cancelled: | F9: =IFERROR(COUNTIFS(I13:I286, "Cancelled"),"") -> 8 | H9: Offers: | I9: =IFERROR(sum(F2:F5),"") -> 79
C10: =C3/C6 -> 3035 | E10: No-Show: | F10: =IFERROR(COUNTIFS(I13:I286, "No-Show"),"") -> 12 | H10: Deals | I10: =F2+F3 -> 30
B12: Date | C12: Name | E12: Phone No. | F12: Ig navn | H12: Source | I12: Outcome | K12: Revenue | L12: Cash | N12: Objection | O12: Objection Notes | Q12: Length | R12: Recording Link | S12: Follow Up/Next Steps | T12: Call Summary
B13: 45661 | C13: Sayed | E13: 45 28 73 83 06 | F13: Sayed_srh | H13: Setter | I13: Full-Pay | K13: 10500 | L13: 3000 | O13: han havde ikke råd | Q13: 6 mdr | S13: Closed
B14: 45661 | C14: Oliver Jensen | E14: 22 55 37 95 | F14: olij06 | H14: Setter | I14: Offer & Didn't Buy | N14: Money | S14: Hot Follow Up
B15: 45661 | C15: Mikkel Nielsen | E15: 93 92 30 65 | F15: mikkel.niels | H15: Setter | I15: Full-Pay | K15: 3750 | L15: 3750 | Q15: 3 mdr | S15: Closed
B16: 45661 | C16: Jakob Voss | E16: 61 42 42 32 | F16: Hey Navn, jeg kom lige i tanke om dig og vores gode snak for ikke så længe siden, hvor vi aldrig kom igang pga økonomien stod i vejen - er det stadig det samme tilfælde? | H16: Setter | I16: Offer & Didn't Buy | N16: Money | O16: han havde ikke råd | S16: Follow Up Set | T16: Han havde ikke penge til det
B17: 45661 | C17: Emil | E17: 26 46 69 55 | F17: Emilbgqvist | H17: Setter | I17: No-Show
B18: 45661 | C18: Andreas Tøndø | E18: 53 53 86 56 | F18: Andreas_t_a | H18: Setter | I18: Full-Pay | K18: 8700 | L18: 2700 | Q18: 6 mdr | S18: Closed
B19: 45661 | C19: Noah | E19: 61608516 | F19: noah_b.j | H19: Setter | I19: Offer & Didn't Buy | N19: Partner | O19: Forældre sagde nej | S19: X | T19: Han var sygt klar, men hans forældre sagde nej. Han ville gerne når han blev 18 år gammel til sep
B20: 45661 | C20: Jonas | E20: 30 23 39 02 | F20: joneswww_ | H20: Setter | I20: Offer & Didn't Buy | N20: Money | O20: Kostede for meget | S20: Hot Follow Up | T20: Han var sygt frisk, men pengene holdte ham tilbage
B21: 45661 | C21: Oliver Kolze | E21: 53 80 23 77 | F21: oliver_kolze | H21: Setter | I21: No-Show
B22: 45692 | C22: Sebastian ladesea | E22: 30 26 22 34 | F22: Sebastianladesea | H22: Setter | I22: No-Show
B23: 45692 | C23: Silas molter | E23: 42 76 60 06 | F23: Silasmolter | H23: Setter | I23: Full-Pay | K23: 8700 | L23: 2700 | Q23: 6 mdr | S23: Closed
B24: 45692 | C24: Andreas arendal | E24: 28 86 68 75 | F24: Andreasarendal | H24: Setter | I24: Full-Pay | K24: 8700 | L24: 2700 | Q24: 6 mdr | S24: Closed
B25: 45692 | C25: William Østergaard | E25: 60 79 01 40 | F25: williamostergaard | H25: Setter | I25: Offer & Didn't Buy | N25: Partner | O25: Forældre sagde nej | S25: Hot Follow Up | T25: Han var SYGT klar, men hans forældre sagde nej, da de synes det var for dyrt
B26: 45692 | C26: Lucas Andersen | E26: 27 84 04 21 | F26: Lucas_Andersen1 | H26: Setter | I26: Full-Pay | K26: 5200 | L26: 2700 | Q26: 3 mdr | S26: Closed
B27: 45692 | C27: hakim Bcheinia | E27: 31 18 22 89 | F27: hakimBcheinia | H27: Setter | I27: No-Show
B28: 45692 | C28: Peter johansen | E28: 29 12 40 55 | F28: Peter_johansen_ | H28: Setter | I28: Full-Pay | K28: 8700 | L28: 2700 | Q28: 6 mdr | S28: Closed
B29: 45720 | C29: Søren | E29: 60 53 62 65 | F29: Soren456 | H29: Setter | I29: Offer & Didn't Buy | N29: Money | O29: Penge holdte ham tilbage | S29: Hot Follow Up | T29: Han skal 100% kontaktes igen om nogen måneder, da han var ready
B30: 45720 | C30: Billy | E30: 31 76 21 09 | F30: Billylindeblad | H30: Setter | I30: Offer & Didn't Buy | N30: Money | O30: Penge holdte ham tilbage | S30: X | T30: 17 årige gut som ikke var 100% klar endnu
B31: 45720 | C31: Haris husedzinivic | E31: 42 72 68 24 | F31: Harishusedzinivic | H31: Setter | I31: Full-Pay | K31: 8750 | L31: 2750 | Q31: 6 mdr | S31: Closed
B32: 45720 | C32: Jeppe Olsen | E32: 27 52 00 60 | F32: ingen ide | H32: Setter | I32: Full-Pay | K32: 8750 | L32: 2750 | Q32: 6 mdr | S32: Closed
B33: 45720 | C33: Amien dahhak | E33: 42 32 06 55 | F33: Amiendahhak1 | H33: Setter | I33: Offer & Didn't Buy | N33: Money | O33: Penge holdte ham tilbage | S33: X | T33: Han var slet ikke der
B34: 45720 | C34: Anders | E34: 42 66 41 68 | F34: anders_staer | H34: Setter | I34: Full-Pay | K34: 5100 | L34: 2700 | Q34: 3 mdr | S34: Closed
B35: 45751 | C35: Frederik sørensen | E35: 21 30 07 40 | F35: Sorensen_frederik129 | H35: Setter | I35: Offer & Didn't Buy | N35: Money | O35: synes det var dyrt | S35: Hot Follow Up | T35: Frederik havde fuldtidsarbejde, havde pengene til det, men tror ikke jeg fik ham comitted nok og derfor ikke så værdien i det. rigtig godt follow up
B36: 45751 | C36: Lucas | E36: 42 65 40 96 | F36: lucas.2.7.4.0 | H36: Setter | I36: Offer & Didn't Buy | N36: Think About It | O36: Han skulle tænke over det | S36: Hot Follow Up | T36: Han var også håndværker og er et rigtig godt follow up
B37: 45751 | C37: Jakob | E37: 40 84 23 99 | F37: Jakobjanum | H37: Setter | I37: Offer & Didn't Buy | N37: Time | O37: Han var ikke klar endnu | S37: X | T37: Ham skal jeg ikke arbejde med
B38: 45751 | C38: Nikolai Louis Møllegaard | E38: 42 23 75 41 | F38: ungnico69 | H38: Setter | I38: Full-Pay | K38: 8750 | L38: 2750 | Q38: 6 mdr | S38: Closed
B39: 45781 | C39: Martin Hellesøe | E39: Over instagram | F39: martin_hellese | H39: Setter | I39: Offer & Didn't Buy | N39: Money | O39: Ikke råd | S39: Hot Follow Up | T39: Rigtig godt lead som faktisk var 100%, havde fuldtidsjob, men da han skulle snakke med fruen, så blev det til et nej
B40: 45781 | C40: Anders Frederiksen | E40: 24201093 | F40: anders_hf | H40: Setter | I40: Offer & Didn't Buy | N40: Money | O40: Ikke råd | S40: Hot Follow Up | T40: Rigtig godt lead, men ville gerne tjene lidt flere penge før han var klar
B41: 45812 | C41: malthe | E41: 22102612 | F41: malthehj__ | H41: Setter | I41: Offer & Didn't Buy | N41: Money | O41: han var klar | S41: X | T41: Han var klar og sagde han ville betale efter kaldet, efter kaldet skriver han at hans mor sagde nej selvom han er 18 år gammel
B42: 45812 | C42: ramazan | D42: 52224531 | E42: 52224531 | F42: ramazan__bostanci__ | H42: Setter | I42: Offer & Didn't Buy | Q42: 6 mdr | S42: Closed | T42: Han betaler først d 1 maj
B43: 45812 | C43: Mathias | E43: 31667525 | F43: 2630_privat | H43: Setter | I43: Offer & Didn't Buy | N43: Fear | O43: han var klar | S43: X | T43: Han var klar til at betale i den nye måned, man han ville klare det efter kaldet og hørte aldrig fra ham igen
B44: 45812 | C44: Gabi | E44: 93 99 98 55 | F44: gabi.s.p | H44: Setter | I44: Full-Pay | K44: 3600 | L44: 3600 | Q44: 3 mdr | S44: Closed
B45: 45812 | C45: Lucas | E45: 26460246 | F45: _lucasmissel_ | H45: Setter | I45: Offer & Didn't Buy | N45: Money | O45: Han havde ikke nok penge | S45: Hot Follow Up | T45: Rigtig godt lead som er vvs, arbejder og træner meget. han havde et par regninger som han gerne ville klare først
B46: 45812 | C46: Enis | E46: 42557383 | F46: enish0 | H46: Setter | I46: Full-Pay | K46: 8750 | L46: 2750 | Q46: 6 mdr | S46: Closed
B47: 45842 | C47: Oliver Valentin | E47: 42164136 | F47: olivervalentin1 | H47: Setter | I47: Full-Pay | K47: =8750 - 1200 - 1200 -> 6350 | L47: 2700 | Q47: 4 mdr | S47: Closed
B48: 45842 | C48: Mathias | E48: 53825462 | F48: sutden2610 | H48: Setter | I48: Offer & Didn't Buy | N48: Money | O48: Han havde ikke penge | S48: X | T48: Ung og ingen penge som 17 årige
B49: 45842 | C49: Frederik | E49: 24607595 | F49: fredz1k0 | H49: Setter | I49: Offer & Didn't Buy | N49: Money | O49: Han havde ikke penge | S49: Hot Follow Up | T49: Han er en god alder, men pengene rækkede ikke
B50: 45842 | C50: Theis | E50: 77 22 88 15 | F50: t.rjorgensen | H50: Setter | I50: No-Show
B51: 45873 | C51: Nicki | E51: 31 32 56 05 | F51: Nicki.henriksenn | H51: Setter | I51: Offer & Didn't Buy | N51: Money | O51: Han havde ikke pengene | S51: Hot Follow Up | T51: Han er en god alder, men har bare ikke pengene til det
B52: 45873 | C52: Nik | E52: 42 94 02 78 | F52: niktatoz | H52: Setter | I52: Offer & Didn't Buy | N52: Money | O52: Han havde ikke pengene | S52: X | T52: Han var klar over dm, men da vi kom til kaldet var han ikke klar
B53: 45873 | C53: Matthias | E53: 52 97 06 28 | F53: Mattiasfreij | H53: Setter | I53: Cancelled
B54: 45873 | C54: Zune | E54: 71 70 59 76 | F54: Zunebudal | H54: Setter | I54: Offer & Didn't Buy | N54: Think About It | O54: Snakke med sin far | S54: Follow Up | T54: Han skulle snakke med sin far
B55: 45904 | C55: Faisal | E55: 28 78 27 88 | F55: faisxxali | H55: Setter | I55: Offer & Didn't Buy | N55: Fear | O55: Synes det var for mange penge | S55: Follow Up | T55: Han kunne være god at følge op på, da han har fulgt mig længe og lød rigtig varm over kaldet
B56: 45904 | C56: Daniel | E56: 22 55 54 42 | F56: dani_mikus | H56: Setter | I56: Full-Pay | K56: 8700 | L56: 2700 | Q56: 6 mdr | S56: Closed
B57: 45904 | C57: Patrick | E57: 23 24 60 06 | F57: Patrickhansen74 | H57: Setter | I57: Offer & Didn't Buy | N57: Money | O57: Penge | S57: Follow Up | T57: Mødet gik sygt godt og vi fik ham også på depositum, men lige efter kaldet ville han gerne hoppe fra
B58: 45965 | C58: Meklas | E58: 61 46 08 60 | F58: Meklas.barfoed | H58: Setter | I58: No-Show
B59: 45965 | C59: Willas | E59: 42 83 03 11 | F59: willas_lantz | H59: Setter | I59: Cancelled | Q59: 6 mdr | S59: Deposit (Follow Up Set) | T59: Han kan først starte op om 3 mdr, da han lige har fået en skade (Han meldte fra)
B60: 45965 | C60: Jimmy | E60: 26 11 62 11 | F60: Jimmyyghost48xx | H60: Setter | I60: Offer & Didn't Buy | N60: Money | O60: Penge | S60: Follow Up | T60: Manden var helt klar og han skulle betale efter kaldet da han ikke havde pung på sig og så meldte han fra efter
B61: 45965 | C61: Oliver | E61: 60 81 77 18 | F61: Oliver_skall | H61: Setter | I61: No-Show
B62: 45965 | C62: Emil | E62: 42 66 57 30 | F62: Emilgodsvig | H62: Setter | I62: Full-Pay | K62: 8700 | L62: 2700 | Q62: 6 mdr | S62: Closed
B63: 14/04/2025 | C63: Musti | E63: 42 49 52 85 | F63: Musti.532 | H63: Setter | I63: No-Show
B64: 14/04/2025 | C64: Emil | E64: 31 33 80 24 | F64: Emil munch | H64: Setter | I64: Full-Pay | K64: 8700 | L64: 2700 | Q64: 6 mdr | S64: Closed
B65: 14/04/2025 | C65: Clent | E65: 51 44 20 47 | F65: Clent Dave | H65: Setter | I65: Offer & Didn't Buy | N65: Think About It | O65: Penge | S65: X | T65: Han var slet ikke et godt lead
B66: 15/04/2025 | C66: Mathias | E66: 50 49 85 20 | F66: Lykke_drage | H66: Setter | I66: Full-Pay | K66: 8700 | L66: 2700 | Q66: 6 mdr | S66: Closed
B67: 15/04/2025 | C67: Nikolaj Merdan Vandrup | E67: 28 44 06 96 | F67: Nikolaj Merdan Vandrup | H67: Setter | I67: Offer & Didn't Buy | N67: Money | O67: Lidt stramt | S67: Hot Follow Up | T67: Han er et rigtig godt og varmt lead. Han skal opfølges på igen til maj
B68: 15/04/2025 | C68: Wali hamidi | E68: 51 18 46 12 | F68: Wali hamidi | H68: Setter | I68: Offer & Didn't Buy | N68: Money | O68: Penge | S68: X | T68: Rigtig dårligt lead og havde næsten ingen penge
B69: 15/04/2025 | C69: Max sandberg | E69: 51 66 07 47 | F69: Max sandberg | H69: Setter | I69: Full-Pay | K69: 8700 | L69: 2700 | Q69: 6 mdr | S69: Closed
B70: 16/04/2025 | C70: Hamza | E70: 60 54 09 43 | F70: Hamzaxmunir | H70: Setter | I70: Offer & Didn't Buy | N70: Think About It | O70: Ville undersøge andre coaches | S70: Hot Follow Up | T70: Han ville tænke over det og lede efter andre coaches, men han vendte aldrig tilbage
B71: 16/04/2025 | C71: Rune | E71: 29 91 97 07 | F71: Fynboen_01 | H71: Setter | I71: Deposit | Q71: 6 mdr | S71: Closed
B72: 16/04/2025 | C72: Dalibor | E72: 26 16 97 63 | F72: Daliborcalavandic | H72: Setter | I72: Offer & Didn't Buy | N72: Think About It | O72: han skulle snakke med hans kone | S72: X | T72: Han skulle snakke med konen og vi hørte aldrig fra ham igen
B73: 16/04/2025 | C73: Jonas bentsen | E73: 27 51 28 81 | F73: Jonas_bentsen | H73: Setter | I73: No-Show
B74: 16/04/2025 | C74: Anton Løjstrup | E74: 51 95 80 90 | F74: Anton Løjstrup | H74: Setter | I74: Offer & Didn't Buy | N74: Money | O74: Han var presset | S74: Hot Follow Up | T74: Han var presset med pengene og ville ikke starte op endnu
B75: 16/04/2025 | C75: Anton | E75: 22 71 77 34 | F75: Anton_m_ward | H75: Setter | I75: Full-Pay | K75: 8700 | L75: 2700 | Q75: 6 mdr | S75: Deposit (Follow Up Set)
B76: 17/04/2025 | C76: Daniel scheppan | E76: 30 42 67 40 | F76: Daniel scheppan | H76: Setter | I76: Cancelled | L76: 1500 | Q76: 6 mdr | S76: Deposit (Follow Up Set)
B77: 17/04/2025 | C77: Marcus Poulsen | E77: 53 70 41 15 | F77: Marcus Poulsen | H77: Setter | I77: Deposit | Q77: 6 mdr | S77: Deposit (Follow Up Set)
B78: 18/04/2025 | C78: Oscar Bugge | E78: 60213149 | F78: bugge.14 | H78: Setter | I78: Offer & Didn't Buy | N78: Money | O78: bare penge | S78: Follow Up | T78: Han lød meget frisk, men tror pengene holdte ham tilbage hvilket er træt
B79: 19/04/2025 | C79: Max Jacobsen | E79: 51 41 05 92 | F79: Max sandberg | H79: Setter | I79: Full-Pay | K79: 8700 | L79: 2700 | Q79: 6 mdr | S79: Closed
B80: 19/04/2025 | C80: Leon | E80: 93 86 51 71 | F80: Leon ramic20 | H80: Setter | I80: Offer & Didn't Buy | N80: Think About It | O80: Han var ready man! | S80: Hot Follow Up | T80: Manden var fkn ready og han skulle til at betale lige indtil han havde glemt sit kort på sit kontor, men så tog han den ikke da jeg ringede tilbage på et aftalt tidspunkt
B81: 20/04/2025 | C81: Mads | E81: 71 52 31 01 | F81: 1312_mads | H81: Setter | I81: Full-Pay | K81: 8700 | L81: 2700 | Q81: 6 mdr | S81: Closed
B82: 20/04/2025 | C82: Lukas | E82: 60 78 88 68 | F82: lukasgandrup | H82: Setter | I82: Offer & Didn't Buy | N82: Think About It | O82: Økonomi | S82: X | T82: Ung fyr som var klar, men hans forældre var ikke for det
B83: 20/04/2025 | C83: Jakob Fernando Vingo Venø | E83: 71 75 01 75 | F83: Jakob Fernando Vingo Venø | H83: Setter | I83: Cancelled
B84: 20/04/2025 | C84: Christian | E84: 42 31 19 95 | F84: chr_post12 | H84: Setter | I84: No-Show
B85: 20/04/2025 | C85: Ali | E85: 971 50 942 497 | F85: s60cph | H85: Setter | I85: Offer & Didn't Buy | N85: Think About It | O85: Han skulle tænke over det | S85: X | T85: Han skulle tænke over det og endte med at finde en anden en. Han var også rimelig weitd
B86: 20/04/2025 | C86: Storm graversen | E86: 61 41 87 07 | F86: graversenstorm | H86: Setter | I86: Offer & Didn't Buy | N86: Money | O86: Blokering | S86: Hot Follow Up | T86: Manden var fuld ready lige indtil han blokere mig, men han har unblokeret mig nu
B87: 20/04/2025 | C87: Malthe højer | E87: 20 55 44 53 | F87: Malthe højer | H87: Setter | I87: Full-Pay | K87: 8700 | L87: 2700 | Q87: 6 mdr | S87: Closed
B88: 21/04/2025 | C88: Jonas Astrup | E88: 42 21 38 52 | F88: Jonas Astrup | H88: Setter | I88: Full-Pay | K88: 8700 | L88: 2700 | Q88: 6 mdr | S88: Closed
B89: 21/04/2025 | C89: Oscar Møller | E89: 51 17 05 06 | F89: ocar__moller06 | H89: Setter | I89: No-Show | N89: Money | O89: Blokering inden kaldet
B90: 21/04/2025 | C90: Mikkel touvdal | E90: 71 78 98 52 | F90: Mikkel touvdal | H90: Setter | I90: Deposit | L90: 100 | Q90: 6 mdr | S90: Closed
B91: 22/04/2025 | C91: Simon | E91: 29 90 34 92 | F91: Hardy_07 | H91: Setter | I91: Full-Pay | K91: 8700 | L91: 2700 | Q91: 6 mdr | S91: Closed
B92: 22/04/2025 | C92: Gustave Tribondeau | E92: 26 11 77 09 | F92: Gustavtribondeau | H92: Setter | I92: Full-Pay | K92: 7700 | L92: 1700 | Q92: 6 mdr | S92: Closed
B93: 22/04/2025 | C93: Cem | E93: 27 60 55 54 | F93: Cem.r_ | H93: Setter | I93: No-Show | O93: Adam blokere inden kaldet
B94: 22/04/2025 | C94: Christian | E94: 50 39 78 05 | F94: Christian Veselinovski | H94: Setter | I94: Deposit | L94: 1500 | Q94: 4 mdr | S94: Closed
B95: 22/04/2025 | C95: Mikkel Kildevang | E95: 42 72 12 66 | F95: kildevangmikkel | H95: Setter | I95: Offer & Didn't Buy | N95: Time | O95: Intet tid | S95: Follow Up | T95: han er god at følge op på om nogen måneder
B96: 22/04/2025 | C96: Tobias | E96: 27 99 53 10 | F96: tobiaskhansson | H96: Setter | I96: Cancelled | O96: Bumsen blokere
B97: 23/04/2025 | C97: Noah | E97: 41 91 01 08 | F97: Noah sølvsteen | H97: Setter | I97: Full-Pay | K97: 9000 | L97: 2750 | Q97: 6 mdr | S97: Closed
B98: 23/04/2025 | C98: Thomas | E98: 51 72 15 06 | F98: thomastlausten | H98: Setter | I98: Offer & Didn't Buy | N98: Money | O98: Penge | S98: Follow Up | T98: Han lød faktisk super frisk, men sagde at opstartsgebyret var det som holdte ham tilbage
B99: 25/04/2025 | C99: Benjamin | E99: 28 51 68 13 | F99: Benjaminnymann0 | H99: Setter | I99: Deposit | Q99: 6 mdr | S99: Closed | T99: Ingen deposit da manden var på farten, men han betaler 1500 d 1 og 1200 hver måned
B100: 25/04/2025 | C100: Gustav | E100: 26 70 37 63 | F100: Gustavkarkov | H100: Setter | I100: Offer & Didn't Buy | N100: Think About It | O100: Ville prøve selv | S100: Hot Follow Up | T100: Manden var vold varm, men ville først prøve selv før han fik en coach på. God follow up om en måned eller 2
B101: 25/04/2025 | C101: Valdemar Drejer hansen | E101: 42 72 12 78 | F101: Valdemar Drejer hansen | H101: Setter | I101: Deposit | L101: 100 | Q101: 6 mdr | S101: Closed | T101: Vi starter d 17 maj, da han har skinne på fordi han er blevet opereret. Så vi giver den gas der
...

Sheet May
B1: Rep: | C1: Name | E1: Outcome | H1: KPIs% | K1: Show Rate | N1: Objections | Q1: Source | U1: Tracking
E2: Full-Pay: | F2: =IFERROR(COUNTIFS(I13:I287, "Full-Pay"),"") -> 4 | H2: Conversion Rate: | I2: =iferror(I10/I8,"") -> 0.47252747 | K2: Rescheduling Rate: | L2: =iferror(F8/I6,"") -> 0 | N2: Think About It | O2: =IFERROR(COUNTIFS(N13:N286, "think about it"),"") -> 10 | Q2: Reschedule | R2: =IFERROR(COUNTIF(H13:H286,Q2),"") -> 0 | S2: Cold Call | T2: =IFERROR(COUNTIF(H13:H286,S2),"") -> 0
B3: Revenue | C3: =IFERROR(SUM(K13:K283),"") -> 315000 | E3: Split-Pay: | F3: =IFERROR(COUNTIFS(I13:I287, "Split-Pay"),"") -> 39 | H3: Offer To Close Rate: | I3: =IFERROR(I10/I9,"") -> 0.47252747 | K3: Cancellation Rate: | L3: =iferror(F9/I6,"") -> 0.045454545 | N3: Money | O3: =IFERROR(COUNTIFS(N13:N286, "money"),"") -> 26 | Q3: YouTube | R3: =IFERROR(COUNTIF(H13:H286,Q3),"") -> 0 | S3: Twitter | T3: =IFERROR(COUNTIF(H13:H286,S3),"") -> 0
B4: Cash | C4: =IFERROR(SUM(L13:L284),"") -> 130600 | E4: Deposits: | F4: =IFERROR(COUNTIFS(I13:I287, "Deposit"),"") -> 4 | H4: Call To Offer Rate: | I4: =IFERROR(I9/I8,"") -> 1 | K4: No-Shows Rate: | L4: =iferror(F10/I6,"") -> 0.12727273 | N4: Time | O4: =IFERROR(COUNTIFS(N13:N286, "time"),"") -> 2 | Q4: YouTube Ads | R4: =IFERROR(COUNTIF(H13:H286,Q4),"") -> 0 | S4: Skool | T4: =IFERROR(COUNTIF(H13:H286,S4),"") -> 0
E5: Offer & Didn't Buy: | F5: =IFERROR(COUNTIFS(I13:I287, "Offer & Didn't Buy"),"") -> 44 | H5: Drag Over Rate: | I5: =IFERROR(F7/(C6+F7+F8),"") -> 0 | K5: Drag Over Rate: | L5: =iferror(F7/I6,"") -> 0 | N5: Partner | O5: =IFERROR(COUNTIFS(N13:N286, "partner"),"") -> 2 | Q5: Email | R5: =IFERROR(COUNTIF(H13:H286,Q5),"") -> 0 | S5: Instagram | T5: =IFERROR(COUNTIF(H13:H286,S5),"") -> 0
B6: Total Calls : | C6: =IFERROR(SUM(F2:F6),"") -> 91 | E6: Bad Fit & No Offer: | F6: =IFERROR(COUNTIFS(I13:I287, "Bad Fit & No Offer"),"") -> 0 | H6: Bookings: | I6: =IFERROR(SUM(F2:F10),"") -> 110 | K6: Show-Up Rate: | L6: =iferror(I7/I6,"") -> 0.82727273 | N6: Fear | O6: =IFERROR(COUNTIFS(N13:N286, "fear"),"") -> 2 | Q6: Facebook | R6: =IFERROR(COUNTIF(H13:H286,Q6),"") -> 0 | S6: TikTok | T6: =IFERROR(COUNTIF(H13:H286,S6),"") -> 0
B7: Total Won : | C7: =IFERROR(F2+F3,"") -> 43 | E7: Drag Over & Show: | F7: =IFERROR(COUNTIFS(I13:I287, "Drag Over & Show"),"") -> 0 | H7: Shows: | I7: =IFERROR(SUM(F2:F7),"") -> 91 | K7: Conducted Rate: | L7: =IFERROR(I8/I6,"") -> 0.82727273 | N7: Value | O7: =IFERROR(COUNTIFS(N14:N287, "value"),"") -> 0 | Q7: Facebook Ads | R7: =IFERROR(COUNTIF(H13:H286,Q7),"") -> 0 | S7: Google | T7: =IFERROR(COUNTIF(H13:H286,S7),"") -> 0
B8: Total Lost : | C8: =COUNTIF(I13:I286,"offer & didn't buy")+countif(I13:I286,"deposit")+countif(I13:I286,"bad fit & no offer") -> 48 | E8: Rescheduled: | F8: =IFERROR(COUNTIFS(I13:I287, "Rescheduled"),"") -> 0 | H8: Calls: | I8: =IFERROR(SUM(F2:F6),"") -> 91 | Q8: LinkedIn | R8: =IFERROR(COUNTIF(H13:H286,Q8),"") -> 0 | S8: Referral | T8: Referral
B9: Closing % : | C9: =iferror(SUM(C7/C6),"") -> 0.47252747 | E9: Cancelled: | F9: =IFERROR(COUNTIFS(I13:I287, "Cancelled"),"") -> 5 | H9: Offers: | I9: =IFERROR(sum(F2:F5),"") -> 91
C10: =C3/C6 -> 3461.5385 | E10: No-Show: | F10: =IFERROR(COUNTIFS(I13:I287, "No-Show"),"") -> 14 | H10: Deals | I10: =F2+F3 -> 43
B12: Date | C12: Name | E12: Phone No. | F12: IG-handle | H12: Source | I12: Outcome | K12: Revenue | L12: Cash | N12: Objection | O12: Objection Notes | Q12: Length | R12: Recording Link | S12: Follow Up/Next Steps | T12: Call Summary
B13: 45662 | C13: Rune | E13: 29 91 97 07 | H13: Setter | I13: Split-Pay | K13: 8700 | L13: 2700 | Q13: 6 mdr | S13: Closed
B14: 45662 | C14: Marcus Poulsen | E14: 53 70 41 15 | F14: Marcus Poulsen | H14: Setter | I14: Split-Pay | K14: 8700 | L14: 2700 | Q14: 6 mdr | S14: Closed
B15: 45662 | C15: Mikkel touvdal | E15: 71 78 98 52 | F15: Mikkel touvdal | H15: Setter | I15: Split-Pay | K15: 8700 | L15: 2700 | Q15: 6 mdr | S15: Closed
B16: 45662 | C16: Christian | E16: 50 39 78 05 | F16: Christian Veselinovski | H16: Setter | I16: Split-Pay | K16: 5500 | L16: 2500 | Q16: 4 mdr | S16: Closed
B17: 45662 | C17: Benjamin | E17: 28 51 68 13 | F17: Benjaminnymann0 | H17: Setter | I17: Split-Pay | K17: 8700 | L17: 2700 | Q17: 6 mdr | S17: Closed | T17: Ingen deposit da manden var på farten, men han betaler 1500 d 1 og 1200 hver måned
B18: 45662 | C18: Valdemar Drejer hansen | E18: 42 72 12 78 | F18: Valdemar Drejer hansen | H18: Setter | I18: Deposit | L18: 100 | Q18: 6 mdr | S18: Closed
B19: 45662 | C19: Jonas Clausen | E19: 61 30 82 12 | F19: Jonas Clausen | H19: Setter | I19: Split-Pay | K19: 5100 | L19: 2700 | Q19: 3 mdr | S19: Closed
B20: 45662 | C20: Marcus | E20: 42 78 43 25 | F20: Marcushff | H20: Setter | I20: Offer & Didn't Buy | N20: Money | O20: penge | S20: Hot Follow Up | T20: han var i bund og grund klar, vi havde sat deposit op, men han hoppede fra. så han skal følges op på lønningsdag
B21: 45662 | C21: Jay | E21: 22 27 04 20 | F21: Jayegbach | H21: Setter | I21: Split-Pay | K21: 8700 | L21: 2700 | Q21: 6 mdr | S21: Closed
B22: 45662 | C22: Elias Busk Hansen | E22: 50 66 39 31 | F22: Elias Busk Hansen | H22: Setter | I22: Offer & Didn't Buy | N22: Money | O22: Money | S22: Follow Up | T22: Han er fin at følge op på, men penge holdte ham tilbage
B23: 45662 | C23: Christian Laursen | E23: 31 39 48 18 | F23: Christian Laursen | H23: Setter | I23: Split-Pay | K23: 8700 | L23: 2700 | Q23: 6 mdr | S23: Closed
B24: 45662 | C24: Stubbe | E24: 42 16 64 76 | F24: stubbe_junior | H24: Setter | I24: Split-Pay | K24: 6300 | L24: 2700 | Q24: 4 mdr | S24: Closed
B25: 45662 | C25: Robert rankeberg | E25: 24 21 00 94 | F25: Robert rankeberg | H25: Setter | I25: Split-Pay | K25: 6300 | L25: 2700 | Q25: 4 mdr | S25: Closed
B26: 45662 | C26: Sebastian pedersen | E26: 42 25 01 01 | F26: Sebastian pedersen | H26: Setter | I26: No-Show
B27: 45693 | C27: Mikkel | E27: 20 43 74 48 | F27: mikkel234s | H27: Setter | I27: Offer & Didn't Buy | N27: Partner | O27: Han skulle snakke med fruen | S27: Hot Follow Up | T27: Skal snakke med ham igen imorgen!
B28: 45693 | C28: Faik | E28: 71 49 17 44 | F28: Faik_1206 | H28: Setter | I28: Split-Pay | K28: 8700 | L28: 2700 | Q28: 6 mdr | S28: Closed
B29: 45693 | C29: Jeppe | E29: 28 18 80 17 | F29: Jeppe S. Nymark | H29: Setter | I29: Split-Pay | K29: 5100 | L29: 2700 | Q29: 3 mdr | S29: Closed
B30: 45693 | C30: Jannick | E30: 50 42 52 26 | F30: Jannickhalme | H30: Setter | I30: Offer & Didn't Buy | N30: Money | O30: Penge | S30: Hot Follow Up | T30: Han var super frisk, men han havde for høje omkostninger
B31: 45693 | C31: Mikkel | E31: 52 81 55 82 | F31: M.hc2620 | H31: Setter | I31: Deposit | Q31: 3 mdr | S31: Deposit (Follow Up Set) | T31: Han betaler og starter d 1 juni
B32: 45693 | C32: Oliver | E32: 22 82 12 57 | F32: oli13106 | H32: Setter | I32: Split-Pay | K32: 5100 | L32: 2700 | Q32: 3 mdr | S32: Closed
B33: 45693 | C33: John | E33: 53 89 25 26 | F33: johnsarfo04 | H33: Setter | I33: Split-Pay | K33: 8700 | L33: 2700 | Q33: 6 mdr | S33: Closed
B34: 45693 | C34: Jacob | E34: 30 38 60 35 | F34: _jacob_olsen | H34: Setter | I34: Full-Pay | K34: 7200 | L34: 7200 | Q34: 6 mdr | S34: Closed
B35: 45721 | C35: Emil Jægershof Rudbeck | E35: 25 70 00 74 | F35: Emil Jægershof Rudbeck | H35: Setter | I35: Offer & Didn't Buy | N35: Money | O35: Penge | S35: Follow Up | T35: Han havde et fuldtids arbejde, boede ude og havde en del omkostninger, så han synes at prisen ikke lige passede ind, men ellers var han super varm!
B36: 45721 | C36: Frederik mogensen | E36: 61 73 14 95 | F36: Frederik mogensen | H36: Setter | I36: Offer & Didn't Buy | N36: Think About It | O36: tænke over det | S36: Follow Up | T36: han lød super frisk, men lige da vi kom til prisen, så begyndte han at lagge, sagde han skulle give mig svar tilbage 30 min efter kaldet og vi hørte aldrig fra ham igen
B37: 45721 | C37: Frederik | E37: 25 98 05 98 | F37: frederik_norre_henriksen | H37: Setter | I37: No-Show | O37: Adam blokere
B38: 45721 | C38: Lucas Sørensen | E38: 42 64 43 17 | F38: Lucas Sørensen | H38: Setter | I38: Split-Pay | K38: 5400 | L38: 2800 | Q38: 3 mdr | S38: Closed
B39: 45721 | C39: Niklas | E39: 21 32 83 73 | F39: 21 32 83 73 | H39: Setter | I39: Offer & Didn't Buy | N39: Think About It | O39: Han havde ikke penge til det | S39: Follow Up | T39: Han var 17 år gammel og var super klar til at starte op. Lige da vi kommer til betalingen, så laggede han. tror det var fordi han troede det var 1500kr første måned og ikke 2800kr
B40: 45721 | C40: Samuel | E40: 81 61 45 28 | F40: Samuel_hanning | H40: Setter | I40: Split-Pay | K40: 5400 | L40: 2800 | Q40: 3 mdr | S40: Closed
B41: 45752 | C41: Sefa | E41: 42 76 15 68 | F41: Sefo_bdk | H41: Setter | I41: Split-Pay | K41: 8700 | L41: 2700 | Q41: 6 mdr | S41: Closed
B42: 45782 | C42: Lui | E42: 61 54 42 55 | F42: Lui_Clausen | H42: Setter | I42: Offer & Didn't Buy | N42: Money | O42: Han havde ikke penge | S42: Follow Up | T42: Han var super klar og skulle snart til at uddanne sig til mekaniker, så for nu havde han ikke penge til det
B43: 45782 | C43: Nicklas | E43: 22 52 65 93 | F43: Nicklas_schack | H43: Setter | I43: Split-Pay | K43: 8700 | L43: 2700 | Q43: 6 mdr | S43: Closed
B44: 45782 | C44: Marcus | E44: 20 10 07 76 | F44: Marcus | H44: Setter | I44: Offer & Didn't Buy | N44: Think About It | O44: Han ville tænke over det | S44: Follow Up | T44: En person som havde det hårdt økonomisk, men også ville tage sig sammen og komme i god form. Han ville rigtig gerne lige tænke over det. så han kunne give mig svar tilbage indenfor de næste par dage
B45: 45782 | C45: Denis | E45: 71 70 21 78 | F45: Denis_bukvic | H45: Setter | I45: Split-Pay | K45: 6300 | L45: 2700 | Q45: 4 mdr | S45: Closed
B46: 45782 | C46: Lucas | E46: 26 46 02 46 | F46: _lucasmissel_ | H46: Setter | I46: Split-Pay | K46: 4100 | L46: 1700 | Q46: 3 mdr | S46: Closed
B47: 45813 | C47: Lasse | E47: 61 51 79 58 | F47: Lasse_oesterlid | H47: Setter | I47: Offer & Didn't Buy | N47: Think About It | S47: X | T47: person som virkede super frisk, var tømre og var bare klar lige indtil han hørte prisen, så det er et fint follow up
B48: 45813 | C48: Ahmed | E48: 71 59 84 41 | F48: Ahmed.rm1 | H48: Setter | I48: No-Show
B49: 45813 | C49: Kristoffer | E49: 20 80 90 51 | F49: Kristoffer.ks | H49: Setter | I49: Offer & Didn't Buy | N49: Money | O49: penge | S49: Hot Follow Up | T49: han var tømre og fucking varm, men han synes det var mange penge da han boede ude osv osv
B50: 45813 | C50: Lucas | E50: 91 53 01 07 | F50: Luc_bahh | H50: Setter | I50: Offer & Didn't Buy | O50: Penge | S50: X | T50: Han var på deposit, men han hoppede fra da han ikke havde pengene til det
B51: 45843 | C51: Conrad | E51: 22 58 03 09 | F51: Conrad_gerhardt | H51: Setter | I51: Offer & Didn't Buy | N51: Money | O51: penge | S51: X | T51: han gik på gym, 18 år gammel og havde ikke penge til det. dog var han super frisk og klar
B52: 45843 | C52: Guney | E52: 23 96 93 28 | F52: Guney_bb | H52: Setter | I52: Offer & Didn't Buy | N52: Money | O52: penge | S52: Hot Follow Up | T52: guney er 25, tømre men står rigtig dårligt økonomisk. han kommer 100% tilbage til sommer eller efter sommer
B53: 45843 | C53: Nicklas | E53: 93 92 15 28 | F53: Nicklasdarlyng | H53: Setter | I53: Offer & Didn't Buy | N53: Money | O53: penge | S53: Hot Follow Up | T53: nicklas, 17 år gammel, tømre, vold klar men han havde ingen penge og er rigtig god at tage fat i ved lønningsdag
B54: 45843 | C54: Magnus | E54: 22 81 89 70 | F54: magnusgulloev | H54: Setter | I54: Offer & Didn't Buy | N54: Money | O54: penge | S54: Hot Follow Up | T54: magnus 17 år gammel, arbejde fuldtid på burgerking, var vold klar og rigtig varmt lead, men han synes det var for mange penge
B55: 45843 | C55: Mathias | E55: 25 60 26 50 | F55: Mathias6710 | H55: Setter | I55: No-Show
B56: 45843 | C56: Yousef | E56: 42 55 52 63 | F56: Yousefali_al | H56: Setter | I56: Offer & Didn't Buy | N56: Think About It | O56: tænke over det | S56: Hot Follow Up | T56: han har et fuldtidsarbejde, super frisk, lige da vi kommer til betaling siger han at han vil tænke over det og lige undersøge markedet
B57: 45874 | C57: Christian | E57: 61 65 58 52 | F57: Christianm0ller | H57: Setter | I57: Split-Pay | K57: 8700 | L57: 2700 | Q57: 6 mdr | S57: Closed
B58: 45874 | C58: Mohammed ali al-jab | E58: 20 77 18 94 | F58: Mohammed ali al-jab | H58: Setter | I58: Offer & Didn't Buy | N58: Money | O58: penge | S58: Follow Up | T58: fuldtidsarbejde, penge haltede og han var ellers super klar og frisk. han ledte efter det billige og derfor ville undersøge markedet. fint follow up
B59: 45874 | C59: Daniel Nielsen | E59: 31 48 90 08 | F59: Daniel Nielsen | H59: Setter | I59: Split-Pay | K59: 5400 | L59: 2700 | Q59: 3 mdr | S59: Closed
B60: 45905 | C60: Miguel | E60: 42 33 35 61 | F60: Migu_vb | H60: Setter | I60: Offer & Didn't Buy | N60: Think About It | O60: fuld frisk | S60: Hot Follow Up | T60: han var fuld frisk, han skulle ordne betalingen da han kom hjem og skulle ringe til ham. jeg hørte aldrig fra ham igen og han tog ikke telefonen.
B61: 45905 | C61: Casper | E61: 26 83 10 40 | F61: Casper_med_c | H61: Setter | I61: Full-Pay | K61: 5000 | L61: 5000 | Q61: 4 mdr | S61: Closed
B62: 45935 | C62: Noah | E62: 60 52 06 98 | F62: Noah.lindblom | H62: Setter | I62: No-Show
B63: 45935 | C63: Marcus | E63: 29 85 57 69 | F63: Marcuslarsen3002 | H63: Setter | I63: Split-Pay | K63: 8700 | L63: 2700 | Q63: 6 mdr | S63: Closed | T63: han starter i slutningen af måneden d 30
B64: 45935 | C64: Sami | E64: 22 85 55 17 | F64: Samiouchrif | H64: Setter | I64: Offer & Didn't Buy | N64: Money | O64: penge | S64: Follow Up | T64: han var super frisk. 25 år studere, vi fandt på en betalingsløsning som fungerede for ham, han betaler og smider sine oplysninger ind lige indtil jeg får en besked fra ham 30 min efter hvor han siger damen blev sur fordi de ikke har økonomien til det, men han kommer tilbage om nogen måneder sagde han
B65: 45966 | C65: Jannick | E65: 52 19 07 12 | F65: Jannick_emanu | H65: Setter | I65: Cancelled | O65: manden blokere mig
B66: 45966 | C66: Patrick | E66: 52 40 24 38 | F66: Patrick_jacobsen98 | H66: Setter | I66: No-Show
B67: 45966 | C67: Justhoel1 | E67: 31 38 23 40 | F67: Justhoel1 | H67: Setter | I67: Cancelled
B68: 45966 | C68: Emil | E68: 42 21 92 90 | F68: Emil_rothemejer | H68: Setter | I68: Offer & Didn't Buy | N68: Money | O68: penge | S68: Hot Follow Up | T68: 17 år, tømre, lige fået første paycheck, han var fuld klar og frisk, men han synes pengene var for mange og tilbød også andre måder men han ville vente, så det er et godt follow up lead
B69: 45966 | C69: Emil | E69: 49 40 47 20 | F69: Emil.saaby | H69: Setter | I69: Offer & Didn't Buy | N69: Money | O69: penge | S69: Hot Follow Up | T69: 21 år, arbejde i elgiganten + studere, pengene er ikke høje, men han var fuld frisk og ville vende tilbage når han var 100% klar - rigtig godt follow up lead
B70: 45996 | C70: Jonas | E70: 42 20 27 57 | F70: Jonas_niklasson18 | H70: Setter | I70: Offer & Didn't Buy | N70: Money | O70: penge | S70: Hot Follow Up | T70: 19 år gammel, tømre, vil gerne tabe sig, han var vold frisk og gerne ville igang også selv efter han hørte prisen, men så ville han snakke med sin mor om det og får 10 min efter en besked fra ham at han ikke er klar
B71: 45996 | C71: Mohammed | E71: 93 60 78 12 | F71: M_hugo1 | H71: Setter | I71: No-Show
B72: 45996 | C72: Valentin | E72: 50 53 36 56 | F72: Valentinmoljan | H72: Setter | I72: Offer & Didn't Buy | N72: Money | O72: penge | S72: Follow Up | T72: 40 årige mand, børn, vejer 120kg, ville gerne tabe sig og ville gerne igang. han har lige fået nyt job, så han ville vente til om nogen måneder hvor økonomien var stabil
B73: 45996 | C73: Silas ask hansen | E73: 93 92 72 04 | F73: Silas ask hansen | H73: Setter | I73: Offer & Didn't Buy | N73: Money | O73: penge | S73: Follow Up | T73: 16 årige dreng, 2000kr tjener han om måneden, vil gerne igang, men giver ikke mening for ham lige nu
B74: 45996 | C74: Ali Mohammed | E74: 31 89 69 68 | F74: _alimohammed05_ | H74: Setter | I74: Offer & Didn't Buy | O74: no comment | S74: X | T74: no comment
B75: 13/05/2025 | C75: Stefan | E75: 52 58 58 48 | F75: StefanKeseric | H75: Setter | I75: Offer & Didn't Buy | N75: Money | O75: penge | S75: Follow Up | T75: stefan, 19 år, elektriker, ville tabe sig og bygge muskelmasse op. han ville rigtig gerne igang, men pengene var hårde, så han ville vende tilbage til slut på måneden hvor han måske ville få løn forhøjelse
B76: 13/05/2025 | C76: Malthe | E76: 25 79 20 71 | F76: Malthe.n | H76: Setter | I76: Offer & Didn't Buy | N76: Money | O76: penge | S76: Follow Up | T76: malthe 20 år, tømre lærling, bor ude, har ejen bil, vejer 127kg og vil gerne kommer under 100kg. Han var sygt klar og ville gerne igang, men han havde ikke råd til det om måneden, så han ville snakke med sine forældre for at hører om de gad hjælpe ham
B77: 14/05/2025 | C77: Mads | E77: 60 87 46 34 | F77: Madsbpedersrn | H77: Setter | I77: Split-Pay | K77: 8700 | L77: 2700 | Q77: 6 mdr | S77: Closed
B78: 14/05/2025 | C78: Oliver | E78: 51 14 71 14 | F78: Olivermlindh | H78: Setter | I78: Split-Pay | K78: 5,400.00 kr. | L78: 2700 | Q78: 3 mdr | S78: Closed
B79: 14/05/2025 | C79: Marcus | E79: 31 92 61 40 | F79: Bergmanden | H79: Setter | I79: Offer & Didn't Buy | N79: Money | O79: konto spærret | S79: Hot Follow Up | T79: 25 årige mand, arbejde 190 timer om måneden. han ville oprtigt gerne igang, men han kom med opjection inden betaling at hans konto var spærret og han lød oprigtig, så vi aftalte at tales ved 3 timer efter for at finde en løsning og hørta aldrig fra ham igen
B80: 14/05/2025 | C80: Jakob | E80: 22 89 86 91 | F80: Jakobfjord1 | H80: Setter | I80: No-Show
B81: 14/05/2025 | C81: Mads housgard | E81: 31 79 20 51 | F81: Mads housgard | H81: Setter | I81: Cancelled | L81: 100 | S81: Hot Follow Up | T81: han skulle starte d 1 juni, men han valgte at springe fra, da han synes det ikke gav særlig god mening, så han skal bare kontaktes igen om nogen måneder!
B82: 14/05/2025 | C82: M.BAZI | E82: 93 80 95 88 | F82: M.BAZI | H82: Setter | I82: Offer & Didn't Buy | N82: Money | O82: penge | S82: Hot Follow Up | T82: 25 årige mand, ville gerne shredde ned, han var ready, men han kunne først financielt i juni, da han kunne sælge en bil som ville give ham en masse penge.
B83: 14/05/2025 | C83: Ali Abedrazak | E83: 46 76 086 35 51 | F83: Ali Abedrazak | H83: Setter | I83: No-Show
B84: 14/05/2025 | C84: Lukas | E84: 41 83 82 14 | F84: Lukaswitek | H84: Setter | I84: Split-Pay | K84: 8700 | L84: 2700 | Q84: 6 mdr | S84: Closed
B85: 15/05/2025 | C85: Valdemar | E85: 31 31 86 76 | F85: Valdemarrb | H85: Setter | I85: Split-Pay | K85: 8700 | L85: 2700 | Q85: 6 mdr | S85: Closed
B86: 15/05/2025 | C86: Adam | E86: 50 92 96 28 | F86: Adam.herskind | H86: Setter | I86: Split-Pay | K86: 8700 | L86: 2700 | Q86: 6 mdr | S86: Closed
B87: 15/05/2025 | C87: Jeppe | E87: 60 87 08 19 | F87: Jeppe_c_nielsen | H87: Setter | I87: No-Show
B88: 15/05/2025 | C88: Fabian | E88: 91 56 82 30 | F88: Fabian | H88: Setter | I88: Offer & Didn't Buy | N88: Think About It | O88: Snakke med sin fam | S88: Hot Follow Up | T88: Jeppe, 20 år, mekaniker, rigtig varmt lead som gerne vil bygge muskelmasse op. han har lige købt bil, så han kan først d 1 og så ville han snakke med sine forældre
B89: 15/05/2025 | C89: Jacob | E89: 30 48 78 82 | F89: 3229jacob | H89: Setter | I89: Offer & Didn't Buy | N89: Time | S89: X | T89: Han var rigtigt på deposit, men han vaglte at hoppe fra da han ikke var 100% klar endnu
B90: 15/05/2025 | C90: Nicklas | E90: 53 50 08 80 | F90: Nicklss_bramm_ | H90: Setter | I90: No-Show
B91: 15/05/2025 | C91: Onur | E91: 31 42 76 26 | F91: Onur.koybasi | H91: Setter | I91: Offer & Didn't Buy | N91: Money | O91: Penge | S91: X | T91: Onur, 18 år, går på gym, arbejder i 365, ville tabe sig og virkede rigtig klar, men han synes det var for dyrt, så ikke et godt follow up lige pt ihvertfald
B92: 16/05/2025 | C92: Benjamin | E92: 91 55 20 68 | F92: Benjamin_stavnhoj | H92: Setter | I92: Offer & Didn't Buy | N92: Think About It | O92: han skulle snakke med komunnen | S92: Hot Follow Up | T92: han giver svar tilbage d 19, da han skulle snakke med kommunen, da det er noget med at de styre hans løn osv osv
B93: 16/05/2025 | C93: Hesham Alfakih | E93: 30 49 42 77 | F93: Hesham Alfakih | H93: Setter | I93: Offer & Didn't Buy | N93: Fear | O93: han lagde på da han skulle betale | S93: Follow Up | T93: han var super varm, havde et fuldtidsarbejde og 18 år gammel. han skulle lige til at betale lige indtil manden lægger på!
B94: 17/05/2025 | C94: Jeppe | E94: 20 51 61 28 | F94: Calman_17 | H94: Setter | I94: Split-Pay | K94: 8700 | L94: 2700 | Q94: 6 mdr | S94: Closed
B95: 17/05/2025 | C95: Tobias | E95: 42 77 05 17 | F95: Tobiasprivat4 | H95: Setter | I95: Offer & Didn't Buy | N95: Time | O95: cutte til næste sommer | S95: Hot Follow Up | T95: super varm person, han ville først cutte til sommer og ikke noget nu, selvom jeg prøvede at overtale ham til at kører et minicut nu
B96: 17/05/2025 | C96: Kenan | E96: 26 33 16 04 | F96: Kenankau | H96: Setter | I96: Offer & Didn't Buy | N96: Money | O96: penge | S96: Hot Follow Up | T96: kenan, 37 år, kok, vil gerne tabe sig 10-15kg, da han var rigtig træt af at være ude af form. overall RIGTIG varm, men han kunne ikke helt comitte sig selv, selvom jeg prøvede. rigtig godt lead når der kommer løn ind og køres et offer på ham
B97: 18/05/2025 | C97: Malthe | E97: 60 65 87 57 | F97: Malthe.mortensen.3 | H97: Setter | I97: Split-Pay | K97: 8700 | L97: 2700 | Q97: 6 mdr | S97: Closed
B98: 18/05/2025 | C98: Hannibal | E98: 42 71 32 23 | F98: Hannibal130107 | H98: Setter | I98: Split-Pay | K98: 8200 | L98: 2200 | Q98: 6 mdr | S98: Closed
B99: 19/05/2025 | C99: Kim | E99: 60 46 47 04 | F99: Kimideppili69 | H99: Setter | I99: Split-Pay | K99: 8700 | L99: 2700 | Q99: 6 mdr | S99: Closed
B100: 19/05/2025 | C100: Alexander | E100: 52 90 47 21 | F100: Boellemis37 | H100: Setter | I100: Split-Pay | K100: 8700 | L100: 2700 | Q100: 6 mdr | S100: Closed
B101: 19/05/2025 | C101: Ciwan | E101: 71 53 71 13 | F101: Jowan.haji88 | H101: Setter | I101: Cancelled
...

Sheet Jun
B1: Rep: | C1: Name | E1: Outcome | H1: KPIs% | K1: Show Rate | N1: Objections | Q1: Source | U1: Tracking
E2: Full-Pay: | F2: =IFERROR(COUNTIFS(I13:I288, "Full-Pay"),"") -> 14 | H2: Conversion Rate: | I2: =iferror(I10/I8,"") -> 0.34259259 | K2: Rescheduling Rate: | L2: =iferror(F8/I6,"") -> 0.075342466 | N2: Think About It | O2: =IFERROR(COUNTIFS(N13:N287, "think about it"),"") -> 17 | Q2: Reschedule | R2: =IFERROR(COUNTIF(H13:H287,Q2),"") -> 0 | S2: Cold Call | T2: =IFERROR(COUNTIF(H13:H287,S2),"") -> 0
B3: Revenue | C3: =IFERROR(SUM(K13:K284),"") -> 289200 | E3: Split-Pay: | F3: =IFERROR(COUNTIFS(I13:I288, "Split-Pay"),"") -> 23 | H3: Offer To Close Rate: | I3: =IFERROR(I10/I9,"") -> 0.34579439 | K3: Cancellation Rate: | L3: =iferror(F9/I6,"") -> 0.02739726 | N3: Money | O3: =IFERROR(COUNTIFS(N13:N287, "money"),"") -> 31 | Q3: YouTube | R3: =IFERROR(COUNTIF(H13:H287,Q3),"") -> 0 | S3: Twitter | T3: =IFERROR(COUNTIF(H13:H287,S3),"") -> 0
B4: Cash | C4: =IFERROR(SUM(L13:L285),"") -> 162400 | E4: Deposits: | F4: =IFERROR(COUNTIFS(I13:I288, "Deposit"),"") -> 9 | H4: Call To Offer Rate: | I4: =IFERROR(I9/I8,"") -> 0.99074074 | K4: No-Shows Rate: | L4: =iferror(F10/I6,"") -> 0.15753425 | N4: Time | O4: =IFERROR(COUNTIFS(N13:N287, "time"),"") -> 6 | Q4: YouTube Ads | R4: =IFERROR(COUNTIF(H13:H287,Q4),"") -> 0 | S4: Skool | T4: =IFERROR(COUNTIF(H13:H287,S4),"") -> 0
E5: Offer & Didn't Buy: | F5: =IFERROR(COUNTIFS(I13:I288, "Offer & Didn't Buy"),"") -> 61 | H5: Drag Over Rate: | I5: =IFERROR(F7/(C6+F7+F8),"") -> 0 | K5: Drag Over Rate: | L5: =iferror(F7/I6,"") -> 0 | N5: Partner | O5: =IFERROR(COUNTIFS(N13:N287, "partner"),"") -> 0 | Q5: Email | R5: =IFERROR(COUNTIF(H13:H287,Q5),"") -> 0 | S5: Instagram | T5: =IFERROR(COUNTIF(H13:H287,S5),"") -> 0
B6: Total Calls : | C6: =IFERROR(SUM(F2:F6),"") -> 108 | E6: Bad Fit & No Offer: | F6: =IFERROR(COUNTIFS(I13:I288, "Bad Fit & No Offer"),"") -> 1 | H6: Bookings: | I6: =IFERROR(SUM(F2:F10),"") -> 146 | K6: Show-Up Rate: | L6: =iferror(I7/I6,"") -> 0.73972603 | N6: Fear | O6: =IFERROR(COUNTIFS(N13:N287, "fear"),"") -> 6 | Q6: Facebook | R6: =IFERROR(COUNTIF(H13:H287,Q6),"") -> 0 | S6: TikTok | T6: =IFERROR(COUNTIF(H13:H287,S6),"") -> 0
B7: Total Won : | C7: =IFERROR(F2+F3,"") -> 37 | E7: Drag Over & Show: | F7: =IFERROR(COUNTIFS(I13:I288, "Drag Over & Show"),"") -> 0 | H7: Shows: | I7: =IFERROR(SUM(F2:F7),"") -> 108 | K7: Conducted Rate: | L7: =IFERROR(I8/I6,"") -> 0.73972603 | N7: Value | O7: =IFERROR(COUNTIFS(N14:N288, "value"),"") -> 0 | Q7: Facebook Ads | R7: =IFERROR(COUNTIF(H13:H287,Q7),"") -> 0 | S7: Google | T7: =IFERROR(COUNTIF(H13:H287,S7),"") -> 0
B8: Total Lost : | C8: =COUNTIF(I13:I287,"offer & didn't buy")+countif(I13:I287,"deposit")+countif(I13:I287,"bad fit & no offer") -> 71 | E8: Rescheduled: | F8: =IFERROR(COUNTIFS(I13:I288, "Rescheduled"),"") -> 11 | H8: Calls: | I8: =IFERROR(SUM(F2:F6),"") -> 108 | Q8: LinkedIn | R8: =IFERROR(COUNTIF(H13:H287,Q8),"") -> 0 | S8: Referral | T8: =IFERROR(COUNTIF(H13:H287,S8),"") -> 0
B9: Closing % : | C9: =iferror(SUM(C7/C6),"") -> 0.34259259 | E9: Cancelled: | F9: =IFERROR(COUNTIFS(I13:I288, "Cancelled"),"") -> 4 | H9: Offers: | I9: =IFERROR(sum(F2:F5),"") -> 107
C10: =C3/C6 -> 2677.7778 | E10: No-Show: | F10: =IFERROR(COUNTIFS(I13:I288, "No-Show"),"") -> 23 | H10: Deals | I10: =F2+F3 -> 37
B12: Date | C12: Name | E12: Phone No. | F12: Email | H12: Source | I12: Outcome | K12: Revenue | L12: Cash | N12: Objection | O12: Objection Notes | Q12: Length | R12: Recording Link | S12: Follow Up/Next Steps | T12: Call Summary
B13: 45663 | C13: Michael | E13: 53 50 02 29 | F13: Michaelchristiansen87 | H13: Setter | I13: Split-Pay | K13: 8700 | L13: 2700 | Q13: 6 mdr | S13: Closed | T13: starter og betaler d 1 juni
B14: 45663 | C14: Jonas | E14: 51 36 91 61 | F14: Jonas_skov09 | H14: Setter | I14: Split-Pay | K14: 8700 | L14: 2700 | Q14: 6 mdr | S14: Closed | T14: starter og betaler d 1 juni
B15: 45663 | C15: Mikkel | E15: 52 81 55 82 | F15: M.hc2620 | H15: Setter | I15: Split-Pay | K15: 5100 | L15: 2700 | Q15: 3 mdr | S15: Closed | T15: Han betaler og starter d 1 juni
B16: 45662 | C16: Valdemar Drejer hansen | E16: 42 72 12 78 | F16: Valdemar Drejer hansen | H16: Setter | I16: Deposit | L16: 100 | Q16: 6 mdr | S16: Closed | T16: mangler stadig betaling fra ham
B17: 45663 | C17: Jimmi Pedersen | E17: 29834939 | F17: jimmip1987 | H17: Setter | I17: Split-Pay | K17: 8700 | L17: 2700 | Q17: 6 mdr | S17: Closed | T17: Han starter d 1 juni
B18: 45663 | C18: Maddy | E18: 22 20 06 80 | F18: Kongen_Maddy | H18: Setter | I18: No-Show
B19: 45694 | C19: Adib | E19: 50 51 95 58 | F19: Adib_aa1912 | H19: Setter | I19: Full-Pay | K19: 7200 | L19: 7200 | Q19: 6 mdr | S19: Closed
B20: 45694 | C20: Ademir | E20: 22 71 77 05 | F20: Aboosabanoovic | H20: Setter | I20: Offer & Didn't Buy | N20: Think About It | O20: Økonomien | S20: Follow Up | T20: ældre mand, fuldtidsarbejde, fodbold træner og havde meget travlt, han ville tænke over det for at finde ud af om det gav mening for ham
B21: 45694 | C21: Blerand | E21: 50 70 13 41 | F21: Bleroo_h | H21: Setter | I21: Full-Pay | K21: 7200 | L21: 7200 | Q21: 6 mdr | S21: Closed
B22: 45694 | C22: Mikkel | E22: 42 91 62 43 | F22: Frandsennn | H22: Setter | I22: Offer & Didn't Buy | N22: Money | O22: Penge | S22: X | T22: ung fyr som ikke havde pengene til det, men han var super varm!
B23: 45694 | C23: Magnus | E23: 27 15 55 06 | F23: Magnus.022 | H23: Setter | I23: No-Show
B24: 45694 | C24: Oscar | E24: 42 37 70 13 | F24: Oscarbundgaard4 | H24: Setter | I24: Split-Pay | K24: 6300 | L24: 2700 | Q24: 6 mdr | S24: Closed
B25: 45722 | C25: Kasper | E25: 42 43 53 66 | F25: Kasperbg22 | H25: Setter | I25: Split-Pay | K25: 5100 | L25: 2700 | Q25: 3 mdr | S25: Closed
B26: 45722 | C26: Milan | E26: 28 12 28 09 | F26: Milan_ban | H26: Setter | I26: Offer & Didn't Buy | N26: Think About It | S26: Follow Up | T26: ældre herre, fuldtidsarbejde, ville gerne tabe sig og stå skarpt, men han havde ikke besluttet sig, så han ville tænke over det
B27: 45722 | C27: Mikkel | E27: 60 56 59 26 | F27: Mikkel.dencker | H27: Setter | I27: No-Show
B28: 45722 | C28: Noah | E28: 50 11 64 65 | F28: Noahstreett | H28: Setter | I28: Offer & Didn't Buy | N28: Money | O28: Penge | S28: Hot Follow Up | T28: Han var vold klar lige indtil han fandt ud af at det var 1500+1200 første måned, så han skal kontaktes igen og give ham noget tilbud på opstart
B29: 45753 | C29: Frederik | E29: 50 71 00 09 | F29: Frederik_damsgaard_ | H29: Setter | I29: Offer & Didn't Buy | N29: Money | O29: penge | S29: Follow Up | T29: Han havde ikke pengene til det. en average gym dreng som arbejdede i ny og næ
B30: 45753 | C30: Linus | E30: 61 41 58 45 | F30: Linus_leffler | H30: Setter | I30: Offer & Didn't Buy | N30: Time | O30: han skulle på højskole | S30: Follow Up | T30: Han var fkn ready, men han skulle på højskole så han er klar til dec senere i år
B31: 45783 | C31: Mads | E31: 31 15 04 52 | F31: Madsdragsbaek | H31: Setter | I31: Offer & Didn't Buy | N31: Money | O31: Penge | S31: Follow Up | T31: Han var totalt klar, men pengene var ikke til det lige nu. han skrev at havde det været 700-800, så havde han været klar nu
B32: 45814 | C32: Gustav Poulsen | E32: 22 22 08 73 | F32: Gustav Poulsen | H32: Setter | I32: Offer & Didn't Buy | N32: Think About It | O32: penge | S32: X | T32: Han havde slet ikke penge til det, men han lød super varm
B33: 45814 | C33: Jonas | E33: 42 83 54 48 | F33: Jonas.Kyndesen | H33: Setter | I33: Offer & Didn't Buy | N33: Think About It | O33: Ikke comittet | S33: X | T33: Han var slet ikke comittet og virkede totalt træls på en måde
B34: 45814 | C34: Sebastian | E34: 53386494 | F34: Sebastianhalsted | H34: Setter | I34: Offer & Didn't Buy | N34: Money | O34: penge | S34: Follow Up | T34: 17 år, får arbejde d 1 august, så der skal han kontaktes igen, da han lige nu kun går på skole og rigtig varm gut
B35: 45814 | C35: Noah | E35: 30 31 72 07 | F35: Noah_toft | H35: Setter | I35: Split-Pay | K35: 8700 | L35: 2700 | Q35: 6 mdr | S35: Closed
B36: 45814 | C36: Simon | E36: 71 72 98 36 | F36: Simon_nordbylino | H36: Setter | I36: Deposit | Q36: 6 mdr | S36: Deposit (Follow Up Set) | T36: starter op d 5 august
B37: 45814 | C37: Artan | E37: 42 83 74 78 | F37: Artan_rmz | H37: Setter | I37: Offer & Didn't Buy | N37: Time | S37: X | T37: Meget spøjs gut
B38: 45814 | C38: Kenneth | E38: 22 54 10 67 | F38: silva.beatbox | H38: Setter | I38: Full-Pay | K38: 7200 | L38: 7200 | Q38: 6 mdr | S38: Closed
B39: 45814 | C39: Lucas | E39: 50 25 93 38 | F39: lucas_fussing | H39: Setter | I39: Full-Pay | K39: 7200 | L39: 7200 | Q39: 6 mdr | S39: Closed
B40: 45844 | C40: Aleksander | E40: 53 85 13 07 | F40: Aleksander.kamp | H40: Setter | I40: Full-Pay | K40: 7200 | L40: 7200 | Q40: 6 mdr | S40: Closed
B41: 45844 | C41: Bertram | E41: 30 27 51 55 | F41: Bertramlindrasmussen | H41: Setter | I41: Offer & Didn't Buy | N41: Think About It | O41: tænke over det | S41: Hot Follow Up | T41: Han var vold varm, tømre, men skulle lige hjem og tjekke det hele igennem og så ville han give svar!
B42: 45844 | C42: Magnus | E42: 42 25 38 49 | F42: Magnus_martinus | H42: Setter | I42: Offer & Didn't Buy | N42: Money | O42: Penge | S42: Follow Up | T42: 20 år, elektriker, super demotiveret og slet ikke comittet
B43: 45844 | C43: Sebatian | E43: 31 34 84 44 | F43: seb._.coleman | H43: Setter | I43: Offer & Didn't Buy | N43: Money | O43: den skal ikke gå igennem | S43: Hot Follow Up | T43: han var varm og klar til at betale, men den gad ikke gå igennem, så bedte ham om at ringe til sin bank og hørte ikke fra ham igen
B44: 45844 | C44: Boor | E44: 61 37 19 02 | F44: boor_nonsungnoen | H44: Setter | I44: Split-Pay | K44: 8700 | L44: 2700 | Q44: 6 mdr | S44: Closed
B45: 45844 | C45: Simran | E45: 31 34 24 70 | F45: ss.alb_ | H45: Setter | I45: Offer & Didn't Buy | N45: Think About It | O45: Tænke det igennem | S45: Hot Follow Up | T45: Super varm, synes ikke det var for mange penge, men han ville gerne tænke det hele igennem
B46: 45844 | C46: Nicolai | E46: 42 77 09 13 | F46: Nicolai_aastrup_ | H46: Setter | I46: No-Show
B47: 45875 | C47: Jeppe | E47: 52 74 49 72 | F47: Jeppepetri | H47: Setter | I47: Offer & Didn't Buy | N47: Think About It | O47: tænke over det | S47: Hot Follow Up | T47: ældre herre, 1 barn og kone, skulle tænke det hele igennem og arbejder med stilads.
B48: 45875 | C48: Vilum | E48: 51 95 77 45 | F48: Vilumhartvig | H48: Setter | I48: Offer & Didn't Buy | N48: Time | O48: han ville vente til efter hans ferie | S48: Hot Follow Up | T48: han skulle til afrika og ville være hjemme om lidt over en måned, prøvede at smide deposit på ham, men det gad han ikke og ville vente til at han var hjemme
B49: 45875 | C49: Jonas | E49: 50 23 09 37 | F49: Hr.kristensen7160 | H49: Setter | I49: Split-Pay | K49: 8700 | L49: 2700 | Q49: 6 mdr | S49: Closed
B50: 45875 | C50: Patrick | E50: 81 53 73 69 | F50: Patrickhagedorn.76 | H50: Setter | I50: Cancelled
B51: 45875 | C51: Marco | E51: 30 45 59 58 | F51: Marcodang8 | H51: Setter | I51: Offer & Didn't Buy | N51: Money | O51: Ikke råd til det | S51: Follow Up | T51: 17 år og gik stadig i skole. han ville godt når han ramte lærlinge løn
B52: 45875 | C52: Krisstoffer | E52: 91 11 28 29 | F52: Krisstoffer1789 | H52: Setter | I52: No-Show
B53: 45875 | C53: _.2424_ | E53: 50 19 73 41 | F53: _.2424_ | H53: Setter | I53: No-Show | T53: ikke kontakt ham igen
B54: 45875 | C54: Noah | E54: 53 62 83 72 | F54: Noah_jensen_privat_ | H54: Setter | I54: Split-Pay | K54: 7200 | L54: 3600 | Q54: 6 mdr | S54: Closed
B55: 45906 | C55: Adreean | E55: 951-565-6248 | F55: Adreean.valencia | H55: Setter | I55: Offer & Didn't Buy | N55: Money | O55: Penge | S55: Follow Up | T55: Bor i usa, har vinduespudser firma og flytter snart hjem til danmark. han var ikke klar da han ikke havde pengene til det
B56: 45906 | C56: Carl | E56: 30 22 10 96 | F56: Carl.emil.privat | H56: Setter | I56: No-Show
B57: 45906 | C57: Mads | E57: 21 80 50 26 | F57: Madsmogensen_ | H57: Setter | I57: Full-Pay | K57: 4800 | L57: 4800 | Q57: 4 mdr | S57: Closed
B58: 45906 | C58: Anders | E58: 41 14 66 48 | F58: Ascaniuskirk | H58: Setter | I58: Split-Pay | K58: 8700 | L58: 2700 | Q58: 6 mdr | S58: Closed
B59: 45936 | C59: Nicolai | E59: 42 94 19 14 | F59: Lord_nicolaia | H59: Setter | I59: Split-Pay | K59: 8700 | L59: 2700 | Q59: 6 mdr | S59: Closed
B60: 45936 | C60: Daniel | E60: 42 66 41 68 | F60: D.soegaard | H60: Setter | I60: No-Show
B61: 45936 | C61: Lasse | E61: 42 66 41 68 | F61: Lasse_7v52 | H61: Setter | I61: No-Show
B62: 45936 | C62: Mick | E62: 42 66 41 68 | F62: Mickriis | H62: Setter | I62: Deposit | Q62: 6 mdr | S62: Deposit (Follow Up Set) | T62: Starter og betaler d 1 juli
B63: 45936 | C63: Puriaan | E63: 42 66 41 68 | F63: Puriaan | H63: Setter | I63: Offer & Didn't Buy | N63: Money | O63: Penge | S63: X | T63: Han er slet ikke den klient jeg leder efter
B64: 45936 | C64: Silas | E64: 53 59 88 27 | F64: Christiansen.silas | H64: Setter | I64: Split-Pay | K64: 8700 | L64: 2700 | Q64: 6 mdr | S64: Closed
B65: 45936 | C65: Malthe | E65: 22 36 25 35 | F65: Malthedm | H65: Setter | I65: Offer & Didn't Buy | N65: Money | O65: Penge | S65: Follow Up | T65: Rigtig godt follow up om nogen uger eller måneder
B66: 45967 | C66: Fabian | E66: 42 50 40 69 | F66: Fabian.gram123 | H66: Setter | I66: Offer & Didn't Buy | N66: Money | O66: penge | S66: Follow Up | T66: håndværker og arbejder meget. Han var flyttet ud og pengene var for lidt, så han ville vente lidt med det
B67: 45967 | C67: Nicolai | E67: 41 69 23 37 | F67: nicolaikrusell | H67: Setter | I67: Offer & Didn't Buy | N67: Money | O67: Penge | S67: Follow Up | T67: Også håndværker, dog ville han gerne tænke over det, men var rigtig varm og ville gerne igang
B68: 45967 | C68: Benjamin | E68: 42 66 71 99 | F68: Benjaminbrandhoj | H68: Setter | I68: Offer & Didn't Buy | N68: Money | O68: Penge | S68: Hot Follow Up | T68: Håndværker og var sygt klar på at tabe sig. han var klar på at betale full, men hans pung lå i hans bil som hans mor lånte. så han ville betale så snart hun kom hjem og lidt efter fik jeg en besked hvor han synes det var mange penge
B69: 45967 | C69: max | E69: 23 20 49 24 | F69: max_leon_beller | H69: Setter | I69: Offer & Didn't Buy | N69: Money | O69: Penge | S69: Follow Up | T69: 17 år og var i lære som murer, dog gik han kun i skole og tjente ingen penge endnu, så han havde ikke råd til det. dog rigtig varm
B70: 45967 | C70: Frank | E70: 51 68 43 34 | F70: franka_16 | H70: Setter | I70: Offer & Didn't Buy | N70: Money | O70: Penge | S70: X | T70: ikke den klient jeg vil arbejde med
B71: 45967 | C71: Viktor | E71: 23 72 00 70 | F71: viktor_m_j | H71: Setter | I71: No-Show
B72: 45967 | C72: Frederik | E72: 60 15 44 91 | F72: Frederikbrockjohansen | H72: Setter | I72: Offer & Didn't Buy | N72: Fear | O72: slet ikke comittet | S72: X | T72: han var slet ikke comittet nok, selvom det lød til at han gerne ville igang. fint lead at lave follow up på om nogen uger eller måneder
B73: 45967 | C73: Mikkel | E73: 22 44 92 29 | F73: Mikkel_cipek | H73: Setter | I73: Offer & Didn't Buy | N73: Fear | O73: heller ikke comittet | S73: X | T73: også brug for hjælp, men slet ikke comittet og det var svært at rykke på ham, men han ville tænke over det
B74: 45997 | C74: Simon | E74: 51 16 72 58 | F74: Simon_sanggaard_brink | H74: Setter | I74: Cancelled
B75: 45997 | C75: Nicolai | E75: 42 36 48 18 | F75: nicolai_jorgensenn | H75: Setter | I75: No-Show
B76: 14/06/2025 | C76: Anton | E76: 93 60 58 56 | F76: Anton.overgaard | H76: Setter | I76: No-Show
B77: 14/06/2025 | C77: Magnus | E77: 22 77 14 22 | F77: _magzie_ | H77: Setter | I77: Rescheduled
B78: 14/06/2025 | C78: Jeppe | E78: 26 22 68 69 | F78: Jeppe53773 | H78: Setter | I78: Offer & Didn't Buy | N78: Money | O78: Penge | S78: Hot Follow Up | T78: håndværker, frisk gut og var klar på at komme igang. dog ville han vente en måned da han lige var flyttet i hus med kæresten og vidste ikke hvordan budgettet var endnu
B79: 14/06/2025 | C79: Oliver | E79: 22 22 05 70 | F79: Oliverva10 | H79: Setter | I79: Rescheduled
B80: 14/06/2025 | C80: Marcus | E80: 42 68 11 34 | F80: Marcus_sondergaard06 | H80: Setter | I80: Rescheduled
B81: 14/06/2025 | C81: Oscar | E81: 24 59 28 24 | F81: Oscar.lillegaard.barrett | H81: Setter | I81: Rescheduled
B82: 15/06/2025 | C82: Victor | E82: 29 11 11 80 | F82: Victor_edvardsen_ | H82: Setter | I82: Split-Pay | K82: 8700 | L82: 2700 | Q82: 6 mdr | S82: Closed
B83: 15/06/2025 | C83: Emil | E83: 29 11 41 44 | F83: e_degn | H83: Setter | I83: Rescheduled
B84: 15/06/2025 | C84: Magnus | E84: 22 77 14 22 | F84: _magzie_ | H84: Setter | I84: No-Show
B85: 15/06/2025 | C85: Marcus | E85: 42 68 11 34 | F85: Marcus_sondergaard06 | H85: Setter | I85: Rescheduled
B86: 15/06/2025 | C86: Oliver | E86: 22 22 05 70 | F86: Oliverva10 | H86: Setter | I86: No-Show
B87: 15/06/2025 | C87: Oscar | E87: 24 59 28 24 | F87: Oscar.lillegaard.barrett | H87: Setter | I87: Rescheduled
B88: 15/06/2025 | C88: Peter | E88: 53 73 93 33 | F88: Peter_klitgaard_klausen | H88: Setter | I88: Rescheduled
B89: 15/06/2025 | C89: Marco | E89: 93 85 42 45 | F89: mr.bronke | H89: Setter | I89: Offer & Didn't Buy | N89: Fear | O89: han fortød | S89: Hot Follow Up | T89: Super frisk gut som bare skulle igang. Han var klar på at starte næste måned, men sendte ham betalingslink og han ville klarer det efter kaldet, da han ikke havde pung på sig og efter skriver han at han har fortrudt, selvom han vejer 120kg og bruger 9k om måneden på junkfood
B90: 15/06/2025 | C90: Erikas | E90: 50 29 18 33 | F90: daddyerikas | H90: Setter | I90: Offer & Didn't Buy | Q90: 6 mdr | S90: Deposit (Follow Up Set) | T90: Betaler og starter d 28 august
B91: 15/06/2025 | C91: Thomas | E91: 60 94 19 52 | F91: jorgensen4503 | H91: Setter | I91: Full-Pay | K91: 7200 | L91: 7200 | Q91: 6 mdr | S91: Closed
B92: 15/06/2025 | C92: Marcus | E92: 42 68 11 34 | F92: marcus_sondergaard06 | H92: Setter | I92: Full-Pay | K92: 7200 | L92: 7200 | Q92: 6 mdr | S92: Closed
B93: 15/06/2025 | C93: Mathias | E93: 60 53 52 59 | F93: mathias7.2 | H93: Setter | I93: Split-Pay | K93: 8700 | L93: 2700 | Q93: 6 mdr | S93: Closed
B94: 16/06/2025 | C94: Emil | E94: 29 11 41 44 | F94: E_degn | H94: Setter | I94: Split-Pay | K94: 8700 | L94: 2700 | Q94: 6 mdr | S94: Closed
B95: 16/06/2025 | C95: Peter | E95: 53 73 93 33 | F95: Peter_klitgaard_klausen | H95: Setter | I95: Offer & Didn't Buy | N95: Think About It | O95: tænke over det | S95: Follow Up | T95: peter, brolægger, arbejder meget men ville spare op til at gå selvstændig, så han var lidt tøvende. Han ville give svar tilbage imorgen og det ved vi godt hvad betyder
B96: 16/06/2025 | C96: Lukas | E96: 30 22 74 89 | F96: Lukas_p557 | H96: Setter | I96: Cancelled
B97: 16/06/2025 | C97: Kasper | E97: 61 67 71 81 | F97: Kasper_winge | H97: Setter | I97: Offer & Didn't Buy | N97: Money | O97: Penge | S97: Follow Up | T97: super godt lead og er klar på at give den gas. lige nu er hans økonomi i vejen, men er nok klar på at starte op i her august eller sep når han har fået betalt hans bøder og alt spiller
B98: 16/06/2025 | C98: Magnus | E98: 24 45 07 48 | F98: Magnus.privaat | H98: Setter | I98: Offer & Didn't Buy | Q98: 6 mdr | S98: X | T98: han var totalt ready og vi starter også op, men han havde problemer med sit kort, så han får styr på det imorgen og så tager vi et opfølgende kald imorgen for at klare betalingen
B99: 16/06/2025 | C99: Oliver | E99: 31 53 93 82 | F99: Oliverhaahrv | H99: Setter | I99: Offer & Didn't Buy | N99: Think About It | O99: penge | S99: Follow Up | T99: han var presset økonomisk, men var vold frisk og bedte ham om at vende tilbage samme dag
B100: 16/06/2025 | C100: Rasmus | E100: 42 61 30 31 | F100: Rasmustc | H100: Setter | I100: Offer & Didn't Buy | N100: Think About It | O100: snakke med andre coaches | S100: Hot Follow Up | T100: vold frisk gut og ville gerne igang, men ville også gerne snakke med andre coaches for at hører mulighederne!
B101: 16/06/2025 | C101: Mads | E101: 21 49 44 24 | F101: madsbrunhoj | H101: Setter | I101: Split-Pay | K101: 8700 | L101: 2700 | Q101: 8 mdr | S101: Closed
...

Sheet Jul
B1: Rep: | C1: Name | E1: Outcome | H1: KPIs% | K1: Show Rate | N1: Objections | Q1: Source | U1: Tracking
E2: Full-Pay: | F2: =IFERROR(COUNTIFS(I13:I287, "Full-Pay"),"") -> 10 | H2: Conversion Rate: | I2: =iferror(I10/I8,"") -> 0.37234043 | K2: Rescheduling Rate: | L2: =iferror(F8/I6,"") -> 0.085714286 | N2: Think About It | O2: =IFERROR(COUNTIFS(N13:N286, "think about it"),"") -> 6 | Q2: Reschedule | R2: =IFERROR(COUNTIF(H13:H286,Q2),"") -> 0 | S2: Cold Call | T2: =IFERROR(COUNTIF(H13:H286,S2),"") -> 0
B3: Revenue | C3: =IFERROR(SUM(K13:K283),"") -> 318600 | E3: Split-Pay: | F3: =IFERROR(COUNTIFS(I13:I287, "Split-Pay"),"") -> 25 | H3: Offer To Close Rate: | I3: =IFERROR(I10/I9,"") -> 0.37634409 | K3: Cancellation Rate: | L3: =iferror(F9/I6,"") -> 0.071428571 | N3: Money | O3: =IFERROR(COUNTIFS(N13:N286, "money"),"") -> 23 | Q3: YouTube | R3: =IFERROR(COUNTIF(H13:H286,Q3),"") -> 0 | S3: Twitter | T3: =IFERROR(COUNTIF(H13:H286,S3),"") -> 0
B4: Cash | C4: =IFERROR(SUM(L13:L284),"") -> 156900 | E4: Deposits: | F4: =IFERROR(COUNTIFS(I13:I287, "Deposit"),"") -> 16 | H4: Call To Offer Rate: | I4: =IFERROR(I9/I8,"") -> 0.9893617 | K4: No-Shows Rate: | L4: =iferror(F10/I6,"") -> 0.17142857 | N4: Time | O4: =IFERROR(COUNTIFS(N13:N286, "time"),"") -> 7 | Q4: YouTube Ads | R4: =IFERROR(COUNTIF(H13:H286,Q4),"") -> 0 | S4: Skool | T4: =IFERROR(COUNTIF(H13:H286,S4),"") -> 0
E5: Offer & Didn't Buy: | F5: =IFERROR(COUNTIFS(I13:I287, "Offer & Didn't Buy"),"") -> 42 | H5: Drag Over Rate: | I5: =IFERROR(F7/(C6+F7+F8),"") -> 0 | K5: Drag Over Rate: | L5: =iferror(F7/I6,"") -> 0 | N5: Partner | O5: =IFERROR(COUNTIFS(N13:N286, "partner"),"") -> 3 | Q5: Email | R5: =IFERROR(COUNTIF(H13:H286,Q5),"") -> 0 | S5: Instagram | T5: =IFERROR(COUNTIF(H13:H286,S5),"") -> 0
B6: Total Calls : | C6: =IFERROR(SUM(F2:F6),"") -> 94 | E6: Bad Fit & No Offer: | F6: =IFERROR(COUNTIFS(I13:I287, "Bad Fit & No Offer"),"") -> 1 | H6: Bookings: | I6: =IFERROR(SUM(F2:F10),"") -> 140 | K6: Show-Up Rate: | L6: =iferror(I7/I6,"") -> 0.67142857 | N6: Fear | O6: =IFERROR(COUNTIFS(N13:N286, "fear"),"") -> 3 | Q6: Facebook | R6: =IFERROR(COUNTIF(H13:H286,Q6),"") -> 0 | S6: TikTok | T6: =IFERROR(COUNTIF(H13:H286,S6),"") -> 0
B7: Total Won : | C7: =IFERROR(F2+F3,"") -> 35 | E7: Drag Over & Show: | F7: =IFERROR(COUNTIFS(I13:I287, "Drag Over & Show"),"") -> 0 | H7: Shows: | I7: =IFERROR(SUM(F2:F7),"") -> 94 | K7: Conducted Rate: | L7: =IFERROR(I8/I6,"") -> 0.67142857 | N7: Value | O7: =IFERROR(COUNTIFS(N14:N287, "value"),"") -> 0 | Q7: Facebook Ads | R7: =IFERROR(COUNTIF(H13:H286,Q7),"") -> 0 | S7: Google | T7: =IFERROR(COUNTIF(H13:H286,S7),"") -> 0
B8: Total Lost : | C8: =COUNTIF(I13:I286,"offer & didn't buy")+countif(I13:I286,"deposit")+countif(I13:I286,"bad fit & no offer") -> 59 | E8: Rescheduled: | F8: =IFERROR(COUNTIFS(I13:I287, "Rescheduled"),"") -> 12 | H8: Calls: | I8: =IFERROR(SUM(F2:F6),"") -> 94 | Q8: LinkedIn | R8: =IFERROR(COUNTIF(H13:H286,Q8),"") -> 0 | S8: Referral | T8: =IFERROR(COUNTIF(H13:H286,S8),"") -> 0
B9: Closing % : | C9: =iferror(SUM(C7/C6),"") -> 0.37234043 | E9: Cancelled: | F9: =IFERROR(COUNTIFS(I13:I287, "Cancelled"),"") -> 10 | H9: Offers: | I9: =IFERROR(sum(F2:F5),"") -> 93
C10: =C3/C6 -> 3389.3617 | E10: No-Show: | F10: =IFERROR(COUNTIFS(I13:I287, "No-Show"),"") -> 24 | H10: Deals | I10: =F2+F3 -> 35
B12: Date | C12: Name | E12: Phone No. | F12: Email | H12: Source | I12: Outcome | K12: Revenue | L12: Cash | N12: Objection | O12: Objection Notes | Q12: Length | R12: Recording Link | S12: Follow Up/Next Steps | T12: Call Summary
C13: Valdemar Drejer hansen | E13: 42 72 12 78 | F13: Valdemar Drejer hansen | H13: Setter | I13: Deposit | L13: 100 | Q13: 6 mdr | S13: Deposit (Follow Up Set) | T13: mangler stadig betaling fra ham
B14: 45664 | C14: Simon | E14: 71 72 98 36 | F14: Simon_nordbylino | H14: Setter | I14: Deposit | Q14: 6 mdr | S14: Deposit (Follow Up Set) | T14: starter op d 20 august
B15: 45664 | C15: Mick | E15: 42 66 41 68 | F15: Mickriis | H15: Setter | I15: Split-Pay | K15: 8700 | L15: 2700 | Q15: 6 mdr | S15: Closed | T15: Starter og betaler d 1 juli
B16: 45664 | C16: Emil | E16: 54 34 67 32 | F16: Emil Munch | H16: Setter | I16: Split-Pay | K16: 8700 | L16: 2700 | Q16: 6 mdr | S16: Closed | T16: starter og betaler d 1 juli | V16: parveenparshant@yahoo.com
B17: 45664 | C17: Oliver | E17: 42 32 00 70 | F17: Oliver_Thyregod | H17: Setter | I17: Split-Pay | K17: 8700 | L17: 2700 | Q17: 6 mdr | S17: Closed | T17: Starter d 7 juli og betaler d 1
B18: 45664 | C18: Oliver | E18: 50 57 73 43 | F18: oliversarto | H18: Setter | I18: Deposit | Q18: 6 mdr | S18: Deposit (Follow Up Set) | T18: starter og betaler d 1 august
B19: 45664 | C19: Kaspar | E19: 28 18 36 14 | F19: Kaspar_privat9 | H19: Setter | I19: Deposit | Q19: 6 mdr | S19: Deposit (Follow Up Set) | T19: starter og betaler d 1 august
B20: 45664 | C20: Thomas | E20: 41 27 20 30 | F20: Thomas_hampen_andersen | H20: Setter | I20: Split-Pay | K20: 10500 | L20: 3000 | Q20: 6 mdr | S20: Closed
B21: 45664 | C21: Mathias | E21: 28 51 05 94 | F21: Mathiashvid12 | H21: Setter | I21: Offer & Didn't Buy | N21: Time | S21: Hot Follow Up | T21: vold varmt lead som gerne ville stå skarpt til hans bryllup hvor ham og hans kone gerne ville blive coachet sammen og de var begge klar på at betale 9kx2 upfront, men han var først klar i det nye år hvilket er træls!
B22: 45695 | C22: Kristian | E22: 50 15 03 56 | F22: Kristiandrechsler | H22: Setter | I22: Deposit | Q22: 6 mdr | S22: Deposit (Follow Up Set) | T22: Starter og betaler d 1 august!
B23: 45695 | C23: Phillip | E23: 29 68 20 12 | F23: Phillipolsen1 | H23: Setter | I23: Split-Pay | K23: 10500 | L23: 3000 | Q23: 6 mdr | S23: Closed
B24: 45723 | C24: Lucca | E24: 60 48 53 55 | F24: lucca_Breck | H24: Setter | I24: No-Show
B25: 45723 | C25: Oliver | E25: 60 48 47 15 | F25: Oliverhallsvensson | H25: Setter | I25: Offer & Didn't Buy | N25: Money | O25: Penge | S25: Hot Follow Up | T25: rigtig godt lead som gerne ville komme i bedre form, men lige gav det ikke mening penge mæssigt, men han var ready så snart der var styr på det hele!
B26: 45723 | C26: phillip | E26: 50 15 03 56 | F26: Phillip_gre_gersen | H26: Setter | I26: Cancelled
B27: 45723 | C27: Nikolai | E27: 29 39 13 98 | F27: Nikolainissen_ | H27: Setter | I27: Cancelled
B28: 45723 | C28: Oliver | E28: 26 31 45 57 | F28: oliver_groening | H28: Setter | I28: Deposit | Q28: 6 mdr | S28: Deposit (Follow Up Set) | T28: starter og betaler d 11 august
B29: 45723 | C29: Thomas | E29: 42 78 67 47 | F29: Thomas.olsen9 | H29: Setter | I29: Split-Pay | K29: 10500 | L29: 3000 | Q29: 6 mdr | S29: Closed
B30: 45723 | C30: Mads | E30: 22 28 71 45 | F30: Madsryttergaardjacobsen | H30: Setter | I30: Offer & Didn't Buy | N30: Time | S30: Hot Follow Up | T30: varmt lead som gerne ville i bedre form. Han vidste godt det ikke var mange penge, men han ville hellere skrive tilbage efter sommeren
B31: 45754 | C31: Lasse | E31: 434 595 517 | F31: Lasdalgaard | H31: Setter | I31: Full-Pay | K31: 9000 | L31: 9000 | Q31: 6 mdr | S31: Closed
B32: 45754 | C32: Dominik | E32: 25 77 80 77 | F32: domcapik | H32: Setter | I32: Offer & Didn't Buy | N32: Money | O32: Penge | S32: Hot Follow Up | T32: varmeste lead som ikke ture at tage springet. han ville gerne tabe sig og stå skarpere. snakkede med ham i 30 min kunne mærke han var klar til at købe, men han kunne bare ikke tage springet
B33: 45754 | C33: Malthe | E33: 23 92 28 08 | F33: malt2662 | H33: Setter | I33: Split-Pay | K33: 10500 | L33: 3000 | Q33: 6 mdr | S33: Closed
B34: 45754 | C34: Mike | E34: 91 99 20 43 | F34: ekelundmike | H34: Setter | I34: No-Show
B35: 45754 | C35: Nicolas | E35: 28 71 73 16 | F35: nicolas_iordanov | H35: Setter | I35: Offer & Didn't Buy | N35: Money | O35: penge | S35: Hot Follow Up | T35: rigtig varmt lead, men pengene var ikke store da han ikke tjente udlærte penge endnu, så han ville skrive når han var ready
B36: 45754 | C36: Victor | E36: 29 71 80 09 | F36: Schwarz0106 | H36: Setter | I36: Split-Pay | K36: 10500 | L36: 3000 | Q36: 6 mdr | S36: Closed
B37: 45815 | C37: Sander | E37: 53 83 80 71 | F37: sander_dam00 | H37: Setter | I37: Offer & Didn't Buy | N37: Money | O37: Penge | S37: Follow Up | T37: han ville gerne igang og bygge mere muskelmasse op, men han var ikke klar til at investere det i forløbet
B38: 45815 | C38: Gustav | E38: 30 23 05 92 | F38: gustavhansen48 | H38: Setter | I38: Cancelled
B39: 45815 | C39: Matin | E39: 91 97 16 68 | F39: Matin.assadi_ | H39: Setter | I39: Offer & Didn't Buy | N39: Money | O39: Penge | S39: Hot Follow Up | T39: Han var så klar og vi nåede endda også at lave en binding, men så skrev han dagen efter at det ikke passede så godt, fordi han havde en masse regninger
B40: 45815 | C40: Frey | E40: 42 15 17 44 | F40: freyager1 | H40: Setter | I40: Offer & Didn't Buy | N40: Money | O40: Penge | S40: Hot Follow Up | T40: Han var så klar og ville bare gerne give den gas og blive større, men han var ikke klar til at investere halvdelen af hans løn hver måned på det
B41: 45845 | C41: Gustav | E41: 60 84 44 20 | F41: gustav_lundgren13 | H41: Setter | I41: Cancelled
B42: 45845 | C42: Milas | E42: 53 29 66 36 | F42: milas.dahlgaard1 | H42: Setter | I42: Offer & Didn't Buy | N42: Money | O42: Penge | S42: Hot Follow Up | T42: Han var klar og allerede haft coach på, men han ville snakke med sin mor først og hørte aldrig fra ham igen!
B43: 45845 | C43: Mike | E43: 50 41 11 65 | F43: dr.dims | H43: Setter | I43: No-Show
B44: 45845 | C44: Mathias | E44: 23 56 09 56 | F44: mathiasfuck8922 | H44: Setter | I44: No-Show
B45: 45845 | C45: Martin | E45: 29 88 73 57 | F45: martinhkjaer7 | H45: Setter | I45: Offer & Didn't Buy | N45: Fear | O45: frygt for at starte | S45: Follow Up | T45: super varmt lead og vidste at han havde pengene, fordi han arbejdede meget. han var bare bange for at tage springet og bruge pengene på det, da han havde hørt meget om coaches
B46: 45845 | C46: Nicolaj | E46: 91 83 50 35 | F46: Nicolajbasland | H46: Setter | I46: No-Show
B47: 45845 | C47: Mads | E47: 29 13 40 54 | F47: _madsskov | H47: Setter | I47: Deposit | Q47: 6 mdr | S47: Deposit (Follow Up Set) | T47: betaler 1 august og starter 1 sep
B48: 45876 | C48: Daniel | E48: 28 97 33 54 | F48: Daniel_moerz | H48: Setter | I48: Split-Pay | K48: 10500 | L48: 3000 | Q48: 6 mdr | S48: Closed
B49: 45876 | C49: Gustav | E49: 60 84 44 20 | F49: Gustav_lundgren123 | H49: Setter | I49: No-Show
B50: 45876 | C50: Laurits | E50: 22 56 74 16 | F50: laurits_viholt | H50: Setter | I50: Deposit | L50: 100 | Q50: 6 mdr | S50: Deposit (Follow Up Set) | T50: starter og betaler d 1 august
B51: 45876 | C51: Viggo | E51: 28 11 72 57 | F51: viggo_mark | H51: Setter | I51: Offer & Didn't Buy | N51: Time | S51: Hot Follow Up | T51: røv varmt lead som rigtig gerne ville igang så snart hans sæson med amerikans fodbold startede, da han skulle cutte der, prøvede at presse men han ville vente
B52: 45907 | C52: William | E52: 51 78 48 10 | F52: Williamjensen18 | H52: Setter | I52: Rescheduled
B53: 45937 | C53: William | E53: 52 17 82 58 | F53: william.kjellberg | H53: Setter | I53: Deposit | L53: 1500 | Q53: 6 mdr | S53: Deposit (Follow Up Set) | T53: han starter d 1 august, men betalte for opstartsgebyr nu
B54: 45937 | C54: William | E54: 60 52 43 24 | F54: Williamtrz | H54: Setter | I54: Offer & Didn't Buy | N54: Money | O54: penge | S54: Hot Follow Up | T54: rigtig god mand, som gerne ville tabe sig og bygge muskelmasse op, men han var ikke klar på at bruge penge på det endnu
B55: 45937 | C55: Tais | E55: 42 53 96 69 | F55: tais_kjaer | H55: Setter | I55: No-Show
B56: 45937 | C56: idk | E56: 41 14 12 36 | F56: J_h_zeerow | H56: Setter | I56: Rescheduled
B57: 45937 | C57: William | E57: 51 78 48 10 | F57: williamjensen18 | H57: Setter | I57: Split-Pay | K57: 6000 | L57: 3000 | Q57: 3 mdr | S57: Closed
B58: 45937 | C58: Marcus | E58: 40 70 99 83 | F58: Marcus_lundager | H58: Setter | I58: Split-Pay | K58: 10500 | L58: 3000 | Q58: 6 mdr | S58: Closed
B59: 45968 | C59: William | E59: 42 66 78 99 | F59: Williamdylandef | H59: Setter | I59: Rescheduled
B60: 13/07/2025 | C60: Thor | E60: 42 92 70 43 | F60: De_sousa2204 | H60: Setter | I60: Full-Pay | K60: 9000 | L60: 9000 | Q60: 6 mdr | S60: Closed
B61: 14/07/2025 | C61: William | E61: 42 66 78 99 | F61: Williamdylander | H61: Setter | I61: Offer & Didn't Buy | N61: Think About It | O61: Tænke over det | S61: Hot Follow Up | T61: Han ville gerne starte med at hører nærmere og var ikke bestemt på kaldet. Han ville tænke over det og give svar dagen efter
B62: 14/07/2025 | C62: Miguel | E62: 53 25 50 15 | F62: miguel_andersen | H62: Setter | I62: Rescheduled
B63: 14/07/2025 | C63: Benedict | E63: 50 59 72 18 | F63: Benedict_sorensen | H63: Setter | I63: Split-Pay | K63: 10500 | L63: 3000 | Q63: 6 mdr | S63: Closed
B64: 14/07/2025 | C64: Bjarke | E64: 22 58 58 48 | F64: Bjarkewinther6 | H64: Setter | I64: Deposit | L64: 100 | S64: Deposit (Follow Up Set) | T64: starter og betaler d 31 juli
B65: 14/07/2025 | C65: Cuno | E65: 42 91 02 13 | F65: Cuncokolbeck | H65: Setter | I65: Offer & Didn't Buy | N65: Money | O65: Penge | S65: X | T65: 17 årige lærling som skulle snakke med sin mor omkring prisen, ellers super varm og klar til at give den maks gas!
B66: 14/07/2025 | C66: Kim | E66: 30 66 79 99 | F66: Kimbandhitjorgensen | H66: Setter | I66: Offer & Didn't Buy | N66: Money | O66: penge | S66: Hot Follow Up | T66: en person som har fulgt mig i 2-3 år og har vist interesse for coaching flere gange, men han synes at prisen var for meget og prøvede også at skubbe til ham, men var stadig ikke klar
B67: 14/07/2025 | C67: Theodor | E67: 25 37 83 30 | F67: theodorwernberg_ | H67: Setter | I67: Offer & Didn't Buy | N67: Time | O67: tiden | S67: X | T67: vi tager en ny snak d 31 juli, da det er der han får løn og der han 100% er klar sagde han, så nu må vi se selvom at jeg prøvede at få et depositum
B68: 15/07/2025 | C68: Lukas | E68: 42 34 46 40 | F68: terp.lukas | H68: Setter | I68: Rescheduled
B69: 15/07/2025 | C69: Miguel | E69: 53 25 50 15 | F69: Miguel_andersen | H69: Setter | I69: Offer & Didn't Buy | N69: Money | O69: Penge | S69: Hot Follow Up | T69: Rigtig varm og skulle bare igang, men han synes bare det var for dyrt hvilket er træls.
B70: 15/07/2025 | C70: Joachim | E70: 42 43 05 79 | F70: Joachimbp06 | H70: Setter | I70: Offer & Didn't Buy | N70: Partner | O70: gym bro | S70: Hot Follow Up | T70: Han var vold varm og skulle bare igang og det gav også mening for ham, men han ville alligevel tænke over den. Så han valgte at vente og prøve med sin gym bro og hvis ikke virkede, så ville han vende tilbage
B71: 15/07/2025 | C71: Oliver | E71: 22 78 16 17 | F71: olivermoelerelmegard | H71: Setter | I71: Full-Pay | K71: 9000 | L71: 9000 | Q71: 6 mdr | S71: Closed
B72: 15/07/2025 | C72: Juan | E72: 41 90 25 47 | F72: _juanr98 | H72: Setter | I72: Offer & Didn't Buy | N72: Fear | O72: Bange | S72: Hot Follow Up | T72: Han var ready og har haft 2-3 coaches før, men da vi kom til betaling kunne han først da han fik fri og han tog den aldrig da jeg ringede. Fik følelsen af at han ikke var comittet nok
B73: 15/07/2025 | C73: Frederik | E73: 27 28 26 03 | F73: Frederikmolander | H73: Setter | I73: Deposit | L73: 500 | Q73: 6 mdr | S73: Deposit (Follow Up Set)
B74: 16/07/2025 | C74: Jens | E74: 27 28 45 98 | F74: Jensbrandt92 | H74: Setter | I74: No-Show
B75: 16/07/2025 | C75: Tobias | E75: 28 55 44 51 | F75: Tobias.bjerg | H75: Setter | I75: Offer & Didn't Buy | N75: Money | O75: Penge | S75: Follow Up | T75: Manden var klar og han sagde pengene ikke var noget problem, så blev lidt varm og sagde at 6 mdr kostede 10k og han var også ready, men han ville hellere betale det månedligt og så sagde jeg at der var opstartsgebyr på 1500 og det hoppede han af på. så det er gg
B76: 16/07/2025 | C76: Nicolas | E76: 31 21 60 16 | F76: Nico.alex.o | H76: Setter | I76: Offer & Didn't Buy | N76: Partner | O76: Forældre | S76: Follow Up | T76: han var også totalt ready, men hans forældre var ikke fan og han kunne ikke overtale dem
B77: 16/07/2025 | C77: Lukas | E77: 42 34 46 40 | F77: Terp.lukas | H77: Setter | I77: Offer & Didn't Buy | N77: Think About It | O77: Tænke over det | S77: Follow Up | T77: Super varm, dog ville han tænke over det og vende tilbage
B78: 18/07/2025 | C78: Laurits | E78: 25 70 17 03 | F78: Lauritsgreig | H78: Setter | I78: Cancelled
B79: 18/07/2025 | C79: Lucas | E79: 22 37 57 56 | F79: Lucas.k176 | H79: Setter | I79: Split-Pay | K79: 10500 | L79: 3000 | Q79: 6 mdr | S79: Closed
B80: 18/07/2025 | C80: Scott | E80: 30 14 41 81 | F80: Scottjensen3882 | H80: Setter | I80: No-Show
B81: 18/07/2025 | C81: Kristian | E81: 53 65 74 13 | F81: Kris._.mikkelsen | H81: Setter | I81: Split-Pay | K81: 10500 | L81: 1500 | Q81: 6 mdr | S81: Closed
B82: 19/07/2025 | C82: Nikolaj | E82: 25 73 00 47 | F82: nikolaj_christ | H82: Setter | I82: Offer & Didn't Buy | N82: Fear | O82: ture ikke | S82: X | T82: han ture slet ikke og var slet ikke comittet nok. Han ville komme tilbage hvis han følte sig 100% klar
B83: 20/07/2025 | C83: Mikkel | E83: 20 36 88 70 | F83: Hr_refsgaard | H83: Setter | I83: Cancelled
B84: 20/07/2025 | C84: Benjamin | E84: 22 54 47 13 | F84: b_ismailovski | H84: Setter | I84: Offer & Didn't Buy | N84: Think About It | O84: Tænke over det | S84: Hot Follow Up | T84: Benjamin ville gerne igang, men var ikke comittet nok inden kaldet og ville bare hører hvordan det hele fungerede til at starte med. han ville snakke med konen og vende tilbage
B85: 20/07/2025 | C85: Magnus | E85: 23 93 91 44 | F85: Magnus_stuhr | H85: Setter | I85: Split-Pay | K85: 6500 | L85: 3000 | Q85: 3 mdr | S85: Closed
B86: 20/07/2025 | C86: Victor | E86: 20 19 59 60 | F86: victorholm0204 | H86: Setter | I86: Split-Pay | K86: 6500 | L86: 3000 | Q86: 3 mdr | S86: Closed
B87: 20/07/2025 | C87: Sander | E87: 29 70 05 10 | F87: Sander_lunddal | H87: Setter | I87: No-Show
B88: 20/07/2025 | C88: Morten | E88: 60 60 84 99 | F88: lost_star89 | H88: Setter | I88: No-Show
B89: 20/07/2025 | C89: Villads | E89: 60 13 68 39 | F89: villads_anderskov | H89: Setter | I89: Split-Pay | K89: 6500 | L89: 3000 | Q89: 3 mdr | S89: Closed
B90: 20/07/2025 | C90: Timmi | E90: 77 17 32 83 | F90: timmi900001 | H90: Setter | I90: No-Show
B91: 20/07/2025 | C91: Kasper | E91: 20 49 15 10 | F91: kasperkberbl | H91: Setter | I91: No-Show
B92: 21/07/2025 | C92: Jonathan | E92: 42 34 90 30 | F92: jonathanwpedersen | H92: Setter | I92: Split-Pay | K92: 10500 | L92: 3000 | Q92: 6 mdr | S92: Closed
B93: 21/07/2025 | C93: Mikkel | E93: 22 85 40 11 | F93: mikkel_tp | H93: Setter | I93: Split-Pay | K93: 10500 | L93: 3000 | Q93: 6 mdr | S93: Closed
B94: 21/07/2025 | C94: Mikkel | E94: 29 25 45 47 | F94: mikkel8430 | H94: Setter | I94: Deposit | S94: Deposit (Follow Up Set) | T94: kender ham og har coachet ham før og prisen holdte ham lidt tilbage, så han spare 1000kr på oprettelse og vi tager et kald d 31 for at få styr på betaling og oprettelse
B95: 21/07/2025 | C95: Christian | E95: 60 67 45 50 | F95: Christianbjerggard | H95: Setter | I95: Full-Pay | K95: 9000 | L95: 9000 | Q95: 6 mdr | S95: Closed
B96: 21/07/2025 | C96: Kasper | E96: 20 49 15 10 | F96: Kasperkberbl | H96: Setter | I96: Full-Pay | K96: 9000 | L96: 9000 | Q96: 6 mdr | S96: Closed
B97: 21/07/2025 | C97: Noah | E97: 23 84 31 01 | F97: noah_mikkelsennn | H97: Setter | I97: Rescheduled
B98: 21/07/2025 | C98: Harald | E98: 53 62 01 91 | F98: jernbol | H98: Setter | I98: No-Show
B99: 21/07/2025 | C99: Ketil | E99: 23 39 16 17 | F99: Ketilbendixen | H99: Setter | I99: Rescheduled
B100: 21/07/2025 | C100: Malthe | E100: 22 71 67 53 | F100: Brygmann4321 | H100: Setter | I100: Deposit | S100: Deposit (Follow Up Set) | T100: Han er fuld ready, men han venter til d 31 når han får løn, så der har vi sat et kald op hvor alt bliver klaret
B101: 21/07/2025 | C101: Magnus | E101: 53 38 15 94 | F101: Magnusgregersen64 | H101: Setter | I101: Offer & Didn't Buy | N101: Money | O101: Penge | S101: Hot Follow Up | T101: Han var rigtig klar og ville gerne igang, men da han hørte prisen slog det ham tilbage, så han ville tænke over det og vende tilbage
...

Sheet Aug
A1: $ | B1: Rep: | C1: Name | E1: Anton KPI's | H1: Outcome | K1: KPIs% | N1: Show Rate | Q1: Objections | T1: Source
E2: Rev per call | F2: =C3/C6 -> 3519.5876 | H2: Full-Pay: | I2: =IFERROR(COUNTIFS(I13:I311, "Full-Pay"),"") -> 14 | K2: Conversion Rate: | L2: =iferror(L10/L8,"") -> 0.39175258 | N2: Rescheduling Rate: | O2: =iferror(I8/L6,"") -> 0.0084033613 | Q2: Think About It | R2: =IFERROR(COUNTIFS(N35:N310, "think about it"),"") -> 10 | T2: Setter | U2: =IFERROR(COUNTIF(H16:H291,"setter"),"") -> 116
B3: Revenue | C3: =IFERROR(SUM(K13:K288),"") -> 341400 | E3: Cash per call | F3: =C4/C6 -> 1800 | H3: Split-Pay: | I3: =IFERROR(COUNTIFS(I13:I311, "Split-Pay"),"") -> 24 | K3: Offer To Close Rate: | L3: =IFERROR(L10/L9,"") -> 0.40425532 | N3: Cancellation Rate: | O3: =iferror(I9/L6,"") -> 0.050420168 | Q3: Money | R3: =IFERROR(COUNTIFS(N35:N310, "money"),"") -> 24 | T3: IG | U3: =IFERROR(COUNTIF(H16:H291,"IG"),"") -> 0
B4: Cash | C4: =IFERROR(SUM(L13:L289),"") -> 174600 | E4: Cash upfront % | F4: =C4/C3*100 -> 51.142355 | H4: Deposits: | I4: =IFERROR(COUNTIFS(I13:I311, "Deposit"),"") -> 11 | K4: Call To Offer Rate: | L4: =IFERROR(L9/L8,"") -> 0.96907216 | N4: No-Shows Rate: | O4: =iferror(I10/L6,"") -> 0.12605042 | Q4: Time | R4: =IFERROR(COUNTIFS(N35:N310, "time"),"") -> 3 | T4: YouTube | U4: =IFERROR(COUNTIF(H16:H291,"youtube"),"") -> 0
E5: PIF % | F5: =I2/C7*100 -> 36.842105 | H5: Offer & Didn't Buy: | I5: =IFERROR(COUNTIFS(I13:I311, "Offer & Didn't Buy"),"") -> 45 | K5: Drag Over Rate: | L5: =IFERROR(I7/(C6+I7+I8),"") -> 0 | N5: Drag Over Rate: | O5: =iferror(I7/L6,"") -> 0 | Q5: Partner | R5: =IFERROR(COUNTIFS(N35:N310, "partner"),"") -> 3 | T5: Email | U5: =IFERROR(COUNTIF(H16:H291,"email"),"") -> 0
B6: Total Calls : | C6: =IFERROR(SUM(I2:I6),"") -> 97 | E6: Average Binding | F6: =AVERAGE(Q13:Q104) -> 5.5263158 | H6: Bad Fit & No Offer: | I6: =IFERROR(COUNTIFS(I13:I311, "Bad Fit & No Offer"),"") -> 3 | K6: Bookings: | L6: =IFERROR(SUM(I2:I10),"") -> 119 | N6: Show-Up Rate: | O6: =iferror(L7/L6,"") -> 0.81512605 | Q6: Fear | R6: =IFERROR(COUNTIFS(N35:N310, "fear"),"") -> 1 | T6: Facebook | U6: =IFERROR(COUNTIF(H16:H291,"facebook"),"") -> 0
B7: Total Won : | C7: =IFERROR(I2+I3,"") -> 38 | E7: Average deal | F7: =C3/C7 -> 8984.2105 | H7: Drag Over & Show: | I7: =IFERROR(COUNTIFS(I13:I311, "Drag Over & Show"),"") -> 0 | K7: Shows: | L7: =IFERROR(SUM(I2:I7),"") -> 97 | N7: Conducted Rate: | O7: =IFERROR(L8/L6,"") -> 0.81512605 | Q7: Value | R7: =IFERROR(COUNTIFS(N36:N311, "value"),"") -> 0 | T7: Facebook Ads | U7: =IFERROR(COUNTIF(H16:H291,"facebook ads"),"") -> 0
B8: Total Lost : | C8: =COUNTIF(I13:I291,"offer & didn't buy")+COUNTIF(I16:I291,"deposit")+COUNTIF(I16:I291,"bad fit & no offer") -> 57 | E8: Average cash | F8: =C4/C7 -> 4594.7368 | H8: Rescheduled: | I8: =IFERROR(COUNTIFS(I13:I311, "Rescheduled"),"") -> 1 | K8: Calls: | L8: =IFERROR(SUM(I2:I6),"") -> 97 | T8: LinkedIn | U8: =IFERROR(COUNTIF(H16:H291,T8),"") -> 0
B9: Closing % : | C9: =iferror(SUM(C7/C6),"") -> 0.39175258 | H9: Cancelled: | I9: =IFERROR(COUNTIFS(I13:I311, "Cancelled"),"") -> 6 | K9: Offers: | L9: =IFERROR(sum(I2:I5),"") -> 94
C10: =C3/C6 -> 3519.5876 | H10: No-Show: | I10: =IFERROR(COUNTIFS(I13:I311, "No-Show"),"") -> 15 | K10: Deals | L10: =I2+I3 -> 38
B12: Date | C12: Name | E12: Phone No. | F12: IG Navn | H12: Source | I12: Outcome | K12: Revenue | L12: Cash | N12: Objection | O12: Objection Notes | Q12: Length | R12: Recording Link | S12: Follow Up/Next Steps | T12: Call Summary
B13: 45665 | C13: Valdemar Drejer hansen | E13: 42 72 12 78 | F13: Valdemar Drejer hansen | H13: Setter | I13: Split-Pay | K13: 8700 | L13: 2700 | Q13: 6 | S13: Closed | T13: Fik endelig betaling fra ham
B14: 45665 | C14: Simon | E14: 71 72 98 36 | F14: Simon_nordbylino | H14: Setter | I14: Deposit | Q14: 6 | S14: Deposit (Follow Up Set) | T14: starter op d 20 august
B15: 45665 | C15: Oliver | E15: 50 57 73 43 | F15: oliversarto | H15: Setter | I15: Deposit | Q15: 6 | S15: Deposit (Follow Up Set) | T15: starter og betaler d 31 august, selvom meningen var at vi startede d 1 august
B16: 45665 | C16: Kaspar | E16: 28 18 36 14 | F16: Kaspar_privat9 | H16: Setter | I16: No-Show | Q16: 6 | S16: Deposit (Follow Up Set) | T16: starter og betaler d 1 august (Han svarer ikke på mine beskeder)
B17: 45665 | C17: Kristian | E17: 50 15 03 56 | F17: Kristiandrechsler | H17: Setter | I17: Split-Pay | K17: 7700 | L17: 1700 | Q17: 6 | S17: Closed | T17: Starter og betaler d 1 august!
B18: 45665 | C18: Oliver | E18: 26 31 45 57 | F18: oliver_groening | H18: Setter | I18: Deposit | Q18: 6 | S18: Deposit (Follow Up Set) | T18: starter og betaler d 11 august
B19: 45665 | C19: Mads | E19: 29 13 40 54 | F19: _madsskov | H19: Setter | I19: Split-Pay | K19: 10500 | L19: 3000 | Q19: 6 | S19: Deposit (Follow Up Set) | T19: betaler 1 august og starter 1 sep (Venter svar fra ham)
B20: 45665 | C20: Laurits | E20: 22 56 74 16 | F20: laurits_viholt | H20: Setter | I20: Deposit | L20: 100 | Q20: 6 | S20: Deposit (Follow Up Set) | T20: starter og betaler d 1 august (bumsen har blokeret mig)
B21: 45665 | C21: William | E21: 52 17 82 58 | F21: william.kjellberg | H21: Setter | I21: Split-Pay | K21: 10500 | L21: 1500 | Q21: 6 | S21: Closed | T21: han starter d 1 august, men betalte for opstartsgebyr nu
B22: 45665 | C22: Bjarke | E22: 22 58 58 48 | F22: Bjarkewinther6 | H22: Setter | I22: Deposit | L22: 100 | S22: Deposit (Follow Up Set) | T22: starter og betaler d 31 juli (han har ikke råd, vi udskyder til 31 august istedet)
B23: 45665 | C23: Frederik | E23: 27 28 26 03 | F23: Frederikmolander | H23: Setter | I23: Split-Pay | K23: 10500 | L23: 2500 | Q23: 6 | S23: Closed | T23: Han betalte 500 sidste måned
B24: 45665 | C24: Max | E24: 23 11 86 23 | F24: max_thybo_ | H24: Setter | I24: Split-Pay | K24: 10500 | L24: 3000 | Q24: 6 | S24: Closed | T24: Han starter d 11 august og han betaler der
B25: 45665 | C25: Christian | E25: 26 33 05 88 | F25: christianhuus | H25: Setter | I25: Deposit | Q25: 6 | S25: Deposit (Follow Up Set) | T25: Han er klar 31 august og der betaler han
B26: 45665 | C26: Martin | E26: 31 95 58 15 | F26: Martin.daoudd | H26: Setter | I26: Full-Pay | K26: 4500 | L26: 4500 | Q26: 4 | S26: Closed
B27: 45665 | C27: Mads | E27: 53 63 09 43 | F27: madspc004 | H27: Setter | I27: Bad Fit & No Offer
B28: 45665 | C28: Axel | E28: 28 60 86 02 | F28: axelhauerslev | H28: Setter | I28: Offer & Didn't Buy | N28: Money | O28: Penge | S28: Follow Up | T28: Han var super nice, men han ville slet ikke smide pengene i det
B29: 45665 | C29: Jonas | E29: 23 86 09 52 | F29: brunduss | H29: Setter | I29: Offer & Didn't Buy | N29: Think About It | O29: tænke over det | S29: Follow Up | T29: fin fyr, men han ville gerne tænke over det!
B30: 45665 | C30: Daniel | E30: 21 16 82 88 | F30: daniel.arnason00 | H30: Setter | I30: Offer & Didn't Buy | N30: Think About It | O30: Tænke over det | S30: Hot Follow Up | T30: Han var frisk og klar, dog ville han tænke over det og vi aftalte et kald om mandagen og han mødte aldrig op
B31: 45665 | C31: Lucas | E31: 42 33 80 96 | F31: lucas-hansen_3914 | H31: Setter | I31: Cancelled | T31: Han skulle på hospitalet
B32: 45665 | C32: Aleksander | E32: 30 11 53 98 | F32: Alexsander.from | H32: Setter | I32: Offer & Didn't Buy | N32: Money | O32: Penge | S32: Hot Follow Up | T32: Sygt frisk gut og det eneste som holdte ham tilbage var ækonomien. Gav ham et tilbud på 750 fra opstart og han var stadig for presset til det
B33: 45665 | C33: Benjamin | E33: 20 13 19 84 | F33: Benjamin_rebmann | H33: Setter | I33: Offer & Didn't Buy | N33: Time | O33: Pung | S33: Hot Follow Up | T33: Han var klar og skulle til at betale, men han kunne ikke finde sin pung. Han ledte efter det og aftalte han skulle ordne betaling så snart han fandt pungen og så skulle han på hospitalet for at være hos sin far og hørte ikke fra ham siden
B34: 45665 | C34: David | E34: 42 50 30 13 | F34: daviddampe | H34: Setter | I34: Split-Pay | K34: 10500 | L34: 3000 | Q34: 6 | S34: Closed
B35: 45665 | C35: Niklas | E35: 42 91 44 42 | F35: Niklasudenc | H35: Setter | I35: Offer & Didn't Buy | N35: Money | O35: Penge | S35: Follow Up | T35: Super fint lead og ville gerne igang, men det var kun prisen som holdte ham tilbage
B36: 45665 | C36: Villas | E36: 30 28 00 67 | F36: Villas_mehlsen | H36: Setter | I36: Deposit | Q36: 6 | S36: Deposit (Follow Up Set) | T36: Har en snak med ham igen d 31 hvor vi får styr på betaling og opstart
B37: 45696 | C37: Frederik | E37: 53 69 76 72 | F37: frederikk_pedersen | H37: Setter | I37: No-Show
B38: 45724 | C38: Victor | E38: 21 49 34 44 | F38: victor_gammelvind | H38: Setter | I38: Split-Pay | K38: 10500 | L38: 3000 | Q38: 6 | S38: Closed
B39: 45724 | C39: Vitus | E39: 93 89 61 06 | F39: vitus_toft | H39: Setter | I39: Offer & Didn't Buy | N39: Partner | O39: Forældre | S39: Follow Up | T39: Ung dreng som gerne ville igang og havde egentlig penge til det, men hans forældre sagde nej
B40: 45724 | C40: Simon | E40: 30 96 29 25 | F40: Simonblumpedersen | H40: Setter | I40: Full-Pay | K40: 9000 | L40: 9000 | Q40: 6 | S40: Closed
B41: 45724 | C41: Noah | E41: 22 56 64 82 | F41: noahpettersson_ | H41: Setter | I41: No-Show
B42: 45724 | C42: Lucas | E42: 92 43 34 92 | F42: Lucas24m | H42: Setter | I42: Full-Pay | K42: 9000 | L42: 9000 | Q42: 6 | S42: Closed
B43: 45724 | C43: Andreas | E43: 60 70 47 88 | F43: Bonde420.01 | H43: Setter | I43: Deposit | Q43: 6 | S43: Deposit (Follow Up Set) | T43: Onboarding kald d 31
B44: 45724 | C44: Patrick | E44: 25 29 63 60 | F44: patricksandberg1 | H44: Setter | I44: Offer & Didn't Buy | N44: Think About It | O44: Anden coach | S44: X | T44: Han valgte en anden coach
B45: 45724 | C45: Balo | E45: 55 23 06 00 | F45: balo_huncho | H45: Setter | I45: Offer & Didn't Buy | N45: Think About It | O45: Tænke over det | S45: Follow Up | T45: Fint lead, han arbejdede meget, men han ville tænke over det men ved godt det var pga pengene
B46: 45724 | C46: Rasmus | E46: 31 71 36 92 | F46: toemrer.rasmus | H46: Setter | I46: Offer & Didn't Buy | N46: Money | O46: Økonomi | S46: Follow Up | T46: Super spøjs fyr. Han ville gerne tabe sig, han havde i bund og grund penge til det og så skulle han også snakke med rasmus sparholdt dagen efter
B47: 45724 | C47: Rasmus | E47: 40 58 21 01 | F47: Rasmus_dworak | H47: Setter | I47: Split-Pay | K47: 10500 | L47: 3000 | Q47: 6 | S47: Closed
B48: 45755 | C48: Mads | E48: 44 16 40 12 | F48: Madsbolmose | H48: Setter | I48: Full-Pay | K48: 9000 | L48: 9000 | Q48: 6 | S48: Closed
B49: 45755 | C49: Daniel | E49: 21 16 82 88 | F49: daniel.arnason00 | H49: Setter | I49: No-Show
B50: 45785 | C50: Rolando | E50: 42 75 79 56 | F50: _ronaldo.rodriquez | H50: Setter | I50: No-Show | T50: Han blokerede mig
B51: 45785 | C51: Peter | E51: 61 70 84 76 | F51: peter_hjortkjær | H51: Setter | I51: Offer & Didn't Buy | N51: Money | O51: Penge | S51: Hot Follow Up | T51: Manden var fucking klar til at give den gas og skulle endda også til at betale, men så sagde han at hans far ringede self. Så hvis man giver tilbud på opstart, så er han nok ready
B52: 45785 | C52: Malthe | E52: 25 56 84 40 | F52: Malthemunk_ | H52: Setter | I52: Offer & Didn't Buy | N52: Time | O52: tid og penge | S52: Follow Up Set | T52: han var fucking klar, men havde ikke pengene, så har smidt ham på onboarding kald d 31, så vi kan klare opstart + betaling
B53: 45785 | C53: Gustav | E53: 29 84 43 16 | F53: Gustav_espenhain | H53: Setter | I53: No-Show
B54: 45785 | C54: Henrik | E54: 27 11 09 29 | F54: henrikbunchjensen | H54: Setter | I54: Full-Pay | K54: 9000 | L54: 9000 | Q54: 6 | S54: Closed
B55: 45785 | C55: Emil | E55: 61 66 41 13 | F55: emil_olsen28 | H55: Setter | I55: Offer & Didn't Buy | N55: Money | O55: Penge | S55: X | T55: ung knægt på 16 som bare ikke havde pengene til det
B56: 45785 | C56: Nicolas | E56: 28 71 73 16 | F56: Nicolas_iordanov | H56: Setter | I56: Split-Pay | K56: 5000 | L56: 2000 | Q56: 3 | S56: Closed
B57: 45816 | C57: Jakob | E57: 23 34 11 69 | F57: J_.drejer | H57: Setter | I57: Cancelled
B58: 45816 | C58: Mike | E58: 42 32 59 02 | F58: mike.jacobsen.77 | H58: Setter | I58: Offer & Didn't Buy | N58: Money | O58: Penge | S58: Follow Up | T58: fint lead, ville også igang, men han synes det var svært at smide 1500kr månedligt, da han bare var en blodhjertet nærig jyde haha
B59: 45816 | C59: Frederik | E59: 22 76 06 27 | F59: Frederik.andersen09_ | H59: Setter | I59: Offer & Didn't Buy | N59: Money | O59: Penge | S59: X | T59: 16 årige knægt uden penge på lommen
B60: 45816 | C60: Rasmus | E60: 91 88 73 44 | F60: rasmuskristianhansen | H60: Setter | I60: Cancelled
B61: 45816 | C61: Umar | E61: 49 176 24770125 | F61: u.sbehi | H61: Setter | I61: Rescheduled
B62: 45846 | C62: Magnus | E62: 20 66 60 87 | F62: magnus_zeuthen | H62: Setter | I62: Split-Pay | K62: 10500 | L62: 3000 | Q62: 6 | S62: Closed
B63: 45846 | C63: Rasmus | E63: 25 72 96 00 | F63: Rasmuslk93 | H63: Setter | I63: Offer & Didn't Buy | N63: Think About It | O63: tænke over det + penge | S63: Follow Up | T63: rigtig godt lead og han skulle igang, men han synes penge var lidt stramme, da han var gået fra damen og lige flyttet i ny lejlighed
B64: 45846 | C64: Kim | E64: 30 66 79 99 | F64: Kimbandhitjorgensen | H64: Setter | I64: Split-Pay | K64: 9500 | L64: 2000 | Q64: 6 | S64: Closed
B65: 45846 | C65: Umar | E65: 49 176 24770125 | F65: U.sbehi | H65: Setter | I65: Offer & Didn't Buy | N65: Money | O65: Penge | S65: X | T65: han venter på at han får løn, så vi har aftalt at snuppe et kald d 31 for at få ham igang + betaling
B66: 45877 | C66: Sigurd | E66: 21 33 08 21 | F66: sigurd_gram | H66: Setter | I66: Offer & Didn't Buy | N66: Money | O66: Penge | S66: Hot Follow Up | T66: VOLD VARM! Snakkede med ham dagen før og han skulle have snakket med banken, så vi aftalte at få styr på det hele dagen efter og hørte aldrig fra ham
B67: 45877 | C67: Murtada | E67: 31 51 54 47 | F67: murtradi_ | H67: Setter | I67: Split-Pay | K67: 6000 | L67: 1500 | Q67: 3 | S67: Closed
B68: 45877 | C68: Silas | E68: 61 60 79 32 | F68: Silasstoklund123 | H68: Setter | I68: Offer & Didn't Buy | N68: Think About It | O68: Tænke over det + penge | S68: Hot Follow Up | T68: Han var også sygt klar, men han ville tænke over det selvom at jeg prøvede at presse ham, og nu hører jeg ikke fra ham
B69: 45908 | C69: Aske | E69: 20 16 16 11 | F69: Rumannaske | H69: Setter | I69: Full-Pay | K69: 9000 | L69: 9000 | Q69: 6 | S69: Closed
B70: 45908 | C70: Hjalte | E70: 20 73 39 71 | F70: skovbyhjalte | H70: Setter | I70: No-Show
B71: 45938 | C71: Silas | E71: 61 60 79 32 | F71: silasstoklund123 | H71: Setter | I71: Split-Pay | K71: 10500 | L71: 3000 | Q71: 6 | S71: Closed
B72: 45999 | C72: Noah | E72: 30119869 | F72: noahejorgensen | H72: Setter | I72: Deposit | S72: Deposit (Follow Up Set) | T72: Tog et kald da han hellere ville snakke med mig spontant. han er klar, men kan først betale og starte op d 31
B73: 45999 | C73: Jonas | E73: 28 19 26 25 | F73: jonas_romney | H73: Setter | I73: Offer & Didn't Buy | S73: Hot Follow Up | T73: Tog et kald med ham, da han hellere ville snakke med mig. har coachet ham før og han kunne først starte d 31 august, da han har penge der (han hoppede fra)
B74: 14/08/2025 | C74: Mathias | E74: 52 90 95 00 | F74: Mathias_s_hald | H74: Setter | I74: Split-Pay | K74: 6000 | L74: 1500 | Q74: 3 | S74: Closed
B75: 14/08/2025 | C75: Valentin | E75: 30 58 25 42 | F75: Valentin_schiavuta | H75: Setter | I75: Full-Pay | K75: 6000 | L75: 6000 | Q75: 4 | S75: Closed | T75: vi har sat et nyt kald op d 14 august for at oprette ham og self klare betaling
B76: 14/08/2025 | C76: Mazlum | E76: 42 48 34 43 | F76: Musti | H76: Setter | I76: Split-Pay | K76: 10500 | L76: 1500 | Q76: 6 | S76: Closed | T76: han betaler bagud istedet for forud
B77: 15/08/2025 | C77: Christian | E77: 40451127 | F77: handbergchristian | H77: Setter | I77: Split-Pay | K77: 10500 | L77: 3000 | Q77: 6 | S77: Closed
B78: 16/08/2025 | C78: Emil | E78: 51 93 22 03 | F78: Emilruchpadowan | H78: Setter | I78: Deposit | N78: Think About It | O78: penge + tænke over det | S78: Deposit (Follow Up Set) | T78: han var i bund og grund klar, men har smidt ham på deposit fordi jeg har planlagt et nyt kald med ham d 31 august
B79: 16/08/2025 | C79: Oliver | E79: 60 17 23 52 | F79: Oliverhestenng | H79: Setter | I79: Offer & Didn't Buy | N79: Think About It | O79: penge + tænke over det | S79: Follow Up | T79: han var ready, men han skulle tænke over prisen og snakke med sine forældre
B80: 16/08/2025 | C80: Lukas | E80: 40 68 00 49 | F80: Soeren_maelkesnitte | H80: Setter | I80: Split-Pay | K80: 10500 | L80: 3000 | Q80: 6 | S80: Closed
B81: 16/08/2025 | C81: Lucas | E81: 42338096 | F81: Lucas.hansen_3914 | H81: Setter | I81: No-Show
B82: 17/08/2025 | C82: Oliver | E82: 60 17 23 52 | F82: Oliverhestenng | H82: Setter | I82: Offer & Didn't Buy | N82: Time | O82: TIden og frygt | S82: Hot Follow Up | T82: Super klar, han var dog i genoptræningsforløb, men ved godt det ikke var derfor han ikke startede. han var nok lidt bange og pengene. dog sagde han at han var 100% klar til december
B83: 17/08/2025 | C83: Lukas | E83: 40 68 00 49 | F83: lukas_blond03 | H83: Setter | I83: Split-Pay | K83: 10500 | L83: 3000 | Q83: 6 | S83: Closed
B84: 17/08/2025 | C84: Lucas | E84: 42338096 | F84: Lucas.hansen_3914 | H84: Setter | I84: No-Show
B85: 19/08/2025 | C85: Mathias | E85: 29 60 17 50 | F85: Mathiasrexrother | H85: Setter | I85: Full-Pay | K85: 9000 | L85: 9000 | Q85: 6 | S85: Closed
B86: 19/08/2025 | C86: Mathias | E86: 30648407 | F86: Mathiastinglef | H86: Setter | I86: Split-Pay | K86: 10500 | L86: 3000 | N86: Money | S86: Closed | T86: Han starter og betaler d 29 august
B87: 21/08/2025 | C87: Benjamin | E87: 50 75 92 55 | F87: Benjaminbjoernholt | H87: Setter | I87: Full-Pay | K87: 9000 | L87: 9000 | S87: Closed | T87: Han betaler 9k d 22 august
B88: 21/08/2025 | C88: Victor | E88: 25 75 28 24 | F88: _victorjensenn_ | H88: Setter | I88: Full-Pay | K88: 6000 | L88: 6000 | Q88: 4 | S88: Closed
B89: 21/08/2025 | C89: Sebastian | E89: 27 58 55 75 | F89: Sebastian.jepsen.73 | H89: Setter | I89: Split-Pay | K89: 9000 | L89: 4500 | Q89: 6 | S89: Closed
B90: 25/08/2025 | C90: Tobias | E90: 91932431 | F90: Tobi.26hv | H90: Setter | I90: Offer & Didn't Buy | N90: Money | O90: Penge | S90: Follow Up Set | T90: Skal snakke med ham igen d 1 sep, da han ikke havde pengene
B91: 25/08/2025 | C91: Alfred | E91: 23 24 41 29 | F91: Alfredfriisa | H91: Setter | I91: Offer & Didn't Buy | N91: Money | O91: Penge og frygt | S91: Follow Up | T91: Han var sygt varm og skulle bare igang, jeg sender ham payment link og så får han kolde fødder. Han skal 100% ringes op igen!
B92: 26/08/2025 | C92: Nicolai | E92: 61 69 09 75 | F92: nicolai_fuglsang | H92: Setter | I92: Cancelled | T92: Han var syg og har ikke svaret tilbage på reschedule offer
B93: 26/08/2025 | C93: Noah | E93: 42 43 70 30 | F93: Noah_fromsejer | H93: Setter | I93: Offer & Didn't Buy | N93: Money | O93: Penge og frygt | T93: han ville gerne igang, men han ville hellere spare op til at flytte ud og så var han også lidt bange for at bruge penge på det
B94: 26/08/2025 | C94: Malthe | E94: 22 20 46 39 | F94: malthepetersen_ | H94: Setter | I94: Full-Pay | K94: 4500 | L94: 4500 | Q94: 3 | S94: Closed
B95: 26/08/2025 | C95: Ludvig | E95: 20 41 14 26 | F95: Ludv0486 | H95: Setter | I95: Offer & Didn't Buy | N95: Money | O95: Penge | S95: X | T95: Han var også rigtig klar og kunne godt se at det var pengene værd, dog ville han tænke over det og fik en besked efter med at hans bil var gået istykker osv osv
B96: 26/08/2025 | C96: Birk | E96: 30 70 80 61 | F96: birkno.9 | H96: Setter | I96: No-Show
B97: 26/08/2025 | C97: Ramazan | E97: 93 87 27 34 | F97: ramazan_dtas01 | H97: Setter | I97: No-Show
B98: 26/08/2025 | C98: Jody | E98: 71456607 | F98: jodykurdo | H98: Setter | I98: Cancelled
B99: 26/08/2025 | C99: Mads | E99: 22 89 38 61 | F99: mads_sorup97 | H99: Setter | I99: Offer & Didn't Buy | N99: Money | O99: penge | S99: Hot Follow Up | T99: Super varm og han skulle bare igang og da vi kommer til penge, så sgade han at han ville skrive tilbage og gad ikke svarer på hvorfor, så tror han ikke havde kroner på lommen, så han skal bare ringes op igen asap nu hvor der er løn
B100: 26/08/2025 | C100: Mathias | E100: 20 74 42 41 | F100: mj_officel1 | H100: Setter | I100: Offer & Didn't Buy | N100: Money | O100: Penge | S100: Follow Up | T100: han var varm og skulle igang, men hans budget var der ikke til det lige nu, så han skal ringes op igen!
B101: 26/08/2025 | C101: Topper | E101: 25 79 22 16 | F101: topperdamgaardharnk | H101: Setter | I101: Offer & Didn't Buy | N101: Money | O101: Penge | S101: X | T101: Han blokere mig midt call
...

Sheet Sep
A1: $ | B1: Rep: | C1: Name | E1: Anton KPI's | H1: Outcome | K1: KPIs% | N1: Show Rate | Q1: Objections | T1: Source
E2: Rev per call | F2: =C3/C6 -> 3231.5789 | H2: Full-Pay: | I2: =IFERROR(COUNTIFS(I13:I311, "Full-Pay"),"") -> 7 | K2: Conversion Rate: | L2: =iferror(L10/L8,"") -> 0.35087719 | N2: Rescheduling Rate: | O2: =iferror(I8/L6,"") -> 0.060240964 | Q2: Think About It | R2: =IFERROR(COUNTIFS(N35:N310, "think about it"),"") -> 2 | T2: Setter | U2: =IFERROR(COUNTIF(H35:H310,"setter"),"") -> 62
B3: Revenue | C3: =IFERROR(SUM(K13:K307),"") -> 184200 | E3: Cash per call | F3: =C4/C6 -> 1496.4912 | H3: Split-Pay: | I3: =IFERROR(COUNTIFS(I13:I311, "Split-Pay"),"") -> 13 | K3: Offer To Close Rate: | L3: =IFERROR(L10/L9,"") -> 0.37037037 | N3: Cancellation Rate: | O3: =iferror(I9/L6,"") -> 0.048192771 | Q3: Money | R3: =IFERROR(COUNTIFS(N35:N310, "money"),"") -> 17 | T3: IG | U3: =IFERROR(COUNTIF(H35:H310,"IG"),"") -> 0
B4: Cash | C4: =IFERROR(SUM(L13:L308),"") -> 85300 | E4: Cash upfront % | F4: =C4/C3*100 -> 46.30836 | H4: Deposits: | I4: =IFERROR(COUNTIFS(I13:I311, "Deposit"),"") -> 1 | K4: Call To Offer Rate: | L4: =IFERROR(L9/L8,"") -> 0.94736842 | N4: No-Shows Rate: | O4: =iferror(I10/L6,"") -> 0.20481928 | Q4: Time | R4: =IFERROR(COUNTIFS(N35:N310, "time"),"") -> 3 | T4: YouTube | U4: =IFERROR(COUNTIF(H35:H310,"youtube"),"") -> 0
E5: PIF % | F5: =I2/C7*100 -> 35 | H5: Offer & Didn't Buy: | I5: =IFERROR(COUNTIFS(I13:I311, "Offer & Didn't Buy"),"") -> 33 | K5: Drag Over Rate: | L5: =IFERROR(I7/(C6+I7+I8),"") -> 0 | N5: Drag Over Rate: | O5: =iferror(I7/L6,"") -> 0 | Q5: Partner | R5: =IFERROR(COUNTIFS(N35:N310, "partner"),"") -> 1 | T5: Email | U5: =IFERROR(COUNTIF(H35:H310,"email"),"") -> 0
B6: Total Calls : | C6: =IFERROR(SUM(I2:I6),"") -> 57 | E6: Average Binding | F6: =AVERAGE(Q13:Q104) -> 5.7333333 | H6: Bad Fit & No Offer: | I6: =IFERROR(COUNTIFS(I13:I311, "Bad Fit & No Offer"),"") -> 3 | K6: Bookings: | L6: =IFERROR(SUM(I2:I10),"") -> 83 | N6: Show-Up Rate: | O6: =iferror(L7/L6,"") -> 0.68674699 | Q6: Fear | R6: =IFERROR(COUNTIFS(N35:N310, "fear"),"") -> 2 | T6: Facebook | U6: =IFERROR(COUNTIF(H35:H310,"facebook"),"") -> 0
B7: Total Won : | C7: =IFERROR(I2+I3,"") -> 20 | E7: Average deal | F7: =C3/C7 -> 9210 | H7: Drag Over & Show: | I7: =IFERROR(COUNTIFS(I13:I311, "Drag Over & Show"),"") -> 0 | K7: Shows: | L7: =IFERROR(SUM(I2:I7),"") -> 57 | N7: Conducted Rate: | O7: =IFERROR(L8/L6,"") -> 0.68674699 | Q7: Value | R7: =IFERROR(COUNTIFS(N36:N311, "value"),"") -> 1 | T7: Facebook Ads | U7: =IFERROR(COUNTIF(H35:H310,"facebook ads"),"") -> 0
B8: Total Lost : | C8: =COUNTIF(I13:I310,"offer & didn't buy")+COUNTIF(I35:I310,"deposit")+COUNTIF(I35:I310,"bad fit & no offer") -> 36 | E8: Average cash | F8: =C4/C7 -> 4265 | H8: Rescheduled: | I8: =IFERROR(COUNTIFS(I13:I311, "Rescheduled"),"") -> 5 | K8: Calls: | L8: =IFERROR(SUM(I2:I6),"") -> 57 | T8: LinkedIn | U8: =IFERROR(COUNTIF(H35:H310,T8),"") -> 0
B9: Closing % : | C9: =iferror(SUM(C7/C6),"") -> 0.35087719 | H9: Cancelled: | I9: =IFERROR(COUNTIFS(I13:I311, "Cancelled"),"") -> 4 | K9: Offers: | L9: =IFERROR(sum(I2:I5),"") -> 54
C10: =C3/C6 -> 3231.5789 | H10: No-Show: | I10: =IFERROR(COUNTIFS(I13:I311, "No-Show"),"") -> 17 | K10: Deals | L10: =I2+I3 -> 20
B12: Date | C12: Name | E12: Phone No. | F12: IG Navn | H12: Source | I12: Outcome | K12: Revenue | L12: Cash | N12: Objection | O12: Objection Notes | Q12: Length | R12: Recording Link | S12: Follow Up/Next Steps | T12: Call Summary
B13: 45666 | C13: Mikkel | E13: idk | F13: mikkelorregaard | H13: Setter | I13: Full-Pay | K13: 6000 | L13: 6000 | N13: Think About It | O13: sove på den | Q13: 4 | S13: Closed
B14: 45666 | C14: Kristian | E14: 22 63 72 90 | F14: Kristian.nissen.soerensen | H14: Setter | I14: Full-Pay | K14: 9000 | L14: 9000 | N14: Think About It | O14: sove på den | Q14: 6 | S14: Closed | T14: nyt kald d 1 og snakke alt igennem
B15: 45666 | C15: Tobias | E15: 91 93 24 31 | F15: tobi.26hv | H15: Setter | I15: No-Show | T15: Det var en onboarding, men manden møder ikke op
B16: 45666 | C16: Oliver | E16: Idk | F16: oliversarto | H16: Setter | I16: Split-Pay | K16: 10500 | L16: 1500 | Q16: 6 | S16: Closed | T16: han betaler bagud
B17: 45697 | C17: Max | E17: 23 20 49 24 | F17: Max_leon_beller | H17: Setter | I17: Split-Pay | K17: 8700 | L17: 2700 | Q17: 6 | S17: Closed | T17: Gammelt lead og han fik det til gammel pris
B18: 45697 | C18: Laurids | E18: 30 46 00 43 | F18: Laurids_sj | H18: Setter | I18: Split-Pay | K18: 10500 | L18: 3000 | Q18: 6 | S18: Closed
B19: 45725 | C19: Nicolai | E19: 21953517 | F19: nicolai_palmelund | H19: Setter | I19: No-Show
B20: 45756 | C20: Jonathan | E20: 61 72 66 83 | F20: jonathan.schneider.lunden | H20: Setter | I20: Offer & Didn't Buy | N20: Money | O20: Penge | S20: Hot Follow Up | T20: Manden var så klar og det var også et onboarding, men han havde ikke penge og efter skriver han at han ikke har penge selvom han havde penge.
B21: 45756 | C21: Mikkel | E21: 91 45 14 73 | F21: Mikkelras203 | H21: Setter | I21: Offer & Didn't Buy | N21: Money | O21: Penge | S21: Follow Up | T21: Godt lead, men ikke særligt investeret fra start. Men godt follow up lead
B22: 45756 | C22: Jannick | E22: 61 41 68 35 | F22: Jannick_laursen | H22: Setter | I22: Full-Pay | K22: 6000 | L22: 6000 | Q22: 4 | S22: Closed
B23: 45756 | C23: Harald | E23: 42 53 87 89 | F23: Harald_gruner | H23: Setter | I23: Offer & Didn't Buy | N23: Money | O23: Penge | S23: X | T23: Han havde ikke penge og hans forældre gad ikke sponsorere
B24: 45756 | C24: Nicklas | E24: 49 90 82 83 | F24: nicklashundrup | H24: Setter | I24: No-Show
B25: 45756 | C25: Oscar | E25: 61516917 | F25: oscabutt | H25: Setter | I25: Offer & Didn't Buy | N25: Think About It | O25: Tænke over det | S25: Follow Up | T25: Han skulle tænke over det, men hørte aldrig tilbage fra ham. super fint lead at ringe op til igen
B26: 45756 | C26: Emin | E26: 42 46 59 92 | F26: Emin_muheljic06 | H26: Setter | I26: Split-Pay | K26: 10500 | L26: 1500 | Q26: 6 | S26: Closed
B27: 45756 | C27: Marcus | E27: 20 80 56 56 | F27: marcus_holm_winther | H27: Setter | I27: Offer & Didn't Buy | N27: Think About It | O27: tænke over det | S27: Follow Up | T27: Han skal ringes op til igen og trykket til ham, fordi han var i klar men var en pussy
B28: 45756 | C28: Johan | E28: 93 92 41 16 | F28: johanerenskjold | H28: Setter | I28: Offer & Didn't Buy | N28: Money | O28: Penge | S28: Follow Up | T28: var klar til at komme igang, men havde ikke pengene nu, han var klar på løningsdag, så der skal søren ringe ham op
B29: 45786 | C29: Victor | E29: 27 21 30 25 | F29: Victor.lundsgaard | H29: Setter | I29: Offer & Didn't Buy | N29: Think About It | S29: Follow Up | T29: manden var også fkn klar og han skulle sove på den. han havde para. søren skal ringe ham op løningsdag!
B30: 45786 | C30: Dylan | E30: 52 81 54 96 | F30: dylan.galeano97 | H30: Setter | I30: Bad Fit & No Offer | S30: X | T30: Manden er fuld attitude på som om jeg havde tvunget ham på kald. ville bare høre pris og han ville ikke betale mere end 1000kr
B31: 45786 | C31: Patrick | E31: 42 71 12 18 | F31: Patrick_vedel_ | H31: Setter | I31: Rescheduled
B32: 45786 | C32: Carsten | E32: 53 88 03 29 | F32: Carstenflink | H32: Setter | I32: Offer & Didn't Buy | N32: Fear | O32: frygt | S32: Hot Follow Up | T32: Manden var fkn klar og skulle til at betale, men kom med dårlige undskyldninger for at udskyde. så har bedt søren om at ringe ham op idag!
B33: 45786 | C33: Tariq | E33: Idk | F33: Ta.saf98 | H33: Setter | I33: Offer & Didn't Buy | N33: Money | S33: Closed
B34: 45786 | C34: Nicolai | E34: 45 42 66 72 72 | F34: nicolai_boye_ | H34: Setter | I34: Split-Pay | J34: Split-Pay | K34: 10500 | L34: 3000 | Q34: 6 | S34: Closed
B35: 45786 | C35: Omid | E35: 53 80 53 29 | F35: omid_gorgarbi | H35: Setter | I35: Offer & Didn't Buy | N35: Partner | S35: Hot Follow Up
B36: 45817 | C36: Zofus | E36: 26 84 78 26 | F36: zofusvl | H36: Setter | I36: No-Show
B37: 45817 | C37: Kasper | E37: 21 33 59 33 | F37: Kasper121a | H37: Setter | I37: Offer & Didn't Buy | N37: Money | O37: Penge | S37: Follow Up | T37: Manden var klar og siger han er fuld klar, men når vi kommer til prisen siger han at han kun har 500kr til overs hver måned hvilket er cap
B38: 45817 | C38: Nikolaj | E38: 22 79 89 93 | F38: nikolaj_braendekilde1337 | H38: Setter | I38: Offer & Didn't Buy | N38: Money | S38: X | T38: Han synes det var for dyrt til hans budget og det er hvad det er
B39: 45817 | C39: Patrick | E39: 42 71 12 18 | F39: Patrick_vedel_ | H39: Setter | I39: No-Show
B40: 45817 | C40: Marcus | E40: 28 19 34 36 | F40: 0740_marcus | H40: Setter | I40: No-Show
B41: 45847 | C41: Jacob | E41: 61 77 28 72 | F41: Jacobbjrgensen | H41: Setter | I41: Rescheduled
B42: 45847 | C42: Rasmus | E42: 22 76 09 45 | F42: rasmus_tsp | H42: Setter | I42: Offer & Didn't Buy | N42: Money | O42: penge | S42: Hot Follow Up | T42: Snakkede med ham 2 gange og i lang tid. manden var på nippen og han ville hellere tage kontakt når han var klar. han skal ringes op om 1 måned!
B43: 45847 | C43: Frederik | E43: 41 61 06 19 | F43: Frederik.s.p | H43: Setter | I43: Offer & Didn't Buy | N43: Money | O43: Penge | S43: Follow Up | T43: Han sprang fra
B44: 45847 | C44: Nicklas | E44: 26237806 | F44: Nicklasgrass | H44: Setter | I44: No-Show
B45: 45847 | C45: Mads | E45: 30 78 06 32 | F45: madslorensen_ | H45: Setter | I45: No-Show
B46: 45878 | C46: Emil | E46: 23 92 27 50 | F46: Emil_rasmussen_ | H46: Setter | I46: Split-Pay | K46: 10500 | L46: 3000 | Q46: 6 | S46: Closed
B47: 45878 | C47: Emil | E47: 53 63 24 17 | F47: Emil_thomsen_4700 | H47: Setter | I47: Split-Pay | K47: 10500 | L47: 3000 | Q47: 6 | S47: Closed
B48: 45878 | C48: Theis | E48: 50 41 38 06 | F48: theis.rosenbaum | H48: Setter | I48: Offer & Didn't Buy | N48: Money | O48: Penge | S48: Follow Up | T48: Han var et rigtig godt lead, men han havde en masse projekter kørende, som var med til at han ikke havde pengene til det
B49: 45878 | C49: Samuel | E49: 26 46 97 55 | F49: samuelhvid | H49: Setter | I49: Offer & Didn't Buy | N49: Money | O49: Penge | S49: X | T49: Manden var sat på deposit og var klar. han havde så ikke forstået at det var 3k først, så han ghostede efter han fandt ud af det
B50: 45878 | C50: Emil | E50: 26 35 55 17 | F50: _emil_viborg_ | H50: Setter | I50: No-Show
B51: 45939 | C51: Andreas | E51: 30 21 82 04 | F51: Andreas.valentini | H51: Setter | I51: No-Show
B52: 45939 | C52: Emil | E52: 50 71 52 32 | F52: Emil_vejiling | H52: Setter | I52: No-Show
B53: 45939 | C53: NOah | E53: 61 60 85 16 | F53: Noah_b.j | H53: Setter | I53: Deposit | L53: 100 | S53: Deposit (Follow Up Set) | T53: Han starter og betaler d 30
B54: 45939 | C54: Alexander | E54: 61 77 22 30 | F54: amby_0108 | H54: Setter | I54: Offer & Didn't Buy | N54: Think About It | O54: Penge og tænke over det | S54: Hot Follow Up | T54: Super godt lead og han ville gerne igang, men det der holdte ham tilbage var pengene og at han havde mabge udgifter i forevejen
B55: 45939 | C55: Bertram | E55: 42 50 90 01 | F55: Bertram0309 | H55: Setter | I55: Split-Pay | K55: 10500 | L55: 3000 | Q55: 6 | S55: Closed
B56: 45970 | C56: Malte | E56: 29 12 02 86 | F56: Malte_molsted | H56: Setter | I56: Offer & Didn't Buy | N56: Money | O56: Penge | S56: Follow Up | T56: Prøvede at presse citronen, da han var et godt lead, men han var bare ikke comittet nok tbh
B57: 45970 | C57: Marcus | E57: 42 40 55 85 | F57: Marcus_k_m | H57: Setter | I57: No-Show
B58: 45970 | C58: Elias | E58: 28 49 11 83 | F58: Eliasschultzz | H58: Setter | I58: Offer & Didn't Buy | N58: Fear | S58: Hot Follow Up | T58: Manden var så tæt på at betale 6k, men hans bank afviste og han fik helt sus på, så det mistede vi ham på
B59: 45970 | C59: Simon | E59: 51 50 73 06 | F59: Thrane_s | H59: Setter | I59: Offer & Didn't Buy | N59: Money | O59: Penge | S59: Follow Up | T59: Super fint lead og han skulle bare igang! Men han valgte ikke at gide investere i det og pressede citronen
B60: 46000 | C60: Jeppe | E60: 61 66 42 72 | F60: jeppe_gertz | H60: Setter | I60: Cancelled
B61: 15/09/2025 | C61: Samuel | E61: 26 46 97 55 | F61: samuelhvid | H61: Setter | I61: No-Show | T61: Manden var som deposit og var klar til at komme igang, men mødte aldrig op
B62: 22/09/2025 | C62: Sebastian | E62: 29 32 18 17 | F62: Sebastianaerkjaer | H62: Setter | I62: Split-Pay | K62: 10500 | L62: 3000 | Q62: 6 | S62: Closed
B63: 22/09/2025 | C63: Albert | E63: 52 24 02 04 | F63: alberthelms3 | H63: Setter | I63: Offer & Didn't Buy | N63: Money | O63: det passede alligevel ikke i hans budget | S63: Follow Up
B64: 23/09/2025 | C64: Sebastian | E64: 27 97 31 86 | F64: sebastian_beske_larsen | H64: Setter | I64: Bad Fit & No Offer | N64: Value | O64: ikke godt match | S64: X | T64: manden ville have en der kunne lave krudt plan til ham
B65: 23/09/2025 | C65: Jonas | E65: 60 72 87 30 | F65: jonaszaatri_ | H65: Setter | I65: Offer & Didn't Buy | N65: Money | O65: Penge | S65: Hot Follow Up | T65: Sygt godt lead og skulle bare have sit fulde potentiale frem. men han skrev at hans mor ikke synes det var en god ide lige nu. God follow up
B66: 24/09/2025 | C66: Elias | E66: 60 52 10 21 | F66: Elias_durak | H66: Setter | I66: Offer & Didn't Buy | N66: Money | O66: Penge | S66: Follow Up | T66: Han troede det kostede 500-600kr som var den pris han fik for nogen år siden. Så det var det som holdte ham tilbage
B67: 24/09/2025 | C67: Raman | E67: 42 33 14 64 | F67: raman1231 | H67: Setter | I67: Bad Fit & No Offer
B68: 24/09/2025 | C68: Lukas | E68: 93 97 00 68 | F68: Lu_kas.2006 | H68: Setter | I68: Offer & Didn't Buy | N68: Time | O68: dårlig timing | S68: Hot Follow Up | T68: Sygt godt follow up og han var klar igen om 1 måned fordi han lige skulle fikse nogen ting
B69: 24/09/2025 | C69: Nicolai | E69: 21 42 16 05 | F69: Nicolai_gadegaard | H69: Setter | I69: Offer & Didn't Buy | N69: Money | O69: Økonomi | S69: Follow Up | T69: Han ville gerne vente med at komme igang og vente til han var udlært da pengene var større der
B70: 24/09/2025 | C70: Mike | E70: 28 19 40 13 | F70: mikeyacoubi | H70: Setter | I70: Full-Pay | K70: 9000 | L70: 9000 | Q70: 6 | S70: Closed
B71: 25/09/2025 | C71: Jonas | E71: 93 60 87 04 | F71: jonashvid04 | H71: Setter | I71: Split-Pay | K71: 10500 | L71: 3000 | Q71: 6 | S71: Closed
B72: 25/09/2025 | C72: Mads | E72: 51 93 47 36 | F72: Mads_liltoft | H72: Setter | I72: Rescheduled
B73: 25/09/2025 | C73: Mattis | E73: 51 71 78 93 | F73: Nygaardmattis | H73: Setter | I73: Offer & Didn't Buy | N73: Money | O73: Penge | S73: Follow Up | T73: Manden var 100% og vi havde sat et opfølgende kald på og han aflyser på dagen. han er en god follow up
B74: 25/09/2025 | C74: Victor | E74: 22 40 65 07 | F74: Victor_weller_10 | H74: Setter | I74: Offer & Didn't Buy | N74: Money | O74: Penge | S74: Follow Up | T74: ung fyr som var 17 og var i skole, så han havde ikke pengene til det
B75: 25/09/2025 | C75: Thor | E75: 61 41 55 12 | F75: Thor_becker | H75: Setter | I75: No-Show
B76: 26/09/2025 | C76: Nicklas | E76: 29 72 94 07 | F76: nicklas_nielsen_ | H76: Setter | I76: Rescheduled | N76: Time | O76: tid | S76: X | T76: Manden var klar om 6 mdr, så vi har sat et nyt kald op 6 mdr frem
B77: 26/09/2025 | C77: Daniel | E77: 42 95 87 96 | F77: s12kruse | H77: Setter | I77: Cancelled
B78: 26/09/2025 | C78: Christian | E78: 21 34 54 47 | F78: Christian_sofus.privat | H78: Setter | I78: Offer & Didn't Buy | N78: Fear | O78: Frygt | S78: Hot Follow Up | T78: Manden var fucking ready og ville bare igang. Da han skal betale, så skal han snakke med sin far om at overfører pengene og så skriver han at han glemte han skulle til værnepligt om 1 måned lol
B79: 27/09/2025 | C79: Jonas | E79: 27 78 40 17 | F79: Jonas_zeiler_frederiksen | H79: Setter | I79: Full-Pay | K79: 9000 | L79: 9000 | Q79: 6 | S79: Closed
B80: 27/09/2025 | C80: Willas | E80: 93 88 47 77 | F80: Willadsbrandt | H80: Setter | I80: Rescheduled | T80: Nyt kald d 31 da det var der han havde penge
B81: 27/09/2025 | C81: Nicklas | E81: 42 54 25 27 | F81: Nick.espri | H81: Setter | I81: No-Show
B82: 28/09/2025 | C82: peter | E82: 25 74 49 41 | F82: Peter_soenderhaven | H82: Setter | I82: Full-Pay | K82: 6000 | L82: 6000 | Q82: 4 mdr | S82: Closed
B83: 28/09/2025 | C83: David | E83: 42 33 92 22 | F83: david_gjerluff_madsen69 | H83: Setter | I83: Cancelled
B84: 28/09/2025 | C84: Nikolai | E84: 28 56 13 89 | F84: Nikolai_fth | H84: Setter | I84: Full-Pay | K84: 4500 | L84: 4500 | Q84: 3 mdr | S84: Closed
B85: 28/09/2025 | C85: Mikail | E85: 42 71 62 46 | F85: Mikail_kizillkaya | H85: Setter | I85: Split-Pay | K85: 10500 | L85: 3000 | Q85: 6 mdr | S85: Closed
B86: 28/09/2025 | C86: Søren | E86: 24 52 55 53 | F86: slundjuhl | H86: Setter | I86: Offer & Didn't Buy | N86: Money | O86: Penge | S86: Follow Up | T86: Det gad han ikke bruge penge på
B87: 29/09/2025 | C87: Kristian | E87: 22 99 35 80 | F87: Kristiansipsen | H87: Setter | I87: Offer & Didn't Buy | N87: Think About It | O87: gad ikke | S87: Hot Follow Up | T87: Manden var vold klar på kaldet og lige efter skriver han at det ikke er for ham. Meget underligt
B88: 29/09/2025 | C88: Okan | E88: 50 53 01 40 | F88: okanpedersen | H88: Setter | I88: Offer & Didn't Buy | N88: Money | O88: Penge | S88: Follow Up | T88: han havde bare ikke pengene til det, ellers var han sej og gerne ville igang
B89: 29/09/2025 | C89: Miakel | E89: 25 70 30 44 | F89: Miakel_yako | H89: Setter | I89: No-Show
B90: 29/09/2025 | C90: Mathias | E90: 93 86 44 19 | F90: Mathias.wallin | H90: Setter | I90: Offer & Didn't Buy | N90: Money | S90: Follow Up | T90: Han var klar og ville give den gas, men han havde ikke pengene til et!
B91: 29/09/2025 | C91: Carl Emil | E91: 30 22 10 96 | F91: Carl.emil_privat | H91: Setter | I91: No-Show
B92: 30/09/2025 | C92: Sebatian | E92: 22 11 98 38 | F92: Sebastian_sib_therkelsen | H92: Setter | I92: Cancelled | T92: han canceller lige inden kaldet og hører ikke fra ham igen
B93: 30/09/2025 | C93: Emanuel | E93: 41 39 25 25 | F93: emanuel.munch | H93: Setter | I93: Split-Pay | K93: 10500 | L93: 3000 | Q93: 6 mdr | S93: Closed
B94: 30/09/2025 | C94: Luca | E94: 60 22 27 62 | F94: lucabeckerh | H94: Setter | I94: Split-Pay | K94: 10500 | L94: 3000 | Q94: 6 mdr | S94: Closed
B95: 30/09/2025 | C95: Jonas | E95: 71 78 02 70 | F95: byskovjonas | H95: Setter | I95: Offer & Didn't Buy | N95: Time | O95: penge | S95: Hot Follow Up | T95: Manden var vold klar i enten oktober eller november, da han skulle have pengene til det og hans bror var også ready
H96: Setter
F222: h

Sheet Oct
A1: $ | B1: Rep: | C1: Name | E1: Anton KPI's | H1: Outcome | K1: KPIs% | N1: Show Rate | Q1: Objections | T1: Source
E2: Rev per call | F2: =C3/C6 -> 3726.1905 | H2: Full-Pay: | I2: =IFERROR(COUNTIFS(I13:I311, "Full-Pay"),"") -> 8 | K2: Conversion Rate: | L2: =iferror(L10/L8,"") -> 0.39285714 | N2: Rescheduling Rate: | O2: =iferror(I8/L6,"") -> 0 | Q2: Think About It | R2: =IFERROR(COUNTIFS(N35:N310, "think about it"),"") -> 6 | T2: Setter | U2: =IFERROR(COUNTIF(H35:H310,"setter"),"") -> 0
B3: Revenue | C3: =IFERROR(SUM(K13:K307),"") -> 313000 | E3: Cash per call | F3: =C4/C6 -> 1520.2381 | H3: Split-Pay: | I3: =IFERROR(COUNTIFS(I13:I311, "Split-Pay"),"") -> 25 | K3: Offer To Close Rate: | L3: =IFERROR(L10/L9,"") -> 0.39759036 | N3: Cancellation Rate: | O3: =iferror(I9/L6,"") -> 0.057692308 | Q3: Money | R3: =IFERROR(COUNTIFS(N35:N310, "money"),"") -> 20 | T3: IG | U3: =IFERROR(COUNTIF(H35:H310,"IG"),"") -> 82
B4: Cash | C4: =IFERROR(SUM(L13:L308),"") -> 127700 | E4: Cash upfront % | F4: =C4/C3*100 -> 40.798722 | H4: Deposits: | I4: =IFERROR(COUNTIFS(I13:I311, "Deposit"),"") -> 5 | K4: Call To Offer Rate: | L4: =IFERROR(L9/L8,"") -> 0.98809524 | N4: No-Shows Rate: | O4: =iferror(I10/L6,"") -> 0.13461538 | Q4: Time | R4: =IFERROR(COUNTIFS(N35:N310, "time"),"") -> 3 | T4: YouTube | U4: =IFERROR(COUNTIF(H35:H310,"youtube"),"") -> 0
E5: PIF % | F5: =I2/C7*100 -> #DIV/0! | H5: Offer & Didn't Buy: | I5: =IFERROR(COUNTIFS(I13:I311, "Offer & Didn't Buy"),"") -> 45 | K5: Drag Over Rate: | L5: =IFERROR(I7/(C6+I7+I8),"") -> 0 | N5: Drag Over Rate: | O5: =iferror(I7/L6,"") -> 0 | Q5: Partner | R5: =IFERROR(COUNTIFS(N35:N310, "partner"),"") -> 1 | T5: Email | U5: =IFERROR(COUNTIF(H35:H310,"email"),"") -> 0
B6: Total Calls : | C6: =IFERROR(SUM(I2:I6),"") -> 84 | E6: Average Binding | F6: =AVERAGE(Q13:Q104) -> 5.7931034 | H6: Bad Fit & No Offer: | I6: =IFERROR(COUNTIFS(I13:I311, "Bad Fit & No Offer"),"") -> 1 | K6: Bookings: | L6: =IFERROR(SUM(I2:I10),"") -> 104 | N6: Show-Up Rate: | O6: =iferror(L7/L6,"") -> 0.80769231 | Q6: Fear | R6: =IFERROR(COUNTIFS(N35:N310, "fear"),"") -> 10 | T6: Facebook | U6: =IFERROR(COUNTIF(H35:H310,"facebook"),"") -> 0
B7: Total Won : | E7: Average deal | F7: =C3/C7 -> #DIV/0! | H7: Drag Over & Show: | I7: =IFERROR(COUNTIFS(I13:I311, "Drag Over & Show"),"") -> 0 | K7: Shows: | L7: =IFERROR(SUM(I2:I7),"") -> 84 | N7: Conducted Rate: | O7: =IFERROR(L8/L6,"") -> 0.80769231 | Q7: Value | R7: =IFERROR(COUNTIFS(N36:N311, "value"),"") -> 1 | T7: Facebook Ads | U7: =IFERROR(COUNTIF(H35:H310,"facebook ads"),"") -> 0
B8: Total Lost : | C8: =iferror(SUM(C7/C6),"") -> 0 | E8: Average cash | F8: =C4/C7 -> #DIV/0! | H8: Rescheduled: | I8: =IFERROR(COUNTIFS(I13:I311, "Rescheduled"),"") -> 0 | K8: Calls: | L8: =IFERROR(SUM(I2:I6),"") -> 84 | T8: LinkedIn | U8: =IFERROR(COUNTIF(H35:H310,T8),"") -> 0
B9: Closing % : | H9: Cancelled: | I9: =IFERROR(COUNTIFS(I13:I311, "Cancelled"),"") -> 6 | K9: Offers: | L9: =IFERROR(sum(I2:I5),"") -> 83
H10: No-Show: | I10: =IFERROR(COUNTIFS(I13:I311, "No-Show"),"") -> 14 | K10: Deals | L10: =I2+I3 -> 33
B12: Date | C12: Name | E12: Phone No. | F12: IG Navn | H12: Source | I12: Outcome | K12: Revenue | L12: Cash | N12: Objection | O12: Objection Notes | Q12: Length | R12: Recording Link | S12: Follow Up/Next Steps | T12: Call Summary
B13: 1 | C13: Victor | D13: idk | E13: idk | F13: Victor_colberg | H13: IG | I13: Split-Pay | K13: 9000 | L13: 1500 | Q13: 6 | S13: Closed | T13: En tidligere klient, som gerne ville starte igen og han sparede opstart fordi han har været på forløb før
B14: 2 | C14: Mikkel | E14: 52174755 | F14: __mikkel__c | H14: IG | I14: Offer & Didn't Buy | N14: Money | O14: PENGE | S14: Follow Up | T14: Manden var ready og var sat på deposit og så skriver han på dagen at det var for dyrt
B15: 2 | C15: Malte | E15: 29120286 | F15: malte_molsted | H15: IG | I15: Offer & Didn't Buy | N15: Partner | O15: hans dame | S15: Follow Up | T15: også deposit og så tager han ikke telefonen på dagen fordi han har dame problemer
B16: 4 | C16: Mikkel | E16: 20 60 02 88 | F16: Mikkel_skerning | H16: IG | I16: Offer & Didn't Buy | N16: Fear | O16: Bange | S16: Hot Follow Up | T16: Manden ville bare gerne igang, men han kunne ikke se behovet da jeg fortalte prisen selvom jeg prøvede at presse ham
B17: 4 | C17: Jacob | E17: idk | F17: jacobjrgensen | H17: IG | I17: No-Show
B18: 4 | C18: Jacob | E18: 30 48 78 82 | F18: 3329jacob | H18: IG | I18: Deposit | L18: 100 | Q18: 6 | S18: Deposit (Follow Up Set) | T18: han starter d 1 november
B19: 4 | C19: Emanuel | E19: 20 63 76 31 | F19: Emmanuelfuglsang | H19: IG | I19: Offer & Didn't Buy | N19: Money | O19: Penge | S19: Follow Up | T19: snakekde med ham i 40 min og han kunne mærke behovet og synes det var en fair pris. Men da vi kommer til prisen vil han gerne betale efter og hører aldrig fra ham igen
B20: 4 | C20: Andreas | E20: 20 70 64 04 | F20: andreas.storgaard | H20: IG | I20: Split-Pay | K20: 10500 | L20: 3000 | Q20: 6 | S20: Closed
B21: 5 | C21: Vitus | E21: 24 23 39 35 | F21: Vitusaaen | H21: IG | I21: Split-Pay | K21: 10500 | L21: 3000 | Q21: 6 | S21: Closed
B22: 5 | C22: Filip | E22: 51 52 95 25 | F22: filipdorf3 | H22: IG | I22: Split-Pay | K22: 10500 | L22: 3000 | Q22: 6 | S22: Closed
B23: 8 | C23: TObias | E23: 93 91 44 02 | F23: Tobias_m4l | H23: IG | I23: Offer & Didn't Buy | N23: Think About It | O23: Tænke over det | S23: Follow Up | T23: Han synes det lød godt, men han var sælger og stilelde mig 100 spørgsmål og var sådan en lidt irriterende dude. Men hørte aldrig fra ham igen
B24: 9 | C24: Oskar | E24: 60 59 94 24 | F24: oskarkirkeby_ | H24: IG | I24: Cancelled | T24: bro troede det var gratis
B25: 9 | C25: Nichlas | E25: 93 60 73 18 | F25: nichlaskotter | H25: IG | I25: Split-Pay | K25: 10500 | L25: 3000 | Q25: 6 | S25: Closed
B26: 9 | C26: Valdemar | E26: 22 84 81 80 | F26: V.sehested | H26: IG | I26: No-Show
B27: 9 | C27: Alexsander | E27: 93 91 19 01 | F27: Alexsanderbogetoft | H27: IG | I27: Offer & Didn't Buy | N27: Money | O27: Penge | S27: Follow Up | T27: Fint follow up da han synes pengene var det som holdte ham tilbage
B28: 10 | C28: Emil | E28: 23 61 36 80 | F28: Emilhm2001 | H28: IG | I28: Cancelled | T28: han aflyser lige inden kaldet
B29: 10 | C29: Martin | E29: 61 70 39 23 | F29: mart_insoerensen | H29: IG | I29: No-Show
B30: 10 | C30: Tamim | E30: 42 30 63 60 | F30: tamim.alkheder | H30: IG | I30: No-Show
B31: 11 | C31: Patrick | E31: 81 73 86 96 | F31: Patrickandersen51 | H31: IG | I31: Split-Pay | K31: 10500 | L31: 3000 | Q31: 6 | S31: Closed
B32: 12 | C32: Tobias | E32: 23 84 58 21 | F32: Jegertobiasjensbydyrholm | H32: IG | I32: Split-Pay | K32: 7500 | L32: 1500 | Q32: 4 | S32: Closed | T32: han betaler resten når han får løn
B33: 13 | C33: Louis | E33: 42 33 52 43 | F33: Louis.haghfelt | H33: IG | I33: Offer & Didn't Buy | N33: Money | O33: penge | S33: Follow Up | T33: rigtig godt follow up som synes det lød godt og gerne ville igang, men han ville lige tænke over den og det gad han ikke. Han sagde også han var presset på økonomi
B34: 13 | C34: Frederik | E34: 29 29 50 12 | F34: rosae.fontanus | H34: IG | I34: Split-Pay | K34: 10500 | L34: 3000 | Q34: 6 | S34: Closed
B35: 13 | C35: Oskar | E35: 23 91 32 11 | F35: oskar_thormann | H35: IG | I35: Offer & Didn't Buy | N35: Fear | O35: han var bange for scam | S35: Follow Up | T35: han lød sygt klar og ville bare gerne igang, men lige da han hørte prisen så sagde han at det var bange for scam loool
B36: 13 | C36: Joachim | E36: 40 81 86 87 | F36: joachimbarlev | H36: IG | I36: Full-Pay | K36: 6000 | L36: 6000 | Q36: 4 | S36: Closed
B37: 13 | C37: Timo | E37: 20 90 62 90 | F37: Timo_lauritzen | H37: IG | I37: No-Show
B38: 13 | C38: Jakob | E38: 60 94 61 87 | F38: Jakob_lind93 | H38: IG | I38: Offer & Didn't Buy | N38: Money | O38: Penge | S38: Hot Follow Up | T38: Han var vold varm og ville bare gerne igang, men han skulle snakke med konen da de også har børn og han vendte tilbage med at økonomien var stram, selvom jeg på kaldet sagde han havde råd til det hvis han prioriteret det
B39: 13 | C39: Jannik | E39: 81 61 64 51 | F39: _jannik_harrison | H39: IG | I39: Split-Pay | K39: 10500 | L39: 1500 | Q39: 6 | S39: Closed | T39: Han betaler resten når han får løn
B40: 14 | C40: Emil | E40: 20 36 62 63 | F40: emiloz__ | H40: IG | I40: Offer & Didn't Buy | L40: 100 | Q40: 6 | S40: X | T40: han starter og betaler d 1 (han blev indlagt på hospitalet)
B41: 14 | C41: Christian | E41: 22 32 02 55 | F41: christian_g_thorsen | H41: IG | I41: Full-Pay | K41: 9000 | L41: 9000 | Q41: 6 | S41: Closed
B42: 14 | C42: Elias | E42: 27 14 77 78 | F42: elliedb__ | H42: IG | I42: Offer & Didn't Buy | N42: Fear | O42: idk | S42: Hot Follow Up | T42: Manden var fucking klar og har haft 3 andre coaches før. vil have deposit fra ham og beder ham smide penge på kontoen og hørte ikke fra ham igen. Så han skal bare kontaktes igen
B43: 14 | C43: Johan | E43: 53 53 20 57 | F43: johan.kjae | H43: IG | I43: Full-Pay | K43: 9000 | L43: 9000 | Q43: 6 | S43: Closed
B44: 14 | C44: belmin | E44: 42 51 04 33 | F44: kasumovic_belmin | H44: IG | I44: No-Show
B45: 14 | C45: Casper | E45: 25 40 72 34 | F45: casperrosenkrantzgroth | H45: IG | I45: Offer & Didn't Buy | N45: Think About It | O45: have det på skrift | S45: Follow Up | T45: bro var klar, men ville have det på skrift og det fik han og så hørte jeg aldrig fra bro igen lol
B46: 14 | C46: Mathias | E46: 25 12 21 15 | F46: mathias.sommerwivel | H46: IG | I46: Offer & Didn't Buy | N46: Fear | O46: Kunne høre det han ikke ture tage springet | S46: Hot Follow Up | T46: Rigtig godt follow up fordi han var sygt klar på kaldet og pengene lød også fint. Lige da han skal betale, så siger han at jeg kan ringe om 15 fordi han var ved at komme ombord på en båd. Så skriver han efter at han selv gerne vil forsøge
B47: 15 | C47: Mads | E47: 91 56 28 40 | F47: Pilotmads8 | H47: IG | I47: Split-Pay | K47: 10500 | L47: 3000 | Q47: 6 | S47: Closed
B48: 15 | C48: Mads | E48: 51 93 47 36 | F48: mads_liltoft | H48: IG | I48: Split-Pay | K48: 10500 | L48: 1500 | Q48: 6 | S48: Closed | T48: Får resten når han får løn
B49: 15 | C49: Adam | E49: 53 82 05 18 | F49: adam_hardt1 | H49: IG | I49: Offer & Didn't Buy | N49: Fear | O49: han følte sig ikke klar | S49: Hot Follow Up | T49: han var super cool og også frisk til at komme igang, men han ville tænke over det og så skrev han at det ikke blev i den her omgang
B50: 15 | C50: Lukas | E50: 28 71 61 05 | F50: lukas_plinius | H50: IG | I50: Full-Pay | K50: 9000 | L50: 9000 | Q50: 6 | S50: Closed
B51: 15 | C51: Jacob | E51: 21 79 68 96 | F51: dax4life | H51: IG | I51: Split-Pay | K51: 10500 | L51: 3000 | Q51: 6 | S51: Closed
B52: 15 | C52: Markus | E52: 22 29 40 18 | F52: markusgrave48 | H52: IG | I52: Offer & Didn't Buy | N52: Fear | O52: bange | S52: X | T52: manden var klar og har haft rene som coach og ville gerne betale pif, men han havde ikke pung på sig og vi aftaler at betale dagen efter og så vågner jeg til at han har blokeret mig lol
B53: 16 | C53: Felix | E53: 21 86 26 32 | F53: Felix_lundhof | H53: IG | I53: Offer & Didn't Buy | N53: Money | O53: Penge | S53: Follow Up | T53: Super nice fyr, men det der holdte ham tilbage var ækonomien, så det blev ikke den her omgang
B54: 16 | C54: Casper | E54: 42 46 73 74 | F54: casper.fck | H54: IG | I54: Split-Pay | K54: 9000 | L54: 4500 | Q54: 6 | S54: Closed | T54: betaler resten når han får løn
B55: 16 | C55: Danni | E55: 27 88 80 44 | F55: dannielling | H55: IG | I55: Deposit | S55: Deposit (Follow Up Set) | T55: det er et deposit som skulle betale som allerede har betalt 500kr. Han tog ikke telefonen?
B56: 16 | C56: Oliver | E56: 71 71 04 71 | F56: oliver_w_petersen | H56: IG | I56: Offer & Didn't Buy | N56: Partner | O56: forældre | S56: Follow Up | T56: han var faktisk klar, men hans forældre sagde nej fordi han var under 18
B57: 16 | C57: Gowsihan | E57: 42 94 19 97 | F57: Gowsighan_dk | H57: IG | I57: Offer & Didn't Buy | N57: Fear | O57: bange og penge | S57: Hot Follow Up | T57: Super cool fyr og ville gerne tabe sig. han var klar og da jeg kommer til at han også kan betale pif, så siger han at han vil have 30 min til at finde ud af hvordan han vil betale og så skriver han efter at han ikke vil starte op lol
B58: 16 | C58: Noah | E58: 22 39 26 56 | F58: noah_assenholt | H58: IG | I58: Offer & Didn't Buy | N58: Money | O58: Penge | S58: Follow Up | T58: For mange penge for ham, men ellers super cool og han kunne godt se ideen i at betale for det og have coach på
B59: 16 | C59: William | E59: 93 90 14 77 | F59: Williamranders0 | H59: IG | I59: Offer & Didn't Buy | N59: Money | O59: Penge | S59: Follow Up | T59: han gad ikke bruge penge på det og så var han også 17, så pengene var ikke store
B60: 17 | C60: Victor | E60: 42 45 40 54 | F60: victormadsenlarsen | H60: IG | I60: Offer & Didn't Buy | N60: Fear | O60: Bange for at tage springet | S60: Hot Follow Up | T60: Han var sygt varm og han ville gerne igang, men han ville have tid til at tænke over det og så vendte han tilbage med et fear svar og det var at han ikke vidste om han var 100% klar til at gå all in
B61: 18 | C61: William | E61: 61 12 00 87 | F61: William.krarup_ | H61: IG | I61: No-Show
B62: 19 | C62: Valdemar | E62: 61 40 96 20 | F62: valdemar_faber_madsen | H62: IG | I62: Offer & Didn't Buy | N62: Think About It | O62: TÆnke over det | S62: Follow Up | T62: Fint follow up lead. han var klar under kaldet, men kunne godt mærke at han ikke var 100% klar og han valgte at takke nej
B63: 19 | C63: Mikey | E63: 60 72 09 14 | F63: mikey_hornbol_andersen | H63: IG | I63: Split-Pay | K63: 10500 | L63: 3000 | Q63: 6 | S63: Closed
B64: 19 | C64: Magnus | E64: 28 91 80 24 | F64: Magnus_hostrup03 | H64: IG | I64: No-Show
B65: 19 | C65: Victor | E65: 93 60 56 50 | F65: victorbrixschmidt | H65: IG | I65: Split-Pay | K65: 10500 | L65: 3000 | N65: Money | O65: Penge | Q65: 6 | S65: Closed | T65: Skal snakke med ham d 31 for at få ham igang
B66: 19 | C66: Micklas | E66: 29 31 87 56 | F66: micklas_dam | H66: IG | I66: Offer & Didn't Buy | N66: Money | O66: Penge | S66: Follow Up | T66: Han var super cool, men slet ikke comittet nok under kaldet. Han ville tænke over det og så skrev han pænt nej tak
B67: 19 | C67: Gustav | E67: 41 98 04 80 | F67: gustavboggild | H67: IG | I67: Split-Pay | K67: 10500 | L67: 3000 | Q67: 6 | S67: Closed | T67: Skal snakke med ham d 31 for at få ham igang
B68: 19 | C68: Lukas | E68: 27 64 88 86 | F68: lukashandrup | H68: IG | I68: Offer & Didn't Buy | N68: Money | O68: Penge | S68: Follow Up | T68: Han havde ikke pengene til det. prøvede at opjection handle, men han kunne slet ikke komme igang
B69: 19 | C69: Lasse | E69: 42 42 31 88 | F69: l.dalsten | H69: IG | I69: Bad Fit & No Offer | S69: X | T69: Manden ville kun hører prisen og så lagde jeg den bare fra starten og det fik ham self til at hoppe af
B70: 20 | C70: Oliver | E70: 50 11 32 75 | F70: oliverfischer27 | H70: IG | I70: No-Show
B71: 20 | C71: Tobias | E71: 42 25 10 75 | F71: Jensen_42_ | H71: IG | I71: Offer & Didn't Buy | N71: Money | O71: Ikke økonomien til det | S71: Follow Up
B72: 20 | C72: Asger | E72: 28 93 19 14 | F72: Asgerdinesen | H72: IG | I72: Cancelled | T72: han gad ikke tage snakken hvis det var over instagram
B73: 20 | C73: Magnus | E73: 22 83 13 77 | F73: Magnus__j | H73: IG | I73: Cancelled | T73: han ville igang og så ville han ikke igang. det var lidt underligt
B74: 20 | C74: Niklas | E74: 22 31 08 37 | F74: Niklas_j.j | H74: IG | I74: Split-Pay | K74: 10500 | L74: 3000 | Q74: 6 | S74: Closed
B75: 20 | C75: Mikkel | E75: 93 83 31 85 | F75: spurgt344 | H75: IG | I75: Offer & Didn't Buy | N75: Money | O75: Penge | S75: Follow Up | T75: Han ville igang og så ville han tage den d 31 da der var løn. så skrev han at han ikke kunne fordi han sofasurfede lige pt
B76: 21 | C76: Emil | E76: 52 19 55 58 | F76: Emil.thoring | H76: IG | I76: Full-Pay | K76: 6000 | L76: 6000 | Q76: 4 | S76: Closed
B77: 21 | C77: Jakob | E77: 22 41 18 35 | F77: jakob__gronfeldt | H77: IG | I77: Offer & Didn't Buy | N77: Fear | O77: bange | S77: Follow Up | T77: sygt godt lead og super nice. han var god til at udskyde og vandt alle hans opjektions. Vi aftalte at få styr på det hele senere på dagen og så mødte han aldrig op til kaldet
B78: 22 | C78: Frederik | E78: 26 20 09 39 | F78: farent91 | H78: IG | I78: Offer & Didn't Buy | N78: Money | O78: jule gaver osv osv | S78: Follow Up | T78: han var super nice og var sådan set klar, men det var økonomien og frygt som holdte ham tilbage
B79: 22 | C79: Rasmus | E79: 71 70 99 67 | F79: Rasmus dalgaard4 | H79: IG | I79: Offer & Didn't Buy | L79: 500 | N79: Time | S79: Hot Follow Up | T79: sygt nice fyr som skulle tabe sig så han kunne lave hud fjerning og betalte endda også 500kr i deposit. han skrev så nogen dage efter at han havde fået en fyreseddel og ikke kunne starte op alligevel
B80: 22 | C80: Dan | E80: 81 74 74 71 | F80: dan_gutmann | H80: IG | I80: Offer & Didn't Buy | N80: Money | O80: Penge | S80: Follow Up | T80: han havde slet ikke penge til at betale for forløbet, så vi rundede hurtigt af
B81: 22 | C81: Asbjørn | E81: 71 92 29 09 | F81: Asbjorn_madsen | H81: IG | I81: Split-Pay | K81: 10500 | L81: 3000 | Q81: 6 | S81: Closed
B82: 22 | C82: Simon | E82: 50 57 08 44 | F82: Simse_4311 | H82: IG | I82: Offer & Didn't Buy | N82: Value | O82: Personlige træninger | S82: Follow Up | T82: Han ville ikke igang, fordi han ikke fik personlige træninger også
B83: 23 | C83: Christian | E83: 42 26 45 71 | F83: Christian_gadegaard | H83: IG | I83: Offer & Didn't Buy | N83: Money | O83: Penge | S83: Follow Up | T83: Christian er tjener som boede ude med kæresten og kunne ikke finde økonomien til at betale for forløbet
B84: 23 | C84: Daniel | E84: 26 16 47 22 | F84: dalleh43 | H84: IG | I84: Deposit | N84: Money | S84: Deposit (Follow Up Set) | T84: Skal snakke med ham d 6 november mht opstart og betaling
B85: 23 | C85: Mikkel | E85: 27 80 15 30 | F85: Hansen_amager | H85: IG | I85: Offer & Didn't Buy | N85: Money | O85: ikke penge | S85: Follow Up | T85: mikkel havde ikke pengene til at starte op, fordi han havde mange udgifter osv osv
B86: 23 | C86: Søren | E86: 22 14 10 91 | F86: _tossen_ | H86: IG | I86: Split-Pay | K86: 10500 | L86: 3000 | Q86: 6 | S86: Closed
B87: 23 | C87: Mathias | E87: 23 60 67 89 | F87: mathiasalarsen1996 | H87: IG | I87: Offer & Didn't Buy | N87: Time | S87: Deposit (Follow Up Set) | T87: skal snakke med ham d 31 (Han ville ikke have en ung coach som var lidt bro agtigt)
B88: 25 | C88: Oliver | E88: 25 67 20 08 | F88: oliver.l.r.andersen | H88: IG | I88: Offer & Didn't Buy | N88: Money | O88: Penge | S88: Follow Up | T88: han havde ikke så høj løn og så tror jeg bare ikke at jeg gav ham behovet som jeg gerne ville
B89: 25 | C89: Silas | E89: 50 55 48 12 | F89: Silas.tinndahl | H89: IG | I89: No-Show
B90: 25 | C90: Mikkel | E90: 93 92 69 47 | F90: Mikkelsand13 | H90: IG | I90: Offer & Didn't Buy | N90: Think About It | O90: tænke over det | S90: Follow Up | T90: super cool fyr faktisk og var sulten for at give den gas. han ville dog gerne tænke over det og har ikke ført fra ham siden
B91: 25 | C91: Simon | E91: 29 17 45 75 | F91: Simon_vinqvist | H91: IG | I91: Offer & Didn't Buy | N91: Think About It | S91: Deposit (Follow Up Set) | T91: har et kald med ham d 31 for at snakke alt igennem (manden aflyser lige inden kaldet)
B92: 25 | C92: Frederik | E92: 21 30 90 97 | F92: frederik_lund22 | H92: IG | I92: Offer & Didn't Buy | N92: Fear | O92: Frygt | S92: Hot Follow Up | T92: han var sygt varm og klar til at give den gas. vi aftalte også follow up, men så skriver han 2 dage før at han har travlt med fodbold og det var bare et tegn på at han gerne ville udskyde eller var bange for at komme igang
B93: 25 | C93: Kasper | E93: 20 30 16 33 | F93: Kasper123w | H93: IG | I93: Cancelled
B94: 25 | C94: Gustav | E94: 51 66 64 46 | F94: Gustav_lybecker_ | H94: IG | I94: Offer & Didn't Buy | N94: Money | O94: penge | S94: Follow Up | T94: han var slet ikke klar til at komme igang og slet ikke comittet, så der rundede jeg også hurtigt af
B95: 25 | C95: Frederik | E95: 25 13 23 51 | F95: frederik_moeslund | H95: IG | I95: Cancelled | T95: han aflyser lige før kaldet
B96: 25 | C96: Rodi | E96: 71 87 45 94 | F96: Rodi.siso | H96: IG | I96: No-Show
B97: 26 | C97: Nikolaj | E97: 28 80 28 26 | F97: Nikolaj23102004 | H97: IG | I97: Full-Pay | K97: 9000 | L97: 9000 | Q97: 6 | S97: Closed
B98: 26 | C98: Victor | E98: 93 89 04 76 | F98: Victor_sundwall | H98: IG | I98: Offer & Didn't Buy | N98: Money | O98: penge | S98: Hot Follow Up | T98: super cool fyr og var bare straight up. Han ville gerne vente indtil han havde pengne og sådan er det
B99: 26 | C99: Mads | E99: 60 60 44 69 | F99: mads_fisker_ | H99: IG | I99: Offer & Didn't Buy | N99: Money | O99: Første års lærling | S99: Follow Up | T99: super cool fyr og han var første års lærling, så han tjente ikke de fleste penge
B100: 26 | C100: Mattias | E100: 30 20 69 15 | F100: mattiaschistensen | H100: IG | I100: Offer & Didn't Buy | N100: Fear | O100: frygt | S100: Follow Up | T100: han var slet ikke klar til at investere penge i det
B101: 27 | C101: Lucas | E101: 22 40 08 70 | F101: Lucas_ravne | H101: IG | I101: Split-Pay | K101: 10500 | L101: 3000 | Q101: 6 | S101: Closed
...

Sheet Nov
A1: $ | B1: Rep: | C1: Name | E1: Anton KPI's | H1: Outcome | K1: KPIs% | N1: Show Rate | Q1: Objections | T1: Source
E2: Rev per call | F2: =C3/C6 -> 2922.0779 | H2: Full-Pay: | I2: =IFERROR(COUNTIFS(I13:I311, "Full-Pay"),"") -> 11 | K2: Conversion Rate: | L2: =iferror(L10/L8,"") -> 0.32467532 | N2: Rescheduling Rate: | O2: =iferror(I8/L6,"") -> 0 | Q2: Think About It | R2: =IFERROR(COUNTIFS(N35:N310, "think about it"),"") -> 9 | T2: Setter | U2: =IFERROR(COUNTIF(H35:H310,"setter"),"") -> 0
B3: Revenue | C3: =IFERROR(SUM(K13:K307),"") -> 225000 | E3: Cash per call | F3: =C4/C6 -> 1525.974 | H3: Split-Pay: | I3: =IFERROR(COUNTIFS(I13:I311, "Split-Pay"),"") -> 14 | K3: Offer To Close Rate: | L3: =IFERROR(L10/L9,"") -> 0.34246575 | N3: Cancellation Rate: | O3: =iferror(I9/L6,"") -> 0.06 | Q3: Money | R3: =IFERROR(COUNTIFS(N35:N310, "money"),"") -> 20 | T3: IG | U3: =IFERROR(COUNTIF(H35:H310,"IG"),"") -> 0
B4: Cash | C4: =IFERROR(SUM(L13:L308),"") -> 117500 | E4: Cash upfront % | F4: =C4/C3*100 -> 52.222222 | H4: Deposits: | I4: =IFERROR(COUNTIFS(I13:I311, "Deposit"),"") -> 7 | K4: Call To Offer Rate: | L4: =IFERROR(L9/L8,"") -> 0.94805195 | N4: No-Shows Rate: | O4: =iferror(I10/L6,"") -> 0.17 | Q4: Time | R4: =IFERROR(COUNTIFS(N35:N310, "time"),"") -> 0 | T4: YouTube | U4: =IFERROR(COUNTIF(H35:H310,"youtube"),"") -> 0
E5: PIF % | F5: =I2/C7*100 -> 44 | H5: Offer & Didn't Buy: | I5: =IFERROR(COUNTIFS(I13:I311, "Offer & Didn't Buy"),"") -> 41 | K5: Drag Over Rate: | L5: =IFERROR(I7/(C6+I7+I8),"") -> 0 | N5: Drag Over Rate: | O5: =iferror(I7/L6,"") -> 0 | Q5: Partner | R5: =IFERROR(COUNTIFS(N35:N310, "partner"),"") -> 1 | T5: Email | U5: =IFERROR(COUNTIF(H35:H310,"email"),"") -> 0
B6: Total Calls : | C6: =IFERROR(SUM(I2:I6),"") -> 77 | E6: Average Binding | F6: =AVERAGE(Q13:Q104) -> 5.1818182 | H6: Bad Fit & No Offer: | I6: =IFERROR(COUNTIFS(I13:I311, "Bad Fit & No Offer"),"") -> 4 | K6: Bookings: | L6: =IFERROR(SUM(I2:I10),"") -> 100 | N6: Show-Up Rate: | O6: =iferror(L7/L6,"") -> 0.77 | Q6: Fear | R6: =IFERROR(COUNTIFS(N35:N310, "fear"),"") -> 5 | T6: Facebook | U6: =IFERROR(COUNTIF(H35:H310,"facebook"),"") -> 0
B7: Total Won : | C7: =IFERROR(I2+I3,"") -> 25 | E7: Average deal | F7: =C3/C7 -> 9000 | H7: Drag Over & Show: | I7: =IFERROR(COUNTIFS(I13:I311, "Drag Over & Show"),"") -> 0 | K7: Shows: | L7: =IFERROR(SUM(I2:I7),"") -> 77 | N7: Conducted Rate: | O7: =IFERROR(L8/L6,"") -> 0.77 | Q7: Value | R7: =IFERROR(COUNTIFS(N36:N311, "value"),"") -> 3 | T7: Facebook Ads | U7: =IFERROR(COUNTIF(H35:H310,"facebook ads"),"") -> 0
B8: Total Lost : | C8: =COUNTIF(I13:I310,"offer & didn't buy")+COUNTIF(I35:I310,"deposit")+COUNTIF(I35:I310,"bad fit & no offer") -> 50 | F8: =C4/C7 -> 4700 | H8: Rescheduled: | I8: =IFERROR(COUNTIFS(I13:I311, "Rescheduled"),"") -> 0 | K8: Calls: | L8: =IFERROR(SUM(I2:I6),"") -> 77 | T8: LinkedIn | U8: =IFERROR(COUNTIF(H35:H310,T8),"") -> 0
B9: Closing % : | C9: =iferror(SUM(C7/C6),"") -> 0.32467532 | H9: Cancelled: | I9: =IFERROR(COUNTIFS(I13:I311, "Cancelled"),"") -> 6 | K9: Offers: | L9: =IFERROR(sum(I2:I5),"") -> 73
H10: No-Show: | I10: =IFERROR(COUNTIFS(I13:I311, "No-Show"),"") -> 17 | K10: Deals | L10: =I2+I3 -> 25
B12: Date | C12: Name | E12: Phone No. | F12: IG Navn | H12: Source | I12: Outcome | K12: Revenue | L12: Cash | N12: Objection | O12: Objection Notes | Q12: Length | R12: Recording Link | S12: Follow Up/Next Steps | T12: Call Summary
B13: 1 | C13: Jason | E13: 31689172 | F13: 4281rider_ | I13: Offer & Didn't Buy | N13: Think About It | O13: Penge | S13: Hot Follow Up | T13: Han var sygt klar og vi havde også sat dato på hvornår han skulle betale og komme igang. lige før kaldet skriver han at han ikke vil alligevel. så han skal bare opfølges på!
B14: 2 | C14: Iassemin | E14: 22 55 93 69 | F14: Iasseminflorim | I14: Full-Pay | K14: 4500 | L14: 4500 | Q14: 3 | S14: Closed
B15: 2 | C15: Jakob | E15: 50 50 44 63 | F15: Jakobpil | I15: No-Show
B16: 2 | C16: Jeppe | E16: 61 60 95 68 | F16: jeppe_kuskeren | I16: Offer & Didn't Buy | N16: Money | O16: Penge og frygt | S16: Hot Follow Up | T16: Manden var sygt klar i første omgang og fik også snakket ham varm, men til sidst sagde han at ikke ville bruge penge på det og mistede salget
B17: 2 | C17: Asbjørn | E17: 26 20 59 47 | F17: asi.kjerulf06 | I17: Split-Pay | K17: 10500 | L17: 3000 | Q17: 6 | S17: Closed
B18: 2 | C18: Daniel | E18: 81 71 68 60 | F18: Danireymax9 | I18: No-Show
B19: 2 | C19: Christian | E19: 42 31 19 95 | F19: Chr_post12 | I19: No-Show
B20: 3 | C20: Kristian | E20: 53 62 09 02 | F20: dubndrive | I20: Split-Pay | K20: 10500 | L20: 3000 | M20: 3000 | Q20: 6 | S20: Closed
B21: 3 | C21: Kristian | E21: 21 27 88 22 | F21: kristian_broechner | I21: Deposit | N21: Money | O21: Penge | S21: Follow Up Set | T21: Skal snakke med ham igen d 20 og der er han ready!
B22: 3 | C22: Frederik | E22: 30 53 47 25 | F22: f.r.e.d.e.r.i.k.lr | I22: Cancelled
B23: 3 | C23: Oskar | E23: 42 91 00 35 | F23: oskarmuhring_ | I23: No-Show
B24: 3 | C24: Miles | E24: 53 76 45 37 | F24: Miles_staunsager | I24: Bad Fit & No Offer | N24: Value | O24: ikke godt fit | S24: X | T24: Ikke et godt match
B25: 3 | C25: Marcus | E25: 53 38 51 91 | F25: Marcus_berner1304 | I25: No-Show
B26: 4 | C26: Kimal | E26: 91 55 37 21 | F26: Kimalnaji | I26: Offer & Didn't Buy | N26: Money | O26: Penge og frygt | S26: Follow Up | T26: Han var okay, men typisk irriterende indvandre som ikke gad betale for det og ville tænke over det
B27: 4 | C27: Noah | E27: 61 42 95 51 | F27: N.lippert1 | I27: Offer & Didn't Buy | N27: Think About It | O27: Frygt og tænke over det | S27: Hot Follow Up | T27: Noah ved jeg er klar, men han skulle bare trykkes mere til hvilket jeg ikke gjorde dsv
B28: 4 | C28: Lucas | E28: 28 73 38 27 | F28: lucas_gotke | I28: Offer & Didn't Buy | N28: Think About It | O28: tænke over det | S28: Hot Follow Up | T28: Lucas var klar til at give den gas, men han ville tænke over det og hørte aldrig fra ham igen
B29: 4 | C29: Petere | E29: 31 37 69 07 | F29: peterkristianlarsen | I29: Split-Pay | K29: 10500 | L29: 3000 | Q29: 6 | S29: Closed | T29: den mand havde så mange undskyldninger, men havde aura på kaldet og lukkede
B30: 4 | C30: Marc | E30: 21 12 38 26 | F30: Marcnybo | I30: Offer & Didn't Buy | N30: Money | O30: økonomisk | S30: Follow Up | T30: rigtig god mand og var tynd og ville gerne til at bygge mere muskelmasse op, men han kørte på lærling løn og det gav ikke mening for ham økonomisk
B31: 5 | C31: Rasmus | E31: 26 13 16 12 | F31: rasmus_chf | I31: No-Show
B32: 5 | C32: Lucas | E32: 25 38 28 29 | F32: _lucas_rasmussen | I32: Offer & Didn't Buy | N32: Time | O32: ville prøve selv | S32: Hot Follow Up | T32: Snakkede med en mand der ville igang, men han var bange for at tage springet og fik den klassiske med at han selv ville prøve først
B33: 5 | C33: Oliver | E33: 53 81 61 98 | F33: 0liverskovbo | I33: Split-Pay | K33: 10500 | L33: 3000 | Q33: 6 | S33: Closed
B34: 5 | C34: Timo | E34: 20 90 62 90 | F34: timo_laurltzen | I34: No-Show
B35: 6 | C35: Mike | E35: 25 34 35 41 | F35: Mikejensen2111 | I35: Deposit | L35: 500 | Q35: 6 | S35: Deposit (Follow Up Set) | T35: han starter og betaler d 14 nov
B36: 6 | C36: Mathias | E36: 24 52 54 02 | F36: Mathias.nielsen12 | I36: Split-Pay | K36: 10500 | L36: 3000 | Q36: 6 | S36: Closed
B37: 6 | C37: Nikolaj | E37: 21 34 45 42 | F37: nikolaj_nrfjand | I37: Offer & Didn't Buy | N37: Fear | O37: bange | S37: Hot Follow Up | T37: han ville selv prøve til at starte og på kaldet skulle han bare igang
B38: 6 | C38: Emil | E38: 50 45 04 98 | F38: Emil_hojris | I38: Split-Pay | K38: 10500 | L38: 1500 | Q38: 6 | S38: Closed | T38: han havde ikke penge til opstartsgebyr, så det betaler han d 1
B39: 9 | C39: Mads | E39: 60 60 44 69 | F39: Mads_fisker_ | I39: Full-Pay | K39: 4500 | L39: 4500 | Q39: 3 | S39: Closed
B40: 9 | C40: Sebastian | E40: 93 93 21 20 | F40: sebastian_wengel | I40: Full-Pay | K40: 6000 | L40: 6000 | Q40: 4 | S40: Closed
B41: 9 | C41: Claus | E41: 50 55 23 81 | F41: claus.pallesen | I41: No-Show
B42: 9 | C42: Victor | E42: 52 30 12 94 | F42: victor_krogh_hvidberg | I42: Deposit | K42: 10500 | L42: 3000 | Q42: 6 | S42: Closed | T42: starter og betaler d 30 nov (han har betalt og startet)
B43: 9 | C43: Malthe | E43: 42 41 43 41 | F43: malthethobo | I43: Offer & Didn't Buy | N43: Fear | O43: bange | S43: Hot Follow Up | T43: manden var ægte ready og han var klar og lige da han hørte at han var bundet, så hoppede han af selvom jeg prøvede at opjection handle
B44: 9 | C44: David | E44: 53 77 43 03 | F44: Officialceoofd | I44: Offer & Didn't Buy | N44: Think About It | O44: Frygt | S44: Follow Up | T44: perker som sagde det ikke var så slemt og da han skal til og betale ville han tænke over det lol
B45: 10 | C45: Andre | E45: 42 41 44 27 | F45: Andrefriismunk | I45: Full-Pay | K45: 4500 | L45: 4500 | Q45: 3 | S45: Closed
B46: 10 | C46: Kristoffer | E46: 91 53 83 12 | F46: Kristoffer_brink_nielsen | I46: Offer & Didn't Buy | N46: Money | O46: penge | S46: Hot Follow Up | T46: en loyal følger igennem tiden og han var så klar på at komme igang. Vi aftalte at tage et kald d 5 jan og fortalte ham at jeg skulle have et depositum på 500kr og så lukkede han den...
B47: 10 | C47: Sebastian | E47: 42 45 75 59 | F47: sebastian_pede | I47: Full-Pay | K47: 4500 | L47: 4500 | Q47: 3 | S47: Closed
B48: 10 | C48: William | E48: 60 53 08 07 | F48: william_bay_ | I48: Full-Pay | K48: 9000 | L48: 9000 | Q48: 6 | S48: Closed
B49: 10 | C49: Kasper | E49: 42 17 17 55 | F49: Kasper.soender | I49: No-Show
B50: 10 | C50: Philip | E50: 53 89 12 13 | F50: Philipvammen | I50: Deposit | N50: Money | O50: penge lige nu | S50: Follow Up Set | T50: skal snakke med ham igen d 30 nov
B51: 11 | C51: Carl | E51: 27210540 | F51: carl.houman | I51: Cancelled | T51: Han aflyser inden kaldet og har fået et tilbud har hans brors ven om at blive coached, men det bliver ikke en succes fordi han enten lyver eller fordi det er gratis. Så han skal kontaktes igen!
B52: 11 | C52: Noah | E52: 42773088 | F52: noah_jespersen123 | I52: Bad Fit & No Offer | N52: Value | O52: Han havde styr på det | S52: X | T52: Han havde allerede styr på det hele og så gode resultater!
B53: 11 | C53: Victor | E53: 42 45 40 54 | F53: victormadsenlarsen | I53: Offer & Didn't Buy | N53: Money | O53: Penge | S53: Follow Up Set | T53: Vi har en snak igen d 30 og manden skulle bare igang. Han ryger hver dag og er et dårligt sted i sit liv
B54: 11 | C54: Thomas | E54: 22 22 00 95 | F54: tr7fit | I54: No-Show
B55: 11 | C55: Daniel | E55: 93 85 55 14 | F55: daniel_johannesen85 | I55: Offer & Didn't Buy | N55: Money | O55: penge | S55: X | T55: Han ville gerne igang og han er også i systemet. Han skulle finde ud af hvornår han kunne betale og har stadig ikke hørt fra ham
B56: 11 | C56: Patrick | E56: 91 99 55 51 | F56: Patrickmm17 | I56: Offer & Didn't Buy | N56: Fear | O56: frygt | S56: Hot Follow Up | T56: Han er super varn og endda også snakket med ham før. Han skrev at han kun ville have fokus på kosten og kunne godt lave et forløb kun udfra kost, så det er under snak
B57: 12 | C57: Lucas | E57: 29 11 63 37 | F57: Lucasskaarup_ | I57: Split-Pay | K57: 6000 | L57: 3000 | S57: Closed | T57: han betaler opstartsgebyr d 30
B58: 12 | C58: Thomas | E58: 22 22 00 95 | F58: tr7fit | I58: Cancelled | T58: Han canceller før kaldet da han gerne ville have en der kunne finde ud af at krudte
B59: 12 | C59: Magnus | E59: 28 40 01 42 | F59: Magnus_andersen88 | I59: Split-Pay | K59: 10500 | L59: 3000 | Q59: 6 | S59: Closed | T59: Har et kald med ham d 30 hvor han starter og betaler (betalt)
B60: 12 | C60: Benjamin | E60: 60 12 42 51 | F60: bkronborg10 | I60: Cancelled | T60: Canceller lige før kaldet
B61: 12 | C61: Noah | E61: 42 72 58 85 | F61: noahbailum | I61: Full-Pay | K61: 6000 | L61: 6000 | Q61: 4 | S61: Closed
B62: 13 | C62: Rasmus | E62: 27 12 32 11 | F62: rgaardsted | I62: Full-Pay | K62: 9000 | L62: 9000 | Q62: 6 | S62: Closed
B63: 13 | C63: Virlan | E63: 50 23 94 37 | F63: virlan.__.robert | I63: Offer & Didn't Buy | N63: Money | O63: Penge | S63: Hot Follow Up | T63: Han var rigtig varm og ville gerne igang, men pengene holdte ham tilbage, for ellers havde vi fået ham igang
B64: 13 | C64: Idk | E64: 31 77 98 94 | F64: nybergtjalfe01 | I64: Offer & Didn't Buy | N64: Money | O64: Penge | S64: Follow Up | T64: Vigtig varm og ville også igang, men han kunne ikke komme igang de næste 2 mdr pga økonomien
B65: 13 | C65: Thomas | E65: 26 70 34 46 | F65: thomasolsen0901 | I65: No-Show | T65: Aben møder ikke op
B66: 14 | C66: Oskar | E66: 31 67 50 25 | F66: Oskaruldal | I66: No-Show | T66: Aben møder ikke op
B67: 15 | C67: Victor | E67: 53 37 73 60 | F67: victorvalbjorn | I67: Split-Pay | K67: 10500 | L67: 3000 | Q67: 6 | S67: Closed | T67: Snak d 30 og starter og betaler der (startet og betalt)
B68: 15 | C68: Tobias | E68: 29 40 65 03 | F68: Tobias.2750 | I68: No-Show | T68: Aben møder ikke op
B69: 15 | C69: Claus | E69: 50 55 23 81 | F69: Claus.pallesen | I69: No-Show | T69: Aben møder ikke op
B70: 15 | C70: Kasper | E70: 28 90 18 69 | F70: Kasper_vang_ | I70: Offer & Didn't Buy | N70: Money | O70: Penge | S70: Follow Up | T70: Han havde ikke økonomien til det
B71: 15 | C71: Patrick | E71: 21 85 46 10 | F71: patrickamtkjaer_ | I71: No-Show | T71: Adam møder ikke op
B72: 15 | C72: Søren | E72: 53 83 88 44 | F72: boisen000 | I72: Full-Pay | K72: 9000 | L72: 9000 | Q72: 6 | S72: Closed
B73: 16 | C73: THomas | E73: 30 43 09 92 | F73: Thom368q | I73: Full-Pay | K73: 9000 | L73: 9000 | Q73: 6 | S73: Closed
B74: 16 | C74: Nikolaj | E74: 21 13 36 59 | F74: Nikolajmollerup | I74: Offer & Didn't Buy | N74: Money | O74: Penge | S74: Follow Up | T74: Manden var ikke klar til at investere idet fordi han var bange for ikke at give den gas og spilde sine penge
B75: 16 | C75: Mikkel | E75: 41 42 24 07 | F75: Mikk964k | I75: Offer & Didn't Buy | N75: Think About It | O75: tænke over dert | S75: Follow Up | T75: Han ville mest af alt høre hvordan det foregik
B76: 17 | C76: David | E76: 25 12 43 28 | F76: davidstberg | I76: Offer & Didn't Buy | N76: Think About It | O76: tænke over det | S76: Follow Up | T76: Han ville mig et svar slut på ugen | V76: ut
B77: 17 | C77: Emil | E77: 29 91 43 00 | F77: emilstenlund_dk | I77: Offer & Didn't Buy | N77: Think About It | O77: Tænke over det og økonomien | S77: Follow Up | T77: Det er 2 gang jeg snakker med ham og han var alligevel ikke klar
B78: 18 | C78: Mikkel | E78: 21 69 35 99 | F78: mikkelhorslevv | I78: Offer & Didn't Buy | N78: Value | O78: han ville have en mental coach | S78: X | T78: Han ville have en mental coach og det er jeg ikke
B79: 18 | C79: Simon | E79: 20 61 04 58 | F79: S.andersen.tylle | I79: Cancelled | T79: han aflyser og skriver han ikke har penge og overskud til det
B80: 18 | C80: Kasper | E80: 60 86 46 69 | F80: Kasperasbo | I80: Offer & Didn't Buy | N80: Money | O80: Penge | S80: Follow Up | T80: Han var for nærig til at betale for det
B81: 18 | C81: Sune | E81: 61 78 97 87 | F81: sune.pedersen | I81: Offer & Didn't Buy | N81: Money | O81: Nærig | S81: Follow Up | T81: Han var super klar, men var for nærig til at betale for det og han ville gerne købe en kostplan, men det kunne være ligemeget
B82: 19 | C82: Christoffer | E82: 53 76 95 12 | F82: Christoffer.fk | I82: Offer & Didn't Buy | L82: 500 | S82: X | T82: starter d 30 og betaler der også (han hoppede fra)
B83: 19 | C83: Hjalte | E83: 21 16 12 08 | F83: h.28____ | I83: Bad Fit & No Offer | N83: Think About It | O83: dårligt lead | S83: X | T83: 16 år og var et helt andet sted i livet
B84: 19 | C84: David | E84: 52 39 88 05 | F84: klitgaard.david | I84: Offer & Didn't Buy | L84: 500 | S84: Follow Up | T84: starter d 30 og betaler der også (han hoppede fra)
B85: 19 | C85: Jonas | E85: 53 58 70 90 | F85: Jonashoppe13 | I85: Bad Fit & No Offer | N85: Money | O85: for ung | S85: X | T85: Han var kun 15 år gammel
B86: 20 | C86: Mikki | E86: 42 42 63 91 | F86: Mikkipetersen21 | I86: Offer & Didn't Buy | N86: Think About It | O86: tænke over det | S86: Hot Follow Up | T86: Jeg var tæt på at få ham på deposit, men så bakkede han ud lige før
B87: 20 | C87: Mathias | E87: 25 78 25 61 | F87: mathias1649 | I87: No-Show
B88: 20 | C88: Patrick | E88: 27 58 15 46 | F88: Patrickstaak | I88: Offer & Didn't Buy | N88: Fear | O88: Bange | S88: Hot Follow Up | T88: Manden var klar til at tabe sig og alt gav mening, men han var en pussy til ikke at komme igang
B89: 21 | C89: Andreas | E89: 61 77 29 63 | F89: Andreas_moellgaard | I89: Offer & Didn't Buy | N89: Money | O89: Penge | S89: Follow Up | T89: han var 17 og tjente ikke de vildeste penge, så det var økonomien
B90: 22 | C90: Andreas | E90: 30 13 47 20 | F90: Andreasvaldimarsson | I90: Offer & Didn't Buy | N90: Fear | O90: Bange | S90: X | T90: Han var super klar og skulle give den gas! Jeg trykkede lidt til ham til sidst og så skrev han at jeg var ubehøvlet og derfor ikke gad igang og det var fordi jeg havde en hård opjection handling
B91: 22 | C91: August | E91: 52 58 86 78 | F91: August.fbd | I91: Offer & Didn't Buy | N91: Money | O91: Penge | S91: Follow Up | T91: Super nice gut, men han kunne ikke sætte pengene til siden til forløbet og så ville han selv prøve at få sig selv på sporet
B92: 22 | C92: Marc | E92: 299 24 31 93 | F92: marciulaanngilaq | I92: Split-Pay | K92: 10500 | L92: 3000 | N92: Money | O92: Penge | S92: Closed | T92: Han ville gerne igang, men han havde ikke pengene til at betale på kaldet (betalt)
B93: 22 | C93: Mads | E93: 40 37 17 79 | F93: madsth27 | I93: Split-Pay | K93: 10500 | L93: 3000 | Q93: 6 | S93: Closed
B94: 22 | C94: Hamza | E94: 52 68 10 45 | F94: hamzalatouf | I94: No-Show
B95: 22 | C95: Oscar | E95: 24 75 00 07 | F95: oscar2608_ | I95: Offer & Didn't Buy | N95: Money | O95: penge | S95: Follow Up | T95: Super cool fyr, dog var han kun 17 og han havde ikke økonomien til det
B96: 22 | C96: Johan | E96: 28 29 51 52 | F96: johanweinr | I96: Offer & Didn't Buy | N96: Think About It | O96: tænke over det og pengene | S96: Hot Follow Up | T96: Han var også super nice og han ville også starte op og give den gas. Dog ville han lige tænke den ordenligt igennem før han tog en beslutning
B97: 23 | C97: David | E97: 20 47 40 42 | F97: david_christoffersen_ | I97: Full-Pay | K97: 6000 | L97: 6000 | Q97: 4 | S97: Closed
B98: 23 | C98: Oliver | E98: 28 96 38 98 | F98: detbarethomasen | I98: Offer & Didn't Buy | N98: Value | O98: Han havde ikke brug for hjælp | S98: X | T98: Bro var allerede flyvende så kunne faktisk ikke hjælpe ham
B99: 23 | C99: Rasmus | E99: 24 44 84 80 | F99: rasmus_arndal | I99: Offer & Didn't Buy | N99: Think About It | O99: tænke over det og pengene | S99: Follow Up | T99: Han ville ikke bruge pengene på det selvom han ville i bedre form
B100: 23 | C100: Simon | E100: 31 12 39 27 | F100: Shahnemann23 | I100: Offer & Didn't Buy | N100: Money | O100: Pengene | S100: Follow Up | T100: Han ville også rigtig gerne igang, men økonomien var ikke til det
B101: 24 | C101: Marcus | E101: 42 31 21 48 | F101: marcus_ostberg | I101: Offer & Didn't Buy | N101: Money | O101: Pengene | S101: Follow Up | T101: Han var 17 og tjente næsten ingen penge, så han havde heller ikke økonomien til det
...

Sheet Dec
A1: $ | B1: Rep: | C1: Name | E1: Anton KPI's | H1: Outcome | K1: KPIs% | N1: Show Rate | Q1: Objections | T1: Source
E2: Rev per call | F2: =C3/C6 -> 2419.3548 | H2: Full-Pay: | I2: =IFERROR(COUNTIFS(I14:I312, "Full-Pay"),"") -> 3 | K2: Conversion Rate: | L2: =iferror(L10/L8,"") -> 0.29032258 | N2: Rescheduling Rate: | O2: =iferror(I8/L6,"") -> 0 | Q2: Think About It | R2: =IFERROR(COUNTIFS(N36:N311, "think about it"),"") -> 0 | T2: Setter | U2: =IFERROR(COUNTIF(H36:H311,"setter"),"") -> 0
B3: Revenue | C3: =IFERROR(SUM(K14:K308),"") -> 75000 | E3: Cash per call | F3: =C4/C6 -> 1258.0645 | H3: Split-Pay: | I3: =IFERROR(COUNTIFS(I14:I312, "Split-Pay"),"") -> 6 | K3: Offer To Close Rate: | L3: =IFERROR(L10/L9,"") -> 0.29032258 | N3: Cancellation Rate: | O3: =iferror(I9/L6,"") -> 0 | Q3: Money | R3: =IFERROR(COUNTIFS(N36:N311, "money"),"") -> 9 | T3: IG | U3: =IFERROR(COUNTIF(H36:H311,"IG"),"") -> 0
B4: Cash | C4: =IFERROR(SUM(L14:L309),"") -> 39000 | E4: Cash upfront % | F4: =C4/C3*100 -> 52 | H4: Deposits: | I4: =IFERROR(COUNTIFS(I14:I312, "Deposit"),"") -> 7 | K4: Call To Offer Rate: | L4: =IFERROR(L9/L8,"") -> 1 | N4: No-Shows Rate: | O4: =iferror(I10/L6,"") -> 0.18421053 | Q4: Time | R4: =IFERROR(COUNTIFS(N36:N311, "time"),"") -> 0 | T4: YouTube | U4: =IFERROR(COUNTIF(H36:H311,"youtube"),"") -> 0
E5: PIF % | F5: =I2/C7*100 -> 33.333333 | H5: Offer & Didn't Buy: | I5: =IFERROR(COUNTIFS(I14:I312, "Offer & Didn't Buy"),"") -> 15 | K5: Drag Over Rate: | L5: =IFERROR(I7/(C6+I7+I8),"") -> 0 | N5: Drag Over Rate: | O5: =iferror(I7/L6,"") -> 0 | Q5: Partner | R5: =IFERROR(COUNTIFS(N36:N311, "partner"),"") -> 1 | T5: Email | U5: =IFERROR(COUNTIF(H36:H311,"email"),"") -> 0
B6: Total Calls : | C6: =IFERROR(SUM(I2:I6),"") -> 31 | E6: Average Binding | F6: =AVERAGE(Q14:Q105) -> 5.2222222 | H6: Bad Fit & No Offer: | I6: =IFERROR(COUNTIFS(I14:I312, "Bad Fit & No Offer"),"") -> 0 | K6: Bookings: | L6: =IFERROR(SUM(I2:I10),"") -> 38 | N6: Show-Up Rate: | O6: =iferror(L7/L6,"") -> 0.81578947 | Q6: Fear | R6: =IFERROR(COUNTIFS(N36:N311, "fear"),"") -> 2 | T6: Facebook | U6: =IFERROR(COUNTIF(H36:H311,"facebook"),"") -> 0
B7: Total Won : | C7: =IFERROR(I2+I3,"") -> 9 | E7: Average deal | F7: =C3/C7 -> 8333.3333 | H7: Drag Over & Show: | I7: =IFERROR(COUNTIFS(I14:I312, "Drag Over & Show"),"") -> 0 | K7: Shows: | L7: =IFERROR(SUM(I2:I7),"") -> 31 | N7: Conducted Rate: | O7: =IFERROR(L8/L6,"") -> 0.81578947 | Q7: Value | R7: =IFERROR(COUNTIFS(N37:N312, "value"),"") -> 0 | T7: Facebook Ads | U7: =IFERROR(COUNTIF(H36:H311,"facebook ads"),"") -> 0
B8: Total Lost : | C8: =COUNTIF(I14:I311,"offer & didn't buy")+COUNTIF(I36:I311,"deposit")+COUNTIF(I36:I311,"bad fit & no offer") -> 20 | E8: Average cash | F8: =C4/C7 -> 4333.3333 | H8: Rescheduled: | I8: =IFERROR(COUNTIFS(I14:I312, "Rescheduled"),"") -> 0 | K8: Calls: | L8: =IFERROR(SUM(I2:I6),"") -> 31 | T8: LinkedIn | U8: =IFERROR(COUNTIF(H36:H311,T8),"") -> 0
B9: Closing % : | C9: =iferror(SUM(C7/C6),"") -> 0.29032258 | E9: Håndværker % | F9: =IFERROR(COUNTIFS(H14:H312, "Håndværker"),"")/C6 -> 0.67741935 | H9: Cancelled: | I9: =IFERROR(COUNTIFS(I14:I312, "Cancelled"),"") -> 0 | K9: Offers: | L9: =IFERROR(sum(I2:I5),"") -> 31
E10: Ikke Håndværker % | F10: =IFERROR(COUNTIFS(H14:H313, "Ikkehåndværker"),"")/C6 -> 0.38709677 | H10: No-Show: | I10: =IFERROR(COUNTIFS(I14:I312, "No-Show"),"") -> 7 | K10: Deals | L10: =I2+I3 -> 9
B12: Date | C12: Name | E12: Phone No. | F12: IG Navn | H12: Source | I12: Outcome | K12: Revenue | L12: Cash | N12: Objection | O12: Objection Notes | Q12: Length | R12: Recording Link | S12: Follow Up/Next Steps | T12: Call Summary
B13: 1 | C13: Bertram | E13: 30 27 51 55 | F13: Bertramrasmussen | H13: Håndværker | I13: Split-Pay | K13: 10500 | L13: 3000 | Q13: 6 | S13: Closed | T13: starter og betaler d 1 dec
B14: 2 | C14: Jonas | E14: 28 45 52 07 | F14: Jk_714kristensen | I14: No-Show
B15: 2 | C15: Frederik | E15: 30 96 24 83 | F15: Frederikaahauge | H15: Håndværker | I15: Split-Pay | K15: 6000 | L15: 3000 | Q15: 4 | S15: Closed
B16: 2 | C16: Oliver | E16: 60 12 69 88 | F16: Hjortholiversvane | H16: Ikkehåndværker | I16: Split-Pay | K16: 10500 | L16: 3000 | Q16: 6 | S16: Closed
B17: 2 | C17: Jakob | E17: 23 31 09 44 | F17: Jakobnorager | H17: Håndværker | I17: Offer & Didn't Buy | N17: Think About It | O17: Tænke over det | S17: Hot Follow Up | T17: Han var super varm, allerede haft en coach, han var klar til at betale pif, men han ville gerne betale med faktura og vidste ikke om jeg kunne, så vi aftalte et nyt tidspunkt og han mødte aldrig op
B18: 2 | C18: Mikkel | E18: 50 57 38 89 | F18: mikkel.la0 | H18: Ikkehåndværker | I18: Offer & Didn't Buy | N18: Think About It | O18: Tænke over det | S18: X | T18: han havde set min vsl og ville bare snakke med mig, så den lukkede jeg hurtigt, fordi han legit bare snakkede
B19: 2 | C19: Luckas | E19: 31 32 39 76 | F19: luckas.111 | H19: Håndværker | I19: Deposit | L19: 500 | S19: Deposit (Follow Up Set) | T19: Kald d 2 med betaling og onboarding
B20: 3 | C20: Mikkel | E20: 51 92 29 41 | F20: mikkel.boel_ | H20: Håndværker | I20: Offer & Didn't Buy | N20: Think About It | O20: Fikse betaling | S20: X | T20: Han skulle fikse betaling og så hørte jeg aldrig fra ham. han var sygt varm
B21: 3 | C21: Elias | E21: 61 37 79 13 | F21: elias_krogh_ | H21: Håndværker | I21: Split-Pay | K21: 7500 | L21: 2500 | Q21: 6 | S21: Closed
B22: 3 | C22: Mattis | E22: 28 19 99 91 | F22: mattis_kuhnau | H22: Håndværker | I22: Full-Pay | K22: 6000 | L22: 6000 | Q22: 4 | S22: Closed
B23: 5 | C23: Patrick | E23: 53 37 62 45 | F23: patrick_hstt | I23: No-Show
B24: 6 | C24: Malthe | E24: 21 46 31 34 | F24: Malthe_bistrup | H24: Ikkehåndværker | I24: Split-Pay | K24: 10500 | L24: 3000 | Q24: 6 | S24: Closed
B25: 7 | C25: Magnus | E25: 42 49 90 30 | F25: Illummagnus | H25: Håndværker | I25: Offer & Didn't Buy | N25: Value | O25: gik med en anden coach | S25: X | T25: Super cool fyr, men han valgte at gå med en anden coach
B26: 8 | C26: Phillip | E26: 61 31 99 07 | F26: Phillip_mortensen | I26: No-Show
B27: 8 | C27: Marcus | E27: 21 29 22 68 | F27: Sorensen_8722 | H27: Håndværker | I27: Offer & Didn't Buy | N27: Money | O27: Penge | S27: X | T27: Hans mor mente at han ikke havde pengene til det
B28: 9 | C28: Malthe | E28: 42 17 37 41 | F28: malthethiesen | H28: Håndværker | I28: Offer & Didn't Buy | N28: Think About It | O28: Hørte aldrig fra ham efter kaldet | S28: Follow Up | T28: Super fin gut, som gerne ville igang og var landmand, men han var lidt nærig og sagde han ville tænke over det og hørte aldrig fra ham igen
B29: 10 | C29: rasmus | E29: 28 55 30 25 | F29: Kjaer21 | I29: No-Show
B30: 10 | C30: Oliver | E30: 20 99 09 86 | F30: Oliver_soendergaard | H30: Ikkehåndværker | I30: Split-Pay | K30: 10500 | L30: 3000 | Q30: 6 | S30: Closed
B31: 11 | C31: Mikkel | E31: 71 77 94 37 | F31: Mikkelbasse_ | H31: Håndværker | I31: Offer & Didn't Buy | N31: Money | O31: Penge | S31: Follow Up | T31: Han ville gerne tænke over det, men ellers sød
B32: 13 | C32: Bertil | E32: 53 83 25 19 | F32: bertilmarcussen | H32: Ikkehåndværker | I32: Full-Pay | K32: 4500 | L32: 4500 | Q32: 3 | S32: Closed
B33: 15 | C33: Bertram | E33: 30 96 41 12 | F33: bertramwass | H33: Håndværker | I33: Deposit | L33: 500 | S33: Deposit (Follow Up Set) | T33: kald d 2 med betaling og onboarding
B34: 15 | C34: Kian | E34: 41 11 47 06 | F34: kianmakholm | H34: Håndværker | I34: Full-Pay | K34: 9000 | L34: 9000 | Q34: 6 | S34: Closed
B35: 17 | C35: Oscar | E35: 42 44 60 15 | F35: oscarhvarregaard | H35: Håndværker | I35: Offer & Didn't Buy | N35: Money | O35: Økonomi | S35: Follow Up | T35: Passsede ikke ind i hans økonomi
B36: 17 | C36: Mads | E36: 31 50 20 54 | F36: Mads_rodrigo | H36: Håndværker | I36: Offer & Didn't Buy | N36: Money | O36: Mange udgifter | S36: Follow Up | T36: Super flink gut og ville bare igang, men han havde alt for mange udgifter
B37: 17 | C37: Thomas | E37: 40 42 10 41 | F37: Lillegaardthomas | H37: Håndværker | I37: Offer & Didn't Buy | N37: Money | O37: Penge | S37: Hot Follow Up | T37: Han ville vende tilbage efter jul, men ellers super nice og var færdigudlært
B38: 18 | C38: Muhammed | E38: 50 51 32 02 | F38: onlymini2611 | H38: Ikkehåndværker | I38: Offer & Didn't Buy | N38: Money | O38: Penge | S38: X | T38: Han gik på gym og havde ingen penge på kontoen. bedte ham skrive når han havde fundet et arbejde
B39: 18 | C39: Noah | E39: 31 32 70 05 | F39: lundnoah | H39: Ikkehåndværker | I39: Deposit | N39: Money | O39: Penge lige nu | S39: Deposit (Follow Up Set) | T39: Onboarding kald d 2 samt betaling
B40: 18 | C40: Mikkel | E40: 22 57 39 50 | F40: mikkeltyrrell_ | H40: Håndværker | I40: No-Show
B41: 19 | C41: Jens | E41: 42 39 64 37 | F41: jens657a | H41: Håndværker | I41: No-Show
B42: 20 | C42: Anthony | E42: 42 30 04 23 | F42: antonio_nielsson.69 | H42: Ikkehåndværker | I42: Deposit | N42: Money | O42: ingen penge nu | S42: Deposit (Follow Up Set) | T42: Starter og betaler d 2 jan
B43: 21 | C43: Albert | E43: 93 60 28 18 | F43: Albertgerguri | H43: Ikkehåndværker | I43: Split-Pay | K43: 10500 | L43: 3000 | Q43: 6 | S43: Closed
B44: 22 | C44: Mads | E44: 91 55 76 55 | F44: mads_freundlich | H44: Ikkehåndværker | I44: Offer & Didn't Buy | N44: Partner | O44: Forældre | S44: Follow Up | T44: Han var sygt klar, men hans forældre gad ikke støtte ham i det, så han droppede det
B45: 23 | C45: Sebastian | E45: 22 79 13 12 | F45: Sebastianvielanderiksen | H45: Håndværker | I45: Deposit | L45: 500 | N45: Money | S45: Deposit (Follow Up Set) | T45: starter og betaler d 2 jan
B46: 23 | C46: William | E46: 52 55 50 60 | F46: Trolle176 | H46: Håndværker | I46: Deposit | L46: 500 | N46: Money | S46: Deposit (Follow Up Set) | T46: starter og betaler d 2 jan
B47: 27 | C47: Matias | E47: 61 76 96 66 | F47: matias_andersn | H47: Håndværker | I47: Deposit | N47: Money | S47: Deposit (Follow Up Set) | T47: starter og betaler forhåbenligt d 2 jan
B48: 27 | C48: Ethan | E48: 22 32 67 97 | F48: ethanjessenn | H48: Ikkehåndværker | I48: Offer & Didn't Buy | N48: Fear | O48: frygt | S48: Hot Follow Up | T48: Han var sygt varm og ville bare igang, men så snart han hørte prisen, så hoppede han af
B49: 27 | C49: Nikolaj | E49: 42 27 60 20 | F49: nikolajkm | H49: Håndværker | I49: Offer & Didn't Buy | N49: Fear | O49: bange | S49: X | T49: Manden var totalt varm og havde penge. da han hørte prisen var han også klar, men da vi kom til betalingen ville han gerne tænke over det og så blokerede han mig
B50: 28 | C50: Jeppe | E50: 23 23 25 15 | F50: jeppebauer | I50: No-Show
B51: 28 | C51: Sune | E51: 21 81 44 22 | F51: sunekildedal | H51: Ikkehåndværker | I51: Offer & Didn't Buy | N51: Money | S51: Hot Follow Up | T51: sygt varm og havde fuldtidsarbejde, men gad ikke starte op fordi han snart skulle flytte ud selvom det faktisk var ham der skrev coach til mig
V77: ut

Sheet Jan 26
A1: $ | B1: Rep: | C1: Name | E1: Anton KPI's | H1: Outcome | K1: KPIs% | N1: Show Rate | Q1: Objections | T1: Source
E2: Rev per call | F2: =C3/C6 -> 4136.6935 | H2: Full-Pay: | I2: =IFERROR(COUNTIFS(I13:I311, "Full-Pay"),"") -> 20 | K2: Conversion Rate: | L2: =iferror(L10/L8,"") -> 0.47580645 | N2: Rescheduling Rate: | O2: =iferror(I8/L6,"") -> 0.014705882 | Q2: Think About It | R2: =IFERROR(COUNTIFS(N35:N310, "think about it"),"") -> 15 | T2: Setter | U2: =IFERROR(COUNTIF(H35:H310,"setter"),"") -> 0
B3: Revenue | C3: =IFERROR(SUM(K13:K307),"") -> 512950 | E3: Cash per call | F3: =C4/C6 -> 2120.3629 | H3: Split-Pay: | I3: =IFERROR(COUNTIFS(I13:I311, "Split-Pay"),"") -> 39 | K3: Offer To Close Rate: | L3: =IFERROR(L10/L9,"") -> 0.49166667 | N3: Cancellation Rate: | O3: =iferror(I9/L6,"") -> 0 | Q3: Money | R3: =IFERROR(COUNTIFS(N35:N310, "money"),"") -> 21 | T3: IG | U3: =IFERROR(COUNTIF(H35:H310,"IG"),"") -> 0
B4: Cash | C4: =IFERROR(SUM(L13:L308),"") -> 262925 | E4: Cash upfront % | F4: =C4/C3*100 -> 51.257433 | H4: Deposits: | I4: =IFERROR(COUNTIFS(I13:I311, "Deposit"),"") -> 9 | K4: Call To Offer Rate: | L4: =IFERROR(L9/L8,"") -> 0.96774194 | N4: No-Shows Rate: | O4: =iferror(I10/L6,"") -> 0.073529412 | Q4: Time | R4: =IFERROR(COUNTIFS(N35:N310, "time"),"") -> 1 | T4: YouTube | U4: =IFERROR(COUNTIF(H35:H310,"youtube"),"") -> 0
E5: PIF % | F5: =I2/C7*100 -> 33.898305 | H5: Offer & Didn't Buy: | I5: =IFERROR(COUNTIFS(I13:I311, "Offer & Didn't Buy"),"") -> 52 | K5: Drag Over Rate: | L5: =IFERROR(I7/(C6+I7+I8),"") -> 0 | N5: Drag Over Rate: | O5: =iferror(I7/L6,"") -> 0 | Q5: Partner | R5: =IFERROR(COUNTIFS(N35:N310, "partner"),"") -> 1 | T5: Email | U5: =IFERROR(COUNTIF(H35:H310,"email"),"") -> 0
B6: Total Calls : | C6: =IFERROR(SUM(I2:I6),"") -> 124 | E6: Average Binding | F6: =AVERAGE(Q13:Q104) -> 5.2380952 | H6: Bad Fit & No Offer: | I6: =IFERROR(COUNTIFS(I13:I311, "Bad Fit & No Offer"),"") -> 4 | K6: Bookings: | L6: =IFERROR(SUM(I2:I10),"") -> 136 | N6: Show-Up Rate: | O6: =iferror(L7/L6,"") -> 0.91176471 | Q6: Fear | R6: =IFERROR(COUNTIFS(N35:N310, "fear"),"") -> 4 | T6: Facebook | U6: =IFERROR(COUNTIF(H35:H310,"facebook"),"") -> 0
B7: Total Won : | C7: =IFERROR(I2+I3,"") -> 59 | E7: Average deal | F7: =C3/C7 -> 8694.0678 | H7: Drag Over & Show: | I7: =IFERROR(COUNTIFS(I13:I311, "Drag Over & Show"),"") -> 0 | K7: Shows: | L7: =IFERROR(SUM(I2:I7),"") -> 124 | N7: Conducted Rate: | O7: =IFERROR(L8/L6,"") -> 0.91176471 | Q7: Value | R7: =IFERROR(COUNTIFS(N36:N311, "value"),"") -> 0 | T7: Facebook Ads | U7: =IFERROR(COUNTIF(H35:H310,"facebook ads"),"") -> 0
B8: Total Lost : | C8: =COUNTIF(I13:I310,"offer & didn't buy")+COUNTIF(I35:I310,"deposit")+COUNTIF(I35:I310,"bad fit & no offer") -> 64 | E8: Average cash | F8: =C4/C7 -> 4456.3559 | H8: Rescheduled: | I8: =IFERROR(COUNTIFS(I13:I311, "Rescheduled"),"") -> 2 | K8: Calls: | L8: =IFERROR(SUM(I2:I6),"") -> 124 | T8: LinkedIn | U8: =IFERROR(COUNTIF(H35:H310,T8),"") -> 0
B9: Closing % : | C9: =iferror(SUM(C7/C6),"") -> 0.47580645 | E9: Håndværker % | F9: =IFERROR(COUNTIFS(H13:H311, "Håndværker"),"")/C6 -> 0.62903226 | H9: Cancelled: | I9: =IFERROR(COUNTIFS(I13:I311, "Cancelled"),"") -> 0 | K9: Offers: | L9: =IFERROR(sum(I2:I5),"") -> 120 | N9: 5500 | O9: =N9*C6 -> 682000
E10: Ikke Håndværker % | F10: =IFERROR(COUNTIFS(H13:H312, "Ikkehåndværker"),"")/C6 -> 0.38709677 | H10: No-Show: | I10: =IFERROR(COUNTIFS(I13:I311, "No-Show"),"") -> 10 | K10: Deals | L10: =I2+I3 -> 59
B12: Date | C12: Name | E12: Phone No. | F12: IG Navn | H12: Source | I12: Outcome | K12: Revenue | L12: Cash | N12: Objection | O12: Objection Notes | Q12: Length | R12: Recording Link | S12: Follow Up/Next Steps | T12: Call Summary
B13: 46023 | C13: Tobias | E13: 42 47 60 68 | F13: Tobias_risvig_ | H13: Håndværker | I13: Split-Pay | K13: 10500 | L13: 3000 | Q13: 6 | S13: Closed
B14: 46023 | C14: Oliver | E14: 31 24 54 21 | F14: Oliver.ulvsgaard | H14: Ikkehåndværker | I14: Split-Pay | K14: 10500 | L14: 3000 | Q14: 6 | S14: Closed
B15: 46023 | C15: Asbjørn | E15: 26 43 86 96 | F15: Asbjørnreventlow | H15: Ikkehåndværker | I15: Split-Pay | K15: 10500 | L15: 3000 | Q15: 6 | S15: Closed
B16: 46054 | C16: Morten | E16: 41 82 10 50 | F16: m.post_205 | H16: Håndværker | I16: Full-Pay | K16: 9000 | L16: 9000 | Q16: 6 | S16: Closed
B17: 46054 | C17: Albion | E17: 23728897 | F17: Albion Peci | H17: Ikkehåndværker | I17: Split-Pay | K17: 8250 | L17: 2250 | Q17: 6 | S17: Closed | T17: Været hos mig i 2024
B18: 46054 | C18: Frederik | E18: 60561605 | F18: frederikkoej | H18: Ikkehåndværker | I18: Split-Pay | K18: 6000 | L18: 3000 | Q18: 3 | S18: Closed
B19: 46054 | C19: Luckas | E19: 31323976 | F19: Luckas.111 | H19: Håndværker | I19: Full-Pay | K19: 4500 | L19: 4500 | P19: 3 | Q19: 3 | S19: Closed
B20: 46054 | C20: Noah | E20: 31327005 | F20: Lundnoah | H20: Ikkehåndværker | I20: Split-Pay | K20: 10500 | L20: 3000 | Q20: 6 | S20: Closed
B21: 46054 | C21: Kalle | E21: 81612168 | F21: Kalletimm07 | I21: No-Show | S21: X
B22: 46054 | C22: Antonio | E22: 42300423 | F22: antonio_nielsson.69 | H22: Ikkehåndværker | I22: Split-Pay | K22: 10500 | L22: 3000 | Q22: 6 | S22: Closed
B23: 46054 | C23: Silas | F23: itsyourboysilas | I23: No-Show | S23: X | T23: Blokeret os
B24: 46054 | C24: Sebastian | E24: 22791312 | F24: sebastianvielanderiksen | H24: Håndværker | I24: Split-Pay | K24: 10500 | L24: 3000 | Q24: 6 | S24: Closed
B25: 46054 | C25: Alush | E25: 42 36 09 77 | F25: Alushoow | H25: Ikkehåndværker | I25: Bad Fit & No Offer
B26: 46054 | C26: Kevin | E26: 42 77 53 27 | F26: S_k3vin | H26: Ikkehåndværker | I26: Split-Pay | K26: 10500 | L26: 3000 | Q26: 6 | S26: Closed
B27: 46054 | C27: Abden | E27: 28 96 70 25 | F27: Ak480_ | H27: Ikkehåndværker | I27: Offer & Didn't Buy | T27: Blokeret os
B28: 46082 | C28: Victor | E28: 25 50 00 66 | F28: victor.kamp | H28: Ikkehåndværker | I28: Split-Pay | K28: 10500 | L28: 3000 | Q28: 6 | S28: Closed
