Workbook

Sheet Ads Snapshot
A1: ADS PERFORMANCE
A2: VARIABLE | B2: VALUE
A3: NEW FOLLOWERS | B3: ='Jan ''25'!C33+'Feb ''25'!C30+'Mar ''25'!C33+#REF!+'May ''25'!C33+'June ''25'!C32+'July ''25'!C33+'Aug ''25'!C33+'Sep ''25'!C32+'Oct ''25'!C33+'Nov ''25'!C32+'Dec ''25'!C33 -> #REF!
A4: AD SPEND | B4: ='Jan ''25'!D33+'Feb ''25'!D30+'Mar ''25'!D33+#REF!+'May ''25'!D33+'June ''25'!D32+'July ''25'!D33+'Aug ''25'!D33+'Sep ''25'!D32+'Oct ''25'!D33+'Nov ''25'!D32+'Dec ''25'!D33 -> #REF!
A5: COST PER FOLLOWER | B5: =B4/B3 -> #REF!
A6: CALLS BOOKED | B6: ='Jan ''25'!F33+'Feb ''25'!F30+'Mar ''25'!G33+#REF!+'May ''25'!F33+'June ''25'!F32+'July ''25'!F33+'Aug ''25'!F33+'Sep ''25'!F32+'Oct ''25'!F33+'Nov ''25'!F32+'Dec ''25'!F33 -> #REF!
A7: COST PER CALL | B7: =B4/B6 -> #REF!
A8: CASH COLLECTED | B8: ='Jan ''25'!B36+'Feb ''25'!B33+'Mar ''25'!B36+'Apr ''25'!B34+'May ''25'!B36+'June ''25'!B35+'July ''25'!B36+'Aug ''25'!B36+'Sep ''25'!B35+'Oct ''25'!B36+'Nov ''25'!B35+'Dec ''25'!B36 -> #REF!
A9: ROAS (CASH) | B9: =B8/B4 -> #REF!
A10: REVENUE | B10: ='Jan ''25'!B38+'Feb ''25'!B35+'Mar ''25'!B38+'Apr ''25'!B36+'May ''25'!B38+'June ''25'!B37+'July ''25'!B38+'Aug ''25'!B38+'Sep ''25'!B37+'Oct ''25'!B38+'Nov ''25'!B37+'Dec ''25'!B38 -> #REF!
A11: ROI (REVENUE) | B11: =B10/B4 -> #REF!
A13: CLICK FILE -> MAKE A COPY to make your own copy that you can edit.
A15: HOW TO USE THIS TRACKING SHEET
A16: Note: The "Sales Calls" tab is separate and not connected to any of the other sheets. It's simply there to help you keep track of your calls, sales, payment plans, etc.
A17: The numbers that affect the table above come from the monthly tabs, so make sure to fill in both the sales calls tracking sheet and the ad spend tracker too.
A18: The columns in the monthly ad tracking tabs that are greyed out are automatically calculated, do NOT input anything there. Only input new stats in the white columns.
A19: For the Sales Calls tracking sheet, you'll have to adjust the "No shows" formula to keep it up to date.

Sheet November
A1: Day | B1: AD Follows | C1: New AD Follows | D1: Total Spend | E1: Daily Spend | F1: Cost/Lead | G1: Calls Booked | H1: Cash Collected | I1: Revenue | J1: Cost per Call | K1: AD 1 | L1: Follows | M1: New AD Follows | N1: Total Spend | O1: Daily Spend | P1: Cost/Lead | Q1: AD 2 | R1: AD Follows | S1: New AD Follows | T1: Total Spend | U1: Daily Spend | V1: Cost/Lead | W1: AD 3 | X1: AD Follows | Y1: New AD Follows | Z1: Total Spend | AA1: Daily Spend | AB1: Cost/Lead | AC1: AD 4 | AD1: AD Follows | AE1: New AD Follows | AF1: Total Spend | AG1: Daily Spend | AH1: Cost/Lead | AI1: AD 5 | AJ1: AD Follows | AK1: New AD Follows | AL1: Total Spend | AM1: Daily Spend | AN1: Cost/Lead | AO1: AD 6 | AP1: AD Follows | AQ1: New AD Follows | AR1: Total Spend | AS1: Daily Spend | AT1: Cost/Lead | AU1: AD 7 | AV1: AD Follows | AW1: New AD Follows | AX1: Total Spend | AY1: Daily Spend | AZ1: Cost/Lead | BA1: AD 8 | BB1: AD Follows | BC1: New AD Follows | BD1: Total Spend | BE1: Daily Spend | BF1: Cost/Lead
A2: 45231 | B2: =SUM(L2+R2+X2+AD2+AJ2) -> 0 | C2: 0 | D2: =SUM(N2+T2+Z2+AF2+AL2) -> 0 | E2: =D2 -> 0 | F2: =D2/C2 -> #DIV/0! | J2: =IF(G2=0, 0, (E2/G2)) -> 0 | M2: 0 | O2: =N2 | P2: =N2/M2 -> #DIV/0! | S2: 0 | U2: =T2 | V2: =T2/S2 -> #DIV/0! | Y2: 0 | AA2: =Z2 | AB2: =Z2/Y2 -> #DIV/0! | AE2: 0 | AG2: =AF2 | AH2: =AF2/AE2 -> #DIV/0! | AK2: 0 | AM2: =AL2 | AN2: =AL2/AK2 -> #DIV/0! | AQ2: 0 | AS2: =AR2 | AT2: =AR2/AQ2 -> #DIV/0! | AW2: 0 | AY2: =AX2 | AZ2: =AX2/AW2 -> #DIV/0! | BC2: 0 | BE2: =BD2 | BF2: =BD2/BC2 -> #DIV/0!
A3: 45232 | B3: =SUM(L3+R3+X3+AD3+AJ3) -> 0 | C3: =IF((B3>0),(B3-B2),0) -> 0 | D3: =SUM(N3+T3+Z3+AF3+AL3) -> 0 | E3: =IF(OR(D3="", D3<D2), 0, D3-D2) -> 0 | F3: =IF(C3=0, 0, (D3-D2)/C3) -> 0 | J3: =IF(G3=0, 0, (E3)/G3) -> 0 | M3: =IF((L3>0),(L3-L2),0) -> 0 | O3: =IF(OR(N3="", N3<N2), 0, N3-N2) -> 0 | P3: =IF(M3=0, 0, (N3-N2)/M3) -> 0 | S3: =IF((R3>0),(R3-R2),0) -> 0 | U3: =IF(OR(T3="", T3<T2), 0, T3-T2) -> 0 | V3: =IF(S3=0, 0, (T3-T2)/S3) -> 0 | Y3: =IF((X3>0),(X3-X2),0) -> 0 | AA3: =IF(OR(Z3="", Z3<Z2), 0, Z3-Z2) -> 0 | AB3: =IF(Y3=0, 0, (Z3-Z2)/Y3) -> 0 | AE3: =IF((AD3>0),(AD3-AD2),0) -> 0 | AG3: =IF(OR(AF3="", AF3<AF2), 0, AF3-AF2) -> 0 | AH3: =IF(AE3=0, 0, (AF3-AF2)/AE3) -> 0 | AK3: =IF((AJ3>0),(AJ3-AJ2),0) -> 0 | AM3: =IF(OR(AL3="", AL3<AL2), 0, AL3-AL2) -> 0 | AN3: =IF(AK3=0, 0, (AL3-AL2)/AK3) -> 0 | AQ3: =IF((AP3>0),(AP3-AP2),0) -> 0 | AS3: =IF(OR(AR3="", AR3<AR2), 0, AR3-AR2) -> 0 | AT3: =IF(AQ3=0, 0, (AR3-AR2)/AQ3) -> 0 | AW3: =IF((AV3>0),(AV3-AV2),0) -> 0 | AY3: =IF(OR(AX3="", AX3<AX2), 0, AX3-AX2) -> 0 | AZ3: =IF(AW3=0, 0, (AX3-AX2)/AW3) -> 0 | BC3: =IF((BB3>0),(BB3-BB2),0) -> 0 | BE3: =IF(OR(BD3="", BD3<BD2), 0, BD3-BD2) -> 0 | BF3: =IF(BC3=0, 0, (BD3-BD2)/BC3) -> 0
A4: 45233 | B4: =SUM(L4+R4+X4+AD4+AJ4) -> 0 | C4: =IF((B4>0),(B4-B3),0) -> 0 | D4: =SUM(N4+T4+Z4+AF4+AL4) -> 0 | E4: =IF(OR(D4="", D4<D3), 0, D4-D3) -> 0 | F4: =IF(C4=0, 0, (D4-D3)/C4) -> 0 | J4: =IF(G4=0, 0, (E4)/G4) -> 0 | M4: =IF((L4>0),(L4-L3),0) -> 0 | O4: =IF(OR(N4="", N4<N3), 0, N4-N3) -> 0 | P4: =IF(M4=0, 0, (N4-N3)/M4) -> 0 | S4: =IF((R4>0),(R4-R3),0) -> 0 | U4: =IF(OR(T4="", T4<T3), 0, T4-T3) -> 0 | V4: =IF(S4=0, 0, (T4-T3)/S4) -> 0 | Y4: =IF((X4>0),(X4-X3),0) -> 0 | AA4: =IF(OR(Z4="", Z4<Z3), 0, Z4-Z3) -> 0 | AB4: =IF(Y4=0, 0, (Z4-Z3)/Y4) -> 0 | AE4: =IF((AD4>0),(AD4-AD3),0) -> 0 | AG4: =IF(OR(AF4="", AF4<AF3), 0, AF4-AF3) -> 0 | AH4: =IF(AE4=0, 0, (AF4-AF3)/AE4) -> 0 | AK4: =IF((AJ4>0),(AJ4-AJ3),0) -> 0 | AM4: =IF(OR(AL4="", AL4<AL3), 0, AL4-AL3) -> 0 | AN4: =IF(AK4=0, 0, (AL4-AL3)/AK4) -> 0 | AQ4: =IF((AP4>0),(AP4-AP3),0) -> 0 | AS4: =IF(OR(AR4="", AR4<AR3), 0, AR4-AR3) -> 0 | AT4: =IF(AQ4=0, 0, (AR4-AR3)/AQ4) -> 0 | AW4: =IF((AV4>0),(AV4-AV3),0) -> 0 | AY4: =IF(OR(AX4="", AX4<AX3), 0, AX4-AX3) -> 0 | AZ4: =IF(AW4=0, 0, (AX4-AX3)/AW4) -> 0 | BC4: =IF((BB4>0),(BB4-BB3),0) -> 0 | BE4: =IF(OR(BD4="", BD4<BD3), 0, BD4-BD3) -> 0 | BF4: =IF(BC4=0, 0, (BD4-BD3)/BC4) -> 0
A5: 45234 | B5: =SUM(L5+R5+X5+AD5+AJ5) -> 0 | C5: =IF((B5>0),(B5-B4),0) -> 0 | D5: =SUM(N5+T5+Z5+AF5+AL5) -> 0 | E5: =IF(OR(D5="", D5<D4), 0, D5-D4) -> 0 | F5: =IF(C5=0, 0, (D5-D4)/C5) -> 0 | J5: =IF(G5=0, 0, (E5)/G5) -> 0 | M5: =IF((L5>0),(L5-L4),0) -> 0 | O5: =IF(OR(N5="", N5<N4), 0, N5-N4) -> 0 | P5: =IF(M5=0, 0, (N5-N4)/M5) -> 0 | S5: =IF((R5>0),(R5-R4),0) -> 0 | U5: =IF(OR(T5="", T5<T4), 0, T5-T4) -> 0 | V5: =IF(S5=0, 0, (T5-T4)/S5) -> 0 | Y5: =IF((X5>0),(X5-X4),0) -> 0 | AA5: =IF(OR(Z5="", Z5<Z4), 0, Z5-Z4) -> 0 | AB5: =IF(Y5=0, 0, (Z5-Z4)/Y5) -> 0 | AE5: =IF((AD5>0),(AD5-AD4),0) -> 0 | AG5: =IF(OR(AF5="", AF5<AF4), 0, AF5-AF4) -> 0 | AH5: =IF(AE5=0, 0, (AF5-AF4)/AE5) -> 0 | AK5: =IF((AJ5>0),(AJ5-AJ4),0) -> 0 | AM5: =IF(OR(AL5="", AL5<AL4), 0, AL5-AL4) -> 0 | AN5: =IF(AK5=0, 0, (AL5-AL4)/AK5) -> 0 | AQ5: =IF((AP5>0),(AP5-AP4),0) -> 0 | AS5: =IF(OR(AR5="", AR5<AR4), 0, AR5-AR4) -> 0 | AT5: =IF(AQ5=0, 0, (AR5-AR4)/AQ5) -> 0 | AW5: =IF((AV5>0),(AV5-AV4),0) -> 0 | AY5: =IF(OR(AX5="", AX5<AX4), 0, AX5-AX4) -> 0 | AZ5: =IF(AW5=0, 0, (AX5-AX4)/AW5) -> 0 | BC5: =IF((BB5>0),(BB5-BB4),0) -> 0 | BE5: =IF(OR(BD5="", BD5<BD4), 0, BD5-BD4) -> 0 | BF5: =IF(BC5=0, 0, (BD5-BD4)/BC5) -> 0
A6: 45235 | B6: =SUM(L6+R6+X6+AD6+AJ6) -> 0 | C6: =IF((B6>0),(B6-B5),0) -> 0 | D6: =SUM(N6+T6+Z6+AF6+AL6) -> 0 | E6: =IF(OR(D6="", D6<D5), 0, D6-D5) -> 0 | F6: =IF(C6=0, 0, (D6-D5)/C6) -> 0 | J6: =IF(G6=0, 0, (E6)/G6) -> 0 | M6: =IF((L6>0),(L6-L5),0) -> 0 | O6: =IF(OR(N6="", N6<N5), 0, N6-N5) -> 0 | P6: =IF(M6=0, 0, (N6-N5)/M6) -> 0 | S6: =IF((R6>0),(R6-R5),0) -> 0 | U6: =IF(OR(T6="", T6<T5), 0, T6-T5) -> 0 | V6: =IF(S6=0, 0, (T6-T5)/S6) -> 0 | Y6: =IF((X6>0),(X6-X5),0) -> 0 | AA6: =IF(OR(Z6="", Z6<Z5), 0, Z6-Z5) -> 0 | AB6: =IF(Y6=0, 0, (Z6-Z5)/Y6) -> 0 | AE6: =IF((AD6>0),(AD6-AD5),0) -> 0 | AG6: =IF(OR(AF6="", AF6<AF5), 0, AF6-AF5) -> 0 | AH6: =IF(AE6=0, 0, (AF6-AF5)/AE6) -> 0 | AK6: =IF((AJ6>0),(AJ6-AJ5),0) -> 0 | AM6: =IF(OR(AL6="", AL6<AL5), 0, AL6-AL5) -> 0 | AN6: =IF(AK6=0, 0, (AL6-AL5)/AK6) -> 0 | AQ6: =IF((AP6>0),(AP6-AP5),0) -> 0 | AS6: =IF(OR(AR6="", AR6<AR5), 0, AR6-AR5) -> 0 | AT6: =IF(AQ6=0, 0, (AR6-AR5)/AQ6) -> 0 | AW6: =IF((AV6>0),(AV6-AV5),0) -> 0 | AY6: =IF(OR(AX6="", AX6<AX5), 0, AX6-AX5) -> 0 | AZ6: =IF(AW6=0, 0, (AX6-AX5)/AW6) -> 0 | BC6: =IF((BB6>0),(BB6-BB5),0) -> 0 | BE6: =IF(OR(BD6="", BD6<BD5), 0, BD6-BD5) -> 0 | BF6: =IF(BC6=0, 0, (BD6-BD5)/BC6) -> 0
A7: 45236 | B7: =SUM(L7+R7+X7+AD7+AJ7) -> 0 | C7: =IF((B7>0),(B7-B6),0) -> 0 | D7: =SUM(N7+T7+Z7+AF7+AL7) -> 0 | E7: =IF(OR(D7="", D7<D6), 0, D7-D6) -> 0 | F7: =IF(C7=0, 0, (D7-D6)/C7) -> 0 | J7: =IF(G7=0, 0, (E7)/G7) -> 0 | M7: =IF((L7>0),(L7-L6),0) -> 0 | O7: =IF(OR(N7="", N7<N6), 0, N7-N6) -> 0 | P7: =IF(M7=0, 0, (N7-N6)/M7) -> 0 | S7: =IF((R7>0),(R7-R6),0) -> 0 | U7: =IF(OR(T7="", T7<T6), 0, T7-T6) -> 0 | V7: =IF(S7=0, 0, (T7-T6)/S7) -> 0 | Y7: =IF((X7>0),(X7-X6),0) -> 0 | AA7: =IF(OR(Z7="", Z7<Z6), 0, Z7-Z6) -> 0 | AB7: =IF(Y7=0, 0, (Z7-Z6)/Y7) -> 0 | AE7: =IF((AD7>0),(AD7-AD6),0) -> 0 | AG7: =IF(OR(AF7="", AF7<AF6), 0, AF7-AF6) -> 0 | AH7: =IF(AE7=0, 0, (AF7-AF6)/AE7) -> 0 | AK7: =IF((AJ7>0),(AJ7-AJ6),0) -> 0 | AM7: =IF(OR(AL7="", AL7<AL6), 0, AL7-AL6) -> 0 | AN7: =IF(AK7=0, 0, (AL7-AL6)/AK7) -> 0 | AQ7: =IF((AP7>0),(AP7-AP6),0) -> 0 | AS7: =IF(OR(AR7="", AR7<AR6), 0, AR7-AR6) -> 0 | AT7: =IF(AQ7=0, 0, (AR7-AR6)/AQ7) -> 0 | AW7: =IF((AV7>0),(AV7-AV6),0) -> 0 | AY7: =IF(OR(AX7="", AX7<AX6), 0, AX7-AX6) -> 0 | AZ7: =IF(AW7=0, 0, (AX7-AX6)/AW7) -> 0 | BC7: =IF((BB7>0),(BB7-BB6),0) -> 0 | BE7: =IF(OR(BD7="", BD7<BD6), 0, BD7-BD6) -> 0 | BF7: =IF(BC7=0, 0, (BD7-BD6)/BC7) -> 0
A8: 45237 | B8: =SUM(L8+R8+X8+AD8+AJ8) -> 0 | C8: =IF((B8>0),(B8-B7),0) -> 0 | D8: =SUM(N8+T8+Z8+AF8+AL8) -> 0 | E8: =IF(OR(D8="", D8<D7), 0, D8-D7) -> 0 | F8: =IF(C8=0, 0, (D8-D7)/C8) -> 0 | J8: =IF(G8=0, 0, (E8)/G8) -> 0 | M8: =IF((L8>0),(L8-L7),0) -> 0 | O8: =IF(OR(N8="", N8<N7), 0, N8-N7) -> 0 | P8: =IF(M8=0, 0, (N8-N7)/M8) -> 0 | S8: =IF((R8>0),(R8-R7),0) -> 0 | U8: =IF(OR(T8="", T8<T7), 0, T8-T7) -> 0 | V8: =IF(S8=0, 0, (T8-T7)/S8) -> 0 | Y8: =IF((X8>0),(X8-X7),0) -> 0 | AA8: =IF(OR(Z8="", Z8<Z7), 0, Z8-Z7) -> 0 | AB8: =IF(Y8=0, 0, (Z8-Z7)/Y8) -> 0 | AE8: =IF((AD8>0),(AD8-AD7),0) -> 0 | AG8: =IF(OR(AF8="", AF8<AF7), 0, AF8-AF7) -> 0 | AH8: =IF(AE8=0, 0, (AF8-AF7)/AE8) -> 0 | AK8: =IF((AJ8>0),(AJ8-AJ7),0) -> 0 | AM8: =IF(OR(AL8="", AL8<AL7), 0, AL8-AL7) -> 0 | AN8: =IF(AK8=0, 0, (AL8-AL7)/AK8) -> 0 | AQ8: =IF((AP8>0),(AP8-AP7),0) -> 0 | AS8: =IF(OR(AR8="", AR8<AR7), 0, AR8-AR7) -> 0 | AT8: =IF(AQ8=0, 0, (AR8-AR7)/AQ8) -> 0 | AW8: =IF((AV8>0),(AV8-AV7),0) -> 0 | AY8: =IF(OR(AX8="", AX8<AX7), 0, AX8-AX7) -> 0 | AZ8: =IF(AW8=0, 0, (AX8-AX7)/AW8) -> 0 | BC8: =IF((BB8>0),(BB8-BB7),0) -> 0 | BE8: =IF(OR(BD8="", BD8<BD7), 0, BD8-BD7) -> 0 | BF8: =IF(BC8=0, 0, (BD8-BD7)/BC8) -> 0
A9: 45238 | B9: =SUM(L9+R9+X9+AD9+AJ9) -> 0 | C9: =IF((B9>0),(B9-B8),0) -> 0 | D9: =SUM(N9+T9+Z9+AF9+AL9) -> 0 | E9: =IF(OR(D9="", D9<D8), 0, D9-D8) -> 0 | F9: =IF(C9=0, 0, (D9-D8)/C9) -> 0 | J9: =IF(G9=0, 0, (E9)/G9) -> 0 | M9: =IF((L9>0),(L9-L8),0) -> 0 | O9: =IF(OR(N9="", N9<N8), 0, N9-N8) -> 0 | P9: =IF(M9=0, 0, (N9-N8)/M9) -> 0 | S9: =IF((R9>0),(R9-R8),0) -> 0 | U9: =IF(OR(T9="", T9<T8), 0, T9-T8) -> 0 | V9: =IF(S9=0, 0, (T9-T8)/S9) -> 0 | Y9: =IF((X9>0),(X9-X8),0) -> 0 | AA9: =IF(OR(Z9="", Z9<Z8), 0, Z9-Z8) -> 0 | AB9: =IF(Y9=0, 0, (Z9-Z8)/Y9) -> 0 | AE9: =IF((AD9>0),(AD9-AD8),0) -> 0 | AG9: =IF(OR(AF9="", AF9<AF8), 0, AF9-AF8) -> 0 | AH9: =IF(AE9=0, 0, (AF9-AF8)/AE9) -> 0 | AK9: =IF((AJ9>0),(AJ9-AJ8),0) -> 0 | AM9: =IF(OR(AL9="", AL9<AL8), 0, AL9-AL8) -> 0 | AN9: =IF(AK9=0, 0, (AL9-AL8)/AK9) -> 0 | AQ9: =IF((AP9>0),(AP9-AP8),0) -> 0 | AS9: =IF(OR(AR9="", AR9<AR8), 0, AR9-AR8) -> 0 | AT9: =IF(AQ9=0, 0, (AR9-AR8)/AQ9) -> 0 | AW9: =IF((AV9>0),(AV9-AV8),0) -> 0 | AY9: =IF(OR(AX9="", AX9<AX8), 0, AX9-AX8) -> 0 | AZ9: =IF(AW9=0, 0, (AX9-AX8)/AW9) -> 0 | BC9: =IF((BB9>0),(BB9-BB8),0) -> 0 | BE9: =IF(OR(BD9="", BD9<BD8), 0, BD9-BD8) -> 0 | BF9: =IF(BC9=0, 0, (BD9-BD8)/BC9) -> 0
A10: 45239 | B10: =SUM(L10+R10+X10+AD10+AJ10) -> 0 | C10: =IF((B10>0),(B10-B9),0) -> 0 | D10: =SUM(N10+T10+Z10+AF10+AL10) -> 0 | E10: =IF(OR(D10="", D10<D9), 0, D10-D9) -> 0 | F10: =IF(C10=0, 0, (D10-D9)/C10) -> 0 | J10: =IF(G10=0, 0, (E10)/G10) -> 0 | M10: =IF((L10>0),(L10-L9),0) -> 0 | O10: =IF(OR(N10="", N10<N9), 0, N10-N9) -> 0 | P10: =IF(M10=0, 0, (N10-N9)/M10) -> 0 | S10: =IF((R10>0),(R10-R9),0) -> 0 | U10: =IF(OR(T10="", T10<T9), 0, T10-T9) -> 0 | V10: =IF(S10=0, 0, (T10-T9)/S10) -> 0 | Y10: =IF((X10>0),(X10-X9),0) -> 0 | AA10: =IF(OR(Z10="", Z10<Z9), 0, Z10-Z9) -> 0 | AB10: =IF(Y10=0, 0, (Z10-Z9)/Y10) -> 0 | AE10: =IF((AD10>0),(AD10-AD9),0) -> 0 | AG10: =IF(OR(AF10="", AF10<AF9), 0, AF10-AF9) -> 0 | AH10: =IF(AE10=0, 0, (AF10-AF9)/AE10) -> 0 | AK10: =IF((AJ10>0),(AJ10-AJ9),0) -> 0 | AM10: =IF(OR(AL10="", AL10<AL9), 0, AL10-AL9) -> 0 | AN10: =IF(AK10=0, 0, (AL10-AL9)/AK10) -> 0 | AQ10: =IF((AP10>0),(AP10-AP9),0) -> 0 | AS10: =IF(OR(AR10="", AR10<AR9), 0, AR10-AR9) -> 0 | AT10: =IF(AQ10=0, 0, (AR10-AR9)/AQ10) -> 0 | AW10: =IF((AV10>0),(AV10-AV9),0) -> 0 | AY10: =IF(OR(AX10="", AX10<AX9), 0, AX10-AX9) -> 0 | AZ10: =IF(AW10=0, 0, (AX10-AX9)/AW10) -> 0 | BC10: =IF((BB10>0),(BB10-BB9),0) -> 0 | BE10: =IF(OR(BD10="", BD10<BD9), 0, BD10-BD9) -> 0 | BF10: =IF(BC10=0, 0, (BD10-BD9)/BC10) -> 0
A11: 45240 | B11: =SUM(L11+R11+X11+AD11+AJ11) -> 0 | C11: =IF((B11>0),(B11-B10),0) -> 0 | D11: =SUM(N11+T11+Z11+AF11+AL11) -> 0 | E11: =IF(OR(D11="", D11<D10), 0, D11-D10) -> 0 | F11: =IF(C11=0, 0, (D11-D10)/C11) -> 0 | J11: =IF(G11=0, 0, (E11)/G11) -> 0 | M11: =IF((L11>0),(L11-L10),0) -> 0 | O11: =IF(OR(N11="", N11<N10), 0, N11-N10) -> 0 | P11: =IF(M11=0, 0, (N11-N10)/M11) -> 0 | S11: =IF((R11>0),(R11-R10),0) -> 0 | U11: =IF(OR(T11="", T11<T10), 0, T11-T10) -> 0 | V11: =IF(S11=0, 0, (T11-T10)/S11) -> 0 | Y11: =IF((X11>0),(X11-X10),0) -> 0 | AA11: =IF(OR(Z11="", Z11<Z10), 0, Z11-Z10) -> 0 | AB11: =IF(Y11=0, 0, (Z11-Z10)/Y11) -> 0 | AE11: =IF((AD11>0),(AD11-AD10),0) -> 0 | AG11: =IF(OR(AF11="", AF11<AF10), 0, AF11-AF10) -> 0 | AH11: =IF(AE11=0, 0, (AF11-AF10)/AE11) -> 0 | AK11: =IF((AJ11>0),(AJ11-AJ10),0) -> 0 | AM11: =IF(OR(AL11="", AL11<AL10), 0, AL11-AL10) -> 0 | AN11: =IF(AK11=0, 0, (AL11-AL10)/AK11) -> 0 | AQ11: =IF((AP11>0),(AP11-AP10),0) -> 0 | AS11: =IF(OR(AR11="", AR11<AR10), 0, AR11-AR10) -> 0 | AT11: =IF(AQ11=0, 0, (AR11-AR10)/AQ11) -> 0 | AW11: =IF((AV11>0),(AV11-AV10),0) -> 0 | AY11: =IF(OR(AX11="", AX11<AX10), 0, AX11-AX10) -> 0 | AZ11: =IF(AW11=0, 0, (AX11-AX10)/AW11) -> 0 | BC11: =IF((BB11>0),(BB11-BB10),0) -> 0 | BE11: =IF(OR(BD11="", BD11<BD10), 0, BD11-BD10) -> 0 | BF11: =IF(BC11=0, 0, (BD11-BD10)/BC11) -> 0
A12: 45241 | B12: =SUM(L12+R12+X12+AD12+AJ12) -> 0 | C12: =IF((B12>0),(B12-B11),0) -> 0 | D12: =SUM(N12+T12+Z12+AF12+AL12) -> 0 | E12: =IF(OR(D12="", D12<D11), 0, D12-D11) -> 0 | F12: =IF(C12=0, 0, (D12-D11)/C12) -> 0 | J12: =IF(G12=0, 0, (E12)/G12) -> 0 | M12: =IF((L12>0),(L12-L11),0) -> 0 | O12: =IF(OR(N12="", N12<N11), 0, N12-N11) -> 0 | P12: =IF(M12=0, 0, (N12-N11)/M12) -> 0 | S12: =IF((R12>0),(R12-R11),0) -> 0 | U12: =IF(OR(T12="", T12<T11), 0, T12-T11) -> 0 | V12: =IF(S12=0, 0, (T12-T11)/S12) -> 0 | Y12: =IF((X12>0),(X12-X11),0) -> 0 | AA12: =IF(OR(Z12="", Z12<Z11), 0, Z12-Z11) -> 0 | AB12: =IF(Y12=0, 0, (Z12-Z11)/Y12) -> 0 | AE12: =IF((AD12>0),(AD12-AD11),0) -> 0 | AG12: =IF(OR(AF12="", AF12<AF11), 0, AF12-AF11) -> 0 | AH12: =IF(AE12=0, 0, (AF12-AF11)/AE12) -> 0 | AK12: =IF((AJ12>0),(AJ12-AJ11),0) -> 0 | AM12: =IF(OR(AL12="", AL12<AL11), 0, AL12-AL11) -> 0 | AN12: =IF(AK12=0, 0, (AL12-AL11)/AK12) -> 0 | AQ12: =IF((AP12>0),(AP12-AP11),0) -> 0 | AS12: =IF(OR(AR12="", AR12<AR11), 0, AR12-AR11) -> 0 | AT12: =IF(AQ12=0, 0, (AR12-AR11)/AQ12) -> 0 | AW12: =IF((AV12>0),(AV12-AV11),0) -> 0 | AY12: =IF(OR(AX12="", AX12<AX11), 0, AX12-AX11) -> 0 | AZ12: =IF(AW12=0, 0, (AX12-AX11)/AW12) -> 0 | BC12: =IF((BB12>0),(BB12-BB11),0) -> 0 | BE12: =IF(OR(BD12="", BD12<BD11), 0, BD12-BD11) -> 0 | BF12: =IF(BC12=0, 0, (BD12-BD11)/BC12) -> 0
A13: 45242 | B13: =SUM(L13+R13+X13+AD13+AJ13) -> 0 | C13: =IF((B13>0),(B13-B12),0) -> 0 | D13: =SUM(N13+T13+Z13+AF13+AL13) -> 0 | E13: =IF(OR(D13="", D13<D12), 0, D13-D12) -> 0 | F13: =IF(C13=0, 0, (D13-D12)/C13) -> 0 | J13: =IF(G13=0, 0, (E13)/G13) -> 0 | M13: =IF((L13>0),(L13-L12),0) -> 0 | O13: =IF(OR(N13="", N13<N12), 0, N13-N12) -> 0 | P13: =IF(M13=0, 0, (N13-N12)/M13) -> 0 | S13: =IF((R13>0),(R13-R12),0) -> 0 | U13: =IF(OR(T13="", T13<T12), 0, T13-T12) -> 0 | V13: =IF(S13=0, 0, (T13-T12)/S13) -> 0 | Y13: =IF((X13>0),(X13-X12),0) -> 0 | AA13: =IF(OR(Z13="", Z13<Z12), 0, Z13-Z12) -> 0 | AB13: =IF(Y13=0, 0, (Z13-Z12)/Y13) -> 0 | AE13: =IF((AD13>0),(AD13-AD12),0) -> 0 | AG13: =IF(OR(AF13="", AF13<AF12), 0, AF13-AF12) -> 0 | AH13: =IF(AE13=0, 0, (AF13-AF12)/AE13) -> 0 | AK13: =IF((AJ13>0),(AJ13-AJ12),0) -> 0 | AM13: =IF(OR(AL13="", AL13<AL12), 0, AL13-AL12) -> 0 | AN13: =IF(AK13=0, 0, (AL13-AL12)/AK13) -> 0 | AQ13: =IF((AP13>0),(AP13-AP12),0) -> 0 | AS13: =IF(OR(AR13="", AR13<AR12), 0, AR13-AR12) -> 0 | AT13: =IF(AQ13=0, 0, (AR13-AR12)/AQ13) -> 0 | AW13: =IF((AV13>0),(AV13-AV12),0) -> 0 | AY13: =IF(OR(AX13="", AX13<AX12), 0, AX13-AX12) -> 0 | AZ13: =IF(AW13=0, 0, (AX13-AX12)/AW13) -> 0 | BC13: =IF((BB13>0),(BB13-BB12),0) -> 0 | BE13: =IF(OR(BD13="", BD13<BD12), 0, BD13-BD12) -> 0 | BF13: =IF(BC13=0, 0, (BD13-BD12)/BC13) -> 0
A14: 45243 | B14: =SUM(L14+R14+X14+AD14+AJ14) -> 0 | C14: =IF((B14>0),(B14-B13),0) -> 0 | D14: =SUM(N14+T14+Z14+AF14+AL14) -> 0 | E14: =IF(OR(D14="", D14<D13), 0, D14-D13) -> 0 | F14: =IF(C14=0, 0, (D14-D13)/C14) -> 0 | J14: =IF(G14=0, 0, (E14)/G14) -> 0 | M14: =IF((L14>0),(L14-L13),0) -> 0 | O14: =IF(OR(N14="", N14<N13), 0, N14-N13) -> 0 | P14: =IF(M14=0, 0, (N14-N13)/M14) -> 0 | S14: =IF((R14>0),(R14-R13),0) -> 0 | U14: =IF(OR(T14="", T14<T13), 0, T14-T13) -> 0 | V14: =IF(S14=0, 0, (T14-T13)/S14) -> 0 | Y14: =IF((X14>0),(X14-X13),0) -> 0 | AA14: =IF(OR(Z14="", Z14<Z13), 0, Z14-Z13) -> 0 | AB14: =IF(Y14=0, 0, (Z14-Z13)/Y14) -> 0 | AE14: =IF((AD14>0),(AD14-AD13),0) -> 0 | AG14: =IF(OR(AF14="", AF14<AF13), 0, AF14-AF13) -> 0 | AH14: =IF(AE14=0, 0, (AF14-AF13)/AE14) -> 0 | AK14: =IF((AJ14>0),(AJ14-AJ13),0) -> 0 | AM14: =IF(OR(AL14="", AL14<AL13), 0, AL14-AL13) -> 0 | AN14: =IF(AK14=0, 0, (AL14-AL13)/AK14) -> 0 | AQ14: =IF((AP14>0),(AP14-AP13),0) -> 0 | AS14: =IF(OR(AR14="", AR14<AR13), 0, AR14-AR13) -> 0 | AT14: =IF(AQ14=0, 0, (AR14-AR13)/AQ14) -> 0 | AW14: =IF((AV14>0),(AV14-AV13),0) -> 0 | AY14: =IF(OR(AX14="", AX14<AX13), 0, AX14-AX13) -> 0 | AZ14: =IF(AW14=0, 0, (AX14-AX13)/AW14) -> 0 | BC14: =IF((BB14>0),(BB14-BB13),0) -> 0 | BE14: =IF(OR(BD14="", BD14<BD13), 0, BD14-BD13) -> 0 | BF14: =IF(BC14=0, 0, (BD14-BD13)/BC14) -> 0
... A31: 45260 | B31: =SUM(L31+R31+X31+AD31+AJ31) -> 0 | C31: =IF((B31>0),(B31-B30),0) -> 0 | D31: =SUM(N31+T31+Z31+AF31+AL31) -> 0 | E31: =IF(OR(D31="", D31<D30), 0, D31-D30) -> 0 | F31: =IF(C31=0, 0, (D31-D30)/C31) -> 0 | J31: =IF(G31=0, 0, (E31)/G31) -> 0 | M31: =IF((L31>0),(L31-L30),0) -> 0 | O31: =IF(OR(N31="", N31<N30), 0, N31-N30) -> 0 | P31: =IF(M31=0, 0, (N31-N30)/M31) -> 0 | S31: =IF((R31>0),(R31-R30),0) -> 0 | U31: =IF(OR(T31="", T31<T30), 0, T31-T30) -> 0 | V31: =IF(S31=0, 0, (T31-T30)/S31) -> 0 | Y31: =IF((X31>0),(X31-X30),0) -> 0 | AA31: =IF(OR(Z31="", Z31<Z30), 0, Z31-Z30) -> 0 | AB31: =IF(Y31=0, 0, (Z31-Z30)/Y31) -> 0 | AE31: =IF((AD31>0),(AD31-AD30),0) -> 0 | AG31: =IF(OR(AF31="", AF31<AF30), 0, AF31-AF30) -> 0 | AH31: =IF(AE31=0, 0, (AF31-AF30)/AE31) -> 0 | AK31: =IF((AJ31>0),(AJ31-AJ30),0) -> 0 | AM31: =IF(OR(AL31="", AL31<AL30), 0, AL31-AL30) -> 0 | AN31: =IF(AK31=0, 0, (AL31-AL30)/AK31) -> 0 | AQ31: =IF((AP31>0),(AP31-AP30),0) -> 0 | AS31: =IF(OR(AR31="", AR31<AR30), 0, AR31-AR30) -> 0 | AT31: =IF(AQ31=0, 0, (AR31-AR30)/AQ31) -> 0 | AW31: =IF((AV31>0),(AV31-AV30),0) -> 0 | AY31: =IF(OR(AX31="", AX31<AX30), 0, AX31-AX30) -> 0 | AZ31: =IF(AW31=0, 0, (AX31-AX30)/AW31) -> 0 | BC31: =IF((BB31>0),(BB31-BB30),0) -> 0 | BE31: =IF(OR(BD31="", BD31<BD30), 0, BD31-BD30) -> 0 | BF31: =IF(BC31=0, 0, (BD31-BD30)/BC31) -> 0
A32: TOTAL | C32: =SUM(C2:C31) -> 0 | E32: =SUM(E2:E31) -> 0 | F32: =IF(E32=0, 0, (E32)/C32) -> 0 | G32: =SUM(G2:G31) -> 0 | H32: =SUM(H1:H31) -> 0 | I32: =SUM(I1:I31) -> 0 | J32: =IF(G32=0, 0, (E32)/G32) -> 0 | M32: =SUM(M2:M31) -> 0 | O32: =SUM(O2:O31) -> 0 | P32: =O32/M32 -> #DIV/0! | S32: =SUM(S2:S31) -> 0 | U32: =SUM(U2:U31) -> 0 | V32: =U32/S32 -> #DIV/0! | Y32: =SUM(Y2:Y31) -> 0 | AA32: =SUM(AA2:AA31) -> 0 | AB32: =AA32/Y32 -> #DIV/0! | AE32: =SUM(AE2:AE31) -> 0 | AG32: =SUM(AG2:AG31) -> 0 | AH32: =AG32/AE32 -> #DIV/0! | AK32: =SUM(AK2:AK31) -> 0 | AM32: =SUM(AM2:AM31) -> 0 | AN32: =AM32/AK32 -> #DIV/0! | AQ32: =SUM(AQ2:AQ31) -> 0 | AS32: =SUM(AS2:AS31) -> 0 | AT32: =AS32/AQ32 -> #DIV/0! | AW32: =SUM(AW2:AW31) -> 0 | AY32: =SUM(AY2:AY31) -> 0 | AZ32: =AY32/AW32 -> #DIV/0! | BC32: =SUM(BC2:BC31) -> 0 | BE32: =SUM(BE2:BE31) -> 0 | BF32: =BE32/BC32 -> #DIV/0!
A34: AD SPEND | B34: =E32 -> 0
A35: CASH | B35: =H32 -> 0
A36: ROI (Cash) | B36: =B35/E32 -> #DIV/0!
A37: REVENUE | B37: =I32 -> 0
A38: ROI (Rev) | B38: =B37/B34 -> #DIV/0!
A39: FOLLOWERS | B39: =C32 -> 0

Sheet December
A1: Day | B1: AD Follows | C1: New AD Follows | D1: Total Spend | E1: Daily Spend | F1: Cost/Lead | G1: Calls Booked | H1: Cash Collected | I1: Revenue | J1: Cost per Call | K1: AD 1 | L1: Follows | M1: New AD Follows | N1: Total Spend | O1: Daily Spend | P1: Cost/Lead | Q1: AD 2 | R1: AD Follows | S1: New AD Follows | T1: Total Spend | U1: Daily Spend | V1: Cost/Lead | W1: AD 3 | X1: AD Follows | Y1: New AD Follows | Z1: Total Spend | AA1: Daily Spend | AB1: Cost/Lead | AC1: AD 4 | AD1: AD Follows | AE1: New AD Follows | AF1: Total Spend | AG1: Daily Spend | AH1: Cost/Lead | AI1: AD 5 | AJ1: AD Follows | AK1: New AD Follows | AL1: Total Spend | AM1: Daily Spend | AN1: Cost/Lead | AO1: AD 6 | AP1: AD Follows | AQ1: New AD Follows | AR1: Total Spend | AS1: Daily Spend | AT1: Cost/Lead | AU1: AD 7 | AV1: AD Follows | AW1: New AD Follows | AX1: Total Spend | AY1: Daily Spend | AZ1: Cost/Lead | BA1: AD 8 | BB1: AD Follows | BC1: New AD Follows | BD1: Total Spend | BE1: Daily Spend | BF1: Cost/Lead
A2: 45261 | B2: =SUM(L2+R2+X2+AD2+AJ2) -> 0 | C2: 0 | D2: =SUM(N2+T2+Z2+AF2+AL2) -> 0 | E2: =D2 -> 0 | F2: =D2/C2 -> #DIV/0! | J2: =IF(G2=0, 0, (E2/G2)) -> 0 | M2: 0 | O2: =N2 | P2: =N2/M2 -> #DIV/0! | S2: 0 | U2: =T2 | V2: =T2/S2 -> #DIV/0! | Y2: 0 | AA2: =Z2 | AB2: =Z2/Y2 -> #DIV/0! | AE2: 0 | AG2: =AF2 | AH2: =AF2/AE2 -> #DIV/0! | AK2: 0 | AM2: =AL2 | AN2: =AL2/AK2 -> #DIV/0! | AQ2: 0 | AS2: =AR2 | AT2: =AR2/AQ2 -> #DIV/0! | AW2: 0 | AY2: =AX2 | AZ2: =AX2/AW2 -> #DIV/0! | BC2: 0 | BE2: =BD2 | BF2: =BD2/BC2 -> #DIV/0!
A3: 45262 | B3: =SUM(L3+R3+X3+AD3+AJ3) -> 0 | C3: =IF((B3>0),(B3-B2),0) -> 0 | D3: =SUM(N3+T3+Z3+AF3+AL3) -> 0 | E3: =IF(OR(D3="", D3<D2), 0, D3-D2) -> 0 | F3: =IF(C3=0, 0, (D3-D2)/C3) -> 0 | J3: =IF(G3=0, 0, (E3)/G3) -> 0 | M3: =IF((L3>0),(L3-L2),0) -> 0 | O3: =IF(OR(N3="", N3<N2), 0, N3-N2) -> 0 | P3: =IF(M3=0, 0, (N3-N2)/M3) -> 0 | S3: =IF((R3>0),(R3-R2),0) -> 0 | U3: =IF(OR(T3="", T3<T2), 0, T3-T2) -> 0 | V3: =IF(S3=0, 0, (T3-T2)/S3) -> 0 | Y3: =IF((X3>0),(X3-X2),0) -> 0 | AA3: =IF(OR(Z3="", Z3<Z2), 0, Z3-Z2) -> 0 | AB3: =IF(Y3=0, 0, (Z3-Z2)/Y3) -> 0 | AE3: =IF((AD3>0),(AD3-AD2),0) -> 0 | AG3: =IF(OR(AF3="", AF3<AF2), 0, AF3-AF2) -> 0 | AH3: =IF(AE3=0, 0, (AF3-AF2)/AE3) -> 0 | AK3: =IF((AJ3>0),(AJ3-AJ2),0) -> 0 | AM3: =IF(OR(AL3="", AL3<AL2), 0, AL3-AL2) -> 0 | AN3: =IF(AK3=0, 0, (AL3-AL2)/AK3) -> 0 | AQ3: =IF((AP3>0),(AP3-AP2),0) -> 0 | AS3: =IF(OR(AR3="", AR3<AR2), 0, AR3-AR2) -> 0 | AT3: =IF(AQ3=0, 0, (AR3-AR2)/AQ3) -> 0 | AW3: =IF((AV3>0),(AV3-AV2),0) -> 0 | AY3: =IF(OR(AX3="", AX3<AX2), 0, AX3-AX2) -> 0 | AZ3: =IF(AW3=0, 0, (AX3-AX2)/AW3) -> 0 | BC3: =IF((BB3>0),(BB3-BB2),0) -> 0 | BE3: =IF(OR(BD3="", BD3<BD2), 0, BD3-BD2) -> 0 | BF3: =IF(BC3=0, 0, (BD3-BD2)/BC3) -> 0
A4: 45263 | B4: =SUM(L4+R4+X4+AD4+AJ4) -> 0 | C4: =IF((B4>0),(B4-B3),0) -> 0 | D4: =SUM(N4+T4+Z4+AF4+AL4) -> 0 | E4: =IF(OR(D4="", D4<D3), 0, D4-D3) -> 0 | F4: =IF(C4=0, 0, (D4-D3)/C4) -> 0 | J4: =IF(G4=0, 0, (E4)/G4) -> 0 | M4: =IF((L4>0),(L4-L3),0) -> 0 | O4: =IF(OR(N4="", N4<N3), 0, N4-N3) -> 0 | P4: =IF(M4=0, 0, (N4-N3)/M4) -> 0 | S4: =IF((R4>0),(R4-R3),0) -> 0 | U4: =IF(OR(T4="", T4<T3), 0, T4-T3) -> 0 | V4: =IF(S4=0, 0, (T4-T3)/S4) -> 0 | Y4: =IF((X4>0),(X4-X3),0) -> 0 | AA4: =IF(OR(Z4="", Z4<Z3), 0, Z4-Z3) -> 0 | AB4: =IF(Y4=0, 0, (Z4-Z3)/Y4) -> 0 | AE4: =IF((AD4>0),(AD4-AD3),0) -> 0 | AG4: =IF(OR(AF4="", AF4<AF3), 0, AF4-AF3) -> 0 | AH4: =IF(AE4=0, 0, (AF4-AF3)/AE4) -> 0 | AK4: =IF((AJ4>0),(AJ4-AJ3),0) -> 0 | AM4: =IF(OR(AL4="", AL4<AL3), 0, AL4-AL3) -> 0 | AN4: =IF(AK4=0, 0, (AL4-AL3)/AK4) -> 0 | AQ4: =IF((AP4>0),(AP4-AP3),0) -> 0 | AS4: =IF(OR(AR4="", AR4<AR3), 0, AR4-AR3) -> 0 | AT4: =IF(AQ4=0, 0, (AR4-AR3)/AQ4) -> 0 | AW4: =IF((AV4>0),(AV4-AV3),0) -> 0 | AY4: =IF(OR(AX4="", AX4<AX3), 0, AX4-AX3) -> 0 | AZ4: =IF(AW4=0, 0, (AX4-AX3)/AW4) -> 0 | BC4: =IF((BB4>0),(BB4-BB3),0) -> 0 | BE4: =IF(OR(BD4="", BD4<BD3), 0, BD4-BD3) -> 0 | BF4: =IF(BC4=0, 0, (BD4-BD3)/BC4) -> 0
A5: 45264 | B5: =SUM(L5+R5+X5+AD5+AJ5) -> 0 | C5: =IF((B5>0),(B5-B4),0) -> 0 | D5: =SUM(N5+T5+Z5+AF5+AL5) -> 0 | E5: =IF(OR(D5="", D5<D4), 0, D5-D4) -> 0 | F5: =IF(C5=0, 0, (D5-D4)/C5) -> 0 | J5: =IF(G5=0, 0, (E5)/G5) -> 0 | M5: =IF((L5>0),(L5-L4),0) -> 0 | O5: =IF(OR(N5="", N5<N4), 0, N5-N4) -> 0 | P5: =IF(M5=0, 0, (N5-N4)/M5) -> 0 | S5: =IF((R5>0),(R5-R4),0) -> 0 | U5: =IF(OR(T5="", T5<T4), 0, T5-T4) -> 0 | V5: =IF(S5=0, 0, (T5-T4)/S5) -> 0 | Y5: =IF((X5>0),(X5-X4),0) -> 0 | AA5: =IF(OR(Z5="", Z5<Z4), 0, Z5-Z4) -> 0 | AB5: =IF(Y5=0, 0, (Z5-Z4)/Y5) -> 0 | AE5: =IF((AD5>0),(AD5-AD4),0) -> 0 | AG5: =IF(OR(AF5="", AF5<AF4), 0, AF5-AF4) -> 0 | AH5: =IF(AE5=0, 0, (AF5-AF4)/AE5) -> 0 | AK5: =IF((AJ5>0),(AJ5-AJ4),0) -> 0 | AM5: =IF(OR(AL5="", AL5<AL4), 0, AL5-AL4) -> 0 | AN5: =IF(AK5=0, 0, (AL5-AL4)/AK5) -> 0 | AQ5: =IF((AP5>0),(AP5-AP4),0) -> 0 | AS5: =IF(OR(AR5="", AR5<AR4), 0, AR5-AR4) -> 0 | AT5: =IF(AQ5=0, 0, (AR5-AR4)/AQ5) -> 0 | AW5: =IF((AV5>0),(AV5-AV4),0) -> 0 | AY5: =IF(OR(AX5="", AX5<AX4), 0, AX5-AX4) -> 0 | AZ5: =IF(AW5=0, 0, (AX5-AX4)/AW5) -> 0 | BC5: =IF((BB5>0),(BB5-BB4),0) -> 0 | BE5: =IF(OR(BD5="", BD5<BD4), 0, BD5-BD4) -> 0 | BF5: =IF(BC5=0, 0, (BD5-BD4)/BC5) -> 0
A6: 45265 | B6: =SUM(L6+R6+X6+AD6+AJ6) -> 0 | C6: =IF((B6>0),(B6-B5),0) -> 0 | D6: =SUM(N6+T6+Z6+AF6+AL6) -> 0 | E6: =IF(OR(D6="", D6<D5), 0, D6-D5) -> 0 | F6: =IF(C6=0, 0, (D6-D5)/C6) -> 0 | J6: =IF(G6=0, 0, (E6)/G6) -> 0 | M6: =IF((L6>0),(L6-L5),0) -> 0 | O6: =IF(OR(N6="", N6<N5), 0, N6-N5) -> 0 | P6: =IF(M6=0, 0, (N6-N5)/M6) -> 0 | S6: =IF((R6>0),(R6-R5),0) -> 0 | U6: =IF(OR(T6="", T6<T5), 0, T6-T5) -> 0 | V6: =IF(S6=0, 0, (T6-T5)/S6) -> 0 | Y6: =IF((X6>0),(X6-X5),0) -> 0 | AA6: =IF(OR(Z6="", Z6<Z5), 0, Z6-Z5) -> 0 | AB6: =IF(Y6=0, 0, (Z6-Z5)/Y6) -> 0 | AE6: =IF((AD6>0),(AD6-AD5),0) -> 0 | AG6: =IF(OR(AF6="", AF6<AF5), 0, AF6-AF5) -> 0 | AH6: =IF(AE6=0, 0, (AF6-AF5)/AE6) -> 0 | AK6: =IF((AJ6>0),(AJ6-AJ5),0) -> 0 | AM6: =IF(OR(AL6="", AL6<AL5), 0, AL6-AL5) -> 0 | AN6: =IF(AK6=0, 0, (AL6-AL5)/AK6) -> 0 | AQ6: =IF((AP6>0),(AP6-AP5),0) -> 0 | AS6: =IF(OR(AR6="", AR6<AR5), 0, AR6-AR5) -> 0 | AT6: =IF(AQ6=0, 0, (AR6-AR5)/AQ6) -> 0 | AW6: =IF((AV6>0),(AV6-AV5),0) -> 0 | AY6: =IF(OR(AX6="", AX6<AX5), 0, AX6-AX5) -> 0 | AZ6: =IF(AW6=0, 0, (AX6-AX5)/AW6) -> 0 | BC6: =IF((BB6>0),(BB6-BB5),0) -> 0 | BE6: =IF(OR(BD6="", BD6<BD5), 0, BD6-BD5) -> 0 | BF6: =IF(BC6=0, 0, (BD6-BD5)/BC6) -> 0
A7: 45266 | B7: =SUM(L7+R7+X7+AD7+AJ7) -> 0 | C7: =IF((B7>0),(B7-B6),0) -> 0 | D7: =SUM(N7+T7+Z7+AF7+AL7) -> 0 | E7: =IF(OR(D7="", D7<D6), 0, D7-D6) -> 0 | F7: =IF(C7=0, 0, (D7-D6)/C7) -> 0 | J7: =IF(G7=0, 0, (E7)/G7) -> 0 | M7: =IF((L7>0),(L7-L6),0) -> 0 | O7: =IF(OR(N7="", N7<N6), 0, N7-N6) -> 0 | P7: =IF(M7=0, 0, (N7-N6)/M7) -> 0 | S7: =IF((R7>0),(R7-R6),0) -> 0 | U7: =IF(OR(T7="", T7<T6), 0, T7-T6) -> 0 | V7: =IF(S7=0, 0, (T7-T6)/S7) -> 0 | Y7: =IF((X7>0),(X7-X6),0) -> 0 | AA7: =IF(OR(Z7="", Z7<Z6), 0, Z7-Z6) -> 0 | AB7: =IF(Y7=0, 0, (Z7-Z6)/Y7) -> 0 | AE7: =IF((AD7>0),(AD7-AD6),0) -> 0 | AG7: =IF(OR(AF7="", AF7<AF6), 0, AF7-AF6) -> 0 | AH7: =IF(AE7=0, 0, (AF7-AF6)/AE7) -> 0 | AK7: =IF((AJ7>0),(AJ7-AJ6),0) -> 0 | AM7: =IF(OR(AL7="", AL7<AL6), 0, AL7-AL6) -> 0 | AN7: =IF(AK7=0, 0, (AL7-AL6)/AK7) -> 0 | AQ7: =IF((AP7>0),(AP7-AP6),0) -> 0 | AS7: =IF(OR(AR7="", AR7<AR6), 0, AR7-AR6) -> 0 | AT7: =IF(AQ7=0, 0, (AR7-AR6)/AQ7) -> 0 | AW7: =IF((AV7>0),(AV7-AV6),0) -> 0 | AY7: =IF(OR(AX7="", AX7<AX6), 0, AX7-AX6) -> 0 | AZ7: =IF(AW7=0, 0, (AX7-AX6)/AW7) -> 0 | BC7: =IF((BB7>0),(BB7-BB6),0) -> 0 | BE7: =IF(OR(BD7="", BD7<BD6), 0, BD7-BD6) -> 0 | BF7: =IF(BC7=0, 0, (BD7-BD6)/BC7) -> 0
A8: 45267 | B8: =SUM(L8+R8+X8+AD8+AJ8) -> 0 | C8: =IF((B8>0),(B8-B7),0) -> 0 | D8: =SUM(N8+T8+Z8+AF8+AL8) -> 0 | E8: =IF(OR(D8="", D8<D7), 0, D8-D7) -> 0 | F8: =IF(C8=0, 0, (D8-D7)/C8) -> 0 | J8: =IF(G8=0, 0, (E8)/G8) -> 0 | M8: =IF((L8>0),(L8-L7),0) -> 0 | O8: =IF(OR(N8="", N8<N7), 0, N8-N7) -> 0 | P8: =IF(M8=0, 0, (N8-N7)/M8) -> 0 | S8: =IF((R8>0),(R8-R7),0) -> 0 | U8: =IF(OR(T8="", T8<T7), 0, T8-T7) -> 0 | V8: =IF(S8=0, 0, (T8-T7)/S8) -> 0 | Y8: =IF((X8>0),(X8-X7),0) -> 0 | AA8: =IF(OR(Z8="", Z8<Z7), 0, Z8-Z7) -> 0 | AB8: =IF(Y8=0, 0, (Z8-Z7)/Y8) -> 0 | AE8: =IF((AD8>0),(AD8-AD7),0) -> 0 | AG8: =IF(OR(AF8="", AF8<AF7), 0, AF8-AF7) -> 0 | AH8: =IF(AE8=0, 0, (AF8-AF7)/AE8) -> 0 | AK8: =IF((AJ8>0),(AJ8-AJ7),0) -> 0 | AM8: =IF(OR(AL8="", AL8<AL7), 0, AL8-AL7) -> 0 | AN8: =IF(AK8=0, 0, (AL8-AL7)/AK8) -> 0 | AQ8: =IF((AP8>0),(AP8-AP7),0) -> 0 | AS8: =IF(OR(AR8="", AR8<AR7), 0, AR8-AR7) -> 0 | AT8: =IF(AQ8=0, 0, (AR8-AR7)/AQ8) -> 0 | AW8: =IF((AV8>0),(AV8-AV7),0) -> 0 | AY8: =IF(OR(AX8="", AX8<AX7), 0, AX8-AX7) -> 0 | AZ8: =IF(AW8=0, 0, (AX8-AX7)/AW8) -> 0 | BC8: =IF((BB8>0),(BB8-BB7),0) -> 0 | BE8: =IF(OR(BD8="", BD8<BD7), 0, BD8-BD7) -> 0 | BF8: =IF(BC8=0, 0, (BD8-BD7)/BC8) -> 0
A9: 45268 | B9: =SUM(L9+R9+X9+AD9+AJ9) -> 0 | C9: =IF((B9>0),(B9-B8),0) -> 0 | D9: =SUM(N9+T9+Z9+AF9+AL9) -> 0 | E9: =IF(OR(D9="", D9<D8), 0, D9-D8) -> 0 | F9: =IF(C9=0, 0, (D9-D8)/C9) -> 0 | J9: =IF(G9=0, 0, (E9)/G9) -> 0 | M9: =IF((L9>0),(L9-L8),0) -> 0 | O9: =IF(OR(N9="", N9<N8), 0, N9-N8) -> 0 | P9: =IF(M9=0, 0, (N9-N8)/M9) -> 0 | S9: =IF((R9>0),(R9-R8),0) -> 0 | U9: =IF(OR(T9="", T9<T8), 0, T9-T8) -> 0 | V9: =IF(S9=0, 0, (T9-T8)/S9) -> 0 | Y9: =IF((X9>0),(X9-X8),0) -> 0 | AA9: =IF(OR(Z9="", Z9<Z8), 0, Z9-Z8) -> 0 | AB9: =IF(Y9=0, 0, (Z9-Z8)/Y9) -> 0 | AE9: =IF((AD9>0),(AD9-AD8),0) -> 0 | AG9: =IF(OR(AF9="", AF9<AF8), 0, AF9-AF8) -> 0 | AH9: =IF(AE9=0, 0, (AF9-AF8)/AE9) -> 0 | AK9: =IF((AJ9>0),(AJ9-AJ8),0) -> 0 | AM9: =IF(OR(AL9="", AL9<AL8), 0, AL9-AL8) -> 0 | AN9: =IF(AK9=0, 0, (AL9-AL8)/AK9) -> 0 | AQ9: =IF((AP9>0),(AP9-AP8),0) -> 0 | AS9: =IF(OR(AR9="", AR9<AR8), 0, AR9-AR8) -> 0 | AT9: =IF(AQ9=0, 0, (AR9-AR8)/AQ9) -> 0 | AW9: =IF((AV9>0),(AV9-AV8),0) -> 0 | AY9: =IF(OR(AX9="", AX9<AX8), 0, AX9-AX8) -> 0 | AZ9: =IF(AW9=0, 0, (AX9-AX8)/AW9) -> 0 | BC9: =IF((BB9>0),(BB9-BB8),0) -> 0 | BE9: =IF(OR(BD9="", BD9<BD8), 0, BD9-BD8) -> 0 | BF9: =IF(BC9=0, 0, (BD9-BD8)/BC9) -> 0
A10: 45269 | B10: =SUM(L10+R10+X10+AD10+AJ10) -> 0 | C10: =IF((B10>0),(B10-B9),0) -> 0 | D10: =SUM(N10+T10+Z10+AF10+AL10) -> 0 | E10: =IF(OR(D10="", D10<D9), 0, D10-D9) -> 0 | F10: =IF(C10=0, 0, (D10-D9)/C10) -> 0 | J10: =IF(G10=0, 0, (E10)/G10) -> 0 | M10: =IF((L10>0),(L10-L9),0) -> 0 | O10: =IF(OR(N10="", N10<N9), 0, N10-N9) -> 0 | P10: =IF(M10=0, 0, (N10-N9)/M10) -> 0 | S10: =IF((R10>0),(R10-R9),0) -> 0 | U10: =IF(OR(T10="", T10<T9), 0, T10-T9) -> 0 | V10: =IF(S10=0, 0, (T10-T9)/S10) -> 0 | Y10: =IF((X10>0),(X10-X9),0) -> 0 | AA10: =IF(OR(Z10="", Z10<Z9), 0, Z10-Z9) -> 0 | AB10: =IF(Y10=0, 0, (Z10-Z9)/Y10) -> 0 | AE10: =IF((AD10>0),(AD10-AD9),0) -> 0 | AG10: =IF(OR(AF10="", AF10<AF9), 0, AF10-AF9) -> 0 | AH10: =IF(AE10=0, 0, (AF10-AF9)/AE10) -> 0 | AK10: =IF((AJ10>0),(AJ10-AJ9),0) -> 0 | AM10: =IF(OR(AL10="", AL10<AL9), 0, AL10-AL9) -> 0 | AN10: =IF(AK10=0, 0, (AL10-AL9)/AK10) -> 0 | AQ10: =IF((AP10>0),(AP10-AP9),0) -> 0 | AS10: =IF(OR(AR10="", AR10<AR9), 0, AR10-AR9) -> 0 | AT10: =IF(AQ10=0, 0, (AR10-AR9)/AQ10) -> 0 | AW10: =IF((AV10>0),(AV10-AV9),0) -> 0 | AY10: =IF(OR(AX10="", AX10<AX9), 0, AX10-AX9) -> 0 | AZ10: =IF(AW10=0, 0, (AX10-AX9)/AW10) -> 0 | BC10: =IF((BB10>0),(BB10-BB9),0) -> 0 | BE10: =IF(OR(BD10="", BD10<BD9), 0, BD10-BD9) -> 0 | BF10: =IF(BC10=0, 0, (BD10-BD9)/BC10) -> 0
A11: 45270 | B11: =SUM(L11+R11+X11+AD11+AJ11) -> 0 | C11: =IF((B11>0),(B11-B10),0) -> 0 | D11: =SUM(N11+T11+Z11+AF11+AL11) -> 0 | E11: =IF(OR(D11="", D11<D10), 0, D11-D10) -> 0 | F11: =IF(C11=0, 0, (D11-D10)/C11) -> 0 | J11: =IF(G11=0, 0, (E11)/G11) -> 0 | M11: =IF((L11>0),(L11-L10),0) -> 0 | O11: =IF(OR(N11="", N11<N10), 0, N11-N10) -> 0 | P11: =IF(M11=0, 0, (N11-N10)/M11) -> 0 | S11: =IF((R11>0),(R11-R10),0) -> 0 | U11: =IF(OR(T11="", T11<T10), 0, T11-T10) -> 0 | V11: =IF(S11=0, 0, (T11-T10)/S11) -> 0 | Y11: =IF((X11>0),(X11-X10),0) -> 0 | AA11: =IF(OR(Z11="", Z11<Z10), 0, Z11-Z10) -> 0 | AB11: =IF(Y11=0, 0, (Z11-Z10)/Y11) -> 0 | AE11: =IF((AD11>0),(AD11-AD10),0) -> 0 | AG11: =IF(OR(AF11="", AF11<AF10), 0, AF11-AF10) -> 0 | AH11: =IF(AE11=0, 0, (AF11-AF10)/AE11) -> 0 | AK11: =IF((AJ11>0),(AJ11-AJ10),0) -> 0 | AM11: =IF(OR(AL11="", AL11<AL10), 0, AL11-AL10) -> 0 | AN11: =IF(AK11=0, 0, (AL11-AL10)/AK11) -> 0 | AQ11: =IF((AP11>0),(AP11-AP10),0) -> 0 | AS11: =IF(OR(AR11="", AR11<AR10), 0, AR11-AR10) -> 0 | AT11: =IF(AQ11=0, 0, (AR11-AR10)/AQ11) -> 0 | AW11: =IF((AV11>0),(AV11-AV10),0) -> 0 | AY11: =IF(OR(AX11="", AX11<AX10), 0, AX11-AX10) -> 0 | AZ11: =IF(AW11=0, 0, (AX11-AX10)/AW11) -> 0 | BC11: =IF((BB11>0),(BB11-BB10),0) -> 0 | BE11: =IF(OR(BD11="", BD11<BD10), 0, BD11-BD10) -> 0 | BF11: =IF(BC11=0, 0, (BD11-BD10)/BC11) -> 0
A12: 45271 | B12: =SUM(L12+R12+X12+AD12+AJ12) -> 0 | C12: =IF((B12>0),(B12-B11),0) -> 0 | D12: =SUM(N12+T12+Z12+AF12+AL12) -> 0 | E12: =IF(OR(D12="", D12<D11), 0, D12-D11) -> 0 | F12: =IF(C12=0, 0, (D12-D11)/C12) -> 0 | J12: =IF(G12=0, 0, (E12)/G12) -> 0 | M12: =IF((L12>0),(L12-L11),0) -> 0 | O12: =IF(OR(N12="", N12<N11), 0, N12-N11) -> 0 | P12: =IF(M12=0, 0, (N12-N11)/M12) -> 0 | S12: =IF((R12>0),(R12-R11),0) -> 0 | U12: =IF(OR(T12="", T12<T11), 0, T12-T11) -> 0 | V12: =IF(S12=0, 0, (T12-T11)/S12) -> 0 | Y12: =IF((X12>0),(X12-X11),0) -> 0 | AA12: =IF(OR(Z12="", Z12<Z11), 0, Z12-Z11) -> 0 | AB12: =IF(Y12=0, 0, (Z12-Z11)/Y12) -> 0 | AE12: =IF((AD12>0),(AD12-AD11),0) -> 0 | AG12: =IF(OR(AF12="", AF12<AF11), 0, AF12-AF11) -> 0 | AH12: =IF(AE12=0, 0, (AF12-AF11)/AE12) -> 0 | AK12: =IF((AJ12>0),(AJ12-AJ11),0) -> 0 | AM12: =IF(OR(AL12="", AL12<AL11), 0, AL12-AL11) -> 0 | AN12: =IF(AK12=0, 0, (AL12-AL11)/AK12) -> 0 | AQ12: =IF((AP12>0),(AP12-AP11),0) -> 0 | AS12: =IF(OR(AR12="", AR12<AR11), 0, AR12-AR11) -> 0 | AT12: =IF(AQ12=0, 0, (AR12-AR11)/AQ12) -> 0 | AW12: =IF((AV12>0),(AV12-AV11),0) -> 0 | AY12: =IF(OR(AX12="", AX12<AX11), 0, AX12-AX11) -> 0 | AZ12: =IF(AW12=0, 0, (AX12-AX11)/AW12) -> 0 | BC12: =IF((BB12>0),(BB12-BB11),0) -> 0 | BE12: =IF(OR(BD12="", BD12<BD11), 0, BD12-BD11) -> 0 | BF12: =IF(BC12=0, 0, (BD12-BD11)/BC12) -> 0
A13: 45272 | B13: =SUM(L13+R13+X13+AD13+AJ13) -> 0 | C13: =IF((B13>0),(B13-B12),0) -> 0 | D13: =SUM(N13+T13+Z13+AF13+AL13) -> 0 | E13: =IF(OR(D13="", D13<D12), 0, D13-D12) -> 0 | F13: =IF(C13=0, 0, (D13-D12)/C13) -> 0 | J13: =IF(G13=0, 0, (E13)/G13) -> 0 | M13: =IF((L13>0),(L13-L12),0) -> 0 | O13: =IF(OR(N13="", N13<N12), 0, N13-N12) -> 0 | P13: =IF(M13=0, 0, (N13-N12)/M13) -> 0 | S13: =IF((R13>0),(R13-R12),0) -> 0 | U13: =IF(OR(T13="", T13<T12), 0, T13-T12) -> 0 | V13: =IF(S13=0, 0, (T13-T12)/S13) -> 0 | Y13: =IF((X13>0),(X13-X12),0) -> 0 | AA13: =IF(OR(Z13="", Z13<Z12), 0, Z13-Z12) -> 0 | AB13: =IF(Y13=0, 0, (Z13-Z12)/Y13) -> 0 | AE13: =IF((AD13>0),(AD13-AD12),0) -> 0 | AG13: =IF(OR(AF13="", AF13<AF12), 0, AF13-AF12) -> 0 | AH13: =IF(AE13=0, 0, (AF13-AF12)/AE13) -> 0 | AK13: =IF((AJ13>0),(AJ13-AJ12),0) -> 0 | AM13: =IF(OR(AL13="", AL13<AL12), 0, AL13-AL12) -> 0 | AN13: =IF(AK13=0, 0, (AL13-AL12)/AK13) -> 0 | AQ13: =IF((AP13>0),(AP13-AP12),0) -> 0 | AS13: =IF(OR(AR13="", AR13<AR12), 0, AR13-AR12) -> 0 | AT13: =IF(AQ13=0, 0, (AR13-AR12)/AQ13) -> 0 | AW13: =IF((AV13>0),(AV13-AV12),0) -> 0 | AY13: =IF(OR(AX13="", AX13<AX12), 0, AX13-AX12) -> 0 | AZ13: =IF(AW13=0, 0, (AX13-AX12)/AW13) -> 0 | BC13: =IF((BB13>0),(BB13-BB12),0) -> 0 | BE13: =IF(OR(BD13="", BD13<BD12), 0, BD13-BD12) -> 0 | BF13: =IF(BC13=0, 0, (BD13-BD12)/BC13) -> 0
A14: 45273 | B14: =SUM(L14+R14+X14+AD14+AJ14) -> 0 | C14: =IF((B14>0),(B14-B13),0) -> 0 | D14: =SUM(N14+T14+Z14+AF14+AL14) -> 0 | E14: =IF(OR(D14="", D14<D13), 0, D14-D13) -> 0 | F14: =IF(C14=0, 0, (D14-D13)/C14) -> 0 | J14: =IF(G14=0, 0, (E14)/G14) -> 0 | M14: =IF((L14>0),(L14-L13),0) -> 0 | O14: =IF(OR(N14="", N14<N13), 0, N14-N13) -> 0 | P14: =IF(M14=0, 0, (N14-N13)/M14) -> 0 | S14: =IF((R14>0),(R14-R13),0) -> 0 | U14: =IF(OR(T14="", T14<T13), 0, T14-T13) -> 0 | V14: =IF(S14=0, 0, (T14-T13)/S14) -> 0 | Y14: =IF((X14>0),(X14-X13),0) -> 0 | AA14: =IF(OR(Z14="", Z14<Z13), 0, Z14-Z13) -> 0 | AB14: =IF(Y14=0, 0, (Z14-Z13)/Y14) -> 0 | AE14: =IF((AD14>0),(AD14-AD13),0) -> 0 | AG14: =IF(OR(AF14="", AF14<AF13), 0, AF14-AF13) -> 0 | AH14: =IF(AE14=0, 0, (AF14-AF13)/AE14) -> 0 | AK14: =IF((AJ14>0),(AJ14-AJ13),0) -> 0 | AM14: =IF(OR(AL14="", AL14<AL13), 0, AL14-AL13) -> 0 | AN14: =IF(AK14=0, 0, (AL14-AL13)/AK14) -> 0 | AQ14: =IF((AP14>0),(AP14-AP13),0) -> 0 | AS14: =IF(OR(AR14="", AR14<AR13), 0, AR14-AR13) -> 0 | AT14: =IF(AQ14=0, 0, (AR14-AR13)/AQ14) -> 0 | AW14: =IF((AV14>0),(AV14-AV13),0) -> 0 | AY14: =IF(OR(AX14="", AX14<AX13), 0, AX14-AX13) -> 0 | AZ14: =IF(AW14=0, 0, (AX14-AX13)/AW14) -> 0 | BC14: =IF((BB14>0),(BB14-BB13),0) -> 0 | BE14: =IF(OR(BD14="", BD14<BD13), 0, BD14-BD13) -> 0 | BF14: =IF(BC14=0, 0, (BD14-BD13)/BC14) -> 0
... A32: 45291 | B32: =SUM(L32+R32+X32+AD32+AJ32) -> 0 | C32: =IF((B32>0),(B32-B31),0) -> 0 | D32: =SUM(N32+T32+Z32+AF32+AL32) -> 0 | E32: =IF(OR(D32="", D32<D31), 0, D32-D31) -> 0 | F32: =IF(C32=0, 0, (D32-D31)/C32) -> 0 | J32: =IF(G32=0, 0, (E32)/G32) -> 0 | M32: =IF((L32>0),(L32-L31),0) -> 0 | O32: =IF(OR(N32="", N32<N31), 0, N32-N31) -> 0 | P32: =IF(M32=0, 0, (N32-N31)/M32) -> 0 | S32: =IF((R32>0),(R32-R31),0) -> 0 | U32: =IF(OR(T32="", T32<T31), 0, T32-T31) -> 0 | V32: =IF(S32=0, 0, (T32-T31)/S32) -> 0 | Y32: =IF((X32>0),(X32-X31),0) -> 0 | AA32: =IF(OR(Z32="", Z32<Z31), 0, Z32-Z31) -> 0 | AB32: =IF(Y32=0, 0, (Z32-Z31)/Y32) -> 0 | AE32: =IF((AD32>0),(AD32-AD31),0) -> 0 | AG32: =IF(OR(AF32="", AF32<AF31), 0, AF32-AF31) -> 0 | AH32: =IF(AE32=0, 0, (AF32-AF31)/AE32) -> 0 | AK32: =IF((AJ32>0),(AJ32-AJ31),0) -> 0 | AM32: =IF(OR(AL32="", AL32<AL31), 0, AL32-AL31) -> 0 | AN32: =IF(AK32=0, 0, (AL32-AL31)/AK32) -> 0 | AQ32: =IF((AP32>0),(AP32-AP31),0) -> 0 | AS32: =IF(OR(AR32="", AR32<AR31), 0, AR32-AR31) -> 0 | AT32: =IF(AQ32=0, 0, (AR32-AR31)/AQ32) -> 0 | AW32: =IF((AV32>0),(AV32-AV31),0) -> 0 | AY32: =IF(OR(AX32="", AX32<AX31), 0, AX32-AX31) -> 0 | AZ32: =IF(AW32=0, 0, (AX32-AX31)/AW32) -> 0 | BC32: =IF((BB32>0),(BB32-BB31),0) -> 0 | BE32: =IF(OR(BD32="", BD32<BD31), 0, BD32-BD31) -> 0 | BF32: =IF(BC32=0, 0, (BD32-BD31)/BC32) -> 0
A33: TOTAL | C33: =SUM(C2:C31) -> 0 | E33: =SUM(E2:E31) -> 0 | F33: =IF(E33=0, 0, (E33)/C33) -> 0 | G33: =SUM(G2:G31) -> 0 | H33: =SUM(H1:H31) -> 0 | I33: =SUM(I1:I31) -> 0 | J33: =IF(G33=0, 0, (E33)/G33) -> 0 | M33: =SUM(M2:M31) -> 0 | O33: =SUM(O2:O31) -> 0 | P33: =O33/M33 -> #DIV/0! | S33: =SUM(S2:S31) -> 0 | U33: =SUM(U2:U31) -> 0 | V33: =U33/S33 -> #DIV/0! | Y33: =SUM(Y2:Y31) -> 0 | AA33: =SUM(AA2:AA31) -> 0 | AB33: =AA33/Y33 -> #DIV/0! | AE33: =SUM(AE2:AE31) -> 0 | AG33: =SUM(AG2:AG31) -> 0 | AH33: =AG33/AE33 -> #DIV/0! | AK33: =SUM(AK2:AK31) -> 0 | AM33: =SUM(AM2:AM31) -> 0 | AN33: =AM33/AK33 -> #DIV/0! | AQ33: =SUM(AQ2:AQ31) -> 0 | AS33: =SUM(AS2:AS31) -> 0 | AT33: =AS33/AQ33 -> #DIV/0! | AW33: =SUM(AW2:AW31) -> 0 | AY33: =SUM(AY2:AY31) -> 0 | AZ33: =AY33/AW33 -> #DIV/0! | BC33: =SUM(BC2:BC31) -> 0 | BE33: =SUM(BE2:BE31) -> 0 | BF33: =BE33/BC33 -> #DIV/0!
A35: AD SPEND | B35: =E33 -> 0
A36: CASH | B36: =H33 -> 0
A37: ROI (Cash) | B37: =B36/E33 -> #DIV/0!
A38: REVENUE | B38: =I33 -> 0
A39: ROI (Rev) | B39: =B38/B35 -> #DIV/0!
A40: FOLLOWERS | B40: =C33 -> 0
