Workbook

Sheet Dashboard
A1: Sales tracking
A2: Key Metrics | B2: YTD | C2: January | D2: February | E2: March | F2: April | G2: May | H2: June | I2: July | J2: August | K2: September | L2: October | M2: November | N2: December | O2: SPARKLINES
A3: Conversion Rate: | B3: =iferror(B12/B10,"") | C3: =Jan!I2 -> #REF! | D3: =IFERROR(Feb!I2,"") | E3: =Mar!I2 -> #REF! | F3: =IFERROR(Template!I2,"") | G3: =IFERROR(May!I2,"") | H3: =IFERROR(Jun!I2,"") -> 0.32 | I3: =IFERROR(Jul!I2,"") -> 0.52941176 | J3: =IFERROR(Aug!I2,"") -> 0.4137931 | K3: =IFERROR(Sep!L2,"") -> 0.31147541 | L3: =IFERROR(Oct!I2,"") | M3: =IFERROR(Nov!I2,"") | N3: =IFERROR(Dec!I2,"") | O3: =IFERROR(__xludf.DUMMYFUNCTION("IFERROR(SPARKLINE(C3:N3, {""chartype"", ""line""; ""color"", ""blue""})) "),"")
A4: Offer To Close Rate: | B4: =iferror(B12/B11,"") | C4: =Jan!I3 -> #REF! | D4: =IFERROR(Feb!I3,"") | E4: =IFERROR(Mar!I3,"") | F4: =IFERROR(Template!I3,"") | G4: =IFERROR(May!I3,"") | H4: =IFERROR(Jun!I3,"") -> 0.34782609 | I4: =IFERROR(Jul!I3,"") -> 0.52941176 | J4: =IFERROR(Aug!I3,"") -> 0.4137931 | K4: =IFERROR(Sep!L3,"") -> 0.3220339 | L4: =IFERROR(Oct!L3,"") -> 0.39655172 | M4: =IFERROR(Nov!I3,"") | N4: =IFERROR(Dec!I3,"") | O4: =IFERROR(__xludf.DUMMYFUNCTION("IFERROR(SPARKLINE(C4:N4, {""chartype"", ""line""; ""color"", ""blue""})) "),"")
A5: Call To Offer Rate: | B5: =IFERROR(B11/B10,"") | C5: =Jan!I4 -> #REF! | D5: =IFERROR(Feb!I4,"") | E5: =IFERROR(Mar!I4,"") | F5: =IFERROR(Template!I4,"") | G5: =IFERROR(May!I4,"") | H5: =IFERROR(Jun!I4,"") -> 0.92 | I5: =IFERROR(Jul!I4,"") -> 1 | J5: =IFERROR(Aug!I4,"") -> 1 | K5: =IFERROR(Sep!L4,"") -> 0.96721311 | L5: =IFERROR(Oct!L4,"") -> 0.98305085 | M5: =IFERROR(Nov!I4,"") | N5: =IFERROR(Dec!I4,"") | O5: =IFERROR(__xludf.DUMMYFUNCTION("IFERROR(SPARKLINE(C5:N5, {""chartype"", ""line""; ""color"", ""blue""})) "),"")
A6: Revenue: | B6: =IFERROR(SUM(C6:N6),"") | C6: =Jan!C3 -> #REF! | D6: =IFERROR(Feb!C3,"") | E6: =IFERROR(Mar!$C3,"") | F6: =IFERROR(Template!$C3,"") -> 0 | G6: =IFERROR(May!$C3,"") -> 0 | H6: =IFERROR(Jun!$C3,"") -> 69500 | I6: =IFERROR(Jul!$C3,"") -> 162000 | J6: =IFERROR(Aug!$C3,"") -> 111000 | K6: =IFERROR(Sep!$C3,"") -> 202500 | L6: =IFERROR(Oct!$C3,"") -> 238500 | M6: =IFERROR(Nov!$C3,"") -> 155000 | N6: =IFERROR(Dec!$C3,"") -> 239000 | O6: =IFERROR(__xludf.DUMMYFUNCTION("IFERROR(SPARKLINE(C6:N6, {""chartype"", ""line""; ""color"", ""blue""})) "),"")
A7: Cash: | B7: =IFERROR(SUM(C7:N7),"") | C7: =Jan!C4 -> #REF! | D7: =IFERROR(Feb!C4,"") | E7: =IFERROR(Mar!$C4,"") | F7: =IFERROR(Template!$C4,"") -> 0 | G7: =IFERROR(May!$C4,"") -> 0 | H7: =IFERROR(Jun!$C4,"") -> 22100 | I7: =IFERROR(Jul!$C4,"") -> 88550 | J7: =IFERROR(Aug!$C4,"") -> 43875 | K7: =IFERROR(Sep!$C4,"") -> 55150 | L7: =IFERROR(Oct!$C4,"") -> 75349.5 | M7: =IFERROR(Nov!$C4,"") -> 64800 | N7: =IFERROR(Dec!$C4,"") -> 80950 | O7: =IFERROR(__xludf.DUMMYFUNCTION("IFERROR(SPARKLINE(C7:N7, {""chartype"", ""line""; ""color"", ""blue""})) "),"")
A8: Bookings: | B8: =IFERROR(SUM(C8:N8),"") | C8: =Jan!I6 -> #REF! | D8: =IFERROR(Feb!I6,"") | E8: =IFERROR(Mar!$I6,"") | F8: =IFERROR(Template!$I6,"") -> 0 | G8: =IFERROR(May!$I6,"") -> 0 | H8: =IFERROR(Jun!$I6,"") -> 31 | I8: =IFERROR(Jul!$I6,"") -> 42 | J8: =IFERROR(Aug!$I6,"") -> 32 | K8: =IFERROR(Sep!$L6,"") -> 70 | L8: =IFERROR(Oct!$L6,"") -> 73 | M8: =IFERROR(Nov!$L6,"") -> 67 | N8: =IFERROR(Dec!$L6,"") -> 65 | O8: =IFERROR(__xludf.DUMMYFUNCTION("IFERROR(SPARKLINE(C8:N8, {""chartype"", ""line""; ""color"", ""blue""})) "),"")
A9: Shows: | B9: =sum(C9:N9) -> #REF! | C9: =Jan!I7 -> #REF! | D9: =IFERROR(Feb!$I$7,"") | E9: =IFERROR(Mar!$I$7,"") | F9: =IFERROR(Template!$I$7,"") -> 0 | G9: =IFERROR(May!$I$7,"") -> 0 | H9: =IFERROR(Jun!$I$7,"") -> 25 | I9: =IFERROR(Jul!$I$7,"") -> 34 | J9: =IFERROR(Aug!$I$7,"") -> 29 | K9: =IFERROR(Sep!$L$7,"") -> 61 | L9: =IFERROR(Oct!$L$7,"") -> 59 | M9: =IFERROR(Nov!$L$7,"") -> 57 | N9: =IFERROR(Dec!$L$7,"") -> 55 | O9: =IFERROR(__xludf.DUMMYFUNCTION("IFERROR(SPARKLINE(C9:N9, {""chartype"", ""line""; ""color"", ""blue""})) "),"")
A10: Calls: | B10: =IFERROR(SUM(C10:N10),"") | C10: =Jan!I7 -> #REF! | D10: =IFERROR(Feb!I8,"") | E10: =IFERROR(Mar!$I8,"") | F10: =IFERROR(Template!$I8,"") -> 0 | G10: =IFERROR(May!$I8,"") -> 0 | H10: =IFERROR(Jun!$I8,"") -> 25 | I10: =IFERROR(Jul!$I8,"") -> 34 | J10: =IFERROR(Aug!$I8,"") -> 29 | K10: =IFERROR(Sep!$L8,"") -> 61 | L10: =IFERROR(Oct!$L8,"") -> 59 | M10: =IFERROR(Nov!$L8,"") -> 57 | N10: =IFERROR(Dec!$L8,"") -> 55 | O10: =IFERROR(__xludf.DUMMYFUNCTION("IFERROR(SPARKLINE(C10:N10, {""chartype"", ""line""; ""color"", ""blue""})) "),"")
A11: Offers: | B11: =IFERROR(SUM(C11:N11),"") | C11: =Jan!I9 -> #REF! | D11: =IFERROR(Feb!I9,"") | E11: =IFERROR(Mar!$I9,"") | F11: =IFERROR(Template!$I9,"") -> 0 | G11: =IFERROR(May!$I9,"") -> 0 | H11: =IFERROR(Jun!$I9,"") -> 23 | I11: =IFERROR(Jul!$I9,"") -> 34 | J11: =IFERROR(Aug!$I9,"") -> 29 | K11: =IFERROR(Sep!$L9,"") -> 59 | L11: =IFERROR(Oct!$L9,"") -> 58 | M11: =IFERROR(Nov!$L9,"") -> 55 | N11: =IFERROR(Dec!$L9,"") -> 52 | O11: =IFERROR(__xludf.DUMMYFUNCTION("IFERROR(SPARKLINE(C11:N11, {""chartype"", ""line""; ""color"", ""blue""})) "),"")
A12: Deals: | B12: =IFERROR(SUM(C12:N12),"") | C12: =Jan!I10 -> #REF! | D12: =IFERROR(Feb!I10,"") | E12: =IFERROR(Mar!$I10,"") | F12: =IFERROR(Template!$I10,"") -> 0 | G12: =IFERROR(May!$I10,"") -> 0 | H12: =IFERROR(Jun!$I10,"") -> 8 | I12: =IFERROR(Jul!$I10,"") -> 18 | J12: =IFERROR(Aug!$I10,"") -> 12 | K12: =IFERROR(Sep!$L10,"") -> 19 | L12: =IFERROR(Oct!$L10,"") -> 23 | M12: =IFERROR(Nov!$L10,"") -> 17 | N12: =IFERROR(Dec!$L10,"") -> 23 | O12: =IFERROR(__xludf.DUMMYFUNCTION("IFERROR(SPARKLINE(C12:N12, {""chartype"", ""line""; ""color"", ""blue""})) "),"")
A13: Full-Pay: | B13: =IFERROR(SUM(C13:N13),"") | C13: =Jan!F2 -> #REF! | D13: =IFERROR(Feb!F2,"") | E13: =IFERROR(Mar!$F2,"") | F13: =IFERROR(Template!$F2,"") -> 0 | G13: =IFERROR(May!$F2,"") -> 0 | H13: =IFERROR(Jun!$F2,"") -> 1 | I13: =IFERROR(Jul!$F2,"") -> 7 | J13: =IFERROR(Aug!$F2,"") -> 3 | K13: =IFERROR(Sep!$I2,"") -> 1 | L13: =IFERROR(Oct!$I2,"") -> 1 | M13: =IFERROR(Nov!$I2,"") -> 5 | N13: =IFERROR(Dec!$I2,"") -> 3 | O13: =IFERROR(__xludf.DUMMYFUNCTION("IFERROR(SPARKLINE(C13:N13, {""chartype"", ""line""; ""color"", ""blue""})) "),"")
A14: Split-Pay: | B14: =IFERROR(SUM(C14:N14),"") | C14: =Jan!F3 -> #REF! | D14: =IFERROR(Feb!F3,"") | E14: =IFERROR(Mar!$F3,"") | F14: =IFERROR(Template!$F3,"") -> 0 | G14: =IFERROR(May!$F3,"") -> 0 | H14: =IFERROR(Jun!$F3,"") -> 7 | I14: =IFERROR(Jul!$F3,"") -> 11 | J14: =IFERROR(Aug!$F3,"") -> 9 | K14: =IFERROR(Sep!$I3,"") -> 18 | L14: =IFERROR(Oct!$I3,"") -> 22 | M14: =IFERROR(Nov!$I3,"") -> 12 | N14: =IFERROR(Dec!$I3,"") -> 20 | O14: =IFERROR(__xludf.DUMMYFUNCTION("IFERROR(SPARKLINE(C14:N14, {""chartype"", ""line""; ""color"", ""blue""})) "),"")
A15: Deposits: | B15: =IFERROR(SUM(C15:N15),"") | C15: =Jan!F4 -> #REF! | D15: =IFERROR(Feb!F4,"") | E15: =IFERROR(Mar!$F4,"") | F15: =IFERROR(Template!$F4,"") -> 0 | G15: =IFERROR(May!$F4,"") -> 0 | H15: =IFERROR(Jun!$F4,"") -> 0 | I15: =IFERROR(Jul!$F4,"") -> 1 | J15: =IFERROR(Aug!$F4,"") -> 1 | K15: =IFERROR(Sep!$I4,"") -> 8 | L15: =IFERROR(Oct!$I4,"") -> 4 | M15: =IFERROR(Nov!$I4,"") -> 7 | N15: =IFERROR(Dec!$I4,"") -> 6 | O15: =IFERROR(__xludf.DUMMYFUNCTION("IFERROR(SPARKLINE(C15:N15, {""chartype"", ""line""; ""color"", ""blue""})) "),"")
A16: Show-Up Rate: | B16: =B9/B8 -> #REF! | C16: =C9/C8 -> #REF! | D16: =D9/D8 -> #DIV/0! | E16: =E9/E8 -> #DIV/0! | F16: =F9/F8 -> #DIV/0! | G16: =G9/G8 -> #DIV/0! | H16: =H9/H8 -> 0.80645161 | I16: =I9/I8 -> 0.80952381 | ... N16: =N9/N8 -> 0.84615385 | O16: =IFERROR(__xludf.DUMMYFUNCTION("IFERROR(SPARKLINE(C16:N16, {""chartype"", ""line""; ""color"", ""blue""})) "),"")
A17: Conducted Rate: | B17: =B10/B8 -> #DIV/0! | C17: =C10/C8 -> #REF! | D17: =D10/D8 -> #DIV/0! | E17: =E10/E8 -> #DIV/0! | F17: =F10/F8 -> #DIV/0! | G17: =G10/G8 -> #DIV/0! | H17: =H10/H8 -> 0.80645161 | I17: =I10/I8 -> 0.80952381 | ... N17: =N10/N8 -> 0.84615385 | O17: =IFERROR(__xludf.DUMMYFUNCTION("IFERROR(SPARKLINE(C17:N17, {""chartype"", ""line""; ""color"", ""blue""})) "),"")

Sheet Template
B1: Rep: | C1: Anna | E1: Outcome | H1: KPIs% | K1: Show Rate | N1: Objections | Q1: Source | U1: Tracking
E2: Full-Pay: | F2: =IFERROR(COUNTIFS(I13:I287, "Full-Pay"),"") -> 0 | H2: Conversion Rate: | I2: =iferror(I10/I8,"") | K2: Rescheduling Rate: | L2: =iferror(F8/I6,"") | N2: Think About It | O2: =IFERROR(COUNTIFS(N13:N286, "think about it"),"") -> 0 | Q2: Reschedule | R2: =IFERROR(COUNTIF(H13:H286,Q2),"") -> 0 | S2: Cold Call | T2: =IFERROR(COUNTIF(H13:H286,S2),"") -> 0
B3: Revenue | C3: =IFERROR(SUM(K13:K284),"") -> 0 | E3: Split-Pay: | F3: =IFERROR(COUNTIFS(I13:I287, "Split-Pay"),"") -> 0 | H3: Offer To Close Rate: | I3: =IFERROR(I10/I9,"") | K3: Cancellation Rate: | L3: =iferror(F9/I6,"") | N3: Money | O3: =IFERROR(COUNTIFS(N13:N286, "money"),"") -> 0 | Q3: YouTube | R3: =IFERROR(COUNTIF(H13:H286,Q3),"") -> 0 | S3: Twitter | T3: =IFERROR(COUNTIF(H13:H286,S3),"") -> 0
B4: Cash | C4: =IFERROR(SUM(L13:L284),"") -> 0 | E4: Deposits: | F4: =IFERROR(COUNTIFS(I13:I287, "Deposit"),"") -> 0 | H4: Call To Offer Rate: | I4: =IFERROR(I9/I8,"") | K4: No-Shows Rate: | L4: =iferror(F10/I6,"") | N4: Time | O4: =IFERROR(COUNTIFS(N13:N286, "time"),"") -> 0 | Q4: YouTube Ads | R4: =IFERROR(COUNTIF(H13:H286,Q4),"") -> 0 | S4: Skool | T4: =IFERROR(COUNTIF(H13:H286,S4),"") -> 0
E5: Offer & Didn't Buy: | F5: =IFERROR(COUNTIFS(I13:I287, "Offer & Didn't Buy"),"") -> 0 | H5: Drag Over Rate: | I5: =IFERROR(F7/(C6+F7+F8),"") | K5: Drag Over Rate: | L5: =iferror(F7/I6,"") | N5: Partner | O5: =IFERROR(COUNTIFS(N13:N286, "partner"),"") -> 0 | Q5: Email | R5: =IFERROR(COUNTIF(H13:H286,Q5),"") -> 0 | S5: Instagram | T5: =IFERROR(COUNTIF(H13:H286,S5),"") -> 0
B6: Total Calls : | C6: =IFERROR(SUM(F2:F6),"") -> 0 | E6: Bad Fit & No Offer: | F6: =IFERROR(COUNTIFS(I13:I287, "Bad Fit & No Offer"),"") -> 0 | H6: Bookings: | I6: =IFERROR(SUM(F2:F10),"") -> 0 | K6: Show-Up Rate: | L6: =iferror(I7/I6,"") | N6: Fear | O6: =IFERROR(COUNTIFS(N13:N286, "fear"),"") -> 0 | Q6: Facebook | R6: =IFERROR(COUNTIF(H13:H286,Q6),"") -> 0 | S6: TikTok | T6: =IFERROR(COUNTIF(H13:H286,S6),"") -> 0
B7: Total Won : | C7: =IFERROR(F2+F3,"") -> 0 | E7: Drag Over & Show: | F7: =IFERROR(COUNTIFS(I13:I287, "Drag Over & Show"),"") -> 0 | H7: Shows: | I7: =IFERROR(SUM(F2:F7),"") -> 0 | K7: Conducted Rate: | L7: =IFERROR(I8/I6,"") | N7: Value | O7: =IFERROR(COUNTIFS(N14:N287, "value"),"") -> 0 | Q7: Facebook Ads | R7: =IFERROR(COUNTIF(H13:H286,Q7),"") -> 0 | S7: Google | T7: =IFERROR(COUNTIF(H13:H286,S7),"") -> 0
B8: Total Lost : | C8: =COUNTIF(I13:I286,"offer & didn't buy")+countif(I13:I286,"deposit")+countif(I13:I286,"bad fit & no offer") -> 0 | E8: Rescheduled: | F8: =IFERROR(COUNTIFS(I13:I287, "Rescheduled"),"") -> 0 | H8: Calls: | I8: =IFERROR(SUM(F2:F6),"") -> 0 | Q8: LinkedIn | R8: =IFERROR(COUNTIF(H13:H286,Q8),"") -> 0 | S8: Referral | T8: =IFERROR(COUNTIF(H13:H286,S8),"") -> 0
B9: Closing % : | C9: =iferror(SUM(C7/C6),"") | E9: Cancelled: | F9: =IFERROR(COUNTIFS(I13:I287, "Cancelled"),"") -> 0 | H9: Offers: | I9: =IFERROR(sum(F2:F5),"") -> 0
E10: No-Show: | F10: =IFERROR(COUNTIFS(I13:I287, "No-Show"),"") -> 0 | H10: Deals | I10: =F2+F3 -> 0
B12: Date | C12: Name | E12: Phone No. | F12: IG | H12: Source | I12: Outcome | K12: Revenue | L12: Cash | N12: Objection | O12: Objection Notes | Q12: Length | R12: Recording Link | S12: Follow Up/Next Steps | T12: Call Summary

Sheet May
B1: Rep: | C1: Name | E1: Outcome | H1: KPIs% | K1: Show Rate | N1: Objections | Q1: Source | U1: Tracking
E2: Full-Pay: | F2: =IFERROR(COUNTIFS(I13:I287, "Full-Pay"),"") -> 0 | H2: Conversion Rate: | I2: =iferror(I10/I8,"") | K2: Rescheduling Rate: | L2: =iferror(F8/I6,"") | N2: Think About It | O2: =IFERROR(COUNTIFS(N13:N286, "think about it"),"") -> 0 | Q2: Reschedule | R2: =IFERROR(COUNTIF(H13:H286,Q2),"") -> 0 | S2: Cold Call | T2: =IFERROR(COUNTIF(H13:H286,S2),"") -> 0
B3: Revenue | C3: =IFERROR(SUM(K13:K283),"") -> 0 | E3: Split-Pay: | F3: =IFERROR(COUNTIFS(I13:I287, "Split-Pay"),"") -> 0 | H3: Offer To Close Rate: | I3: =IFERROR(I10/I9,"") | K3: Cancellation Rate: | L3: =iferror(F9/I6,"") | N3: Money | O3: =IFERROR(COUNTIFS(N13:N286, "money"),"") -> 0 | Q3: YouTube | R3: =IFERROR(COUNTIF(H13:H286,Q3),"") -> 0 | S3: Twitter | T3: =IFERROR(COUNTIF(H13:H286,S3),"") -> 0
B4: Cash | C4: =IFERROR(SUM(L13:L284),"") -> 0 | E4: Deposits: | F4: =IFERROR(COUNTIFS(I13:I287, "Deposit"),"") -> 0 | H4: Call To Offer Rate: | I4: =IFERROR(I9/I8,"") | K4: No-Shows Rate: | L4: =iferror(F10/I6,"") | N4: Time | O4: =IFERROR(COUNTIFS(N13:N286, "time"),"") -> 0 | Q4: YouTube Ads | R4: =IFERROR(COUNTIF(H13:H286,Q4),"") -> 0 | S4: Skool | T4: =IFERROR(COUNTIF(H13:H286,S4),"") -> 0
E5: Offer & Didn't Buy: | F5: =IFERROR(COUNTIFS(I13:I287, "Offer & Didn't Buy"),"") -> 0 | H5: Drag Over Rate: | I5: =IFERROR(F7/(C6+F7+F8),"") | K5: Drag Over Rate: | L5: =iferror(F7/I6,"") | N5: Partner | O5: =IFERROR(COUNTIFS(N13:N286, "partner"),"") -> 0 | Q5: Email | R5: =IFERROR(COUNTIF(H13:H286,Q5),"") -> 0 | S5: Instagram | T5: =IFERROR(COUNTIF(H13:H286,S5),"") -> 0
B6: Total Calls : | C6: =IFERROR(SUM(F2:F6),"") -> 0 | E6: Bad Fit & No Offer: | F6: =IFERROR(COUNTIFS(I13:I287, "Bad Fit & No Offer"),"") -> 0 | H6: Bookings: | I6: =IFERROR(SUM(F2:F10),"") -> 0 | K6: Show-Up Rate: | L6: =iferror(I7/I6,"") | N6: Fear | O6: =IFERROR(COUNTIFS(N13:N286, "fear"),"") -> 0 | Q6: Facebook | R6: =IFERROR(COUNTIF(H13:H286,Q6),"") -> 0 | S6: TikTok | T6: =IFERROR(COUNTIF(H13:H286,S6),"") -> 0
B7: Total Won : | C7: =IFERROR(F2+F3,"") -> 0 | E7: Drag Over & Show: | F7: =IFERROR(COUNTIFS(I13:I287, "Drag Over & Show"),"") -> 0 | H7: Shows: | I7: =IFERROR(SUM(F2:F7),"") -> 0 | K7: Conducted Rate: | L7: =IFERROR(I8/I6,"") | N7: Value | O7: =IFERROR(COUNTIFS(N14:N287, "value"),"") -> 0 | Q7: Facebook Ads | R7: =IFERROR(COUNTIF(H13:H286,Q7),"") -> 0 | S7: Google | T7: =IFERROR(COUNTIF(H13:H286,S7),"") -> 0
B8: Total Lost : | C8: =COUNTIF(I13:I286,"offer & didn't buy")+countif(I13:I286,"deposit")+countif(I13:I286,"bad fit & no offer") -> 0 | E8: Rescheduled: | F8: =IFERROR(COUNTIFS(I13:I287, "Rescheduled"),"") -> 0 | H8: Calls: | I8: =IFERROR(SUM(F2:F6),"") -> 0 | Q8: LinkedIn | R8: =IFERROR(COUNTIF(H13:H286,Q8),"") -> 0 | S8: Referral | T8: =IFERROR(COUNTIF(H13:H286,S8),"") -> 0
B9: Closing % : | C9: =iferror(SUM(C7/C6),"") | E9: Cancelled: | F9: =IFERROR(COUNTIFS(I13:I287, "Cancelled"),"") -> 0 | H9: Offers: | I9: =IFERROR(sum(F2:F5),"") -> 0
E10: No-Show: | F10: =IFERROR(COUNTIFS(I13:I287, "No-Show"),"") -> 0 | H10: Deals | I10: =F2+F3 -> 0
B12: Date | C12: Name | E12: Phone No. | F12: Email | H12: Source | I12: Outcome | K12: Revenue | L12: Cash | N12: Objection | O12: Objection Notes | Q12: Length | R12: Recording Link | S12: Follow Up/Next Steps | T12: Call Summary

Sheet Jun
B1: Rep: | C1: Name | E1: Outcome | H1: KPIs% | K1: Show Rate | N1: Objections | Q1: Source | U1: Tracking
E2: Full-Pay: | F2: =IFERROR(COUNTIFS(I13:I287, "Full-Pay"),"") -> 1 | H2: Conversion Rate: | I2: =iferror(I10/I8,"") -> 0.32 | K2: Rescheduling Rate: | L2: =iferror(F8/I6,"") -> 0.064516129 | N2: Think About It | O2: =IFERROR(COUNTIFS(N13:N286, "think about it"),"") -> 1 | Q2: Reschedule | R2: =IFERROR(COUNTIF(H13:H286,Q2),"") -> 0 | S2: Cold Call | T2: =IFERROR(COUNTIF(H13:H286,S2),"") -> 0
B3: Revenue | C3: =IFERROR(SUM(K13:K283),"") -> 69500 | E3: Split-Pay: | F3: =IFERROR(COUNTIFS(I13:I287, "Split-Pay"),"") -> 7 | H3: Offer To Close Rate: | I3: =IFERROR(I10/I9,"") -> 0.34782609 | K3: Cancellation Rate: | L3: =iferror(F9/I6,"") -> 0.032258065 | N3: Money | O3: =IFERROR(COUNTIFS(N13:N286, "money"),"") -> 10 | Q3: YouTube | R3: =IFERROR(COUNTIF(H13:H286,Q3),"") -> 0 | S3: Twitter | T3: =IFERROR(COUNTIF(H13:H286,S3),"") -> 0
B4: Cash | C4: =IFERROR(SUM(L13:L284),"") -> 22100 | E4: Deposits: | F4: =IFERROR(COUNTIFS(I13:I287, "Deposit"),"") -> 0 | H4: Call To Offer Rate: | I4: =IFERROR(I9/I8,"") -> 0.92 | K4: No-Shows Rate: | L4: =iferror(F10/I6,"") -> 0.096774194 | N4: Time | O4: =IFERROR(COUNTIFS(N13:N286, "time"),"") -> 2 | Q4: YouTube Ads | R4: =IFERROR(COUNTIF(H13:H286,Q4),"") -> 0 | S4: Skool | T4: =IFERROR(COUNTIF(H13:H286,S4),"") -> 0
E5: Offer & Didn't Buy: | F5: =IFERROR(COUNTIFS(I13:I287, "Offer & Didn't Buy"),"") -> 15 | H5: Drag Over Rate: | I5: =IFERROR(F7/(C6+F7+F8),"") -> 0 | K5: Drag Over Rate: | L5: =iferror(F7/I6,"") -> 0 | N5: Partner | O5: =IFERROR(COUNTIFS(N13:N286, "partner"),"") -> 1 | Q5: Email | R5: =IFERROR(COUNTIF(H13:H286,Q5),"") -> 0 | S5: Instagram | T5: =IFERROR(COUNTIF(H13:H286,S5),"") -> 0
B6: Total Calls : | C6: =IFERROR(SUM(F2:F6),"") -> 25 | E6: Bad Fit & No Offer: | F6: =IFERROR(COUNTIFS(I13:I287, "Bad Fit & No Offer"),"") -> 2 | H6: Bookings: | I6: =IFERROR(SUM(F2:F10),"") -> 31 | K6: Show-Up Rate: | L6: =iferror(I7/I6,"") -> 0.80645161 | N6: Fear | O6: =IFERROR(COUNTIFS(N13:N286, "fear"),"") -> 3 | Q6: Facebook | R6: =IFERROR(COUNTIF(H13:H286,Q6),"") -> 0 | S6: TikTok | T6: =IFERROR(COUNTIF(H13:H286,S6),"") -> 0
B7: Total Won : | C7: =IFERROR(F2+F3,"") -> 8 | E7: Drag Over & Show: | F7: =IFERROR(COUNTIFS(I13:I287, "Drag Over & Show"),"") -> 0 | H7: Shows: | I7: =IFERROR(SUM(F2:F7),"") -> 25 | K7: Conducted Rate: | L7: =IFERROR(I8/I6,"") -> 0.80645161 | N7: Value | O7: =IFERROR(COUNTIFS(N14:N287, "value"),"") -> 0 | Q7: Facebook Ads | R7: =IFERROR(COUNTIF(H13:H286,Q7),"") -> 7 | S7: Google | T7: =IFERROR(COUNTIF(H13:H286,S7),"") -> 0
B8: Total Lost : | C8: =COUNTIF(I13:I286,"offer & didn't buy")+countif(I13:I286,"deposit")+countif(I13:I286,"bad fit & no offer") -> 17 | E8: Rescheduled: | F8: =IFERROR(COUNTIFS(I13:I287, "Rescheduled"),"") -> 2 | H8: Calls: | I8: =IFERROR(SUM(F2:F6),"") -> 25 | Q8: LinkedIn | R8: =IFERROR(COUNTIF(H13:H286,Q8),"") -> 0 | S8: Referral | T8: =IFERROR(COUNTIF(H13:H286,S8),"") -> 0
B9: Closing % : | C9: =iferror(SUM(C7/C6),"") -> 0.32 | E9: Cancelled: | F9: =IFERROR(COUNTIFS(I13:I287, "Cancelled"),"") -> 1 | H9: Offers: | I9: =IFERROR(sum(F2:F5),"") -> 23
E10: No-Show: | F10: =IFERROR(COUNTIFS(I13:I287, "No-Show"),"") -> 3 | H10: Deals | I10: =F2+F3 -> 8
B12: Date | C12: Name | E12: Phone No. | F12: Email | H12: Source | I12: Outcome | K12: Revenue | L12: Cash | N12: Objection | O12: Objection Notes | Q12: Length | R12: Recording Link | S12: Follow Up/Next Steps | T12: Call Summary
B13: 2. juni | C13: Alex Pedersen | E13: 20742600 | F13: alexelfving@hotmail.dk | H13: Setter | I13: Offer & Didn't Buy | N13: Money | O13: Nævnt både tid og pengene, men var nok i bund og grund pengene | S13: X | T13: Var i bund og grund ikke klar til a committe og syntes det var dyrt, i forhold til hvad han ville lægge i det
B14: 2. juni | C14: Malte Brix | E14: 30209070 | F14: brixmalte392@gmail.com | H14: Landing page | I14: Rescheduled | S14: Follow Up
B15: 3. juni | C15: Patrick Hansen | E15: 22584551 | F15: paatrickkh@gmail.com | H15: Landing page | I15: Offer & Didn't Buy | N15: Money | O15: Syntes det var dyrt og lige pludseligt var der det ene og andet i vejen | S15: X | T15: Havde ikke tænkt over hvorfor det var vigtigt for ham, tror ikke rigtigt han havde tænkt det igennem
B16: 3. juni | C16: Pia Mattheisen | E16: 26361821 | F16: blomst1981@hotmail.com | H16: Setter | I16: Split-pay | K16: 6500 | L16: 500 | N16: Money | O16: Var det økonomisk med 4 børn der trykkede | Q16: 4 Måneder | S16: Closed | T16: Syntes det var en god samtale jeg havde med hende lød ret klar og følger op på hende i morgen kl 16:15
B17: 5. juni | C17: Agnes Balch | E17: 60549433 | F17: agnesbalch@gmail.com | H17: Setter | I17: Offer & Didn't Buy | N17: Partner | O17: Skulle snakke med sin mor om det, fordi hun også ville støtte hende økonomisk, føler først det gav mening efter sommerferien, hvor skoledagen pressed på igen. Har tilbudt hende en plads efter sommerferien, hvis hun lægger et depositum | S17: Follow Up Set | T17: Rigtig god snak hun virker varm, jeg hører noget om et par timer
B18: 5.juni | C18: Marie Rasmussen | E18: 20872787 | F18: marielrasmussen01@gmail.com | H18: Setter | I18: Split-pay | K18: 9000 | L18: 3000 | Q18: 5 Måneder | S18: Closed | T18: Havde ikke tænkt over hvorfor det var vigtigt for ham, tror ikke rigtigt han havde tænkt det igennem
B19: 6. juni | C19: Cathrine NIlson | E19: 40195943 | F19: cathrinehn@hotmail.com | H19: Facebook Ads | I19: No-Show
B20: 6. juni | C20: Malthe Reilund | E20: 53607017 | F20: malthereilund@icloud.com | H20: Facebook Ads | I20: Offer & Didn't Buy | N20: Fear | O20: Sagde han skulle tænke over, og det var hverken penge, værdi, eller noget andet | S20: X | T20: Han sagde jeg til alt i forhold til om at følte det var det rette for ham kunne bare ikke commite sig og endte med at lægge på
B21: 6. juni | C21: Nana Sommer | E21: 51160980 | F21: nanasommer99@gmail.com | H21: Setter | I21: Split-pay | K21: 9000 | L21: 1800 | Q21: 5 Måneder | S21: Closed | T21: God samtale, vi havde, hun kunne nemmere få det til at fungere med en højere månedlig pris end en opstart
B22: 9. juni | C22: Line Chan Larsen | E22: 61418828 | F22: linechanlarsen@gmail.com | H22: Setter | I22: Offer & Didn't Buy | N22: Time | O22: Sagde det var dårlig timing i forhold til hvor hun var lige nu, følger op på hende 1. august, der sagde hun det ville passe | S22: Follow Up Set | T22: Samtalen, kunne godt have gået bedre, var ikke god nok i discovery og gik ikke skabt nok pain og urgency
B23: 9. juni | C23: Johannes Jensen | E23: 24228199 | F23: jensenjohannes5@gmail.com | H23: Landing page | I23: Split-pay | K23: 9000 | L23: 3000 | Q23: 5 Måneder
B24: 11. juni | C24: Malte Brix | E24: 30209070 | F24: brixmalte392@gmail.com | H24: Landing page | I24: No-Show
B25: 11. juni | C25: Nikoline Pilgaard Nielsen | E25: 20829235 | F25: nikoline.pilgaard@gmail.com | H25: Setter | I25: Offer & Didn't Buy | N25: Think About It | O25: Hun sagde nu ikke var sikker på om en online træner var noget for hende, nu nok havde mere gavn af en fysisk | S25: X | T25: Var bedre i discovery fandt noget pain og havde fokus på at frame samtalen godt.(kom til at sprøge om de samme spørgsmål for mange gang.) Fucker nok lidt op ved pricedrop, og corner hende lidt for meget i forhold til objection handling, skal være/lyde mere hjælpsom. Hun endte med at lægge på
B26: 13. juni | C26: Lucas Starup | E26: 23919060 | F26: lucas.jorgensen.starup@gmail.com | H26: Setter | I26: Bad Fit & No Offer | S26: X | T26: God snak med lucas, fucker lidt på med hans money objection, ved ikke hvorfor jeg ikke bare følger frameworket. Han havde ingen penge nu, så kunne først lade sig gøre 1. august, derfor ingen startup :(. Viser sig han ikke har fået forældre tilladelse (under 18) selvom han sagde det ikke var et problem
B27: 16. juni | C27: Carina Jensen | E27: 22662912 | F27: carinawj@hotmail.com | H27: Setter | I27: Offer & Didn't Buy | N27: Money | O27: Det kunne simpelthen ikke lade sig gøre økonomisk. Hun sagde udgifterne var større end indkomsten, og sådan havde det egenligt været de sidste par måneder | S27: X | T27: God snak, hun syntes det virkede fedt, skulle bare tjekke op på det økonomiske. Kunne simpelthen ikke lade sig gøre
B28: 16. juni | C28: Sofia Bogarch | E28: 30747351 | F28: sofia.bogarch@gmail.com | H28: Setter | I28: Split-pay | K28: 9000 | L28: 1000 | Q28: 5 Måneder | S28: Closed | T28: Gik godt, havde ikke de store indsigelser, godt være skarpere på nogle spørgsmål. betalte 1000 upfront og resten delt i 3
B29: 17. juni | C29: Naya Lindevang-Hilstrø, | E29: 26643009 | F29: aya_hil@hotmail.con | H29: Facebook Ads | I29: Offer & Didn't Buy | N29: Money | O29: Hun var pt på barsel, så hun skulle lige undersøge økonomien i det | S29: Follow Up Set | T29: Hun var klar, det var kun pengene, der var problemet, eller så var hun 100 procent klar når hun kom tilbage fra barsel
B30: 17 juni | C30: Jeppe Bach Olesen | E30: 61319741 | F30: jeppebacholesen@gmail.com | H30: Facebook Ads | I30: Offer & Didn't Buy | N30: Money | O30: Han skulle simpelthen, bare kigge på det økonomien i det | S30: X | T30: Har en aftale med ham i morgen kl 17. Skulle have brugt den med "jeg ved hvad der sker når vi lægger på nu her...." Ved ikke hvorfor jeg ikke gjorde det
B31: 17. juni | C31: William Holm Carlson | E31: 20866807 | F31: williamholm.carlson@icloud.com | H31: Landing page | I31: Rescheduled | T31: Skal have forældrene med var under 18
B32: 18. juni | C32: Hørður í geil | E32: 52232168 | F32: hig1998@gmail.com | H32: Setter | I32: Cancelled
B33: 18. juni | C33: Tommy Lindevang Hansen | E33: 20652890 | F33: tommylhansen@hotmail.com | H33: Facebook Ads | I33: Full-Pay | K33: 9000 | L33: 9000 | Q33: 5 måneder | S33: Closed | T33: Klasse snak, prøvede at arbejde med med tonailty, og brugte feedback i picth
B34: 22. juni | C34: Cecilie H | E34: 42154443 | F34: madison.hartwich@gmail.com | H34: Setter | I34: Offer & Didn't Buy | N34: Money | O34: Hun var på SU, skulle betale husleje og havde bil, så kunne ikke lade sig gøre | S34: Follow Up Set | T34: Syntes, vi havde en god snak, skulle have brugt commitment noget mere. Har en aftale med at kontakte hende igen slut august, når hun skal i lære og har nogle flere penge
B35: 22. juni | C35: Jesper Mortensen | E35: 20473963 | F35: soegaard96@gmail.com | H35: Facebook Ads | I35: Offer & Didn't Buy | N35: Money | O35: Økonomien var ikke til har ikke job fra næste måned af så nok også timing | T35: Havde en god snak med ham, lød virkeligt på. Lød til ham super gerne ville, men det var pengene, der kom i vejen. Han sagde det nok godt kunne lade sig gøre, men han stod uden job i slutningen af den her måned, så det holdte ham tilbage. Han endte med at lægge på
B36: 23. juni | C36: Mette Møller | E36: 26496120 | F36: mette@family-moeller.net | H36: Setter | I36: Offer & Didn't Buy | N36: Fear | O36: Det er faktisk kan hjælpe hende, da nu har noget løs hud hun ikke er sikker på kan trænes væk | S36: Follow Up Set | T36: Virker virkeligt på bare usikker på om vi kan få hende i mål. Hun har tidligere været på et andet forløb, hvor hun ikke kom i mål. Ringer tilbage til hende i morgen
B37: 23. juni | C37: Michelle Als | E37: 53382706 | F37: missals@live.dk | H37: Facebook Ads | I37: Bad Fit & No Offer | T37: Ville være et dårligt fit hun har en sclerose og det er ikke noget vi normalt arbejder med
B38: 24. juni | C38: Lykke Henckel | E38: 25781914 | H38: Setter | I38: Offer & Didn't Buy | N38: Money | O38: Skulle høre om mor ikke kunne hjælpe | S38: Follow Up | T38: Ville virkeligt gerne, men havde ikke pengene selv, så ville hører sin mor
B39: 24. juni | C39: Jack andersen | E39: 23238865 | F39: jackandersen66@gmail.com | H39: Setter | I39: Offer & Didn't Buy | N39: Fear | O39: Han ghoestede mig selvom han sagde ja til det, så havde en lige pludseligt ikket et kort det virkede | S39: X | T39: Endte jo med han sagde ja, men var nok stadig i tvivel eller turde ikke sige nej, så kunne godt blive bedre
B40: 25. juni | C40: Lasse Lund | E40: 61519344 | F40: lasselund2404@gmail.com | H40: Landing page | I40: Split-pay | K40: 9000 | L40: 1800 | Q40: 5 måneder | S40: Closed | T40: Vidste ikke hvorfor han ikke skulle gøre det, der var i hvert fald noget fear, men endte med han gjorde det
B41: 28. juni | C41: David Silva | E41: 50184073 | F41: ds8.1999@gmail.com | H41: Setter | I41: Split-pay | K41: 9000 | L41: 2000 | N41: Time | O41: Han vil første starte til August | S41: Closed | T41: God snak, han ville udfylde mailen og kort oplysninger i dag
B42: 30. juni | C42: Mikkel Hansen | E42: 25717014 | F42: mikkelhansen@toftlund.net | H42: Setter | I42: Offer & Didn't Buy | N42: Money | O42: Er egenligt ikke helt klar over, hvad det var, men syntes ikke det var det rette for ham, det var ikke det han havde brug for og syntes også det var dyrt | S42: X | T42: Fucker op i starten med discovery det kunne godt have været bedre, men syntes, det var en lidt mærkelig snak og ærligt jeg får ham sku ikke solgt.
B43: 30. juni | C43: Ciao Peruzzo | E43: 91803464 | F43: caioperusso@hotmail.com | H43: IG | I43: No-Show

Sheet Jul
B1: Rep: | C1: Name | E1: Outcome | H1: KPIs% | K1: Show Rate | N1: Objections | Q1: Source | U1: Tracking
E2: Full-Pay: | F2: =IFERROR(COUNTIFS(I13:I287, "Full-Pay"),"") -> 7 | H2: Conversion Rate: | I2: =iferror(I10/I8,"") -> 0.52941176 | K2: Rescheduling Rate: | L2: =iferror(F8/I6,"") -> 0.047619048 | N2: Think About It | O2: =IFERROR(COUNTIFS(N13:N286, "think about it"),"") -> 0 | Q2: Reschedule | R2: =IFERROR(COUNTIF(H13:H286,Q2),"") -> 0 | S2: Cold Call | T2: =IFERROR(COUNTIF(H13:H286,S2),"") -> 0
B3: Revenue | C3: =IFERROR(SUM(K13:K283),"") -> 162000 | E3: Split-Pay: | F3: =IFERROR(COUNTIFS(I13:I287, "Split-Pay"),"") -> 11 | H3: Offer To Close Rate: | I3: =IFERROR(I10/I9,"") -> 0.52941176 | K3: Cancellation Rate: | L3: =iferror(F9/I6,"") -> 0.071428571 | N3: Money | O3: =IFERROR(COUNTIFS(N13:N286, "money"),"") -> 12 | Q3: YouTube | R3: =IFERROR(COUNTIF(H13:H286,Q3),"") -> 0 | S3: Twitter | T3: =IFERROR(COUNTIF(H13:H286,S3),"") -> 0
B4: Cash | C4: =IFERROR(SUM(L13:L284),"") -> 88550 | E4: Deposits: | F4: =IFERROR(COUNTIFS(I13:I287, "Deposit"),"") -> 1 | H4: Call To Offer Rate: | I4: =IFERROR(I9/I8,"") -> 1 | K4: No-Shows Rate: | L4: =iferror(F10/I6,"") -> 0.071428571 | N4: Time | O4: =IFERROR(COUNTIFS(N13:N286, "time"),"") -> 1 | Q4: YouTube Ads | R4: =IFERROR(COUNTIF(H13:H286,Q4),"") -> 0 | S4: Skool | T4: =IFERROR(COUNTIF(H13:H286,S4),"") -> 0
E5: Offer & Didn't Buy: | F5: =IFERROR(COUNTIFS(I13:I287, "Offer & Didn't Buy"),"") -> 15 | H5: Drag Over Rate: | I5: =IFERROR(F7/(C6+F7+F8),"") -> 0 | K5: Drag Over Rate: | L5: =iferror(F7/I6,"") -> 0 | N5: Partner | O5: =IFERROR(COUNTIFS(N13:N286, "partner"),"") -> 3 | Q5: Email | R5: =IFERROR(COUNTIF(H13:H286,Q5),"") -> 0 | S5: Instagram | T5: =IFERROR(COUNTIF(H13:H286,S5),"") -> 0
B6: Total Calls : | C6: =IFERROR(SUM(F2:F6),"") -> 34 | E6: Bad Fit & No Offer: | F6: =IFERROR(COUNTIFS(I13:I287, "Bad Fit & No Offer"),"") -> 0 | H6: Bookings: | I6: =IFERROR(SUM(F2:F10),"") -> 42 | K6: Show-Up Rate: | L6: =iferror(I7/I6,"") -> 0.80952381 | N6: Fear | O6: =IFERROR(COUNTIFS(N13:N286, "fear"),"") -> 1 | Q6: Facebook | R6: =IFERROR(COUNTIF(H13:H286,Q6),"") -> 0 | S6: TikTok | T6: =IFERROR(COUNTIF(H13:H286,S6),"") -> 0
B7: Total Won : | C7: =IFERROR(F2+F3,"") -> 18 | E7: Drag Over & Show: | F7: =IFERROR(COUNTIFS(I13:I287, "Drag Over & Show"),"") -> 0 | H7: Shows: | I7: =IFERROR(SUM(F2:F7),"") -> 34 | K7: Conducted Rate: | L7: =IFERROR(I8/I6,"") -> 0.80952381 | N7: Value | O7: =IFERROR(COUNTIFS(N14:N287, "value"),"") -> 0 | Q7: Facebook Ads | R7: =IFERROR(COUNTIF(H13:H286,Q7),"") -> 0 | S7: Google | T7: =IFERROR(COUNTIF(H13:H286,S7),"") -> 0
B8: Total Lost : | C8: =COUNTIF(I13:I286,"offer & didn't buy")+countif(I13:I286,"deposit")+countif(I13:I286,"bad fit & no offer") -> 16 | E8: Rescheduled: | F8: =IFERROR(COUNTIFS(I13:I287, "Rescheduled"),"") -> 2 | H8: Calls: | I8: =IFERROR(SUM(F2:F6),"") -> 34 | Q8: LinkedIn | R8: =IFERROR(COUNTIF(H13:H286,Q8),"") -> 0 | S8: Referral | T8: =IFERROR(COUNTIF(H13:H286,S8),"") -> 0
B9: Closing % : | C9: =iferror(SUM(C7/C6),"") -> 0.52941176 | E9: Cancelled: | F9: =IFERROR(COUNTIFS(I13:I287, "Cancelled"),"") -> 3 | H9: Offers: | I9: =IFERROR(sum(F2:F5),"") -> 34
C10: =C3/C6 -> 4764.7059 | E10: No-Show: | F10: =IFERROR(COUNTIFS(I13:I287, "No-Show"),"") -> 3 | H10: Deals | I10: =F2+F3 -> 18
B12: Date | C12: Name | E12: Phone No. | F12: Ig navn | H12: Source | I12: Outcome | K12: Revenue | L12: Cash | N12: Objection | O12: Objection Notes | Q12: Length | R12: Recording Link | S12: Follow Up/Next Steps | T12: Call Summary
B13: 1. Juli | C13: Emma Dybdal Knudsen | E13: 28964056 | F13: https://www.instagram.com/emma__knudsen/ | H13: Setter | I13: Split-pay | K13: 9000 | L13: 3000 | N13: Money | O13: Skulle tjekke om det kunne lade sig gøre, mistanke om der er noget fear | Q13: 5 måneder | S13: Closed | T13: Syntes vi havde en virkeligt god snak, hun var så tæt på, men skulle lige tænke over det økonomiske. Ringer til hende igen i morgen
B14: 4. juli | C14: Amma Kvist | E14: 54320193 | F14: https://www.instagram.com/a_kvist/ | H14: Setter | I14: Split-pay | K14: 9000 | L14: 3000 | Q14: 5 måneder | S14: Closed | T14: Hun havde egenligt sagt nu nok ikke havde pengene, men havde slet ingen objections, så hun må jo have være solgt. Hun havde ingen internet, så hun kunne ikke svare på mailsene, men vil gøre det i dag
B15: 6. juli | C15: Mia Rørdam Støckel | E15: 42910033 | F15: https://www.instagram.com/miastockel/ | H15: Setter | I15: Split-pay | K15: 9000 | L15: 2800 | Q15: 5 måneder | S15: Closed | T15: Hun var bare klar på der skulle ske noget, havde lidt en objection om hendes arbejde fyldte en del men, fik hende i gang
B16: 7. juli | C16: Mathilde Knudsen | E16: 29275838 | F16: @matildeknudsen04 | H16: Setter | I16: Offer & Didn't Buy | N16: Partner | O16: Skulle vende den med forældrene og så vil hun tænke over det til i morgen | S16: X | T16: Fik et depositum, lød virkeligt hooked, men skulle så lige vende den med forældrene og ville gerne have pengene igen for en sikkerhedsskyld. Følte allerede hun var solgt, så challenged hende ikke nok og sprang over nogle spørgsmål og dykkede ikke nok ned i hendes pain og især hendes commitment og motivation
B17: 8. juli | C17: Marie Christina Gryndahl | E17: 20949289 | F17: https://www.instagram.com/mariechristina75/ | H17: Setter | I17: Offer & Didn't Buy | N17: Time | O17: Hun sagde tiden ikke var den rigtige, det var meget på tapetet, mistænker også fear | S17: X | T17: Var allerede fra startet ikke afklaret med det var noget hun ville det her. Var en hård nød at knække. Kunne sku ikke få hende solgt
B18: 8. juli | C18: Nanna Cajer | E18: 25734947 | F18: https://www.instagram.com/nannacajar/ | H18: Setter | I18: Offer & Didn't Buy | N18: Money | O18: Skulle vende den med sin bankrådgiver | S18: X | T18: Lød meget positivt, hun ville vende tilbage i morgen i forhold til hvad bankrådgiveren siger, hun mente selv, det kunne lade sig gøre.
B19: 9. juli | C19: Helle Toft Hansen | E19: 53620100 | F19: helle_t_hansen | H19: Setter | I19: Full-Pay | K19: 9000 | L19: 9000 | Q19: 5 måneder | S19: Closed | T19: Klasse samtale, energi var der bare og tonailty spillede. Vigtigst af alt jeg var hjælpende
B20: 9. juli | C20: Mads Gøsta Brøgger | E20: 29888407 | F20: @kunmads | H20: Setter | I20: Full-Pay | K20: 9000 | L20: 9000 | Q20: 5 måneder | S20: Closed | T20: Skulle lige flytte rundt på nogle penge, ville sende når han kom hjem i aften
B21: 10. juli | C21: Maya B Laursen | E21: 22877779 | F21: https://www.instagram.com/mayabetaklaursen/ | H21: Setter | I21: Offer & Didn't Buy | L21: 1500 | N21: Fear | S21: X | T21: Hun skulle lige have tænker over det, hun var ikke i tvivl om værdien og hun havde pengene. Skulle have spurgt, hvad det var hun skulle tænke over, i stedet for at gå for deposit
B22: 11. juli | C22: Merle Iversen | E22: 25696521 | F22: https://www.instagram.com/merle_iversen_/ | H22: Setter | I22: No-Show
B23: 13. juli | C23: Mikkel Lohse | E23: 21578559 | F23: https://www.instagram.com/lohse_fyren/ | H23: Setter | I23: Rescheduled
B24: 14. juli | C24: Lea Marie W. Wesselhoff | E24: 27129310 | F24: https://www.instagram.com/leawesselhoff/ | H24: Setter | I24: Cancelled
B25: 14. juli | C25: Benjamin Kyoo Dysager | E25: 61462357 | F25: https://www.instagram.com/benjamin_dysager/ | H25: Setter | I25: Cancelled
B26: 14. juli | C26: August Rothstein | E26: 30499574 | F26: https://www.instagram.com/august_rothstein/ | H26: Setter | I26: Offer & Didn't Buy | N26: Money | O26: havde sagt han ikke havde pengene at de ville være et problem på forhånd er kun 17 | S26: Follow Up Set | T26: God snak, følger egenligt jeg fik ham solgt, men jo ikke nok kan man sige. Kunne godt have skubbet mere på i forhold til at han ikke havde pengene, men han siger 100 eller 500 kr. ville ødelægge hans budget, kunne først gøre noget d. 1 august
B27: 14. juli | C27: Mathilde Sund | E27: 30560719 | F27: https://www.instagram.com/mathilde_dannow/ | H27: Setter | I27: Offer & Didn't Buy | N27: Money | O27: På SU havde ikke pengene | S27: Follow Up Set | T27: Kunne nok godt få hende solgt mere på og fundet mere pain. Når alt kom til alt havde hun bare ikke pengene, sad med hende i 15-20 min for at prøve at få det til at lade sig gøre, ved ikke lige hvad jeg skulle gøre i sådan en situation ellers. Følger op på hende på om et par måneder, det var det vi aftalte
B28: 14. juli | C28: Jakob Haakenstad | E28: 25778050 | F28: https://www.instagram.com/jakob_haakenstad/ | H28: Setter | I28: Split-pay | K28: 9000 | L28: 1500 | Q28: 5 måneder | S28: Closed | T28: Havde ikke pengene nu, fik først løn d. 1 august så der kommer 2500 kr. mere ind
B29: 15. juli | C29: Maria Thygsen | E29: 51896148 | F29: https://www.instagram.com/thygesen88/ | H29: Setter | I29: Offer & Didn't Buy | N29: Money | O29: Hun havde bare ikke pegene | S29: Follow Up Set | T29: Vender tilbage til hende d. 1 september
B30: 15. juli | C30: Line Svendsen | E30: 60156529 | F30: https://www.instagram.com/linelindgaardsvendsen/ | H30: Setter | I30: Rescheduled | S30: Follow Up
B31: 15. juli | C31: Johanne Fredslund | E31: 61683219 | F31: https://www.instagram.com/johanneaagaardd/ | H31: Setter | I31: Offer & Didn't Buy | N31: Money | O31: Havde ikke pengene | S31: X | T31: Syntes det var en svær snak, tænker hun var mere nysgerrig på en samtale en villig til at gøre noget. Klart pengene der holdte hende tilbage
B32: 16. Juli | C32: Heidi Henriksen | E32: 53614922 | F32: @henriksen1397 | H32: Setter | I32: Offer & Didn't Buy | N32: Money | O32: Havde ikke pengene | S32: Follow Up Set | T32: Skal snakke med hende igen om en uge, for at se om hun kan skaffe pengene. Skulle have dykket mere ned i hendes pain hun nævnte hun følte sig grim, skulle bare have stukket den fucking kniv ind, fandme dumt
B33: 17. juli | C33: Rebecca Storm Olesen | E33: 42607807 | F33: Rebecca_s_olesen | H33: Setter | I33: Split-pay | K33: 9000 | L33: 1500 | Q33: 5 måneder | S33: Closed
B34: 20. Juli | C34: Christian Andersen | E34: 51863021 | F34: candersen725@gmail.com | H34: Landing page | I34: Full-Pay | K34: 9000 | L34: 9000 | Q34: 5 måneder | S34: Closed
B35: 21. juli | C35: Gustav Jeremiassen | E35: 71703230 | F35: @gustavjeremiassen | H35: Setter | I35: Full-Pay | K35: 9000 | L35: 9000 | Q35: 5 måneder | S35: Closed
B36: 21. juli | C36: Mikkel Lohse | E36: 21578559 | F36: https://www.instagram.com/lohse_fyren/ | H36: Setter | I36: No-Show
B37: 21. juli | C37: Julie Lorenzen | E37: 26937770 | F37: @julielorenzen24 | H37: Setter | I37: Cancelled
B38: 22. juli | C38: Kristoffer Wiedemann | E38: 28629575 | F38: kristofferwiedemann@gmail.com | H38: Landing page | I38: Full-Pay | K38: 9000 | L38: 9000 | Q38: 5 måneder
B39: 22. juli | C39: Lise Kjærsgaard | E39: 20778306 | F39: @lisekg | H39: Setter | I39: Offer & Didn't Buy | N39: Money | O39: Hun havde brug for at afdække markedet, siger hun er sådan hun ikke gør noget impulsivt | S39: Follow Up Set | T39: Snakke med hende igen 3. august. Får hende jo klart ikke solgt godt nok. Hun sagde pengene ikke var et problem, men det skulle priorteres, kunne godt have fået kørt det på en bedre måde efter det, og faktisk spurgt hvad var mest værd. Fik presset hende for meget i stedet for.
B40: 23. juli | C40: Laura Mearun | E40: 41914040 | F40: @lauraraun | H40: Setter | I40: Offer & Didn't Buy | N40: Money | O40: Nåede ikke objection handling fordi hun skulle til læge. WTF! | S40: X | T40: Lidt en mærkeligt snak, gav ikke ret meget af sig selv og forstod ikke hvad jeg spurgte om. Havde ikke sat tid af til snakken
B41: 25. juli | C41: Ida Hakansson | E41: 30 49 41 72 | F41: https://www.instagram.com/idamarie.hakansson/ | H41: Setter | I41: Offer & Didn't Buy | N41: Money | O41: 100 procent pengene | S41: Follow Up Set | T41: Har en rigtigt god fornemmelse med den her follow up
B42: 25. juli | C42: Ciano kristensen | E42: 60197359 | F42: ciakristensen@gmail.com | H42: Landing page | I42: Deposit | L42: 250 | N42: Money | O42: Skulle vende den med mor, der havde styr på budgettet | S42: Deposit (Follow Up Set) | T42: Han ville super gerne, men skulle lige have vente økonomien han sagde han kunne finde de første 1000 kr. fik et symbols deposit på 250 kr. for at vise det var noget han ville
B43: 25. juli | C43: Mathias Hyldager | E43: 53 28 89 52 | F43: @hyldagerrn | H43: Setter | I43: No-Show
B44: 26. juli | C44: Nanna Kjeldsen | E44: 41 44 69 79 | F44: https://www.instagram.com/nanna_kjeldsen_/ | H44: Setter | I44: Split-pay | K44: 9000 | L44: 1500 | Q44: 5 måneder | S44: Closed
B45: 27. juli | C45: Kristian Antonsen | E45: 42 26 10 71 | F45: https://www.instagram.com/kristianantonsen82/ | H45: Setter | I45: Split-pay | K45: 9000 | L45: 1500 | Q45: 5 måneder | S45: Closed
B46: 27. juli | C46: Tobias Poulsen | E46: 51 91 29 03 | F46: https://www.instagram.com/tobiaspoulsen_/ | H46: Setter | I46: Split-pay | K46: 9000 | L46: 1500 | Q46: 5 måneder | S46: Closed
B47: 28. juli | C47: Lucas Lauridsen | E47: 22 59 64 43 | F47: https://www.instagram.com/lauridsenlucas/ | H47: Setter | I47: Full-Pay | K47: 9000 | L47: 9000 | Q47: 5 måneder
B48: 28. juli | C48: Anja Marker Tuet | E48: 24 63 49 28 | F48: https://www.instagram.com/anjamaerker/ | H48: Setter | I48: Split-pay | K48: 9000 | L48: 1500 | Q48: 5 måneder | S48: Closed
B49: 29. juli | C49: Rosa Schmidt | E49: 93 88 54 23 | H49: Landing page | I49: Offer & Didn't Buy | N49: Partner | O49: Var under 18, så havde mor med på samtalen og skulle lige vendes i familien | S49: X | T49: Rosa som det handlede om var solgt, men hendes mor var heller ikke, var ikke helt sikker på hvordan den skulle tackles
B50: 29. juli | C50: Mark Lykke | E50: 22 45 47 69 | F50: https://www.instagram.com/mark5900/ | H50: Setter | I50: Split-pay | K50: 9000 | L50: 3000 | Q50: 5 måneder | S50: Closed
B51: 29. juli | C51: Ziggy Saaby Nielsen | E51: 42 31 12 11 | F51: https://www.instagram.com/ziggysaaby/ | H51: Setter | I51: Offer & Didn't Buy | N51: Money | O51: Ville være 100 på han havde pengene, fik først et job til september | S51: Follow Up Set | T51: Havde ikke kongens mønt sagde han havde 90 kroner på kortet lige nu. Vil fucking gerne, havde begået en fejl før, hvor han ikke havde pengene, så de ville han ikke begå igen. Ringer til ham 31. august
B52: 31. juli | C52: Camilla Fræhr Hansen | E52: 93 93 13 80 | F52: https://www.instagram.com/c_fraehr/ | H52: Setter | I52: Offer & Didn't Buy | N52: Partner | O52: Skulle vende økonomi med kærsten de havde fælles økonomi | S52: Follow Up Set | T52: Ringer til hende i morgen formiddag, skulle have dykket mere ned i partner f.eks spøge om "Det er selvfølelig, du skal bare snakke med dem, hvad ville der sker hvis partner sagde nej?, hvis partner ikke vil have du bruger penge, på at løse dit problem … hvad ville du så gøre?" Skulle også have haft mere commitment ud af hende og brugt mere tid der
B53: 31. juli | C53: Mads Konrad | E53: 28 55 11 73 | F53: https://www.instagram.com/madshkonrad/ | H53: Setter | I53: Full-Pay | K53: 9000 | L53: 9000 | S53: Closed
B54: 31. juli | C54: Albert Speth Hansen | E54: 25 38 52 02 | F54: https://www.instagram.com/albert_speth/ | H54: Setter | I54: Split-pay | K54: 9000 | L54: 3000 | S54: Closed

Sheet Aug
B1: Rep: | C1: Name | E1: Outcome | H1: KPIs% | K1: Show Rate | N1: Objections | Q1: Source | U1: Tracking
E2: Full-Pay: | F2: =IFERROR(COUNTIFS(I13:I287, "Full-Pay"),"") -> 3 | H2: Conversion Rate: | I2: =iferror(I10/I8,"") -> 0.4137931 | K2: Rescheduling Rate: | L2: =iferror(F8/I6,"") -> 0.03125 | N2: Think About It | O2: =IFERROR(COUNTIFS(N13:N286, "think about it"),"") -> 2 | Q2: Reschedule | R2: =IFERROR(COUNTIF(H13:H286,Q2),"") -> 0 | S2: Cold Call | T2: =IFERROR(COUNTIF(H13:H286,S2),"") -> 0
B3: Revenue | C3: =IFERROR(SUM(K13:K283),"") -> 111000 | E3: Split-Pay: | F3: =IFERROR(COUNTIFS(I13:I287, "Split-Pay"),"") -> 9 | H3: Offer To Close Rate: | I3: =IFERROR(I10/I9,"") -> 0.4137931 | K3: Cancellation Rate: | L3: =iferror(F9/I6,"") -> 0 | N3: Money | O3: =IFERROR(COUNTIFS(N13:N286, "money"),"") -> 9 | Q3: YouTube | R3: =IFERROR(COUNTIF(H13:H286,Q3),"") -> 0 | S3: Twitter | T3: =IFERROR(COUNTIF(H13:H286,S3),"") -> 0
B4: Cash | C4: =IFERROR(SUM(L13:L284),"") -> 43875 | E4: Deposits: | F4: =IFERROR(COUNTIFS(I13:I287, "Deposit"),"") -> 1 | H4: Call To Offer Rate: | I4: =IFERROR(I9/I8,"") -> 1 | K4: No-Shows Rate: | L4: =iferror(F10/I6,"") -> 0.0625 | N4: Time | O4: =IFERROR(COUNTIFS(N13:N286, "time"),"") -> 1 | Q4: YouTube Ads | R4: =IFERROR(COUNTIF(H13:H286,Q4),"") -> 0 | S4: Skool | T4: =IFERROR(COUNTIF(H13:H286,S4),"") -> 0
E5: Offer & Didn't Buy: | F5: =IFERROR(COUNTIFS(I13:I287, "Offer & Didn't Buy"),"") -> 16 | H5: Drag Over Rate: | I5: =IFERROR(F7/(C6+F7+F8),"") -> 0 | K5: Drag Over Rate: | L5: =iferror(F7/I6,"") -> 0 | N5: Partner | O5: =IFERROR(COUNTIFS(N13:N286, "partner"),"") -> 0 | Q5: Email | R5: =IFERROR(COUNTIF(H13:H286,Q5),"") -> 0 | S5: Instagram | T5: =IFERROR(COUNTIF(H13:H286,S5),"") -> 0
B6: Total Calls : | C6: =IFERROR(SUM(F2:F6),"") -> 29 | E6: Bad Fit & No Offer: | F6: =IFERROR(COUNTIFS(I13:I287, "Bad Fit & No Offer"),"") -> 0 | H6: Bookings: | I6: =IFERROR(SUM(F2:F10),"") -> 32 | K6: Show-Up Rate: | L6: =iferror(I7/I6,"") -> 0.90625 | N6: Fear | O6: =IFERROR(COUNTIFS(N13:N286, "fear"),"") -> 2 | Q6: Facebook | R6: =IFERROR(COUNTIF(H13:H286,Q6),"") -> 0 | S6: TikTok | T6: =IFERROR(COUNTIF(H13:H286,S6),"") -> 0
B7: Total Won : | C7: =IFERROR(F2+F3,"") -> 12 | E7: Drag Over & Show: | F7: =IFERROR(COUNTIFS(I13:I287, "Drag Over & Show"),"") -> 0 | H7: Shows: | I7: =IFERROR(SUM(F2:F7),"") -> 29 | K7: Conducted Rate: | L7: =IFERROR(I8/I6,"") -> 0.90625 | N7: Value | O7: =IFERROR(COUNTIFS(N14:N287, "value"),"") -> 3 | Q7: Facebook Ads | R7: =IFERROR(COUNTIF(H13:H286,Q7),"") -> 0 | S7: Google | T7: =IFERROR(COUNTIF(H13:H286,S7),"") -> 0
B8: Total Lost : | C8: =COUNTIF(I13:I286,"offer & didn't buy")+countif(I13:I286,"deposit")+countif(I13:I286,"bad fit & no offer") -> 17 | E8: Rescheduled: | F8: =IFERROR(COUNTIFS(I13:I287, "Rescheduled"),"") -> 1 | H8: Calls: | I8: =IFERROR(SUM(F2:F6),"") -> 29 | Q8: LinkedIn | R8: =IFERROR(COUNTIF(H13:H286,Q8),"") -> 0 | S8: Referral | T8: =IFERROR(COUNTIF(H13:H286,S8),"") -> 0
B9: Closing % : | C9: =iferror(SUM(C7/C6),"") -> 0.4137931 | E9: Cancelled: | F9: =IFERROR(COUNTIFS(I13:I287, "Cancelled"),"") -> 0 | H9: Offers: | I9: =IFERROR(sum(F2:F5),"") -> 29
B10: Rev per lead | C10: =C3/C6 -> 3827.5862 | E10: No-Show: | F10: =IFERROR(COUNTIFS(I13:I287, "No-Show"),"") -> 2 | H10: Deals | I10: =F2+F3 -> 12
B12: Date | C12: Name | E12: Phone No. | F12: IG | H12: Source | I12: Outcome | K12: Revenue | L12: Cash | N12: Objection | O12: Objection Notes | Q12: Length | R12: Recording Link | S12: Follow Up/Next Steps | T12: Call Summary
B13: 45870 | C13: Thomas Vasegaard | E13: 21 39 50 36 | F13: https://www.instagram.com/thomas_vasegaard/ | H13: Setter | I13: Offer & Didn't Buy | N13: Fear | O13: Lagde på da han skulle betale | S13: X
B14: 45880 | C14: Magnus Hagmann | E14: 29 87 42 00 | F14: https://www.instagram.com/magnus_hamann/ | H14: Setter | I14: Split-pay | K14: 13500 | L14: 3375 | Q14: 8 måneder | S14: Closed
B15: 45880 | C15: Zilas Andersen | E15: 21 22 09 53 | F15: https://www.instagram.com/zilaswinzini/ | H15: Setter | I15: Offer & Didn't Buy | L15: 500 | N15: Money | O15: Skulle finde ud af om mor kunne betale lidt til det og lige have den vendt med hende | S15: X | T15: Follow up onsdag kl 16
B16: 45880 | C16: Lukas Lind | E16: 23 93 79 21 | F16: https://www.instagram.com/lukas_lind_737/ | H16: Setter | I16: No-Show | S16: X
B17: 45880 | C17: Nicklas Burkal | E17: 20 35 41 33 | F17: https://www.instagram.com/nicklas.burkal/ | H17: Setter | I17: Full-Pay | K17: 9000 | L17: 3000 | Q17: 5 måneder | S17: Closed
B18: 45880 | C18: Oliver Rosenvinge | E18: 30 24 23 71 | F18: https://www.instagram.com/olirosenvinge/ | H18: Setter | I18: Rescheduled | S18: X
B19: 45881 | C19: Christian Rasmussen | E19: 22 89 44 83 | F19: https://www.instagram.com/_christian_rasmussen_/ | H19: Setter | I19: Offer & Didn't Buy | N19: Money | O19: Havde ikke pengene sagde han kun havde et par 100 om måneden | S19: X | T19: Vidste på forhånd han nok ikke havde pengene og sagde det ogsåp tidligt i samtalen, men kørte på alligvel
B20: 45882 | C20: Mikkel Overgaard Vængtoft | E20: 22 42 65 14 | F20: https://www.instagram.com/mikkelovergaardvaengtoft/ | H20: Setter | I20: Full-Pay | K20: 9000 | L20: 9000 | Q20: 5 måneder | S20: Closed
B21: 45883 | C21: Ofelia Branco | E21: 60 20 08 33 | F21: https://www.instagram.com/ofelia_branco7/ | H21: Setter | I21: Offer & Didn't Buy | S21: X
B22: 45883 | C22: Mikkel Vielsted | E22: 22302167 | H22: Landing page | I22: Split-pay | K22: 9000 | L22: 3000 | Q22: 5 måneder | S22: Closed
B23: 45885 | C23: Cathrine Ottzen | E23: 21 90 50 48 | F23: https://www.instagram.com/cath_ottzen/ | H23: Setter | I23: Split-pay | K23: 9000 | L23: 3000 | Q23: 5 måneder | S23: Closed
B24: 45886 | C24: Andreas Olesen | E24: 24 67 36 87 | F24: https://www.instagram.com/andreas.ole/ | H24: Setter | I24: Split-pay | K24: 9000 | L24: 3000 | Q24: 5 måneder | S24: Closed
B25: 45887 | C25: Victoria Taulbæk | E25: 21 22 17 85 | F25: https://www.instagram.com/victoriataulbaek/ | H25: Setter | I25: Offer & Didn't Buy | N25: Money | O25: Var alt for mange penge | S25: X | T25: Ikke det rigtige fit, hun var fast besluttet på hun kun skulle have en træningsplan, og hun allerde følte hun havde meldt det kun var det for hendes økonomi slet ikke var til det. Så hun var egenligt lidt ærgerlig over at have brug tid på det når vi ikke kunne imødekomme hendes behov
B26: 45887 | C26: Brit Knudsen | E26: 60 12 59 75 | F26: https://www.instagram.com/brit_knudsen/ | H26: Setter | I26: No-Show | S26: Follow Up
B27: 45888 | C27: Mikkel Holm | E27: 30 95 89 69 | F27: https://www.instagram.com/mikkelholm__/ | H27: Setter | I27: Offer & Didn't Buy | N27: Think About It | S27: X | T27: Han ville fucking skulle bare tænke over det og sove på den kunne ikke få ham overbevidt om han bare skulle gøre
B28: 45888 | C28: Arnaq Pjettursson | E28: 28 96 98 67 | F28: https://www.instagram.com/arnaqpjettursson/ | H28: Setter | I28: Offer & Didn't Buy | N28: Time | O28: Skulle til Grønland | S28: X | T28: Hun starter op 1. september, Modtog en SMS her til aften, så havde hun bare lige glemt hun skulle på Grønland til sin hjemby så det kunne ikke lade sig gøre alligevel
B29: 45889 | C29: Signe Holck | E29: 22 43 44 30 | F29: https://www.instagram.com/signeholck93/ | H29: Setter | I29: Offer & Didn't Buy | N29: Money | O29: Hun siger hun skal tænke over det, men det nok faktisk var pengene | S29: Follow Up Set | T29: Hun vil super gerne også noget der var vigtigt for hende at finde en løsning på, hun skulle bare lige vende den om det var det hun skulle. Følger op på hende 5. september
B30: 45889 | C30: Kristine Aagaard | E30: 30 29 33 30 | F30: https://www.instagram.com/kristineaagaard/ | H30: Setter | I30: Offer & Didn't Buy | N30: Value | O30: Vidste ikke om det ville være pengene værd i forhold til hvor hun stod. Vil også rigtigt gerne have noget på skrift | S30: X | T30: Har aftalt at ringe til hende om en uge eller 2. Syntes egenligt jeg finder noget pain og hun havde et mål om at stå skarpt til sit bryllup, men vidste ikke om det værd pengene, og vil gerne undersøge andre muligheder og om hun kunne gøre det selv eller der var et alternativ
B31: 45891 | C31: Emma Juliane | E31: 25 79 76 90 | F31: https://www.instagram.com/emma_juliane05/ | H31: Setter | I31: Split-pay | K31: 7500 | L31: 3000 | N31: Money | O31: Skulle være sikker på det kunne løbe rundt og have hjælp af mor til at få lagt et budget | Q31: Indtil 1. december | S31: Closed | T31: Var frisk på det hele syntes det var det helt rigtige, hun skulle bare være sikker på hun kunne få det til at ske økonomisk, fordi hun havde en meget ustabil inkomst. Ringer til hende i morgen før kl 13
B32: 45891 | C32: Simone Schønning Larsen | E32: 29 87 58 50 | F32: https://www.instagram.com/simone_schonning1/ | H32: Setter | I32: Offer & Didn't Buy | N32: Money | O32: Sagde det var pengene, men var noget fear | S32: X | T32: Ringer på mandag til hende kl 16. Syntes snakken var god og hun var klar og sagde egenligt ja, men så kom undskuldninger og fik dem krydset godt af, det var helt irrationelt at hun skulle tænke over det
B33: 45892 | C33: Leonie Simsch | E33: 71 48 71 43 | F33: https://www.instagram.com/leoniesimsch/ | H33: Setter | I33: Split-pay | K33: 9000 | L33: 3000 | N33: Value | O33: Om det virkeligt var noget hun ville prioriterer frem for en skiferie eller en racercykel | Q33: 5 måneder | S33: Closed | T33: Syntes vi havde en god snak og fik lagt en rigtigt god plan for hende, hendes store bekymring var om det var pengene værd, hun siger egenligt det ville være og var klar til at gennemgå økonomien med mig, men det sagde hun at hun ikke havde tid til, så det gør vi på tirsdag
B34: 45892 | C34: Sophia de Linde | E34: 31 38 06 05 | F34: https://www.instagram.com/sophiadelinde/ | H34: Setter | I34: Split-pay | K34: 9000 | L34: 3000 | Q34: 5 måneder | S34: Closed | T34: Så god snak fik hende bar solgt
B35: 45892 | C35: Sara Eram | E35: 61 67 10 07 | F35: https://www.instagram.com/s_eram/ | H35: Setter | I35: Offer & Didn't Buy | N35: Fear | O35: Hun havde meget svært ved at få hjælp ude fra havde altid klaret tingene selv | S35: X | T35: Det var det rigtige for hende og hun fik Tony Robins talen og det hele og var milimeter fra at sige ja, men hun har bare så svært ved at be om hjælp fordi hun ser sig selv som den her stærke kvinde, der ikke har brug for hjælp
B36: 45894 | C36: Emilia Børresen | E36: 60 61 51 04 | F36: https://www.instagram.com/_emilia_borresen_/ | H36: Setter | I36: Deposit
B37: 45894 | C37: Simon Sloth | E37: 61 71 24 73 | F37: https://www.instagram.com/simon_sloth_/ | H37: Landing page | I37: Offer & Didn't Buy | N37: Think About It | O37: Havde allerede booket møde med en anden coach | S37: X | T37: Han sagde det var det helt rigtige for ham, men ville hører hvad en anden kunne tilbyde og om det bare var det "samme" og så gå med det billigste. Spørger ham om det det billigste også var det bedst "nej det var det jo ikke så kunen det være man ikke gik lige små meget op i det. Follow up i morgen kl 12
B38: 45895 | C38: Christina Vammen Andreassen | E38: 28 19 88 56 | F38: https://www.instagram.com/christinavammen88/ | H38: Setter | I38: Offer & Didn't Buy | N38: Money | O38: Nogle måneder havde hun pengene, men andre havde hun ikke | S38: Follow Up Set | T38: Hun var så klar og syntes det var mega fedt. Hun var bare ikke sikker på om hun kunne skrabe 1500 kr. sammen alle månederne da hun pt gik sygmeldt. Så vi har lagt en plan for hun laver et budget og jeg ringer til hende igen d. 1 Sep. Skulle have været lidt bedre i objection handling følg nu bare det script og få krydset en ting af ad gangen
B39: 45897 | C39: Mette Lassen Matthiasen | E39: 22 77 67 77 | F39: https://www.instagram.com/mettelassen86/ | H39: Setter | I39: Offer & Didn't Buy | N39: Value | O39: At den energi hun havde set og faktisk købt ind i fra både mig men også Daniel var det hun fik | S39: Follow Up Set | T39: Fandt super meget pain og brugt lang tid på det, og hun siger det lød som det rigtige for hende især efter tidligere dårlige oplevelser med coaching, det her var meget mere hende. Kunne ikke nå at negotiate, fordi hun fakitsk var på arbejde og ikke havde mere tid. Booker en snak ind til hende med Daniel på mandag
B40: 45897 | C40: Mia Vejrum | E40: 25 70 06 44 | F40: https://www.instagram.com/mia_vejrum/ | H40: Setter | I40: Split-pay | K40: 9000 | L40: 500 | Q40: 5 måneder | S40: Closed | T40: Syntes det var en mega god snak, kom hurtigt til pointe og hendes pain, og fik hende bare solgt godt. De kunne først betale til oktober, men kunne smide 500 kr. nu og så komme i gang, og så betale første invoice til oktober
B41: 45897 | C41: Frederik Lüth | E41: 60 53 06 09 | F41: https://www.instagram.com/friddeluth?igsh=MTRrcGg4MGM3cHFmdQ== | H41: Setter | I41: Offer & Didn't Buy | N41: Money | O41: Syntes det var mange penge og skulle tænke over det for han budget var ret høj | S41: X | T41: Vi vibede ret godt og lavede nogle jokes undervejs, han ville passe perfekt ind. Var svær at finde noget pain ved, men fandt da noget, kunne sagtens have været bedre. Kunne godt have objection handlede bedre også
B42: 45897 | C42: Mathias Jensen | E42: 40 32 71 96 | H42: Setter | I42: Split-pay | K42: 9000 | L42: 500 | Q42: 5 måneder | S42: Closed | T42: Var bare med ved siden af Mia (kæresten) sagde ikke så meget
B43: 45900 | C43: Nikolai Rahbech Højgaard | E43: 27 79 63 25 | F43: https://www.instagram.com/nikolai1702/ | H43: Setter | I43: Full-Pay | K43: 9000 | L43: 9000 | Q43: 5 måneder | S43: Closed | T43: Havde sagt i DM'en han ikke rigitgt havde pengene. Så søgte bare efter alt det pain jeg kunne og labeled ham som en der udskød ting om det var noget han ville blive ved med og konsekvenserne ved ikke at gøre det
B44: 45900 | C44: Magnus Helkiær | E44: 51 86 36 56 | F44: https://www.instagram.com/m.helkiaer/ | H44: Setter | I44: Offer & Didn't Buy | N44: Money | O44: Skulle tjekke hvor meget han kunne smide nu så han kunne komme i gang | S44: Follow Up Set | T44: Ringer til ham igen slut september. Super godt fit han var klar på det hele skulle bare lige have finanserne på plads. Kunne godt have været hårde ved ham da han sagde han bar skinny og rankler, altid var ham man kunne skubbe væk på fodboldbanen "Hvordan er det som mand og være ham?" Skulle bare have fundet mere pain

Sheet Sep
B1: Rep: | C1: Name | E1: Anton KPI's | H1: Outcome | K1: KPIs% | N1: Show Rate | Q1: Objections | S1: kvinde/mand
E2: Rev per call | F2: =C3/C6 -> 3319.6721 | H2: Full-Pay: | I2: =IFERROR(COUNTIFS(I13:I286, "Full-Pay"),"") -> 1 | K2: Conversion Rate: | L2: =iferror(L10/L8,"") -> 0.31147541 | N2: Rescheduling Rate: | O2: =iferror(I8/L6,"") -> 0.071428571 | Q2: Think About It | R2: =IFERROR(COUNTIFS(N13:N285, "think about it"),"") -> 1 | S2: Kvinde kald | T2: =COUNTIF(F13:F359,"Kvinde") -> 0
B3: Revenue | C3: =IFERROR(SUM(K13:K282),"") -> 202500 | E3: Cash per call | F3: =C4/C6 -> 904.09836 | H3: Split-Pay: | I3: =IFERROR(COUNTIFS(I13:I286, "Split-Pay"),"") -> 18 | K3: Offer To Close Rate: | L3: =IFERROR(L10/L9,"") -> 0.3220339 | N3: Cancellation Rate: | O3: =iferror(I9/L6,"") -> 0.042857143 | Q3: Money | R3: =IFERROR(COUNTIFS(N13:N285, "money"),"") -> 26 | S3: Mande kald | T3: =COUNTIF(F13:F359,"Mand") -> 0
B4: Cash | C4: =IFERROR(SUM(L13:L283),"") -> 55150 | E4: Cash upfront % | F4: =C4/C3*100 -> 27.234568 | H4: Deposits: | I4: =IFERROR(COUNTIFS(I13:I286, "Deposit"),"") -> 8 | K4: Call To Offer Rate: | L4: =IFERROR(L9/L8,"") -> 0.96721311 | N4: No-Shows Rate: | O4: =iferror(I10/L6,"") -> 0.014285714 | Q4: Time | R4: =IFERROR(COUNTIFS(N13:N285, "time"),"") -> 6 | S4: Kvinde salg | T4: =COUNTIFS($F13:$F359,E2,$I13:$I359,"Split-pay","Full-pay") -> #N/A
E5: PIF % | F5: =I2/C7*100 -> 5.2631579 | H5: Offer & Didn't Buy: | I5: =IFERROR(COUNTIFS(I13:I286, "Offer & Didn't Buy"),"") -> 32 | K5: Drag Over Rate: | L5: =IFERROR(I7/(C6+I7+I8),"") -> 0 | N5: Drag Over Rate: | O5: =iferror(I7/L6,"") -> 0 | Q5: Partner | R5: =IFERROR(COUNTIFS(N13:N285, "partner"),"") -> 6 | S5: Mande salg | T5: =IFERROR(COUNTIF(G13:G285,S5),"") -> 0
B6: Total Calls : | C6: =IFERROR(SUM(I2:I6),"") -> 61 | E6: Average Binding | F6: =AVERAGE(Q13:Q103) -> 6.2222222 | H6: Bad Fit & No Offer: | I6: =IFERROR(COUNTIFS(I13:I286, "Bad Fit & No Offer"),"") -> 2 | K6: Bookings: | L6: =IFERROR(SUM(I2:I10),"") -> 70 | N6: Show-Up Rate: | O6: =iferror(L7/L6,"") -> 0.87142857 | Q6: Fear | R6: =IFERROR(COUNTIFS(N13:N285, "fear"),"") -> 3 | S6: Kvinde closing % | T6: =IFERROR(COUNTIF(G13:G285,S6),"") -> 0
B7: Total Won : | C7: =IFERROR(I2+I3,"") -> 19 | E7: Average deal | F7: =C3/C7 -> 10657.895 | H7: Drag Over & Show: | I7: =IFERROR(COUNTIFS(I13:I286, "Drag Over & Show"),"") -> 0 | K7: Shows: | L7: =IFERROR(SUM(I2:I7),"") -> 61 | N7: Conducted Rate: | O7: =IFERROR(L8/L6,"") -> 0.87142857 | Q7: Value | R7: =IFERROR(COUNTIFS(N14:N286, "value"),"") -> 0 | S7: Mande closing % | T7: =IFERROR(COUNTIF(G13:G285,S7),"") -> 0
B8: Total Lost : | C8: =COUNTIF(I13:I285,"offer & didn't buy")+countif(I13:I285,"deposit")+countif(I13:I285,"bad fit & no offer") -> 42 | E8: Average cash | F8: =C4/C7 -> 2902.6316 | H8: Rescheduled: | I8: =IFERROR(COUNTIFS(I13:I286, "Rescheduled"),"") -> 5 | K8: Calls: | L8: =IFERROR(SUM(I2:I6),"") -> 61
B9: Closing % : | C9: =iferror(SUM(C7/C6),"") -> 0.31147541 | H9: Cancelled: | I9: =IFERROR(COUNTIFS(I13:I286, "Cancelled"),"") -> 3 | K9: Offers: | L9: =IFERROR(sum(I2:I5),"") -> 59
H10: No-Show: | I10: =IFERROR(COUNTIFS(I13:I286, "No-Show"),"") -> 1 | K10: Deals | L10: =I2+I3 -> 19
B12: Date | C12: Name | E12: Phone No. | F12: Ig | H12: Source | I12: Outcome | K12: Revenue | L12: Cash | N12: Objection | O12: Objection Notes | Q12: Length | R12: Recording Link | S12: Follow Up/Next Steps | T12: Call Summary
B13: 45901 | C13: Mikkel Vielsted | E13: 22302167 | H13: Landing page | I13: Split-pay | K13: 9000 | L13: 3000 | Q13: 5 | S13: Closed
B14: 45902 | C14: Josephine Alexandra Abildtrup | E14: 51 15 03 22 | H14: Setter | I14: Full-Pay | K14: 9000 | L14: 9000 | Q14: 5 | S14: Closed
B15: 45902 | C15: Jonathan Mikkelsen | E15: 61 28 53 09 | H15: Setter | I15: Bad Fit & No Offer | N15: Partner | S15: Follow Up | T15: Han havde nogle fysiske og mentale udfordringer, og stod ikke selv for sin økonomi. Fandt rigtigt meget pain og han ville også gøre det, hvis han selv stod for sin økonomi, men det er desværre forældrene, der gør det. Så har aftalt han skriver til sin forældre, om de har tid. Han nævnte hans forældre var ligeglad med ham og hvordan han havde og de ikke ville støtte ham
B16: 45903 | C16: Jesper Stubkjær Hummelmose Brühl | E16: 28 34 95 83 | H16: Setter | I16: Offer & Didn't Buy | N16: Time | S16: Follow Up | T16: Sagde flere gange til at starte med at det ikke var et forløb han var ude i han det troede det var var en guidet snak, men syntes egenligt jeg fik ham overtalt og endte dag også med at pitche for ham, men han skulle føle sig klar mentalt og havde også en brækket hånd der skulle styr på. Var nødt til at afslutte samtalen fordi hans børn stod og råbte i baggrunden
B17: 45903 | C17: Lucas Denker | E17: 53 82 56 58 | H17: Setter | I17: No-Show | S17: Follow Up
B18: 45904 | C18: Emil Engel | E18: 20 72 55 62 | H18: Setter | I18: Bad Fit & No Offer | O18: Havde ingen intentioner om at starte op og mener det kun var "Daniel dert havde presset på i forhold til en samtale" | S18: Follow Up
B19: 45906 | C19: Linda Hvidberg Sørensen | E19: 24 22 88 47 | H19: Setter | I19: Split-pay | K19: 10500 | L19: 2650 | N19: Time | O19: Hun havde nogle blodprøver fra læge som hun lige skulle have svar på, på mandag | S19: Closed | T19: Ringer til hende igen på mandag
B20: 45906 | C20: Pola Karim | E20: 31 17 16 86 | H20: Setter | I20: Split-pay | K20: 10500 | L20: 3000 | Q20: 6 | S20: Closed
B21: 45907 | C21: Michael Rasmussen | E21: 60 27 73 39 | H21: Setter | I21: Offer & Didn't Buy | N21: Fear | S21: Follow Up | T21: Kunne ikke få sig selv til at gøre det og tage i mod hjælpen, gjorde alt der stod i min magt
B22: 45907 | C22: Magnus Lazarotti | E22: 30 86 51 86 | H22: Setter | I22: Offer & Didn't Buy | N22: Partner | O22: Det er han forældre der styrer hans økonomi | S22: Follow Up | T22: Han var så frisk på det, men var nervøs for hans forældre ikke ville se værdien i det og syntes det var for mange penge, så får et kald med ham og dem på onsdag eller i weekenden
B23: 45908 | C23: Mia Frederiksen | E23: 21 51 08 09 | H23: Setter | I23: Split-pay | K23: 13500 | L23: 3000 | Q23: 8 | S23: Closed
B24: 45908 | C24: Bertram A. Rosendal Fagerlind | E24: 25 19 17 27 | H24: Setter | I24: Offer & Didn't Buy | N24: Money | O24: Havde pengene, men hvis ha brugte dem på det her havde han ikke penge til noget andet | S24: Follow Up | T24: Ringer til ham igen i morgen. Syntes egenligt jeg var god på snakken. Han sagde han havde 100 kr. tilbage, hvis han brugte pengene på det så vil undersøge om han kunne tage noget fra opsparringen, men havde ikke selv adgang til den så skulle spørge en af sin forældre
B25: 45910 | C25: Therese S. Langfjord | E25: 42 83 04 42 | H25: Setter | I25: Offer & Didn't Buy | N25: Time | O25: En blanding af timing ifht. job og økonomien så hun var 100 procent klar | S25: Follow Up Set | T25: Follow-up Fredag kl 13. Hun ville sygt gerne hun skulle bare have alle brikkerne til at falde på plads, så følte faktisk ikke jeg ville presse hende for meget, for hun virkede virkeligt oprigtig og ærlig
B26: 45910 | C26: Anne Lê Karlsen | E26: 51 21 57 18 | H26: Setter | I26: Offer & Didn't Buy | N26: Money | O26: hende og kæresten stod midt i en flytning og hun havde ikke et arbejde, så hun ville gerne når de var flyttet | S26: Hot Follow Up | T26: Virkeligt et sludreshatol, føltes lidt som en terpai session, men hun siger flere gange hun gerne ville have programmet og alt den støtte det giver, men det ikke kunne lade sig gøre pga en flytning og dobbelt husleje, men hun ville igang når økonomien tillod det
B27: 45911 | C27: Mathias Hanen | E27: 22 72 62 15 | H27: Setter | I27: Rescheduled
B28: 45911 | C28: Peter Lørup | E28: 22 42 68 39 | H28: Setter | I28: Offer & Didn't Buy | N28: Money | O28: Havde ikke pengene før Oktober | S28: Follow Up | T28: Følger op på ham 23. september
B29: 45911 | C29: Johan Loch | E29: 22 67 61 17 | H29: Setter | I29: Split-pay | K29: 10500 | L29: 3000 | Q29: 6 | S29: Closed
B30: 45912 | C30: Frederik Duborg Juhl | E30: 29 84 21 21 | H30: Setter | I30: Cancelled | O30: Ville ikke når der var andre end Daniel
B31: 45913 | C31: Johanne Norrland Grauslund | E31: 71 70 06 17 | H31: Setter | I31: Offer & Didn't Buy | N31: Money | O31: Havde ikke et overblik over økonomien | S31: Follow Up Set | T31: Skulle undersøge økonomi fordi hun ikke havde fået sin første løn hende om det så kunne lade sig gøre, gik fra hun kun vil have kost til hun faktisk ville have hele pakkeb
B32: 45914 | C32: Clara Smidt | E32: 81 75 15 88 | H32: Setter | I32: Split-pay | K32: 10500 | L32: 3000 | Q32: 6 | S32: Closed | T32: Mega god samtale tror måske det var en af mine bedste samtaler, jeg stillte gode og præcise spørgsmål, så samtalen blev heller ikke for lang, men jeg fandt ud af de jeg skulle finde ud af
B33: 45914 | C33: Dmytro Torbynskyi | E33: 91 41 99 81 | H33: Setter | I33: Offer & Didn't Buy | N33: Think About It | S33: Follow Up Set | T33: Lidt et mystisk kald, syntes det var svært på engelsk når man har det hele i hovedet på dansk. Han vil gerne have et overblik over hvordan det så ud inde i appen så det sendte jeg videre til ham hører fra ham i morgen eller overmorgen
B34: 45914 | C34: Rolf Hansen | E34: 30 32 20 97 | H34: Landing page | I34: Rescheduled
B35: 45915 | C35: Kathrine Nordentoft | E35: 31518860 | H35: Landing page | I35: Split-pay | K35: 9000 | L35: 3000 | Q35: 5 | S35: Closed | T35: Rigtig god snak, syntes egenligt hun havde besluttet sig på forhånd, og så lavede jeg bare en god pitch til hende og var god i discovery
B36: 45915 | C36: Emil Christensen | E36: 60175300 | H36: Landing page | I36: Split-pay | K36: 10500 | L36: 3000 | Q36: 6 | S36: Closed
B37: 45915 | C37: ilyaas bashir | E37: 71 39 85 79 | H37: Setter | I37: Deposit | R37: booket ind | S37: Deposit (Follow Up Set) | T37: 18 år gammel som virkeligt gerne vil blive tilfreds med spejlbilledet der er hængemave og hængebryster og det er på tid at gøre noget både for synets skyld men også sundhedsmæssigt. Han vil gerne tabe 35-40 kg har af den grund bundet ham et år for vi er sikre på vi får ham helt i mål. Han bor stadigt hjemme, så vil selvfølgelig gerne spise aftensmad med forældrene og bare få redskaberne til hvordan det skal gribes an. Så bare en god og effektiv plan der holder ham motiveret og ikke smider håndklædet i ringen Han havde tidligere været på forløb, men syntes ikke han fik den støtte som han havde brug for, og det var vigtigt for ham Han får nogle indsprøjtninger ved lægen for at mindske appetitten, men det var ikke weegovy, en nog lignende
B38: 45916 | C38: Natalie Klamer | E38: 40 98 60 70 | H38: Setter | I38: Offer & Didn't Buy | N38: Partner | O38: Under 18 | R38: booket ind | S38: Follow Up | T38: Snakkede både med Natalie og kæresten. Lød begge to solgte men skulle vende den med forældrene, hører noget her til aften
B39: 45916 | C39: Pernille Jespersen | E39: 93 94 85 33 | H39: Setter | I39: Cancelled
B40: 45916 | C40: Magnus mejlvang grum | E40: 22113009 | H40: Setter | I40: Rescheduled
B41: 45917 | C41: Malou | E41: 60 88 46 01 | H41: Setter | I41: Offer & Didn't Buy | N41: Money | O41: Havde ikke overblik og økonomien, hun havde nogle udfordringer så hun får hjælp til at lægge budget | R41: Booket ind | S41: Follow Up | T41: Har follow-up med hende d. 25 kl 16:30. Hun lød super solgt og sagde det het ville være det helt rigtige for hende
B42: 45918 | C42: Kia Bodeholt | E42: 31 50 34 98 | H42: Setter | I42: Split-pay | K42: 10500 | L42: 1500 | Q42: 6 | R42: Booket ind | S42: Closed
B43: 45918 | C43: Frederik Flensborg | E43: 53 85 14 00 | H43: Setter | I43: Offer & Didn't Buy | N43: Money | O43: Skulle finde pengene | R43: Booket ind | S43: Follow Up Set | T43: Har follow-up med ham om en måned d. 21 oktober, han ville virkeligt gerne og ville finde pengene til det og så finder vi en løsning
B44: 45918 | C44: Carl Søgaard Vangsøe | E44: 22 37 43 12 | H44: Setter | I44: Offer & Didn't Buy | N44: Money | R44: Booket ind | S44: X | T44: Fik ham sku ikke solgt, føltes ikke som han så værdien i det og ikke noget han havde brug for
B45: 45918 | C45: Lukas Grejs | E45: 27 29 03 10 | H45: Setter | I45: Split-pay | K45: 9000 | L45: 1500 | Q45: 6 | S45: Closed
B46: 45918 | C46: Marcus Olsen | E46: 42212965 | H46: Setter | I46: Split-pay | K46: 9000 | L46: 1500 | Q46: 6 | S46: Closed
B47: 45918 | C47: Lucas Jørgensen | E47: 61 16 51 79 | H47: Setter | I47: Offer & Didn't Buy | N47: Money | O47: Under 18 så skulle vendes med forældrene | R47: Booket ind | S47: X | T47: Syntes snakken var god og jeg fik af solgt stod han selv for pengene havde han 100 procent gjort det
B48: 45919 | C48: Julie Wael Foss | E48: 51 80 20 25 | H48: Setter | I48: Split-pay | K48: 10500 | L48: 3000 | Q48: 6 | R48: Booket ind | S48: Closed
B49: 45919 | C49: Sascha Nielsen | E49: 25 78 87 38 | H49: Setter | I49: Offer & Didn't Buy | N49: Money | O49: Hun sagde hun skulle prioritere pengene og det godt kunne lade sig gøre, men hun også var typen der skulle tænke over det | S49: Follow Up Set | T49: Mega godt snak og hun lød virkeligt postiv på det hele og at det faktisk var noget for hende, men det hele var kommet meget pludseligt, så har follow - up med hende sødan d.21 om eftermiddagen, så finder vi en løsning på det der
B50: 45921 | C50: Mikkel Flygenring Mørch | E50: 53 85 85 60 | F50: https://www.instagram.com/mikkel_moerch06/ | H50: Setter | I50: Offer & Didn't Buy | N50: Partner | O50: Skulle vende den med forældrene og have deres Bekræftelse | S50: Follow Up | T50: Han giver lyd tilbage til mig i aften, ville super gerne men skulle have forældrenes accept. Han sagde flere gange han tit var en som udskød ting, så det kunne jeg 100 procent have challegende ham på
B51: 45921 | C51: Sebastian Lund | E51: 22 86 84 89 | F51: https://www.instagram.com/sebastianlund.28/ | H51: Setter | I51: Offer & Didn't Buy | N51: Money | O51: Havde ikke pengene | S51: Follow Up | T51: Han sagde det var noget som betød rigtigt meget for ham, men han havde ikke pengene til
B52: 45921 | C52: Martha-Malou Sørensen | E52: 50 91 13 15 | F52: https://www.instagram.com/marthassorensen/ | H52: Setter | I52: Deposit | N52: Money | O52: Havde ikke pengene før d. 1 oktober | S52: Deposit (Follow Up Set) | T52: Super god snak mega frisk på at starte op her til d.1 oktober
B53: 45921 | C53: Melissa Sofia | E53: 27 28 53 78 | F53: https://www.instagram.com/melissatheibel_/ | H53: Setter | I53: Offer & Didn't Buy | N53: Time | O53: Det passede dårligt nu i forhold til hun skulle have helt styr på helbredet og nogle eksamner | S53: Follow Up Set | T53: Følger op på hende 27. Oktober kl 13:30. Super god snak og hun vil super gerne, så fik hende solgt godt så det blev noget på hendes præmisser. Hun var histamintolerant og havde pots. Ville gerne tabe 3-5 kg, bygge noget muskelmasse så hun kan føle sig sund og rask med en sund krop
B54: 45921 | C54: Emil Bejder | E54: 42 23 06 13 | F54: https://www.instagram.com/emilbejder/ | H54: Setter | I54: Deposit | N54: Money | O54: Har først penge til den første | S54: Deposit (Follow Up Set) | T54: Har først pengene til den første
B55: 45922 | C55: Sophia Seidelin Nordby | E55: 20 94 82 28 | F55: https://www.instagram.com/sophiasnordby/ | H55: Setter | I55: Offer & Didn't Buy | N55: Money | O55: Skulle have lagt budgettet om, så det kunne lade sig gøre | R55: Booket ind | S55: Follow Up Set | T55: Ringer til hende igen på fredag kl 9. Det lød helt sikkert som om det var noget for hende, men pengene skulle bare findes til det
B56: 45922 | C56: Matti Christoffersen | E56: 53 69 64 61 | F56: https://www.instagram.com/matti_christoffersen/ | H56: Setter | I56: Deposit | N56: Money | O56: Ingen penge før den 1. oktober | S56: Deposit (Follow Up Set) | T56: Totalt solgt skal bare blive et rigtigt møgsvin, starter op d. 1 oktober
B57: 45922 | C57: Osvald Lynge Larsen | E57: 60 17 77 94 | F57: https://www.instagram.com/detjoikosvald/ | H57: Setter | I57: Offer & Didn't Buy | N57: Partner | O57: Det var moren der skulle lægge pengene | S57: Follow Up | T57: Ringer til mig igen i aften
B58: 45922 | C58: Anja Lykke Vögeli | E58: 61 33 77 73 | F58: https://www.instagram.com/anjavogeli/ | H58: Setter | I58: Cancelled
B59: 45922 | C59: Tobias Rosengreen | E59: 26 78 00 11 | F59: https://www.instagram.com/tobias_rosengreen/ | H59: Setter | I59: Deposit | N59: Money | O59: Først penge d.1 oktober | S59: Deposit (Follow Up Set) | T59: Starter op d. 1 oktober
B60: 45922 | C60: Marius | E60: 25 39 78 00 | F60: https://www.instagram.com/marsiusis/ | H60: Setter | I60: Deposit | N60: Money | O60: Havde første penge til November | S60: Deposit (Follow Up Set) | T60: Starter op d. 1 november
B61: 45923 | C61: Martin Herholdt Friederichsen | E61: 28 26 80 91 | F61: https://www.instagram.com/friederichsenmartin/ | H61: Setter | I61: Offer & Didn't Buy | N61: Money | O61: Har ikke pengene lige nu pga han betaler til wegovy | S61: Follow Up Set | T61: Skal snakke hame ham igen til d.1 oktober, hvor han skal op til sygeplejerske og hører om han skal forsætte på wegovy, hvis ikke så har han pengene til at komme i gang
B62: 45923 | C62: Noah Raunholt Herlufsen | E62: 91 36 52 22 | F62: https://www.instagram.com/noah_raunholt/ | H62: Setter | I62: Offer & Didn't Buy | N62: Money | O62: Har først penge til November | S62: Follow Up Set | T62: Snakker med ham igen d. 1 November hvor han har fået mere i løn. Han vil så gerne i gang med at bygge noget muskelmasse, så han kan blive tilfreds og så skarpt til sommer når han skal på ferie med gutterne
B63: 45923 | C63: Tina Thomsen | E63: 23 36 64 19 | F63: https://www.instagram.com/tina_lthomsen/ | H63: Setter | I63: Deposit | N63: Money | O63: Betaler til december | S63: Deposit (Follow Up Set) | T63: Ringer til hende i morgen kl 16. Hun følte det var det som skulle til og det eneste hun ikke havde prøvet endnu
B64: 45925 | C64: Freja Thomsen | E64: 42 23 77 02 | F64: https://www.instagram.com/freja_marbo/ | H64: Setter | I64: Offer & Didn't Buy | N64: Partner | O64: Ville vende den med kæresten, men gjorde det alligvel | S64: Closed | T64: Mega god snak fik hende virkeligt solgt. Hvade først nogle money concerns, men dem fik vi clearet og vi fik også clearet at hun ville gøre det, hvis partneren sagde nej "Så måtte hun jo låne pengene, for det var virkeligt noget hun ville" Så kæmpe succes
B65: 45925 | C65: Christian Osther | E65: 22 89 04 50 | F65: https://www.instagram.com/christian_osther_/ | H65: Setter | I65: Offer & Didn't Buy | N65: Fear | O65: Skulle bare vende den med vennerne (havde en ven med en tidligere dårlig oplevelse) | S65: Follow Up Set | T65: Ringer til ham igen på lørdag kl. 12 - Ville super gerne og det hele lød god den skulle bare vendes fordig han havde en kammerat, der tidligere havde været i et dårligt forløb, så ville være sikker på han ikke bare hoppede ud i noget
B66: 45926 | C66: Asger Olsen | E66: 61 28 68 65 | F66: https://www.instagram.com/asgerolsen__/ | H66: Setter | I66: Offer & Didn't Buy | N66: Money | O66: Syntes det var mange penge | S66: X | T66: Har followup med ham på mandag kl 10:45. Ville fucking gerne men stod og skulle ud på en rejse til Januar, så pengene var lidt små
B67: 45926 | C67: Jeanette Borregaard Jensen | E67: 20 93 45 64 | F67: https://www.instagram.com/jeanette.borregaard.jensen/ | H67: Setter | I67: Split-pay | K67: 19500 | L67: 1500 | Q67: 12 | S67: Closed | T67: Var totalt på hendes niveau og satte mig totalt ind i hendes sted så hun følte hun blev hørt og set
B68: 45926 | C68: Gustav Hansen | E68: 24 75 09 24 | F68: https://www.instagram.com/gustavhansen79/ | H68: Setter | I68: Split-pay | K68: 10500 | L68: 3000 | Q68: 6 | S68: Closed | T68: Det var bare det helt rigtige for ham og var helt solgt
B69: 45928 | C69: Heidi Amos | E69: 22 16 66 02 | F69: https://www.instagram.com/heidi_amos/ | H69: Setter | I69: Split-pay | K69: 12000 | L69: 3000 | Q69: 7 | S69: Closed
B70: 45928 | C70: Mads Johansen | E70: 24 24 09 81 | F70: https://www.instagram.com/mads.valentin3/ | H70: Setter | I70: Offer & Didn't Buy | N70: Money | O70: Havde ikke et job, men kunne godt lade sig gøre, hvis han prioriterede det, så undersøger det til fredag | S70: Follow Up Set | T70: Ringer til ham igen på fredag kl 15, hvor vi har hans mor med. Ville så gerne og har søgt en coach længe, men følte ikke kemien var der og følte så det her var det rigtigt match for ham
B71: 45928 | C71: Gustav Vilfing | E71: 51 36 45 57 | F71: https://www.instagram.com/gustav.vilfing/ | H71: Setter | I71: Rescheduled
B72: 45928 | C72: Malene Møller | E72: 24 41 60 37 | F72: https://www.instagram.com/moeller.1992/ | H72: Setter | I72: Offer & Didn't Buy | N72: Time | O72: Skulle snakke med 2 andre coaches i morgen | S72: Follow Up Set | T72: Skal ringe til hende igen på tirsdag kl 16. Hun sagde hun havde en god fornemmelse med det hele og det for hende var det vigtigste at blive set og ikke bare være et nummer i rækken
B73: 45928 | C73: Daniel Bille | E73: 91 70 05 44 | F73: https://www.instagram.com/daniel_bille2300/ | H73: Setter | I73: Deposit | N73: Money | O73: Starter til November | S73: Follow Up Set | T73: Sagde på kaldet han ikke havde tænkt han skulle starte på men det lød som noget for ham og det der skulle til for ham
B74: 45928 | C74: Frederik Eisgart | E74: 22 55 91 41 | F74: https://www.instagram.com/frederik_eisgart/ | H74: Setter | I74: Rescheduled
B75: 45929 | C75: Linn Aiyuan | E75: 51 16 69 39 | F75: https://www.instagram.com/linnaiyuan/ | H75: Setter | I75: Offer & Didn't Buy | N75: Money | S75: Follow Up Set | T75: Havde tidligere været i forløb, hvor det ikke havde fungeret, men det her lød som noget meget mere for hende. Det var vigtigt det hele ikke blev for meget på en gang men gik i et tempo så hun kunne følge med, så det ikke bare blev fra 0-100
B76: 45929 | C76: Sarah Christine Mess Nielsen | E76: 23 91 35 30 | F76: https://www.instagram.com/sarahmesssss/ | H76: Setter | I76: Offer & Didn't Buy | N76: Money | O76: Havde bare ikke pengene | S76: Follow Up
B77: 45929 | C77: Kristina Wentzel | E77: 28 72 13 52 | F77: https://www.instagram.com/kristinawentzel_1991/ | H77: Setter | I77: Offer & Didn't Buy | N77: Money | S77: Follow Up Set
B78: 45929 | C78: Joanne Sophia Salazar | E78: 40 54 36 31 | F78: https://www.instagram.com/sophia_s84/ | H78: Setter | I78: Split-pay | K78: 10500 | L78: 3000 | S78: Closed
B79: 45929 | C79: Charlotte Winther | E79: 23 98 73 98 | F79: https://www.instagram.com/charlottebwinther/ | H79: Setter | I79: Split-pay | K79: 9000 | L79: 1500 | N79: Time | O79: Kunne først starte til december pga en rejse og flytning | Q79: 6 | S79: Closed
B80: 45929 | C80: Laura Tandrup Sørensen | E80: 28 57 60 86 | F80: https://www.instagram.com/lauratandrup/ | H80: Setter | I80: Offer & Didn't Buy | N80: Fear | O80: Lagde på da der skulle betales | Q80: 5 | S80: X | T80: Ingen ide om hvorfor hun lagde på og nu har blokeret mig og Daniel IG
B81: 45930 | C81: Anna Hartwigsen | E81: 93 94 31 22 | F81: https://www.instagram.com/annahartwigsen/ | H81: Setter | I81: Offer & Didn't Buy | N81: Money | O81: Havde ikke et fuldtidsjob | S81: Follow Up Set | T81: Ringer til hende d. 31 Oktober, hvor hun sagde hun ville have et job. Havde ikke den bedste kemi til at starte med, hun kom med nogle meget korte svar og var sku svær at åbne op, men vi sluttede ham på en god note og lød som noget for hende, når hun havde pengene til slut oktober og havde fået et job
B82: 45930 | C82: Celina Hindhede | E82: 22762277 | H82: Landing page | I82: Split-pay | K82: 9000 | L82: 3000 | Q82: 5 | S82: Closed | T82: Var bare klar på det hele direkte fra landingpage

Sheet Oct
B1: Rep: | C1: Name | E1: Anton KPI's | H1: Outcome | K1: KPIs% | N1: Show Rate | Q1: Objections | T1: Source
E2: Rev per call | F2: =C3/C6 -> 4042.3729 | H2: Full-Pay: | I2: =IFERROR(COUNTIFS(I13:I287, "Full-Pay"),"") -> 1 | K2: Conversion Rate: | L2: =iferror(L10/L8,"") -> 0.38983051 | N2: Rescheduling Rate: | O2: =iferror(I8/L6,"") -> 0.095890411 | Q2: Think About It | R2: =IFERROR(COUNTIFS(N13:N286, "think about it"),"") -> 5 | T2: Reschedule | U2: =IFERROR(COUNTIF(H13:H286,T2),"") -> 0
B3: Revenue | C3: =IFERROR(SUM(K13:K283),"") -> 238500 | E3: Cash per call | F3: =C4/C6 -> 1277.1102 | H3: Split-Pay: | I3: =IFERROR(COUNTIFS(I13:I287, "Split-Pay"),"") -> 22 | K3: Offer To Close Rate: | L3: =IFERROR(L10/L9,"") -> 0.39655172 | N3: Cancellation Rate: | O3: =iferror(I9/L6,"") -> 0.054794521 | Q3: Money | R3: =IFERROR(COUNTIFS(N13:N286, "money"),"") -> 20 | T3: YouTube | U3: =IFERROR(COUNTIF(H13:H286,T3),"") -> 0
B4: Cash | C4: =IFERROR(SUM(L13:L284),"") -> 75349.5 | E4: Cash upfront % | F4: =C4/C3*100 -> 31.593082 | H4: Deposits: | I4: =IFERROR(COUNTIFS(I13:I287, "Deposit"),"") -> 4 | K4: Call To Offer Rate: | L4: =IFERROR(L9/L8,"") -> 0.98305085 | N4: No-Shows Rate: | O4: =iferror(I10/L6,"") -> 0.04109589 | Q4: Time | R4: =IFERROR(COUNTIFS(N13:N286, "time"),"") -> 1 | T4: YouTube Ads | U4: =IFERROR(COUNTIF(H13:H286,T4),"") -> 0
E5: PIF % | F5: =I2/C7*100 -> 4.3478261 | H5: Offer & Didn't Buy: | I5: =IFERROR(COUNTIFS(I13:I287, "Offer & Didn't Buy"),"") -> 31 | K5: Drag Over Rate: | L5: =IFERROR(I7/(C6+I7+I8),"") -> 0 | N5: Drag Over Rate: | O5: =iferror(I7/L6,"") -> 0 | Q5: Partner | R5: =IFERROR(COUNTIFS(N13:N286, "partner"),"") -> 5 | T5: Email | U5: =IFERROR(COUNTIF(H13:H286,T5),"") -> 0
B6: Total Calls : | C6: =IFERROR(SUM(I2:I6),"") -> 59 | E6: Average Binding | F6: =AVERAGE(Q13:Q104) -> 5.9565217 | H6: Bad Fit & No Offer: | I6: =IFERROR(COUNTIFS(I13:I287, "Bad Fit & No Offer"),"") -> 1 | K6: Bookings: | L6: =IFERROR(SUM(I2:I10),"") -> 73 | N6: Show-Up Rate: | O6: =iferror(L7/L6,"") -> 0.80821918 | Q6: Fear | R6: =IFERROR(COUNTIFS(N13:N286, "fear"),"") -> 4 | T6: Facebook | U6: =IFERROR(COUNTIF(H13:H286,T6),"") -> 0
B7: Total Won : | C7: =IFERROR(I2+I3,"") -> 23 | E7: Average deal | F7: =C3/C7 -> 10369.565 | H7: Drag Over & Show: | I7: =IFERROR(COUNTIFS(I13:I287, "Drag Over & Show"),"") -> 0 | K7: Shows: | L7: =IFERROR(SUM(I2:I7),"") -> 59 | N7: Conducted Rate: | O7: =IFERROR(L8/L6,"") -> 0.80821918 | Q7: Value | R7: =IFERROR(COUNTIFS(N14:N287, "value"),"") -> 4 | T7: Facebook Ads | U7: =IFERROR(COUNTIF(H13:H286,T7),"") -> 0
B8: Total Lost : | C8: =COUNTIF(I13:I286,"offer & didn't buy")+countif(I13:I286,"deposit")+countif(I13:I286,"bad fit & no offer") -> 36 | E8: Average cash | F8: =C4/C7 -> 3276.0652 | H8: Rescheduled: | I8: =IFERROR(COUNTIFS(I13:I287, "Rescheduled"),"") -> 7 | K8: Calls: | L8: =IFERROR(SUM(I2:I6),"") -> 59 | T8: LinkedIn | U8: =IFERROR(COUNTIF(H13:H286,T8),"") -> 0
B9: Closing % : | C9: =iferror(SUM(C7/C6),"") -> 0.38983051 | H9: Cancelled: | I9: =IFERROR(COUNTIFS(I13:I287, "Cancelled"),"") -> 4 | K9: Offers: | L9: =IFERROR(sum(I2:I5),"") -> 58
H10: No-Show: | I10: =IFERROR(COUNTIFS(I13:I287, "No-Show"),"") -> 3 | K10: Deals | L10: =I2+I3 -> 23
B12: Date | C12: Name | E12: Phone | F12: IG | H12: Source | I12: Outcome | K12: Revenue | L12: Cash | N12: Objection | O12: Objection Notes | Q12: Length | R12: Recording Link | S12: Follow Up/Next Steps | T12: Call Summary
B13: 45931 | C13: Martha-Malou Sørensen | E13: 50 91 13 15 | F13: https://www.instagram.com/marthassorensen/ | H13: Setter | I13: Split-pay | K13: 13500 | L13: 3000 | Q13: 8 | S13: Closed
B14: 45931 | C14: Emil Bejder | E14: 42 23 06 13 | F14: https://www.instagram.com/emilbejder/ | H14: Setter | I14: Split-pay | K14: 10500 | L14: 3000 | Q14: 6 | S14: Closed
B15: 45931 | C15: Tobias Rosengreen | E15: 26 78 00 11 | F15: https://www.instagram.com/tobias_rosengreen/ | H15: Setter | I15: Split-pay | K15: 10500 | L15: 3000 | Q15: 6 | S15: Closed
B16: 45931 | C16: Sara Block Bach | E16: 42 97 85 75 | F16: https://www.instagram.com/back_bloch/ | H16: Setter | I16: Split-pay | K16: 12000 | L16: 3000 | Q16: 7 | S16: Closed
B17: 45931 | C17: Christina S. Nielsen | E17: 60 21 97 03 | F17: https://www.instagram.com/christina.sn03/ | H17: Setter | I17: Split-pay | K17: 10500 | L17: 2449.5 | N17: Money | O17: Penge skulle prioriteres og kunne skaffes til d. 13 oktober | S17: Closed
B18: 45931 | C18: Naja Ravnsdal Rasmussen | E18: 29 70 31 71 | F18: https://www.instagram.com/najaravnsdal/ | H18: Setter | I18: Offer & Didn't Buy | N18: Money | O18: Kun slet ikke lade sig gøre | S18: Follow Up | T18: Mega god snak syntes og jeg får stillet de rigtige spørgsmål, men var udelukkende pengene der gjorde udfaldet
B19: 45931 | C19: Oliver Otkjær Ulriksen Thune | E19: 30 70 55 67 | F19: https://www.instagram.com/oliverotkjerulriksenthune/ | H19: Setter | I19: Bad Fit & No Offer | S19: Follow Up
B20: 45931 | C20: Frederikke | E20: 22 84 24 69 | F20: https://www.instagram.com/frederikkeayoe/ | H20: Setter | I20: Deposit | N20: Money | O20: Starter d. 1 November havde først pegnene der | Q20: 5 | S20: Deposit (Follow Up Set) | T20: Gik virkeligt godt meget åben person så nok at tage fat i. Hun ville så gerne men pengene resten af den her måned var virkeligt små, men det kunne lade sig gøre fra d. 1 november. Kunne jo hører økonomisk det kunne lade sig gøre, skulle bare sprøge hende om det var et eller andet der holdte hende tilbage ligesom på kaldet ned Christina
B21: 45932 | C21: Gustav Vilfing | E21: 51 36 45 57 | F21: https://www.instagram.com/gustav.vilfing/ | H21: Setter | I21: Split-pay | K21: 10500 | L21: 3000 | Q21: 6 | S21: Closed | T21: Det gik virkeligt godt, havde nævnt det var hans forældre som skulle støtte ham økonomisk handlede den til at starte med, og det virkede jo så
B22: 45932 | C22: Mikkel Skovgaard | E22: 22 38 33 82 | F22: https://www.instagram.com/mik.skovgaard/ | H22: Setter | I22: Offer & Didn't Buy | S22: Follow Up | T22: Spiller amerikansk fodbold på højt niveau, så han havde adgang til kosten igennem hans klub som havde virkeligt godt styr på, så det var kun træningsprogrammet han var interesseret i
B23: 45932 | C23: Jesper | E23: 22 62 01 08 | F23: https://www.instagram.com/jespero87/ | H23: Setter | I23: Offer & Didn't Buy | N23: Think About It | O23: Havde en masse skavanker, som han lige skulle have styr, inden han kunne | S23: Follow Up | T23: Han gav ikke så meget af sig selv, men fik ham da åbnet op og stilte nogle gode spørgsmål, men han var nok ikke helt solgt på ide for så havde han jo gjort det. Vigtigt det blev holdbart og på hans præmisser så det ikke blev en kæmpe opvæltning
B24: 45933 | C24: Simone Frøslev | E24: 61 40 61 26 | F24: https://www.instagram.com/mrs_stop_giving_up/ | H24: Setter | I24: Split-pay | K24: 10500 | L24: 3000 | N24: Think About It | Q24: 6 | S24: Closed | T24: Skulle bare tænke over det og sige det højt for sig selv
B25: 45933 | C25: Nick Seliger Sommer | E25: 53 77 28 93 | F25: https://www.instagram.com/nickseligersommer/ | H25: Setter | I25: Rescheduled
B26: 45935 | C26: Ana Monik | E26: 50 29 74 79 | F26: https://www.instagram.com/marabouaddict/ | H26: Setter | I26: No-Show
B27: 45935 | C27: Suzie M Ruusgaard | E27: 61 70 62 58 | F27: https://www.instagram.com/suzie.m.ruusgaard/ | H27: Setter | I27: Offer & Didn't Buy | N27: Partner | O27: Skulle informere manden om det | S27: Follow Up | T27: Ringer til hende i morgen aften. virkede som det helt rigtige for hende, hun havde pengene, ville gøre det selvom partneren sagde, nej hun skulle bare informere ham om det. Startede med hun først ville i gang til nytår, men fik hende til at indse det skulle være nu og lavede et kæmpe gap.
B28: 45935 | C28: Caroline Slipsager Aebeloe | E28: 30 20 74 38 | F28: https://www.instagram.com/aebeloe.eq/ | H28: Setter | I28: Offer & Didn't Buy | N28: Money | O28: Havde et stramt budget med hest | S28: Follow Up | T28: Ringer til hende tirsdag kl 20. Hun havde en masse pain og det blev også fundet aldrig været tilfreds. Skulle nok have gennemgået mere iforhold hvad konsekvenser var ved ikke at gøre noget
B29: 45936 | C29: Nicki Lund | E29: 23 67 72 00 | F29: https://www.instagram.com/nickilund007/ | H29: Setter | I29: Split-pay | K29: 10500 | L29: 400 | N29: Money | O29: Kunne kun smide 400 kr. nu her o | Q29: 6 | S29: Closed
B30: 45936 | C30: Alexander Marion | E30: 53 62 60 79 | F30: https://www.instagram.com/marionadefar/ | H30: Setter | I30: Offer & Didn't Buy | N30: Fear | O30: Turde ikke tage skridtet | S30: Hot Follow Up | T30: Ringer til ham kl 16:30 i morgen. Ville sygt gerne kunne bare ikke få ham til at tage skridtet
B31: 45936 | C31: Emilie Stilling | E31: 29 66 22 03 | F31: https://www.instagram.com/emilie_stilling/ | H31: Setter | I31: Split-pay | K31: 9000 | L31: 3000 | N31: Money | Q31: 5 | S31: Closed | T31: Super fin snak vi havde, fik fundet noget pain, hun altid havde døjet med vægten og aldrig været helt tilfreds. Så hun også havde nogle mål og hun ikke ville skuffe sig selv. Kunne godt have spurgt mere ind til, hvis hun ikke nåede de her mål.
B32: 45936 | C32: Oskar Kjærsgaard | E32: 61 45 22 41 | F32: https://www.instagram.com/oskar_kjaersgaard/ | H32: Setter | I32: Deposit | N32: Money | O32: Havde først pengene til novmeber | S32: Deposit (Follow Up Set) | T32: Virkede ikke til han havde pain, men havde røv meget pain, så det var fucking nice. Så god discovery førte til salg
B33: 45937 | C33: Miha Mihaela | E33: 25 12 37 93 | F33: https://www.instagram.com/miha560/ | H33: Setter | I33: Offer & Didn't Buy
B34: 45937 | C34: Amalie Bramsted | E34: 91 25 18 21 | F34: https://www.instagram.com/amaliebramsted/ | H34: Setter | I34: Offer & Didn't Buy | N34: Partner | O34: Skulle bare vende den med forældrene | S34: Follow Up | T34: Hun ville vende tilbage, hun var bange for at det ville blive for seriøst og hun ville ikke spilde vores tid. Hører fra hende til aften d. 7
B35: 45937 | C35: Catharina Dam | E35: 27 14 28 54 | F35: https://www.instagram.com/cathdam/ | H35: Setter | I35: Offer & Didn't Buy | N35: Value | O35: Kunne ikke få hende til det, skulle tænke over det | S35: Follow Up Set | T35: Var vel i bund og grund jeg ikke fik hende solgt godt, nok sygt godt nok jeg generelt strugglede i dag med min kald, ikke de bedste discoveries ved sku ikke lige hvad der skete.
B36: 45938 | C36: Malene Helsinghoff | E36: 29 87 70 96 | F36: https://www.instagram.com/helsinghoff/ | H36: Setter | I36: Offer & Didn't Buy
B37: 45938 | C37: Daniel Schlippe | E37: 53 20 36 33 | F37: https://www.instagram.com/danielschlippe?igsh=dWw0M2kybzZsNGgz | H37: Setter | I37: Split-pay | K37: 9000 | L37: 9000 | Q37: 6 | S37: Closed
B38: 45938 | C38: Miha Mihaela | E38: 25 12 37 93 | F38: https://www.instagram.com/miha560/ | H38: Setter | I38: Offer & Didn't Buy | S38: X | T38: Ville virkeligt gerne, men kunne simplhent ikke få hende til at tage en beslutning, hun tænkte altid over tingene. Var svært at snakke med ikke den bedste til dansk og snakkede ekstremt meget
B39: 45938 | C39: Albert Føgh Lenler | E39: 30 20 19 01 | F39: https://www.instagram.com/albert.lenler?igsh=MW94bWZlaGlrcHdtNg== | H39: Setter | I39: Offer & Didn't Buy | N39: Value | O39: Ville fortryde det, hvis han kunne på egen hånd | S39: Follow Up | T39: Skal Reviewes. Fik ham ikke til at se den fulde værdi i det, ville hellere gøre det selv og ikke bruge pengene på det. Ville fortryde endnu mere hvis han gjore det her og så heller ikke kom i mål og havde spildt pengene
B40: 45939 | C40: Hjalte Westeraa | E40: 22 58 16 51 | F40: https://www.instagram.com/hjaltewesteraa02/ | H40: Setter | I40: Offer & Didn't Buy | L40: 1500 | N40: Money | O40: Skulle have tjekket op det hele kunne lade sig gøre | Q40: 6 | S40: Hot Follow Up | T40: Skal snakke med Daniel igen på mandag, hvor de gennemgår programmet. Vil gerne tage det næste skridt, og tage det til næste niveau, så han kan blive så stor som overhovedte muligt
B41: 45939 | C41: Caroline Hauge | E41: 21 62 39 04 | F41: https://www.instagram.com/carolinehauge?igsh=NXZmMnlybDA1Ynp0 | H41: Setter | I41: Rescheduled
B42: 45940 | C42: Line Larsen | E42: 22 95 18 79 | F42: https://www.instagram.com/linensl/ | H42: Setter | I42: Split-pay | K42: 12000 | L42: 3000 | N42: Fear | Q42: 7 | S42: Closed | T42: Var meget tilbageholdende med at gøre det, fordi hun tidligere havde været i nogle forløb som ikke var gået ret godt, men fik en til at indse det var det rigtige for hende
B43: 45941 | C43: Janni Fruergaard | E43: 20 68 21 37 | F43: https://www.instagram.com/janni86dk/ | H43: Setter | I43: Offer & Didn't Buy | N43: Partner | O43: Skulle vendes med manden | S43: Follow Up | T43: Prøvede egenligt at prime hende til at det her var den rigtigt løsning for hende og det var det rigtige for hende at få den her hjælp og det mente hun også det var skulle bare vendes med manden.
B44: 45941 | C44: Maria Balskov Jakobsen | E44: 24 47 68 99 | F44: https://www.instagram.com/balskov2/ | H44: Setter | I44: Cancelled | T44: Vil gerne have en snak til nytår
B45: 45942 | C45: Lucca Augusta Bennetzen | E45: 26 34 11 77 | H45: Landing page | I45: Split-pay | K45: 7500 | L45: 3000 | Q45: 4 | S45: Closed
B46: 45943 | C46: Sofie Callesen | E46: 25 76 60 01 | F46: https://www.instagram.com/callesen.s/ | H46: Setter | I46: Rescheduled
B47: 45943 | C47: Mathias Zickert | E47: 21 39 95 90 | F47: https://www.instagram.com/mathias.zickert/ | H47: Setter | I47: Cancelled
B48: 45943 | C48: Mia Rindom | E48: 27 28 62 19 | F48: https://www.instagram.com/miarindom/ | H48: Setter | I48: Offer & Didn't Buy | S48: Follow Up | T48: En mærkelig case faktisk, kunne nok 100 procent hjælpe hende med havde svært ved at finde den rigtige løsning for hende i forhold til hvad hun ønskede, skal lige have fat i Daniel og så ringer jeg
B49: 45944 | C49: Andreas Sørensen | E49: 22 53 79 33 | F49: https://www.instagram.com/andreassorensen667/ | H49: Setter | I49: Offer & Didn't Buy | N49: Money | O49: Stod mellem 2 jobs, så vidste ikke om han have nogen indtægt fra på søndag af | S49: Follow Up Set | T49: Have en virkeligt god snak med ham, var det helt rigtige for ham og ville så gerne, det eneste der holdt ham tilbage var han stod uden job fra på søndag. Havde en venide han trænede med som også ville ind i poliitiet som også var interesseret i det, så hende prøver jeg at få med på mandag når jeg ringer til ham igen, ellers så ringer jeg selv til hende
B50: 45944 | C50: Tobias Godske Højgaard | E50: 93 92 10 05 | F50: https://www.instagram.com/direct/t/100373261360420/ | H50: Setter | I50: Offer & Didn't Buy | N50: Money | O50: Var i stedet ende at han syntes det var for mange penge, og så helt klart noget fear | S50: X | T50: Kunne sku ikke få ham over stregen, gjorde alt jeg kunne syntes jeg, men i bund og grund fik jeg ham ikke solgt godt nok, skulle have bygget et større gap fra hvor han nu til der han gerne ville hen. Fundet ud af hvordan jeg prober mere i stedet for at tænke "jeg har nok"
B51: 45946 | C51: Kathrine Kallehauge | E51: 60 86 26 54 | F51: https://www.instagram.com/kathrinekallehauge/ | H51: Setter | I51: Offer & Didn't Buy | N51: Money | O51: Hun vidste hun skulle til at flytte ud om 6 måneder og skulle bruge en god opsparing til det | S51: Hot Follow Up | T51: Fik hende ikke solgt godt nok for så havde hun jo købt. Hvis hun skar ind til benet havde hun pengene, men hun vægtede højere hun havde penge til en lejlighed til om 6 måneder og så var hun lige starte på et terapi forløb, som hun selv sagde var en non-negotinable for hende
B52: 45946 | C52: Emma Kjær | E52: 31 35 89 98 | F52: https://www.instagram.com/emma_kjaer__/ | H52: Setter | I52: Offer & Didn't Buy | N52: Money | O52: En blanding af penge og fear | S52: Follow Up | T52: Hun syntes virkeligt det lød som noget for hende, men hun havde tidligere været i forløb, hvor hun var blevet lovet nogle at de kunne hjælpe i fothold til hendes delte mavemuskler, hvor de så ikke kunne og kastede nærmeste pengene ud af vinduet som hun selv sagde
B53: 45947 | C53: Andreas Frederiksen | E53: 30 83 43 02 | F53: https://www.instagram.com/andrewmf87/ | H53: Setter | I53: Deposit | N53: Time | O53: Han var allerede i gang med et andet forløb som han skulle have afslutet | S53: Deposit (Follow Up Set) | T53: Følger op på ham på mandag. Skulle have afsluttet et allerede igangværende forløb og lige finde ud af hvordan fungerede. Havde aftalt han skulle ligge et depsitum for at få pladsen til 1/12
B54: 45947 | C54: Camilla Holm | E54: 22 96 57 70 | F54: https://www.instagram.com/camillaholm1803/ | H54: Setter | I54: Split-pay | K54: 9000 | L54: 3000 | Q54: 5 | S54: Closed
B55: 45947 | C55: Victoria Hansen | E55: 71 95 92 60 | F55: https://www.instagram.com/v_hansen20/ | H55: Setter | I55: Rescheduled
B56: 45947 | C56: Kicki Bervild | E56: 28 25 16 98 | F56: https://www.instagram.com/kickibervild/ | H56: Setter | I56: Offer & Didn't Buy | N56: Money | O56: Var pegnene der holdte hende tilbage | S56: Follow Up | T56: Skal ringe til hende på mandag kl 16:30. Bliver en alt for langt samtale, fokusere ikke nok på det vigtige, så den trækker voldsomt ud, og kunne sku ikke få hende til det rent økonomisk. Hun har haft en tidligere dårlige oplevelse i hende unge dag i forhold til at bruge flere penge end hun har
B57: 45947 | C57: Simone Larsen | E57: 41 60 60 66 | F57: https://www.instagram.com/simone.larsen.9465/ | H57: Setter | I57: Split-pay | K57: 10500 | L57: 3000 | Q57: 6 | S57: Closed
B58: 45949 | C58: Diana Behlic | E58: 51 78 56 00 | F58: https://www.instagram.com/dianabehlic/ | H58: Setter | I58: Split-pay | K58: 13500 | L58: 1500 | N58: Fear | O58: Var bange for at skuffe og ikke kunne leve op til forventningerne | Q58: 8 | S58: Closed
B59: 45949 | C59: Jannie Pihl Pedersen | E59: 61 65 66 16 | F59: https://www.instagram.com/_janniepihl_/ | H59: Setter | I59: Cancelled
B60: 45949 | C60: Annika Roskov | E60: 60 77 61 68 | F60: https://www.instagram.com/roskovannika/ | H60: Setter | I60: No-Show
B61: 45950 | C61: Victoria Hansen | E61: 71 95 92 60 | F61: https://www.instagram.com/v_hansen20/ | H61: Setter | I61: No-Show
B62: 45950 | C62: Ronni | E62: 40 89 25 58 | F62: https://www.instagram.com/ronnikn/ | H62: Setter | I62: Offer & Didn't Buy | N62: Partner | S62: Follow Up | T62: Bliver en alt for lang snak den løber sku lidt af sporet for mig, syntes det er noget jeg har meget svært ved. Får heller ikke sat framet ordenligt fra starten af.
B63: 45950 | C63: FILIPPA WEBER PAUSTIAN | E63: 81 71 71 81 | F63: https://www.instagram.com/filippa_paustian/ | H63: Setter | I63: Offer & Didn't Buy | N63: Fear | O63: Tidligere dårligere oplevelse med coaching | S63: Follow Up Set | T63: Sagde hun havde en rigtig god mavefornemmelse, men hun skulle sove på den og det samme gjaldt inden samtale, hun skulle også på den og finde ud af om det var noget for hende
B64: 45950 | C64: Martina Bangsø | E64: 26 84 09 28 | F64: https://www.instagram.com/martina.bangsoe?igsh=Y3R6dDd1czF3cGow | H64: Setter | I64: Split-pay | K64: 10500 | L64: 3000 | N64: Partner | O64: Hendes mand der ikke var helt solgt | Q64: 6 | S64: Closed | T64: Par forløb hun er fuldstændigt solgt og vil overtale manden til de skal igang og kan sætte fundamentet for resten af deres liv.
B65: 45950 | C65: Heidi Nyborg Kristensen | E65: 22 17 17 05 | F65: https://www.instagram.com/heidinyborgkr/ | H65: Setter | I65: Cancelled | N65: Money | O65: Udeklukkende pengene der holder hende tilbage | S65: Hot Follow Up
B66: 45951 | C66: Line-Johanne Schmidt Popall | E66: 61 48 19 86 | F66: https://www.instagram.com/line.j.popall/ | H66: Setter | I66: Offer & Didn't Buy | N66: Value | O66: Følte ikke det var det rigtige for hende | S66: Follow Up
B67: 45951 | C67: Hanne Vieland Ågård | E67: 22 73 24 47 | F67: https://www.instagram.com/hannevieland/ | H67: Setter | I67: Split-pay | K67: 9000 | L67: 3000 | Q67: 5 | S67: Closed
B68: 45952 | C68: Ditte Lykke Kleis Borch Sørensen | E68: 50 47 09 12 | F68: https://www.instagram.com/dittelkborch/ | H68: Setter | I68: Offer & Didn't Buy
B69: 45953 | C69: Daniella Elna Schor-Stott Andersen | E69: 42 75 02 18 | F69: https://www.instagram.com/dannimus01_basim/ | H69: Setter | I69: Deposit | N69: Money | O69: Var meget tilbageholdende med at bruge pengene på det, om det var spild af penge | S69: Deposit (Follow Up Set) | T69: Starter op til d. 1 december, var din eneste løsning
B70: 45953 | C70: Rico | E70: 50 31 18 72 | F70: https://www.instagram.com/javricoj/ | H70: Setter | I70: Offer & Didn't Buy | N70: Think About It | O70: Skulle bare altid tænke over det noget han stod meget fast ved | S70: Hot Follow Up | T70: Ville give Daniel et svar tilbage. En svær snak, fordi han ikke var så god til dansk, så han forstod ikke alle mine spørgsmål, så vi misforstod hinanden, så blev ikke den perfekte samtale, men sagde at fornemmelse med det hele var bedre nu end før han gik på kald, så nu må vi se
B71: 45953 | C71: Rebecca Bech | E71: 28 57 92 13 | F71: https://www.instagram.com/rebeccabechh/ | H71: Setter | I71: Offer & Didn't Buy | N71: Money | O71: Hun kunne ikke andet end at tænke på pengene, men var også noget fear for at få dem brugt | S71: Hot Follow Up | T71: Hun var ultra fokuseret på hun ikke havde pengene og det eneste hun tænkte på, og hun var bange for at bruge dem. Skulle helt klart have talt mere ind i konsekvenserne ved ikke at gøre noget. Hun blev frusteret og irriteret på sig selv, fordi hun ville sygt gerne men kunne bare ikke pga "pengene"
B72: 45954 | C72: Signe Liv Hyldahl Lauritzen | E72: 22 23 18 31 | F72: https://www.instagram.com/signe_liv_lauritzen/ | H72: Setter | I72: Split-pay | K72: 10500 | L72: 3000 | Q72: 6 | S72: Closed
B73: 45957 | C73: Kristina Skov | E73: 42 39 69 81 | F73: https://www.instagram.com/kristinaskov?igsh=MTMwdTdlbHdxcGpsZg== | H73: Setter | I73: Rescheduled
B74: 45957 | C74: Magda De Castro | E74: 71 58 53 12 | F74: https://www.instagram.com/magda_d_castro/ | H74: Setter | I74: Rescheduled
B75: 45957 | C75: Mads Frederik Møller Marcussen | E75: 21 35 73 51 | F75: https://www.instagram.com/alahwaqba?igsh=NGx1bHdlenB1ZDJk | H75: Setter | I75: Split-pay | K75: 10500 | L75: 3000 | Q75: 6 | S75: Closed
B76: 45957 | C76: Stephanie Vestergaard | E76: 25 11 18 07 | F76: https://www.instagram.com/stephanie.klindtworth?igsh=cWxzbTMxNHJxYzh6 | H76: Setter | I76: Offer & Didn't Buy | N76: Money | O76: Havde sagt ja og sendt penge men fortrød et par timer senere, da det var for mange penge og det ikke kunne lade sig gøre | S76: Hot Follow Up | T76: Var det helt rigtige for hende, hun havde jo goså sagt ja, men efter at have kigget på hvor mange penge hun havde, fortrød hun. Mega ærgerligt især når jeg følte det var en mega god snak
B77: 45957 | C77: Nicolai Ærbo Jensen | E77: 51 17 11 76 | F77: https://www.instagram.com/nicolai_aerbo?igsh=cXN6cWNmNDg4M2E3 | H77: Setter | I77: Offer & Didn't Buy | N77: Think About It | O77: Han ville gerne have noget PT, hvor jeg havde snakket med Daniel om jeg kunne gøre det fordi han var fra Aarhus. Så skal mødes med ham på mandag til en træning, inden han lige sagde ja til det hele | S77: Follow Up Set | T77: Skal mødes med ham på mandag, fordi han gerne ville have noget PT ved siden af forløbet, og jeg havde tilbudt at gøre det, men ville gerne lige se mig an om vi klikkede og det sagde jeg så ja til. Det ville han gerne inde han lige sagde ja til det hele
B78: 45957 | C78: Lisbeth Thim Fabricius Frederiksen | E78: 60 48 43 21 | H78: Referral | I78: Full-Pay | K78: 9000 | L78: 9000 | Q78: 6 | S78: Closed
B79: 45958 | C79: Ole Anders | E79: 27 13 07 73 | F79: https://www.instagram.com/besseby/ | H79: Setter | I79: Offer & Didn't Buy | N79: Money | S79: Follow Up Set | T79: Han giver lyd i morgen. Daniel snakked også med ham ifht. PT som egenligt var det vigtigste for ham
B80: 45959 | C80: Martin Hove | E80: 81 24 37 28 | F80: https://www.instagram.com/martin.hove?igsh=MWVnc2FrZjBqcHFxaw== | H80: Setter | I80: Offer & Didn't Buy | N80: Value | O80: Kunne ikke se det var pengene værd | S80: Closed | T80: Han er fysisk klient. Får slet ikke fundet nok pain, så han ender selvfølgelig ikke med at købe. Skal sku blive meget bedre i discovery.
B81: 45959 | C81: Dominic Kamke | E81: 60 13 27 01 | H81: Landing page | I81: Split-pay | K81: 9000 | L81: 3000 | N81: Think About It | O81: Sagde jeg ikke fik et svar i dag | Q81: 5 | S81: Closed | T81: Ringer til ham i morgen kl 10. Svær snak når vi begge snakker ikke snakker engelsk som vores først sprog, så kom nogle misforståelse undervejs, får ikke stillede de rigtige spørgsmål, og heller ikke altid han helt forstod, hvad jeg spurgte om, men tager det med oprejst pande.
B82: 45960 | C82: Agnethe Wallin | E82: 26 16 66 68 | F82: https://www.instagram.com/agnethewallin/ | H82: Setter | I82: Offer & Didn't Buy | N82: Money | O82: Havde ikke pengene, nu stod i en dårlig situation med hus salg og lån | S82: Hot Follow Up | T82: Følte mig meget mere tilstede på samtalen, end jeg har gjort de sidste mange gange og kunne virkeligt mærke en forskel, selvom den ikke blev lukket. Har skrevet i kalenderen jeg følger op på hende til d.1 december
B83: 45960 | C83: Rasmus Valsted Thellemann | E83: 30 74 12 01 | F83: https://www.instagram.com/rasmusthellemann/ | H83: Setter | I83: Rescheduled
B84: 45961 | C84: Mikkel Lohse | E84: 21 57 85 59 | F84: https://www.instagram.com/lohse_fyren/ | H84: Lost lead | I84: Split-pay | K84: 10500 | L84: 500 | N84: Money | O84: Kunne første betale resten, når han kom hjem fra job og på mandag | Q84: 6 | S84: Closed | T84: Dejlig kort samtale, fandt noget pain og fandt ud af, hvad der var vigtigt for ham, og brugte det i gennem samtalen
B85: 45961 | C85: Frederik Eisgart | E85: 22 55 91 41 | F85: https://www.instagram.com/frederik_eisgart/ | H85: Setter | I85: Split-pay | K85: 10500 | L85: 3000 | S85: Closed | T85: Super god snak, bragte den helt gode energi, og fandt ud af hvorfor det var vigtigt for ham

Sheet Nov
A1: emma | B1: Rep: | C1: Name | E1: Anton KPI's | H1: Outcome | K1: KPIs% | N1: Show Rate | Q1: Objections | T1: Source
E2: Rev per call | F2: =C3/C6 -> 2719.2982 | H2: Full-Pay: | I2: =IFERROR(COUNTIFS(I13:I284, "Full-Pay"),"") -> 5 | K2: Conversion Rate: | L2: =iferror(L10/L8,"") -> 0.29824561 | N2: Rescheduling Rate: | O2: =iferror(I8/L6,"") -> 0.074626866 | Q2: Think About It | R2: =IFERROR(COUNTIFS(N13:N283, "think about it"),"") -> 1 | T2: Reschedule | U2: =IFERROR(COUNTIF(H13:H283,T2),"") -> 0
B3: Revenue | C3: =IFERROR(SUM(K13:K280),"") -> 155000 | E3: Cash per call | F3: =C4/C6 -> 1136.8421 | H3: Split-Pay: | I3: =IFERROR(COUNTIFS(I13:I284, "Split-Pay"),"") -> 12 | K3: Offer To Close Rate: | L3: =IFERROR(L10/L9,"") -> 0.30909091 | N3: Cancellation Rate: | O3: =iferror(I9/L6,"") -> 0.029850746 | Q3: Money | R3: =IFERROR(COUNTIFS(N13:N283, "money"),"") -> 24 | T3: YouTube | U3: =IFERROR(COUNTIF(H13:H283,T3),"") -> 0
B4: Cash | C4: =IFERROR(SUM(L13:L281),"") -> 64800 | E4: Cash upfront % | F4: =C4/C3*100 -> 41.806452 | H4: Deposits: | I4: =IFERROR(COUNTIFS(I13:I284, "Deposit"),"") -> 7 | K4: Call To Offer Rate: | L4: =IFERROR(L9/L8,"") -> 0.96491228 | N4: No-Shows Rate: | O4: =iferror(I10/L6,"") -> 0.044776119 | Q4: Time | R4: =IFERROR(COUNTIFS(N13:N283, "time"),"") -> 5 | T4: YouTube Ads | U4: =IFERROR(COUNTIF(H13:H283,T4),"") -> 0
E5: PIF % | F5: =I2/C7*100 -> 29.411765 | H5: Offer & Didn't Buy: | I5: =IFERROR(COUNTIFS(I13:I284, "Offer & Didn't Buy"),"") -> 31 | K5: Drag Over Rate: | L5: =IFERROR(I7/(C6+I7+I8),"") -> 0 | N5: Drag Over Rate: | O5: =iferror(I7/L6,"") -> 0 | Q5: Partner | R5: =IFERROR(COUNTIFS(N13:N283, "partner"),"") -> 4 | T5: Email | U5: =IFERROR(COUNTIF(H13:H283,T5),"") -> 0
B6: Total Calls : | C6: =IFERROR(SUM(I2:I6),"") -> 57 | E6: Average Binding | F6: =AVERAGE(Q13:Q104) -> 5.6666667 | H6: Bad Fit & No Offer: | I6: =IFERROR(COUNTIFS(I13:I284, "Bad Fit & No Offer"),"") -> 2 | K6: Bookings: | L6: =IFERROR(SUM(I2:I10),"") -> 67 | N6: Show-Up Rate: | O6: =iferror(L7/L6,"") -> 0.85074627 | Q6: Fear | R6: =IFERROR(COUNTIFS(N13:N283, "fear"),"") -> 4 | T6: Facebook | U6: =IFERROR(COUNTIF(H13:H283,T6),"") -> 0
B7: Total Won : | C7: =IFERROR(I2+I3,"") -> 17 | E7: Average deal | F7: =C3/C7 -> 9117.6471 | H7: Drag Over & Show: | I7: =IFERROR(COUNTIFS(I13:I284, "Drag Over & Show"),"") -> 0 | K7: Shows: | L7: =IFERROR(SUM(I2:I7),"") -> 57 | N7: Conducted Rate: | O7: =IFERROR(L8/L6,"") -> 0.85074627 | Q7: Value | R7: =IFERROR(COUNTIFS(N14:N284, "value"),"") -> 4 | T7: Facebook Ads | U7: =IFERROR(COUNTIF(H13:H283,T7),"") -> 0
B8: Total Lost : | C8: =COUNTIF(I13:I283,"offer & didn't buy")+countif(I13:I283,"deposit")+countif(I13:I283,"bad fit & no offer") -> 40 | E8: Average cash | F8: =C4/C7 -> 3811.7647 | H8: Rescheduled: | I8: =IFERROR(COUNTIFS(I13:I284, "Rescheduled"),"") -> 5 | K8: Calls: | L8: =IFERROR(SUM(I2:I6),"") -> 57 | T8: LinkedIn | U8: =IFERROR(COUNTIF(H13:H283,T8),"") -> 0
B9: Closing % : | C9: =iferror(SUM(C7/C6),"") -> 0.29824561 | H9: Cancelled: | I9: =IFERROR(COUNTIFS(I13:I284, "Cancelled"),"") -> 2 | K9: Offers: | L9: =IFERROR(sum(I2:I5),"") -> 55
H10: No-Show: | I10: =IFERROR(COUNTIFS(I13:I284, "No-Show"),"") -> 3 | K10: Deals | L10: =I2+I3 -> 17
B12: Date | C12: Name | E12: Phone No. | F12: Email | H12: Source | I12: Outcome | K12: Revenue | L12: Cash | N12: Objection | O12: Objection Notes | Q12: Length | R12: Recording Link | S12: Follow Up/Next Steps | T12: Call Summary
B13: 45962 | C13: Frederikke | E13: 22 84 24 69 | F13: https://www.instagram.com/frederikkeayoe/ | H13: Setter | I13: Split-pay | K13: 9000 | L13: 1800 | N13: Money | O13: Delte hendes opstart op udover 5 måneder, var inden vi aftale 6 måneders binding | Q13: 5 | S13: Closed
B14: 45962 | C14: Rasmus Mortensen | E14: 81 67 04 44 | F14: https://www.instagram.com/ra_mortensen/ | H14: Setter | I14: Offer & Didn't Buy | N14: Money | O14: Han havde pengene, men skulle lige kigge det igennem | S14: Follow Up | T14: Fik et deposit på 500 kr. Han skriver til mig senere og sagde han troede det godt kunne lade sig gøre
B15: 45963 | C15: Thea Stange Smed | E15: 26 82 79 55 | F15: https://www.instagram.com/theastangesmed/ | H15: Setter | I15: Rescheduled
B16: 45963 | C16: Nickolai Hansen | E16: 81 29 18 89 | F16: https://www.instagram.com/nhansen899/ | H16: Setter | I16: Deposit | N16: Money | O16: Havde ingen penge nu pga han lige har betalt indskud til lejlighed, men har fra d. 1 december | S16: Deposit (Follow Up Set)
B17: 45963 | C17: Ole Anders | E17: 27 13 07 73 | F17: https://www.instagram.com/besseby/ | H17: Setter | I17: Split-pay | K17: 4500 | L17: 1500 | S17: Closed | T17: Han er fysisk klient med Daniel, så er på down-sell og går mest op i fysisk træning
B18: 45964 | C18: Kathrine Libergren | E18: 51 27 21 62 | F18: https://www.instagram.com/kathrinelibergren/ | H18: Setter | I18: Offer & Didn't Buy | O18: Lægger på | S18: X | T18: Var et super god kald syntes jeg, hun var klar, no clue hvorfor hun smider røret på. Så den er jeg ærgerlig over, for syntes det var et rigtigt god kald, men kan jeg ikke gøre noget ved nu
B19: 45964 | C19: Mathias Marcussen | E19: 22 21 14 95 | F19: https://www.instagram.com/mathias.marcussen/ | H19: Setter | I19: Full-Pay | K19: 6000 | L19: 6000 | Q19: 4 | S19: Closed | T19: Kun 4 måneder pga, han skulle på en lang rejse til marts
B20: 45965 | C20: Sofie Marie Kurtz | E20: 22 64 07 15 | F20: https://www.instagram.com/sofiekurtz/ | H20: Setter | I20: Offer & Didn't Buy | N20: Money | O20: Var pengene der holdte hende tilbage | S20: Follow Up Set | T20: Fik ikke fundet nok pain, hun sagde hun havde noget fedt hun var træt af blandt andet på maven, det får jeg ikke spurgt nok ind til og kommer også for sent ind på det i samtalen
B21: 45965 | C21: Sarah Christine Mess Nielsen | E21: 23 91 35 30 | F21: https://www.instagram.com/sarahmesssss/ | H21: Setter | I21: Offer & Didn't Buy | N21: Money
B22: 45965 | C22: Jasper Vestergaard | E22: 93 96 17 37 | F22: https://www.instagram.com/jaspervestergaard/ | H22: Setter | I22: Offer & Didn't Buy | N22: Money | O22: Var kun interesseret i det gratis
B23: 45966 | C23: Rebecca Møller Nielsen | E23: 42 28 43 45 | F23: https://www.instagram.com/rebecca__nielsen/ | H23: Setter | I23: Offer & Didn't Buy | N23: Partner | O23: Skulle snakke med manden om pengene | S23: Hot Follow Up | T23: Kunne godt have været mere skarp på samtalen, ved ikke hvorfor jeg ikke var det, lidt mere tilstedeværelse havde været rigtig, godt selvom jeg egenligt syntes vi har en udmærket snak. Skulle vende det med manden og skulle se om det kunne lade sig gøre oveni iet husbyggeri, bryllup og en operation
B24: 45966 | C24: Kristina Skov | E24: 42 39 69 81 | F24: https://www.instagram.com/kristinaskov/ | H24: Setter | I24: Split-pay | K24: 16500 | L24: 1500 | N24: Money | O24: Kunne kun betale opstart nu | Q24: 7 | S24: Closed
B25: 45966 | C25: Thea Stange Smed | E25: 26 82 79 55 | F25: https://www.instagram.com/theastangesmed/ | H25: Setter | I25: Deposit | L25: 1500 | N25: Time | O25: Var allerde på et andet forløb, som hun afslutter til slut januar | S25: Closed | T25: Ville gerne tage det hele til næste niveau, har været på forløb de sidste 4 år, men trængte til forandring at få et nyt sæt øjne på det hele. Så hun starter op til februar når hun afslutter sit nuværende forløb
B26: 45966 | C26: Tobias Mittun | E26: 25 33 49 04 | F26: https://www.instagram.com/tobias_mittun/ | H26: Setter | I26: Cancelled
B27: 45967 | C27: Emil Schultz-Vistedsen | E27: 29 70 43 44 | F27: https://www.instagram.com/emilschultz.99/ | H27: Setter | I27: Full-Pay | K27: 6000 | L27: 6000 | N27: Money | O27: Skulle lige tjekke økonomien helt i gennem | Q27: 4 | S27: Closed | T27: Ringer til ham i morgen, og får styr på det sidste, så får vi ham igang til mandag
B28: 45967 | C28: Tanja Steenbjerg | E28: 51 62 23 70 | F28: https://www.instagram.com/t_steenbjerg/ | H28: Setter | I28: Offer & Didn't Buy | N28: Money | O28: Har ikke pengene | S28: Follow Up | T28: Syntes jeg får stillet nogle gode spørgsmål og at det er en god snak vi har. Hun siger tidligt hun ikke har pengene pga. hun lige er stoppet på et andet forløb og er blevet sygmeldt og ikek aner, hvornår hun er tilbage på job. Så prøvede bare at give hende en masse værdi, så hun indser et forløb her vil være det helt rigtige for hende
B29: 45967 | C29: Steffen Nielsen | E29: 29 47 11 81 | F29: https://www.instagram.com/steffennielsen1980/ | H29: Setter | I29: Offer & Didn't Buy | N29: Value | O29: Om han kunne selv | S29: Follow Up | T29: Jeg ringer til ham igen i morgen kl 13:45. Skulle have fundet mere pain, men syntes det var en svær snak. Skulle have kommet med de "kritisk spørgsmål noget før. Skulle have primet ham noget mere, for han siger han har været på andre kald før. Skulle have spurgt hvad har gjort du ikke har tog action den gang, hvilke resultater har det givet dig?
B30: 45968 | C30: Maiken | E30: 28 59 86 51 | F30: https://www.instagram.com/maikenvesth/ | H30: Setter | I30: Rescheduled
B31: 45968 | C31: Nanna Elisabeth Pedersen | E31: 42 44 95 68 | F31: https://www.instagram.com/nannaelisabethpedersen/ | H31: Setter | I31: Offer & Didn't Buy | N31: Value | O31: Var mest interesseret i de gratis planer | S31: Follow Up | T31: Syntes egenligt vi har en god snak, men ligesom hun ikke kører på alle cylindere. Bliver lidt en sjov afslutning både før jeg pitcher og efter, der siger hun allerede hun skal tænke over det. Så endte bare med at sende hende de gratis planer
B32: 45968 | C32: Benjamin Ejler | E32: 22 42 16 10 | F32: https://www.instagram.com/ejler2000/ | H32: Setter | I32: Split-pay | K32: 9000 | L32: 3000 | Q32: 6 | S32: Closed
B33: 45969 | C33: Mikkel Baungård Olesen | E33: 71 70 41 42 | F33: https://www.instagram.com/mikkel_bo99/ | H33: Setter | I33: Offer & Didn't Buy | N33: Money | O33: Sagde det var pengene | S33: Follow Up | T33: fik ham ikke solgt godt nok for ellers havde han jo købt. Ville hellere prøve selv så
B34: 45970 | C34: Alexander Mathiassen | E34: 22 58 27 00 | F34: https://www.instagram.com/alexandervalsgaard/ | H34: Setter | I34: Full-Pay | K34: 9000 | L34: 9000 | Q34: 6 | S34: Closed
B35: 45970 | C35: Laura Froberg | E35: 20 36 26 14 | F35: https://www.instagram.com/laurafroberg_/ | H35: Setter | I35: Offer & Didn't Buy | N35: Money | O35: Skulle finde ud af om hun havde pengene,s kulle til at sparre op til kørekort også | S35: Follow Up | T35: Syntes egenligt vi havde en god snak, fik stillet noget gode spørgsmål. Var under 18 og havde mor med på sidelinjen, så pressede ikke citronen for meget i forhold til objection handling. Sluttede på en god note om at hun havde en god mavefornemmelse. Ringer til hende og mor igen i morgen kl 16:15
B36: 45970 | C36: Bertram Geisler Jensen | E36: 53 85 60 95 | F36: https://www.instagram.com/bertram_gj/ | H36: Setter | I36: Split-pay | K36: 10500 | L36: 3000 | Q36: 6 | S36: Closed | T36: Fik ham bare totalt solgt med fucking meget conviction, han kunne hører jeg var eksperten og kunne se han var langt fra at af den nødvendige viden og fik af til at se, hvad er ville ske, hvis han ikke kom mål
B37: 45971 | C37: Kristian Weber Johansen | E37: 60 54 20 84 | F37: https://www.instagram.com/kristianweber05/ | H37: Setter | I37: Offer & Didn't Buy | N37: Fear | O37: Han havde pengene, tiden og følte sig tryg ved programemt | S37: Follow Up | T37: Han skulle bare tænke over det lød ikke på ham, som han var helt klar til at tage en beslutning her over telefonen, lige som det ikke var det, som han havde signet op til
B38: 45971 | C38: Tenna R Christensen | E38: 28 18 92 14 | F38: https://www.instagram.com/tenna.christensen/ | H38: Setter | I38: Offer & Didn't Buy | N38: Partner | O38: Skulle vende den med sin partner | S38: Follow Up Set | T38: Ringer til hende lørdag kl 15. Syntes egenligt jeg får hende spurgt godt ind, kunne godt have været mere aktivt lyttende, for ved jo, det er det som virker. Hun siger hun vil være klar til at investerer i sig selv. Skulle begynde at sprøge ind til om de bor alene eller hvordan, så jeg kan prehandle partner.
B39: 45971 | C39: Sidsel Kjellstrøm Larsen | E39: 93 99 05 28 | H39: Landing page | I39: Offer & Didn't Buy | N39: Time | O39: Havde forventet længden på forløber var 1 eller 2 måneder | S39: Follow Up Set | T39: Har en aftale med hende i morgen aften. Hun var en great to even greater prospect så ikke ret meget, pain så lagde ikke fokus på det, men skulle jeg nok og så konsekvenserne ved ikke at få styr på det.
B40: 45972 | C40: Mads Lund | E40: 29 89 17 57 | F40: https://www.instagram.com/lmads_/ | H40: Setter | I40: Offer & Didn't Buy | N40: Fear | O40: Ville syge gerne bare ikke få sig selv til det | S40: Follow Up Set | T40: Vil prøve at få hans forældre med på kald
B41: 45972 | C41: Julie Pietersen | E41: 41 20 09 82 | F41: https://www.instagram.com/juliapietersenn/ | H41: Setter | I41: Offer & Didn't Buy | N41: Think About It | S41: Follow Up | T41: Fik stillet hende nogle god spørgsmål og samtalen blev ret følelsesmæssig, endte med hun græd flere gang, så hun havde jo virkeligt dyb pain. Men vidste ikke om det var pengene værd. Vi objection handlede længe, hvor det endte med hun smed på, og jeg var også allerede gået 15 min over tid
B42: 45972 | C42: Lea Hedegaard Berg | E42: 41 81 73 21 | F42: https://www.instagram.com/leahedegaardberg/ | H42: Setter | I42: Offer & Didn't Buy | N42: Money | O42: Havde sagt ja og skulle starte d. 1 december | S42: Follow Up | T42: God snak, hun var rigtigt varm i forvejen, men fik hendes stadig solgt godt, og gik for premium forløbet, men hun var førtidspensionist så havde ikke det helt vilde at gøre med. Hun syntes hun havde taget en forhastet beslutning så endte med at melde fra selvom hun havde udfyldt det hele og var klar
B43: 45972 | C43: Emilia Breumlund Uldall Jepsen | E43: 29 91 37 21 | F43: https://www.instagram.com/emiliaujepsen/ | H43: Setter | I43: Split-pay | K43: 6500 | L43: 1500 | Q43: 6 | S43: Closed | T43: En jeg tidligere havde snakket med, hvor pengene holdte hende tilbage, så gik for downsell
B44: 45973 | C44: Maiken | E44: 28 59 86 51 | F44: https://www.instagram.com/maikenvesth/ | H44: Setter | I44: Offer & Didn't Buy | N44: Money | O44: Penge, og så også med at bruge dem på sig selv, istedte for andre | S44: Follow Up Set
B45: 45974 | C45: Chris Pedersen | E45: 71 36 14 48 | F45: https://www.instagram.com/bullietshot/ | H45: Setter | I45: Offer & Didn't Buy | N45: Money | O45: Stod ikke selv for sin økonmi | S45: Follow Up Set | T45: Rigtigt god snak, fat rigtigt meget pain og fik ham solgt godt og grundigt, hvis han selv stod for sin økonomi havde han overført med det sammen. Føler den er totalt ude af mine hænder
B46: 45975 | C46: Marcus Bank Topp | E46: 71 75 92 12 | F46: https://www.instagram.com/marcus__topp/ | H46: Setter | I46: Offer & Didn't Buy | N46: Money | O46: Mest interesseret i de gratis planer | S46: Follow Up
B47: 45976 | C47: Steen Bro Demant | E47: 40 35 72 92 | F47: https://www.instagram.com/steenbrodemant/ | H47: Setter | I47: Deposit | N47: Time | O47: Resten af den her måned var december passede bare dårligt | S47: Deposit (Follow Up Set) | T47: Har betalt opstart på 1500, og starter d. 1 januar
B48: 45976 | C48: Christian | E48: 42 31 19 95 | F48: https://www.instagram.com/chr_post12/ | H48: Setter | I48: No-Show | S48: Follow Up
B49: 45978 | C49: Gitte Kirkegaard | E49: 23 61 81 78 | F49: https://www.instagram.com/gittebkirkegaard/ | H49: Setter | I49: Offer & Didn't Buy | N49: Value | O49: Følte ikke rigtigt hun havde brug for hjælp lige nu | S49: Follow Up | T49: Finder intet pain, som i slet ingenting. Havde ærligt nok besluttet mig på forhånd, at jeg ikke vidste hvordan jeg skulle hjælpe hende
B50: 45978 | C50: Maria Daisy | E50: 60 52 63 76 | F50: https://www.instagram.com/mariadaisykjoensen/ | H50: Setter | I50: Offer & Didn't Buy | N50: Fear | O50: Hun havde penge, men insisterede på at sove på den | S50: Follow Up Set | T50: Gik for længe før jeg kommer med the killer question og fik fundet hendes pain, ikke godt nok
B51: 45978 | C51: Mathias Kamp | E51: 26 22 85 24 | F51: https://www.instagram.com/mathiaskamp/ | H51: Setter | I51: Offer & Didn't Buy | N51: Money | O51: Var stadig på lærlige løn, gik over på svendeløn fra december | S51: Follow Up Set | T51: Kunne godt have fået endnu mere pain ud af ham, hvordan det påvirkede ham og om hvad andre tænkte, bare virkeligt få ham til at føle den. Kunne godt have udfordret ham mere i forhold til at tage en beslutning og bruge den reframe ifht. "den måde han tager beslutninger på" eller hvis han var i min situaition
B52: 45978 | C52: Jessica Müller Winther | E52: 31 39 77 05 | F52: https://www.instagram.com/wintherjessica/ | H52: Setter | I52: Offer & Didn't Buy | N52: Money | O52: Pengene der holdte hende tilbage og så det her med at binde sig til noget | S52: Follow Up | T52: Skulle have udfordret hende mere, når hun komme med vage svar, også i forhold til hvor vigtigt det var for hende
B53: 45979 | C53: Marcus Haun | E53: 21 64 86 12 | F53: https://www.instagram.com/marcus.haun.1/ | H53: Setter | I53: Offer & Didn't Buy | S53: Follow Up
B54: 45979 | C54: Anne-Marie Asperup | E54: 28 23 51 52 | F54: https://www.instagram.com/asperup/ | H54: Setter | I54: Deposit | N54: Time | O54: Havde meget at se til resten af måneden, så starter 1. december | S54: Deposit (Follow Up Set) | T54: Kunne sagtens have fået mere pain ud af hende, føler lidt det er som om jeg er bange for at stille de svære spørgsmål, men ved også på den anden hånd det er det, som skal til for at lukke dem
B55: 45979 | C55: Jonas Victor | E55: 91 53 28 74 | F55: https://www.instagram.com/liljonasvictor/ | H55: Setter | I55: Deposit | N55: Money | O55: Han havde først pengene d. 1 december | S55: Deposit (Follow Up Set) | T55: Var en svær snak, for han havde bare verdens værste højtaler og mikrofon i sin telefon. Han havde først pengene til d. 1 december
B56: 45980 | C56: Dorthe Elmbo | E56: 61 27 72 04 | F56: https://www.instagram.com/elmbodorthe/ | H56: Setter | I56: Split-pay | K56: 10500 | L56: 1500 | Q56: 6 | S56: Closed
B57: 45980 | C57: Trine Kastrup | E57: 40 33 76 10 | F57: https://www.instagram.com/trine.kastrup/ | H57: Setter | I57: Offer & Didn't Buy | N57: Time | O57: Havde sagt på forhånd nu slet ikke var et sted, hvor det skulle være nu | S57: Hot Follow Up | T57: Jeg syntes hun var svært at danse med, kunne ikke rigtigt få noget konkret ud af hende, havde ikke nogle mål som sådan, andet end det var meget fluffy. Så finder faktisk ikke noget pain. Havde prøvet 2 andre forløb der ikke havde været nogen succes. Får ikke holdt frameworket på mine præmisser
B58: 45980 | C58: Magnus Nielsen | E58: 42 19 16 23 | F58: https://www.instagram.com/kursist87/ | H58: Setter | I58: Full-Pay | K58: 9000 | L58: 9000 | Q58: 6 | S58: Closed | T58: Havde rigtigt meget pain, som jeg kom ind på med det samme, så blev en kort snak. Han var heller ikke en mand af ret mange ord
B59: 45980 | C59: Mira Christiansen | E59: 60 17 09 13 | F59: https://www.instagram.com/itsmiravibes/ | H59: Setter | I59: Deposit | N59: Money | O59: Hun sagde hun var 80/20 i forhold til om det kunne lade sig gøre | Q59: 4 | S59: Follow Up Set | T59: Kunne godt have udfordret hende mere i forhold til pengene, hvor hun kunne finde nogle, og spørger en ekstra gang i stedet for bare at acceptere hendes svar. Men ved ikke om det var BS det hun sagde med hun var 80/20 om det. kunne lade sig gøre. Så valgte at slutte på en god tone, hvilket måske er lidt for naivt af mig
B60: 45981 | C60: William Henriksen | E60: 61 27 78 19 | F60: https://www.instagram.com/william_henriksen07/ | H60: Setter | I60: Offer & Didn't Buy | N60: Partner | O60: Var kun 18 så han skulle vende den med sin mor, men sagde tidligere på kaldet det var hans beslutning, så nok bare noget BS | S60: Hot Follow Up | T60: Skulle have dykket langt dybere i hans pain, selvom jeg finder noget er det kun en halv åben dør, den skal sku brækkes helt op.
B61: 45981 | C61: Brian Eriksson | E61: 42 15 89 92 | F61: https://www.instagram.com/sjonedk1971/ | H61: Setter | I61: Deposit | N61: Money | O61: Ville først kunne starte til Januar | S61: Deposit (Follow Up Set) | T61: Skulle have holdt ham mere på sporet i starten. Kunne ikke udfylde noget endnu, da han var ude at køre
B62: 45981 | C62: Ellen Ibsen | E62: 40 61 34 38 | F62: https://www.instagram.com/ellen_ibsen/ | H62: Setter | I62: Cancelled | N62: Fear | O62: Sagde hun havde meget angst og tiden ikke var til det selvom hun slev havde rakt ud
B63: 45983 | C63: Anna Dyreborg Frost | E63: 25 74 09 55 | F63: https://www.instagram.com/ellamyangel/ | H63: Setter | I63: Bad Fit & No Offer | O63: Ville have dårlgt samvittighed ved at sende hende videre | S63: X
B64: 45983 | C64: Nicolaj Mortensen | E64: 42 50 90 68 | F64: https://www.instagram.com/nicolajhmortensen/ | H64: Setter | I64: Bad Fit & No Offer | Q64: 6 | S64: X
B65: 45983 | C65: Sille Ahle | E65: 60 17 57 21 | F65: https://www.instagram.com/sille_ahle/ | H65: Setter | I65: Split-pay | K65: 10500 | L65: 3000 | Q65: 6 | S65: Closed
B66: 45985 | C66: Sofiya | E66: 53 56 22 26 | F66: https://www.instagram.com/sofiya_saint_/ | H66: Setter | I66: Offer & Didn't Buy | N66: Value | O66: Var sikker på hun skulle have en personligtræner | S66: Hot Follow Up | T66: Hun følte ikke det var det rigtige for hende , hun syntes hun skulle have en PT i stedet for, så fik hende ikke solgt godt nok, og kom også med dårlige svar under pitchen og efter.
B67: 45985 | C67: Rikke L Petersen | E67: 31 69 60 04 | F67: https://www.instagram.com/petersenrikkel/ | H67: Setter | I67: Rescheduled | T67: Gik direkete på telefonsvarer
B68: 45986 | C68: Mette Vilsen Kragholm | E68: 24 83 19 85 | F68: https://www.instagram.com/mettekragholm/ | H68: Setter | I68: Offer & Didn't Buy | N68: Partner | O68: Skulle vende den med sin mand | S68: Follow Up Set | T68: Bliver en aaaaalt for lang snak, har svært ved at styre de der sludrechatoler, og holde samtalen på sporet. Får ikke prehandlet ordenligt hun siger tidligt i kaldet hun skal vende den med med manden, men får jeg slet ikke vendt. Får spurgt hende, hvis ansvar det er at tage action på det her, det er hende siger hun, så skulle jeg 100 procent have noteret det med manden "Hvad så i forhold til at vende den med ham
B69: 45986 | C69: Rikke-Cæcilie Kronvold Carlsen | E69: 27 11 59 56 | F69: https://www.instagram.com/rikkecaecilie/ | H69: Setter | I69: Rescheduled
B70: 45988 | C70: Liv Bjørn Larsen | E70: 25 59 89 90 | F70: https://www.instagram.com/livbjoernlarsen/ | H70: Setter | I70: Offer & Didn't Buy | N70: Money | O70: Var allerede på wegoovy, så havde ikke penge til coaching også. Havde været ved 3 andre coach, som ikke hvad hjulpet hende, så ville meget gerne holde fast i wegoovyen, fordi det var det første som havde hjulpet hende | S70: Follow Up | T70: Skulle have dykket mere ned i hvorfor hun havde valgt at tage en samtale, nu når hun havde været på 3 andre mislykket forløb, hvorfor hun så tror det her var noget for hende. Hun siger til sidst hun sagde i DM hun ikke havde pengene, så det lød som om det irriterede hende vi ikke havde taget højde for det.
B71: 45988 | C71: Kristian Nordahl Lange | E71: 23 80 80 16 | F71: https://www.instagram.com/nordahlkristian/ | H71: Setter | I71: Full-Pay | K71: 9000 | L71: 9000 | N71: Money | O71: Var meget nervøs for pengene, men fik prehandlet den godt | Q71: 6 | S71: Closed | T71: Syntes jeg var rigtig god på det her kald, bragte den hel god energi, var overbevisende og fik prehandlet hans money objection rigtigt og talt ind i hvad der ville være mest værd på sigt, at have det lidt hårdt nu, men kunne have det fucking fedt på den anden side
B72: 45989 | C72: Nina E. Bruun | E72: 52 39 98 08 | F72: https://www.instagram.com/ninabruun_solsikkepige_denmark/ | H72: Setter | I72: Split-pay | K72: 10500 | L72: 1500 | N72: Money | O72: Hun syntes det var mange penge, men ville være villig til at finde dem | Q72: 6 | S72: Closed | T72: Skal styre hende bedre, når hun bare. begynder og snakke om alt muligt andet. Skal komme hurtigere ind på de rigtige spørgsmål, der går alt alt for længe
B73: 45989 | C73: Trine Snitgaard Betzer Nielsen | E73: 40 79 70 20 | F73: https://www.instagram.com/trinebnielsen/ | H73: Setter | I73: Split-pay | K73: 10500 | L73: 3000 | Q73: 6 | S73: Closed
B74: 45990 | C74: Sacha Heron | E74: 44 11 20 36 | F74: https://www.instagram.com/h_sacha/ | H74: Setter | I74: Split-pay | K74: 9000 | L74: 1500 | Q74: 6 | S74: Closed
B75: 45990 | C75: Kira Theander Price | E75: 51 70 16 52 | F75: https://www.instagram.com/kiratheanderpriice/ | H75: Setter | I75: Split-pay | K75: 9000 | L75: 1500 | Q75: 6 | S75: Closed
B76: 45990 | C76: Rikke L Petersen | E76: 31 69 60 04 | F76: https://www.instagram.com/petersenrikkel/ | H76: Setter | I76: No-Show
B77: 45991 | C77: Merle Iversen | E77: 25 69 65 21 | I77: No-Show
B78: 45991 | C78: Nanna Starris-Reiffenstein | E78: 42 18 03 22 | F78: https://www.instagram.com/nansen_07/ | H78: Setter | I78: Rescheduled
B79: 45991 | C79: Arsan Pourmozaffari | E79: 30 30 33 54 | F79: https://www.instagram.com/arsan.pourmozaffari?igsh=NTd6dHJpcmxuMXIy | H79: Setter | I79: Offer & Didn't Buy | N79: Money | S79: Follow Up | T79: Mit fokus ligger for meget på at prehandle de objections jeg vidste ville komme i stedet for at dykke ned i hendes pain og virkeligt få hende til at føle den

Sheet Dec
A1: a | B1: Rep: | C1: Name | E1: Anton KPI's | H1: Outcome | K1: KPIs% | N1: Show Rate | Q1: Objections | T1: Source
E2: Rev per call | F2: =C3/C6 -> 4345.4545 | H2: Full-Pay: | I2: =IFERROR(COUNTIFS(I13:I287, "Full-Pay"),"") -> 3 | K2: Conversion Rate: | L2: =iferror(L10/L8,"") -> 0.41818182 | N2: Rescheduling Rate: | O2: =iferror(I8/L6,"") -> 0.092307692 | Q2: Think About It | R2: =IFERROR(COUNTIFS(N13:N286, "think about it"),"") -> 3 | T2: Reschedule | U2: =IFERROR(COUNTIF(H13:H286,T2),"") -> 0
B3: Revenue | C3: =IFERROR(SUM(K13:K283),"") -> 239000 | E3: Cash per call | F3: =C4/C6 -> 1471.8182 | H3: Split-Pay: | I3: =IFERROR(COUNTIFS(I13:I287, "Split-Pay"),"") -> 20 | K3: Offer To Close Rate: | L3: =IFERROR(L10/L9,"") -> 0.44230769 | N3: Cancellation Rate: | O3: =iferror(I9/L6,"") -> 0.061538462 | Q3: Money | R3: =IFERROR(COUNTIFS(N13:N286, "money"),"") -> 18 | T3: YouTube | U3: =IFERROR(COUNTIF(H13:H286,T3),"") -> 0
B4: Cash | C4: =IFERROR(SUM(L13:L284),"") -> 80950 | E4: Cash upfront % | F4: =C4/C3*100 -> 33.870293 | H4: Deposits: | I4: =IFERROR(COUNTIFS(I13:I287, "Deposit"),"") -> 6 | K4: Call To Offer Rate: | L4: =IFERROR(L9/L8,"") -> 0.94545455 | N4: No-Shows Rate: | O4: =iferror(I10/L6,"") -> 0 | Q4: Time | R4: =IFERROR(COUNTIFS(N13:N286, "time"),"") -> 3 | T4: YouTube Ads | U4: =IFERROR(COUNTIF(H13:H286,T4),"") -> 0
E5: PIF % | F5: =I2/C7*100 -> 13.043478 | H5: Offer & Didn't Buy: | I5: =IFERROR(COUNTIFS(I13:I287, "Offer & Didn't Buy"),"") -> 23 | K5: Drag Over Rate: | L5: =IFERROR(I7/(C6+I7+I8),"") -> 0 | N5: Drag Over Rate: | O5: =iferror(I7/L6,"") -> 0 | Q5: Partner | R5: =IFERROR(COUNTIFS(N13:N286, "partner"),"") -> 4 | T5: Email | U5: =IFERROR(COUNTIF(H13:H286,T5),"") -> 0
B6: Total Calls : | C6: =IFERROR(SUM(I2:I6),"") -> 55 | E6: Average Binding | F6: =AVERAGE(Q13:Q104) -> 5.962963 | H6: Bad Fit & No Offer: | I6: =IFERROR(COUNTIFS(I13:I287, "Bad Fit & No Offer"),"") -> 3 | K6: Bookings: | L6: =IFERROR(SUM(I2:I10),"") -> 65 | N6: Show-Up Rate: | O6: =iferror(L7/L6,"") -> 0.84615385 | Q6: Fear | R6: =IFERROR(COUNTIFS(N13:N286, "fear"),"") -> 2 | T6: Facebook | U6: =IFERROR(COUNTIF(H13:H286,T6),"") -> 0
B7: Total Won : | C7: =IFERROR(I2+I3,"") -> 23 | E7: Average deal | F7: =C3/C7 -> 10391.304 | H7: Drag Over & Show: | I7: =IFERROR(COUNTIFS(I13:I287, "Drag Over & Show"),"") -> 0 | K7: Shows: | L7: =IFERROR(SUM(I2:I7),"") -> 55 | N7: Conducted Rate: | O7: =IFERROR(L8/L6,"") -> 0.84615385 | Q7: Value | R7: =IFERROR(COUNTIFS(N14:N287, "value"),"") -> 3 | T7: Facebook Ads | U7: =IFERROR(COUNTIF(H13:H286,T7),"") -> 0
B8: Total Lost : | C8: =COUNTIF(I13:I286,"offer & didn't buy")+countif(I13:I286,"deposit")+countif(I13:I286,"bad fit & no offer") -> 32 | E8: Average cash | F8: =C4/C7 -> 3519.5652 | H8: Rescheduled: | I8: =IFERROR(COUNTIFS(I13:I287, "Rescheduled"),"") -> 6 | K8: Calls: | L8: =IFERROR(SUM(I2:I6),"") -> 55 | T8: LinkedIn | U8: =IFERROR(COUNTIF(H13:H286,T8),"") -> 0
B9: Closing % : | C9: =iferror(SUM(C7/C6),"") -> 0.41818182 | H9: Cancelled: | I9: =IFERROR(COUNTIFS(I13:I287, "Cancelled"),"") -> 4 | K9: Offers: | L9: =IFERROR(sum(I2:I5),"") -> 52
H10: No-Show: | I10: =IFERROR(COUNTIFS(I13:I287, "No-Show"),"") -> 0 | K10: Deals | L10: =I2+I3 -> 23
B12: Date | C12: Name | E12: Phone No. | F12: IG | H12: Source | I12: Outcome | K12: Revenue | L12: Cash | N12: Objection | O12: Objection Notes | Q12: Length | R12: Recording Link | S12: Follow Up/Next Steps | T12: Call Summary
B13: 45992 | C13: Andreas Frederiksen | E13: 30 83 43 02 | F13: https://www.instagram.com/andrewmf87/ | H13: Setter | I13: Split-pay | K13: 10500 | L13: 3000 | Q13: 6 | S13: Closed
B14: 45992 | C14: Oskar Kjærsgaard | E14: 61 45 22 41 | F14: https://www.instagram.com/oskar_kjaersgaard/ | H14: Setter | I14: Split-pay | K14: 10500 | L14: 3000 | Q14: 6 | S14: Closed
B15: 45992 | C15: Tina Thomsen | E15: 23 36 64 19 | F15: https://www.instagram.com/tina_lthomsen/ | H15: Setter | I15: Split-pay | K15: 9000 | L15: 3000 | Q15: 5 | S15: Closed
B16: 45992 | C16: Anne-Marie Asperup | E16: 28 23 51 52 | F16: https://www.instagram.com/asperup/ | H16: Setter | I16: Split-pay | K16: 9000 | L16: 1500 | Q16: 6 | S16: Closed
B17: 45992 | C17: Kholud El Masri | E17: 93 84 32 22 | F17: https://www.instagram.com/kholud_elmasri/ | H17: Setter | I17: Split-pay | K17: 9000 | L17: 1500 | Q17: 6 | S17: Closed
B18: 45992 | C18: Anaa Ramadan | E18: 22 88 46 33 | F18: https://www.instagram.com/frk_ramadan?igsh=aGp2cGo1a2kxMXJj | H18: Setter | I18: Split-pay | K18: 9000 | L18: 1500 | Q18: 6 | S18: Closed
B19: 45992 | C19: Magda De Castro | E19: 71 58 53 12 | F19: https://www.instagram.com/magda_d_castro/ | H19: Setter | I19: Offer & Didn't Buy | N19: Money | O19: Skulle være sikker på hun kunne sige helt ja | S19: Follow Up | T19: Skulle have vendt tilbage til det her med hun udsatte tingene og challenge hende på hendes måde at tage beslutninger på
B20: 45992 | C20: Nanna Starris-Reiffenstein | E20: 42 18 03 22 | F20: https://www.instagram.com/nansen_07/ | H20: Setter | I20: Rescheduled
B21: 45993 | C21: Jonas Victor | E21: 91 53 28 74 | F21: https://www.instagram.com/liljonasvictor/ | H21: Setter | I21: Split-pay | K21: 10500 | L21: 3000 | Q21: 6 | S21: Closed
B22: 45993 | C22: Maria Louise Buus Nielsen | E22: 61 27 02 96 | F22: https://www.instagram.com/marialouisebuus?igsh=MXEzb3Q5cW5uMjkxeA== | H22: Setter | I22: Offer & Didn't Buy | N22: Time | O22: Stod midt i en graviditet med kejsersnit, så kunne først være henne i slut januar starte februar | S22: Follow Up | T22: Skulle have gjort hendes mål mere specifikt og malet billedet noget bedre. Syntes det var svært ifht. hun stod midt i en graviditet, så er det svært at lave konsekvens ved ikke at tage action fordi hun kan ikke tage action før efter hun har født og kommet sig over sig kejsersnit.
B23: 45993 | C23: Gitte Christensen | E23: 42 32 89 14 | F23: https://www.instagram.com/gitte_betinalaulau?igsh=MTMwb29panlnbm12bg== | H23: Setter | I23: Offer & Didn't Buy | N23: Partner | O23: 100 procent bs, hun skulle vende den med partner | S23: Follow Up | T23: Fik ikke bygget nok pain i starten af kaldet, især i forhold til hvordan hun så ud, og hvorfor hun ikke var tilfreds med det, så var hun bare ikke solgt nok for hun havde pengene, tiden, og det kun var for at informere sin mand, så reelt ikke noget der holdte hende tilbage, men kan jo regne ud der var et eller andet.
B24: 45993 | C24: Dina Alexandra Pedersen | E24: 53 62 80 49 | F24: https://www.instagram.com/dinaaa_alexandra/ | H24: Setter | I24: Bad Fit & No Offer | N24: Value | O24: Virkede slet ikke til hun var klar over hvorfor vi sad der | S24: Follow Up | T24: Var virkeligt svær at få noget ud af, men ender alligevel med at snakke med hende i 30 minutter, men offer hende aldrig dealen. Skal gerne erkende jeg havde givet op på hende tidligt i kaldet og nok noget hun kunne mærke
B25: 45994 | C25: Lene Bjerre | E25: 40 33 96 48 | F25: https://www.instagram.com/bjerre1986/ | H25: Setter | I25: Full-Pay | K25: 9000 | L25: 9000 | Q25: 6 | S25: Closed | T25: Dejlig snak, kom ind på det som var vigtigt for hende hun blev også rørt på et tidspunkt ifht. hvis hun ikke gjorde noget, så fik gjort det vigtigt for hende, som var vigtigt fordi hun aldrig havde prioriteret sig selv
B26: 45994 | C26: Kristina Wentzel | E26: 28 72 13 52 | F26: https://www.instagram.com/kristinawentzel_1991/ | H26: Setter | I26: Deposit | N26: Money | O26: Havde ikke pengene i december, så vi starter hende op til januar | S26: Closed | T26: Var vigtigt for hende endeligt at gøre noget godt for sig selv. Nu var det på tide
B27: 45994 | C27: Frederik Dalgaard høj | E27: 42 31 38 59 | F27: https://www.instagram.com/frederdalgaard/ | H27: Setter | I27: Split-pay | K27: 9000 | L27: 1500 | Q27: 6 | S27: Closed
B28: 45995 | C28: Stephanie Barner Æbeløe Jørgensen | E28: 60 89 71 08 | F28: https://www.instagram.com/stephanie_barner/ | H28: Setter | I28: Offer & Didn't Buy | N28: Partner | O28: Skulle snakke øknomi med partneren | S28: Follow Up | T28: Kunne godt at have trukket pain endnu længere ud. Skulle 100 procent have prehandlet partner objectionen, om det var hendes beslutningen eller mandens
B29: 45995 | C29: Alexander | E29: 23 92 90 71 | F29: https://www.instagram.com/alexsorensen_?igsh=MXF4NjVuNHQxaGdkbw== | H29: Setter | I29: Offer & Didn't Buy | N29: Money | O29: Havde ikke et arbejde pt | S29: Hot Follow Up | T29: Skulle have prehandlet hans money objection bedre, han stod i en situation hvir han ikke havde et job og lige var flyttet hjemmefra. Skulle virkeligt have taget ham endnu mere ned i pain, så han virkeligt følte den
B30: 45995 | C30: Nikolai Holt Petersen | E30: 51 92 18 24 | I30: Full-Pay | K30: 8000 | L30: 8000 | Q30: 6 | S30: Closed
B31: 45998 | C31: Jeanette | E31: 24 61 64 25 | F31: https://www.instagram.com/jeanettegylling?igsh=bGQyeW1wOHJzM3My | H31: Setter | I31: Offer & Didn't Buy | N31: Think About It | O31: Hun havde noget der hed proteinurin, så meget gerne ville have hun skulle have undersøgt | S31: Follow Up | T31: Får ikke holdt godt nok styr på samtalen, hun skulle være ledt meget mere og afbrudt hende, når hun bare begyndt at snakke. Men også en anderledes snak for hun havde den her nyresygdom, så ville ikke kunne sende hende videre med god samvittighed, før det var undersøgt
B32: 45998 | C32: Jan Kenneth Bøge Jensen | E32: 40 94 14 11 | F32: Han siger mange gange, at han ikke er helt utilfreds, men er utilfreds. Skal være lidt hårdere ved ham der og få ham til at anse, så længe han siger det kan han ikke lave en ændring. | H32: Setter | I32: Offer & Didn't Buy | N32: Money | O32: Havde ikke pengene nu | S32: Follow Up | T32: Skal være meget mere ledende og direkte, i mine samtaler for de er sku begyndt at trække for langt ud. Skulle have fundet mere pain komme med killer spørgsmålet tidligere. Skulle have prehandlet hans money objection, for kunne hører, det godt kunne komme til at ske, fordi han brugte penge hver dag på tanken. Kan sku godt være lidt hårdere
B33: 45998 | C33: Alexander Vibeholm | E33: 22 58 21 88 | F33: https://www.instagram.com/alexandervibeholm/ | H33: Setter | I33: Cancelled
B34: 45998 | C34: Gabriella Mikkelsen | E34: 42 15 37 43 | F34: https://www.instagram.com/gabriella_956/ | H34: Setter | I34: Deposit | K34: 9000 | L34: 1500 | Q34: 6 | S34: Closed | T34: Han kvinde af få ord, men fandt pain og prehandlet hendes money concern, som så endte ud i et salg
B35: 45998 | C35: Sara V Macedo | E35: 53 66 25 26 | F35: https://www.instagram.com/sara_v_macedo/ | H35: Setter | I35: Offer & Didn't Buy | N35: Money | O35: Syntes det var for mange penge | S35: Follow Up | T35: Hun ville give sig i kast med sine egne programmer. Gik ind til samtalen med en dårlig attitude, spørg mig ikke hvorfor havde bare ikke min bedste dag
B36: 45999 | C36: Line Kamstrup | E36: 61 30 69 27 | F36: https://www.instagram.com/linekamstrup/ | H36: Setter | I36: Offer & Didn't Buy | N36: Money | O36: Stod ikke selv for sin egen økonomi | S36: X | T36: Vi slår hovederne sammen igen på fredag. Kunne godt have gjort samtalen lidt kortere og ledt hende mere
B37: 45999 | C37: Olga Dmytruk | E37: 27 57 32 45 | F37: https://www.instagram.com/olgad_k?igsh=MTRmeXljbTRrNzlvMg== | H37: Setter | I37: Offer & Didn't Buy | N37: Fear | O37: Hun havde penge, men skulle være 100 procent sikker | S37: X | T37: Skal helt klart blive bedre til at stille mere præcise sprøgsmål, og så dykke mere ned i detaljen nærmest diagnosticere ligesom en læge ville gøre det for at finde pain.
B38: 45999 | C38: Albert Fuglsang-Madsen | E38: 71 48 66 39 | F38: https://www.instagram.com/fuglsangmadsen/ | H38: Setter | I38: Bad Fit & No Offer | N38: Value | O38: Syntes ikke det var noget for ham | S38: X | T38: Skulle have grebet det fra en anden indgangsvinkel, med at han havde været i gang i et halvt år, hvor han ikke rigtigt havde set nogle resultaer og spørger ind til "Hvad mener du med det? Trækker meget på det når jeg spørger indtil om han er 100 procent tilfreds med spejlbilledet, det skal han udfordres på. Han siger han har det "fint" med hvordan han ser ud, men var sku ikke meget for jeg stillede ham de spørgsmål
B39: 45999 | C39: Tobias Jørgensen | E39: 21 56 41 05 | F39: https://www.instagram.com/tonser12/ | H39: Setter | I39: Deposit | N39: Time | O39: Han kunne ikke starte før d. 22 Januar | Q39: 6 | S39: Deposit (Follow Up Set) | T39: Vi starter ham på d. 22 januar og er nærmest 100 procent sikker på han kommer i gang. Vi havde en god snak og fik sat nogle gode perspektiver på, så han indså det var vigtigt for ham. Ved ikke om jeg skulle have udfordret ham mere på at han skulle smide penge i dag.
B40: 46000 | C40: Freya Pallesgaard | E40: 53 27 22 38 | F40: https://www.instagram.com/msoedorf/ | H40: Setter | I40: Deposit | N40: Time | O40: Hun havde ikke budgeteret med pengene den her måned men er klar til Januar | Q40: 6 | S40: Deposit (Follow Up Set) | T40: Hun starter til d. 2 Januar. Skulle have spurgt ind til hvad der kunne ske til januar, så det ikke kunne lade sig gøre, og så bare dobbeldown efter price drop
B41: 46001 | C41: Michelle Sødorf Svendsen | E41: 22 34 75 80 | F41: https://www.instagram.com/msoedorf/ | H41: Setter | I41: Split-pay | K41: 10500 | L41: 3000 | Q41: 6 | S41: Closed
B42: 46001 | C42: Dea Nordstrøm Ferré | E42: 23 73 88 14 | F42: https://www.instagram.com/dunsemarie/ | H42: Setter | I42: Full-Pay | K42: 9000 | L42: 9000 | N42: Think About It | O42: Skulle bare lige vende den i hovedet og med manden | Q42: 6 | S42: Closed | T42: Skulle bare have fuldt framework, doubledown, value og clarify pengene, og så have brugt det vi gennem gik med fear objection og reframe, men skal gerne indrømme jeg ikke følte mig helt komfortable med at gøre det, fordi jeg ikke havde øvet det og gennemgået det i hovedet. Skulle have brugt den her med "Har du taget en stor beslutning før?" - "Hvordan føles det inde? Hvad så med efter?"
B43: 46001 | C43: Louise Fliis Schwærter | E43: 52 40 86 87 | F43: https://www.instagram.com/louiseschwaerter/ | H43: Setter | I43: Offer & Didn't Buy | N43: Money | O43: Det var økonomien der holdte hende igen | S43: Follow Up | T43: Finder slet ikke nok pain, syntes det var svært at finde noget, vil faktisk sige det er decideret ringe, men syntes ærligt det var svært med hende. Jeg fik til gengæld øvet det her med hun bare skulle tænke over det. Glemmer desværre det her med, hvad konsekvensen er ved slet ikke at gøre noget. Tænker hvis der var fundet mere pain var hun lukket, for så så hun også mere value i det
B44: 46002 | C44: Berfe Zeynep Sari | E44: 51 72 25 14 | F44: https://www.instagram.com/berfezeynep3/ | H44: Landing page | I44: Deposit | L44: 700 | N44: Money | O44: Havde ikke mere end 700 kr. her i december | Q44: 6 | S44: Deposit (Follow Up Set) | T44: Hun kunne kun smide 700 kr. nu her og så betaler hun resten af opstarten og for først måned, en måned fra nu
B45: 46002 | C45: Nanna Starris-Reiffenstein | E45: 42 18 03 22 | F45: https://www.instagram.com/nansen_07?igsh=MTY1ajVyY3p6dDhjdA== | H45: Setter | I45: Cancelled | S45: Hot Follow Up
B46: 46002 | C46: Ann Michelle Woltemaht | E46: 61 33 37 22 | F46: https://www.instagram.com/woltemaht?igsh=c2czNGF3eTQyYzYy | H46: Setter | I46: Split-pay | K46: 9000 | L46: 1500 | Q46: 6 | S46: Closed
B47: 46003 | C47: Trine Mortensen | E47: 21 51 37 51 | F47: https://www.instagram.com/gnominden/ | H47: Setter | I47: Offer & Didn't Buy | N47: Money | O47: Pengene der holdte hende tilbage | S47: Follow Up | T47: Får ikke fundet nok pain, følte mig træt og lidt ugidelig her til først kald, hvilket gjorde jeg ikke fik fik fundet nok pain og bygget nok value. Syntes sku selv det lød til for robotagtigt, der var ikke rigtigt flow i samtalen, blev mere et interview end en samtale.
B48: 46003 | C48: Elisabeth Ryaa | E48: 26 54 60 86 | F48: https://www.instagram.com/ryaa32/ | H48: Setter | I48: Offer & Didn't Buy | N48: Partner | O48: Var urokkelig skulle vende den med manden | S48: X | T48: Syntes det er en hård fin balance ar finde i forhold til at presse på i objectionhandling, valgte at gå med mavefornemmelse at hun bare lige skulle informere manden om inden hun brugte penge. Vi har aftalt at sætte det hele op på søndag kl 9
B49: 46003 | C49: Kenneth Nørgaard Jensen | E49: 31 55 50 41 | F49: https://www.instagram.com/knj_87/ | H49: Setter | I49: Split-pay | K49: 10500 | L49: 3000 | Q49: 6 | S49: Closed
B50: 46003 | C50: Sille | E50: 20 36 61 20 | F50: https://www.instagram.com/sille07/ | H50: Setter | I50: Split-pay | K50: 10500 | L50: 3000 | Q50: 6 | S50: Closed | T50: Hun var meget det der med, jeg er jo okay tilfreds, og så slemt er det ikke, så jeg kaldte hende bare ud på det, og så kunne hun jo egenligt godt set det selv
B51: 46003 | C51: Helena Olsen | E51: 22 27 57 23 | F51: https://www.instagram.com/helenaaaolsen/ | H51: Setter | I51: Cancelled
B52: 46004 | C52: Pernille | E52: 27 62 43 49 | F52: https://www.instagram.com/pernille_upside_down/ | H52: Setter | I52: Split-pay | K52: 10500 | L52: 3000 | Q52: 6 | S52: Closed
B53: 46005 | C53: Anja Kristensen | E53: 20 40 44 01 | F53: https://www.instagram.com/anjakristensen6/ | H53: Setter | I53: Split-pay | K53: 10500 | L53: 3000 | Q53: 6 | S53: Closed | T53: Hun sagde mange gange, hun egenligt godt vidste, hvad der skulle til, fordi hun selv var coach, så spurgt hende også rigtigt mange gange, hvorfor hun så har brug for hjælp
B54: 46006 | C54: Cecilie Kjær | E54: 26 19 67 80 | F54: https://www.instagram.com/cecilie_t_kjaer?igsh=MTF6b2M3OGgwY2x3eA== | H54: Setter | I54: Cancelled
B55: 46006 | C55: Maria Koll | E55: 25 14 95 18 | F55: https://www.instagram.com/m_koll/ | H55: Setter | I55: Deposit | N55: Money | O55: Det var for mange penge her i december måned, men er klar til januar | S55: Deposit (Follow Up Set) | T55: Hun havde ikke penge lige nu, men sagde hun var totalt klar til januar, så gik efter deposit til Januar. Spurgte hende flere gange om hun var sikker om det kunne lade sig gøre til januar, og hvordan det føles at have taget den her beslutning. Så har ro i maven, om hun nok skal betale til Januar
B56: 46006 | C56: Johnny Bech Jensen | E56: 42 18 67 17 | F56: https://www.instagram.com/johnnybechjensen8230/ | H56: Setter | I56: Rescheduled
B57: 46006 | C57: Betina | E57: 93 10 11 22 | F57: https://www.instagram.com/laerkeredensunivers/ | H57: Setter | I57: Offer & Didn't Buy | N57: Money | O57: Havde simpelthen ikke pengene | S57: Follow Up | T57: Går lidt for lang tid før, jeg stiller de svære spørgsmål. Får ikke prehandlet hendes money objection ordenligt, skulle jeg have gjort bedre. Skulle have spurgt mere konkret hvad hendes penge går til, og kommer også til at handle for meget om pengene
B58: 46007 | C58: Bitten Boelt Nielsen | E58: 23 29 16 49 | F58: https://www.instagram.com/bittenboelt/ | H58: Setter | I58: Split-pay | K58: 16500 | L58: 4000 | Q58: 6 | S58: Closed | T58: Gav hende sygt meget kontrol, skulle nærmest ikke spørge hende, hun kom bare med alt selv, så spurgte bare hvorfor det var vigtigt for hende og så konsekvesen ved ikke at komme i mål. Så også spørge indtil hvorfor vi så sidder her, hvis hun har prøvet så mange forskellige coaches
B59: 46007 | C59: Sabine Hjorth Jensen | E59: 31 13 84 07 | F59: https://www.instagram.com/sabine5026/ | H59: Setter | I59: Split-pay | K59: 9000 | L59: 1500 | Q59: 6 | S59: Closed | T59: Syntes jeg gjorde det virkeligt godt på det her kald fik hende solgt, fik klaret de objections hun kom med. Fulgte bare frameworket til punkt og prikke og sørgede for at være totalt hjælpende. Er sku stolt af mig selv efter det her kald
B60: 46007 | C60: Henrik | E60: 50 73 56 58 | F60: https://www.instagram.com/henrikt2000/ | H60: Setter | I60: Rescheduled
B61: 46007 | C61: Johnny Bech Jensen | E61: 42 18 67 17 | F61: https://www.instagram.com/johnnybechjensen8230/ | H61: Setter | I61: Offer & Didn't Buy | N61: Value | O61: Han sagde det var pengene, men var i bund og grund value | S61: Follow Up | T61: Får ærligt ikke solgt ham godt nok, får ikke nok pain ud af ham, som gør at han ikke ser value i det, og derfor ikke er villig til at købe. Så discoveryen skal ses igennem, for hvad der kunne gøres anderledes
B62: 46009 | C62: Helena Olsen | E62: 22 27 57 23 | F62: https://www.instagram.com/helenaaaolsen/ | H62: Setter | I62: Rescheduled
B63: 46009 | C63: Emma | E63: 30 12 40 39 | F63: https://www.instagram.com/emmawolf.farbaek/ | H63: Setter | I63: Split-pay | K63: 9000 | L63: 4500 | Q63: 6 | S63: Closed
B64: 46010 | C64: Trine Haboe la Cour | E64: 50 59 66 90 | F64: https://www.instagram.com/trinehaboelacour/ | H64: Setter | I64: Rescheduled | O64: Hun har en baby på armen, så kunne ikke gennemfører snakker så ringer til hende igen d. 29. Endte aldrig med at pitche | S64: Follow Up | T64: Skulle have holdt samtlane kortere, og bryde noget mere ind når hun snakkede lort. Nåede ikke at pitche for hende og hun havde gang i alle mulige ting imens, fordi babyen vågnede. Vil gerne have en rutine, der passede til hende som hjemmegående mor på barsel med 2 smål børn, så hun kunne få noget mere overskud og energi, og ikke være den her sure mor
B65: 46010 | C65: Simone Dyveke Damgaard Jensen | E65: 20 94 51 84 | F65: https://www.instagram.com/simoneddj/ | H65: Setter | I65: Offer & Didn't Buy | N65: Money | O65: Hun syntes det var mange penge | S65: Follow Up | T65: Får det ikke gjort håndgribeligt nok og får et specifikt nok mål, det bliver for fluffy, det bliver ikke vigtigt nok
B66: 46010 | C66: Henrik | E66: 50 73 56 58 | F66: https://www.instagram.com/henrikt2000/ | H66: Setter | I66: Offer & Didn't Buy | N66: Money | S66: Follow Up | T66: Syntes det var en svært samtale, ikke lige en avatar jeg var vant til at snakke med. Han stod allerede godt trænede 6 gange om ugen gik meget op i kosten, og syntes egenligt ikke han vil bruge penge på det når han allerede så resultater. Så syntes det var svært at finde pain, som jeg heller ikke rigtigt får gjort
B67: 46010 | C67: Mathias Tobiesen | E67: 22 16 18 62 | F67: https://www.instagram.com/mtobiesen_/ | H67: Setter | I67: Rescheduled
B68: 46010 | C68: Jeannet | E68: 61 70 83 16 | F68: https://www.instagram.com/jeannet_707/ | H68: Setter | I68: Offer & Didn't Buy | N68: Money | O68: Stod ikke selv for sin økonomi, skulle snakke med sin vejleder | S68: X | T68: Stod desværre ikke selv for sit budget, så kunne hverken sige ja eller nej. Skulle dykke med ned i pain og virkeligt få hende til at føle din, og få det til at blive mere flydende
B69: 46012 | C69: Anton Emil Christensen | E69: 24 97 33 22 | F69: https://www.instagram.com/antonemil.ch/ | H69: Setter | I69: Offer & Didn't Buy | N69: Fear | O69: Kunne ikke få ham til at tage beslutningen | S69: Follow Up | T69: Skulle have fundet endnu dybere pain. Han smed alle objections efter mig, så kom ned til noget frygt. Skulle have udfordet ham på "hvis du fortæller dig selv du ikke kan tage beslutninger, så er det jo sådan det bil blive".
B70: 46018 | C70: Jesper Boelt Johnsen | E70: 42 42 53 61 | F70: https://www.instagram.com/jesper_boelt/ | H70: Setter | I70: Split-pay | K70: 10500 | L70: 3000 | N70: Partner | O70: Ville rigtigt gerne snakke med forældrene, men fik ham til at sende 1500 alligvel | Q70: 6 | S70: Closed | T70: Synts jeg virkede lidt rusten og stillede nogle halv dårlige spørgsmål undervejs, men gik jo godt alligevel
B71: 46019 | C71: Lærke Bøgehave Kristiansen | E71: 27 19 49 77 | F71: https://www.instagram.com/laerke_boegehave/ | H71: Setter | I71: Offer & Didn't Buy | N71: Money | O71: Kunne ikke finde pengene | S71: Follow Up | T71: Får slet ikke gjort det vigtigt nok for hende, og finder hendes pain, skal udfordre hende mere, når hun kommer med vage svar
B72: 46019 | C72: Christeen Jacoub | E72: 52 11 61 73 | F72: https://www.instagram.com/christeenjacoub/ | H72: Setter | I72: Offer & Didn't Buy | N72: Money | O72: Skulle tjekke budgettet | S72: X | T72: Syntes det er svært med det her, når de siger de ikke har pengene, men i sidste ende er det fordi jeg ikke får bygget nok value op for dem. Har Pcos, insulin resistent
B73: 46019 | C73: Malin C. Dagenborg Christensen | E73: 50 11 86 18 | F73: https://www.instagram.com/mcatrine/ | H73: Setter | I73: Offer & Didn't Buy | N73: Money | O73: Pengene holdt hende tilbage efter nogle svære år | S73: Follow Up | T73: Bliver en alt for lang snak med, at hun bare yapper, ved ikke hvorfor jeg ikke bare bryder ind, det bliver hele tiden med jeg skal trække samtalen tilbage til det vigtige, som bare gør, at hun ikke kommer til at føle den, og så ved jeg ikke hvorfor jeg ikke bare følger frameworket, da hun så hører prisen, det er jo snot dumt. For ved jo det virker, tror bare jeg syntes snakken allerede havde været alt for lang. Skal bare følge det hver evigt eneste gang
B74: 46019 | C74: Daniel Lund Christensen | E74: 30 27 66 04 | F74: https://www.instagram.com/daniellundchristensen/ | H74: Setter | I74: Split-pay | K74: 10500 | L74: 3000 | Q74: 6 | S74: Closed | T74: Var sku nærmest presold og havde besluttet sig på forhånd, fik ham bare solgt endnu mere
B75: 46020 | C75: Amalie Høyrup-Andreasen | E75: 28 89 69 67 | F75: https://www.instagram.com/amaliehoeyrup/ | H75: Setter | I75: Split-pay | K75: 10500 | L75: 2250 | N75: Money | O75: Skulle kigge økonomi | Q75: 6 | S75: Closed | T75: Følger jeg har svært ved at finde nok pain på de her kald med "good to great" prospects, for får ikke bygget nok value for dem
B76: 46020 | C76: Mathias Tobiesen | E76: 22 16 18 62 | F76: https://www.instagram.com/mtobiesen_/ | H76: Setter | I76: Bad Fit & No Offer | S76: X | T76: Online coaching var ikke det rigtige for ham, hvis jeg skal være ærlig. Havde tidligere haft en spiseforstyre, så det her med struktur omkring træning og kost kunne han slet ikke arbejde med i hovedet. Det han havde brug for var nærmere end psykolog
B77: 46021 | C77: Jonas Sørensen | E77: 50 54 20 05 | H77: Landing page | I77: Offer & Didn't Buy | N77: Think About It | O77: Skulle tænke over det | S77: Follow Up Set

Sheet Jan 26
B1: Rep: | C1: Anna | E1: Anton KPI's | H1: Outcome | K1: KPIs% | N1: Show Rate | Q1: Objections | T1: Source
E2: Rev per call | F2: =C3/C6 -> 5254.5455 | H2: Full-Pay: | I2: =IFERROR(COUNTIFS(I13:I288, "Full-Pay"),"") -> 4 | K2: Conversion Rate: | L2: =iferror(L10/L8,"") -> 0.41818182 | N2: Rescheduling Rate: | O2: =iferror(I8/L6,"") -> 0.09375 | Q2: Think About It | R2: =IFERROR(COUNTIFS(N13:N287, "think about it"),"") -> 6 | T2: Reschedule | U2: =IFERROR(COUNTIF(H13:H287,T2),"") -> 0
B3: Revenue | C3: =IFERROR(SUM(K13:K285),"") -> 289000 | E3: Cash per call | F3: =C4/C6 -> 2151.5091 | H3: Split-Pay: | I3: =IFERROR(COUNTIFS(I13:I288, "Split-Pay"),"") -> 19 | K3: Offer To Close Rate: | L3: =IFERROR(L10/L9,"") -> 0.43396226 | N3: Cancellation Rate: | O3: =iferror(I9/L6,"") -> 0.015625 | Q3: Money | R3: =IFERROR(COUNTIFS(N13:N287, "money"),"") -> 18 | T3: YouTube | U3: =IFERROR(COUNTIF(H13:H287,T3),"") -> 0
B4: Cash | C4: =IFERROR(SUM(L13:L285),"") -> 118333 | E4: Cash upfront % | F4: =C4/C3*100 -> 40.945675 | H4: Deposits: | I4: =IFERROR(COUNTIFS(I13:I288, "Deposit"),"") -> 1 | K4: Call To Offer Rate: | L4: =IFERROR(L9/L8,"") -> 0.96363636 | N4: No-Shows Rate: | O4: =iferror(I10/L6,"") -> 0.03125 | Q4: Time | R4: =IFERROR(COUNTIFS(N13:N287, "time"),"") -> 1 | T4: YouTube Ads | U4: =IFERROR(COUNTIF(H13:H287,T4),"") -> 0
E5: PIF % | F5: =I2/C7*100 -> 17.391304 | H5: Offer & Didn't Buy: | I5: =IFERROR(COUNTIFS(I13:I288, "Offer & Didn't Buy"),"") -> 29 | K5: Drag Over Rate: | L5: =IFERROR(I7/(C6+I7+I8),"") -> 0 | N5: Drag Over Rate: | O5: =iferror(I7/L6,"") -> 0 | Q5: Partner | R5: =IFERROR(COUNTIFS(N13:N287, "partner"),"") -> 3 | T5: Email | U5: =IFERROR(COUNTIF(H13:H287,T5),"") -> 0
B6: Total Calls : | C6: =IFERROR(SUM(I2:I6),"") -> 55 | E6: Average Binding | F6: =AVERAGE(Q13:Q105) -> 5.8947368 | H6: Bad Fit & No Offer: | I6: =IFERROR(COUNTIFS(I13:I288, "Bad Fit & No Offer"),"") -> 2 | K6: Bookings: | L6: =IFERROR(SUM(I2:I10),"") -> 64 | N6: Show-Up Rate: | O6: =iferror(L7/L6,"") -> 0.859375 | Q6: Fear | R6: =IFERROR(COUNTIFS(N13:N287, "fear"),"") -> 2 | T6: Facebook | U6: =IFERROR(COUNTIF(H13:H287,T6),"") -> 0
B7: Total Won : | C7: =IFERROR(I2+I3,"") -> 23 | E7: Average deal | F7: =C3/C7 -> 12565.217 | H7: Drag Over & Show: | I7: =IFERROR(COUNTIFS(I13:I288, "Drag Over & Show"),"") -> 0 | K7: Shows: | L7: =IFERROR(SUM(I2:I7),"") -> 55 | N7: Conducted Rate: | O7: =IFERROR(L8/L6,"") -> 0.859375 | Q7: Value | R7: =IFERROR(COUNTIFS(N14:N288, "value"),"") -> 4 | T7: Facebook Ads | U7: =IFERROR(COUNTIF(H13:H287,T7),"") -> 0
B8: Total Lost : | C8: =COUNTIF(I13:I287,"offer & didn't buy")+countif(I13:I287,"deposit")+countif(I13:I287,"bad fit & no offer") -> 32 | E8: Average cash | F8: =C4/C7 -> 5144.913 | H8: Rescheduled: | I8: =IFERROR(COUNTIFS(I13:I288, "Rescheduled"),"") -> 6 | K8: Calls: | L8: =IFERROR(SUM(I2:I6),"") -> 55 | T8: LinkedIn | U8: =IFERROR(COUNTIF(H13:H287,T8),"") -> 0
B9: Closing % : | C9: =iferror(SUM(C7/C6),"") -> 0.41818182 | H9: Cancelled: | I9: =IFERROR(COUNTIFS(I13:I288, "Cancelled"),"") -> 1 | K9: Offers: | L9: =IFERROR(sum(I2:I5),"") -> 53
H10: No-Show: | I10: =IFERROR(COUNTIFS(I13:I288, "No-Show"),"") -> 2 | K10: Deals | L10: =I2+I3 -> 23
B12: Date | C12: Name | E12: Phone No. | F12: IG | H12: Source | I12: Outcome | K12: Revenue | L12: Cash | N12: Objection | O12: Objection Notes | Q12: Length | R12: Recording Link | S12: Follow Up/Next Steps | T12: Call Summary
B13: 46023 | C13: Steen Bro Demant | E13: 40 35 72 92 | F13: https://www.instagram.com/steenbrodemant/ | H13: Setter | I13: Split-pay | K13: 10500 | L13: 3000 | Q13: 6 | S13: Closed
B14: 46023 | C14: Rico | E14: 50 31 18 72 | F14: https://www.instagram.com/javricoj/ | H14: Setter | I14: Split-pay | K14: 10500 | L14: 3500 | Q14: 6 | S14: Closed
B15: 46023 | C15: Mira Christiansen | E15: 60 17 09 13 | F15: https://www.instagram.com/itsmiravibes/ | H15: Setter | I15: Split-pay | K15: 6000 | L15: 1500 | Q15: 4 | S15: Closed
B16: 46024 | C16: Freya Pallesgaard | E16: 53 27 22 38 | F16: https://www.instagram.com/msoedorf/ | H16: Setter | I16: Split-pay | K16: 10500 | L16: 3000 | Q16: 6 | S16: Closed
B17: 46024 | C17: Maria Koll | E17: 25 14 95 18 | F17: https://www.instagram.com/m_koll/ | H17: Setter | I17: Split-pay | K17: 10500 | L17: 3000 | Q17: 6 | S17: Closed
B18: 46024 | C18: Kristina Wentzel | E18: 28 72 13 52 | F18: https://www.instagram.com/kristinawentzel_1991/ | H18: Setter | I18: Split-pay | K18: 9000 | L18: 1500 | Q18: 6 | S18: Closed
B19: 46024 | C19: Søren Glinvad | E19: 51 34 25 22 | F19: https://www.instagram.com/s_glinvad/ | H19: Setter | I19: Split-pay | K19: 13500 | L19: 3500 | Q19: 6 | S19: Closed
B20: 46025 | C20: Theis Schiødts | E20: 42 43 85 13 | F20: https://www.instagram.com/thjeis69/ | H20: Setter | I20: Offer & Didn't Buy | N20: Money | O20: Havde ikke penge før d. 1 februar | S20: X | T20: Er nervøs for han ikke ender med at betale, for han nævnte han var ved at blive udredt for nogle ting. Men spurgte ham flere gange om han havde pengene, der til februar hvor han svarede ja, så nu må vi se
B21: 46025 | C21: Marko Marojevic | E21: 42 36 79 55 | F21: https://www.instagram.com/markomarojevic92/ | H21: Setter | I21: Rescheduled
B22: 46026 | C22: Marko Marojevic | E22: 42 36 79 55 | F22: https://www.instagram.com/markomarojevic92/ | H22: Setter | I22: No-Show
B23: 46026 | C23: Magnus N Nielsen | E23: 22 73 62 11 | F23: https://www.instagram.com/magnus.kvist/ | H23: Landing page | I23: Offer & Didn't Buy | N23: Think About It | O23: Han havde en anden samtale linet op med en anden coach senere i dag | S23: Follow Up | T23: Er usikker på hvordan jeg skal finde pain i sådan et prospect som ham, om fokus skal være på at finde den dybde pain, eller om fokus skal ligge på det her med at hvorfor at være average ikke er godt nok til ham. Det var det sidste mit fokus lå på til den her samtale
B24: 46026 | C24: Julia | E24: 42 43 05 05 | F24: https://www.instagram.com/juliahansen111/ | H24: Setter | I24: Offer & Didn't Buy | N24: Value | O24: Så ikke værdien i det følte godt hun kunne selv, men skulle bare tage sig sammen | S24: X | T24: Sagde nej hun syntes det var for mange penge. Skulle have fået langt mere pain, hver gang hun sagde noget trak hun i land kaldte hende også flere gang ud på dansker-menataliteten, men blev ved med at køre i det her med hun ikke var tilfreds, hun ville bare være helt tilfreds. Kunne ikke få hende ud af det tankemønster, men i bund og grund får jeg ikke bygget nok værdi op for hende
B25: 46026 | C25: Dorthe Pernille Nielsen | E25: 30 89 13 56 | F25: https://www.instagram.com/dopernie/ | H25: Setter | I25: Offer & Didn't Buy | N25: Money | O25: En blanding af mange penge og partner | S25: Follow Up | T25: Syntes ikke der var det bedste flow samtalen, kunne godt have fundet endnu dybere pain selvom jeg finder en del. Syntes det er virkeligt svært i forhold til dem her der tidligt nævner pengene er et problem
B26: 46026 | C26: Christine Kristensen | E26: 52 11 00 61 | F26: https://www.instagram.com/_christinek/ | H26: Setter | I26: Bad Fit & No Offer | S26: X | T26: Ville være et dårligt fit, lød til hun havde noget spiseforstyrrelse der ikke var blevet diagnositseret. Hun siger hun nærmest kunne gå flere dage uden at spise, og bare fik kvalme ved at kigge på mad. Ville ikke med god samvittighed kunne starte hende op
B27: 46026 | C27: Peter Stuhr Hollænder | E27: 31 16 25 37 | F27: https://www.instagram.com/peterstuhr/ | H27: Setter | I27: Split-pay | K27: 13500 | L27: 3500 | Q27: 6 | S27: Closed
B28: 46027 | C28: Stine Kelly | E28: 28 93 38 52 | F28: https://www.instagram.com/kellymoren/ | H28: Setter | I28: Split-pay | K28: 11500 | L28: 5750 | N28: Think About It | O28: Skulle bare tænke over det | Q28: 6 | S28: Closed | T28: Skulle 100 p have fundet mere pain, og spurgt ind til det her med spejlbillede (rookie mistake) syntes ellers jeg har en kanon startvar udfordende, stillede gode spørgsmål. Ville ikke have hun skulle føle sig presset og hun sagde selv vi starter i morgen, men nu må vi se om jeg er for godtroende. Skulle have kørt reframen i forhold til det her med at tage store beslutninger.
B29: 46028 | C29: Emma Søgaard Jensen | E29: 40 62 03 56 | H29: Landing page | I29: Split-pay | K29: 13500 | L29: 3500 | S29: Closed | T29: Får stillet hende de helt rigtige spørgsmål, som gør hun blive virkeligt rørt, og så sælger jeg hende bare fucking godt
B30: 46028 | C30: Nikolaj | E30: 42 51 42 53 | H30: Landing page | I30: Offer & Didn't Buy | N30: Money | O30: Skulle finde ud af om det kunne lade sig gøre | S30: Follow Up | T30: Lost lead jeg aldrig fik snakket med, men som skrev efter jeg havde sendt ham en del beskeder, så tog snakken med ham. Var svært at få pain ud af ham, fik ikke ham selv til at sætte ord på hvorfor han ikke var tilfreds, men lagde meget vægt på det her med han var average. Skulle også have ham til at sætte flere ord på dreamstate
B31: 46028 | C31: Sarah Lee Wolff Beck | E31: 30 48 53 66 | F31: https://www.instagram.com/sarahleebeck/ | H31: Setter | I31: Offer & Didn't Buy | S31: Follow Up | T31: Vi kommer skævt ind på hinanden til at starte på føler hun var helt delusional og havde virkeligt svært ved at få hende ned på jorden, så det blev en lang snak og havde så svært ved at få pain ud af hende.
B32: 46030 | C32: Adam Lund Jensen | E32: 28 61 59 09 | F32: https://www.instagram.com/adamlundjensen/ | H32: Setter | I32: Offer & Didn't Buy | N32: Money | O32: Var kun på SU, og kunne først starte, når han havde fundet en læreplads | S32: Hot Follow Up | T32: Er i tvivl om, hvordan jeg skal handle sådan en, når han allerede på starten af kaldet siger han er nødt til at vente indtil han har en læreplads. Kunne selv udfordre ham mere på og gennemgået framework
B33: 46031 | C33: Tobias | E33: 42 68 05 38 | F33: https://www.instagram.com/tobiasvlund/ | H33: Setter | I33: Full-Pay | K33: 11500 | L33: 11500 | Q33: 6 | S33: Closed | T33: Vi vibede godt og fik ham bare solgt sindsygt godt, sikker på jeg godt kunne have fået ham til at sætte endnu flere ord på sin pain.
B34: 46031 | C34: Maya Nicholls | E34: 52 42 12 01 | F34: https://www.instagram.com/nicholls90/ | H34: Setter | I34: Offer & Didn't Buy | N34: Money | O34: En god blanding af penge og fear | S34: X | T34: Bliver en meget coachende samtale med mange perspektiver og reframes, ender med samtalen bliver for lang, hun kommer med en masse objections, som leder mig på vildspor for følger ikke frame work, går direkete i fear objections selvom jeg først skal krydes value og money af
B35: 46034 | C35: Kenneth Da Silva Nielsen | E35: 22 54 10 67 | F35: https://www.instagram.com/silva.beatbox/ | H35: Setter | I35: Offer & Didn't Buy | N35: Fear | O35: Havde haft dårlige oplevelser med andre forløb | S35: Follow Up | T35: Skal virkeligt dykke ned i hans pain mere og virkeligt grave, og få ham til at se, hvad der sker hvis han ikke gør noget og hvordan det vil være.
B36: 46034 | C36: Christopher Maersk Grau Poulsen | E36: 81 73 50 99 | F36: https://www.instagram.com/christopher.maersk?igsh=M2pqZDVvYXV4d3Iw | H36: Setter | I36: Offer & Didn't Buy | N36: Money | O36: Pengene da han var på SU | S36: Follow Up | T36: Han er meget fokuseret på han syntes det er dyrt. Får ikke prehandlet hans money objection godt nok (Noget jeg skal have fokus på at blive bedre til). Da det så kommer til objection handling ved jeg jo godt han ikke ender med at købe, skal have lavet en langt bedre struktur i forhold til netop objection handling, så jeg gør det samme hver gang. I stedet for at flyve rundt
B37: 46036 | C37: Kira S. Bengtsson | E37: 60 38 21 31 | F37: https://www.instagram.com/ks.bengtsson/ | H37: Setter | I37: Offer & Didn't Buy | N37: Think About It | O37: Skulle bare tygge på den | S37: Follow Up | T37: Skal blive langt skarpere i objection handlingen. Ved der er et eller andet hun siger som jeg ikke får fundet, og er det som holder hende tilbage. hun siger tidligt på kaldet hun har svært ved at prioritere sig selv, det er klart en jeg skal gribe
B38: 46036 | C38: Majken Christensen | E38: 50 62 59 52 | F38: https://www.instagram.com/majkenchristensen03/ | H38: Setter | I38: Cancelled
B39: 46038 | C39: Cecilie Nielsen | E39: 23 41 04 41 | F39: https://www.instagram.com/majkenchristensen03/ | H39: Setter | I39: Split-pay | K39: 13500 | L39: 1500 | Q39: 6 | S39: Closed | T39: Hendes pain var ikke hvordan hun så ud, hendes pain var ikke at komme i mål med det hun satte sig for. Så fik jeg pre-handled hendes money objection ret godt!
B40: 46038 | C40: Linnea Annastacia Kinslev | E40: 61 54 66 32 | F40: https://www.instagram.com/linnea_0752/ | H40: Setter | I40: Offer & Didn't Buy | N40: Partner | O40: Havde ikke pengene selv, så skulle snakke med kæresten | S40: Follow Up | T40: Kun ikke lade sig gøre med mindre hun fik økonomisk støtte fra kærsten, syntes jeg finder pain, det var bare en reel objection
B41: 46038 | C41: Malou | E41: 60 15 87 46 | F41: https://www.instagram.com/malouhoegenhaven?igsh=ZTlmc3lwZW0zNzY0 | H41: Setter | I41: Split-pay | K41: 13500 | L41: 1500 | N41: Time | O41: Starter til Februar | Q41: 6 | S41: Closed
B42: 46038 | C42: Thomas Zanchetta | E42: 60 89 03 99 | F42: https://www.instagram.com/thomaszanchetta?igsh=MTJjdzBobTk1ZDcydA== | H42: Setter | I42: Offer & Didn't Buy | N42: Fear | O42: Han havde pengene, men kunne bare ikke tage en beslutning | S42: Hot Follow Up
B43: 46040 | C43: Sille Ehlers Bonne | E43: 60 35 16 17 | F43: https://www.instagram.com/sillebonne/ | H43: Setter | I43: Split-pay | K43: 11500 | L43: 5750 | Q43: 6 | S43: Closed | T43: Hun var bare klar til at gøre, noget prøvede også at disqualify hende nogle gange, som jo så gjorde hun bare solgt sig selv endnu mere
B44: 46040 | C44: Nanna Starris-Reiffenstein | E44: 42 18 03 22 | F44: https://www.instagram.com/nansen_07?igsh=MTY1ajVyY3p6dDhjdA== | H44: Setter | I44: Split-pay | K44: 13500 | L44: 3500 | Q44: 6 | S44: Closed | T44: Det handlede mere for hende om at tage beslutning, det var det svære for hende, at comitte sig, men fik stillet hende de rigtigte spørgsmål
B45: 46041 | C45: Michael Holme | E45: 30 33 93 77 | F45: https://www.instagram.com/holmegopro/ | H45: Setter | I45: Offer & Didn't Buy | N45: Think About It | O45: Ville det have på mail | S45: Follow Up Set | T45: Syntes ikke vi connecter alt for godt, så viben er der ikke helt, han bliver træt af min spørgsmål. Følte ikke jeg havde nok autoritet på kaldet, for skulle klart have trukket den ud, skal ærligt godt sige jeg følte mig som en pussy
B46: 46041 | C46: Steven | E46: 21 35 79 11 | F46: https://www.instagram.com/steven_t_hertz/ | H46: Setter | I46: Rescheduled
B47: 46041 | C47: Simon Nielsen | E47: 25 29 48 67 | F47: https://www.instagram.com/simon_nielsen_2000?igsh=dHE3ZWM0cm04Y3li | H47: Setter | I47: Full-Pay | K47: 24000 | L47: 24000 | Q47: 6 | S47: Closed
B48: 46041 | C48: Christina Hermansen | E48: 25 30 88 84 | F48: https://www.instagram.com/_scubamermaid_/ | H48: Setter | I48: Offer & Didn't Buy | N48: Money | O48: Manglede et job, men sagde hun var klar når hun fik | S48: Follow Up Set | T48: Var ikke rigtigt med på det var hendes egen ide, med hun skulle på forløb, så det arbejde vi lidt med, kørte den så langt jeg kunne havde et kald lige efter. Havde svært ved at finde pain ved hende
B49: 46041 | C49: Oscar Dall | E49: 30 74 37 00 | F49: https://www.instagram.com/oscar.dall_?igsh=eTJ4c240YXZ2cGpo | H49: Setter | I49: Offer & Didn't Buy | N49: Value | O49: Var i tvivl om han kunne selv | S49: Follow Up Set | T49: Skulle have fået mere pain ud af ham findet det egenligt, men så svarer han ikke ordenligt på min spørgsmål og snakker uden om
B50: 46041 | C50: Oliver Svensson | E50: 60 48 47 15 | F50: https://www.instagram.com/oliverhallsvensson?igsh=MXZwdXN1Z3l0ZDlpZQ== | H50: Setter | I50: Split-pay | K50: 13500 | L50: 3500 | Q50: 6 | S50: Closed
B51: 46042 | C51: Betina Hammelsvang | E51: 31 77 09 93 | F51: https://www.instagram.com/betinahammelsvang/ | H51: Setter | I51: Offer & Didn't Buy | N51: Money | O51: Skulle finde ud af om hun havde pengene | S51: Follow Up | T51: Skulle have lagt mere vægt på, hvad hvis hun ikke gjorde noget, da jeg objection handlede, så hun så endnu mere af værdien i det
B52: 46042 | C52: Sarah Pedersen | E52: 40 24 26 15 | F52: https://www.instagram.com/sarah__pedersen_/ | H52: Setter | I52: Full-Pay | K52: 11500 | L52: 11500 | N52: Partner | O52: Hun skulle have støtte fra sin kæreste | Q52: 6 | S52: Closed | T52: Får fundet ud af hun har en opsparring og har pengene til det, hun skal også bare have manden med på vognen. Skal blive bedre til at bruge det hun har sagt tidligere som ammo. Ved hun er dårligt til at pritoitere sig selv og udsætter tingene. Det skal jeg 100 procent bruge f.eks "Er det ikke den her adfærd, der vender tilbage, med du udskyder det og du ikke prioritere dig selv?"
B53: 46042 | C53: Heidi Valentin | E53: 60 78 96 98 | F53: https://www.instagram.com/heidi_valentin87/ | H53: Setter | I53: Offer & Didn't Buy | N53: Money | O53: Hun havde simpelthen bare ikke pengene | S53: Follow Up Set | T53: Har svært ved at få pain ud af hende, for hun føler hun har styr på det, får hende så til at indse det har hun ikke, men går for lang tid før jeg gør.
B54: 46042 | C54: Martin Skoubo | E54: 28 94 98 69 | F54: https://www.instagram.com/ma_skoubo/ | H54: Setter | I54: Bad Fit & No Offer | S54: Hot Follow Up | T54: Han havde en overrevet skulder og kendt slet ikke situationen eller havd enogen tidshorsiont på det. Så vi har aftalt at holde hinanden opdateret
B55: 46043 | C55: Gustav Hallas | E55: 91 56 71 17 | F55: https://www.instagram.com/gustav_hallas/ | H55: Setter | I55: Full-Pay | K55: 12000 | L55: 12000 | Q55: 6 | S55: Closed | T55: Virkeligt et godt kald, får fundet hans pain og han vil bare super gerne, kommer alligvel med en concern, hvor han ville vende den med mutti, men fik double-down og snakket økonomi og fortalte ham han kunne spare 2000 ved at betale det hele på en gang
B56: 46043 | C56: Julie Hoffmann Frederiksen | E56: 21 68 18 22 | F56: https://www.instagram.com/_.juwels/ | H56: Setter | I56: Split-pay | K56: 14000 | L56: 2333 | N56: Money | O56: Havde ikke penge før d. 30 januar | S56: Deposit (Follow Up Set)
B57: 46043 | C57: Emil Jens Christensen | E57: 27 40 32 05 | F57: https://www.instagram.com/losemilos40?igsh=MWd1NGQyN24yZGNwYg== | H57: Setter | I57: Offer & Didn't Buy | N57: Value | O57: Vægtede kørekort højere | S57: Follow Up | T57: Slukke have fået ham til at sætte endnu flere ord på hans pain, for endte med han ikke så nok værdi i det
B58: 46044 | C58: Niklas Holm | E58: 61 71 14 15 | F58: https://www.instagram.com/niklasholm_/ | H58: Setter | I58: Offer & Didn't Buy | N58: Value | O58: Syntes det var mange penge, og om det var det værd | S58: Follow Up Set | T58: Skal handle ham langt bedre til sidste, har ikke fået skabt nok værdi igennem kaldet ellers havde han jo købt
B59: 46044 | C59: Tobias Jørgensen | E59: 21 56 41 05 | F59: https://www.instagram.com/tonser12/ | H59: Setter | I59: Split-pay | K59: 13500 | L59: 3500
B60: 46044 | C60: Lasse Lund Hansen | E60: 27 84 74 99 | F60: https://www.instagram.com/lasselundhansen9?igsh=Z2NyMTRvczhoM2dn | H60: Setter | I60: Offer & Didn't Buy | N60: Money | O60: Havde ikke pengene | S60: Follow Up | T60: Havde sindsygt meget pain, Han havde virkeligt svært ved at tage beslutningen og gik vildt meget op i pengene, så var svært at trække sig væk fra det. Tror han havde nogle penge der kunne prioriteres anderledes. Fandt painen, men fik ikke hjulepet ham nok med at tage en beslutning
B61: 46044 | C61: Emma Julie Olafsen | E61: 91 56 24 18 | F61: https://www.instagram.com/emmaju2/ | H61: Setter | I61: Offer & Didn't Buy | N61: Money | O61: Blev overvældet af det bare lød som noget for hende så lagde på | Q61: 6 | S61: Follow Up | T61: Hun ville vildt gerne, og havde sagt ja og bookede hende ind til en snak med Daniel, men så var hun langsom om at få betalt og lagde så på fordi hun var flov over at sige ja, men så ikke kunne alligvel
B62: 46045 | C62: Line Frederiksen | E62: 27 62 05 16 | F62: https://www.instagram.com/linehalling/ | H62: Setter | I62: Rescheduled
B63: 46045 | C63: Victor Fryland | E63: 30 27 27 90 | F63: https://www.instagram.com/victor_fryland?igsh=NGQxZm43MHZrdTdp | H63: Setter | I63: Split-pay | K63: 14000 | L63: 2000 | N63: Money | S63: Closed | T63: Har betalt opstart betaler for første måned d. 1 februar, han var bare mega klar, prøvede at disqualify ham en del gange, som gjorde han bare snakkede sig selv mere ind i det
B64: 46045 | C64: Mikkel Lindskov Brentegani | E64: 52 17 74 83 | F64: https://www.instagram.com/mikkelbrentegani/ | H64: Setter | I64: Offer & Didn't Buy | N64: Money | O64: Vi gennemgik økonomien, men pengene var der ikke | S64: Follow Up | T64: Syntes jeg fandt virkeligt meget pain, vi gennemgik også økonomien, men penge var bare ikke til det som det så ud, så er i tvivle om hvad jeg ellers skulle have gjort, selvom jeg godt ved et kaldt aldrig er perfekt, man kan altid gøre noget bedre
B65: 46045 | C65: Mia | E65: 42 92 40 32 | F65: https://www.instagram.com/miadalhauge?igsh=MWtma2tlemw1ZDZodA== | H65: Setter | I65: No-Show
B66: 46046 | C66: Line Frederiksen | E66: 27 62 05 16 | F66: https://www.instagram.com/linehalling/ | H66: Setter | I66: Rescheduled
B67: 46046 | C67: Christina | E67: 27 13 82 34 | F67: https://www.instagram.com/luksuskokkener?igsh=MWpyeTY4dmVjbWZnNw== | H67: Setter | I67: Offer & Didn't Buy | N67: Think About It | O67: Lod hende slippe, troede oprigtigt på hende, så må vi se om hun røvrender mig | S67: Follow Up Set | T67: Vi har aftalt, at få hende i gang i morgen. Fandt super meget pain. Min mavefornemmelse sagde mig hun havde brug for space til at tage beslutningen, så det gjorde jeg i stedet for at presse hende ind i et hjørne, tager det 100 procent på min kappe, hvis hun så ghoster. Kunne fået krydset nogle flere bokse af, med value og om hun havde pengene, før jeg lod hende gå
B68: 46046 | C68: Kokulan Komathithevan | E68: 42 32 23 14 | F68: https://www.instagram.com/mrkokulan/ | H68: Setter | I68: Offer & Didn't Buy | N68: Think About It | O68: Havde samtale med 2 andre coaches, som han havde opsøgt først selv, før "Daniel" strøg ind i indbakken | S68: Hot Follow Up | T68: Var aller mest interesseret i en fysisk træner, prøvede at forklare ham det kun var en ingrediens, men han tror ikke helt han købte denog så havde han de her 2 andre samtler efterfølgende
B69: 46046 | C69: Ida Friis Anker | E69: 22 96 15 12 | F69: https://www.instagram.com/ida_friis_anker/ | H69: Setter | I69: Rescheduled
B70: 46051 | C70: Steven | E70: 21 35 79 11 | F70: https://www.instagram.com/steven_t_hertz/ | H70: Setter | I70: Offer & Didn't Buy | N70: Partner | O70: Skulle vende den med manden | S70: Follow Up Set | T70: Får ikke kørt min partner objecjtion, snakker med sin manden i dag, coachede ham i hvordan han skulle sige det til manden, så vi fik ham med på vognen
B71: 46051 | C71: Hamit Tugay Cem Erarslan | E71: 20 81 70 53 | F71: https://www.instagram.com/hamit_tugaycemerarslan/ | H71: Setter | I71: Deposit | N71: Money | O71: Aftalt vi får ham i gang i morgen | S71: Follow Up Set | T71: Syntes det er lidt et "double edge sword" med at pitche premium, fordi ham her vil aller helst have premium og heller vente, til han kan få det til at lade sig gøre end at start på signatur. Blev også en alt for lang snak. Vi har aftalt at få ham i gang i morgen, enten på premium om 3 måneder, pga han havde et kørekort, vil selvfølgelig helst have ham i gang på signatur så vi kan gøre det med det samme
B72: 46052 | C72: Ninna Nygaard | E72: 30 59 02 09 | F72: https://www.instagram.com/ninna_nygaard/ | H72: Setter | I72: Rescheduled
B73: 46052 | C73: Line Frederiksen | E73: 27 62 05 16 | F73: https://www.instagram.com/linehalling/ | H73: Setter | I73: Offer & Didn't Buy | N73: Money | O73: Havde ikke pengene | T73: Fejler med at ikke finde ret meget, pain lægger mere fokus hvorfor hun søger hjælp når hun allerede havde været på flere forskellige forløb. Hun manglede den personlige kontakte og tænkte derfor premium var det helt rigtige for hende, men det var helt udenfor hendes prisklasse, og vidste "normal" coaching" ikke var noget for hende
B74: 46053 | C74: Casper | E74: 41 44 02 47 | F74: https://www.instagram.com/casperstenbjerg/ | H74: Setter | I74: Offer & Didn't Buy | N74: Money | S74: X | T74: Vi kom skævt ind på hinanden, jeg fik stillet nogle dårlige spørgsmål
B75: 46053 | C75: Anja Nielsen | E75: 29 24 34 18 | F75: https://www.instagram.com/anjanielsen_90/ | H75: Setter | I75: Offer & Didn't Buy | N75: Money | O75: Fik et helt chok over prisen | S75: X | T75: Syntes det er vrkeligt svært med dem her hvor pengene fylder meget, og de har fortalt på forhånd at de ikke har ret mange penge. Hende her følte sig nærmest stødt da hun hørte pris og at hun ikke var blevet hørt, fordi hun allerede havde fortalt om hende situation
B76: 46053 | C76: Fie | D76: 22 56 42 22 | E76: 22 56 42 22 | F76: https://www.instagram.com/annsofiemortensen9/ | H76: Setter | I76: Split-pay | K76: 14000 | L76: 4000 | S76: Closed

Sheet Feb 26
A1: 2 | B1: Rep: | C1: Anna | E1: Anton KPI's | H1: Outcome | K1: KPIs% | N1: Show Rate | Q1: Objections | T1: Source
E2: Rev per call | F2: =C3/C6 -> 4091.0526 | H2: Full-Pay: | I2: =IFERROR(COUNTIFS(I13:I287, "Full-Pay"),"") -> 1 | K2: Conversion Rate: | L2: =iferror(L10/L8,"") -> 0.28947368 | N2: Rescheduling Rate: | O2: =iferror(I8/L6,"") -> 0.11320755 | Q2: Think About It | R2: =IFERROR(COUNTIFS(N13:N286, "think about it"),"") -> 3 | T2: Reschedule | U2: =IFERROR(COUNTIF(H13:H286,T2),"") -> 0
B3: Revenue | C3: =IFERROR(SUM(K13:K284),"") -> 155460 | E3: Cash per call | F3: =C4/C6 -> 1310.5263 | H3: Split-Pay: | I3: =IFERROR(COUNTIFS(I13:I287, "Split-Pay"),"") -> 10 | K3: Offer To Close Rate: | L3: =IFERROR(L10/L9,"") -> 0.2972973 | N3: Cancellation Rate: | O3: =iferror(I9/L6,"") -> 0.037735849 | Q3: Money | R3: =IFERROR(COUNTIFS(N13:N286, "money"),"") -> 19 | T3: YouTube | U3: =IFERROR(COUNTIF(H13:H286,T3),"") -> 0
B4: Cash | C4: =IFERROR(SUM(L13:L284),"") -> 49800 | E4: Cash upfront % | F4: =C4/C3*100 -> 32.033964 | H4: Deposits: | I4: =IFERROR(COUNTIFS(I13:I287, "Deposit"),"") -> 1 | K4: Call To Offer Rate: | L4: =IFERROR(L9/L8,"") -> 0.97368421 | N4: No-Shows Rate: | O4: =iferror(I10/L6,"") -> 0.13207547 | Q4: Time | R4: =IFERROR(COUNTIFS(N13:N286, "time"),"") -> 0 | T4: YouTube Ads | U4: =IFERROR(COUNTIF(H13:H286,T4),"") -> 0
E5: PIF % | F5: =I2/C7*100 -> 9.0909091 | H5: Offer & Didn't Buy: | I5: =IFERROR(COUNTIFS(I13:I287, "Offer & Didn't Buy"),"") -> 25 | K5: Drag Over Rate: | L5: =IFERROR(I7/(C6+I7+I8),"") -> 0 | N5: Drag Over Rate: | O5: =iferror(I7/L6,"") -> 0 | Q5: Partner | R5: =IFERROR(COUNTIFS(N13:N286, "partner"),"") -> 0 | T5: Email | U5: =IFERROR(COUNTIF(H13:H286,T5),"") -> 0
B6: Total Calls : | C6: =IFERROR(SUM(I2:I6),"") -> 38 | E6: Average Binding | F6: =AVERAGE(Q13:Q105) -> 5.75 | H6: Bad Fit & No Offer: | I6: =IFERROR(COUNTIFS(I13:I287, "Bad Fit & No Offer"),"") -> 1 | K6: Bookings: | L6: =IFERROR(SUM(I2:I10),"") -> 53 | N6: Show-Up Rate: | O6: =iferror(L7/L6,"") -> 0.71698113 | Q6: Fear | R6: =IFERROR(COUNTIFS(N13:N286, "fear"),"") -> 2 | T6: Facebook | U6: =IFERROR(COUNTIF(H13:H286,T6),"") -> 0
B7: Total Won : | C7: =IFERROR(I2+I3,"") -> 11 | E7: Average deal | F7: =C3/C7 -> 14132.727 | H7: Drag Over & Show: | I7: =IFERROR(COUNTIFS(I13:I287, "Drag Over & Show"),"") -> 0 | K7: Shows: | L7: =IFERROR(SUM(I2:I7),"") -> 38 | N7: Conducted Rate: | O7: =IFERROR(L8/L6,"") -> 0.71698113 | Q7: Value | R7: =IFERROR(COUNTIFS(N14:N287, "value"),"") -> 2 | T7: Facebook Ads | U7: =IFERROR(COUNTIF(H13:H286,T7),"") -> 0
B8: Total Lost : | C8: =COUNTIF(I13:I286,"offer & didn't buy")+countif(I13:I286,"deposit")+countif(I13:I286,"bad fit & no offer") -> 27 | E8: Average cash | F8: =C4/C7 -> 4527.2727 | H8: Rescheduled: | I8: =IFERROR(COUNTIFS(I13:I287, "Rescheduled"),"") -> 6 | K8: Calls: | L8: =IFERROR(SUM(I2:I6),"") -> 38 | T8: LinkedIn | U8: =IFERROR(COUNTIF(H13:H286,T8),"") -> 0
B9: Closing % : | C9: =iferror(SUM(C7/C6),"") -> 0.28947368 | H9: Cancelled: | I9: =IFERROR(COUNTIFS(I13:I287, "Cancelled"),"") -> 2 | K9: Offers: | L9: =IFERROR(sum(I2:I5),"") -> 37
H10: No-Show: | I10: =IFERROR(COUNTIFS(I13:I287, "No-Show"),"") -> 7 | K10: Deals | L10: =I2+I3 -> 11
B12: Date | C12: Name | E12: Phone No. | F12: IG | H12: Source | I12: Outcome | K12: Revenue | L12: Cash | N12: Objection | O12: Objection Notes | Q12: Length | R12: Recording Link | S12: Follow Up/Next Steps | T12: Call Summary
B13: 46055 | C13: Name | E13: 31 33 93 34 | F13: https://www.instagram.com/frederiksalling/ | H13: Setter | I13: Offer & Didn't Buy | N13: Money | O13: Havde ikke pengene nu | T13: Var selv sælger, havde også haft de her samtaler før, så den blev lidt atypisk. Han ville egenligt godt bare have styr på kosten, om vi kunne hjælpe ham ifht til det. Skulle dog klart have fundet mere pain og dykket ned i det.
B14: 46055 | C14: Ida Friis Anker | E14: 22 96 15 12 | F14: https://www.instagram.com/ida_friis_anker/ | H14: Setter | I14: No-Show
B15: 46055 | C15: Dennis Scharno Bertram | E15: 26 91 94 26 | F15: https://www.instagram.com/dennis_s_bertram/ | H15: Setter | I15: Rescheduled
B16: 46055 | C16: Anja | E16: 22 14 44 83 | F16: https://www.instagram.com/anjajungnielsen/ | H16: Setter | I16: Rescheduled
B17: 46055 | C17: Michael Overgaard | E17: 22 45 28 18 | H17: Landing page | I17: split-pay | K17: 24000 | L17: 4000 | Q17: 6 | S17: Closed | T17: Er nysgerrig, er interesseret i ham og hans situation og får fundet det der gør, at han køber
B18: 46056 | C18: Jonathan Mortensen | E18: 51 70 37 87 | F18: https://www.instagram.com/jonamort02?igsh=M2R0NzcydGNwaDlx | H18: Setter | I18: Offer & Didn't Buy | L18: 500
B19: 46056 | C19: Liv Toft Sølvmose Simonsen | E19: 25 32 14 45 | F19: https://www.instagram.com/livtss2000/ | H19: Setter | I19: split-pay | K19: 11660 | L19: 4000 | N19: Fear | O19: Skulle bare tænke over det og vende det med en veninde | Q19: 5 | S19: Closed | T19: Kunne godt have været mere skarp i obejtion handling og bruge den her usikkerhed hun havde som ammonition, at det var derfor hun ikke kunne tage en beslutning
B20: 46056 | C20: Lucas | E20: 42 46 37 52 | F20: https://www.instagram.com/lu3as.t0mmi/ | H20: Setter | I20: Offer & Didn't Buy | N20: Money | S20: Follow Up Set | T20: Ikke det bedste flow i samtalen, det kunne godt ah været bedre. Bliver ikke så skarpt som jeg gerne vil have den skulle været, det bliver hakkende. Frusterende at han lige en jeg dropper prisen om jeg kan sende det på en mail, fordi han var ved at pakke bilen ud. Så dropper prisen og så føler jeg, at jeg får travlt så får ikke gennemgået frameworket efter
B21: 46057 | C21: Micky | E21: 91 78 57 82 | F21: https://www.instagram.com/mickychristianhavtorn/ | H21: Setter | I21: Offer & Didn't Buy | S21: Follow Up Set | T21: Følte ikke at han var helt med på, hvad der foregik og hvordan det fungerede. I sidste ende får jeg ham ikke solgt nok, for han syntes 6 måneder var alt for lang tid og kunne ikke få ham til at indse, det var det som skulle til. Får ikke tacklet hans objection ordenligt, skal bare følge det forbandet framework
B22: 46057 | C22: Mikkel Raakjær | E22: 28 15 57 39 | H22: Landing page | I22: Full-Pay | K22: 12000 | L22: 12000 | Q22: 6 | S22: Closed
B23: 46057 | C23: Dennis fuglesang | E23: 22 26 41 10 | H23: Landing page | I23: split-pay | K23: 14000 | L23: 4000 | Q23: 6 | S23: Closed
B24: 46057 | C24: Anja | E24: 22 14 44 83 | F24: https://www.instagram.com/anjajungnielsen/ | H24: Setter | I24: Offer & Didn't Buy | N24: Think About It | O24: Hun var egenligt ikke lige klar på at starte nu, men ville gerne lige vente med at sætte det i gang til mandag | S24: Follow Up Set | T24: Bliver en for lang snak syntes jeg, får først fundet pain alt for sent
B25: 46057 | C25: Tobias Grøndal Jensen | E25: 53 29 75 00 | F25: https://www.instagram.com/tobiasgjensen_/ | H25: Setter | I25: Offer & Didn't Buy | N25: Value | O25: Følte ikke det ville være værd at starte nu, når han havde en skade med hånden | T25: Får ikke fundet hans pain, han var svært at få noget ud af, får ham ikke brudt nok ned. Ender med han en bliver ret interesseret, men kommer med en undskyldning om en skade
B26: 46058 | C26: Lina Thejman | E26: 42 71 30 19 | F26: https://www.instagram.com/linathejlman?igsh=MW55cnhrMnV2OGZ0YQ== | H26: Setter | I26: split-pay | K26: 14000 | L26: 4000 | N26: Money | O26: Var under 18 så skulle vende med med mor og far | S26: Closed | T26: Syntes det er svært at objection handle når farmand sidder ved siden af og det jo egenligt i bund og grund er ham/moren, som skal lægge pengene, så fik double down og hørt om det syntes det var pengene hver, men slap dem så der
B27: 46058 | C27: Annette Westergaard Petersen | E27: 42 67 60 27 | F27: https://www.instagram.com/mortil4unger/ | H27: Setter | I27: Bad Fit & No Offer | T27: Hun smed røret på efter 20 minutter
B28: 46060 | C28: Laura Vorsholt Hellesøe | E28: 30 55 57 71 | F28: https://www.instagram.com/lauravhellesoe/ | H28: Setter | I28: Offer & Didn't Buy | N28: Money | O28: Havde ikke pengene | S28: Hot Follow Up | T28: Syntes virkeligt det er svært med dem her som, siger de bare ikke har pengene
B29: 46060 | C29: Tina | E29: 31 21 27 78 | F29: https://www.instagram.com/tinaragnhildblomstrand/ | H29: Setter | I29: Offer & Didn't Buy | N29: Money | S29: Follow Up | T29: Vi har aftalt at sætte det hele op på mandag, vi vibede godt syntes og havde god kemi. Men kunne mærke jeg blev bange for at udforde hende til sidste at da hun sagde den lige skulle vendes med manden.
B30: 46061 | C30: Vibeke | E30: 29 34 15 25 | F30: https://www.instagram.com/vibekelindekrantz?igsh=MWFrbGc5ZGIxaWh1cg== | H30: Setter | I30: Offer & Didn't Buy | N30: Money | S30: Follow Up | T30: Der kommer slet ikke nok pain eller konsekvens ved inaction, hun føler den slet ikke. Var ikke solgt på ideen med online coaching, da hun havde prøvet det før og det med at skrive ikke var noget for hende
B31: 46062 | C31: Helle Kirk Sørensen | E31: 61 68 44 38 | F31: https://www.instagram.com/helle_s_lopper/ | H31: Setter | I31: Offer & Didn't Buy | N31: Think About It | O31: "Skulle altid tænke over det" | S31: Follow Up Set | T31: Snakken blev for lang, kom for stor afsted mellem det der betød noget og så snak. Som resulterede i der ikke var nok tid til negotiation
B32: 46063 | C32: Samuel | E32: 28 87 82 84 | F32: https://www.instagram.com/samueljust_/ | H32: Setter | I32: Offer & Didn't Buy | N32: Fear | O32: Turde ikke tage en beslutning | S32: Follow Up Set | T32: Syntes ikke flowet er ret godt, får skabt unødvendig modstand i kaldet, som ikke var nødvenidg. Så nævner han inden jeg pitcher, han er på vej ude at døren, som stresser mig, så da det kommet til neogtiation, får jeg ikke gjort det ordenligt
B33: 46063 | C33: Niclas | E33: 31 52 95 90 | F33: https://www.instagram.com/niclas_stromgren/ | H33: Setter | I33: Offer & Didn't Buy | N33: Value | O33: Havde svært ved at tage beslutningen, og følte han kunne nå noget af vejen selv | S33: Follow Up Set | T33: Skal have hørt kaldet igennem igen, får ham ikke til at sætte nok ord på sin pain, kommer med nogle alt for kringlet spørgsmål, han nævner han har trænet med sin ven og det motivere han, det skulle jeg helt klart have udfordret ham på hvorfor han ikke bare bruger ham. Så også med at han havde motivationen nu, hvad så når den forsvinder?
B34: 46065 | C34: Gustav Ruby | E34: 30 48 68 25 | F34: https://www.instagram.com/gullegagav/ | H34: Setter | I34: Offer & Didn't Buy | N34: Money | O34: Havde ikke råd til det | S34: Follow Up | T34: Bliver en alt for lang snak painen er der ikke
B35: 46065 | C35: Line Wassmann | E35: 60 11 67 49 | F35: https://www.instagram.com/linewassmann/ | H35: Setter | I35: split-pay | K35: 14000 | L35: 4000 | S35: Closed | T35: Det var et godt kald, kom ind med god energi lavede sjov med hende og hun elskede det
B36: 46068 | C36: Pernille Schaumann Andreasen | E36: 23 88 98 64 | F36: https://www.instagram.com/pernilleandreasens/ | H36: Setter | I36: Deposit | N36: Money | O36: Var allerede i andet forløb, så betaler 1. marts | S36: Deposit (Follow Up Set) | T36: Hun starter op 1. marts
B37: 46068 | C37: Emma | E37: 23 92 73 00 | F37: https://www.instagram.com/emmaerichsensorensen/ | H37: Setter | I37: Offer & Didn't Buy | N37: Money | O37: Syntes det var for mange penge ifht. til hendes budget | S37: Follow Up | T37: Fandt pain, men skulle have hende fået til at sætte flere ord på det selv, så gappet blev større og kosten ved in-action også blev større
B38: 46068 | C38: Noah Vejborg | E38: 40 60 11 12 | F38: https://www.instagram.com/noah.vejborg/ | H38: Setter | I38: Offer & Didn't Buy | N38: Think About It | O38: Var under 18 og farmand sad ved siden af | S38: Follow Up Set | T38: Svær snak fordi når jeg spurgte om noget lagde faren ordene i munden på Noah i stedte for han selv sagde det. Hvis det 100 p stod til Noah var vi startet op var sku faren der holdte ham tilbage
B39: 46069 | C39: Magnus | E39: 42 20 52 75 | F39: https://www.instagram.com/magnus_hornbeck?igsh=cnc5NmdrMjFreHVo | H39: Setter | I39: Offer & Didn't Buy | N39: Money | O39: Troede han kunne få rabat | S39: Follow Up | T39: Skal blive bedre til bare at grave den pain helt ned, fordi det endte med han ikke købte selvom han havde pengene, han ville dog slet ikke have noget tilbage så. Føler godt jeg kunne have fået ham der
B40: 46069 | C40: Simone Johansen | E40: 27 57 32 49 | F40: https://www.instagram.com/simonejohansen_03/ | H40: Setter | I40: No-Show
B41: 46071 | C41: Liva Elise | E41: 29 60 98 61 | H41: Landing page | I41: Offer & Didn't Buy | N41: Money | O41: Havde lige sagt sit job op og på sabbatår | S41: Follow Up Set | T41: Hendes udfordring lå i at hun tidligere havde haft en dårlig oplevelse med at snakke med en coach og så have tillid til at springe ud i det. Jeg skulle have fået hende til at sætte flere ord på hendes nuværende situation. Logistisk kunne det ikke hænge sammen nu uden job, men vi gennemgik økonomien og fandt steder der kunne spares, og hun sagde hun gerne være villig til at spare det og prioritere når hun fandt et job
B42: 46072 | C42: Benjamin Pilemann | E42: 29 93 86 12 | F42: https://www.instagram.com/benjamin.priess/ | H42: Setter | I42: No-Show
B43: 46073 | C43: Simone Frøkjær | E43: 28 76 65 84 | F43: https://www.instagram.com/simonefrokjaer/ | H43: Setter | I43: No-Show
B44: 46075 | C44: Simone Johansen | E44: 27 57 32 49 | F44: https://www.instagram.com/simonejohansen_03/ | H44: Setter | I44: split-pay | K44: 14000 | L44: 2000 | O44: Betaler resten til den første | S44: Closed
B45: 46075 | C45: Benjamin Pilemann | E45: 29 93 86 12 | F45: https://www.instagram.com/benjamin.priess/ | H45: Setter | I45: Offer & Didn't Buy | N45: Money | O45: Den eneste som holdt ham tilbage var økonomien, havde ikke et job | S45: Follow Up Set | T45: Jeg snakket med ham igen torsdag, for at høre hvor han står i forhold til job. Kunne godt have udfordret ham noget mere, og der hvor jeg spørger, om han kan overbevise mig skal jeg også få ham fucking til det
B46: 46075 | C46: Philip Bertelsen | E46: 42 55 09 03 | F46: https://www.instagram.com/philip_bertelsen/ | H46: Setter | I46: No-Show
B47: 46075 | C47: Anders Mosegaard Kappel | E47: 31 20 23 22 | F47: https://www.instagram.com/hamderkappel/ | H47: Setter | I47: Rescheduled
B48: 46075 | C48: Anne Kathrine Bang Larsen | E48: 50 82 26 69 | F48: https://www.instagram.com/anne_kathirine?igsh=ejU2MDVncXQwaGc1 | H48: Setter | I48: Offer & Didn't Buy | N48: Money | O48: Lige fået job, så venter på den første løn | S48: Follow Up Set | T48: Hun ender med at få nogle bekymringer til sidst, som jeg ikke får handlet godt nok, det skal gøres bedre. Syntes eller jeg sælger hende godt, den skal sku bare over målstregen til sidst.
B49: 46075 | C49: Mathias | E49: 60 47 50 05 | F49: https://www.instagram.com/mathiasvi_ch?igsh=M3B5NGE5amd6aTB3 | H49: Setter | I49: Rescheduled
B50: 46075 | C50: Mickey | E50: 50 51 15 47 | F50: https://www.instagram.com/mickey__moeller/ | H50: Setter | I50: Rescheduled
B51: 46076 | C51: Anders Mosegaard Kappel | E51: 31 20 23 22 | F51: https://www.instagram.com/hamderkappel/ | H51: Setter | I51: Cancelled
B52: 46076 | C52: Zenia Gjerlev | E52: 60 61 22 60 | F52: https://www.instagram.com/zenia.a.gjerlev/ | H52: Setter | I52: Offer & Didn't Buy | N52: Money | O52: Skulle til syn med bilen på onsdag, så skulel lige have status på den | S52: Deposit (Follow Up Set) | T52: Hun smed symbolsk deposit, skulle lige have status med på bil på onsdag, og så får vi hende i gang. Havde fokus på ikke at følge scriptet slavisk, men når det gav mening, det syntes jeg, at jeg fik en langt bedre samtale ud af
