Workbook

Sheet PnL 2025
A1: Category | B1: Total | C1: 45682 | D1: 45713 | E1: 45741 | F1: 45772 | G1: 45802 | H1: 45833 | I1: 45863 | J1: 45894 | K1: 45925 | L1: 45955 | M1: 45986 | N1: 46016
A2: Income
A3: Total revenue | B3: =sum(C3:N3) -> 241993 | C3: =SUM(C4) -> 0 | D3: =sum(D4) -> 8300 | E3: =SUM(E4) -> 14533 | F3: =sum(F4) -> 19753 | G3: =SUM(G4) -> 19213 | H3: =sum(H4) -> 15950 | I3: =SUM(I4) -> 24516 | J3: =sum(J4) -> 15376 | K3: =SUM(K4) -> 16833 | L3: =sum(L4) -> 35975 | M3: =SUM(M4) -> 36222 | N3: =sum(N4) -> 35322
A4: Cash collected (New costumers | B4: =sum(C4:N4) -> 241993 | C4: =SUMIFS(Datalist!$D:$D, Datalist!$C:$C, ">="&DATE(2025,1,1), Datalist!$C:$C, "<"&DATE(2025,2,1)) -> 0 | D4: =SUMIFS(Datalist!$D:$D, Datalist!$C:$C, ">="&DATE(2025,2,1), Datalist!$C:$C, "<"&DATE(2025,3,1)) -> 8300 | E4: =SUMIFS(Datalist!$D:$D, Datalist!$C:$C, ">="&DATE(2025,3,1), Datalist!$C:$C, "<"&DATE(2025,4,1)) -> 14533 | F4: =SUMIFS(Datalist!$D:$D, Datalist!$C:$C, ">="&DATE(2025,4,1), Datalist!$C:$C, "<"&DATE(2025,5,1)) -> 19753 | G4: =SUMIFS(Datalist!$D:$D, Datalist!$C:$C, ">="&DATE(2025,5,1), Datalist!$C:$C, "<"&DATE(2025,6,1)) -> 19213 | H4: =SUMIFS(Datalist!$D:$D, Datalist!$C:$C, ">="&DATE(2025,6,1), Datalist!$C:$C, "<"&DATE(2025,7,1)) -> 15950 | I4: =SUMIFS(Datalist!$D:$D, Datalist!$C:$C, ">="&DATE(2025,7,1), Datalist!$C:$C, "<"&DATE(2025,8,1)) -> 24516 | J4: =SUMIFS(Datalist!$D:$D, Datalist!$C:$C, ">="&DATE(2025,8,1), Datalist!$C:$C, "<"&DATE(2025,9,1)) -> 15376 | K4: =SUMIFS(Datalist!$D:$D, Datalist!$C:$C, ">="&DATE(2025,9,1), Datalist!$C:$C, "<"&DATE(2025,10,1)) -> 16833 | L4: =SUMIFS(Datalist!$D:$D, Datalist!$C:$C, ">="&DATE(2025,10,1), Datalist!$C:$C, "<"&DATE(2025,11,1)) -> 35975 | M4: =SUMIFS(Datalist!$D:$D, Datalist!$C:$C, ">="&DATE(2025,11,1), Datalist!$C:$C, "<"&DATE(2025,12,1)) -> 36222 | N4: =SUMIFS(Datalist!$D:$D, Datalist!$C:$C, ">="&DATE(2025,12,1), Datalist!$C:$C, "<"&DATE(2026,1,1)) -> 35322
A7: Total cash collected | B7: =sum(C7:N7) -> 241993 | C7: =SUM(C4:C6) -> 0 | D7: =SUM(D4:D6) -> 8300 | E7: =SUM(E4:E6) -> 14533 | F7: =SUM(F4:F6) -> 19753 | G7: =SUM(G4:G6) -> 19213 | H7: =SUM(H4:H6) -> 15950 | I7: =SUM(I4:I6) -> 24516 | J7: =SUM(J4:J6) -> 15376 | ... N7: =SUM(N4:N6) -> 35322
A8: Expenses
A9: Ads Total | B9: =sum(C9:N9) -> 3054 | C9: 0 | D9: 0 | E9: 190 | F9: 900 | G9: 1024 | H9: 600 | I9: 340 | J9: 0 | K9: 0 | L9: 0 | M9: 0 | N9: 0
A10: Meta | C10: 0 | D10: 0 | E10: 0 | F10: 0 | G10: 0 | H10: 0 | I10: 0 | J10: 0 | K10: 0 | L10: 0 | M10: 0 | N10: 0
A11: TikTok | C11: 0 | D11: 0 | E11: 0 | F11: 0 | G11: 0 | H11: 0 | I11: 0 | J11: 0 | K11: 0 | L11: 0 | M11: 0 | N11: 0
A12: Youtube | C12: 0 | D12: 0 | E12: 0 | F12: 0 | G12: 0 | H12: 0 | I12: 0 | J12: 0 | K12: 0 | L12: 0 | M12: 0 | N12: 0
A13: Google | C13: 0 | D13: 0 | E13: 0 | F13: 0 | G13: 0 | H13: 0 | I13: 0 | J13: 0 | K13: 0 | L13: 0 | M13: 0 | N13: 0
A14: Closers/Setters Total | B14: =sum(C14:N14) -> 12552.5 | C14: 0 | D14: 0 | E14: 4530 | F14: 2915 | G14: 1790 | H14: =660 + 280 -> 940 | I14: 2377.5 | J14: 0 | K14: 0 | L14: 0 | M14: 0 | N14: 0
A15: Anton | C15: 0 | D15: 0 | E15: 0 | F15: 0 | G15: 0 | H15: 0 | I15: 0 | J15: 0 | K15: 0 | L15: 0 | M15: 0 | N15: 0
A16: Håvard | B16: =sum(C16:N16) -> 0 | C16: 0 | D16: 0 | E16: 0 | F16: 0 | G16: 0 | H16: 0 | I16: 0 | J16: 0 | K16: 0 | L16: 0 | M16: 0 | N16: 0
A17: Stripe | B17: =sum(C17:N17) -> 10420.751 | C17: 0 | D17: =D7-(D7/1.045) -> 357.41627 | E17: =E7-(E7/1.045) -> 625.82297 | F17: =F7-(F7/1.045) -> 850.60766 | G17: =G7-(G7/1.045) -> 827.35407 | H17: =H7-(H7/1.045) -> 686.84211 | I17: =I7-(I7/1.045) -> 1055.7129 | J17: =J7-(J7/1.045) -> 662.1244 | K17: =K7-(K7/1.045) -> 724.86603 | ... N17: =N7-(N7/1.045) -> 1521.0431
B18: =sum(C18:N18) -> 0 | C18: 0 | D18: 0 | E18: 0 | F18: 0 | G18: 0 | H18: 0 | I18: 0 | J18: 0 | K18: 0 | L18: 0 | M18: 0 | N18: 0
B19: =sum(C19:N19) -> 0 | C19: 0 | D19: 0 | E19: 0 | F19: 0 | G19: 0 | H19: 0 | I19: 0 | J19: 0 | K19: 0 | L19: 0 | M19: 0 | N19: 0
B20: =sum(C20:N20) -> 0 | C20: 0 | D20: 0 | E20: 0 | F20: 0 | G20: 0 | H20: 0 | I20: 0 | J20: 0 | K20: 0 | L20: 0 | M20: 0 | N20: 0
A21: Softwares | B21: =sum(C21:N21) -> 3865 | C21: 0 | D21: 0 | E21: 615 | F21: 661 | G21: 785 | H21: 902 | I21: 902 | J21: 0 | K21: 0 | L21: 0 | M21: 0 | N21: 0
A22: Content expenses | B22: =sum(C22:N22) -> 1850 | C22: 0 | D22: 0 | E22: 0 | F22: 0 | G22: 0 | H22: 0 | I22: 1850 | J22: 0 | K22: 0 | L22: 0 | M22: 0 | N22: 0
A23: Total costs | B23: =sum(C23:N23) -> 52857.299 | C23: =C9+C14+C17 -> 0 | D23: =D9+D14+D17 -> 357.41627 | E23: =E9+E14+E17+E21+E22 -> 5960.823 | F23: =F9+F14+F17+F21+F22 -> 5326.6077 | G23: =G9+G14+G17 -> 3641.3541 | H23: =H9+H14+H17+H21+H22 -> 3128.8421 | I23: =I9+I14+I17+I21+I22 -> 6525.2129 | J23: 6599 | K23: 6599 | L23: 6599 | M23: 6599 | N23: =SUM(N9:N22) -> 1521.0431
A25: Total profit (After VAT) | B25: =sum(C25:N25) -> 201660.83 | C25: =C3-C23 -> 0 | D25: =D3/1.2 -> 6916.6667 | E25: =E3/1.2 -> 12110.833 | F25: =F3/1.2 -> 16460.833 | G25: =G3/1.2 -> 16010.833 | H25: =H3/1.2 -> 13291.667 | I25: =I3/1.2 -> 20430 | J25: =J3/1.2 -> 12813.333 | K25: =K3/1.2 -> 14027.5 | ... N25: =N3/1.2 -> 29435
A26: Total profit (After Expenses) | B26: =sum(C26:N26) -> 148803.53 | C26: =C6+C4 -> 0 | D26: =D25-D23 -> 6559.2504 | E26: =E25-E23 -> 6150.0104 | F26: =F25-F23 -> 11134.226 | G26: =G25-G23 -> 12369.479 | H26: =H25-H23 -> 10162.825 | I26: =I25-I23 -> 13904.787 | J26: =J25-J23 -> 6214.3333 | K26: =K25-K23 -> 7428.5 | ... N26: =N25-N23 -> 27913.957
A29: NYSAESON cut | B29: =(B25)*0.2 -> 40332.167 | C29: =(C25)*0.3 -> 0 | D29: =(D25)*0.2 -> 1383.3333 | E29: =(E25)*0.2 -> 2422.1667 | F29: =(F25)*0.2 -> 3292.1667 | G29: =(G25)*0.2 -> 3202.1667 | H29: =(H25)*0.2 -> 2658.3333 | I29: =(I25)*0.2 -> 4086 | J29: =(J26)*0.2 -> 1242.8667 | K29: =(K26)*0.2 -> 1485.7 | L29: =(L26)*0.2 -> 4676.0333 | M29: =(M26)*0.2 -> 4717.2 | N29: =(N25)*0.2 -> 5887
A30: Lucas cut | B30: =(B26)*0.8 -> 119042.83 | C30: =(C26)*0.7 -> 0 | D30: =(D26)*0.8 -> 5247.4003 | E30: =(E26)*0.8 -> 4920.0083 | F30: =(F26)*0.8 -> 8907.3805 | G30: =(G26)*0.8 -> 9895.5834 | H30: =(H26)*0.8 -> 8130.2596 | I30: =(I26)*0.8 -> 11123.83 | J30: =(J26)*0.8 -> 4971.4667 | K30: =(K26)*0.8 -> 5942.8 | ... N30: =(N26)*0.8 -> 22331.166

Sheet PnL 2026
A1: Category | B1: Total | C1: 46047 | D1: 45713 | E1: 45741 | F1: 45772 | G1: 45802 | H1: 45833 | I1: 45863 | J1: 45894 | K1: 45925 | L1: 45955 | M1: 45986 | N1: 46016
A2: Income
A3: Total revenue | B3: =sum(C3:N3) -> 545803 | C3: =SUM(C4) -> 48723 | D3: =sum(D4) -> 49708 | E3: =SUM(E4) -> 0 | F3: =sum(F4) -> 49708 | G3: =sum(G4) -> 49708 | H3: =sum(H4) -> 49708 | I3: =sum(I4) -> 49708 | J3: =sum(J4) -> 49708 | K3: =sum(K4) -> 49708 | L3: =sum(L4) -> 49708 | M3: =sum(M4) -> 49708 | N3: =sum(N4) -> 49708
A4: Cash collected (New costumers | B4: =sum(C4:N4) -> 545803 | C4: =SUMIFS(Datalist!$D:$D, Datalist!$C:$C, ">="&DATE(2026,1,1), Datalist!$C:$C, "<"&DATE(2026,2,1)) -> 48723 | D4: =SUMIFS(Datalist!$D:$D, Datalist!$C:$C, ">="&DATE(2026,2,1), Datalist!$C:$C, "<"&DATE(2026,3,1)) -> 49708 | E4: =SUMIFS(Datalist!$D:$D, Datalist!$C:$C, ">="&DATE(2026,3,1), Datalist!$C:$C, "<"&DATE(2026,4,1)) -> 0 | F4: =SUMIFS(Datalist!$D:$D, Datalist!$C:$C, ">="&DATE(2026,2,1), Datalist!$C:$C, "<"&DATE(2026,3,1)) -> 49708 | G4: =SUMIFS(Datalist!$D:$D, Datalist!$C:$C, ">="&DATE(2026,2,1), Datalist!$C:$C, "<"&DATE(2026,3,1)) -> 49708 | H4: =SUMIFS(Datalist!$D:$D, Datalist!$C:$C, ">="&DATE(2026,2,1), Datalist!$C:$C, "<"&DATE(2026,3,1)) -> 49708 | I4: =SUMIFS(Datalist!$D:$D, Datalist!$C:$C, ">="&DATE(2026,2,1), Datalist!$C:$C, "<"&DATE(2026,3,1)) -> 49708 | J4: =SUMIFS(Datalist!$D:$D, Datalist!$C:$C, ">="&DATE(2026,2,1), Datalist!$C:$C, "<"&DATE(2026,3,1)) -> 49708 | K4: =SUMIFS(Datalist!$D:$D, Datalist!$C:$C, ">="&DATE(2026,2,1), Datalist!$C:$C, "<"&DATE(2026,3,1)) -> 49708 | L4: =SUMIFS(Datalist!$D:$D, Datalist!$C:$C, ">="&DATE(2026,2,1), Datalist!$C:$C, "<"&DATE(2026,3,1)) -> 49708 | M4: =SUMIFS(Datalist!$D:$D, Datalist!$C:$C, ">="&DATE(2026,2,1), Datalist!$C:$C, "<"&DATE(2026,3,1)) -> 49708 | N4: =SUMIFS(Datalist!$D:$D, Datalist!$C:$C, ">="&DATE(2026,2,1), Datalist!$C:$C, "<"&DATE(2026,3,1)) -> 49708
A7: Total cash collected | B7: =sum(C7:N7) -> 545803 | C7: =SUM(C4:C5) -> 48723 | D7: =SUM(D4:D6) -> 49708 | E7: =SUM(E4:E6) -> 0 | F7: =SUM(F4:F6) -> 49708 | G7: =SUM(G4:G6) -> 49708 | H7: =SUM(H4:H6) -> 49708 | I7: =SUM(I4:I6) -> 49708 | J7: =SUM(J4:J6) -> 49708 | K7: =SUM(K4:K6) -> 49708 | ... N7: =SUM(N4:N6) -> 49708
A8: Expenses
A9: Ads Total | B9: =sum(C9:N9) -> 3369 | C9: 3369 | D9: 0 | E9: 0 | F9: 0 | G9: 0 | H9: 0 | I9: 0 | J9: 0 | K9: 0 | L9: 0 | M9: 0 | N9: 0
A10: Meta | C10: 0 | D10: 0 | E10: 0 | F10: 0 | G10: 0 | H10: 0 | I10: 0 | J10: 0 | K10: 0 | L10: 0 | M10: 0 | N10: 0
A11: TikTok | C11: 0 | D11: 0 | E11: 0 | F11: 0 | G11: 0 | H11: 0 | I11: 0 | J11: 0 | K11: 0 | L11: 0 | M11: 0 | N11: 0
A12: Youtube | C12: 0 | D12: 0 | E12: 0 | F12: 0 | G12: 0 | H12: 0 | I12: 0 | J12: 0 | K12: 0 | L12: 0 | M12: 0 | N12: 0
A13: Google | C13: 0 | D13: 0 | E13: 0 | F13: 0 | G13: 0 | H13: 0 | I13: 0 | J13: 0 | K13: 0 | L13: 0 | M13: 0 | N13: 0
A14: Closers/Setters Total | B14: =sum(C14:N14) -> 3000 | C14: =3000 -> 3000 | D14: 0 | E14: 0 | F14: 0 | G14: 0 | H14: 0 | I14: 0 | J14: 0 | K14: 0 | L14: 0 | M14: 0 | N14: 0
A15: Anton | C15: 0 | D15: 0 | E15: 0 | F15: 0 | G15: 0 | H15: 0 | I15: 0 | J15: 0 | K15: 0 | L15: 0 | M15: 0 | N15: 0
A16: Håvard | B16: =sum(C16:N16) -> 0 | C16: 0 | D16: 0 | E16: 0 | F16: 0 | G16: 0 | H16: 0 | I16: 0 | J16: 0 | K16: 0 | L16: 0 | M16: 0 | N16: 0
A17: Stripe | B17: =sum(C17:N17) -> 23503.478 | C17: =C7-(C7/1.045) -> 2098.1196 | D17: =D7-(D7/1.045) -> 2140.5359 | E17: =E7-(E7/1.045) -> 0 | F17: =F7-(F7/1.045) -> 2140.5359 | G17: =G7-(G7/1.045) -> 2140.5359 | H17: =H7-(H7/1.045) -> 2140.5359 | I17: =I7-(I7/1.045) -> 2140.5359 | J17: =J7-(J7/1.045) -> 2140.5359 | ... N17: =N7-(N7/1.045) -> 2140.5359
B18: =sum(C18:N18) -> 0 | C18: 0 | D18: 0 | E18: 0 | F18: 0 | G18: 0 | H18: 0 | I18: 0 | J18: 0 | K18: 0 | L18: 0 | M18: 0 | N18: 0
B19: =sum(C19:N19) -> 0 | C19: 0 | D19: 0 | E19: 0 | F19: 0 | G19: 0 | H19: 0 | I19: 0 | J19: 0 | K19: 0 | L19: 0 | M19: 0 | N19: 0
B20: =sum(C20:N20) -> 0 | C20: 0 | D20: 0 | E20: 0 | F20: 0 | G20: 0 | H20: 0 | I20: 0 | J20: 0 | K20: 0 | L20: 0 | M20: 0 | N20: 0
A21: Softwares | B21: =sum(C21:N21) -> 0 | C21: 0 | D21: 0 | E21: 0 | F21: 0 | G21: 0 | H21: 0 | I21: 0 | J21: 0 | K21: 0 | L21: 0 | M21: 0 | N21: 0
A22: Content expenses | B22: =sum(C22:N22) -> 1000 | C22: 1000 | D22: 0 | E22: 0 | F22: 0 | G22: 0 | H22: 0 | I22: 0 | J22: 0 | K22: 0 | L22: 0 | M22: 0 | N22: 0
A23: Total costs | B23: =sum(C23:N23) -> 30872.478 | C23: =C9+C14+C17+C21+C22 -> 9467.1196 | D23: =D9+D14+D17 -> 2140.5359 | E23: =E9+E14+E17+E21+E22 -> 0 | F23: =F9+F14+F17 -> 2140.5359 | G23: =G9+G14+G17 -> 2140.5359 | H23: =H9+H14+H17 -> 2140.5359 | I23: =I9+I14+I17 -> 2140.5359 | J23: =J9+J14+J17 -> 2140.5359 | K23: =K9+K14+K17 -> 2140.5359 | L23: =L9+L14+L17 -> 2140.5359 | M23: =M9+M14+M17 -> 2140.5359 | N23: =N9+N14+N17 -> 2140.5359
A25: Total profit (After VAT) | B25: =sum(C25:N25) -> 454835.83 | C25: =C3/1.2 -> 40602.5 | D25: =D3/1.2 -> 41423.333 | E25: =E3/1.2 -> 0 | F25: =F3/1.2 -> 41423.333 | G25: =G3/1.2 -> 41423.333 | H25: =H3/1.2 -> 41423.333 | I25: =I3/1.2 -> 41423.333 | J25: =J3/1.2 -> 41423.333 | ... N25: =N3/1.2 -> 41423.333
A26: Total profit (After Expenses) | B26: =sum(C26:N26) -> 423963.35 | C26: =C25-C23 -> 31135.38 | D26: =D25-D23 -> 39282.797 | E26: =E25-E23 -> 0 | F26: =F25-F23 -> 39282.797 | G26: =G25-G23 -> 39282.797 | H26: =H25-H23 -> 39282.797 | I26: =I25-I23 -> 39282.797 | J26: =J25-J23 -> 39282.797 | ... N26: =N25-N23 -> 39282.797
A29: NYSAESON cut | B29: =(B25)*0.2 -> 90967.167 | C29: =(C25)*0.2 -> 8120.5 | D29: =(D25)*0.2 -> 8284.6667 | E29: =(E25)*0.2 -> 0 | F29: =(F25)*0.2 -> 8284.6667 | G29: =(G25)*0.2 -> 8284.6667 | H29: =(H25)*0.2 -> 8284.6667 | I29: =(I25)*0.2 -> 8284.6667 | J29: =(J26)*0.2 -> 7856.5595 | K29: =(K26)*0.2 -> 7856.5595 | L29: =(L26)*0.2 -> 7856.5595 | M29: =(M26)*0.2 -> 7856.5595 | N29: =(N25)*0.2 -> 8284.6667
A30: Lucas cut | B30: =(B26)*0.8 -> 339170.68 | C30: =(C26)*0.8 -> 24908.304 | D30: =(D26)*0.8 -> 31426.238 | E30: =(E26)*0.8 -> 0 | F30: =(F26)*0.8 -> 31426.238 | G30: =(G26)*0.8 -> 31426.238 | H30: =(H26)*0.8 -> 31426.238 | I30: =(I26)*0.8 -> 31426.238 | ... N30: =(N26)*0.8 -> 31426.238

Sheet Datalist
A1: Name | B1: E-mail | C1: Date | D1: CASH COLLECTED
A2: Oskar | C2: 45705.419 | D2: 800
A3: Halvard | C3: 45706 | D3: 100
A4: Nicolas | C4: 45707 | D4: 800
A5: Matteo | C5: 45708 | D5: 3200
A6: Alexander Hoffmann | B6: hello@retro23.de | C6: 45709 | D6: 1600
A7: Joana Coelho | B7: joanafilipa_coelho@hotmail.com | C7: 45710 | D7: 100
A8: Rúben Deus | B8: rubenmjd@gmail.com | C8: 45711 | D8: 800
A9: Donovan Stuhlmuller | B9: dstuhlmuller@gmail.com | C9: 45712 | D9: 100
A10: Donovan Stuhlmuller | B10: dstuhlmuller@gmail.com | C10: 45713 | D10: 100
A11: Simon Skiöld | B11: simons@lsn.se | C11: 45714 | D11: 400
A12: Ali Amer | B12: ali.amer0324@gmail.com | C12: 45715 | D12: 100
A13: Radovan Sliz | B13: sliz.radovan@gmail.com | C13: 45716 | D13: 200
A14: Donata Leonova | B14: Donata.Leonova@citadel.com | C14: 45717 | D14: 1800
A15: Nikolaj Gyldenvang | B15: nikolaj_gyldenvang@hotmail.com | C15: 45717 | D15: 100
A16: Tom Roder | B16: tomroder25@gmail.com | C16: 45718 | D16: 400
A17: Daniel Erik Destefani | B17: danne88@gmail.com | C17: 45719 | D17: 600
... A51: Bentohey Francisco Ramos | B51: bentorey77@gmail.com | C51: 45750 | D51: 400
C52: 45751 | D52: 800
A53: Leo Samuelsson | B53: leosamuelsson2005@gmail.com | C53: 45752 | D53: 100
A54: Arie Kok | B54: arco-kok@hotmail.com | C54: 45753 | D54: 600
A55: Victor Fallesen | B55: victor@asbohvb.se | C55: 45754 | D55: 420
A56: Sandip | C56: 45754 | D56: 400 | G56: usd
A57: Nikolaj | C57: 45754 | D57: 400
A58: Andrea | C58: 45754 | D58: 200
A59: Matthew Haughey | B59: Matthew.Haughey@gmail.com | C59: 45754 | D59: 600 | G59: usd
C60: 45754 | D60: 533 | G60: usd
C61: 45754 | D61: 400 | G61: usd
A62: Ross McKee | B62: contactrossmckee@gmail.com | C62: 45754 | D62: 100 | G62: usd
A63: Radovan Sliz | B63: radko.sliz@gmail.com | C63: 45754 | D63: 200 | G63: eur
C64: 45760.832 | D64: 400 | G64: usd
A65: Antonio Magzal | B65: antonio.magzal@gmail.com | C65: 45761.362 | D65: 600 | G65: usd
A66: Jackson Vogel | B66: jacksonvogel371@gmail.com | C66: 45761.533 | D66: 600 | G66: usd
C67: 45762.745 | D67: 200 | G67: usd
A68: Jackson C Brandt | B68: jacksonbrandt235@gmail.com | C68: 45763.538 | D68: 900 | G68: usd
A69: Bentohey Francisco Ramos | B69: bentorey77@gmail.com | C69: 45763.593 | D69: 1400 | G69: usd
A70: Sebaztian Blomqvist Gustafsson | C70: 45764.133 | D70: 200 | G70: usd
A71: Oreste (Sondrio company name) Arbouw | C71: 45765.526 | D71: 400 | G71: usd
A72: Hannes Erestål | B72: hanneserestal@icloud.com | C72: 45766.404 | D72: 200 | G72: usd
A73: Simon Skiöld | B73: simon95skiold@gmail.com | C73: 45767.185 | D73: 400 | G73: usd
A74: Hannes Erestål | B74: hanneserestal@icloud.com | C74: 45770.402 | D74: 400 | G74: usd
A75: Declan Connors | B75: declanc_013@hotmail.com | C75: 45770.774 | D75: 400 | G75: usd
A76: Jacques Scully | B76: jacquesmscully@icloud.com | C76: 45770.861 | D76: 400 | G76: usd
A77: Leo Samuelsson | B77: leosamuelsson2005@gmail.com | C77: 45772.38 | D77: 300 | G77: usd
A78: Michael Jeunen | B78: michael-jeunen@hotmail.com | C78: 45773.425 | D78: 600 | G78: usd
A79: Adam Vesterberg | C79: 45773.813 | D79: 400 | G79: usd
A80: Dylan Tjon | B80: dylantjon@gmail.com | C80: 45775.113 | D80: 600 | G80: usd
A81: Ignacio Canales Rocca | C81: 45776.746 | D81: 400 | G81: usd
A82: Ata | B82: ata.turkoglu@outlook.com | C82: 45777.458 | D82: 2200 | G82: usd
A83: Tonda Řihák | C83: 45777.588 | D83: 400 | G83: usd
A84: Donovan Stuhlmuller | C84: 45779.786 | D84: 400 | G84: usd
A85: Andre Teixeira | B85: andre.txr14@gmail.com | C85: 45782.482 | D85: 300 | G85: usd
A86: Andre Martins Teixeira | B86: andre.txr14@gmail.com | C86: 45782.537 | D86: 300 | G86: usd
A87: Melvin Cicek | B87: melle.c@hotmail.com | C87: 45783.404 | D87: 400 | G87: usd
A88: Nikolaj Gyldenvang | C88: 45784.296 | D88: 400 | G88: usd
C89: 45784.296 | D89: 533 | G89: usd
A90: DKVFILM AB | B90: dannek90@icloud.com | C90: 45784.53 | D90: 600 | G90: usd
A91: Richard Holmgren | B91: richolmgren@outlook.com | C91: 45784.588 | D91: 1200 | G91: usd
A92: Andrea Napolitano | C92: 45785.296 | D92: 200 | G92: usd
C93: 45785.296 | D93: 400 | G93: usd
A94: Matthew Haughey | C94: 45785.502 | D94: 400 | G94: usd
A95: Mark Overeem | B95: contact@elevantum.nl | C95: 45785.583 | D95: 800 | G95: usd
A96: Donovan Stuhlmuller | C96: 45787.296 | D96: 400 | G96: usd
C97: 45785.296 | D97: 400 | G97: usd
C98: 45783.296 | D98: 200 | G98: usd
A99: Alvar Södling | C99: 45791.574 | D99: 1030 | G99: sek
A100: Bayron Fernando Zuniga An | B100: fz85430@gmail.com | C100: 45792.066 | D100: 600 | G100: usd
A101: Maleek Byrd | C101: 45793.82 | D101: 200 | G101: usd
C102: 45794.338 | D102: 2250 | G102: sek
A103: Oskar | B103: oskar-spiesberger@t-online.de | C103: 45796.867 | D103: 800 | G103: usd
A104: Joe Lira-Alarcon | B104: lirajoe002@gmail.com | C104: 45798.706 | D104: 100 | G104: usd
A105: Adam Vesterberg | C105: 45799.295 | D105: 400 | G105: usd
C106: 45799.837 | D106: 400 | G106: usd
A107: Ignacio Canales Rocca | C107: 45794.296 | D107: 400 | G107: usd
A108: Oreste (Sondrio company name) Arbouw | C108: 45800.276 | D108: 400 | G108: usd
A109: Dylan | C109: 45805.304 | D109: 400 | G109: usd
A110: Tonda Řihák | C110: 45807.294 | D110: 400 | G110: usd
A111: Ulas | C111: 45807.294 | D111: 2200
A112: Ian Slipp | B112: ianhypeboi@gmail.com | C112: 45807.571 | D112: 300 | G112: usd
A113: Ian Slipp | B113: ianhypeboi@gmail.com | C113: 45807.572 | D113: 100 | G113: usd
A114: Lukas Proos | C114: 45808.319 | D114: 2300 | G114: usd
C115: 45810.51 | D115: 400 | G115: usd
A116: Robert Myers | B116: robert@shipredline.com | C116: 45811.734 | D116: 600 | G116: usd
A117: Melvin Cicek | C117: 45814.315 | D117: 250 | G117: usd
A118: Nikolaj Gyldenvang | C118: 45815.296 | D118: 400 | G118: usd
A119: Matthew Haughey | C119: 45816.296 | D119: 400 | G119: usd
C120: 45816.295 | D120: 400 | G120: usd
A121: N.O. Stulp | B121: stulpstaalwerk@gmail.com | C121: 45819.69 | D121: 2200 | G121: usd
C122: 45821.219 | D122: 500 | G122: usd
C123: 45821.504 | D123: 400 | G123: usd
A124: THOMAS JONASSON | B124: thojo84@gmail.com | C124: 45823.359 | D124: 500 | G124: usd
C125: 45814.296 | D125: 200 | G125: usd
A126: J van Aubel | B126: julesvanaubel@gmail.com | C126: 45823.691 | D126: 600 | G126: usd
A127: Heine Sveinsgjerd | C127: 45824.297 | D127: 400 | G127: usd
C128: 45824.404 | D128: 1700 | G128: usd
A129: Oreste (Sondrio company name) Arbouw | C129: 45825.296 | D129: 400 | G129: usd
B130: jonasalkassam@icloud.com | C130: 45826.31 | D130: 800 | G130: usd
A131: Jonas Al Kassam | C131: 45827.522 | D131: 1400 | G131: usd
C132: 45827.571 | D132: 600 | G132: usd
A133: Adam Vesterberg | C133: 45830.295 | D133: 400 | G133: usd
...
